{
  "type": "Feature",
  "properties": {
    "gn:admin1_code":"13.0",
    "gn:asciiname":"Kampung Kabang Hulu",
    "gn:country_code":"MY",
    "gn:dem":30,
    "gn:feature_class":"P",
    "gn:feature_code":"PPL",
    "gn:name":"Kampung Kabang Hulu",
    "gn:population":0,
    "gn:timezone":"Asia/Kuala_Lumpur",
    "iso:country":"MY",
    "name:msa_x_preferred":[
        "Kampung Kabang Hulu"
    ],
    "name:und_x_variant":[
        "Kampung Kabang Ulu"
    ],
    "wof:name":"Kampung Kabang Hulu",
    "wof:placetype":"locality"
},
  "geometry": {"coordinates":[103.2578,4.3462],"type":"Point"}
}