{
  "type": "Feature",
  "properties": {
    "gn:admin1_code":"12",
    "gn:asciiname":"Kampung Pulau Sebok",
    "gn:country_code":"MY",
    "gn:dem":18,
    "gn:feature_class":"P",
    "gn:feature_code":"PPL",
    "gn:name":"Kampung Pulau Sebok",
    "gn:population":0,
    "gn:timezone":"Asia/Kuala_Lumpur",
    "iso:country":"MY",
    "name:msa_x_preferred":[
        "Kampung Pulau Sebok"
    ],
    "name:und_x_variant":[
        "Kampong Pulau Sabak",
        "Kampong Pulau Sebak"
    ],
    "wof:name":"Kampung Pulau Sebok",
    "wof:placetype":"locality"
},
  "geometry": {"coordinates":[101.6241,2.9565],"type":"Point"}
}