{
  "type": "Feature",
  "properties": {
    "gn:admin1_code":"11",
    "gn:asciiname":"Kampong Sungai Mersan",
    "gn:country_code":"MY",
    "gn:dem":-9999,
    "gn:feature_class":"P",
    "gn:feature_code":"PPL",
    "gn:name":"Kampong Sungai Mersan",
    "gn:population":0,
    "gn:timezone":"Asia/Kuching",
    "iso:country":"MY",
    "wof:name":"Kampong Sungai Mersan",
    "wof:placetype":"locality"
},
  "geometry": {"coordinates":[110.26667,1.71667],"type":"Point"}
}