{
  "type": "Feature",
  "properties": {
    "gn:admin1_code":"1",
    "gn:asciiname":"Kampung Mensudut Pindah",
    "gn:country_code":"MY",
    "gn:dem":44,
    "gn:feature_class":"P",
    "gn:feature_code":"PPL",
    "gn:name":"Kampung Mensudut Pindah",
    "gn:population":0,
    "gn:timezone":"Asia/Kuala_Lumpur",
    "iso:country":"MY",
    "name:und_x_variant":[
        "Kampong Mensudot Pindan"
    ],
    "wof:name":"Kampung Mensudut Pindah",
    "wof:placetype":"locality"
},
  "geometry": {"coordinates":[102.73224999999999,2.64878],"type":"Point"}
}