{
  "type": "Feature",
  "properties": {
    "gn:admin1_code":"1.0",
    "gn:asciiname":"Kampung Baru Bekoh",
    "gn:country_code":"MY",
    "gn:dem":24,
    "gn:feature_class":"P",
    "gn:feature_code":"PPL",
    "gn:name":"Kampung Baru Bekoh",
    "gn:population":0,
    "gn:timezone":"Asia/Kuala_Lumpur",
    "iso:country":"MY",
    "name:msa_x_preferred":[
        "Kampung Baru Bekoh"
    ],
    "wof:name":"Kampung Baru Bekoh",
    "wof:placetype":"locality"
},
  "geometry": {"coordinates":[102.518,2.3499],"type":"Point"}
}