{
  "type": "Feature",
  "properties": {
    "gn:admin1_code":"6.0",
    "gn:asciiname":"Kampung Membalau",
    "gn:country_code":"MY",
    "gn:dem":20,
    "gn:feature_class":"P",
    "gn:feature_code":"PPL",
    "gn:name":"Kampung Membalau",
    "gn:population":0,
    "gn:timezone":"Asia/Kuala_Lumpur",
    "iso:country":"MY",
    "name:msa_x_preferred":[
        "Kampung Membalau"
    ],
    "wof:name":"Kampung Membalau",
    "wof:placetype":"locality"
},
  "geometry": {"coordinates":[102.9358,3.0753],"type":"Point"}
}