{
  "type": "Feature",
  "properties": {
    "gn:admin1_code":"11",
    "gn:asciiname":"Kampong Sebako",
    "gn:country_code":"MY",
    "gn:dem":26,
    "gn:feature_class":"P",
    "gn:feature_code":"PPL",
    "gn:name":"Kampong Sebako",
    "gn:population":0,
    "gn:timezone":"Asia/Kuching",
    "iso:country":"MY",
    "name:und_x_variant":[
        "Kampung Sebako"
    ],
    "wof:name":"Kampong Sebako",
    "wof:placetype":"locality"
},
  "geometry": {"coordinates":[109.73728,1.73638],"type":"Point"}
}