{
  "type": "Feature",
  "properties": {
    "gn:admin1_code":"2",
    "gn:asciiname":"Mata Ayer",
    "gn:country_code":"MY",
    "gn:dem":3,
    "gn:feature_class":"P",
    "gn:feature_code":"PPL",
    "gn:name":"Mata Ayer",
    "gn:population":0,
    "gn:timezone":"Asia/Kuala_Lumpur",
    "iso:country":"MY",
    "name:epo_x_preferred":[
        "Mata Ayer"
    ],
    "name:msa_x_preferred":[
        "Mata Ayer"
    ],
    "wof:name":"Mata Ayer",
    "wof:placetype":"locality"
},
  "geometry": {"coordinates":[100.40000000000001,5.81667],"type":"Point"}
}