{
  "type": "Feature",
  "properties": {
    "gn:admin1_code":"6.0",
    "gn:asciiname":"Kampung Berkat",
    "gn:country_code":"MY",
    "gn:dem":41,
    "gn:feature_class":"P",
    "gn:feature_code":"PPL",
    "gn:name":"Kampung Berkat",
    "gn:population":0,
    "gn:timezone":"Asia/Kuala_Lumpur",
    "iso:country":"MY",
    "name:msa_x_preferred":[
        "Kampung Berkat"
    ],
    "wof:name":"Kampung Berkat",
    "wof:placetype":"locality"
},
  "geometry": {"coordinates":[102.77330000000001,3.5932],"type":"Point"}
}