{
  "type": "Feature",
  "properties": {
    "gn:admin1_code":"5",
    "gn:asciiname":"Kampung Batang Penajis",
    "gn:country_code":"MY",
    "gn:dem":76,
    "gn:feature_class":"P",
    "gn:feature_code":"PPL",
    "gn:name":"Kampung Batang Penajis",
    "gn:population":0,
    "gn:timezone":"Asia/Kuala_Lumpur",
    "iso:country":"MY",
    "name:msa_x_preferred":[
        "Kampung Batang Penajis"
    ],
    "name:und_x_variant":[
        "Kampong Batang Penajis"
    ],
    "wof:name":"Kampung Batang Penajis",
    "wof:placetype":"locality"
},
  "geometry": {"coordinates":[102.0949,2.6432],"type":"Point"}
}