{
  "type": "Feature",
  "properties": {
    "gn:admin1_code":"16.0",
    "gn:asciiname":"Kampung Kepayan Baru",
    "gn:country_code":"MY",
    "gn:dem":328,
    "gn:feature_class":"P",
    "gn:feature_code":"PPL",
    "gn:name":"Kampung Kepayan Baru",
    "gn:population":0,
    "gn:timezone":"Asia/Kuching",
    "iso:country":"MY",
    "name:msa_x_preferred":[
        "Kampung Kepayan Baru"
    ],
    "wof:name":"Kampung Kepayan Baru",
    "wof:placetype":"locality"
},
  "geometry": {"coordinates":[116.2697,5.4459],"type":"Point"}
}