{
  "type": "Feature",
  "properties": {
    "gn:admin1_code":"16",
    "gn:asciiname":"Kanar",
    "gn:country_code":"MY",
    "gn:dem":232,
    "gn:feature_class":"P",
    "gn:feature_code":"PPL",
    "gn:name":"Kanar",
    "gn:population":0,
    "gn:timezone":"Asia/Kuching",
    "iso:country":"MY",
    "wof:name":"Kanar",
    "wof:placetype":"locality"
},
  "geometry": {"coordinates":[115.95,5.15],"type":"Point"}
}