{
  "type": "Feature",
  "properties": {
    "gn:admin1_code":"6.0",
    "gn:asciiname":"Kampung Baharu Ah Tong",
    "gn:country_code":"MY",
    "gn:dem":10,
    "gn:feature_class":"P",
    "gn:feature_code":"PPL",
    "gn:name":"Kampung Baharu Ah Tong",
    "gn:population":0,
    "gn:timezone":"Asia/Kuala_Lumpur",
    "iso:country":"MY",
    "name:msa_x_preferred":[
        "Kampung Baharu Ah Tong"
    ],
    "wof:name":"Kampung Baharu Ah Tong",
    "wof:placetype":"locality"
},
  "geometry": {"coordinates":[103.1726,3.8814],"type":"Point"}
}