{
  "type": "Feature",
  "properties": {
    "gn:admin1_code":"16",
    "gn:asciiname":"Kampung Natai",
    "gn:country_code":"MY",
    "gn:dem":328,
    "gn:feature_class":"P",
    "gn:feature_code":"PPL",
    "gn:name":"Kampung Natai",
    "gn:population":0,
    "gn:timezone":"Asia/Kuching",
    "iso:country":"MY",
    "name:msa_x_preferred":[
        "Kampung Natai"
    ],
    "name:und_x_variant":[
        "Natai",
        "Kampong Natai"
    ],
    "wof:name":"Kampung Natai",
    "wof:placetype":"locality"
},
  "geometry": {"coordinates":[116.2265,6.0202],"type":"Point"}
}