{
  "type": "Feature",
  "properties": {
    "gn:admin1_code":"16",
    "gn:asciiname":"Kampung Lubah",
    "gn:country_code":"MY",
    "gn:dem":21,
    "gn:feature_class":"P",
    "gn:feature_code":"PPL",
    "gn:name":"Kampung Lubah",
    "gn:population":0,
    "gn:timezone":"Asia/Kuching",
    "iso:country":"MY",
    "name:msa_x_preferred":[
        "Kampung Lubah"
    ],
    "name:und_x_variant":[
        "Kampong Lubah"
    ],
    "wof:name":"Kampung Lubah",
    "wof:placetype":"locality"
},
  "geometry": {"coordinates":[116.7226,6.4745],"type":"Point"}
}