{
  "type": "Feature",
  "properties": {
    "gn:admin1_code":"5",
    "gn:asciiname":"Kampung Sertang",
    "gn:country_code":"MY",
    "gn:dem":130,
    "gn:feature_class":"P",
    "gn:feature_code":"PPL",
    "gn:name":"Kampung Sertang",
    "gn:population":0,
    "gn:timezone":"Asia/Kuala_Lumpur",
    "iso:country":"MY",
    "name:msa_x_preferred":[
        "Kampung Sertang"
    ],
    "name:und_x_variant":[
        "Kampong Sertang"
    ],
    "wof:name":"Kampung Sertang",
    "wof:placetype":"locality"
},
  "geometry": {"coordinates":[102.1618,3.1498],"type":"Point"}
}