{
  "type": "Feature",
  "properties": {
    "gn:admin1_code":"9",
    "gn:asciiname":"Kampung Siam",
    "gn:cc2":"MY",
    "gn:country_code":"MY",
    "gn:dem":6,
    "gn:feature_class":"P",
    "gn:feature_code":"PPL",
    "gn:name":"Kampung Siam",
    "gn:population":0,
    "gn:timezone":"Asia/Kuala_Lumpur",
    "iso:country":"MY",
    "name:msa_x_preferred":[
        "Kampung Siam"
    ],
    "name:und_x_variant":[
        "Kampong Siam"
    ],
    "wof:name":"Kampung Siam",
    "wof:placetype":"locality"
},
  "geometry": {"coordinates":[100.50221000000001,5.54635],"type":"Point"}
}