{
  "type": "Feature",
  "properties": {
    "gn:country":"MY",
    "gn:fcode":"PPL",
    "gn:pop":0,
    "iso:country":"MY",
    "name:msa_x_preferred":[
        "Kampung Bertam Bharu"
    ],
    "name:unk_x_variant":[
        "Bertam"
    ],
    "qs:name":"Bertam Baharu",
    "qs:name_adm0":"Malaysia",
    "qs:name_adm1":"Kelantan",
    "qs:photos_9k":1,
    "qs:photos_9r":1,
    "qs:photos_all":2,
    "qs:photos_sr":0,
    "qs:placetype":"Town",
    "qs:pop_sr":"3",
    "wof:name":"Bertam Baharu",
    "wof:placetype":"locality",
    "wof:population":0
},
  "geometry": {"coordinates":[102.0475,5.1454],"type":"Point"}
}