{
  "type": "Feature",
  "properties": {
    "gn:admin1_code":"2",
    "gn:asciiname":"Kampung Limau",
    "gn:cc2":"MY",
    "gn:country_code":"MY",
    "gn:dem":19,
    "gn:feature_class":"P",
    "gn:feature_code":"PPL",
    "gn:name":"Kampung Limau",
    "gn:population":0,
    "gn:timezone":"Asia/Kuala_Lumpur",
    "iso:country":"MY",
    "name:msa_x_preferred":[
        "Kampung Limau"
    ],
    "name:und_x_variant":[
        "Kampong Limau"
    ],
    "wof:name":"Kampung Limau",
    "wof:placetype":"locality"
},
  "geometry": {"coordinates":[100.65688,5.21756],"type":"Point"}
}