{
  "type": "Feature",
  "properties": {
    "gn:admin1_code":"1.0",
    "gn:asciiname":"Kampung Parit Empat",
    "gn:country_code":"MY",
    "gn:dem":15,
    "gn:feature_class":"P",
    "gn:feature_code":"PPL",
    "gn:name":"Kampung Parit Empat",
    "gn:population":0,
    "gn:timezone":"Asia/Kuala_Lumpur",
    "iso:country":"MY",
    "name:msa_x_preferred":[
        "Kampung Parit Empat"
    ],
    "wof:name":"Kampung Parit Empat",
    "wof:placetype":"locality"
},
  "geometry": {"coordinates":[103.2587,1.8114],"type":"Point"}
}