{
  "type": "Feature",
  "properties": {
    "gn:admin1_code":"12",
    "gn:asciiname":"Kampung Bukit Kemandul",
    "gn:country_code":"MY",
    "gn:dem":25,
    "gn:feature_class":"P",
    "gn:feature_code":"PPL",
    "gn:name":"Kampung Bukit Kemandul",
    "gn:population":0,
    "gn:timezone":"Asia/Kuala_Lumpur",
    "iso:country":"MY",
    "name:msa_x_preferred":[
        "Kampung Bukit Kemandul"
    ],
    "name:und_x_variant":[
        "Kampong Bukit Kemandul"
    ],
    "wof:name":"Kampung Bukit Kemandul",
    "wof:placetype":"locality"
},
  "geometry": {"coordinates":[101.53870000000001,2.9466],"type":"Point"}
}