{
  "type": "Feature",
  "properties": {
    "gn:admin1_code":"7",
    "gn:asciiname":"Kampung Sungai Haji Mohamad",
    "gn:country_code":"MY",
    "gn:dem":3,
    "gn:feature_class":"P",
    "gn:feature_code":"PPL",
    "gn:name":"Kampung Sungai Haji Mohamad",
    "gn:population":0,
    "gn:timezone":"Asia/Kuala_Lumpur",
    "iso:country":"MY",
    "name:msa_x_preferred":[
        "Kampung Sungai Haji Mohamad"
    ],
    "name:und_x_variant":[
        "Kampong Sungai Haji Mohamad"
    ],
    "wof:name":"Kampung Sungai Haji Mohamad",
    "wof:placetype":"locality"
},
  "geometry": {"coordinates":[100.77760000000001,3.905],"type":"Point"}
}