{
  "type": "Feature",
  "properties": {
    "gn:admin1_code":"7",
    "gn:asciiname":"Kampung Bandar Lama",
    "gn:country_code":"MY",
    "gn:dem":18,
    "gn:feature_class":"P",
    "gn:feature_code":"PPL",
    "gn:name":"Kampung Bandar Lama",
    "gn:population":0,
    "gn:timezone":"Asia/Kuala_Lumpur",
    "iso:country":"MY",
    "name:msa_x_preferred":[
        "Kampung Bandar Lama"
    ],
    "name:und_x_variant":[
        "Kampong Bandar Lama"
    ],
    "wof:name":"Kampung Bandar Lama",
    "wof:placetype":"locality"
},
  "geometry": {"coordinates":[100.9267,4.1902],"type":"Point"}
}