{
  "type": "Feature",
  "properties": {
    "gn:admin1_code":"2.0",
    "gn:asciiname":"Kampung Tebing Tinggi",
    "gn:country_code":"MY",
    "gn:dem":48,
    "gn:feature_class":"P",
    "gn:feature_code":"PPL",
    "gn:name":"Kampung Tebing Tinggi",
    "gn:population":0,
    "gn:timezone":"Asia/Kuala_Lumpur",
    "iso:country":"MY",
    "name:msa_x_preferred":[
        "Kampung Tebing Tinggi"
    ],
    "wof:name":"Kampung Tebing Tinggi",
    "wof:placetype":"locality"
},
  "geometry": {"coordinates":[100.83292,5.66793],"type":"Point"}
}