{
  "type": "Feature",
  "properties": {
    "iso:country":"MY",
    "qs:name":"Pulau Carey",
    "qs:name_adm0":"Malaysia",
    "qs:name_adm1":"Selangor",
    "qs:photos":145,
    "qs:photos_1k":29,
    "qs:photos_9k":1,
    "qs:photos_9r":3,
    "qs:photos_all":145,
    "qs:photos_sr":3,
    "qs:placetype":"Town",
    "qs:pop_sr":"0",
    "wof:name":"Pulau Carey",
    "wof:placetype":"locality"
},
  "geometry": {"coordinates":[101.836395,2.973898],"type":"Point"}
}