{
  "type": "Feature",
  "properties": {
    "gn:admin1_code":"7.0",
    "gn:asciiname":"Kedai Empat",
    "gn:cc2":"MY",
    "gn:country_code":"MY",
    "gn:dem":2,
    "gn:feature_class":"P",
    "gn:feature_code":"PPL",
    "gn:name":"Kedai Empat",
    "gn:population":0,
    "gn:timezone":"Asia/Kuala_Lumpur",
    "iso:country":"MY",
    "name:msa_x_preferred":[
        "Kedai Empat"
    ],
    "wof:name":"Kedai Empat",
    "wof:placetype":"locality"
},
  "geometry": {"coordinates":[100.43724,5.11097],"type":"Point"}
}