{
  "type": "Feature",
  "properties": {
    "gn:admin1_code":"7.0",
    "gn:asciiname":"Kampung Bendang Machang",
    "gn:country_code":"MY",
    "gn:dem":64,
    "gn:feature_class":"P",
    "gn:feature_code":"PPL",
    "gn:name":"Kampung Bendang Machang",
    "gn:population":0,
    "gn:timezone":"Asia/Kuala_Lumpur",
    "iso:country":"MY",
    "name:msa_x_preferred":[
        "Kampung Bendang Machang"
    ],
    "wof:name":"Kampung Bendang Machang",
    "wof:placetype":"locality"
},
  "geometry": {"coordinates":[100.95950000000001,4.8513],"type":"Point"}
}