{
  "type": "Feature",
  "properties": {
    "gn:admin1_code":"11",
    "gn:asciiname":"Rumah Umin",
    "gn:country_code":"MY",
    "gn:dem":153,
    "gn:feature_class":"P",
    "gn:feature_code":"PPL",
    "gn:name":"Rumah Umin",
    "gn:population":0,
    "gn:timezone":"Asia/Kuching",
    "iso:country":"MY",
    "wof:name":"Rumah Umin",
    "wof:placetype":"locality"
},
  "geometry": {"coordinates":[111.73333,1.76667],"type":"Point"}
}