{
  "type": "Feature",
  "properties": {
    "gn:admin1_code":"1",
    "gn:asciiname":"Bukit Kumbar",
    "gn:country_code":"MY",
    "gn:dem":55,
    "gn:feature_class":"P",
    "gn:feature_code":"PPL",
    "gn:name":"Bukit Kumbar",
    "gn:population":0,
    "gn:timezone":"Asia/Kuala_Lumpur",
    "iso:country":"MY",
    "name:und_x_variant":[
        "Bukit Kombel"
    ],
    "wof:name":"Bukit Kumbar",
    "wof:placetype":"locality"
},
  "geometry": {"coordinates":[102.82129999999999,2.58124],"type":"Point"}
}