{
  "type": "Feature",
  "properties": {
    "gn:admin1_code":"16",
    "gn:asciiname":"Kampung Sumilad",
    "gn:country_code":"MY",
    "gn:dem":34,
    "gn:feature_class":"P",
    "gn:feature_code":"PPL",
    "gn:name":"Kampung Sumilad",
    "gn:population":0,
    "gn:timezone":"Asia/Kuching",
    "iso:country":"MY",
    "name:msa_x_preferred":[
        "Kampung Sumilad"
    ],
    "name:und_x_variant":[
        "Kampong Sumilad"
    ],
    "wof:name":"Kampung Sumilad",
    "wof:placetype":"locality"
},
  "geometry": {"coordinates":[117.2042,5.806],"type":"Point"}
}