{
  "type": "Feature",
  "properties": {
    "gn:admin1_code":"9",
    "gn:asciiname":"Kampung Bukit Teh",
    "gn:cc2":"MY",
    "gn:country_code":"MY",
    "gn:dem":17,
    "gn:feature_class":"P",
    "gn:feature_code":"PPL",
    "gn:name":"Kampung Bukit Teh",
    "gn:population":0,
    "gn:timezone":"Asia/Kuala_Lumpur",
    "iso:country":"MY",
    "name:msa_x_preferred":[
        "Kampung Bukit Teh"
    ],
    "name:und_x_variant":[
        "Kampong Bukit Teh"
    ],
    "wof:name":"Kampung Bukit Teh",
    "wof:placetype":"locality"
},
  "geometry": {"coordinates":[100.50982999999999,5.316],"type":"Point"}
}