{
  "type": "Feature",
  "properties": {
    "gn:admin1_code":"11",
    "gn:asciiname":"Kampong Kandis Lama",
    "gn:cc2":"MY",
    "gn:country_code":"MY",
    "gn:dem":17,
    "gn:feature_class":"P",
    "gn:feature_code":"PPL",
    "gn:name":"Kampong Kandis Lama",
    "gn:population":0,
    "gn:timezone":"Asia/Kuching",
    "iso:country":"MY",
    "name:und_x_variant":[
        "Kandis",
        "Kampong Kandis",
        "Kampong Kandis Lama"
    ],
    "wof:name":"Kampong Kandis Lama",
    "wof:placetype":"locality"
},
  "geometry": {"coordinates":[110.21666999999999,1.45],"type":"Point"}
}