{
  "type": "Feature",
  "properties": {
    "iso:country":"MY",
    "name:ceb_x_preferred":[
        "Lumut"
    ],
    "name:msa_x_preferred":[
        "Lumut"
    ],
    "name:nld_x_preferred":[
        "Lumut"
    ],
    "name:pol_x_preferred":[
        "Lumut"
    ],
    "name:swe_x_preferred":[
        "Lumut"
    ],
    "qs:name":"Lumut",
    "qs:name_adm0":"Malaysia",
    "qs:name_adm1":"Perak",
    "qs:photos":143,
    "qs:photos_1k":29,
    "qs:photos_9k":19,
    "qs:photos_9r":12,
    "qs:photos_all":4186,
    "qs:photos_sr":3,
    "qs:placetype":"LocalAdmin",
    "qs:pop_sr":"0",
    "wd:wordcount":26,
    "wof:name":"Lumut",
    "wof:placetype":"localadmin"
},
  "geometry": {"coordinates":[100.557968,4.217254],"type":"Point"}
}