{
  "type": "Feature",
  "properties": {
    "gn:admin1_code":"6",
    "gn:asciiname":"Kampung Paya Kecil",
    "gn:country_code":"MY",
    "gn:dem":40,
    "gn:feature_class":"P",
    "gn:feature_code":"PPL",
    "gn:name":"Kampung Paya Kecil",
    "gn:population":0,
    "gn:timezone":"Asia/Kuala_Lumpur",
    "iso:country":"MY",
    "name:msa_x_preferred":[
        "Kampung Paya Kecil"
    ],
    "name:und_x_variant":[
        "Kampong Paya Kechik"
    ],
    "wof:name":"Kampung Paya Kecil",
    "wof:placetype":"locality"
},
  "geometry": {"coordinates":[102.3942,3.4665],"type":"Point"}
}