{
  "type": "Feature",
  "properties": {
    "gn:admin1_code":"16.0",
    "gn:asciiname":"Kampung Silawa",
    "gn:country_code":"MY",
    "gn:dem":-9999,
    "gn:feature_class":"P",
    "gn:feature_code":"PPL",
    "gn:name":"Kampung Silawa",
    "gn:population":0,
    "gn:timezone":"Asia/Kuching",
    "iso:country":"MY",
    "name:msa_x_preferred":[
        "Kampung Silawa"
    ],
    "name:und_x_variant":[
        "Silawa"
    ],
    "wof:name":"Kampung Silawa",
    "wof:placetype":"locality"
},
  "geometry": {"coordinates":[118.5797,4.5545],"type":"Point"}
}