{
  "type": "Feature",
  "properties": {
    "gn:admin1_code":"1",
    "gn:asciiname":"Kampung Batu Sembilan Belas",
    "gn:country_code":"MY",
    "gn:dem":34,
    "gn:feature_class":"P",
    "gn:feature_code":"PPL",
    "gn:name":"Kampung Batu Sembilan Belas",
    "gn:population":0,
    "gn:timezone":"Asia/Kuala_Lumpur",
    "iso:country":"MY",
    "name:msa_x_preferred":[
        "Kampung Batu Sembilan Belas"
    ],
    "name:und_x_variant":[
        "Kampong Batu"
    ],
    "wof:name":"Kampung Batu Sembilan Belas",
    "wof:placetype":"locality"
},
  "geometry": {"coordinates":[102.66540000000001,2.2935],"type":"Point"}
}