{
  "type": "Feature",
  "properties": {
    "gn:admin1_code":"6.0",
    "gn:asciiname":"Kampung Baharu Sempalit Hilir",
    "gn:country_code":"MY",
    "gn:dem":146,
    "gn:feature_class":"P",
    "gn:feature_code":"PPL",
    "gn:name":"Kampung Baharu Sempalit Hilir",
    "gn:population":0,
    "gn:timezone":"Asia/Kuala_Lumpur",
    "iso:country":"MY",
    "name:msa_x_preferred":[
        "Kampung Baharu Sempalit Hilir"
    ],
    "wof:name":"Kampung Baharu Sempalit Hilir",
    "wof:placetype":"locality"
},
  "geometry": {"coordinates":[101.87139999999999,3.8001],"type":"Point"}
}