{
  "type": "Feature",
  "properties": {
    "gn:admin1_code":"13.0",
    "gn:asciiname":"Pak Sabah",
    "gn:country_code":"MY",
    "gn:dem":11,
    "gn:feature_class":"P",
    "gn:feature_code":"PPL",
    "gn:name":"Pak Sabah",
    "gn:population":0,
    "gn:timezone":"Asia/Kuala_Lumpur",
    "iso:country":"MY",
    "name:msa_x_preferred":[
        "Pak Sabah"
    ],
    "wof:name":"Pak Sabah",
    "wof:placetype":"locality"
},
  "geometry": {"coordinates":[103.4148,4.7525],"type":"Point"}
}