{
  "type": "Feature",
  "properties": {
    "gn:admin1_code":"12.0",
    "gn:asciiname":"Kampung Batu Sebelas",
    "gn:country_code":"MY",
    "gn:dem":94,
    "gn:feature_class":"P",
    "gn:feature_code":"PPL",
    "gn:name":"Kampung Batu Sebelas",
    "gn:population":0,
    "gn:timezone":"Asia/Kuala_Lumpur",
    "iso:country":"MY",
    "name:msa_x_preferred":[
        "Kampung Batu Sebelas"
    ],
    "wof:name":"Kampung Batu Sebelas",
    "wof:placetype":"locality"
},
  "geometry": {"coordinates":[101.7294,3.2812],"type":"Point"}
}