{
  "type": "Feature",
  "properties": {
    "gn:admin1_code":"1",
    "gn:asciiname":"Kampung Teluk Sauk",
    "gn:country_code":"MY",
    "gn:dem":50,
    "gn:feature_class":"P",
    "gn:feature_code":"PPL",
    "gn:name":"Kampung Teluk Sauk",
    "gn:population":0,
    "gn:timezone":"Asia/Kuala_Lumpur",
    "iso:country":"MY",
    "name:msa_x_preferred":[
        "Kampung Teluk Sauk"
    ],
    "name:und_x_variant":[
        "Kampong Telok Sauk"
    ],
    "wof:name":"Kampung Teluk Sauk",
    "wof:placetype":"locality"
},
  "geometry": {"coordinates":[104.1003,2.2992],"type":"Point"}
}