{
  "type": "Feature",
  "properties": {
    "gn:admin1_code":"16.0",
    "gn:asciiname":"Kampung Gading Gading",
    "gn:country_code":"MY",
    "gn:dem":19,
    "gn:feature_class":"P",
    "gn:feature_code":"PPL",
    "gn:name":"Kampung Gading Gading",
    "gn:population":0,
    "gn:timezone":"Asia/Kuching",
    "iso:country":"MY",
    "name:und_x_variant":[
        "Gago",
        "Sago",
        "Kampong Gading Gading",
        "Kampung Gading Gading"
    ],
    "wof:name":"Kampung Gading Gading",
    "wof:placetype":"locality"
},
  "geometry": {"coordinates":[118.36109999999999,4.6296],"type":"Point"}
}