{
  "type": "Feature",
  "properties": {
    "gn:admin1_code":"6.0",
    "gn:asciiname":"Kampung Asap",
    "gn:country_code":"MY",
    "gn:dem":117,
    "gn:feature_class":"P",
    "gn:feature_code":"PPL",
    "gn:name":"Kampung Asap",
    "gn:population":0,
    "gn:timezone":"Asia/Kuala_Lumpur",
    "iso:country":"MY",
    "name:msa_x_preferred":[
        "Kampung Asap"
    ],
    "wof:name":"Kampung Asap",
    "wof:placetype":"locality"
},
  "geometry": {"coordinates":[101.90089999999999,3.6212],"type":"Point"}
}