{
  "type": "Feature",
  "properties": {
    "gn:admin1_code":"2",
    "gn:asciiname":"Kampung Padang Ah Taw",
    "gn:cc2":"MY",
    "gn:country_code":"MY",
    "gn:dem":33,
    "gn:feature_class":"P",
    "gn:feature_code":"PPL",
    "gn:name":"Kampung Padang Ah Taw",
    "gn:population":0,
    "gn:timezone":"Asia/Kuala_Lumpur",
    "iso:country":"MY",
    "name:msa_x_preferred":[
        "Kampung Padang Ah Taw"
    ],
    "name:und_x_variant":[
        "Kampong Padang Ah Taw"
    ],
    "wof:name":"Kampung Padang Ah Taw",
    "wof:placetype":"locality"
},
  "geometry": {"coordinates":[100.68783000000001,5.51106],"type":"Point"}
}