{
  "type": "Feature",
  "properties": {
    "gn:admin1_code":"9",
    "gn:asciiname":"Kampung Pa Bo",
    "gn:cc2":"MY",
    "gn:country_code":"MY",
    "gn:dem":9,
    "gn:feature_class":"P",
    "gn:feature_code":"PPL",
    "gn:name":"Kampung Pa Bo",
    "gn:population":0,
    "gn:timezone":"Asia/Kuala_Lumpur",
    "iso:country":"MY",
    "name:msa_x_preferred":[
        "Kampung Pa Bo"
    ],
    "name:und_x_variant":[
        "Pa Boi",
        "Kampong Pa Boi"
    ],
    "wof:name":"Kampung Pa Bo",
    "wof:placetype":"locality"
},
  "geometry": {"coordinates":[100.45775999999999,5.26683],"type":"Point"}
}