{
  "type": "Feature",
  "properties": {
    "gn:admin1_code":"16.0",
    "gn:asciiname":"Kampung Mandurian",
    "gn:country_code":"MY",
    "gn:dem":26,
    "gn:feature_class":"P",
    "gn:feature_code":"PPL",
    "gn:name":"Kampung Mandurian",
    "gn:population":0,
    "gn:timezone":"Asia/Kuching",
    "iso:country":"MY",
    "name:msa_x_preferred":[
        "Kampung Mandurian"
    ],
    "wof:name":"Kampung Mandurian",
    "wof:placetype":"locality"
},
  "geometry": {"coordinates":[117.0446,6.6361],"type":"Point"}
}