{
  "type": "Feature",
  "properties": {
    "gn:admin1_code":"11.0",
    "gn:asciiname":"Teng Bukap",
    "gn:country_code":"MY",
    "gn:dem":106,
    "gn:feature_class":"P",
    "gn:feature_code":"PPL",
    "gn:name":"Teng Bukap",
    "gn:population":0,
    "gn:timezone":"Asia/Kuching",
    "iso:country":"MY",
    "name:und_x_variant":[
        "Tiang Bakap"
    ],
    "wof:name":"Teng Bukap",
    "wof:placetype":"locality"
},
  "geometry": {"coordinates":[110.3655,1.20832],"type":"Point"}
}