{
  "type": "Feature",
  "properties": {
    "gn:admin1_code":"6",
    "gn:asciiname":"Kampung Belawin",
    "gn:country_code":"MY",
    "gn:dem":72,
    "gn:feature_class":"P",
    "gn:feature_code":"PPL",
    "gn:name":"Kampung Belawin",
    "gn:population":0,
    "gn:timezone":"Asia/Kuala_Lumpur",
    "iso:country":"MY",
    "name:msa_x_preferred":[
        "Kampung Belawin"
    ],
    "name:und_x_variant":[
        "Kampong Blawin",
        "Kampong Belawin"
    ],
    "wof:name":"Kampung Belawin",
    "wof:placetype":"locality"
},
  "geometry": {"coordinates":[102.3844,4.2339],"type":"Point"}
}