{
  "type": "Feature",
  "properties": {
    "gn:admin1_code":"8.0",
    "gn:asciiname":"Pantai Cenang",
    "gn:country_code":"MY",
    "gn:dem":8,
    "gn:feature_class":"P",
    "gn:feature_code":"PPL",
    "gn:name":"Pantai Cenang",
    "gn:population":15000,
    "gn:timezone":"Asia/Kuala_Lumpur",
    "iso:country":"MY",
    "name:rus_x_preferred":[
        "\u041f\u0430\u043d\u0442\u0430\u0439-\u0421\u0435\u043d\u0430\u043d\u0433"
    ],
    "name:und_x_variant":[
        "\u041f\u0430\u043d\u0442\u0430\u0439 \u0427\u0435\u043d\u0430\u043d\u0433",
        "\u041f\u0430\u043d\u0442\u0430\u0439-\u0422\u0435\u043d\u0433\u0430\u0445"
    ],
    "wof:name":"Pantai Cenang",
    "wof:placetype":"locality",
    "wof:population":15000
},
  "geometry": {"coordinates":[99.72786000000001,6.29369],"type":"Point"}
}