{
  "type": "Feature",
  "properties": {
    "gn:admin1_code":"1.0",
    "gn:asciiname":"Kampung Tanjung Gading Laut",
    "gn:country_code":"MY",
    "gn:dem":11,
    "gn:feature_class":"P",
    "gn:feature_code":"PPL",
    "gn:name":"Kampung Tanjung Gading Laut",
    "gn:population":0,
    "gn:timezone":"Asia/Kuala_Lumpur",
    "iso:country":"MY",
    "name:msa_x_preferred":[
        "Kampung Tanjung Gading Laut"
    ],
    "wof:name":"Kampung Tanjung Gading Laut",
    "wof:placetype":"locality"
},
  "geometry": {"coordinates":[102.5421,2.0684],"type":"Point"}
}