{
  "type": "Feature",
  "properties": {
    "gn:admin1_code":"2.0",
    "gn:asciiname":"Kampung Bukit Terbak",
    "gn:country_code":"MY",
    "gn:dem":55,
    "gn:feature_class":"P",
    "gn:feature_code":"PPL",
    "gn:name":"Kampung Bukit Terbak",
    "gn:population":0,
    "gn:timezone":"Asia/Kuala_Lumpur",
    "iso:country":"MY",
    "name:msa_x_preferred":[
        "Kampung Bukit Terbak"
    ],
    "wof:name":"Kampung Bukit Terbak",
    "wof:placetype":"locality"
},
  "geometry": {"coordinates":[100.85236,5.64184],"type":"Point"}
}