{
  "type": "Feature",
  "properties": {
    "gn:admin1_code":"2.0",
    "gn:asciiname":"Kampung Baharu Batu Enam Belas",
    "gn:country_code":"MY",
    "gn:dem":37,
    "gn:feature_class":"P",
    "gn:feature_code":"PPL",
    "gn:name":"Kampung Baharu Batu Enam Belas",
    "gn:population":0,
    "gn:timezone":"Asia/Kuala_Lumpur",
    "iso:country":"MY",
    "name:msa_x_preferred":[
        "Kampung Baharu Batu Enam Belas"
    ],
    "wof:name":"Kampung Baharu Batu Enam Belas",
    "wof:placetype":"locality"
},
  "geometry": {"coordinates":[100.61084,5.21794],"type":"Point"}
}