{
  "type": "Feature",
  "properties": {
    "gn:admin1_code":"4.0",
    "gn:asciiname":"Kampung Parit Sialang",
    "gn:country_code":"MY",
    "gn:dem":12,
    "gn:feature_class":"P",
    "gn:feature_code":"PPL",
    "gn:name":"Kampung Parit Sialang",
    "gn:population":0,
    "gn:timezone":"Asia/Kuala_Lumpur",
    "iso:country":"MY",
    "name:msa_x_preferred":[
        "Kampung Parit Sialang"
    ],
    "wof:name":"Kampung Parit Sialang",
    "wof:placetype":"locality"
},
  "geometry": {"coordinates":[102.4894,2.1458],"type":"Point"}
}