{
  "type": "Feature",
  "properties": {
    "gn:admin1_code":"1.0",
    "gn:asciiname":"Kampung Baharu Camek",
    "gn:country_code":"MY",
    "gn:dem":41,
    "gn:feature_class":"P",
    "gn:feature_code":"PPL",
    "gn:name":"Kampung Baharu Camek",
    "gn:population":0,
    "gn:timezone":"Asia/Kuala_Lumpur",
    "iso:country":"MY",
    "name:msa_x_preferred":[
        "Kampung Baharu Camek"
    ],
    "wof:name":"Kampung Baharu Camek",
    "wof:placetype":"locality"
},
  "geometry": {"coordinates":[103.2668,2.1688],"type":"Point"}
}