{
  "type": "Feature",
  "properties": {
    "gn:admin1_code":"6.0",
    "gn:asciiname":"Kampung Gua Lima",
    "gn:country_code":"MY",
    "gn:dem":160,
    "gn:feature_class":"P",
    "gn:feature_code":"PPL",
    "gn:name":"Kampung Gua Lima",
    "gn:population":0,
    "gn:timezone":"Asia/Kuala_Lumpur",
    "iso:country":"MY",
    "name:msa_x_preferred":[
        "Kampung Gua Lima"
    ],
    "wof:name":"Kampung Gua Lima",
    "wof:placetype":"locality"
},
  "geometry": {"coordinates":[102.00149999999999,4.6835],"type":"Point"}
}