{
  "type": "Feature",
  "properties": {
    "gn:admin1_code":"1.0",
    "gn:asciiname":"Ladang Sungai Gemas",
    "gn:country_code":"MY",
    "gn:dem":41,
    "gn:feature_class":"P",
    "gn:feature_code":"PPL",
    "gn:name":"Ladang Sungai Gemas",
    "gn:population":0,
    "gn:timezone":"Asia/Kuala_Lumpur",
    "iso:country":"MY",
    "name:msa_x_preferred":[
        "Ladang Sungai Gemas"
    ],
    "wof:name":"Ladang Sungai Gemas",
    "wof:placetype":"locality"
},
  "geometry": {"coordinates":[102.6438,2.5796],"type":"Point"}
}