{
  "type": "Feature",
  "properties": {
    "gn:admin1_code":"1",
    "gn:asciiname":"Kampung Baharu Ban Foo",
    "gn:country_code":"MY",
    "gn:dem":45,
    "gn:feature_class":"P",
    "gn:feature_code":"PPL",
    "gn:name":"Kampung Baharu Ban Foo",
    "gn:population":0,
    "gn:timezone":"Asia/Kuala_Lumpur",
    "iso:country":"MY",
    "name:msa_x_preferred":[
        "Kampung Baharu Ban Foo"
    ],
    "name:und_x_variant":[
        "Ban Foo New Village",
        "Ban Foo",
        "Kampong Baru Ban Foo"
    ],
    "wof:name":"Kampung Baharu Ban Foo",
    "wof:placetype":"locality"
},
  "geometry": {"coordinates":[103.8533,1.5675],"type":"Point"}
}