{
  "type": "Feature",
  "properties": {
    "gn:admin1_code":"6",
    "gn:asciiname":"Kampong Keledik",
    "gn:cc2":"MY",
    "gn:country_code":"MY",
    "gn:dem":119,
    "gn:feature_class":"P",
    "gn:feature_code":"PPL",
    "gn:name":"Kampong Keledik",
    "gn:population":0,
    "gn:timezone":"Asia/Kuala_Lumpur",
    "iso:country":"MY",
    "name:und_x_variant":[
        "Kampong Kledik",
        "Kampong Keledik"
    ],
    "wof:name":"Kampong Keledik",
    "wof:placetype":"locality"
},
  "geometry": {"coordinates":[101.91667,4.23333],"type":"Point"}
}