{
  "type": "Feature",
  "properties": {
    "gn:admin1_code":"1.0",
    "gn:asciiname":"Kampung Bukit Kuching",
    "gn:country_code":"MY",
    "gn:dem":29,
    "gn:feature_class":"P",
    "gn:feature_code":"PPL",
    "gn:name":"Kampung Bukit Kuching",
    "gn:population":0,
    "gn:timezone":"Asia/Kuala_Lumpur",
    "iso:country":"MY",
    "name:msa_x_preferred":[
        "Kampung Bukit Kuching"
    ],
    "wof:name":"Kampung Bukit Kuching",
    "wof:placetype":"locality"
},
  "geometry": {"coordinates":[103.59990000000001,1.3875],"type":"Point"}
}