{
  "type": "Feature",
  "properties": {
    "gn:country":"MY",
    "gn:fcode":"PPL",
    "gn:population":0,
    "iso:country":"MY",
    "qs:name":"Long Lama",
    "qs:name_adm0":"Malaysia",
    "qs:name_adm1":"Sarawak",
    "qs:photos_9k":1,
    "qs:photos_9r":4,
    "qs:photos_all":182,
    "qs:photos_sr":0,
    "qs:placetype":"Town",
    "qs:pop_sr":"0",
    "wof:name":"Long Lama",
    "wof:placetype":"locality",
    "wof:population":0
},
  "geometry": {"coordinates":[114.40000000000001,3.76667],"type":"Point"}
}