{
  "type": "Feature",
  "properties": {
    "gn:admin1_code":"16.0",
    "gn:asciiname":"Kampung Dalas",
    "gn:country_code":"MY",
    "gn:dem":27,
    "gn:feature_class":"P",
    "gn:feature_code":"PPL",
    "gn:name":"Kampung Dalas",
    "gn:population":0,
    "gn:timezone":"Asia/Kuching",
    "iso:country":"MY",
    "name:msa_x_preferred":[
        "Kampung Dalas"
    ],
    "wof:name":"Kampung Dalas",
    "wof:placetype":"locality"
},
  "geometry": {"coordinates":[117.14749999999999,6.9936],"type":"Point"}
}