{
  "type": "Feature",
  "properties": {
    "gn:admin1_code":"3.0",
    "gn:asciiname":"Lubok Batu",
    "gn:country_code":"MY",
    "gn:dem":52,
    "gn:feature_class":"P",
    "gn:feature_code":"PPL",
    "gn:name":"Lubok Batu",
    "gn:population":0,
    "gn:timezone":"Asia/Kuala_Lumpur",
    "iso:country":"MY",
    "name:msa_x_preferred":[
        "Lubok Batu"
    ],
    "wof:name":"Lubok Batu",
    "wof:placetype":"locality"
},
  "geometry": {"coordinates":[102.21598,5.67896],"type":"Point"}
}