{
  "type": "Feature",
  "properties": {
    "gn:admin1_code":"11.0",
    "gn:asciiname":"Rumah Lutom",
    "gn:country_code":"MY",
    "gn:dem":71,
    "gn:feature_class":"P",
    "gn:feature_code":"PPL",
    "gn:name":"Rumah Lutom",
    "gn:population":0,
    "gn:timezone":"Asia/Kuching",
    "iso:country":"MY",
    "wof:name":"Rumah Lutom",
    "wof:placetype":"locality"
},
  "geometry": {"coordinates":[112.90000000000001,2.06667],"type":"Point"}
}