{
  "type": "Feature",
  "properties": {
    "gn:admin1_code":"6",
    "gn:asciiname":"Kampung Orang Asli Sungai Jin",
    "gn:country_code":"MY",
    "gn:dem":44,
    "gn:feature_class":"P",
    "gn:feature_code":"PPL",
    "gn:name":"Kampung Orang Asli Sungai Jin",
    "gn:population":0,
    "gn:timezone":"Asia/Kuala_Lumpur",
    "iso:country":"MY",
    "name:msa_x_preferred":[
        "Kampung Orang Asli Sungai Jin"
    ],
    "name:und_x_variant":[
        "Kampong Sungai Jin"
    ],
    "wof:name":"Kampung Orang Asli Sungai Jin",
    "wof:placetype":"locality"
},
  "geometry": {"coordinates":[103.0301,3.9647],"type":"Point"}
}