{
  "type": "Feature",
  "properties": {
    "gn:admin1_code":"6",
    "gn:asciiname":"Kampong Keluyong",
    "gn:country_code":"MY",
    "gn:dem":104,
    "gn:feature_class":"P",
    "gn:feature_code":"PPL",
    "gn:name":"Kampong Keluyong",
    "gn:population":0,
    "gn:timezone":"Asia/Kuala_Lumpur",
    "iso:country":"MY",
    "wof:name":"Kampong Keluyong",
    "wof:placetype":"locality"
},
  "geometry": {"coordinates":[101.81667,4.28333],"type":"Point"}
}