{
  "type": "Feature",
  "properties": {
    "gn:admin1_code":"12.0",
    "gn:asciiname":"Taman Hiew Piow",
    "gn:country_code":"MY",
    "gn:dem":50,
    "gn:feature_class":"P",
    "gn:feature_code":"PPL",
    "gn:name":"Taman Hiew Piow",
    "gn:population":0,
    "gn:timezone":"Asia/Kuala_Lumpur",
    "iso:country":"MY",
    "name:msa_x_preferred":[
        "Taman Hiew Piow"
    ],
    "wof:name":"Taman Hiew Piow",
    "wof:placetype":"locality"
},
  "geometry": {"coordinates":[101.8489,2.9621],"type":"Point"}
}