{
  "type": "Feature",
  "properties": {
    "gn:admin1_code":"1.0",
    "gn:asciiname":"Kampung Tanah Merah",
    "gn:country_code":"MY",
    "gn:dem":51,
    "gn:feature_class":"P",
    "gn:feature_code":"PPL",
    "gn:name":"Kampung Tanah Merah",
    "gn:population":0,
    "gn:timezone":"Asia/Kuala_Lumpur",
    "iso:country":"MY",
    "name:msa_x_preferred":[
        "Kampung Tanah Merah"
    ],
    "wof:name":"Kampung Tanah Merah",
    "wof:placetype":"locality"
},
  "geometry": {"coordinates":[102.8437,2.0705],"type":"Point"}
}