{
  "type": "Feature",
  "properties": {
    "gn:admin1_code":"2.0",
    "gn:asciiname":"Kampung Paya Serdang",
    "gn:country_code":"MY",
    "gn:dem":18,
    "gn:feature_class":"P",
    "gn:feature_code":"PPL",
    "gn:name":"Kampung Paya Serdang",
    "gn:population":0,
    "gn:timezone":"Asia/Kuala_Lumpur",
    "iso:country":"MY",
    "name:msa_x_preferred":[
        "Kampung Paya Serdang"
    ],
    "wof:name":"Kampung Paya Serdang",
    "wof:placetype":"locality"
},
  "geometry": {"coordinates":[100.57093,5.44909],"type":"Point"}
}