{
  "type": "Feature",
  "properties": {
    "gn:admin1_code":"7",
    "gn:asciiname":"Kampong Banggol Batu",
    "gn:cc2":"MY",
    "gn:country_code":"MY",
    "gn:dem":71,
    "gn:feature_class":"P",
    "gn:feature_code":"PPL",
    "gn:name":"Kampong Banggol Batu",
    "gn:population":0,
    "gn:timezone":"Asia/Kuala_Lumpur",
    "iso:country":"MY",
    "name:und_x_variant":[
        "Kampong Banggul Batu",
        "Kampong Banggol Batu"
    ],
    "wof:name":"Kampong Banggol Batu",
    "wof:placetype":"locality"
},
  "geometry": {"coordinates":[100.96238,5.06273],"type":"Point"}
}