{
  "type": "Feature",
  "properties": {
    "gn:admin1_code":"2",
    "gn:asciiname":"Kampung Jerai",
    "gn:cc2":"MY",
    "gn:country_code":"MY",
    "gn:dem":66,
    "gn:feature_class":"P",
    "gn:feature_code":"PPL",
    "gn:name":"Kampung Jerai",
    "gn:population":0,
    "gn:timezone":"Asia/Kuala_Lumpur",
    "iso:country":"MY",
    "name:msa_x_preferred":[
        "Kampung Jerai"
    ],
    "name:und_x_variant":[
        "Kampong Jerai"
    ],
    "wof:name":"Kampung Jerai",
    "wof:placetype":"locality"
},
  "geometry": {"coordinates":[100.78225999999999,5.83641],"type":"Point"}
}