{
  "type": "Feature",
  "properties": {
    "iso:country":"MY",
    "name:und_x_variant":[
        "Kampung Batu Lanchang"
    ],
    "qs:gn_adm0_cc":"MY",
    "qs:gn_local":1735106,
    "qs:local_max":5776,
    "qs:local_sum":22216,
    "qs:localhoods":25,
    "qs:name":"Kampung Batu Lanchang",
    "qs:name_adm0":"Malaysia",
    "qs:name_adm1":"Pulau Pinang",
    "qs:name_adm2":"Timur Laut",
    "qs:name_lau":"Bandar Jelutung",
    "qs:name_local":"George Town",
    "qs:photo_max":16,
    "qs:photo_sum":16,
    "qs:placetype":"Suburb",
    "qs:quad_count":1,
    "qs:woe_adm0":23424901,
    "qs:woe_adm1":2346304,
    "qs:woe_adm2":56013581,
    "qs:woe_funk":"Parented by a neighborhood",
    "qs:woe_lau":56013786,
    "qs:woe_local":1141153,
    "qs:woe_ver":"7.10.0",
    "wof:lang":[
        "unk"
    ],
    "wof:name":"Kampung Batu Lanchang",
    "wof:placetype":"neighbourhood"
},
  "geometry": {"coordinates":[100.313416,5.400008],"type":"Point"}
}