{
  "type": "Feature",
  "properties": {
    "gn:admin1_code":"16.0",
    "gn:asciiname":"Kampung Radtak",
    "gn:country_code":"MY",
    "gn:dem":60,
    "gn:feature_class":"P",
    "gn:feature_code":"PPL",
    "gn:name":"Kampung Radtak",
    "gn:population":0,
    "gn:timezone":"Asia/Kuching",
    "iso:country":"MY",
    "name:msa_x_preferred":[
        "Kampung Radtak"
    ],
    "name:und_x_variant":[
        "Radta",
        "Radtak"
    ],
    "wof:name":"Kampung Radtak",
    "wof:placetype":"locality"
},
  "geometry": {"coordinates":[116.75539999999999,6.736],"type":"Point"}
}