{
  "type": "Feature",
  "properties": {
    "gn:admin1_code":"1",
    "gn:asciiname":"Kampung Paya Pulai",
    "gn:country_code":"MY",
    "gn:dem":20,
    "gn:feature_class":"P",
    "gn:feature_code":"PPL",
    "gn:name":"Kampung Paya Pulai",
    "gn:population":0,
    "gn:timezone":"Asia/Kuala_Lumpur",
    "iso:country":"MY",
    "name:msa_x_preferred":[
        "Kampung Paya Pulai"
    ],
    "name:und_x_variant":[
        "Paya Pulai",
        "Kampong Paya Pulai"
    ],
    "wof:name":"Kampung Paya Pulai",
    "wof:placetype":"locality"
},
  "geometry": {"coordinates":[102.8227,2.4931],"type":"Point"}
}