{
  "type": "Feature",
  "properties": {
    "gn:admin1_code":"6.0",
    "gn:asciiname":"Kampung Baru Bukit Lada",
    "gn:country_code":"MY",
    "gn:dem":66,
    "gn:feature_class":"P",
    "gn:feature_code":"PPL",
    "gn:name":"Kampung Baru Bukit Lada",
    "gn:population":0,
    "gn:timezone":"Asia/Kuala_Lumpur",
    "iso:country":"MY",
    "name:msa_x_preferred":[
        "Kampung Baru Bukit Lada"
    ],
    "wof:name":"Kampung Baru Bukit Lada",
    "wof:placetype":"locality"
},
  "geometry": {"coordinates":[102.5552,3.5219],"type":"Point"}
}