{
  "type": "Feature",
  "properties": {
    "gn:admin1_code":"2.0",
    "gn:asciiname":"Kampung Tok Kun",
    "gn:country_code":"MY",
    "gn:dem":26,
    "gn:feature_class":"P",
    "gn:feature_code":"PPL",
    "gn:name":"Kampung Tok Kun",
    "gn:population":0,
    "gn:timezone":"Asia/Kuala_Lumpur",
    "iso:country":"MY",
    "name:msa_x_preferred":[
        "Kampung Tok Kun"
    ],
    "wof:name":"Kampung Tok Kun",
    "wof:placetype":"locality"
},
  "geometry": {"coordinates":[100.51369,6.14754],"type":"Point"}
}