{
  "type": "Feature",
  "properties": {
    "gn:admin1_code":"13",
    "gn:asciiname":"Padang Luas",
    "gn:country_code":"MY",
    "gn:dem":22,
    "gn:feature_class":"P",
    "gn:feature_code":"PPL",
    "gn:name":"Padang Luas",
    "gn:population":0,
    "gn:timezone":"Asia/Kuala_Lumpur",
    "iso:country":"MY",
    "name:msa_x_preferred":[
        "Padang Luas"
    ],
    "wof:name":"Padang Luas",
    "wof:placetype":"locality"
},
  "geometry": {"coordinates":[102.47311999999999,5.73677],"type":"Point"}
}