{
  "type": "Feature",
  "properties": {
    "gn:admin1_code":"16.0",
    "gn:asciiname":"Kelapa",
    "gn:country_code":"MY",
    "gn:dem":14,
    "gn:elevation":"0.0",
    "gn:feature_class":"P",
    "gn:feature_code":"PPL",
    "gn:name":"Kelapa",
    "gn:population":0,
    "gn:timezone":"Asia/Kuching",
    "iso:country":"MY",
    "name:ceb_x_preferred":[
        "Kelapa"
    ],
    "name:nld_x_preferred":[
        "Kelapa"
    ],
    "name:swe_x_preferred":[
        "Kelapa"
    ],
    "name:und_x_variant":[
        "Kampong Kelapa"
    ],
    "wof:name":"Kelapa",
    "wof:placetype":"locality"
},
  "geometry": {"coordinates":[117.7885,4.3929],"type":"Point"}
}