{
  "type": "Feature",
  "properties": {
    "gn:admin1_code":"2.0",
    "gn:asciiname":"Kampung Platehi",
    "gn:cc2":"MY",
    "gn:country_code":"MY",
    "gn:dem":77,
    "gn:feature_class":"P",
    "gn:feature_code":"PPL",
    "gn:name":"Kampung Platehi",
    "gn:population":0,
    "gn:timezone":"Asia/Kuala_Lumpur",
    "iso:country":"MY",
    "name:msa_x_preferred":[
        "Kampung Platehi"
    ],
    "wof:name":"Kampung Platehi",
    "wof:placetype":"locality"
},
  "geometry": {"coordinates":[100.74045,6.02469],"type":"Point"}
}