{
  "type": "Feature",
  "properties": {
    "gn:admin1_code":"16",
    "gn:asciiname":"Malaing",
    "gn:country_code":"MY",
    "gn:dem":416,
    "gn:feature_class":"P",
    "gn:feature_code":"PPL",
    "gn:name":"Malaing",
    "gn:population":0,
    "gn:timezone":"Asia/Kuching",
    "iso:country":"MY",
    "wof:name":"Malaing",
    "wof:placetype":"locality"
},
  "geometry": {"coordinates":[116.13333,4.95],"type":"Point"}
}