{
  "type": "Feature",
  "properties": {
    "gn:admin1_code":"16",
    "gn:asciiname":"Kampung Kalasunan",
    "gn:country_code":"MY",
    "gn:dem":226,
    "gn:feature_class":"P",
    "gn:feature_code":"PPL",
    "gn:name":"Kampung Kalasunan",
    "gn:population":0,
    "gn:timezone":"Asia/Kuching",
    "iso:country":"MY",
    "name:msa_x_preferred":[
        "Kampung Kalasunan"
    ],
    "name:und_x_variant":[
        "Kampong Kalasunan"
    ],
    "wof:name":"Kampung Kalasunan",
    "wof:placetype":"locality"
},
  "geometry": {"coordinates":[116.211,5.9411],"type":"Point"}
}