{
  "type": "Feature",
  "properties": {
    "gn:admin1_code":"9",
    "gn:asciiname":"Kampung Pa Thau",
    "gn:country_code":"MY",
    "gn:dem":6,
    "gn:feature_class":"P",
    "gn:feature_code":"PPL",
    "gn:name":"Kampung Pa Thau",
    "gn:population":0,
    "gn:timezone":"Asia/Kuala_Lumpur",
    "iso:country":"MY",
    "name:msa_x_preferred":[
        "Kampung Pa Thau"
    ],
    "name:und_x_variant":[
        "Pa Thau",
        "Kampong Pa Thau"
    ],
    "wof:name":"Kampung Pa Thau",
    "wof:placetype":"locality"
},
  "geometry": {"coordinates":[100.45648,5.27767],"type":"Point"}
}