{
  "type": "Feature",
  "properties": {
    "iso:country":"MY",
    "qs:name":"Serendah",
    "qs:name_adm0":"Malaysia",
    "qs:name_adm1":"Selangor",
    "qs:photos":2,
    "qs:photos_1k":1,
    "qs:photos_9k":1,
    "qs:photos_9r":2,
    "qs:photos_all":53,
    "qs:photos_sr":1,
    "qs:placetype":"LocalAdmin",
    "qs:pop_sr":"0",
    "wd:wordcount":184,
    "wof:name":"Serendah",
    "wof:placetype":"localadmin"
},
  "geometry": {"coordinates":[101.54800400000001,3.420893],"type":"Point"}
}