{
  "type": "Feature",
  "properties": {
    "iso:country":"MY",
    "name:bul_x_preferred":[
        "\u0421\u0435\u0440\u0435\u043d\u0434\u0430\u0445"
    ],
    "name:ceb_x_preferred":[
        "Serendah"
    ],
    "name:eng_x_preferred":[
        "Serendah"
    ],
    "name:epo_x_preferred":[
        "Serendah"
    ],
    "name:fas_x_preferred":[
        "\u0633\u0631\u0646\u062f\u0627\u0647"
    ],
    "name:jpn_x_preferred":[
        "\u30b9\u30ec\u30f3\u30c0"
    ],
    "name:msa_x_preferred":[
        "Serendah"
    ],
    "name:nld_x_preferred":[
        "Serendah"
    ],
    "name:tam_x_preferred":[
        "\u0b9a\u0bc6\u0bb0\u0ba3\u0bcd\u0b9f\u0bbe"
    ],
    "name:zho_x_preferred":[
        "\u53cc\u6587\u4e39"
    ],
    "qs:name":"Serendah",
    "qs:name_adm0":"Malaysia",
    "qs:name_adm1":"Selangor",
    "qs:photos":2,
    "qs:photos_1k":1,
    "qs:photos_9k":1,
    "qs:photos_9r":2,
    "qs:photos_all":53,
    "qs:photos_sr":1,
    "qs:placetype":"LocalAdmin",
    "qs:pop_sr":"0",
    "wd:wordcount":184,
    "wof:name":"Serendah",
    "wof:placetype":"localadmin"
},
  "geometry": {"coordinates":[101.54800400000001,3.420893],"type":"Point"}
}