{
  "type": "Feature",
  "properties": {
    "gn:admin1_code":"13",
    "gn:asciiname":"Kampung Lerek",
    "gn:country_code":"MY",
    "gn:dem":13,
    "gn:feature_class":"P",
    "gn:feature_code":"PPL",
    "gn:name":"Kampung Lerek",
    "gn:population":0,
    "gn:timezone":"Asia/Kuala_Lumpur",
    "iso:country":"MY",
    "name:msa_x_preferred":[
        "Kampung Lerek"
    ],
    "name:und_x_variant":[
        "Kampong Lerek"
    ],
    "wof:name":"Kampung Lerek",
    "wof:placetype":"locality"
},
  "geometry": {"coordinates":[103.05249999999999,5.3462],"type":"Point"}
}