{
  "type": "Feature",
  "properties": {
    "gn:admin1_code":"6",
    "gn:asciiname":"Kampung Hulu Temau",
    "gn:country_code":"MY",
    "gn:dem":125,
    "gn:feature_class":"P",
    "gn:feature_code":"PPL",
    "gn:name":"Kampung Hulu Temau",
    "gn:population":0,
    "gn:timezone":"Asia/Kuala_Lumpur",
    "iso:country":"MY",
    "name:msa_x_preferred":[
        "Kampung Hulu Temau"
    ],
    "name:und_x_variant":[
        "Kampong Ulu Temau"
    ],
    "wof:name":"Kampung Hulu Temau",
    "wof:placetype":"locality"
},
  "geometry": {"coordinates":[101.9344,3.9309],"type":"Point"}
}