{
  "type": "Feature",
  "properties": {
    "gn:admin1_code":"3.0",
    "gn:asciiname":"Kampung Buluh Galah",
    "gn:cc2":"MY",
    "gn:country_code":"MY",
    "gn:dem":71,
    "gn:feature_class":"P",
    "gn:feature_code":"PPL",
    "gn:name":"Kampung Buluh Galah",
    "gn:population":0,
    "gn:timezone":"Asia/Kuala_Lumpur",
    "iso:country":"MY",
    "name:und_x_variant":[
        "Kampong Buloh Galah",
        "Kampung Buluh Galah"
    ],
    "wof:name":"Kampung Buluh Galah",
    "wof:placetype":"locality"
},
  "geometry": {"coordinates":[101.86667,5.66667],"type":"Point"}
}