{
  "type": "Feature",
  "properties": {
    "gn:admin1_code":"1",
    "gn:asciiname":"Kampung Jakon",
    "gn:country_code":"MY",
    "gn:dem":13,
    "gn:feature_class":"P",
    "gn:feature_code":"PPL",
    "gn:name":"Kampung Jakon",
    "gn:population":0,
    "gn:timezone":"Asia/Kuala_Lumpur",
    "iso:country":"MY",
    "name:msa_x_preferred":[
        "Kampung Jakon"
    ],
    "name:und_x_variant":[
        "Kampong Jakon"
    ],
    "wof:name":"Kampung Jakon",
    "wof:placetype":"locality"
},
  "geometry": {"coordinates":[103.4551,1.3697],"type":"Point"}
}