{
  "type": "Feature",
  "properties": {
    "gn:country":"MY",
    "iso:country":"MY",
    "qs:name":"Mukim H Sungai Burung",
    "qs:name_adm0":"Malaysia",
    "qs:name_adm1":"Pulau Pinang",
    "qs:photos":3,
    "qs:photos_1k":1,
    "qs:photos_9k":1,
    "qs:photos_9r":2,
    "qs:photos_all":28,
    "qs:photos_sr":1,
    "qs:placetype":"LocalAdmin",
    "qs:pop_sr":"0",
    "wof:name":"Mukim H Sungai Burung",
    "wof:placetype":"localadmin"
},
  "geometry": {"coordinates":[100.19522600000001,5.338886],"type":"Point"}
}