{
  "type": "Feature",
  "properties": {
    "gn:admin1_code":"16",
    "gn:asciiname":"Kampung Menampilik",
    "gn:country_code":"MY",
    "gn:dem":-9999,
    "gn:feature_class":"P",
    "gn:feature_code":"PPL",
    "gn:name":"Kampung Menampilik",
    "gn:population":0,
    "gn:timezone":"Asia/Kuching",
    "iso:country":"MY",
    "name:und_x_variant":[
        "Kampong Menampilek",
        "Kampung Menampilik"
    ],
    "wof:name":"Kampung Menampilik",
    "wof:placetype":"locality"
},
  "geometry": {"coordinates":[118.57289,4.34569],"type":"Point"}
}