{
  "type": "Feature",
  "properties": {
    "gn:admin1_code":"8",
    "gn:asciiname":"Kampung Jejawi Hutan Buloh",
    "gn:cc2":"MY",
    "gn:country_code":"MY",
    "gn:dem":9,
    "gn:feature_class":"P",
    "gn:feature_code":"PPL",
    "gn:name":"Kampung Jejawi Hutan Buloh",
    "gn:population":0,
    "gn:timezone":"Asia/Kuala_Lumpur",
    "iso:country":"MY",
    "name:msa_x_preferred":[
        "Kampung Jejawi Hutan Buloh"
    ],
    "name:und_x_variant":[
        "Hutan Buloh"
    ],
    "wof:name":"Kampung Jejawi Hutan Buloh",
    "wof:placetype":"locality"
},
  "geometry": {"coordinates":[100.24097999999999,6.46032],"type":"Point"}
}