{
  "type": "Feature",
  "properties": {
    "gn:admin1_code":"16.0",
    "gn:asciiname":"Kampung Berabangan",
    "gn:country_code":"MY",
    "gn:dem":8,
    "gn:feature_class":"P",
    "gn:feature_code":"PPL",
    "gn:name":"Kampung Berabangan",
    "gn:population":0,
    "gn:timezone":"Asia/Kuching",
    "iso:country":"MY",
    "name:msa_x_preferred":[
        "Kampung Berabangan"
    ],
    "wof:name":"Kampung Berabangan",
    "wof:placetype":"locality"
},
  "geometry": {"coordinates":[115.765,5.4851],"type":"Point"}
}