{
  "type": "Feature",
  "properties": {
    "gn:admin1_code":"0",
    "gn:asciiname":"Kampong Perbahan",
    "gn:country_code":"MY",
    "gn:dem":35,
    "gn:feature_class":"P",
    "gn:feature_code":"PPL",
    "gn:name":"Kampong Perbahan",
    "gn:population":0,
    "gn:timezone":"Asia/Kuala_Lumpur",
    "iso:country":"MY",
    "wof:name":"Kampong Perbahan",
    "wof:placetype":"locality"
},
  "geometry": {"coordinates":[101.41667,3.38333],"type":"Point"}
}