{
  "type": "Feature",
  "properties": {
    "gn:admin1_code":"11",
    "gn:asciiname":"Rumah Lagan",
    "gn:cc2":"MY",
    "gn:country_code":"MY",
    "gn:dem":44,
    "gn:feature_class":"P",
    "gn:feature_code":"PPL",
    "gn:name":"Rumah Lagan",
    "gn:population":0,
    "gn:timezone":"Asia/Kuching",
    "iso:country":"MY",
    "name:und_x_variant":[
        "Rumah Legan",
        "Rumah Lagan"
    ],
    "wof:name":"Rumah Lagan",
    "wof:placetype":"locality"
},
  "geometry": {"coordinates":[113.78333000000001,3.73333],"type":"Point"}
}