{
  "type": "Feature",
  "properties": {
    "gn:admin1_code":"0.0",
    "gn:asciiname":"Takul",
    "gn:country_code":"MY",
    "gn:dem":461,
    "gn:feature_class":"P",
    "gn:feature_code":"PPL",
    "gn:name":"Takul",
    "gn:population":0,
    "gn:timezone":"Asia/Kuching",
    "iso:country":"MY",
    "wof:name":"Takul",
    "wof:placetype":"locality"
},
  "geometry": {"coordinates":[116.46666999999999,4.98333],"type":"Point"}
}