{
  "type": "Feature",
  "properties": {
    "gn:admin1_code":"0",
    "gn:asciiname":"Kampong Haji Mohamad Sariff",
    "gn:country_code":"MY",
    "gn:dem":81,
    "gn:feature_class":"P",
    "gn:feature_code":"PPL",
    "gn:name":"Kampong Haji Mohamad Sariff",
    "gn:population":0,
    "gn:timezone":"Asia/Kuala_Lumpur",
    "iso:country":"MY",
    "wof:name":"Kampong Haji Mohamad Sariff",
    "wof:placetype":"locality"
},
  "geometry": {"coordinates":[101.48333,3.15],"type":"Point"}
}