{
  "type": "Feature",
  "properties": {
    "gn:country":"MY",
    "gn:fcode":"PPL",
    "gn:population":0,
    "iso:country":"MY",
    "name:eng_x_preferred":[
        "Pengkalan Kubur"
    ],
    "name:epo_x_preferred":[
        "Pengkalan Kubur"
    ],
    "name:msa_x_preferred":[
        "Kampung Pengkalan Kubur"
    ],
    "name:msa_x_variant":[
        "Pengkalan Kubor"
    ],
    "name:nld_x_preferred":[
        "Pengkalan Kubur"
    ],
    "name:zho_x_preferred":[
        "\u5f6d\u52a0\u5170\u53e4\u5821"
    ],
    "qs:name":"Kampung Pengkalan Kubur",
    "qs:name_adm0":"Malaysia",
    "qs:name_adm1":"Kelantan",
    "qs:photos":6,
    "qs:photos_1k":1,
    "qs:photos_9k":1,
    "qs:photos_9r":1,
    "qs:photos_all":6,
    "qs:photos_sr":1,
    "qs:placetype":"Town",
    "qs:pop_sr":"0",
    "wof:name":"Kampung Pengkalan Kubur",
    "wof:placetype":"locality",
    "wof:population":0
},
  "geometry": {"coordinates":[102.09464,6.23215],"type":"Point"}
}