{
  "type": "Feature",
  "properties": {
    "gn:admin1_code":"3",
    "gn:asciiname":"Kampung Hantu",
    "gn:country_code":"MY",
    "gn:dem":112,
    "gn:feature_class":"P",
    "gn:feature_code":"PPL",
    "gn:name":"Kampung Hantu",
    "gn:population":0,
    "gn:timezone":"Asia/Kuala_Lumpur",
    "iso:country":"MY",
    "name:und_x_variant":[
        "Kampong Hantu"
    ],
    "wof:name":"Kampung Hantu",
    "wof:placetype":"locality"
},
  "geometry": {"coordinates":[102.29716999999999,4.78619],"type":"Point"}
}