{
  "type": "Feature",
  "properties": {
    "gn:admin1_code":"7.0",
    "gn:asciiname":"Medan Desa Perpaduan",
    "gn:country_code":"MY",
    "gn:dem":65,
    "gn:feature_class":"P",
    "gn:feature_code":"PPL",
    "gn:name":"Medan Desa Perpaduan",
    "gn:population":0,
    "gn:timezone":"Asia/Kuala_Lumpur",
    "iso:country":"MY",
    "name:msa_x_preferred":[
        "Medan Desa Perpaduan"
    ],
    "wof:name":"Medan Desa Perpaduan",
    "wof:placetype":"locality"
},
  "geometry": {"coordinates":[101.14279999999999,4.6504],"type":"Point"}
}