{
  "type": "Feature",
  "properties": {
    "gn:admin1_code":"1.0",
    "gn:asciiname":"Kampung Parit Kadir Darat",
    "gn:country_code":"MY",
    "gn:dem":9,
    "gn:feature_class":"P",
    "gn:feature_code":"PPL",
    "gn:name":"Kampung Parit Kadir Darat",
    "gn:population":0,
    "gn:timezone":"Asia/Kuala_Lumpur",
    "iso:country":"MY",
    "name:msa_x_preferred":[
        "Kampung Parit Kadir Darat"
    ],
    "wof:name":"Kampung Parit Kadir Darat",
    "wof:placetype":"locality"
},
  "geometry": {"coordinates":[102.6414,2.0825],"type":"Point"}
}