{
  "type": "Feature",
  "properties": {
    "gn:admin1_code":"5",
    "gn:asciiname":"Kampung Parit Tengah",
    "gn:country_code":"MY",
    "gn:dem":127,
    "gn:feature_class":"P",
    "gn:feature_code":"PPL",
    "gn:name":"Kampung Parit Tengah",
    "gn:population":0,
    "gn:timezone":"Asia/Kuala_Lumpur",
    "iso:country":"MY",
    "name:msa_x_preferred":[
        "Kampung Parit Tengah"
    ],
    "name:und_x_variant":[
        "Kampong Parit Tengah"
    ],
    "wof:name":"Kampung Parit Tengah",
    "wof:placetype":"locality"
},
  "geometry": {"coordinates":[102.1465,2.7337],"type":"Point"}
}