{
  "type": "Feature",
  "properties": {
    "gn:admin1_code":"7.0",
    "gn:asciiname":"Taman Orkid",
    "gn:country_code":"MY",
    "gn:dem":14,
    "gn:feature_class":"P",
    "gn:feature_code":"PPL",
    "gn:name":"Taman Orkid",
    "gn:population":0,
    "gn:timezone":"Asia/Kuala_Lumpur",
    "iso:country":"MY",
    "name:msa_x_preferred":[
        "Taman Orkid"
    ],
    "wof:name":"Taman Orkid",
    "wof:placetype":"locality"
},
  "geometry": {"coordinates":[101.16719999999999,3.9998],"type":"Point"}
}