{
  "type": "Feature",
  "properties": {
    "gn:admin1_code":"13",
    "gn:asciiname":"Kampung Telaga",
    "gn:country_code":"MY",
    "gn:dem":17,
    "gn:feature_class":"P",
    "gn:feature_code":"PPL",
    "gn:name":"Kampung Telaga",
    "gn:population":0,
    "gn:timezone":"Asia/Kuala_Lumpur",
    "iso:country":"MY",
    "name:msa_x_preferred":[
        "Kampung Telaga"
    ],
    "name:und_x_variant":[
        "Kampong Telaga"
    ],
    "wof:name":"Kampung Telaga",
    "wof:placetype":"locality"
},
  "geometry": {"coordinates":[103.00020000000001,5.0898],"type":"Point"}
}