{
  "type": "Feature",
  "properties": {
    "gn:admin1_code":"6",
    "gn:asciiname":"Kampung Sungai La",
    "gn:country_code":"MY",
    "gn:dem":116,
    "gn:feature_class":"P",
    "gn:feature_code":"PPL",
    "gn:name":"Kampung Sungai La",
    "gn:population":0,
    "gn:timezone":"Asia/Kuala_Lumpur",
    "iso:country":"MY",
    "name:msa_x_preferred":[
        "Kampung Sungai La"
    ],
    "name:und_x_variant":[
        "Kampong Sungei La",
        "Kampong Sungai Lar"
    ],
    "wof:name":"Kampung Sungai La",
    "wof:placetype":"locality"
},
  "geometry": {"coordinates":[101.8946,3.9039],"type":"Point"}
}