{
  "type": "Feature",
  "properties": {
    "gn:admin1_code":"4.0",
    "gn:asciiname":"Kampung Terentang",
    "gn:country_code":"MY",
    "gn:dem":106,
    "gn:feature_class":"P",
    "gn:feature_code":"PPL",
    "gn:name":"Kampung Terentang",
    "gn:population":0,
    "gn:timezone":"Asia/Kuala_Lumpur",
    "iso:country":"MY",
    "name:msa_x_preferred":[
        "Kampung Terentang"
    ],
    "wof:name":"Kampung Terentang",
    "wof:placetype":"locality"
},
  "geometry": {"coordinates":[102.41719999999999,2.4356],"type":"Point"}
}