{
  "type": "Feature",
  "properties": {
    "gn:admin1_code":"3.0",
    "gn:asciiname":"Kemajuan Tanah Paloh Satu",
    "gn:country_code":"MY",
    "gn:dem":128,
    "gn:feature_class":"P",
    "gn:feature_code":"PPL",
    "gn:name":"Kemajuan Tanah Paloh Satu",
    "gn:population":0,
    "gn:timezone":"Asia/Kuala_Lumpur",
    "iso:country":"MY",
    "name:msa_x_preferred":[
        "Kemajuan Tanah Paloh Satu"
    ],
    "wof:name":"Kemajuan Tanah Paloh Satu",
    "wof:placetype":"locality"
},
  "geometry": {"coordinates":[102.23269999999999,5.0128],"type":"Point"}
}