{
  "type": "Feature",
  "properties": {
    "gn:admin1_code":"1.0",
    "gn:asciiname":"Calet Pulau Besar Hujong",
    "gn:country_code":"MY",
    "gn:dem":31,
    "gn:feature_class":"P",
    "gn:feature_code":"PPL",
    "gn:name":"Calet Pulau Besar Hujong",
    "gn:population":0,
    "gn:timezone":"Asia/Kuala_Lumpur",
    "iso:country":"MY",
    "name:msa_x_preferred":[
        "Calet Pulau Besar Hujong"
    ],
    "wof:name":"Calet Pulau Besar Hujong",
    "wof:placetype":"locality"
},
  "geometry": {"coordinates":[103.95058,2.48977],"type":"Point"}
}