{
  "type": "Feature",
  "properties": {
    "gn:admin1_code":"3",
    "gn:asciiname":"Kampong Kalai Baharu",
    "gn:country_code":"MY",
    "gn:dem":116,
    "gn:feature_class":"P",
    "gn:feature_code":"PPL",
    "gn:name":"Kampong Kalai Baharu",
    "gn:population":0,
    "gn:timezone":"Asia/Kuala_Lumpur",
    "iso:country":"MY",
    "wof:name":"Kampong Kalai Baharu",
    "wof:placetype":"locality"
},
  "geometry": {"coordinates":[101.74059,5.75188],"type":"Point"}
}