{
  "type": "Feature",
  "properties": {
    "gn:admin1_code":"16.0",
    "gn:asciiname":"Matopang",
    "gn:cc2":"MY",
    "gn:country_code":"MY",
    "gn:dem":214,
    "gn:feature_class":"P",
    "gn:feature_code":"PPL",
    "gn:name":"Matopang",
    "gn:population":0,
    "gn:timezone":"Asia/Kuching",
    "iso:country":"MY",
    "name:und_x_variant":[
        "Kampong Matopang",
        "Matopang"
    ],
    "wof:name":"Matopang",
    "wof:placetype":"locality"
},
  "geometry": {"coordinates":[116.95,5.71667],"type":"Point"}
}