{
  "type": "Feature",
  "properties": {
    "gn:admin1_code":"11.0",
    "gn:asciiname":"Busang Tijok",
    "gn:country_code":"MY",
    "gn:dem":42,
    "gn:feature_class":"P",
    "gn:feature_code":"PPL",
    "gn:name":"Busang Tijok",
    "gn:population":0,
    "gn:timezone":"Asia/Kuching",
    "iso:country":"MY",
    "name:msa_x_preferred":[
        "Busang Tijok"
    ],
    "name:und_x_variant":[
        "Busang Tejo",
        "Busang Tuyo"
    ],
    "wof:name":"Busang Tijok",
    "wof:placetype":"locality"
},
  "geometry": {"coordinates":[114.42789999999999,3.4848],"type":"Point"}
}