{
  "type": "Feature",
  "properties": {
    "gn:admin1_code":"5.0",
    "gn:asciiname":"Taman Dato Haji Abdul Samad",
    "gn:country_code":"MY",
    "gn:dem":16,
    "gn:feature_class":"P",
    "gn:feature_code":"PPL",
    "gn:name":"Taman Dato Haji Abdul Samad",
    "gn:population":0,
    "gn:timezone":"Asia/Kuala_Lumpur",
    "iso:country":"MY",
    "name:msa_x_preferred":[
        "Taman Dato Haji Abdul Samad"
    ],
    "wof:name":"Taman Dato Haji Abdul Samad",
    "wof:placetype":"locality"
},
  "geometry": {"coordinates":[101.8369,2.5096],"type":"Point"}
}