{
  "type": "Feature",
  "properties": {
    "gn:admin1_code":"2.0",
    "gn:asciiname":"Taman Anggerik",
    "gn:country_code":"MY",
    "gn:dem":28,
    "gn:feature_class":"P",
    "gn:feature_code":"PPL",
    "gn:name":"Taman Anggerik",
    "gn:population":0,
    "gn:timezone":"Asia/Kuala_Lumpur",
    "iso:country":"MY",
    "name:msa_x_preferred":[
        "Taman Anggerik"
    ],
    "wof:name":"Taman Anggerik",
    "wof:placetype":"locality"
},
  "geometry": {"coordinates":[100.53538,5.34666],"type":"Point"}
}