{
  "type": "Feature",
  "properties": {
    "gn:admin1_code":"13",
    "gn:asciiname":"Kampung Tiruk",
    "gn:country_code":"MY",
    "gn:dem":19,
    "gn:feature_class":"P",
    "gn:feature_code":"PPL",
    "gn:name":"Kampung Tiruk",
    "gn:population":0,
    "gn:timezone":"Asia/Kuala_Lumpur",
    "iso:country":"MY",
    "name:msa_x_preferred":[
        "Kampung Tiruk"
    ],
    "name:und_x_variant":[
        "Kampong Tirok"
    ],
    "wof:name":"Kampung Tiruk",
    "wof:placetype":"locality"
},
  "geometry": {"coordinates":[103.0402,5.2271],"type":"Point"}
}