{
  "type": "Feature",
  "properties": {
    "gn:admin1_code":"6",
    "gn:asciiname":"Kampung Pancur",
    "gn:country_code":"MY",
    "gn:dem":34,
    "gn:feature_class":"P",
    "gn:feature_code":"PPL",
    "gn:name":"Kampung Pancur",
    "gn:population":0,
    "gn:timezone":"Asia/Kuala_Lumpur",
    "iso:country":"MY",
    "name:und_x_variant":[
        "Kampong Panchor"
    ],
    "wof:name":"Kampung Pancur",
    "wof:placetype":"locality"
},
  "geometry": {"coordinates":[102.94194,3.05397],"type":"Point"}
}