{
  "type": "Feature",
  "properties": {
    "gn:admin1_code":"16.0",
    "gn:asciiname":"Kampung Mogis",
    "gn:country_code":"MY",
    "gn:dem":371,
    "gn:feature_class":"P",
    "gn:feature_code":"PPL",
    "gn:name":"Kampung Mogis",
    "gn:population":0,
    "gn:timezone":"Asia/Kuching",
    "iso:country":"MY",
    "name:msa_x_preferred":[
        "Kampung Mogis"
    ],
    "wof:name":"Kampung Mogis",
    "wof:placetype":"locality"
},
  "geometry": {"coordinates":[116.79300000000001,6.2732],"type":"Point"}
}