{
  "type": "Feature",
  "properties": {
    "gn:admin1_code":"1",
    "gn:asciiname":"Kampung Guntong",
    "gn:country_code":"MY",
    "gn:dem":25,
    "gn:feature_class":"P",
    "gn:feature_code":"PPL",
    "gn:name":"Kampung Guntong",
    "gn:population":0,
    "gn:timezone":"Asia/Kuala_Lumpur",
    "iso:country":"MY",
    "name:msa_x_preferred":[
        "Kampung Guntong"
    ],
    "name:und_x_variant":[
        "Kampong Guntong"
    ],
    "wof:name":"Kampung Guntong",
    "wof:placetype":"locality"
},
  "geometry": {"coordinates":[102.81619999999999,2.5489],"type":"Point"}
}