{
  "type": "Feature",
  "properties": {
    "gn:admin1_code":"8.0",
    "gn:asciiname":"Kampung Telok Kachang",
    "gn:country_code":"MY",
    "gn:dem":7,
    "gn:feature_class":"P",
    "gn:feature_code":"PPL",
    "gn:name":"Kampung Telok Kachang",
    "gn:population":0,
    "gn:timezone":"Asia/Kuala_Lumpur",
    "iso:country":"MY",
    "name:msa_x_preferred":[
        "Kampung Telok Kachang"
    ],
    "wof:name":"Kampung Telok Kachang",
    "wof:placetype":"locality"
},
  "geometry": {"coordinates":[100.17789999999999,6.43936],"type":"Point"}
}