{
  "type": "Feature",
  "properties": {
    "gn:admin1_code":"6",
    "gn:asciiname":"Kampung Batu Gajah",
    "gn:country_code":"MY",
    "gn:dem":20,
    "gn:feature_class":"P",
    "gn:feature_code":"PPL",
    "gn:name":"Kampung Batu Gajah",
    "gn:population":0,
    "gn:timezone":"Asia/Kuala_Lumpur",
    "iso:country":"MY",
    "name:und_x_variant":[
        "Kampong Batu Gajah"
    ],
    "wof:name":"Kampung Batu Gajah",
    "wof:placetype":"locality"
},
  "geometry": {"coordinates":[103.07078,3.55813],"type":"Point"}
}