{
  "type": "Feature",
  "properties": {
    "gn:admin1_code":"1.0",
    "gn:asciiname":"Kemajuan Tanah Chemplak Barat",
    "gn:country_code":"MY",
    "gn:dem":47,
    "gn:feature_class":"P",
    "gn:feature_code":"PPL",
    "gn:name":"Kemajuan Tanah Chemplak Barat",
    "gn:population":0,
    "gn:timezone":"Asia/Kuala_Lumpur",
    "iso:country":"MY",
    "name:msa_x_preferred":[
        "Kemajuan Tanah Chemplak Barat"
    ],
    "wof:name":"Kemajuan Tanah Chemplak Barat",
    "wof:placetype":"locality"
},
  "geometry": {"coordinates":[102.934,2.388],"type":"Point"}
}