{
  "type": "Feature",
  "properties": {
    "gn:admin1_code":"7.0",
    "gn:asciiname":"Taman Rasi Kuala Kuang",
    "gn:country_code":"MY",
    "gn:dem":71,
    "gn:feature_class":"P",
    "gn:feature_code":"PPL",
    "gn:name":"Taman Rasi Kuala Kuang",
    "gn:population":0,
    "gn:timezone":"Asia/Kuala_Lumpur",
    "iso:country":"MY",
    "name:msa_x_preferred":[
        "Taman Rasi Kuala Kuang"
    ],
    "wof:name":"Taman Rasi Kuala Kuang",
    "wof:placetype":"locality"
},
  "geometry": {"coordinates":[101.1118,4.7067],"type":"Point"}
}