{
  "type": "Feature",
  "properties": {
    "gn:admin1_code":"11",
    "gn:asciiname":"Kampong Perin",
    "gn:cc2":"MY",
    "gn:country_code":"MY",
    "gn:dem":9,
    "gn:feature_class":"P",
    "gn:feature_code":"PPL",
    "gn:name":"Kampong Perin",
    "gn:population":0,
    "gn:timezone":"Asia/Kuching",
    "iso:country":"MY",
    "name:und_x_variant":[
        "Kampong Prin",
        "Kampong Perin"
    ],
    "wof:name":"Kampong Perin",
    "wof:placetype":"locality"
},
  "geometry": {"coordinates":[110.66667,1.43333],"type":"Point"}
}