{
  "type": "Feature",
  "properties": {
    "gn:admin1_code":"6",
    "gn:asciiname":"Kampung Samak",
    "gn:country_code":"MY",
    "gn:dem":34,
    "gn:feature_class":"P",
    "gn:feature_code":"PPL",
    "gn:name":"Kampung Samak",
    "gn:population":0,
    "gn:timezone":"Asia/Kuala_Lumpur",
    "iso:country":"MY",
    "name:msa_x_preferred":[
        "Kampung Samak"
    ],
    "name:und_x_variant":[
        "Kampong Samak"
    ],
    "wof:name":"Kampung Samak",
    "wof:placetype":"locality"
},
  "geometry": {"coordinates":[102.9323,3.0259],"type":"Point"}
}