{
  "type": "Feature",
  "properties": {
    "gn:admin1_code":"6.0",
    "gn:asciiname":"Kampung Cerus",
    "gn:country_code":"MY",
    "gn:dem":413,
    "gn:feature_class":"P",
    "gn:feature_code":"PPL",
    "gn:name":"Kampung Cerus",
    "gn:population":0,
    "gn:timezone":"Asia/Kuala_Lumpur",
    "iso:country":"MY",
    "name:msa_x_preferred":[
        "Kampung Cerus"
    ],
    "wof:name":"Kampung Cerus",
    "wof:placetype":"locality"
},
  "geometry": {"coordinates":[101.5967,4.4146],"type":"Point"}
}