{
  "type": "Feature",
  "properties": {
    "gn:admin1_code":"16",
    "gn:asciiname":"Kampung Papason",
    "gn:country_code":"MY",
    "gn:dem":27,
    "gn:feature_class":"P",
    "gn:feature_code":"PPL",
    "gn:name":"Kampung Papason",
    "gn:population":0,
    "gn:timezone":"Asia/Kuching",
    "iso:country":"MY",
    "name:msa_x_preferred":[
        "Kampung Papason"
    ],
    "name:und_x_variant":[
        "Kampong Papason"
    ],
    "wof:name":"Kampung Papason",
    "wof:placetype":"locality"
},
  "geometry": {"coordinates":[116.0608,5.8826],"type":"Point"}
}