{
  "type": "Feature",
  "properties": {
    "gn:admin1_code":"3",
    "gn:asciiname":"Kampong Gelam",
    "gn:cc2":"MY",
    "gn:country_code":"MY",
    "gn:dem":20,
    "gn:feature_class":"P",
    "gn:feature_code":"PPL",
    "gn:name":"Kampong Gelam",
    "gn:population":0,
    "gn:timezone":"Asia/Kuala_Lumpur",
    "iso:country":"MY",
    "name:und_x_variant":[
        "Kampong Glam",
        "Kampong Gelam"
    ],
    "wof:name":"Kampong Gelam",
    "wof:placetype":"locality"
},
  "geometry": {"coordinates":[102.16667,5.98333],"type":"Point"}
}