{
  "type": "Feature",
  "properties": {
    "gn:admin1_code":"1.0",
    "gn:asciiname":"Kampung Pengkalan Kota",
    "gn:country_code":"MY",
    "gn:dem":17,
    "gn:feature_class":"P",
    "gn:feature_code":"PPL",
    "gn:name":"Kampung Pengkalan Kota",
    "gn:population":0,
    "gn:timezone":"Asia/Kuala_Lumpur",
    "iso:country":"MY",
    "name:msa_x_preferred":[
        "Kampung Pengkalan Kota"
    ],
    "wof:name":"Kampung Pengkalan Kota",
    "wof:placetype":"locality"
},
  "geometry": {"coordinates":[102.8052,2.3402],"type":"Point"}
}