{
  "type": "Feature",
  "properties": {
    "gn:admin1_code":"16",
    "gn:asciiname":"Kampong Nontun",
    "gn:country_code":"MY",
    "gn:dem":776,
    "gn:feature_class":"P",
    "gn:feature_code":"PPL",
    "gn:name":"Kampong Nontun",
    "gn:population":0,
    "gn:timezone":"Asia/Kuching",
    "iso:country":"MY",
    "name:msa_x_preferred":[
        "Kampong Nontun"
    ],
    "name:und_x_variant":[
        "Kampong Nuntun"
    ],
    "wof:name":"Kampong Nontun",
    "wof:placetype":"locality"
},
  "geometry": {"coordinates":[116.3623,5.8749],"type":"Point"}
}