{
  "type": "Feature",
  "properties": {
    "gn:admin1_code":"16",
    "gn:asciiname":"Katutar",
    "gn:country_code":"MY",
    "gn:dem":230,
    "gn:feature_class":"P",
    "gn:feature_code":"PPL",
    "gn:name":"Katutar",
    "gn:population":0,
    "gn:timezone":"Asia/Kuching",
    "iso:country":"MY",
    "wof:name":"Katutar",
    "wof:placetype":"locality"
},
  "geometry": {"coordinates":[116.59999999999999,4.46667],"type":"Point"}
}