{
  "type": "Feature",
  "properties": {
    "gn:admin1_code":"8.0",
    "gn:asciiname":"Kampung Kubang Tiga",
    "gn:cc2":"MY",
    "gn:country_code":"MY",
    "gn:dem":38,
    "gn:feature_class":"P",
    "gn:feature_code":"PPL",
    "gn:name":"Kampung Kubang Tiga",
    "gn:population":0,
    "gn:timezone":"Asia/Kuala_Lumpur",
    "iso:country":"MY",
    "name:msa_x_preferred":[
        "Kampung Kubang Tiga"
    ],
    "name:und_x_variant":[
        "Kampong Kubang Tiga",
        "Kubang Tiga"
    ],
    "wof:name":"Kampung Kubang Tiga",
    "wof:placetype":"locality"
},
  "geometry": {"coordinates":[100.27529,6.56993],"type":"Point"}
}