{
  "type": "Feature",
  "properties": {
    "gn:country":"MY",
    "gn:fcode":"PPL",
    "gn:pop":0,
    "iso:country":"MY",
    "name:ceb_x_preferred":[
        "Setiu"
    ],
    "name:ind_x_preferred":[
        "Setiu"
    ],
    "name:msa_x_preferred":[
        "Guntong"
    ],
    "name:msa_x_variant":[
        "Setiu"
    ],
    "name:nld_x_preferred":[
        "Setiu"
    ],
    "name:urd_x_preferred":[
        "\u0636\u0644\u0639 \u0633\u062a\u06cc\u0648"
    ],
    "name:vie_x_preferred":[
        "Setiu"
    ],
    "name:zho_x_preferred":[
        "\u58eb\u5146\u53bf"
    ],
    "qs:name":"Guntung",
    "qs:name_adm0":"Malaysia",
    "qs:name_adm1":"Perak",
    "qs:photos":13,
    "qs:photos_1k":3,
    "qs:photos_9k":1,
    "qs:photos_9r":1,
    "qs:photos_all":13,
    "qs:photos_sr":1,
    "qs:placetype":"Suburb",
    "qs:pop_sr":"0",
    "wd:wordcount":85,
    "wof:name":"Guntung",
    "wof:placetype":"neighbourhood",
    "wof:population":0
},
  "geometry": {"coordinates":[101.05419999999999,4.5964],"type":"Point"}
}