{
  "type": "Feature",
  "properties": {
    "gn:admin1_code":"1.0",
    "gn:asciiname":"Kampung Sungai Sayong",
    "gn:country_code":"MY",
    "gn:dem":72,
    "gn:feature_class":"P",
    "gn:feature_code":"PPL",
    "gn:name":"Kampung Sungai Sayong",
    "gn:population":0,
    "gn:timezone":"Asia/Kuala_Lumpur",
    "iso:country":"MY",
    "name:msa_x_preferred":[
        "Kampung Sungai Sayong"
    ],
    "name:und_x_variant":[
        "Kampong Sungai Sayong",
        "Sungai Sayong Village",
        "Sungai Sayung"
    ],
    "wof:name":"Kampung Sungai Sayong",
    "wof:placetype":"locality"
},
  "geometry": {"coordinates":[103.3734,1.9221],"type":"Point"}
}