{
  "type": "Feature",
  "properties": {
    "gn:admin1_code":"11.0",
    "gn:asciiname":"Batu Danau",
    "gn:cc2":"MY",
    "gn:country_code":"MY",
    "gn:dem":19,
    "gn:feature_class":"P",
    "gn:feature_code":"PPL",
    "gn:name":"Batu Danau",
    "gn:population":0,
    "gn:timezone":"Asia/Kuching",
    "iso:country":"MY",
    "name:und_x_variant":[
        "Kampong Batu Danau",
        "Batu Danau"
    ],
    "wof:name":"Batu Danau",
    "wof:placetype":"locality"
},
  "geometry": {"coordinates":[114.83333,4.65],"type":"Point"}
}