{
  "type": "Feature",
  "properties": {
    "gn:admin1_code":"16",
    "gn:asciiname":"Kampung Mapila",
    "gn:country_code":"MY",
    "gn:dem":372,
    "gn:feature_class":"P",
    "gn:feature_code":"PPL",
    "gn:name":"Kampung Mapila",
    "gn:population":0,
    "gn:timezone":"Asia/Kuching",
    "iso:country":"MY",
    "name:msa_x_preferred":[
        "Kampung Mapila"
    ],
    "name:und_x_variant":[
        "Mapila"
    ],
    "wof:name":"Kampung Mapila",
    "wof:placetype":"locality"
},
  "geometry": {"coordinates":[116.25920000000001,5.1684],"type":"Point"}
}