{
  "type": "Feature",
  "properties": {
    "gn:admin1_code":"16",
    "gn:asciiname":"Kampung Tagad",
    "gn:country_code":"MY",
    "gn:dem":22,
    "gn:feature_class":"P",
    "gn:feature_code":"PPL",
    "gn:name":"Kampung Tagad",
    "gn:population":0,
    "gn:timezone":"Asia/Kuching",
    "iso:country":"MY",
    "name:und_x_variant":[
        "Kampong Togob"
    ],
    "wof:name":"Kampung Tagad",
    "wof:placetype":"locality"
},
  "geometry": {"coordinates":[116.09193999999999,5.88796],"type":"Point"}
}