{
  "type": "Feature",
  "properties": {
    "gn:gn_country":"MY",
    "gn:gn_fcode":"ADM3",
    "gn:gn_pop":0,
    "iso:country":"MY",
    "qs_pg:aaroncc":"MY",
    "qs_pg:gn_country":"MY",
    "qs_pg:gn_fcode":"ADM3",
    "qs_pg:gn_pop":0,
    "qs_pg:name":"Kota Marudu",
    "qs_pg:photos_9r":0,
    "qs_pg:photos_sr":0,
    "qs_pg:pop_sr":0,
    "qs_pg:qs_pg_placetype":"localadmin",
    "wof:name":"Kota Marudu",
    "wof:placetype":"localadmin"
},
  "geometry": {"coordinates":[116.75,6.41667],"type":"Point"}
}