{
  "type": "Feature",
  "properties": {
    "gn:country":"MY",
    "gn:fcode":"PPL",
    "gn:pop":0,
    "iso:country":"MY",
    "name:msa_x_preferred":[
        "Kampung Kuala Tekai"
    ],
    "qs:name":"Kampung Kuala Teriang",
    "qs:name_adm0":"Malaysia",
    "qs:name_adm1":"Kedah",
    "qs:photos":188,
    "qs:photos_1k":38,
    "qs:photos_9k":1,
    "qs:photos_9r":4,
    "qs:photos_all":188,
    "qs:photos_sr":4,
    "qs:placetype":"Town",
    "qs:pop_sr":"0",
    "wof:name":"Kampung Kuala Teriang",
    "wof:placetype":"locality",
    "wof:population":0
},
  "geometry": {"coordinates":[100.65734999999999,6.22471],"type":"Point"}
}