{
  "type": "Feature",
  "properties": {
    "gn:admin1_code":"16.0",
    "gn:asciiname":"Kampong Karudon",
    "gn:country_code":"MY",
    "gn:dem":18,
    "gn:feature_class":"P",
    "gn:feature_code":"PPL",
    "gn:name":"Kampong Karudon",
    "gn:population":0,
    "gn:timezone":"Asia/Kuching",
    "iso:country":"MY",
    "wof:name":"Kampong Karudon",
    "wof:placetype":"locality"
},
  "geometry": {"coordinates":[117.53735,6.27543],"type":"Point"}
}