{
  "type": "Feature",
  "properties": {
    "gn:admin1_code":"16",
    "gn:asciiname":"Kampung Masak",
    "gn:country_code":"MY",
    "gn:dem":304,
    "gn:feature_class":"P",
    "gn:feature_code":"PPL",
    "gn:name":"Kampung Masak",
    "gn:population":0,
    "gn:timezone":"Asia/Kuching",
    "iso:country":"MY",
    "name:msa_x_preferred":[
        "Kampung Masak"
    ],
    "name:und_x_variant":[
        "Masak"
    ],
    "wof:name":"Kampung Masak",
    "wof:placetype":"locality"
},
  "geometry": {"coordinates":[116.1454,5.3423],"type":"Point"}
}