{
  "type": "Feature",
  "properties": {
    "gn:admin1_code":"5.0",
    "gn:asciiname":"Kampung Ampang Kasai",
    "gn:country_code":"MY",
    "gn:dem":120,
    "gn:feature_class":"P",
    "gn:feature_code":"PPL",
    "gn:name":"Kampung Ampang Kasai",
    "gn:population":0,
    "gn:timezone":"Asia/Kuala_Lumpur",
    "iso:country":"MY",
    "name:msa_x_preferred":[
        "Kampung Ampang Kasai"
    ],
    "wof:name":"Kampung Ampang Kasai",
    "wof:placetype":"locality"
},
  "geometry": {"coordinates":[102.173,2.7769],"type":"Point"}
}