{
  "type": "Feature",
  "properties": {
    "gn:admin1_code":"7.0",
    "gn:asciiname":"Taman Kamiri",
    "gn:country_code":"MY",
    "gn:dem":79,
    "gn:feature_class":"P",
    "gn:feature_code":"PPL",
    "gn:name":"Taman Kamiri",
    "gn:population":0,
    "gn:timezone":"Asia/Kuala_Lumpur",
    "iso:country":"MY",
    "name:msa_x_preferred":[
        "Taman Kamiri"
    ],
    "wof:name":"Taman Kamiri",
    "wof:placetype":"locality"
},
  "geometry": {"coordinates":[101.09610000000001,4.8213],"type":"Point"}
}