{
  "type": "Feature",
  "properties": {
    "gn:admin1_code":"1",
    "gn:asciiname":"Kampung Chok Gadong",
    "gn:country_code":"MY",
    "gn:dem":32,
    "gn:feature_class":"P",
    "gn:feature_code":"PPL",
    "gn:name":"Kampung Chok Gadong",
    "gn:population":0,
    "gn:timezone":"Asia/Kuala_Lumpur",
    "iso:country":"MY",
    "name:msa_x_preferred":[
        "Kampung Chok Gadong"
    ],
    "name:und_x_variant":[
        "Kampong Chok Gadong"
    ],
    "wof:name":"Kampung Chok Gadong",
    "wof:placetype":"locality"
},
  "geometry": {"coordinates":[102.8192,2.5505],"type":"Point"}
}