{
  "type": "Feature",
  "properties": {
    "gn:admin1_code":"5",
    "gn:asciiname":"Kampung Tanah Datar Bongek",
    "gn:country_code":"MY",
    "gn:dem":42,
    "gn:feature_class":"P",
    "gn:feature_code":"PPL",
    "gn:name":"Kampung Tanah Datar Bongek",
    "gn:population":0,
    "gn:timezone":"Asia/Kuala_Lumpur",
    "iso:country":"MY",
    "name:msa_x_preferred":[
        "Kampung Tanah Datar Bongek"
    ],
    "name:und_x_variant":[
        "Kampong Tanah Datar Bongek"
    ],
    "wof:name":"Kampung Tanah Datar Bongek",
    "wof:placetype":"locality"
},
  "geometry": {"coordinates":[102.11709999999999,2.5588],"type":"Point"}
}