{
  "type": "Feature",
  "properties": {
    "gn:admin1_code":"6.0",
    "gn:asciiname":"Keratung Tujuh",
    "gn:country_code":"MY",
    "gn:dem":73,
    "gn:feature_class":"P",
    "gn:feature_code":"PPL",
    "gn:name":"Keratung Tujuh",
    "gn:population":0,
    "gn:timezone":"Asia/Kuala_Lumpur",
    "iso:country":"MY",
    "name:msa_x_preferred":[
        "Keratung Tujuh"
    ],
    "wof:name":"Keratung Tujuh",
    "wof:placetype":"locality"
},
  "geometry": {"coordinates":[102.98820000000001,2.8515],"type":"Point"}
}