{
  "type": "Feature",
  "properties": {
    "gn:admin1_code":"4",
    "gn:asciiname":"Kampung Padang Kambing",
    "gn:country_code":"MY",
    "gn:dem":44,
    "gn:feature_class":"P",
    "gn:feature_code":"PPL",
    "gn:name":"Kampung Padang Kambing",
    "gn:population":0,
    "gn:timezone":"Asia/Kuala_Lumpur",
    "iso:country":"MY",
    "name:msa_x_preferred":[
        "Kampung Padang Kambing"
    ],
    "name:und_x_variant":[
        "Padang Kambing"
    ],
    "wof:name":"Kampung Padang Kambing",
    "wof:placetype":"locality"
},
  "geometry": {"coordinates":[102.14870000000001,2.4202],"type":"Point"}
}