{
  "type": "Feature",
  "properties": {
    "gn:admin1_code":"5",
    "gn:asciiname":"Kampung Kayu Ara",
    "gn:country_code":"MY",
    "gn:dem":50,
    "gn:feature_class":"P",
    "gn:feature_code":"PPL",
    "gn:name":"Kampung Kayu Ara",
    "gn:population":0,
    "gn:timezone":"Asia/Kuala_Lumpur",
    "iso:country":"MY",
    "name:msa_x_preferred":[
        "Kampung Kayu Ara"
    ],
    "name:und_x_variant":[
        "Kampong Kayu Ara"
    ],
    "wof:name":"Kampung Kayu Ara",
    "wof:placetype":"locality"
},
  "geometry": {"coordinates":[101.9102,2.6745],"type":"Point"}
}