{
  "type": "Feature",
  "properties": {
    "gn:admin1_code":"6.0",
    "gn:asciiname":"Kampung Sungai Tekam",
    "gn:country_code":"MY",
    "gn:dem":69,
    "gn:feature_class":"P",
    "gn:feature_code":"PPL",
    "gn:name":"Kampung Sungai Tekam",
    "gn:population":0,
    "gn:timezone":"Asia/Kuala_Lumpur",
    "iso:country":"MY",
    "name:msa_x_preferred":[
        "Kampung Sungai Tekam"
    ],
    "wof:name":"Kampung Sungai Tekam",
    "wof:placetype":"locality"
},
  "geometry": {"coordinates":[102.5291,3.8703],"type":"Point"}
}