{
  "type": "Feature",
  "properties": {
    "gn:admin1_code":"11",
    "gn:asciiname":"Kampong Masio",
    "gn:country_code":"MY",
    "gn:dem":1,
    "gn:feature_class":"P",
    "gn:feature_code":"PPL",
    "gn:name":"Kampong Masio",
    "gn:population":0,
    "gn:timezone":"Asia/Kuching",
    "iso:country":"MY",
    "wof:name":"Kampong Masio",
    "wof:placetype":"locality"
},
  "geometry": {"coordinates":[109.86444,1.71408],"type":"Point"}
}