{
  "type": "Feature",
  "properties": {
    "gn:admin1_code":"6.0",
    "gn:asciiname":"Pulau Tengku Muda",
    "gn:country_code":"MY",
    "gn:dem":9,
    "gn:feature_class":"P",
    "gn:feature_code":"PPL",
    "gn:name":"Pulau Tengku Muda",
    "gn:population":0,
    "gn:timezone":"Asia/Kuala_Lumpur",
    "iso:country":"MY",
    "name:msa_x_preferred":[
        "Pulau Tengku Muda"
    ],
    "wof:name":"Pulau Tengku Muda",
    "wof:placetype":"locality"
},
  "geometry": {"coordinates":[103.3856,3.5047],"type":"Point"}
}