{
  "type": "Feature",
  "properties": {
    "gn:admin1_code":"16.0",
    "gn:asciiname":"Kampung Gumpa",
    "gn:country_code":"MY",
    "gn:dem":20,
    "gn:feature_class":"P",
    "gn:feature_code":"PPL",
    "gn:name":"Kampung Gumpa",
    "gn:population":0,
    "gn:timezone":"Asia/Kuching",
    "iso:country":"MY",
    "name:msa_x_preferred":[
        "Kampung Gumpa"
    ],
    "name:und_x_variant":[
        "Gumpah"
    ],
    "wof:name":"Kampung Gumpa",
    "wof:placetype":"locality"
},
  "geometry": {"coordinates":[117.10963999999998,6.85759],"type":"Point"}
}