{
  "type": "Feature",
  "properties": {
    "gn:admin1_code":"9",
    "gn:asciiname":"Kampung Titi Teras",
    "gn:country_code":"MY",
    "gn:dem":19,
    "gn:feature_class":"P",
    "gn:feature_code":"PPL",
    "gn:name":"Kampung Titi Teras",
    "gn:population":0,
    "gn:timezone":"Asia/Kuala_Lumpur",
    "iso:country":"MY",
    "name:msa_x_preferred":[
        "Kampung Titi Teras"
    ],
    "name:und_x_variant":[
        "Kampong Titi Tras"
    ],
    "wof:name":"Kampung Titi Teras",
    "wof:placetype":"locality"
},
  "geometry": {"coordinates":[100.22372,5.358],"type":"Point"}
}