{
  "type": "Feature",
  "properties": {
    "iso:country":"MY",
    "qs:name":"T K/plek Perniagaan Munshi Abdullah",
    "qs:name_adm0":"Malaysia",
    "qs:name_adm1":"Melaka",
    "qs:photos":183,
    "qs:photos_1k":37,
    "qs:photos_9k":1,
    "qs:photos_9r":4,
    "qs:photos_all":183,
    "qs:photos_sr":4,
    "qs:placetype":"Suburb",
    "qs:pop_sr":"0",
    "wof:name":"T K/plek Perniagaan Munshi Abdullah",
    "wof:placetype":"neighbourhood"
},
  "geometry": {"coordinates":[102.25420800000001,2.197169],"type":"Point"}
}