{
  "type": "Feature",
  "properties": {
    "iso:country":"MY",
    "qs:name":"Beserah",
    "qs:name_adm0":"Malaysia",
    "qs:name_adm1":"Pahang",
    "qs:photos":163,
    "qs:photos_1k":33,
    "qs:photos_9k":1,
    "qs:photos_9r":4,
    "qs:photos_all":262,
    "qs:photos_sr":4,
    "qs:placetype":"LocalAdmin",
    "qs:pop_sr":"0",
    "wd:wordcount":36,
    "wof:name":"Beserah",
    "wof:placetype":"localadmin"
},
  "geometry": {"coordinates":[103.3665685,3.8855555],"type":"Point"}
}