{
  "type": "Feature",
  "properties": {
    "gn:admin1_code":"11",
    "gn:asciiname":"Rumah Penghulu Ajot",
    "gn:cc2":"MY",
    "gn:country_code":"MY",
    "gn:dem":33,
    "gn:feature_class":"P",
    "gn:feature_code":"PPL",
    "gn:name":"Rumah Penghulu Ajot",
    "gn:population":0,
    "gn:timezone":"Asia/Kuching",
    "iso:country":"MY",
    "name:und_x_variant":[
        "Rumah Peng Ajat",
        "Rumah Peng Bush",
        "Rumah Penghulu Ajot"
    ],
    "wof:name":"Rumah Penghulu Ajot",
    "wof:placetype":"locality"
},
  "geometry": {"coordinates":[112.36667,1.96667],"type":"Point"}
}