{
  "type": "Feature",
  "properties": {
    "gn:admin1_code":"2",
    "gn:asciiname":"Kampung Tandop",
    "gn:country_code":"MY",
    "gn:dem":7,
    "gn:feature_class":"P",
    "gn:feature_code":"PPL",
    "gn:name":"Kampung Tandop",
    "gn:population":0,
    "gn:timezone":"Asia/Kuala_Lumpur",
    "iso:country":"MY",
    "name:msa_x_preferred":[
        "Kampung Tandop"
    ],
    "name:und_x_variant":[
        "Kampong Tandob",
        "Kampong Tandok"
    ],
    "wof:name":"Kampung Tandop",
    "wof:placetype":"locality"
},
  "geometry": {"coordinates":[100.36449,6.07705],"type":"Point"}
}