{
  "type": "Feature",
  "properties": {
    "gn:admin1_code":"16",
    "gn:asciiname":"Kampung Lugu",
    "gn:country_code":"MY",
    "gn:dem":85,
    "gn:feature_class":"P",
    "gn:feature_code":"PPL",
    "gn:name":"Kampung Lugu",
    "gn:population":0,
    "gn:timezone":"Asia/Kuching",
    "iso:country":"MY",
    "name:msa_x_preferred":[
        "Kampung Lugu"
    ],
    "name:und_x_variant":[
        "Kampong Lugu"
    ],
    "wof:name":"Kampung Lugu",
    "wof:placetype":"locality"
},
  "geometry": {"coordinates":[116.5981,6.5247],"type":"Point"}
}