{
  "type": "Feature",
  "properties": {
    "gn:admin1_code":"16",
    "gn:asciiname":"Kampung Kandawayang",
    "gn:country_code":"MY",
    "gn:dem":3,
    "gn:feature_class":"P",
    "gn:feature_code":"PPL",
    "gn:name":"Kampung Kandawayang",
    "gn:population":0,
    "gn:timezone":"Asia/Kuching",
    "iso:country":"MY",
    "name:msa_x_preferred":[
        "Kampung Kandawayang"
    ],
    "name:und_x_variant":[
        "Kampong Kandawayang"
    ],
    "wof:name":"Kampung Kandawayang",
    "wof:placetype":"locality"
},
  "geometry": {"coordinates":[116.73779999999999,6.5074],"type":"Point"}
}