{
  "type": "Feature",
  "properties": {
    "gn:admin1_code":"1.0",
    "gn:asciiname":"Kampung Simpang Arang",
    "gn:country_code":"MY",
    "gn:dem":22,
    "gn:feature_class":"P",
    "gn:feature_code":"PPL",
    "gn:name":"Kampung Simpang Arang",
    "gn:population":0,
    "gn:timezone":"Asia/Kuala_Lumpur",
    "iso:country":"MY",
    "name:msa_x_preferred":[
        "Kampung Simpang Arang"
    ],
    "wof:name":"Kampung Simpang Arang",
    "wof:placetype":"locality"
},
  "geometry": {"coordinates":[103.5684,1.4125],"type":"Point"}
}