{
  "type": "Feature",
  "properties": {
    "gn:admin1_code":"1",
    "gn:asciiname":"Kampung Paya Getah",
    "gn:country_code":"MY",
    "gn:dem":38,
    "gn:feature_class":"P",
    "gn:feature_code":"PPL",
    "gn:name":"Kampung Paya Getah",
    "gn:population":0,
    "gn:timezone":"Asia/Kuala_Lumpur",
    "iso:country":"MY",
    "name:msa_x_preferred":[
        "Kampung Paya Getah"
    ],
    "name:und_x_variant":[
        "Kampong Paya Getah"
    ],
    "wof:name":"Kampung Paya Getah",
    "wof:placetype":"locality"
},
  "geometry": {"coordinates":[102.8258,2.5609],"type":"Point"}
}