{
  "type": "Feature",
  "properties": {
    "iso:country":"MY",
    "name:msa_x_preferred":[
        "Taman Tas"
    ],
    "name:und_x_preferred":[
        "Taman Taz"
    ],
    "name:unk_x_variant":[
        "Taman Taz"
    ],
    "qs:gn_adm0_cc":"MY",
    "qs:gn_fcode":"PPL",
    "qs:gn_local":1735227,
    "qs:gn_nam_loc":"Kuantan, Kuala Kuantan, Kuantan, Pahang, MY",
    "qs:gn_namadm1":"06",
    "qs:gn_name":"Taman Tas",
    "qs:local_max":328,
    "qs:local_sum":845,
    "qs:localhoods":9,
    "qs:name":"Taman Taz",
    "qs:name_adm0":"Malaysia",
    "qs:name_adm1":"Pahang",
    "qs:name_adm2":"Kuantan",
    "qs:name_lau":"Kuala Kuantan",
    "qs:name_local":"Kuantan",
    "qs:photo_max":3,
    "qs:photo_sum":11,
    "qs:placetype":"Suburb",
    "qs:quad_count":5,
    "qs:woe_adm0":23424901,
    "qs:woe_adm1":2346301,
    "qs:woe_adm2":56013625,
    "qs:woe_lau":56014360,
    "qs:woe_local":1154799,
    "qs:woe_ver":"7.10.0",
    "wof:lang":[
        "unk"
    ],
    "wof:name":"Taman Taz",
    "wof:placetype":"neighbourhood"
},
  "geometry": {"coordinates":[103.35578099999999,3.819354],"type":"Point"}
}