{
  "type": "Feature",
  "properties": {
    "gn:admin1_code":"6",
    "gn:asciiname":"Kampung Mangin",
    "gn:country_code":"MY",
    "gn:dem":62,
    "gn:feature_class":"P",
    "gn:feature_code":"PPL",
    "gn:name":"Kampung Mangin",
    "gn:population":0,
    "gn:timezone":"Asia/Kuala_Lumpur",
    "iso:country":"MY",
    "name:msa_x_preferred":[
        "Kampung Mangin"
    ],
    "name:und_x_variant":[
        "Kampong Mangin"
    ],
    "wof:name":"Kampung Mangin",
    "wof:placetype":"locality"
},
  "geometry": {"coordinates":[102.0489,3.4198],"type":"Point"}
}