{
  "type": "Feature",
  "properties": {
    "gn:admin1_code":"3",
    "gn:asciiname":"Kampong Baharu Ulu Kusial",
    "gn:country_code":"MY",
    "gn:dem":57,
    "gn:feature_class":"P",
    "gn:feature_code":"PPL",
    "gn:name":"Kampong Baharu Ulu Kusial",
    "gn:population":0,
    "gn:timezone":"Asia/Kuala_Lumpur",
    "iso:country":"MY",
    "wof:name":"Kampong Baharu Ulu Kusial",
    "wof:placetype":"locality"
},
  "geometry": {"coordinates":[102.03333000000001,5.73333],"type":"Point"}
}