{
  "type": "Feature",
  "properties": {
    "gn:admin1_code":"16",
    "gn:asciiname":"Kampung Kobusak",
    "gn:country_code":"MY",
    "gn:dem":8,
    "gn:feature_class":"P",
    "gn:feature_code":"PPL",
    "gn:name":"Kampung Kobusak",
    "gn:population":0,
    "gn:timezone":"Asia/Kuching",
    "iso:country":"MY",
    "name:msa_x_preferred":[
        "Kampung Kobusak"
    ],
    "name:und_x_variant":[
        "Kampong Kabusik"
    ],
    "wof:name":"Kampung Kobusak",
    "wof:placetype":"locality"
},
  "geometry": {"coordinates":[116.0804,5.935],"type":"Point"}
}