{
  "type": "Feature",
  "properties": {
    "gn:admin1_code":"9.0",
    "gn:asciiname":"Kampung Permatang Tengah",
    "gn:cc2":"MY",
    "gn:country_code":"MY",
    "gn:dem":7,
    "gn:feature_class":"P",
    "gn:feature_code":"PPL",
    "gn:name":"Kampung Permatang Tengah",
    "gn:population":0,
    "gn:timezone":"Asia/Kuala_Lumpur",
    "iso:country":"MY",
    "name:msa_x_preferred":[
        "Kampung Permatang Tengah"
    ],
    "wof:name":"Kampung Permatang Tengah",
    "wof:placetype":"locality"
},
  "geometry": {"coordinates":[100.45869,5.32785],"type":"Point"}
}