{
  "type": "Feature",
  "properties": {
    "gn:admin1_code":"7.0",
    "gn:asciiname":"Bandar Seri Manjung",
    "gn:country_code":"MY",
    "gn:dem":5,
    "gn:feature_class":"P",
    "gn:feature_code":"PPL",
    "gn:name":"Bandar Seri Manjung",
    "gn:population":0,
    "gn:timezone":"Asia/Kuala_Lumpur",
    "iso:country":"MY",
    "name:msa_x_preferred":[
        "Bandar Seri Manjung"
    ],
    "wof:name":"Bandar Seri Manjung",
    "wof:placetype":"locality"
},
  "geometry": {"coordinates":[100.67440000000001,4.2026],"type":"Point"}
}