{
  "type": "Feature",
  "properties": {
    "gn:admin1_code":"9.0",
    "gn:asciiname":"Guar Perahu",
    "gn:country_code":"MY",
    "gn:dem":22,
    "gn:feature_class":"P",
    "gn:feature_code":"PPL",
    "gn:name":"Guar Perahu",
    "gn:population":0,
    "gn:timezone":"Asia/Kuala_Lumpur",
    "iso:country":"MY",
    "name:msa_x_preferred":[
        "Guar Perahu"
    ],
    "wof:name":"Guar Perahu",
    "wof:placetype":"locality"
},
  "geometry": {"coordinates":[100.47175,5.42849],"type":"Point"}
}