{
  "type": "Feature",
  "properties": {
    "gn:admin1_code":"13",
    "gn:asciiname":"Kampung Kar Buluh",
    "gn:country_code":"MY",
    "gn:dem":12,
    "gn:feature_class":"P",
    "gn:feature_code":"PPL",
    "gn:name":"Kampung Kar Buluh",
    "gn:population":0,
    "gn:timezone":"Asia/Kuala_Lumpur",
    "iso:country":"MY",
    "name:msa_x_preferred":[
        "Kampung Kar Buluh"
    ],
    "name:und_x_variant":[
        "Kampong Kar Buloh"
    ],
    "wof:name":"Kampung Kar Buluh",
    "wof:placetype":"locality"
},
  "geometry": {"coordinates":[103.108,5.2161],"type":"Point"}
}