{
  "type": "Feature",
  "properties": {
    "gn:admin1_code":"1",
    "gn:asciiname":"Kampung Parit Hulu",
    "gn:country_code":"MY",
    "gn:dem":9,
    "gn:feature_class":"P",
    "gn:feature_code":"PPL",
    "gn:name":"Kampung Parit Hulu",
    "gn:population":0,
    "gn:timezone":"Asia/Kuala_Lumpur",
    "iso:country":"MY",
    "name:und_x_variant":[
        "Kampong Parit Ulu"
    ],
    "wof:name":"Kampung Parit Hulu",
    "wof:placetype":"locality"
},
  "geometry": {"coordinates":[102.63939999999999,2.05738],"type":"Point"}
}