{
  "type": "Feature",
  "properties": {
    "gn:admin1_code":"11",
    "gn:asciiname":"Kampong Pelaman Tabiyan Patung",
    "gn:cc2":"MY",
    "gn:country_code":"MY",
    "gn:dem":25,
    "gn:feature_class":"P",
    "gn:feature_code":"PPL",
    "gn:name":"Kampong Pelaman Tabiyan Patung",
    "gn:population":0,
    "gn:timezone":"Asia/Kuching",
    "iso:country":"MY",
    "name:und_x_variant":[
        "Kampong Plaman Tabiyan Patung",
        "Kampong Pelaman Tabiyan Patung"
    ],
    "wof:name":"Kampong Pelaman Tabiyan Patung",
    "wof:placetype":"locality"
},
  "geometry": {"coordinates":[110.38333,1.31667],"type":"Point"}
}