{
  "type": "Feature",
  "properties": {
    "gn:country":"MY",
    "gn:fcode":"PPL",
    "gn:population":0,
    "iso:country":"MY",
    "name:msa_x_preferred":[
        "Kampung Teluk Tempoyak Kecil"
    ],
    "name:msa_x_variant":[
        "Kampung Telok"
    ],
    "name:und_x_variant":[
        "Kampong Telok"
    ],
    "qs:name":"Kampong Telok Tempoyak Kechil",
    "qs:name_adm0":"Malaysia",
    "qs:name_adm1":"Pulau Pinang",
    "qs:photos":57,
    "qs:photos_1k":12,
    "qs:photos_9k":1,
    "qs:photos_9r":2,
    "qs:photos_all":57,
    "qs:photos_sr":2,
    "qs:placetype":"Suburb",
    "qs:pop_sr":"0",
    "wof:name":"Kampong Telok Tempoyak Kechil",
    "wof:placetype":"neighbourhood",
    "wof:population":0
},
  "geometry": {"coordinates":[100.28832,5.27783],"type":"Point"}
}