{
  "type": "Feature",
  "properties": {
    "gn:admin1_code":"16",
    "gn:asciiname":"Kampung Nuluan Dua",
    "gn:country_code":"MY",
    "gn:dem":804,
    "gn:feature_class":"P",
    "gn:feature_code":"PPL",
    "gn:name":"Kampung Nuluan Dua",
    "gn:population":0,
    "gn:timezone":"Asia/Kuching",
    "iso:country":"MY",
    "name:msa_x_preferred":[
        "Kampung Nuluan Dua"
    ],
    "name:und_x_variant":[
        "Kampong Nuluan Dua"
    ],
    "wof:name":"Kampung Nuluan Dua",
    "wof:placetype":"locality"
},
  "geometry": {"coordinates":[116.3993,5.9794],"type":"Point"}
}