{
  "type": "Feature",
  "properties": {
    "gn:admin1_code":"5.0",
    "gn:asciiname":"Taman Bukit Labu",
    "gn:country_code":"MY",
    "gn:dem":68,
    "gn:feature_class":"P",
    "gn:feature_code":"PPL",
    "gn:name":"Taman Bukit Labu",
    "gn:population":0,
    "gn:timezone":"Asia/Kuala_Lumpur",
    "iso:country":"MY",
    "name:msa_x_preferred":[
        "Taman Bukit Labu"
    ],
    "wof:name":"Taman Bukit Labu",
    "wof:placetype":"locality"
},
  "geometry": {"coordinates":[101.92140000000001,2.7209],"type":"Point"}
}