{
  "type": "Feature",
  "properties": {
    "gn:admin1_code":"3",
    "gn:asciiname":"Kampung Batu Lembu",
    "gn:country_code":"MY",
    "gn:dem":56,
    "gn:feature_class":"P",
    "gn:feature_code":"PPL",
    "gn:name":"Kampung Batu Lembu",
    "gn:population":0,
    "gn:timezone":"Asia/Kuala_Lumpur",
    "iso:country":"MY",
    "name:und_x_variant":[
        "Kampong Lembu"
    ],
    "wof:name":"Kampung Batu Lembu",
    "wof:placetype":"locality"
},
  "geometry": {"coordinates":[101.95,5.41667],"type":"Point"}
}