{
  "type": "Feature",
  "properties": {
    "gn:admin1_code":"7.0",
    "gn:asciiname":"Kampung Nering",
    "gn:country_code":"MY",
    "gn:dem":40,
    "gn:feature_class":"P",
    "gn:feature_code":"PPL",
    "gn:name":"Kampung Nering",
    "gn:population":0,
    "gn:timezone":"Asia/Kuala_Lumpur",
    "iso:country":"MY",
    "name:msa_x_preferred":[
        "Kampung Nering"
    ],
    "wof:name":"Kampung Nering",
    "wof:placetype":"locality"
},
  "geometry": {"coordinates":[100.9648,4.5852],"type":"Point"}
}