{
  "type": "Feature",
  "properties": {
    "gn:admin1_code":"16.0",
    "gn:asciiname":"Kolamail Bekal",
    "gn:country_code":"MY",
    "gn:dem":116,
    "gn:feature_class":"P",
    "gn:feature_code":"PPL",
    "gn:name":"Kolamail Bekal",
    "gn:population":0,
    "gn:timezone":"Asia/Kuching",
    "iso:country":"MY",
    "name:msa_x_preferred":[
        "Kolamail Bekal"
    ],
    "wof:name":"Kolamail Bekal",
    "wof:placetype":"locality"
},
  "geometry": {"coordinates":[116.1143,5.9478],"type":"Point"}
}