{
  "type": "Feature",
  "properties": {
    "gn:admin1_code":"1.0",
    "gn:asciiname":"Kampung Jempul",
    "gn:country_code":"MY",
    "gn:dem":14,
    "gn:feature_class":"P",
    "gn:feature_code":"PPL",
    "gn:name":"Kampung Jempul",
    "gn:population":0,
    "gn:timezone":"Asia/Kuala_Lumpur",
    "iso:country":"MY",
    "name:msa_x_preferred":[
        "Kampung Jempul"
    ],
    "wof:name":"Kampung Jempul",
    "wof:placetype":"locality"
},
  "geometry": {"coordinates":[103.94110000000001,1.6451],"type":"Point"}
}