{
  "type": "Feature",
  "properties": {
    "gn:admin1_code":"16",
    "gn:asciiname":"Kampung Mangis",
    "gn:country_code":"MY",
    "gn:dem":295,
    "gn:feature_class":"P",
    "gn:feature_code":"PPL",
    "gn:name":"Kampung Mangis",
    "gn:population":0,
    "gn:timezone":"Asia/Kuching",
    "iso:country":"MY",
    "name:msa_x_preferred":[
        "Kampung Mangis"
    ],
    "name:und_x_variant":[
        "Kampong Manggis"
    ],
    "wof:name":"Kampung Mangis",
    "wof:placetype":"locality"
},
  "geometry": {"coordinates":[116.7651,6.1993],"type":"Point"}
}