{
  "type": "Feature",
  "properties": {
    "gn:admin1_code":"5.0",
    "gn:asciiname":"Taman Rashibah Indah",
    "gn:country_code":"MY",
    "gn:dem":76,
    "gn:feature_class":"P",
    "gn:feature_code":"PPL",
    "gn:name":"Taman Rashibah Indah",
    "gn:population":0,
    "gn:timezone":"Asia/Kuala_Lumpur",
    "iso:country":"MY",
    "name:msa_x_preferred":[
        "Taman Rashibah Indah"
    ],
    "wof:name":"Taman Rashibah Indah",
    "wof:placetype":"locality"
},
  "geometry": {"coordinates":[101.9543,2.7462],"type":"Point"}
}