{
  "type": "Feature",
  "properties": {
    "gn:admin1_code":"3.0",
    "gn:asciiname":"Perkampungan Biak A",
    "gn:country_code":"MY",
    "gn:dem":64,
    "gn:feature_class":"P",
    "gn:feature_code":"PPL",
    "gn:name":"Perkampungan Biak A",
    "gn:population":0,
    "gn:timezone":"Asia/Kuala_Lumpur",
    "iso:country":"MY",
    "name:msa_x_preferred":[
        "Perkampungan Biak A"
    ],
    "wof:name":"Perkampungan Biak A",
    "wof:placetype":"locality"
},
  "geometry": {"coordinates":[101.9915,5.4132],"type":"Point"}
}