{
  "type": "Feature",
  "properties": {
    "gn:admin1_code":"1.0",
    "gn:asciiname":"Bukit Benut Village",
    "gn:country_code":"MY",
    "gn:dem":71,
    "gn:feature_class":"P",
    "gn:feature_code":"PPL",
    "gn:name":"Bukit Benut Village",
    "gn:population":0,
    "gn:timezone":"Asia/Kuala_Lumpur",
    "iso:country":"MY",
    "name:und_x_variant":[
        "Kampong Bukit Benut",
        "Bukit Benut Village"
    ],
    "wof:name":"Bukit Benut Village",
    "wof:placetype":"locality"
},
  "geometry": {"coordinates":[103.33333,1.91667],"type":"Point"}
}