{
  "type": "Feature",
  "properties": {
    "gn:admin1_code":"16",
    "gn:asciiname":"Kampung Kilugus",
    "gn:country_code":"MY",
    "gn:dem":25,
    "gn:feature_class":"P",
    "gn:feature_code":"PPL",
    "gn:name":"Kampung Kilugus",
    "gn:population":0,
    "gn:timezone":"Asia/Kuching",
    "iso:country":"MY",
    "name:msa_x_preferred":[
        "Kampung Kilugus"
    ],
    "name:und_x_variant":[
        "Kampong Kilugus"
    ],
    "wof:name":"Kampung Kilugus",
    "wof:placetype":"locality"
},
  "geometry": {"coordinates":[115.5729,5.5591],"type":"Point"}
}