{
  "type": "Feature",
  "properties": {
    "gn:admin1_code":"16",
    "gn:asciiname":"Kampung Batu Luang",
    "gn:country_code":"MY",
    "gn:dem":20,
    "gn:feature_class":"P",
    "gn:feature_code":"PPL",
    "gn:name":"Kampung Batu Luang",
    "gn:population":0,
    "gn:timezone":"Asia/Kuching",
    "iso:country":"MY",
    "name:msa_x_preferred":[
        "Kampung Batu Luang"
    ],
    "name:und_x_variant":[
        "Batu Luang",
        "Kampong Batu Luang"
    ],
    "wof:name":"Kampung Batu Luang",
    "wof:placetype":"locality"
},
  "geometry": {"coordinates":[115.527,5.5253],"type":"Point"}
}