{
  "type": "Feature",
  "properties": {
    "gn:admin1_code":"6.0",
    "gn:asciiname":"Kampung Jengar",
    "gn:country_code":"MY",
    "gn:dem":117,
    "gn:feature_class":"P",
    "gn:feature_code":"PPL",
    "gn:name":"Kampung Jengar",
    "gn:population":0,
    "gn:timezone":"Asia/Kuala_Lumpur",
    "iso:country":"MY",
    "name:msa_x_preferred":[
        "Kampung Jengar"
    ],
    "wof:name":"Kampung Jengar",
    "wof:placetype":"locality"
},
  "geometry": {"coordinates":[102.2047,3.8938],"type":"Point"}
}