{
  "type": "Feature",
  "properties": {
    "gn:admin1_code":"1.0",
    "gn:asciiname":"Kampung Sumber Jaya Tiga",
    "gn:country_code":"MY",
    "gn:dem":11,
    "gn:feature_class":"P",
    "gn:feature_code":"PPL",
    "gn:name":"Kampung Sumber Jaya Tiga",
    "gn:population":0,
    "gn:timezone":"Asia/Kuala_Lumpur",
    "iso:country":"MY",
    "name:msa_x_preferred":[
        "Kampung Sumber Jaya Tiga"
    ],
    "wof:name":"Kampung Sumber Jaya Tiga",
    "wof:placetype":"locality"
},
  "geometry": {"coordinates":[103.3544,1.7411],"type":"Point"}
}