{
  "type": "Feature",
  "properties": {
    "gn:admin1_code":"16",
    "gn:asciiname":"Kampong Paka Paka",
    "gn:country_code":"MY",
    "gn:dem":31,
    "gn:feature_class":"P",
    "gn:feature_code":"PPL",
    "gn:name":"Kampong Paka Paka",
    "gn:population":0,
    "gn:timezone":"Asia/Kuching",
    "iso:country":"MY",
    "name:msa_x_preferred":[
        "Kampong Paka Paka"
    ],
    "name:und_x_variant":[
        "Paka Paka"
    ],
    "wof:name":"Kampong Paka Paka",
    "wof:placetype":"locality"
},
  "geometry": {"coordinates":[116.40170000000001,6.3317],"type":"Point"}
}