{
  "type": "Feature",
  "properties": {
    "gn:country":"MY",
    "gn:fcode":"PPL",
    "gn:pop":0,
    "iso:country":"MY",
    "name:msa_x_preferred":[
        "Taman Maju Jaya"
    ],
    "qs:name":"Taman Temu Jaya",
    "qs:name_adm0":"Malaysia",
    "qs:name_adm1":"Melaka",
    "qs:photos_9r":0,
    "qs:photos_sr":0,
    "qs:placetype":"Town",
    "qs:pop_sr":"0",
    "wof:name":"Taman Temu Jaya",
    "wof:placetype":"locality",
    "wof:population":0
},
  "geometry": {"coordinates":[102.36020000000001,3.1289],"type":"Point"}
}