{
  "type": "Feature",
  "properties": {
    "gn:admin1_code":"13",
    "gn:asciiname":"Kampung Bukit Munduk",
    "gn:country_code":"MY",
    "gn:dem":23,
    "gn:feature_class":"P",
    "gn:feature_code":"PPL",
    "gn:name":"Kampung Bukit Munduk",
    "gn:population":0,
    "gn:timezone":"Asia/Kuala_Lumpur",
    "iso:country":"MY",
    "name:msa_x_preferred":[
        "Kampung Bukit Munduk"
    ],
    "name:und_x_variant":[
        "Kampong Bukit Mundok"
    ],
    "wof:name":"Kampung Bukit Munduk",
    "wof:placetype":"locality"
},
  "geometry": {"coordinates":[102.93170000000001,5.2227],"type":"Point"}
}