{
  "type": "Feature",
  "properties": {
    "gn:admin1_code":"16",
    "gn:asciiname":"Kampung Nabusong",
    "gn:country_code":"MY",
    "gn:dem":103,
    "gn:feature_class":"P",
    "gn:feature_code":"PPL",
    "gn:name":"Kampung Nabusong",
    "gn:population":0,
    "gn:timezone":"Asia/Kuching",
    "iso:country":"MY",
    "name:msa_x_preferred":[
        "Kampung Nabusong"
    ],
    "name:und_x_variant":[
        "Kampong Nabusong"
    ],
    "wof:name":"Kampung Nabusong",
    "wof:placetype":"locality"
},
  "geometry": {"coordinates":[116.6474,6.7017],"type":"Point"}
}