{
  "type": "Feature",
  "properties": {
    "iso:country":"MY",
    "qs:name":"Damansara",
    "qs:name_adm0":"Malaysia",
    "qs:name_adm1":"Selangor",
    "qs:photos":1,
    "qs:photos_1k":1,
    "qs:photos_9k":48,
    "qs:photos_9r":16,
    "qs:photos_all":10769,
    "qs:photos_sr":1,
    "qs:placetype":"LocalAdmin",
    "qs:pop_sr":"0",
    "wd:wordcount":55,
    "wof:name":"Damansara",
    "wof:placetype":"localadmin"
},
  "geometry": {"coordinates":[101.574348,3.053037],"type":"Point"}
}