{
  "type": "Feature",
  "properties": {
    "gn:admin1_code":"16",
    "gn:asciiname":"Noduh",
    "gn:country_code":"MY",
    "gn:dem":649,
    "gn:feature_class":"P",
    "gn:feature_code":"PPL",
    "gn:name":"Noduh",
    "gn:population":0,
    "gn:timezone":"Asia/Kuching",
    "iso:country":"MY",
    "wof:name":"Noduh",
    "wof:placetype":"locality"
},
  "geometry": {"coordinates":[116.38333,5.68333],"type":"Point"}
}