{
  "type": "Feature",
  "properties": {
    "iso:country":"MY",
    "name:und_x_preferred":[
        "Mutiara Puchong"
    ],
    "name:unk_x_variant":[
        "Mutiara Puchong"
    ],
    "qs:gn_local":0,
    "qs:local_max":491,
    "qs:local_sum":2868,
    "qs:localhoods":17,
    "qs:name":"Mutiara Puchong",
    "qs:name_adm0":"Malaysia",
    "qs:name_adm1":"Selangor",
    "qs:name_adm2":"Petaling",
    "qs:name_lau":"Petaling",
    "qs:name_local":"Subang Jaya",
    "qs:photo_max":25,
    "qs:photo_sum":130,
    "qs:placetype":"Suburb",
    "qs:quad_count":17,
    "qs:woe_adm0":23424901,
    "qs:woe_adm1":2346306,
    "qs:woe_adm2":56013632,
    "qs:woe_lau":56014451,
    "qs:woe_local":55862650,
    "qs:woe_ver":"7.10.0",
    "wof:lang":[
        "unk"
    ],
    "wof:name":"Mutiara Puchong",
    "wof:placetype":"neighbourhood"
},
  "geometry": {"coordinates":[101.617079,3.027743],"type":"Point"}
}