{
  "type": "Feature",
  "properties": {
    "gn:admin1_code":"16",
    "gn:asciiname":"Kampong Tiung Kemburaan",
    "gn:country_code":"MY",
    "gn:dem":642,
    "gn:feature_class":"P",
    "gn:feature_code":"PPL",
    "gn:name":"Kampong Tiung Kemburaan",
    "gn:population":0,
    "gn:timezone":"Asia/Kuching",
    "iso:country":"MY",
    "wof:name":"Kampong Tiung Kemburaan",
    "wof:placetype":"locality"
},
  "geometry": {"coordinates":[116.40000000000001,6.23333],"type":"Point"}
}