{
  "type": "Feature",
  "properties": {
    "gn:admin1_code":"7",
    "gn:asciiname":"Kampung Temelong",
    "gn:cc2":"MY",
    "gn:country_code":"MY",
    "gn:dem":81,
    "gn:feature_class":"P",
    "gn:feature_code":"PPL",
    "gn:name":"Kampung Temelong",
    "gn:population":0,
    "gn:timezone":"Asia/Kuala_Lumpur",
    "iso:country":"MY",
    "name:msa_x_preferred":[
        "Kampung Temelong"
    ],
    "name:und_x_variant":[
        "Kampong Temelong"
    ],
    "wof:name":"Kampung Temelong",
    "wof:placetype":"locality"
},
  "geometry": {"coordinates":[100.99796000000001,5.1101],"type":"Point"}
}