{
  "type": "Feature",
  "properties": {
    "gn:admin1_code":"6.0",
    "gn:asciiname":"Kampung Batu Malim",
    "gn:country_code":"MY",
    "gn:dem":125,
    "gn:feature_class":"P",
    "gn:feature_code":"PPL",
    "gn:name":"Kampung Batu Malim",
    "gn:population":0,
    "gn:timezone":"Asia/Kuala_Lumpur",
    "iso:country":"MY",
    "name:msa_x_preferred":[
        "Kampung Batu Malim"
    ],
    "wof:name":"Kampung Batu Malim",
    "wof:placetype":"locality"
},
  "geometry": {"coordinates":[101.7837,3.9773],"type":"Point"}
}