{
  "type": "Feature",
  "properties": {
    "gn:admin1_code":"16",
    "gn:asciiname":"Kampung Gelam",
    "gn:country_code":"MY",
    "gn:dem":7,
    "gn:feature_class":"P",
    "gn:feature_code":"PPL",
    "gn:name":"Kampung Gelam",
    "gn:population":0,
    "gn:timezone":"Asia/Kuching",
    "iso:country":"MY",
    "name:msa_x_preferred":[
        "Kampung Gelam"
    ],
    "name:und_x_variant":[
        "Kampong Glam",
        "Kampong Gelam"
    ],
    "wof:name":"Kampung Gelam",
    "wof:placetype":"locality"
},
  "geometry": {"coordinates":[118.10890000000001,5.8384],"type":"Point"}
}