{
  "type": "Feature",
  "properties": {
    "gn:admin1_code":"5",
    "gn:asciiname":"Kampung Bukit Kerdas",
    "gn:country_code":"MY",
    "gn:dem":83,
    "gn:feature_class":"P",
    "gn:feature_code":"PPL",
    "gn:name":"Kampung Bukit Kerdas",
    "gn:population":0,
    "gn:timezone":"Asia/Kuala_Lumpur",
    "iso:country":"MY",
    "name:msa_x_preferred":[
        "Kampung Bukit Kerdas"
    ],
    "name:und_x_variant":[
        "Kampong Bukit Kerdas"
    ],
    "wof:name":"Kampung Bukit Kerdas",
    "wof:placetype":"locality"
},
  "geometry": {"coordinates":[102.327,2.8366],"type":"Point"}
}