{
  "type": "Feature",
  "properties": {
    "gn:admin1_code":"11",
    "gn:asciiname":"Samu",
    "gn:country_code":"MY",
    "gn:dem":51,
    "gn:feature_class":"P",
    "gn:feature_code":"PPL",
    "gn:name":"Samu",
    "gn:population":0,
    "gn:timezone":"Asia/Kuching",
    "iso:country":"MY",
    "wof:name":"Samu",
    "wof:placetype":"locality"
},
  "geometry": {"coordinates":[111.53333000000001,1.55],"type":"Point"}
}