{
  "type": "Feature",
  "properties": {
    "gn:admin1_code":"2.0",
    "gn:asciiname":"Taman Simpang Empat",
    "gn:country_code":"MY",
    "gn:dem":6,
    "gn:feature_class":"P",
    "gn:feature_code":"PPL",
    "gn:name":"Taman Simpang Empat",
    "gn:population":0,
    "gn:timezone":"Asia/Kuala_Lumpur",
    "iso:country":"MY",
    "name:msa_x_preferred":[
        "Taman Simpang 4"
    ],
    "name:msa_x_variant":[
        "Taman Simpang Empat"
    ],
    "name:und_x_variant":[
        "Simpang Ampat",
        "Simpang Empat"
    ],
    "wof:name":"Taman Simpang Empat",
    "wof:placetype":"locality"
},
  "geometry": {"coordinates":[100.38773999999999,6.02228],"type":"Point"}
}