{
  "type": "Feature",
  "properties": {
    "gn:admin1_code":"4",
    "gn:asciiname":"Kampung Ujong",
    "gn:country_code":"MY",
    "gn:dem":6,
    "gn:feature_class":"P",
    "gn:feature_code":"PPL",
    "gn:name":"Kampung Ujong",
    "gn:population":0,
    "gn:timezone":"Asia/Kuala_Lumpur",
    "iso:country":"MY",
    "name:msa_x_preferred":[
        "Kampung Ujong"
    ],
    "name:und_x_variant":[
        "Kampong Ujong"
    ],
    "wof:name":"Kampung Ujong",
    "wof:placetype":"locality"
},
  "geometry": {"coordinates":[102.2944,2.1879],"type":"Point"}
}