{
  "type": "Feature",
  "properties": {
    "gn:admin1_code":"16.0",
    "gn:asciiname":"Mutiala",
    "gn:country_code":"MY",
    "gn:dem":28,
    "gn:elevation":"0.0",
    "gn:feature_class":"P",
    "gn:feature_code":"PPL",
    "gn:name":"Mutiala",
    "gn:population":0,
    "gn:timezone":"Asia/Kuching",
    "iso:country":"MY",
    "wof:name":"Mutiala",
    "wof:placetype":"locality"
},
  "geometry": {"coordinates":[117.8528,4.3226],"type":"Point"}
}