{
  "type": "Feature",
  "properties": {
    "gn:admin1_code":"0.0",
    "gn:asciiname":"Kampung Kuala Sungai Perlis",
    "gn:cc2":"MY",
    "gn:country_code":"MY",
    "gn:dem":52,
    "gn:feature_class":"P",
    "gn:feature_code":"PPL",
    "gn:name":"Kampung Kuala Sungai Perlis",
    "gn:population":0,
    "gn:timezone":"Asia/Kuala_Lumpur",
    "iso:country":"MY",
    "name:und_x_variant":[
        "Kampong Kuala Sungei Perlis",
        "Kampung Kuala Sungai Perlis"
    ],
    "wof:name":"Kampung Kuala Sungai Perlis",
    "wof:placetype":"locality"
},
  "geometry": {"coordinates":[103.03333000000001,4.63333],"type":"Point"}
}