{
  "type": "Feature",
  "properties": {
    "gn:admin1_code":"16.0",
    "gn:asciiname":"Kijang",
    "gn:country_code":"MY",
    "gn:dem":214,
    "gn:elevation":"0.0",
    "gn:feature_class":"P",
    "gn:feature_code":"PPL",
    "gn:name":"Kijang",
    "gn:population":0,
    "gn:timezone":"Asia/Kuching",
    "iso:country":"MY",
    "wof:name":"Kijang",
    "wof:placetype":"locality"
},
  "geometry": {"coordinates":[117.81480000000001,4.4716],"type":"Point"}
}