{
  "type": "Feature",
  "properties": {
    "gn:admin1_code":"2",
    "gn:asciiname":"Kampung Bakar Sampah",
    "gn:cc2":"MY",
    "gn:country_code":"MY",
    "gn:dem":31,
    "gn:feature_class":"P",
    "gn:feature_code":"PPL",
    "gn:name":"Kampung Bakar Sampah",
    "gn:population":0,
    "gn:timezone":"Asia/Kuala_Lumpur",
    "iso:country":"MY",
    "name:msa_x_preferred":[
        "Kampung Bakar Sampah"
    ],
    "name:und_x_variant":[
        "Kampong Bakar Sampah Baharu"
    ],
    "wof:name":"Kampung Bakar Sampah",
    "wof:placetype":"locality"
},
  "geometry": {"coordinates":[100.56126999999999,5.37042],"type":"Point"}
}