{
  "type": "Feature",
  "properties": {
    "gn:admin1_code":"4.0",
    "gn:asciiname":"Kampung Permatang Ayer Pasir",
    "gn:country_code":"MY",
    "gn:dem":43,
    "gn:feature_class":"P",
    "gn:feature_code":"PPL",
    "gn:name":"Kampung Permatang Ayer Pasir",
    "gn:population":0,
    "gn:timezone":"Asia/Kuala_Lumpur",
    "iso:country":"MY",
    "name:msa_x_preferred":[
        "Kampung Permatang Ayer Pasir"
    ],
    "wof:name":"Kampung Permatang Ayer Pasir",
    "wof:placetype":"locality"
},
  "geometry": {"coordinates":[102.3317,2.3806],"type":"Point"}
}