{
  "type": "Feature",
  "properties": {
    "gn:admin1_code":"6.0",
    "gn:asciiname":"Kampung Betung",
    "gn:country_code":"MY",
    "gn:dem":131,
    "gn:feature_class":"P",
    "gn:feature_code":"PPL",
    "gn:name":"Kampung Betung",
    "gn:population":0,
    "gn:timezone":"Asia/Kuala_Lumpur",
    "iso:country":"MY",
    "name:msa_x_preferred":[
        "Kampung Betung"
    ],
    "wof:name":"Kampung Betung",
    "wof:placetype":"locality"
},
  "geometry": {"coordinates":[102.0792,3.993],"type":"Point"}
}