{
  "type": "Feature",
  "properties": {
    "gn:admin1_code":"11",
    "gn:asciiname":"Kampong Manjelin",
    "gn:country_code":"MY",
    "gn:dem":19,
    "gn:feature_class":"P",
    "gn:feature_code":"PPL",
    "gn:name":"Kampong Manjelin",
    "gn:population":0,
    "gn:timezone":"Asia/Kuching",
    "iso:country":"MY",
    "wof:name":"Kampong Manjelin",
    "wof:placetype":"locality"
},
  "geometry": {"coordinates":[113.83333,4.08333],"type":"Point"}
}