{
  "type": "Feature",
  "properties": {
    "gn:admin1_code":"6.0",
    "gn:asciiname":"Kampung Tanjung Kelat",
    "gn:country_code":"MY",
    "gn:dem":60,
    "gn:feature_class":"P",
    "gn:feature_code":"PPL",
    "gn:name":"Kampung Tanjung Kelat",
    "gn:population":0,
    "gn:timezone":"Asia/Kuala_Lumpur",
    "iso:country":"MY",
    "name:msa_x_preferred":[
        "Kampung Tanjung Kelat"
    ],
    "wof:name":"Kampung Tanjung Kelat",
    "wof:placetype":"locality"
},
  "geometry": {"coordinates":[102.39019999999999,3.4076],"type":"Point"}
}