{
  "type": "Feature",
  "properties": {
    "gn:admin1_code":"13",
    "gn:asciiname":"Kampung Rantau Panjang Hilir",
    "gn:country_code":"MY",
    "gn:dem":16,
    "gn:feature_class":"P",
    "gn:feature_code":"PPL",
    "gn:name":"Kampung Rantau Panjang Hilir",
    "gn:population":0,
    "gn:timezone":"Asia/Kuala_Lumpur",
    "iso:country":"MY",
    "name:msa_x_preferred":[
        "Kampung Rantau Panjang Hilir"
    ],
    "name:und_x_variant":[
        "Kampong Rantau Panjang Hilir"
    ],
    "wof:name":"Kampung Rantau Panjang Hilir",
    "wof:placetype":"locality"
},
  "geometry": {"coordinates":[103.2659,4.281],"type":"Point"}
}