{
  "type": "Feature",
  "properties": {
    "gn:admin1_code":"2",
    "gn:asciiname":"Kampung Padang Dan",
    "gn:cc2":"MY",
    "gn:country_code":"MY",
    "gn:dem":76,
    "gn:feature_class":"P",
    "gn:feature_code":"PPL",
    "gn:name":"Kampung Padang Dan",
    "gn:population":0,
    "gn:timezone":"Asia/Kuala_Lumpur",
    "iso:country":"MY",
    "name:msa_x_preferred":[
        "Kampung Padang Dan"
    ],
    "name:und_x_variant":[
        "Kampong Padang Dan"
    ],
    "wof:name":"Kampung Padang Dan",
    "wof:placetype":"locality"
},
  "geometry": {"coordinates":[100.88233,5.57216],"type":"Point"}
}