{
  "type": "Feature",
  "properties": {
    "gn:admin1_code":"9",
    "gn:asciiname":"Kampung Pulau Mertajam",
    "gn:cc2":"MY",
    "gn:country_code":"MY",
    "gn:dem":14,
    "gn:feature_class":"P",
    "gn:feature_code":"PPL",
    "gn:name":"Kampung Pulau Mertajam",
    "gn:population":0,
    "gn:timezone":"Asia/Kuala_Lumpur",
    "iso:country":"MY",
    "name:msa_x_preferred":[
        "Kampung Pulau Mertajam"
    ],
    "name:und_x_variant":[
        "Pulau Mertajam",
        "Kampong Pulau Mertajam"
    ],
    "wof:name":"Kampung Pulau Mertajam",
    "wof:placetype":"locality"
},
  "geometry": {"coordinates":[100.36284999999999,5.57294],"type":"Point"}
}