{
  "type": "Feature",
  "properties": {
    "gn:admin1_code":"7",
    "gn:asciiname":"Kampong Beluru",
    "gn:cc2":"MY",
    "gn:country_code":"MY",
    "gn:dem":47,
    "gn:feature_class":"P",
    "gn:feature_code":"PPL",
    "gn:name":"Kampong Beluru",
    "gn:population":0,
    "gn:timezone":"Asia/Kuala_Lumpur",
    "iso:country":"MY",
    "name:und_x_variant":[
        "Kampong Beturu",
        "Kampong Beluru"
    ],
    "wof:name":"Kampong Beluru",
    "wof:placetype":"locality"
},
  "geometry": {"coordinates":[100.95,4.81667],"type":"Point"}
}