{
  "type": "Feature",
  "properties": {
    "gn:admin1_code":"11",
    "gn:asciiname":"Kampong Remun",
    "gn:country_code":"MY",
    "gn:dem":28,
    "gn:feature_class":"P",
    "gn:feature_code":"PPL",
    "gn:name":"Kampong Remun",
    "gn:population":0,
    "gn:timezone":"Asia/Kuching",
    "iso:country":"MY",
    "wof:name":"Kampong Remun",
    "wof:placetype":"locality"
},
  "geometry": {"coordinates":[110.65000000000001,1.15],"type":"Point"}
}