{
  "type": "Feature",
  "properties": {
    "gn:admin1_code":"11",
    "gn:asciiname":"Rumah Beriak",
    "gn:cc2":"MY",
    "gn:country_code":"MY",
    "gn:dem":106,
    "gn:feature_class":"P",
    "gn:feature_code":"PPL",
    "gn:name":"Rumah Beriak",
    "gn:population":0,
    "gn:timezone":"Asia/Kuching",
    "iso:country":"MY",
    "name:und_x_variant":[
        "Rumah Briak",
        "Rumah Beriak"
    ],
    "wof:name":"Rumah Beriak",
    "wof:placetype":"locality"
},
  "geometry": {"coordinates":[112.33333,1.91667],"type":"Point"}
}