{
  "type": "Feature",
  "properties": {
    "gn:admin1_code":"16.0",
    "gn:asciiname":"Kampung Tigat",
    "gn:country_code":"MY",
    "gn:dem":279,
    "gn:feature_class":"P",
    "gn:feature_code":"PPL",
    "gn:name":"Kampung Tigat",
    "gn:population":0,
    "gn:timezone":"Asia/Kuching",
    "iso:country":"MY",
    "name:msa_x_preferred":[
        "Kampung Tigat"
    ],
    "wof:name":"Kampung Tigat",
    "wof:placetype":"locality"
},
  "geometry": {"coordinates":[116.1934,5.3592],"type":"Point"}
}