{
  "type": "Feature",
  "properties": {
    "gn:admin1_code":"6.0",
    "gn:asciiname":"Kampung Biul",
    "gn:country_code":"MY",
    "gn:dem":151,
    "gn:feature_class":"P",
    "gn:feature_code":"PPL",
    "gn:name":"Kampung Biul",
    "gn:population":0,
    "gn:timezone":"Asia/Kuala_Lumpur",
    "iso:country":"MY",
    "name:msa_x_preferred":[
        "Kampung Biul"
    ],
    "wof:name":"Kampung Biul",
    "wof:placetype":"locality"
},
  "geometry": {"coordinates":[102.02,3.945],"type":"Point"}
}