{
  "type": "Feature",
  "properties": {
    "gn:admin1_code":"1.0",
    "gn:asciiname":"Kampung Parit Haji Abdul Karim",
    "gn:country_code":"MY",
    "gn:dem":13,
    "gn:feature_class":"P",
    "gn:feature_code":"PPL",
    "gn:name":"Kampung Parit Haji Abdul Karim",
    "gn:population":0,
    "gn:timezone":"Asia/Kuala_Lumpur",
    "iso:country":"MY",
    "name:msa_x_preferred":[
        "Kampung Parit Haji Abdul Karim"
    ],
    "wof:name":"Kampung Parit Haji Abdul Karim",
    "wof:placetype":"locality"
},
  "geometry": {"coordinates":[103.3578,1.5984],"type":"Point"}
}