{
  "type": "Feature",
  "properties": {
    "gn:admin1_code":"7.0",
    "gn:asciiname":"Kampung Seberang",
    "gn:country_code":"MY",
    "gn:dem":44,
    "gn:feature_class":"P",
    "gn:feature_code":"PPL",
    "gn:name":"Kampung Seberang",
    "gn:population":0,
    "gn:timezone":"Asia/Kuala_Lumpur",
    "iso:country":"MY",
    "name:msa_x_preferred":[
        "Kampung Seberang"
    ],
    "wof:name":"Kampung Seberang",
    "wof:placetype":"locality"
},
  "geometry": {"coordinates":[100.9593,4.8372],"type":"Point"}
}