{
  "type": "Feature",
  "properties": {
    "gn:admin1_code":"2",
    "gn:asciiname":"Kampung Banggol Durian",
    "gn:cc2":"MY",
    "gn:country_code":"MY",
    "gn:dem":31,
    "gn:feature_class":"P",
    "gn:feature_code":"PPL",
    "gn:name":"Kampung Banggol Durian",
    "gn:population":0,
    "gn:timezone":"Asia/Kuala_Lumpur",
    "iso:country":"MY",
    "name:msa_x_preferred":[
        "Kampung Banggol Durian"
    ],
    "name:und_x_variant":[
        "Kampong Banggol Durian"
    ],
    "wof:name":"Kampung Banggol Durian",
    "wof:placetype":"locality"
},
  "geometry": {"coordinates":[100.72521999999999,5.27002],"type":"Point"}
}