{
  "type": "Feature",
  "properties": {
    "gn:admin1_code":"2.0",
    "gn:asciiname":"Taman Sri Tasik",
    "gn:country_code":"MY",
    "gn:dem":5,
    "gn:feature_class":"P",
    "gn:feature_code":"PPL",
    "gn:name":"Taman Sri Tasik",
    "gn:population":0,
    "gn:timezone":"Asia/Kuala_Lumpur",
    "iso:country":"MY",
    "name:msa_x_preferred":[
        "Taman Sri Tasik"
    ],
    "wof:name":"Taman Sri Tasik",
    "wof:placetype":"locality"
},
  "geometry": {"coordinates":[100.48007,5.28897],"type":"Point"}
}