{
  "type": "Feature",
  "properties": {
    "gn:admin1_code":"6.0",
    "gn:asciiname":"Kampung Sungai Siak",
    "gn:country_code":"MY",
    "gn:dem":38,
    "gn:feature_class":"P",
    "gn:feature_code":"PPL",
    "gn:name":"Kampung Sungai Siak",
    "gn:population":0,
    "gn:timezone":"Asia/Kuala_Lumpur",
    "iso:country":"MY",
    "name:msa_x_preferred":[
        "Kampung Sungai Siak"
    ],
    "wof:name":"Kampung Sungai Siak",
    "wof:placetype":"locality"
},
  "geometry": {"coordinates":[102.4413,3.4395],"type":"Point"}
}