{
  "type": "Feature",
  "properties": {
    "gn:admin1_code":"6.0",
    "gn:asciiname":"Kampung Baharu Tada",
    "gn:country_code":"MY",
    "gn:dem":73,
    "gn:feature_class":"P",
    "gn:feature_code":"PPL",
    "gn:name":"Kampung Baharu Tada",
    "gn:population":0,
    "gn:timezone":"Asia/Kuala_Lumpur",
    "iso:country":"MY",
    "name:msa_x_preferred":[
        "Kampung Baharu Tada"
    ],
    "wof:name":"Kampung Baharu Tada",
    "wof:placetype":"locality"
},
  "geometry": {"coordinates":[102.35769999999999,4.161],"type":"Point"}
}