{
  "type": "Feature",
  "properties": {
    "gn:admin1_code":"13",
    "gn:asciiname":"Kampung Kepala Gajah",
    "gn:country_code":"MY",
    "gn:dem":10,
    "gn:feature_class":"P",
    "gn:feature_code":"PPL",
    "gn:name":"Kampung Kepala Gajah",
    "gn:population":0,
    "gn:timezone":"Asia/Kuala_Lumpur",
    "iso:country":"MY",
    "name:msa_x_preferred":[
        "Kampung Kepala Gajah"
    ],
    "name:und_x_variant":[
        "Kampong Kepala Gajah"
    ],
    "wof:name":"Kampung Kepala Gajah",
    "wof:placetype":"locality"
},
  "geometry": {"coordinates":[102.61225,5.683],"type":"Point"}
}