{
  "type": "Feature",
  "properties": {
    "gn:admin1_code":"2",
    "gn:asciiname":"Kampong Bukit Karong",
    "gn:country_code":"MY",
    "gn:dem":48,
    "gn:feature_class":"P",
    "gn:feature_code":"PPL",
    "gn:name":"Kampong Bukit Karong",
    "gn:population":0,
    "gn:timezone":"Asia/Kuala_Lumpur",
    "iso:country":"MY",
    "wof:name":"Kampong Bukit Karong",
    "wof:placetype":"locality"
},
  "geometry": {"coordinates":[100.46666999999999,5.73333],"type":"Point"}
}