{
  "type": "Feature",
  "properties": {
    "gn:admin1_code":"11",
    "gn:asciiname":"Kampong Raya",
    "gn:country_code":"MY",
    "gn:dem":491,
    "gn:feature_class":"P",
    "gn:feature_code":"PPL",
    "gn:name":"Kampong Raya",
    "gn:population":0,
    "gn:timezone":"Asia/Kuching",
    "iso:country":"MY",
    "name:und_x_variant":[
        "Tringgus",
        "Kampong Rayah",
        "Kampong Tringgus",
        "Kampong Raya"
    ],
    "wof:name":"Kampong Raya",
    "wof:placetype":"locality"
},
  "geometry": {"coordinates":[110.08631,1.22568],"type":"Point"}
}