{
  "type": "Feature",
  "properties": {
    "gn:admin1_code":"13",
    "gn:asciiname":"Kampung Wakaf Tok Jambai",
    "gn:country_code":"MY",
    "gn:dem":15,
    "gn:feature_class":"P",
    "gn:feature_code":"PPL",
    "gn:name":"Kampung Wakaf Tok Jambai",
    "gn:population":0,
    "gn:timezone":"Asia/Kuala_Lumpur",
    "iso:country":"MY",
    "name:msa_x_preferred":[
        "Kampung Wakaf Tok Jambai"
    ],
    "name:und_x_variant":[
        "To\u2019 Jembai",
        "Tok Jembai",
        "Kampong Wakaf Tok Jambai"
    ],
    "wof:name":"Kampung Wakaf Tok Jambai",
    "wof:placetype":"locality"
},
  "geometry": {"coordinates":[103.1024,5.3962],"type":"Point"}
}