{
  "type": "Feature",
  "properties": {
    "gn:admin1_code":"11.0",
    "gn:asciiname":"Long Sukang",
    "gn:country_code":"MY",
    "gn:dem":387,
    "gn:feature_class":"P",
    "gn:feature_code":"PPL",
    "gn:name":"Long Sukang",
    "gn:population":0,
    "gn:timezone":"Asia/Kuching",
    "iso:country":"MY",
    "name:msa_x_preferred":[
        "Long Sukang"
    ],
    "name:und_x_variant":[
        "Sukang"
    ],
    "wof:name":"Long Sukang",
    "wof:placetype":"locality"
},
  "geometry": {"coordinates":[115.4889,4.5528],"type":"Point"}
}