{
  "type": "Feature",
  "properties": {
    "gn:admin1_code":"2.0",
    "gn:asciiname":"Taman Keranji",
    "gn:country_code":"MY",
    "gn:dem":57,
    "gn:feature_class":"P",
    "gn:feature_code":"PPL",
    "gn:name":"Taman Keranji",
    "gn:population":0,
    "gn:timezone":"Asia/Kuala_Lumpur",
    "iso:country":"MY",
    "name:msa_x_preferred":[
        "Taman Keranji"
    ],
    "wof:name":"Taman Keranji",
    "wof:placetype":"locality"
},
  "geometry": {"coordinates":[100.53801,5.3685],"type":"Point"}
}