{
  "type": "Feature",
  "properties": {
    "gn:admin1_code":"1.0",
    "gn:asciiname":"Taman Pertama",
    "gn:country_code":"MY",
    "gn:dem":30,
    "gn:feature_class":"P",
    "gn:feature_code":"PPL",
    "gn:name":"Taman Pertama",
    "gn:population":0,
    "gn:timezone":"Asia/Kuala_Lumpur",
    "iso:country":"MY",
    "name:msa_x_preferred":[
        "Taman Pertama"
    ],
    "wof:name":"Taman Pertama",
    "wof:placetype":"locality"
},
  "geometry": {"coordinates":[103.5882,1.6685],"type":"Point"}
}