{
  "type": "Feature",
  "properties": {
    "gn:admin1_code":"6.0",
    "gn:asciiname":"Kemajuan Tanah Kampung Awah",
    "gn:country_code":"MY",
    "gn:dem":63,
    "gn:feature_class":"P",
    "gn:feature_code":"PPL",
    "gn:name":"Kemajuan Tanah Kampung Awah",
    "gn:population":0,
    "gn:timezone":"Asia/Kuala_Lumpur",
    "iso:country":"MY",
    "name:msa_x_preferred":[
        "Kemajuan Tanah Kampung Awah"
    ],
    "wof:name":"Kemajuan Tanah Kampung Awah",
    "wof:placetype":"locality"
},
  "geometry": {"coordinates":[102.5264,3.507],"type":"Point"}
}