{
  "type": "Feature",
  "properties": {
    "gn:admin1_code":"4.0",
    "gn:asciiname":"Kampung Bukit Piatu",
    "gn:country_code":"MY",
    "gn:dem":5,
    "gn:feature_class":"P",
    "gn:feature_code":"PPL",
    "gn:name":"Kampung Bukit Piatu",
    "gn:population":0,
    "gn:timezone":"Asia/Kuala_Lumpur",
    "iso:country":"MY",
    "name:msa_x_preferred":[
        "Kampung Bukit Piatu"
    ],
    "wof:name":"Kampung Bukit Piatu",
    "wof:placetype":"locality"
},
  "geometry": {"coordinates":[102.2765,2.2068],"type":"Point"}
}