{
  "type": "Feature",
  "properties": {
    "gn:admin1_code":"5",
    "gn:asciiname":"Kampung Merbau Sembilan",
    "gn:country_code":"MY",
    "gn:dem":34,
    "gn:feature_class":"P",
    "gn:feature_code":"PPL",
    "gn:name":"Kampung Merbau Sembilan",
    "gn:population":0,
    "gn:timezone":"Asia/Kuala_Lumpur",
    "iso:country":"MY",
    "name:msa_x_preferred":[
        "Kampung Merbau Sembilan"
    ],
    "name:und_x_variant":[
        "Kampong Merbau Sembilan"
    ],
    "wof:name":"Kampung Merbau Sembilan",
    "wof:placetype":"locality"
},
  "geometry": {"coordinates":[102.0517,2.563],"type":"Point"}
}