{
  "type": "Feature",
  "properties": {
    "gn:admin1_code":"16.0",
    "gn:asciiname":"Tagong",
    "gn:country_code":"MY",
    "gn:dem":12,
    "gn:feature_class":"P",
    "gn:feature_code":"PPL",
    "gn:name":"Tagong",
    "gn:population":0,
    "gn:timezone":"Asia/Kuching",
    "iso:country":"MY",
    "name:msa_x_preferred":[
        "Tagong"
    ],
    "name:zho_x_preferred":[
        "\u5854\u516c\u4e61"
    ],
    "wof:name":"Tagong",
    "wof:placetype":"locality"
},
  "geometry": {"coordinates":[116.7882,6.5209],"type":"Point"}
}