{
  "type": "Feature",
  "properties": {
    "gn:admin1_code":"13",
    "gn:asciiname":"Kampung Jawa",
    "gn:country_code":"MY",
    "gn:dem":14,
    "gn:feature_class":"P",
    "gn:feature_code":"PPL",
    "gn:name":"Kampung Jawa",
    "gn:population":0,
    "gn:timezone":"Asia/Kuala_Lumpur",
    "iso:country":"MY",
    "name:msa_x_preferred":[
        "Kampung Jawa"
    ],
    "name:und_x_variant":[
        "Kampong Jawa"
    ],
    "wof:name":"Kampung Jawa",
    "wof:placetype":"locality"
},
  "geometry": {"coordinates":[103.2914,4.2239],"type":"Point"}
}