{
  "type": "Feature",
  "properties": {
    "gn:admin1_code":"5.0",
    "gn:asciiname":"Kampung Ulu Inas",
    "gn:country_code":"MY",
    "gn:dem":132,
    "gn:feature_class":"P",
    "gn:feature_code":"PPL",
    "gn:name":"Kampung Ulu Inas",
    "gn:population":0,
    "gn:timezone":"Asia/Kuala_Lumpur",
    "iso:country":"MY",
    "name:msa_x_preferred":[
        "Kampung Ulu Inas"
    ],
    "name:und_x_variant":[
        "Kampong Ulu Inas",
        "Kampung Hulu Inas"
    ],
    "wof:name":"Kampung Ulu Inas",
    "wof:placetype":"locality"
},
  "geometry": {"coordinates":[102.2337,2.642],"type":"Point"}
}