{
  "type": "Feature",
  "properties": {
    "gn:admin1_code":"4.0",
    "gn:asciiname":"Mata Kucing",
    "gn:country_code":"MY",
    "gn:dem":16,
    "gn:feature_class":"P",
    "gn:feature_code":"PPL",
    "gn:name":"Mata Kucing",
    "gn:population":0,
    "gn:timezone":"Asia/Kuala_Lumpur",
    "iso:country":"MY",
    "name:msa_x_preferred":[
        "Mata Kucing"
    ],
    "wof:name":"Mata Kucing",
    "wof:placetype":"locality"
},
  "geometry": {"coordinates":[102.26091,2.22001],"type":"Point"}
}