{
  "type": "Feature",
  "properties": {
    "gn:admin1_code":"1",
    "gn:asciiname":"Kampung Tenggayon",
    "gn:country_code":"MY",
    "gn:dem":13,
    "gn:feature_class":"P",
    "gn:feature_code":"PPL",
    "gn:name":"Kampung Tenggayon",
    "gn:population":0,
    "gn:timezone":"Asia/Kuala_Lumpur",
    "iso:country":"MY",
    "name:msa_x_preferred":[
        "Kampung Tenggayon"
    ],
    "name:und_x_variant":[
        "Kampong Tigong",
        "Kampong Tenggayon"
    ],
    "wof:name":"Kampung Tenggayon",
    "wof:placetype":"locality"
},
  "geometry": {"coordinates":[103.4281,1.4633],"type":"Point"}
}