{
  "type": "Feature",
  "properties": {
    "gn:admin1_code":"2",
    "gn:asciiname":"Kampung Gua Tinggi",
    "gn:cc2":"MY",
    "gn:country_code":"MY",
    "gn:dem":31,
    "gn:feature_class":"P",
    "gn:feature_code":"PPL",
    "gn:name":"Kampung Gua Tinggi",
    "gn:population":0,
    "gn:timezone":"Asia/Kuala_Lumpur",
    "iso:country":"MY",
    "name:msa_x_preferred":[
        "Kampung Gua Tinggi"
    ],
    "name:und_x_variant":[
        "Gua Tinggi",
        "Kampong Kerchut",
        "Kampong Gua Tinggi"
    ],
    "wof:name":"Kampung Gua Tinggi",
    "wof:placetype":"locality"
},
  "geometry": {"coordinates":[100.69529,5.65006],"type":"Point"}
}