{
  "type": "Feature",
  "properties": {
    "gn:admin1_code":"7",
    "gn:asciiname":"Kampung Keledang Kanan",
    "gn:country_code":"MY",
    "gn:dem":53,
    "gn:feature_class":"P",
    "gn:feature_code":"PPL",
    "gn:name":"Kampung Keledang Kanan",
    "gn:population":0,
    "gn:timezone":"Asia/Kuala_Lumpur",
    "iso:country":"MY",
    "name:msa_x_preferred":[
        "Kampung Keledang Kanan"
    ],
    "name:und_x_variant":[
        "Kampong Kledang",
        "Kampong Keledang"
    ],
    "wof:name":"Kampung Keledang Kanan",
    "wof:placetype":"locality"
},
  "geometry": {"coordinates":[100.9597,4.8085],"type":"Point"}
}