{
  "type": "Feature",
  "properties": {
    "gn:admin1_code":"2.0",
    "gn:asciiname":"Senara",
    "gn:cc2":"MY",
    "gn:country_code":"MY",
    "gn:dem":5,
    "gn:feature_class":"P",
    "gn:feature_code":"PPL",
    "gn:name":"Senara",
    "gn:population":0,
    "gn:timezone":"Asia/Kuala_Lumpur",
    "iso:country":"MY",
    "name:und_x_variant":[
        "Kampong Senara",
        "Senara"
    ],
    "wof:name":"Senara",
    "wof:placetype":"locality"
},
  "geometry": {"coordinates":[100.53333000000001,6.06667],"type":"Point"}
}