{
  "type": "Feature",
  "properties": {
    "gn:admin1_code":"1",
    "gn:asciiname":"Kampung Roscote",
    "gn:country_code":"MY",
    "gn:dem":57,
    "gn:feature_class":"P",
    "gn:feature_code":"PPL",
    "gn:name":"Kampung Roscote",
    "gn:population":0,
    "gn:timezone":"Asia/Kuala_Lumpur",
    "iso:country":"MY",
    "name:msa_x_preferred":[
        "Kampung Roscote"
    ],
    "name:und_x_variant":[
        "Roscote",
        "Roscote Village"
    ],
    "wof:name":"Kampung Roscote",
    "wof:placetype":"locality"
},
  "geometry": {"coordinates":[103.6935,1.6682],"type":"Point"}
}