{
  "type": "Feature",
  "properties": {
    "gn:admin1_code":"16",
    "gn:asciiname":"Gua Paka",
    "gn:country_code":"MY",
    "gn:dem":3326,
    "gn:feature_class":"P",
    "gn:feature_code":"PPL",
    "gn:name":"Gua Paka",
    "gn:population":0,
    "gn:timezone":"Asia/Kuching",
    "iso:country":"MY",
    "name:und_x_variant":[
        "Raka Cave",
        "Gua Paka",
        "Paka Cave"
    ],
    "wof:name":"Gua Paka",
    "wof:placetype":"locality"
},
  "geometry": {"coordinates":[116.56637000000001,6.06034],"type":"Point"}
}