{
  "type": "Feature",
  "properties": {
    "gn:admin1_code":"13",
    "gn:asciiname":"Kampung Pengkalan Leban",
    "gn:country_code":"MY",
    "gn:dem":23,
    "gn:feature_class":"P",
    "gn:feature_code":"PPL",
    "gn:name":"Kampung Pengkalan Leban",
    "gn:population":0,
    "gn:timezone":"Asia/Kuala_Lumpur",
    "iso:country":"MY",
    "name:msa_x_preferred":[
        "Kampung Pengkalan Leban"
    ],
    "name:und_x_variant":[
        "Kampong Pengkalan Leban"
    ],
    "wof:name":"Kampung Pengkalan Leban",
    "wof:placetype":"locality"
},
  "geometry": {"coordinates":[102.8682,5.3446],"type":"Point"}
}