{
  "type": "Feature",
  "properties": {
    "gn:admin1_code":"12",
    "gn:asciiname":"Kampung Batu Tiga Puloh Enam",
    "gn:country_code":"MY",
    "gn:dem":6,
    "gn:feature_class":"P",
    "gn:feature_code":"PPL",
    "gn:name":"Kampung Batu Tiga Puloh Enam",
    "gn:population":0,
    "gn:timezone":"Asia/Kuala_Lumpur",
    "iso:country":"MY",
    "name:msa_x_preferred":[
        "Kampung Batu Tiga Puloh Enam"
    ],
    "name:und_x_variant":[
        "Kampong Batu Thirty-six"
    ],
    "wof:name":"Kampung Batu Tiga Puloh Enam",
    "wof:placetype":"locality"
},
  "geometry": {"coordinates":[100.9388,3.7307],"type":"Point"}
}