{
  "type": "Feature",
  "properties": {
    "gn:admin1_code":"1.0",
    "gn:asciiname":"Taman Sri Senai",
    "gn:country_code":"MY",
    "gn:dem":23,
    "gn:feature_class":"P",
    "gn:feature_code":"PPL",
    "gn:name":"Taman Sri Senai",
    "gn:population":0,
    "gn:timezone":"Asia/Kuala_Lumpur",
    "iso:country":"MY",
    "name:msa_x_preferred":[
        "Taman Sri Senai"
    ],
    "wof:name":"Taman Sri Senai",
    "wof:placetype":"locality"
},
  "geometry": {"coordinates":[103.6554,1.6132],"type":"Point"}
}