{
  "type": "Feature",
  "properties": {
    "gn:admin1_code":"13.0",
    "gn:asciiname":"Kampung Bukit Kecil",
    "gn:country_code":"MY",
    "gn:dem":19,
    "gn:feature_class":"P",
    "gn:feature_code":"PPL",
    "gn:name":"Kampung Bukit Kecil",
    "gn:population":0,
    "gn:timezone":"Asia/Kuala_Lumpur",
    "iso:country":"MY",
    "name:msa_x_preferred":[
        "Kampung Bukit Kecil"
    ],
    "wof:name":"Kampung Bukit Kecil",
    "wof:placetype":"locality"
},
  "geometry": {"coordinates":[103.2731,5.0306],"type":"Point"}
}