{
  "type": "Feature",
  "properties": {
    "gn:admin1_code":"16.0",
    "gn:asciiname":"Kampung Libang",
    "gn:country_code":"MY",
    "gn:dem":503,
    "gn:feature_class":"P",
    "gn:feature_code":"PPL",
    "gn:name":"Kampung Libang",
    "gn:population":0,
    "gn:timezone":"Asia/Kuching",
    "iso:country":"MY",
    "name:msa_x_preferred":[
        "Kampung Libang"
    ],
    "wof:name":"Kampung Libang",
    "wof:placetype":"locality"
},
  "geometry": {"coordinates":[116.693,5.9675],"type":"Point"}
}