{
  "type": "Feature",
  "properties": {
    "gn:admin1_code":"5.0",
    "gn:asciiname":"Kemajuan Tanah Pasoh Satu",
    "gn:country_code":"MY",
    "gn:dem":89,
    "gn:feature_class":"P",
    "gn:feature_code":"PPL",
    "gn:name":"Kemajuan Tanah Pasoh Satu",
    "gn:population":0,
    "gn:timezone":"Asia/Kuala_Lumpur",
    "iso:country":"MY",
    "name:msa_x_preferred":[
        "Kemajuan Tanah Pasoh Satu"
    ],
    "wof:name":"Kemajuan Tanah Pasoh Satu",
    "wof:placetype":"locality"
},
  "geometry": {"coordinates":[102.267,3.0204],"type":"Point"}
}