{
  "type": "Feature",
  "properties": {
    "gn:admin1_code":"11",
    "gn:asciiname":"Patau",
    "gn:country_code":"MY",
    "gn:dem":13,
    "gn:feature_class":"P",
    "gn:feature_code":"PPL",
    "gn:name":"Patau",
    "gn:population":0,
    "gn:timezone":"Asia/Kuching",
    "iso:country":"MY",
    "name:fin_x_preferred":[
        "Patau"
    ],
    "wof:name":"Patau",
    "wof:placetype":"locality"
},
  "geometry": {"coordinates":[113.59999999999999,3.76667],"type":"Point"}
}