{
  "type": "Feature",
  "properties": {
    "gn:admin1_code":"13",
    "gn:asciiname":"Kampung Tok Randok",
    "gn:country_code":"MY",
    "gn:dem":24,
    "gn:feature_class":"P",
    "gn:feature_code":"PPL",
    "gn:name":"Kampung Tok Randok",
    "gn:population":0,
    "gn:timezone":"Asia/Kuala_Lumpur",
    "iso:country":"MY",
    "name:msa_x_preferred":[
        "Kampung Tok Randok"
    ],
    "name:und_x_variant":[
        "Kampong Tok Randok"
    ],
    "wof:name":"Kampung Tok Randok",
    "wof:placetype":"locality"
},
  "geometry": {"coordinates":[103.1018,5.0724],"type":"Point"}
}