{
  "type": "Feature",
  "properties": {
    "gn:admin1_code":"16",
    "gn:asciiname":"Kampung Bulad",
    "gn:country_code":"MY",
    "gn:dem":285,
    "gn:feature_class":"P",
    "gn:feature_code":"PPL",
    "gn:name":"Kampung Bulad",
    "gn:population":0,
    "gn:timezone":"Asia/Kuching",
    "iso:country":"MY",
    "name:msa_x_preferred":[
        "Kampung Bulad"
    ],
    "name:und_x_variant":[
        "Kampong Bulad"
    ],
    "wof:name":"Kampung Bulad",
    "wof:placetype":"locality"
},
  "geometry": {"coordinates":[116.684,6.5662],"type":"Point"}
}