{
  "type": "Feature",
  "properties": {
    "gn:admin1_code":"6.0",
    "gn:asciiname":"Kampung Denai",
    "gn:country_code":"MY",
    "gn:dem":12,
    "gn:feature_class":"P",
    "gn:feature_code":"PPL",
    "gn:name":"Kampung Denai",
    "gn:population":0,
    "gn:timezone":"Asia/Kuala_Lumpur",
    "iso:country":"MY",
    "name:msa_x_preferred":[
        "Kampung Denai"
    ],
    "name:und_x_variant":[
        "Denai"
    ],
    "wof:name":"Kampung Denai",
    "wof:placetype":"locality"
},
  "geometry": {"coordinates":[103.60556,2.58861],"type":"Point"}
}