{
  "type": "Feature",
  "properties": {
    "gn:admin1_code":"6",
    "gn:asciiname":"Kampung Sungai Sekur",
    "gn:country_code":"MY",
    "gn:dem":12,
    "gn:feature_class":"P",
    "gn:feature_code":"PPL",
    "gn:name":"Kampung Sungai Sekur",
    "gn:population":0,
    "gn:timezone":"Asia/Kuala_Lumpur",
    "iso:country":"MY",
    "name:msa_x_preferred":[
        "Kampung Sungai Sekur"
    ],
    "name:und_x_variant":[
        "Kampong Sekor"
    ],
    "wof:name":"Kampung Sungai Sekur",
    "wof:placetype":"locality"
},
  "geometry": {"coordinates":[103.318,3.5281],"type":"Point"}
}