{
  "type": "Feature",
  "properties": {
    "gn:admin1_code":"1.0",
    "gn:asciiname":"Simpang Empat",
    "gn:country_code":"MY",
    "gn:dem":7,
    "gn:feature_class":"P",
    "gn:feature_code":"PPL",
    "gn:name":"Simpang Empat",
    "gn:population":0,
    "gn:timezone":"Asia/Kuala_Lumpur",
    "iso:country":"MY",
    "name:ind_x_preferred":[
        "Simpang Empat"
    ],
    "name:msa_x_preferred":[
        "Simpang Empat"
    ],
    "name:nld_x_preferred":[
        "Simpang Empat"
    ],
    "wof:name":"Simpang Empat",
    "wof:placetype":"locality"
},
  "geometry": {"coordinates":[102.61920000000001,2.0595],"type":"Point"}
}