{
  "type": "Feature",
  "properties": {
    "gn:admin1_code":"7.0",
    "gn:asciiname":"Kampung Melayu Langkap",
    "gn:country_code":"MY",
    "gn:dem":12,
    "gn:feature_class":"P",
    "gn:feature_code":"PPL",
    "gn:name":"Kampung Melayu Langkap",
    "gn:population":0,
    "gn:timezone":"Asia/Kuala_Lumpur",
    "iso:country":"MY",
    "name:msa_x_preferred":[
        "Kampung Melayu Langkap"
    ],
    "name:und_x_variant":[
        "Kampung Langkap"
    ],
    "wof:name":"Kampung Melayu Langkap",
    "wof:placetype":"locality"
},
  "geometry": {"coordinates":[101.1434,4.0636],"type":"Point"}
}