{
  "type": "Feature",
  "properties": {
    "gn:gn_country":"MY",
    "gn:gn_fcode":"PPL",
    "gn:gn_pop":0,
    "iso:country":"MY",
    "name:eng_x_preferred":[
        "Sintok"
    ],
    "name:ind_x_preferred":[
        "Sintok"
    ],
    "name:jav_x_preferred":[
        "Sintok"
    ],
    "name:msa_x_preferred":[
        "Sintok"
    ],
    "name:nld_x_preferred":[
        "Sintok"
    ],
    "name:unk_x_variant":[
        "Sintok"
    ],
    "name:zho_x_preferred":[
        "\u8f9b\u6258\u514b"
    ],
    "qs_pg:aaroncc":"MY",
    "qs_pg:gn_country":"MY",
    "qs_pg:gn_fcode":"PPL",
    "qs_pg:gn_pop":0,
    "qs_pg:name":"Sintuk",
    "qs_pg:name_adm0":"Malaysia",
    "qs_pg:name_adm1":"Kedah",
    "qs_pg:photos_9r":0,
    "qs_pg:photos_sr":0,
    "qs_pg:pop_sr":0,
    "qs_pg:qs_pg_placetype":"locality",
    "qs_pg:qs_pg_placetype_gp":"Town",
    "qs_pg:woe_adm0":23424901,
    "woe:adm0_id":23424901,
    "woe:name_adm0":"Malaysia",
    "woe:name_adm1":"Kedah",
    "woe:placetype":"Town",
    "wof:name":"Sintuk",
    "wof:placetype":"locality"
},
  "geometry": {"coordinates":[100.5235,6.44233],"type":"Point"}
}