{
  "type": "Feature",
  "properties": {
    "gn:admin1_code":"1",
    "gn:asciiname":"Kampung Batu Hampar",
    "gn:country_code":"MY",
    "gn:dem":30,
    "gn:feature_class":"P",
    "gn:feature_code":"PPL",
    "gn:name":"Kampung Batu Hampar",
    "gn:population":0,
    "gn:timezone":"Asia/Kuala_Lumpur",
    "iso:country":"MY",
    "name:msa_x_preferred":[
        "Kampung Batu Hampar"
    ],
    "name:und_x_variant":[
        "Kampong Batu Hampar"
    ],
    "wof:name":"Kampung Batu Hampar",
    "wof:placetype":"locality"
},
  "geometry": {"coordinates":[102.8058,2.5105],"type":"Point"}
}