{
  "type": "Feature",
  "properties": {
    "gn:admin1_code":"8.0",
    "gn:asciiname":"Kampung Guar Ujang Batu",
    "gn:cc2":"MY",
    "gn:country_code":"MY",
    "gn:dem":7,
    "gn:feature_class":"P",
    "gn:feature_code":"PPL",
    "gn:name":"Kampung Guar Ujang Batu",
    "gn:population":0,
    "gn:timezone":"Asia/Kuala_Lumpur",
    "iso:country":"MY",
    "name:msa_x_preferred":[
        "Kampung Guar Ujang Batu"
    ],
    "wof:name":"Kampung Guar Ujang Batu",
    "wof:placetype":"locality"
},
  "geometry": {"coordinates":[100.20381999999999,6.40823],"type":"Point"}
}