{
  "type": "Feature",
  "properties": {
    "gn:admin1_code":"12.0",
    "gn:asciiname":"Kampung Melayu Batu Enam Belas",
    "gn:country_code":"MY",
    "gn:dem":46,
    "gn:feature_class":"P",
    "gn:feature_code":"PPL",
    "gn:name":"Kampung Melayu Batu Enam Belas",
    "gn:population":0,
    "gn:timezone":"Asia/Kuala_Lumpur",
    "iso:country":"MY",
    "name:msa_x_preferred":[
        "Kampung Melayu Batu Enam Belas"
    ],
    "wof:name":"Kampung Melayu Batu Enam Belas",
    "wof:placetype":"locality"
},
  "geometry": {"coordinates":[101.5962,3.3069],"type":"Point"}
}