{
  "type": "Feature",
  "properties": {
    "gn:admin1_code":"6.0",
    "gn:asciiname":"Kampung Kenau",
    "gn:country_code":"MY",
    "gn:dem":155,
    "gn:feature_class":"P",
    "gn:feature_code":"PPL",
    "gn:name":"Kampung Kenau",
    "gn:population":0,
    "gn:timezone":"Asia/Kuala_Lumpur",
    "iso:country":"MY",
    "name:msa_x_preferred":[
        "Kampung Kenau"
    ],
    "wof:name":"Kampung Kenau",
    "wof:placetype":"locality"
},
  "geometry": {"coordinates":[102.0201,3.9487],"type":"Point"}
}