{
  "type": "Feature",
  "properties": {
    "gn:admin1_code":"13",
    "gn:asciiname":"Kampung Bukit Gharu",
    "gn:country_code":"MY",
    "gn:dem":31,
    "gn:feature_class":"P",
    "gn:feature_code":"PPL",
    "gn:name":"Kampung Bukit Gharu",
    "gn:population":0,
    "gn:timezone":"Asia/Kuala_Lumpur",
    "iso:country":"MY",
    "name:msa_x_preferred":[
        "Kampung Bukit Gharu"
    ],
    "name:und_x_variant":[
        "Kampong Bukit Gharu"
    ],
    "wof:name":"Kampung Bukit Gharu",
    "wof:placetype":"locality"
},
  "geometry": {"coordinates":[102.8189,5.3699],"type":"Point"}
}