{
  "type": "Feature",
  "properties": {
    "gn:admin1_code":"13",
    "gn:asciiname":"Kampung Tetambah",
    "gn:country_code":"MY",
    "gn:dem":11,
    "gn:feature_class":"P",
    "gn:feature_code":"PPL",
    "gn:name":"Kampung Tetambah",
    "gn:population":0,
    "gn:timezone":"Asia/Kuala_Lumpur",
    "iso:country":"MY",
    "name:msa_x_preferred":[
        "Kampung Tetambah"
    ],
    "name:und_x_variant":[
        "Kampong Tetambah"
    ],
    "wof:name":"Kampung Tetambah",
    "wof:placetype":"locality"
},
  "geometry": {"coordinates":[103.04519999999999,5.3049],"type":"Point"}
}