{
  "type": "Feature",
  "properties": {
    "gn:admin1_code":"1",
    "gn:asciiname":"Kampung Bukit Tunggal",
    "gn:country_code":"MY",
    "gn:dem":19,
    "gn:feature_class":"P",
    "gn:feature_code":"PPL",
    "gn:name":"Kampung Bukit Tunggal",
    "gn:population":0,
    "gn:timezone":"Asia/Kuala_Lumpur",
    "iso:country":"MY",
    "name:msa_x_preferred":[
        "Kampung Bukit Tunggal"
    ],
    "name:und_x_variant":[
        "Kampong Bukit Tunggal"
    ],
    "wof:name":"Kampung Bukit Tunggal",
    "wof:placetype":"locality"
},
  "geometry": {"coordinates":[102.73350000000001,2.4697],"type":"Point"}
}