{
  "type": "Feature",
  "properties": {
    "gn:admin1_code":"6",
    "gn:asciiname":"Kampong Tengka Jeram",
    "gn:country_code":"MY",
    "gn:dem":122,
    "gn:feature_class":"P",
    "gn:feature_code":"PPL",
    "gn:name":"Kampong Tengka Jeram",
    "gn:population":0,
    "gn:timezone":"Asia/Kuala_Lumpur",
    "iso:country":"MY",
    "wof:name":"Kampong Tengka Jeram",
    "wof:placetype":"locality"
},
  "geometry": {"coordinates":[101.90000000000001,4.15],"type":"Point"}
}