{
  "type": "Feature",
  "properties": {
    "gn:admin1_code":"5",
    "gn:asciiname":"Kampung Batu Dua",
    "gn:country_code":"MY",
    "gn:dem":7,
    "gn:feature_class":"P",
    "gn:feature_code":"PPL",
    "gn:name":"Kampung Batu Dua",
    "gn:population":0,
    "gn:timezone":"Asia/Kuala_Lumpur",
    "iso:country":"MY",
    "name:msa_x_preferred":[
        "Kampung Batu Dua"
    ],
    "name:und_x_variant":[
        "Kampong Java",
        "Kampong Batu Dua"
    ],
    "wof:name":"Kampung Batu Dua",
    "wof:placetype":"locality"
},
  "geometry": {"coordinates":[101.80786000000001,2.54825],"type":"Point"}
}