{
  "type": "Feature",
  "properties": {
    "gn:admin1_code":"11.0",
    "gn:asciiname":"Muara Tuang",
    "gn:cc2":"MY",
    "gn:country_code":"MY",
    "gn:dem":8,
    "gn:feature_class":"P",
    "gn:feature_code":"PPL",
    "gn:name":"Muara Tuang",
    "gn:population":0,
    "gn:timezone":"Asia/Kuching",
    "iso:country":"MY",
    "name:und_x_variant":[
        "Kampong Muara Tuang",
        "Muara Tuang"
    ],
    "wof:name":"Muara Tuang",
    "wof:placetype":"locality"
},
  "geometry": {"coordinates":[110.48333,1.45],"type":"Point"}
}