{
  "type": "Feature",
  "properties": {
    "gn:country":"MY",
    "gn:fcode":"PPL",
    "gn:pop":0,
    "iso:country":"MY",
    "name:msa_x_preferred":[
        "Kampung Sungai Raya"
    ],
    "qs:name":"Kg. Sungai Raya",
    "qs:name_adm0":"Malaysia",
    "qs:name_adm1":"Selangor",
    "qs:photos":15,
    "qs:photos_1k":3,
    "qs:photos_9k":1,
    "qs:photos_9r":1,
    "qs:photos_all":15,
    "qs:photos_sr":1,
    "qs:placetype":"Suburb",
    "qs:pop_sr":"0",
    "wof:name":"Kg. Sungai Raya",
    "wof:placetype":"neighbourhood",
    "wof:population":0
},
  "geometry": {"coordinates":[102.04259999999999,2.9155],"type":"Point"}
}