{
  "type": "Feature",
  "properties": {
    "gn:admin1_code":"2",
    "gn:asciiname":"Kampung Matang Paku",
    "gn:country_code":"MY",
    "gn:dem":6,
    "gn:feature_class":"P",
    "gn:feature_code":"PPL",
    "gn:name":"Kampung Matang Paku",
    "gn:population":0,
    "gn:timezone":"Asia/Kuala_Lumpur",
    "iso:country":"MY",
    "name:msa_x_preferred":[
        "Kampung Matang Paku"
    ],
    "name:und_x_variant":[
        "Kampong Permatang Paku"
    ],
    "wof:name":"Kampung Matang Paku",
    "wof:placetype":"locality"
},
  "geometry": {"coordinates":[100.27361999999999,6.26251],"type":"Point"}
}