{
  "type": "Feature",
  "properties": {
    "gn:admin1_code":"11",
    "gn:asciiname":"Kampong Merakep",
    "gn:country_code":"MY",
    "gn:dem":240,
    "gn:feature_class":"P",
    "gn:feature_code":"PPL",
    "gn:name":"Kampong Merakep",
    "gn:population":0,
    "gn:timezone":"Asia/Kuching",
    "iso:country":"MY",
    "name:und_x_variant":[
        "Kampong Rayang",
        "Kampong Merakap",
        "Kampung Rudan Rayang"
    ],
    "wof:name":"Kampong Merakep",
    "wof:placetype":"locality"
},
  "geometry": {"coordinates":[110.33768000000001,1.10778],"type":"Point"}
}