{
  "type": "Feature",
  "properties": {
    "gn:admin1_code":"7",
    "gn:asciiname":"Kampung Dedap",
    "gn:country_code":"MY",
    "gn:dem":3,
    "gn:feature_class":"P",
    "gn:feature_code":"PPL",
    "gn:name":"Kampung Dedap",
    "gn:population":0,
    "gn:timezone":"Asia/Kuala_Lumpur",
    "iso:country":"MY",
    "name:und_x_variant":[
        "Kampong Ulu Dudap"
    ],
    "wof:name":"Kampung Dedap",
    "wof:placetype":"locality"
},
  "geometry": {"coordinates":[100.92468,4.08113],"type":"Point"}
}