{
  "type": "Feature",
  "properties": {
    "gn:country":"MY",
    "gn:fcode":"PPL",
    "gn:population":0,
    "iso:country":"MY",
    "name:msa_x_preferred":[
        "Taman Bukit Tiram"
    ],
    "qs:name":"Taman Bukit Tiram",
    "qs:name_adm0":"Malaysia",
    "qs:name_adm1":"Johor",
    "qs:photos_9k":1,
    "qs:photos_9r":1,
    "qs:photos_all":3,
    "qs:photos_sr":0,
    "qs:placetype":"Town",
    "qs:pop_sr":"0",
    "wof:name":"Taman Bukit Tiram",
    "wof:placetype":"locality",
    "wof:population":0
},
  "geometry": {"coordinates":[103.809,1.6064],"type":"Point"}
}