{
  "type": "Feature",
  "properties": {
    "gn:admin1_code":"1.0",
    "gn:asciiname":"Parit Serom Dua",
    "gn:country_code":"MY",
    "gn:dem":11,
    "gn:feature_class":"P",
    "gn:feature_code":"PPL",
    "gn:name":"Parit Serom Dua",
    "gn:population":0,
    "gn:timezone":"Asia/Kuala_Lumpur",
    "iso:country":"MY",
    "name:msa_x_preferred":[
        "Parit Serom Dua"
    ],
    "wof:name":"Parit Serom Dua",
    "wof:placetype":"locality"
},
  "geometry": {"coordinates":[102.5712,2.1854],"type":"Point"}
}