{
  "type": "Feature",
  "properties": {
    "gn:admin1_code":"6",
    "gn:asciiname":"Kampung Jeransang",
    "gn:country_code":"MY",
    "gn:dem":51,
    "gn:feature_class":"P",
    "gn:feature_code":"PPL",
    "gn:name":"Kampung Jeransang",
    "gn:population":0,
    "gn:timezone":"Asia/Kuala_Lumpur",
    "iso:country":"MY",
    "name:msa_x_preferred":[
        "Kampung Jeransang"
    ],
    "name:und_x_variant":[
        "Kampong Jeransang"
    ],
    "wof:name":"Kampung Jeransang",
    "wof:placetype":"locality"
},
  "geometry": {"coordinates":[102.3653,3.8622],"type":"Point"}
}