{
  "type": "Feature",
  "properties": {
    "gn:admin1_code":"1",
    "gn:asciiname":"Kampung Tanjung Che Lahom",
    "gn:country_code":"MY",
    "gn:dem":1,
    "gn:feature_class":"P",
    "gn:feature_code":"PPL",
    "gn:name":"Kampung Tanjung Che Lahom",
    "gn:population":0,
    "gn:timezone":"Asia/Kuala_Lumpur",
    "iso:country":"MY",
    "name:msa_x_preferred":[
        "Kampung Tanjung Che Lahom"
    ],
    "name:und_x_variant":[
        "Kampong Tanjong Che Lahom"
    ],
    "wof:name":"Kampung Tanjung Che Lahom",
    "wof:placetype":"locality"
},
  "geometry": {"coordinates":[104.2574,1.3642],"type":"Point"}
}