{
  "type": "Feature",
  "properties": {
    "gn:admin1_code":"8.0",
    "gn:asciiname":"Kampung Panggas Kechil",
    "gn:country_code":"MY",
    "gn:dem":23,
    "gn:feature_class":"P",
    "gn:feature_code":"PPL",
    "gn:name":"Kampung Panggas Kechil",
    "gn:population":0,
    "gn:timezone":"Asia/Kuala_Lumpur",
    "iso:country":"MY",
    "name:msa_x_preferred":[
        "Kampung Panggas Kechil"
    ],
    "wof:name":"Kampung Panggas Kechil",
    "wof:placetype":"locality"
},
  "geometry": {"coordinates":[100.27786,6.51138],"type":"Point"}
}