{
  "type": "Feature",
  "properties": {
    "gn:admin1_code":"13.0",
    "gn:asciiname":"Taman Rashidah",
    "gn:country_code":"MY",
    "gn:dem":13,
    "gn:feature_class":"P",
    "gn:feature_code":"PPL",
    "gn:name":"Taman Rashidah",
    "gn:population":0,
    "gn:timezone":"Asia/Kuala_Lumpur",
    "iso:country":"MY",
    "name:msa_x_preferred":[
        "Taman Rashidah"
    ],
    "wof:name":"Taman Rashidah",
    "wof:placetype":"locality"
},
  "geometry": {"coordinates":[103.182,5.2507],"type":"Point"}
}