{
  "type": "Feature",
  "properties": {
    "gn:admin1_code":"16",
    "gn:asciiname":"Kampung Losok",
    "gn:country_code":"MY",
    "gn:dem":21,
    "gn:feature_class":"P",
    "gn:feature_code":"PPL",
    "gn:name":"Kampung Losok",
    "gn:population":0,
    "gn:timezone":"Asia/Kuching",
    "iso:country":"MY",
    "name:msa_x_preferred":[
        "Kampung Losok"
    ],
    "name:und_x_variant":[
        "Rosok",
        "Kampong Losok"
    ],
    "wof:name":"Kampung Losok",
    "wof:placetype":"locality"
},
  "geometry": {"coordinates":[116.52160000000001,6.4133],"type":"Point"}
}