{
  "type": "Feature",
  "properties": {
    "gn:admin1_code":"6",
    "gn:asciiname":"Kampung Pia",
    "gn:country_code":"MY",
    "gn:dem":76,
    "gn:feature_class":"P",
    "gn:feature_code":"PPL",
    "gn:name":"Kampung Pia",
    "gn:population":0,
    "gn:timezone":"Asia/Kuala_Lumpur",
    "iso:country":"MY",
    "name:msa_x_preferred":[
        "Kampung Pia"
    ],
    "name:und_x_variant":[
        "Kampong Pia"
    ],
    "wof:name":"Kampung Pia",
    "wof:placetype":"locality"
},
  "geometry": {"coordinates":[102.2119,4.1389],"type":"Point"}
}