{
  "type": "Feature",
  "properties": {
    "gn:admin1_code":"13",
    "gn:asciiname":"Kampung Buluh Gading",
    "gn:country_code":"MY",
    "gn:dem":16,
    "gn:feature_class":"P",
    "gn:feature_code":"PPL",
    "gn:name":"Kampung Buluh Gading",
    "gn:population":0,
    "gn:timezone":"Asia/Kuala_Lumpur",
    "iso:country":"MY",
    "name:und_x_variant":[
        "Kampong Buloh Gading"
    ],
    "wof:name":"Kampung Buluh Gading",
    "wof:placetype":"locality"
},
  "geometry": {"coordinates":[103.27772,4.15738],"type":"Point"}
}