{
  "type": "Feature",
  "properties": {
    "gn:admin1_code":"11.0",
    "gn:asciiname":"Ulu Akup",
    "gn:country_code":"MY",
    "gn:dem":266,
    "gn:feature_class":"P",
    "gn:feature_code":"PPL",
    "gn:name":"Ulu Akup",
    "gn:population":0,
    "gn:timezone":"Asia/Kuching",
    "iso:country":"MY",
    "wof:name":"Ulu Akup",
    "wof:placetype":"locality"
},
  "geometry": {"coordinates":[111.73333,1.46667],"type":"Point"}
}