{
  "type": "Feature",
  "properties": {
    "gn:admin1_code":"2.0",
    "gn:asciiname":"Kampung Parit Masjid",
    "gn:country_code":"MY",
    "gn:dem":7,
    "gn:feature_class":"P",
    "gn:feature_code":"PPL",
    "gn:name":"Kampung Parit Masjid",
    "gn:population":0,
    "gn:timezone":"Asia/Kuala_Lumpur",
    "iso:country":"MY",
    "name:msa_x_preferred":[
        "Kampung Parit Masjid"
    ],
    "wof:name":"Kampung Parit Masjid",
    "wof:placetype":"locality"
},
  "geometry": {"coordinates":[100.38533,6.01715],"type":"Point"}
}