{
  "type": "Feature",
  "properties": {
    "gn:admin1_code":"16",
    "gn:asciiname":"Kampong Melinsun",
    "gn:cc2":"MY",
    "gn:country_code":"MY",
    "gn:dem":6,
    "gn:feature_class":"P",
    "gn:feature_code":"PPL",
    "gn:name":"Kampong Melinsun",
    "gn:population":0,
    "gn:timezone":"Asia/Kuching",
    "iso:country":"MY",
    "name:und_x_variant":[
        "Malinsong",
        "Kampong Melinsun"
    ],
    "wof:name":"Kampong Melinsun",
    "wof:placetype":"locality"
},
  "geometry": {"coordinates":[115.96666999999999,5.76667],"type":"Point"}
}