{
  "type": "Feature",
  "properties": {
    "gn:admin1_code":"16.0",
    "gn:asciiname":"Kampung Mantus",
    "gn:country_code":"MY",
    "gn:dem":58,
    "gn:feature_class":"P",
    "gn:feature_code":"PPL",
    "gn:name":"Kampung Mantus",
    "gn:population":0,
    "gn:timezone":"Asia/Kuching",
    "iso:country":"MY",
    "name:msa_x_preferred":[
        "Kampung Mantus"
    ],
    "wof:name":"Kampung Mantus",
    "wof:placetype":"locality"
},
  "geometry": {"coordinates":[116.9183,6.6094],"type":"Point"}
}