{
  "type": "Feature",
  "properties": {
    "iso:country":"MY",
    "name:deu_x_preferred":[
        "Technische Universit\u00e4t Malaysia"
    ],
    "name:fas_x_preferred":[
        "\u062f\u0627\u0646\u0634\u06af\u0627\u0647 \u0635\u0646\u0639\u062a\u06cc \u0645\u0627\u0644\u0632\u06cc"
    ],
    "name:ind_x_preferred":[
        "Universitas Teknologi Malaysia"
    ],
    "name:msa_x_preferred":[
        "Universiti Teknologi Malaysia"
    ],
    "name:und_x_preferred":[
        "Universiti Teknologi Malaysia"
    ],
    "name:unk_x_variant":[
        "Universiti Teknologi Malaysia"
    ],
    "name:zho_x_preferred":[
        "\u9a6c\u6765\u897f\u4e9a\u5de5\u827a\u5927\u5b66"
    ],
    "qs:gn_adm0_cc":"MY",
    "qs:gn_local":1732752,
    "qs:local_max":681,
    "qs:local_sum":3607,
    "qs:localhoods":29,
    "qs:name":"Universiti Teknologi Malaysia",
    "qs:name_adm0":"Malaysia",
    "qs:name_adm1":"Johor",
    "qs:name_adm2":"Johor Bahru",
    "qs:name_lau":"Senai Kulai",
    "qs:name_local":"Johor Baharu",
    "qs:photo_max":59,
    "qs:photo_sum":154,
    "qs:placetype":"Suburb",
    "qs:quad_count":19,
    "qs:woe_adm0":23424901,
    "qs:woe_adm1":2346296,
    "qs:woe_adm2":56013565,
    "qs:woe_lau":56014537,
    "qs:woe_local":1154698,
    "qs:woe_ver":"7.10.0",
    "wd:wordcount":2060,
    "wof:lang":[
        "unk"
    ],
    "wof:name":"Universiti Teknologi Malaysia",
    "wof:placetype":"neighbourhood"
},
  "geometry": {"coordinates":[103.638437,1.558707],"type":"Point"}
}