{
  "type": "Feature",
  "properties": {
    "iso:country":"MY",
    "name:azb_x_preferred":[
        "\u0645\u0627\u0644\u0632\u06cc \u062a\u06a9\u0646\u0648\u0644\u0648\u0698\u06cc \u0628\u06cc\u0644\u06cc\u0645\u200c\u06cc\u0648\u0631\u062f\u0648"
    ],
    "name:ben_x_preferred":[
        "\u0987\u0989\u09a8\u09bf\u09ad\u09be\u09b0\u09cd\u09b8\u09bf\u099f\u09bf \u0985\u09ac \u099f\u09c7\u0995\u09a8\u09cb\u09b2\u099c\u09bf"
    ],
    "name:deu_x_preferred":[
        "Technische Universit\u00e4t Malaysia"
    ],
    "name:ell_x_preferred":[
        "\u03a4\u03b5\u03c7\u03bd\u03bf\u03bb\u03bf\u03b3\u03b9\u03ba\u03cc \u03a0\u03b1\u03bd\u03b5\u03c0\u03b9\u03c3\u03c4\u03ae\u03bc\u03b9\u03bf \u03c4\u03b7\u03c2 \u039c\u03b1\u03bb\u03b1\u03b9\u03c3\u03af\u03b1\u03c2"
    ],
    "name:eng_x_preferred":[
        "University of Technology Malaysia"
    ],
    "name:fas_x_preferred":[
        "\u062f\u0627\u0646\u0634\u06af\u0627\u0647 \u0635\u0646\u0639\u062a\u06cc \u0645\u0627\u0644\u0632\u06cc"
    ],
    "name:ind_x_preferred":[
        "Universitas Teknologi Malaysia"
    ],
    "name:jpn_x_preferred":[
        "\u30de\u30ec\u30fc\u30b7\u30a2\u6280\u8853\u5927\u5b66"
    ],
    "name:msa_x_preferred":[
        "Universiti Teknologi Malaysia"
    ],
    "name:swe_x_preferred":[
        "University of Technology"
    ],
    "name:tgl_x_preferred":[
        "Unibersidad ng Teknolohiya"
    ],
    "name:und_x_preferred":[
        "Universiti Teknologi Malaysia"
    ],
    "name:unk_x_variant":[
        "Universiti Teknologi Malaysia"
    ],
    "name:zho_x_preferred":[
        "\u9a6c\u6765\u897f\u4e9a\u5de5\u827a\u5927\u5b66"
    ],
    "qs:gn_adm0_cc":"MY",
    "qs:gn_local":1732752,
    "qs:local_max":681,
    "qs:local_sum":3607,
    "qs:localhoods":29,
    "qs:name":"Universiti Teknologi Malaysia",
    "qs:name_adm0":"Malaysia",
    "qs:name_adm1":"Johor",
    "qs:name_adm2":"Johor Bahru",
    "qs:name_lau":"Senai Kulai",
    "qs:name_local":"Johor Baharu",
    "qs:photo_max":59,
    "qs:photo_sum":154,
    "qs:placetype":"Suburb",
    "qs:quad_count":19,
    "qs:woe_adm0":23424901,
    "qs:woe_adm1":2346296,
    "qs:woe_adm2":56013565,
    "qs:woe_lau":56014537,
    "qs:woe_local":1154698,
    "qs:woe_ver":"7.10.0",
    "wd:wordcount":2060,
    "wof:lang":[
        "unk"
    ],
    "wof:name":"Universiti Teknologi Malaysia",
    "wof:placetype":"neighbourhood"
},
  "geometry": {"coordinates":[103.638437,1.558707],"type":"Point"}
}