{
  "type": "Feature",
  "properties": {
    "gn:admin1_code":"9.0",
    "gn:asciiname":"Batu Lintang",
    "gn:cc2":"MY",
    "gn:country_code":"MY",
    "gn:dem":28,
    "gn:feature_class":"P",
    "gn:feature_code":"PPL",
    "gn:name":"Batu Lintang",
    "gn:population":0,
    "gn:timezone":"Asia/Kuala_Lumpur",
    "iso:country":"MY",
    "name:msa_x_preferred":[
        "Batu Lintang"
    ],
    "wof:name":"Batu Lintang",
    "wof:placetype":"locality"
},
  "geometry": {"coordinates":[100.48098,5.38162],"type":"Point"}
}