{
  "type": "Feature",
  "properties": {
    "gn:admin1_code":"16.0",
    "gn:asciiname":"Bakapit",
    "gn:country_code":"MY",
    "gn:dem":13,
    "gn:feature_class":"P",
    "gn:feature_code":"PPL",
    "gn:name":"Bakapit",
    "gn:population":0,
    "gn:timezone":"Asia/Kuching",
    "iso:country":"MY",
    "name:msa_x_preferred":[
        "Bakapit"
    ],
    "wof:name":"Bakapit",
    "wof:placetype":"locality"
},
  "geometry": {"coordinates":[118.5838,4.9573],"type":"Point"}
}