{
  "type": "Feature",
  "properties": {
    "gn:admin1_code":"1",
    "gn:asciiname":"Kampung Sentosa",
    "gn:country_code":"MY",
    "gn:dem":24,
    "gn:feature_class":"P",
    "gn:feature_code":"PPL",
    "gn:name":"Kampung Sentosa",
    "gn:population":0,
    "gn:timezone":"Asia/Kuala_Lumpur",
    "iso:country":"MY",
    "name:msa_x_preferred":[
        "Kampung Sentosa"
    ],
    "name:und_x_variant":[
        "Kampong Sentosa"
    ],
    "wof:name":"Kampung Sentosa",
    "wof:placetype":"locality"
},
  "geometry": {"coordinates":[102.8304,2.2575],"type":"Point"}
}