{
  "type": "Feature",
  "properties": {
    "gn:admin1_code":"16.0",
    "gn:asciiname":"Gahui",
    "gn:country_code":"MY",
    "gn:dem":132,
    "gn:feature_class":"P",
    "gn:feature_code":"PPL",
    "gn:name":"Gahui",
    "gn:population":0,
    "gn:timezone":"Asia/Kuching",
    "iso:country":"MY",
    "wof:name":"Gahui",
    "wof:placetype":"locality"
},
  "geometry": {"coordinates":[116.45,6.18333],"type":"Point"}
}