{
  "type": "Feature",
  "properties": {
    "gn:admin1_code":"7",
    "gn:asciiname":"Kampung Setia",
    "gn:country_code":"MY",
    "gn:dem":71,
    "gn:feature_class":"P",
    "gn:feature_code":"PPL",
    "gn:name":"Kampung Setia",
    "gn:population":0,
    "gn:timezone":"Asia/Kuala_Lumpur",
    "iso:country":"MY",
    "name:msa_x_preferred":[
        "Kampung Setia"
    ],
    "name:und_x_variant":[
        "Kampong Setia"
    ],
    "wof:name":"Kampung Setia",
    "wof:placetype":"locality"
},
  "geometry": {"coordinates":[100.9816,4.8353],"type":"Point"}
}