{
  "type": "Feature",
  "properties": {
    "gn:admin1_code":"1",
    "gn:asciiname":"Kampung Parit Bilah",
    "gn:country_code":"MY",
    "gn:dem":10,
    "gn:feature_class":"P",
    "gn:feature_code":"PPL",
    "gn:name":"Kampung Parit Bilah",
    "gn:population":0,
    "gn:timezone":"Asia/Kuala_Lumpur",
    "iso:country":"MY",
    "name:msa_x_preferred":[
        "Kampung Parit Bilah"
    ],
    "name:und_x_variant":[
        "Kampong Parit Bilah"
    ],
    "wof:name":"Kampung Parit Bilah",
    "wof:placetype":"locality"
},
  "geometry": {"coordinates":[102.66200000000001,2.2008],"type":"Point"}
}