{
  "type": "Feature",
  "properties": {
    "gn:admin1_code":"5",
    "gn:asciiname":"Kampung Telekong",
    "gn:country_code":"MY",
    "gn:dem":114,
    "gn:feature_class":"P",
    "gn:feature_code":"PPL",
    "gn:name":"Kampung Telekong",
    "gn:population":0,
    "gn:timezone":"Asia/Kuala_Lumpur",
    "iso:country":"MY",
    "name:msa_x_preferred":[
        "Kampung Telekong"
    ],
    "name:und_x_variant":[
        "Kampong Telekong"
    ],
    "wof:name":"Kampung Telekong",
    "wof:placetype":"locality"
},
  "geometry": {"coordinates":[102.09910000000001,3.0873],"type":"Point"}
}