{
  "type": "Feature",
  "properties": {
    "gn:admin1_code":"16",
    "gn:asciiname":"Kampung Tiku",
    "gn:country_code":"MY",
    "gn:dem":232,
    "gn:feature_class":"P",
    "gn:feature_code":"PPL",
    "gn:name":"Kampung Tiku",
    "gn:population":0,
    "gn:timezone":"Asia/Kuching",
    "iso:country":"MY",
    "name:msa_x_preferred":[
        "Kampung Tiku"
    ],
    "name:und_x_variant":[
        "Tiku",
        "Kampong Tiku"
    ],
    "wof:name":"Kampung Tiku",
    "wof:placetype":"locality"
},
  "geometry": {"coordinates":[116.1648,5.7868],"type":"Point"}
}