{
  "type": "Feature",
  "properties": {
    "gn:admin1_code":"12.0",
    "gn:asciiname":"Kampung Kuala Kubu Road",
    "gn:country_code":"MY",
    "gn:dem":66,
    "gn:feature_class":"P",
    "gn:feature_code":"PPL",
    "gn:name":"Kampung Kuala Kubu Road",
    "gn:population":0,
    "gn:timezone":"Asia/Kuala_Lumpur",
    "iso:country":"MY",
    "name:msa_x_preferred":[
        "Kampung Kuala Kubu Road"
    ],
    "wof:name":"Kampung Kuala Kubu Road",
    "wof:placetype":"locality"
},
  "geometry": {"coordinates":[101.6232,3.5672],"type":"Point"}
}