{
  "type": "Feature",
  "properties": {
    "gn:admin1_code":"2.0",
    "gn:asciiname":"Kampung Seputeh",
    "gn:country_code":"MY",
    "gn:dem":77,
    "gn:feature_class":"P",
    "gn:feature_code":"PPL",
    "gn:name":"Kampung Seputeh",
    "gn:population":0,
    "gn:timezone":"Asia/Kuala_Lumpur",
    "iso:country":"MY",
    "name:msa_x_preferred":[
        "Kampung Seputeh"
    ],
    "wof:name":"Kampung Seputeh",
    "wof:placetype":"locality"
},
  "geometry": {"coordinates":[100.76005000000001,5.77603],"type":"Point"}
}