{
  "type": "Feature",
  "properties": {
    "gn:admin1_code":"6",
    "gn:asciiname":"Kampong Jering",
    "gn:country_code":"MY",
    "gn:dem":112,
    "gn:feature_class":"P",
    "gn:feature_code":"PPL",
    "gn:name":"Kampong Jering",
    "gn:population":0,
    "gn:timezone":"Asia/Kuala_Lumpur",
    "iso:country":"MY",
    "wof:name":"Kampong Jering",
    "wof:placetype":"locality"
},
  "geometry": {"coordinates":[101.90000000000001,4.16667],"type":"Point"}
}