{
  "type": "Feature",
  "properties": {
    "gn:admin1_code":"7",
    "gn:asciiname":"Kampung Sahum",
    "gn:country_code":"MY",
    "gn:dem":75,
    "gn:feature_class":"P",
    "gn:feature_code":"PPL",
    "gn:name":"Kampung Sahum",
    "gn:population":0,
    "gn:timezone":"Asia/Kuala_Lumpur",
    "iso:country":"MY",
    "name:msa_x_preferred":[
        "Kampung Sahum"
    ],
    "name:und_x_variant":[
        "Kampong Sahum"
    ],
    "wof:name":"Kampung Sahum",
    "wof:placetype":"locality"
},
  "geometry": {"coordinates":[101.22750000000001,4.3689],"type":"Point"}
}