{
  "type": "Feature",
  "properties": {
    "gn:admin1_code":"6",
    "gn:asciiname":"Kampung Jerena",
    "gn:country_code":"MY",
    "gn:dem":36,
    "gn:feature_class":"P",
    "gn:feature_code":"PPL",
    "gn:name":"Kampung Jerena",
    "gn:population":0,
    "gn:timezone":"Asia/Kuala_Lumpur",
    "iso:country":"MY",
    "name:msa_x_preferred":[
        "Kampung Jerena"
    ],
    "name:und_x_variant":[
        "Kampong Jerena"
    ],
    "wof:name":"Kampung Jerena",
    "wof:placetype":"locality"
},
  "geometry": {"coordinates":[102.4575,3.2785],"type":"Point"}
}