{
  "type": "Feature",
  "properties": {
    "gn:admin1_code":"12.0",
    "gn:asciiname":"Taman Sri Ampang",
    "gn:country_code":"MY",
    "gn:dem":65,
    "gn:feature_class":"P",
    "gn:feature_code":"PPL",
    "gn:name":"Taman Sri Ampang",
    "gn:population":0,
    "gn:timezone":"Asia/Kuala_Lumpur",
    "iso:country":"MY",
    "name:msa_x_preferred":[
        "Taman Sri Ampang"
    ],
    "wof:name":"Taman Sri Ampang",
    "wof:placetype":"locality"
},
  "geometry": {"coordinates":[101.7783,3.1437],"type":"Point"}
}