{
  "type": "Feature",
  "properties": {
    "gn:admin1_code":"5.0",
    "gn:asciiname":"Taman Port Dickson Utama",
    "gn:country_code":"MY",
    "gn:dem":22,
    "gn:feature_class":"P",
    "gn:feature_code":"PPL",
    "gn:name":"Taman Port Dickson Utama",
    "gn:population":0,
    "gn:timezone":"Asia/Kuala_Lumpur",
    "iso:country":"MY",
    "name:msa_x_preferred":[
        "Taman Port Dickson Utama"
    ],
    "wof:name":"Taman Port Dickson Utama",
    "wof:placetype":"locality"
},
  "geometry": {"coordinates":[101.8279,2.5184],"type":"Point"}
}