{
  "type": "Feature",
  "properties": {
    "gn:admin1_code":"11",
    "gn:asciiname":"Kampung Teluk Melano",
    "gn:country_code":"MY",
    "gn:dem":-9999,
    "gn:feature_class":"P",
    "gn:feature_code":"PPL",
    "gn:name":"Kampung Teluk Melano",
    "gn:population":0,
    "gn:timezone":"Asia/Kuching",
    "iso:country":"MY",
    "name:und_x_variant":[
        "Melanau",
        "Kampong Milano",
        "Kampong Melano",
        "Kampong Telok Melano",
        "Kampung Teluk Melano"
    ],
    "wof:name":"Kampung Teluk Melano",
    "wof:placetype":"locality"
},
  "geometry": {"coordinates":[109.64570999999999,2.00663],"type":"Point"}
}