{
  "type": "Feature",
  "properties": {
    "gn:admin1_code":"2",
    "gn:asciiname":"Kampung Ketayap",
    "gn:country_code":"MY",
    "gn:dem":3,
    "gn:feature_class":"P",
    "gn:feature_code":"PPL",
    "gn:name":"Kampung Ketayap",
    "gn:population":0,
    "gn:timezone":"Asia/Kuala_Lumpur",
    "iso:country":"MY",
    "name:msa_x_preferred":[
        "Kampung Ketayap"
    ],
    "name:und_x_variant":[
        "Kampong Ketayap"
    ],
    "wof:name":"Kampung Ketayap",
    "wof:placetype":"locality"
},
  "geometry": {"coordinates":[100.33338000000001,6.12413],"type":"Point"}
}