{
  "type": "Feature",
  "properties": {
    "gn:admin1_code":"16",
    "gn:asciiname":"Kampung Pantai",
    "gn:country_code":"MY",
    "gn:dem":976,
    "gn:feature_class":"P",
    "gn:feature_code":"PPL",
    "gn:name":"Kampung Pantai",
    "gn:population":0,
    "gn:timezone":"Asia/Kuching",
    "iso:country":"MY",
    "name:msa_x_preferred":[
        "Kampung Pantai"
    ],
    "name:und_x_variant":[
        "Kampong Pantai"
    ],
    "wof:name":"Kampung Pantai",
    "wof:placetype":"locality"
},
  "geometry": {"coordinates":[116.3394,5.8789],"type":"Point"}
}