{
  "type": "Feature",
  "properties": {
    "gn:admin1_code":"13.0",
    "gn:asciiname":"Batu Dua Puluh Tiga",
    "gn:country_code":"MY",
    "gn:dem":24,
    "gn:feature_class":"P",
    "gn:feature_code":"PPL",
    "gn:name":"Batu Dua Puluh Tiga",
    "gn:population":0,
    "gn:timezone":"Asia/Kuala_Lumpur",
    "iso:country":"MY",
    "name:msa_x_preferred":[
        "Batu Dua Puluh Tiga"
    ],
    "wof:name":"Batu Dua Puluh Tiga",
    "wof:placetype":"locality"
},
  "geometry": {"coordinates":[103.0363,5.0716],"type":"Point"}
}