{
  "type": "Feature",
  "properties": {
    "gn:admin1_code":"2.0",
    "gn:asciiname":"Kampung Kelang Ketapan",
    "gn:cc2":"MY",
    "gn:country_code":"MY",
    "gn:dem":61,
    "gn:feature_class":"P",
    "gn:feature_code":"PPL",
    "gn:name":"Kampung Kelang Ketapan",
    "gn:population":0,
    "gn:timezone":"Asia/Kuala_Lumpur",
    "iso:country":"MY",
    "name:msa_x_preferred":[
        "Kampung Kelang Ketapan"
    ],
    "wof:name":"Kampung Kelang Ketapan",
    "wof:placetype":"locality"
},
  "geometry": {"coordinates":[100.47998,5.78791],"type":"Point"}
}