{
  "type": "Feature",
  "properties": {
    "gn:admin1_code":"1.0",
    "gn:asciiname":"Kampung Permas Besar",
    "gn:country_code":"MY",
    "gn:dem":8,
    "gn:feature_class":"P",
    "gn:feature_code":"PPL",
    "gn:name":"Kampung Permas Besar",
    "gn:population":0,
    "gn:timezone":"Asia/Kuala_Lumpur",
    "iso:country":"MY",
    "name:msa_x_preferred":[
        "Kampung Permas Besar"
    ],
    "wof:name":"Kampung Permas Besar",
    "wof:placetype":"locality"
},
  "geometry": {"coordinates":[103.4601,1.3414],"type":"Point"}
}