{
  "type": "Feature",
  "properties": {
    "gn:admin1_code":"1",
    "gn:asciiname":"Kampung Kenangan",
    "gn:country_code":"MY",
    "gn:dem":36,
    "gn:feature_class":"P",
    "gn:feature_code":"PPL",
    "gn:name":"Kampung Kenangan",
    "gn:population":0,
    "gn:timezone":"Asia/Kuala_Lumpur",
    "iso:country":"MY",
    "name:msa_x_preferred":[
        "Kampung Kenangan"
    ],
    "name:und_x_variant":[
        "Kampong Kenangan"
    ],
    "wof:name":"Kampung Kenangan",
    "wof:placetype":"locality"
},
  "geometry": {"coordinates":[102.71469999999999,2.5699],"type":"Point"}
}