{
  "type": "Feature",
  "properties": {
    "gn:admin1_code":"16",
    "gn:asciiname":"Kampung Tangal",
    "gn:country_code":"MY",
    "gn:dem":11,
    "gn:feature_class":"P",
    "gn:feature_code":"PPL",
    "gn:name":"Kampung Tangal",
    "gn:population":0,
    "gn:timezone":"Asia/Kuching",
    "iso:country":"MY",
    "name:und_x_variant":[
        "Kampong Tangar",
        "Kampung Tangal"
    ],
    "wof:name":"Kampung Tangal",
    "wof:placetype":"locality"
},
  "geometry": {"coordinates":[118.65628,4.49078],"type":"Point"}
}