{
  "type": "Feature",
  "properties": {
    "gn:admin1_code":"7",
    "gn:asciiname":"Kampong Seleboh",
    "gn:cc2":"MY",
    "gn:country_code":"MY",
    "gn:dem":20,
    "gn:feature_class":"P",
    "gn:feature_code":"PPL",
    "gn:name":"Kampong Seleboh",
    "gn:population":0,
    "gn:timezone":"Asia/Kuala_Lumpur",
    "iso:country":"MY",
    "name:und_x_variant":[
        "Kampong Selboh",
        "Kampong Seleboh"
    ],
    "wof:name":"Kampong Seleboh",
    "wof:placetype":"locality"
},
  "geometry": {"coordinates":[100.90000000000001,4.46667],"type":"Point"}
}