{
  "type": "Feature",
  "properties": {
    "gn:country":"MY",
    "gn:fcode":"PPL",
    "gn:pop":0,
    "iso:country":"MY",
    "name:unk_x_variant":[
        "Kampong To Uban"
    ],
    "qs:name":"To Uban",
    "qs:name_adm0":"Malaysia",
    "qs:name_adm1":"Kelantan",
    "qs:photos_9r":0,
    "qs:photos_sr":0,
    "qs:placetype":"Town",
    "qs:pop_sr":"0",
    "wof:name":"To Uban",
    "wof:placetype":"locality",
    "wof:population":0
},
  "geometry": {"coordinates":[102.15000000000001,5.98333],"type":"Point"}
}