{
  "type": "Feature",
  "properties": {
    "gn:admin1_code":"7.0",
    "gn:asciiname":"Taman Saga",
    "gn:country_code":"MY",
    "gn:dem":69,
    "gn:feature_class":"P",
    "gn:feature_code":"PPL",
    "gn:name":"Taman Saga",
    "gn:population":0,
    "gn:timezone":"Asia/Kuala_Lumpur",
    "iso:country":"MY",
    "name:msa_x_preferred":[
        "Taman Saga"
    ],
    "wof:name":"Taman Saga",
    "wof:placetype":"locality"
},
  "geometry": {"coordinates":[101.14660000000001,4.6293],"type":"Point"}
}