{
  "type": "Feature",
  "properties": {
    "gn:admin1_code":"11",
    "gn:asciiname":"Rumah Asen",
    "gn:cc2":"MY",
    "gn:country_code":"MY",
    "gn:dem":5,
    "gn:feature_class":"P",
    "gn:feature_code":"PPL",
    "gn:name":"Rumah Asen",
    "gn:population":0,
    "gn:timezone":"Asia/Kuching",
    "iso:country":"MY",
    "name:und_x_variant":[
        "Rumah Asson",
        "Rumah Asen"
    ],
    "wof:name":"Rumah Asen",
    "wof:placetype":"locality"
},
  "geometry": {"coordinates":[111.21666999999999,1.86667],"type":"Point"}
}