{
  "type": "Feature",
  "properties": {
    "gn:admin1_code":"6.0",
    "gn:asciiname":"Kampung Gua Kalang",
    "gn:country_code":"MY",
    "gn:dem":143,
    "gn:feature_class":"P",
    "gn:feature_code":"PPL",
    "gn:name":"Kampung Gua Kalang",
    "gn:population":0,
    "gn:timezone":"Asia/Kuala_Lumpur",
    "iso:country":"MY",
    "name:msa_x_preferred":[
        "Kampung Gua Kalang"
    ],
    "wof:name":"Kampung Gua Kalang",
    "wof:placetype":"locality"
},
  "geometry": {"coordinates":[101.9892,4.6264],"type":"Point"}
}