{
  "type": "Feature",
  "properties": {
    "gn:admin1_code":"1",
    "gn:asciiname":"Kampung Mengkudu",
    "gn:country_code":"MY",
    "gn:dem":26,
    "gn:feature_class":"P",
    "gn:feature_code":"PPL",
    "gn:name":"Kampung Mengkudu",
    "gn:population":0,
    "gn:timezone":"Asia/Kuala_Lumpur",
    "iso:country":"MY",
    "name:msa_x_preferred":[
        "Kampung Mengkudu"
    ],
    "name:und_x_variant":[
        "Kampong Mengkudu"
    ],
    "wof:name":"Kampung Mengkudu",
    "wof:placetype":"locality"
},
  "geometry": {"coordinates":[102.81910000000001,2.5294],"type":"Point"}
}