{
  "type": "Feature",
  "properties": {
    "gn:admin1_code":"7",
    "gn:asciiname":"Kampung Prek Dalam",
    "gn:country_code":"MY",
    "gn:dem":59,
    "gn:feature_class":"P",
    "gn:feature_code":"PPL",
    "gn:name":"Kampung Prek Dalam",
    "gn:population":0,
    "gn:timezone":"Asia/Kuala_Lumpur",
    "iso:country":"MY",
    "name:und_x_variant":[
        "Kampong Prek Dalam"
    ],
    "wof:name":"Kampung Prek Dalam",
    "wof:placetype":"locality"
},
  "geometry": {"coordinates":[100.98935,4.84964],"type":"Point"}
}