{
  "type": "Feature",
  "properties": {
    "gn:admin1_code":"16",
    "gn:asciiname":"Kampung Taburan Besar",
    "gn:country_code":"MY",
    "gn:dem":75,
    "gn:feature_class":"P",
    "gn:feature_code":"PPL",
    "gn:name":"Kampung Taburan Besar",
    "gn:population":0,
    "gn:timezone":"Asia/Kuching",
    "iso:country":"MY",
    "name:msa_x_preferred":[
        "Kampung Taburan Besar"
    ],
    "name:und_x_variant":[
        "Taburan",
        "Kampong Taburan Besar"
    ],
    "wof:name":"Kampung Taburan Besar",
    "wof:placetype":"locality"
},
  "geometry": {"coordinates":[116.595,6.6182],"type":"Point"}
}