{
  "type": "Feature",
  "properties": {
    "gn:admin1_code":"3",
    "gn:asciiname":"Kampung Tebing Timbah",
    "gn:country_code":"MY",
    "gn:dem":59,
    "gn:feature_class":"P",
    "gn:feature_code":"PPL",
    "gn:name":"Kampung Tebing Timbah",
    "gn:population":0,
    "gn:timezone":"Asia/Kuala_Lumpur",
    "iso:country":"MY",
    "name:und_x_variant":[
        "Kampong Tebing Timbah"
    ],
    "wof:name":"Kampung Tebing Timbah",
    "wof:placetype":"locality"
},
  "geometry": {"coordinates":[101.89506,5.49938],"type":"Point"}
}