{
  "type": "Feature",
  "properties": {
    "gn:admin1_code":"5",
    "gn:asciiname":"Kampung Baharu Gedong Lalang",
    "gn:country_code":"MY",
    "gn:dem":62,
    "gn:feature_class":"P",
    "gn:feature_code":"PPL",
    "gn:name":"Kampung Baharu Gedong Lalang",
    "gn:population":0,
    "gn:timezone":"Asia/Kuala_Lumpur",
    "iso:country":"MY",
    "name:msa_x_preferred":[
        "Kampung Baharu Gedong Lalang"
    ],
    "name:und_x_variant":[
        "Kampong Baharu Gedang Lalang"
    ],
    "wof:name":"Kampung Baharu Gedong Lalang",
    "wof:placetype":"locality"
},
  "geometry": {"coordinates":[101.97199999999999,2.7313],"type":"Point"}
}