{
  "type": "Feature",
  "properties": {
    "gn:admin1_code":"16.0",
    "gn:asciiname":"Kampung Tiga Taruk",
    "gn:country_code":"MY",
    "gn:dem":1,
    "gn:feature_class":"P",
    "gn:feature_code":"PPL",
    "gn:name":"Kampung Tiga Taruk",
    "gn:population":0,
    "gn:timezone":"Asia/Kuching",
    "iso:country":"MY",
    "name:msa_x_preferred":[
        "Kampung Tiga Taruk"
    ],
    "name:und_x_variant":[
        "Tiga Tarok"
    ],
    "wof:name":"Kampung Tiga Taruk",
    "wof:placetype":"locality"
},
  "geometry": {"coordinates":[117.07259999999999,6.9808],"type":"Point"}
}