{
  "type": "Feature",
  "properties": {
    "gn:admin1_code":"5.0",
    "gn:asciiname":"Kampung Geliu Ilir",
    "gn:country_code":"MY",
    "gn:dem":149,
    "gn:feature_class":"P",
    "gn:feature_code":"PPL",
    "gn:name":"Kampung Geliu Ilir",
    "gn:population":0,
    "gn:timezone":"Asia/Kuala_Lumpur",
    "iso:country":"MY",
    "name:msa_x_preferred":[
        "Kampung Geliu Ilir"
    ],
    "wof:name":"Kampung Geliu Ilir",
    "wof:placetype":"locality"
},
  "geometry": {"coordinates":[102.0274,2.9089],"type":"Point"}
}