{
  "type": "Feature",
  "properties": {
    "gn:admin1_code":"6",
    "gn:asciiname":"Kampung Baharu",
    "gn:country_code":"MY",
    "gn:dem":90,
    "gn:feature_class":"P",
    "gn:feature_code":"PPL",
    "gn:name":"Kampung Baharu",
    "gn:population":0,
    "gn:timezone":"Asia/Kuala_Lumpur",
    "iso:country":"MY",
    "name:und_x_variant":[
        "Kampong Baharu"
    ],
    "wof:name":"Kampung Baharu",
    "wof:placetype":"locality"
},
  "geometry": {"coordinates":[102.39664999999999,4.26243],"type":"Point"}
}