{
  "type": "Feature",
  "properties": {
    "gn:admin1_code":"16",
    "gn:asciiname":"Kampung Tanah Merah",
    "gn:country_code":"MY",
    "gn:dem":31,
    "gn:feature_class":"P",
    "gn:feature_code":"PPL",
    "gn:name":"Kampung Tanah Merah",
    "gn:population":0,
    "gn:timezone":"Asia/Kuching",
    "iso:country":"MY",
    "name:msa_x_preferred":[
        "Kampung Tanah Merah"
    ],
    "name:und_x_variant":[
        "Kampong Tanah Merah"
    ],
    "wof:name":"Kampung Tanah Merah",
    "wof:placetype":"locality"
},
  "geometry": {"coordinates":[118.0937,5.8367],"type":"Point"}
}