{
  "type": "Feature",
  "properties": {
    "gn:admin1_code":"13.0",
    "gn:asciiname":"Kampung Gadung",
    "gn:country_code":"MY",
    "gn:dem":116,
    "gn:feature_class":"P",
    "gn:feature_code":"PPL",
    "gn:name":"Kampung Gadung",
    "gn:population":0,
    "gn:timezone":"Asia/Kuala_Lumpur",
    "iso:country":"MY",
    "name:msa_x_preferred":[
        "Kampung Gadung"
    ],
    "name:und_x_variant":[
        "Kampong Gadong",
        "Kampung Gadung"
    ],
    "wof:name":"Kampung Gadung",
    "wof:placetype":"locality"
},
  "geometry": {"coordinates":[103.18519999999999,4.5238],"type":"Point"}
}