{
  "type": "Feature",
  "properties": {
    "gn:admin1_code":"7.0",
    "gn:asciiname":"Kampung Tersusun Tanah Hitam",
    "gn:country_code":"MY",
    "gn:dem":99,
    "gn:feature_class":"P",
    "gn:feature_code":"PPL",
    "gn:name":"Kampung Tersusun Tanah Hitam",
    "gn:population":0,
    "gn:timezone":"Asia/Kuala_Lumpur",
    "iso:country":"MY",
    "name:msa_x_preferred":[
        "Kampung Tersusun Tanah Hitam"
    ],
    "wof:name":"Kampung Tersusun Tanah Hitam",
    "wof:placetype":"locality"
},
  "geometry": {"coordinates":[101.13849999999999,4.725],"type":"Point"}
}