{
  "type": "Feature",
  "properties": {
    "gn:admin1_code":"16",
    "gn:asciiname":"Kampong Bulanut",
    "gn:cc2":"MY",
    "gn:country_code":"MY",
    "gn:dem":136,
    "gn:feature_class":"P",
    "gn:feature_code":"PPL",
    "gn:name":"Kampong Bulanut",
    "gn:population":0,
    "gn:timezone":"Asia/Kuching",
    "iso:country":"MY",
    "name:und_x_variant":[
        "Bulonot",
        "Kampong Bulanut"
    ],
    "wof:name":"Kampong Bulanut",
    "wof:placetype":"locality"
},
  "geometry": {"coordinates":[117.11667,5.38333],"type":"Point"}
}