{
  "type": "Feature",
  "properties": {
    "gn:admin1_code":"11",
    "gn:asciiname":"Kampong Danu",
    "gn:cc2":"MY",
    "gn:country_code":"MY",
    "gn:dem":249,
    "gn:feature_class":"P",
    "gn:feature_code":"PPL",
    "gn:name":"Kampong Danu",
    "gn:population":0,
    "gn:timezone":"Asia/Kuching",
    "iso:country":"MY",
    "name:und_x_variant":[
        "Kampong Danau",
        "Kampong Danu"
    ],
    "wof:name":"Kampong Danu",
    "wof:placetype":"locality"
},
  "geometry": {"coordinates":[110.23333,1.26667],"type":"Point"}
}