{
  "type": "Feature",
  "properties": {
    "gn:admin1_code":"2",
    "gn:asciiname":"Kampung Jelutong",
    "gn:cc2":"MY",
    "gn:country_code":"MY",
    "gn:dem":79,
    "gn:feature_class":"P",
    "gn:feature_code":"PPL",
    "gn:name":"Kampung Jelutong",
    "gn:population":0,
    "gn:timezone":"Asia/Kuala_Lumpur",
    "iso:country":"MY",
    "name:msa_x_preferred":[
        "Kampung Jelutong"
    ],
    "name:und_x_variant":[
        "Kampong Jelutong"
    ],
    "wof:name":"Kampung Jelutong",
    "wof:placetype":"locality"
},
  "geometry": {"coordinates":[100.77803,5.85723],"type":"Point"}
}