{
  "type": "Feature",
  "properties": {
    "gn:admin1_code":"16.0",
    "gn:asciiname":"Panambangan",
    "gn:country_code":"MY",
    "gn:dem":1200,
    "gn:feature_class":"P",
    "gn:feature_code":"PPL",
    "gn:name":"Panambangan",
    "gn:population":0,
    "gn:timezone":"Asia/Kuching",
    "iso:country":"MY",
    "name:msa_x_preferred":[
        "Panambangan"
    ],
    "wof:name":"Panambangan",
    "wof:placetype":"locality"
},
  "geometry": {"coordinates":[116.4914,5.9385],"type":"Point"}
}