{
  "type": "Feature",
  "properties": {
    "gn:admin1_code":"16",
    "gn:asciiname":"Matandak",
    "gn:country_code":"MY",
    "gn:dem":21,
    "gn:feature_class":"P",
    "gn:feature_code":"PPL",
    "gn:name":"Matandak",
    "gn:population":0,
    "gn:timezone":"Asia/Kuching",
    "iso:country":"MY",
    "wof:name":"Matandak",
    "wof:placetype":"locality"
},
  "geometry": {"coordinates":[118.34999999999999,4.65],"type":"Point"}
}