{
  "type": "Feature",
  "properties": {
    "gn:admin1_code":"3",
    "gn:asciiname":"Kampong Sepor",
    "gn:country_code":"MY",
    "gn:dem":418,
    "gn:feature_class":"P",
    "gn:feature_code":"PPL",
    "gn:name":"Kampong Sepor",
    "gn:population":0,
    "gn:timezone":"Asia/Kuala_Lumpur",
    "iso:country":"MY",
    "wof:name":"Kampong Sepor",
    "wof:placetype":"locality"
},
  "geometry": {"coordinates":[101.59999999999999,5.83333],"type":"Point"}
}