{
  "type": "Feature",
  "properties": {
    "gn:admin1_code":"7",
    "gn:asciiname":"Kampong Simpang Perak",
    "gn:country_code":"MY",
    "gn:dem":319,
    "gn:feature_class":"P",
    "gn:feature_code":"PPL",
    "gn:name":"Kampong Simpang Perak",
    "gn:population":0,
    "gn:timezone":"Asia/Kuala_Lumpur",
    "iso:country":"MY",
    "wof:name":"Kampong Simpang Perak",
    "wof:placetype":"locality"
},
  "geometry": {"coordinates":[101.05,5.71667],"type":"Point"}
}