{
  "type": "Feature",
  "properties": {
    "gn:admin1_code":"8.0",
    "gn:asciiname":"Kampung Telaga Buluh",
    "gn:country_code":"MY",
    "gn:dem":5,
    "gn:feature_class":"P",
    "gn:feature_code":"PPL",
    "gn:name":"Kampung Telaga Buluh",
    "gn:population":0,
    "gn:timezone":"Asia/Kuala_Lumpur",
    "iso:country":"MY",
    "name:msa_x_preferred":[
        "Kampung Telaga Buluh"
    ],
    "wof:name":"Kampung Telaga Buluh",
    "wof:placetype":"locality"
},
  "geometry": {"coordinates":[100.25928,6.35755],"type":"Point"}
}