{
  "type": "Feature",
  "properties": {
    "gn:admin1_code":"7.0",
    "gn:asciiname":"Bagan Sungai Burong",
    "gn:country_code":"MY",
    "gn:dem":3,
    "gn:feature_class":"P",
    "gn:feature_code":"PPL",
    "gn:name":"Bagan Sungai Burong",
    "gn:population":0,
    "gn:timezone":"Asia/Kuala_Lumpur",
    "iso:country":"MY",
    "name:epo_x_preferred":[
        "Bagan Sungai Burong"
    ],
    "name:msa_x_preferred":[
        "Bagan Sungai Burong"
    ],
    "wof:name":"Bagan Sungai Burong",
    "wof:placetype":"locality"
},
  "geometry": {"coordinates":[100.7055,3.9769],"type":"Point"}
}