{
  "type": "Feature",
  "properties": {
    "gn:admin1_code":"4",
    "gn:asciiname":"Gapam",
    "gn:country_code":"MY",
    "gn:dem":25,
    "gn:feature_class":"P",
    "gn:feature_code":"PPL",
    "gn:name":"Gapam",
    "gn:population":0,
    "gn:timezone":"Asia/Kuala_Lumpur",
    "iso:country":"MY",
    "name:msa_x_preferred":[
        "Gapam"
    ],
    "name:und_x_variant":[
        "Solok Gapam"
    ],
    "wof:name":"Gapam",
    "wof:placetype":"locality"
},
  "geometry": {"coordinates":[102.3334,2.2842],"type":"Point"}
}