{
  "type": "Feature",
  "properties": {
    "gn:admin1_code":"3.0",
    "gn:asciiname":"Kampung Tunggal",
    "gn:country_code":"MY",
    "gn:dem":107,
    "gn:feature_class":"P",
    "gn:feature_code":"PPL",
    "gn:name":"Kampung Tunggal",
    "gn:population":0,
    "gn:timezone":"Asia/Kuala_Lumpur",
    "iso:country":"MY",
    "wof:name":"Kampung Tunggal",
    "wof:placetype":"locality"
},
  "geometry": {"coordinates":[102.05,5.28333],"type":"Point"}
}