{
  "type": "Feature",
  "properties": {
    "gn:admin1_code":"11.0",
    "gn:asciiname":"Kampong Sain",
    "gn:country_code":"MY",
    "gn:dem":177,
    "gn:feature_class":"P",
    "gn:feature_code":"PPL",
    "gn:name":"Kampong Sain",
    "gn:population":0,
    "gn:timezone":"Asia/Kuching",
    "iso:country":"MY",
    "name:und_x_variant":[
        "Kampong Kujang Sain",
        "Kampong Sain"
    ],
    "wof:name":"Kampong Sain",
    "wof:placetype":"locality"
},
  "geometry": {"coordinates":[110.44454,0.94704],"type":"Point"}
}