{
  "type": "Feature",
  "properties": {
    "gn:admin1_code":"11",
    "gn:asciiname":"Ijok Ulu",
    "gn:country_code":"MY",
    "gn:dem":10,
    "gn:feature_class":"P",
    "gn:feature_code":"PPL",
    "gn:name":"Ijok Ulu",
    "gn:population":0,
    "gn:timezone":"Asia/Kuching",
    "iso:country":"MY",
    "wof:name":"Ijok Ulu",
    "wof:placetype":"locality"
},
  "geometry": {"coordinates":[111.53333000000001,1.21667],"type":"Point"}
}