{
  "type": "Feature",
  "properties": {
    "gn:admin1_code":"5",
    "gn:asciiname":"Kampung Larong",
    "gn:country_code":"MY",
    "gn:dem":135,
    "gn:feature_class":"P",
    "gn:feature_code":"PPL",
    "gn:name":"Kampung Larong",
    "gn:population":0,
    "gn:timezone":"Asia/Kuala_Lumpur",
    "iso:country":"MY",
    "name:msa_x_preferred":[
        "Kampung Larong"
    ],
    "name:und_x_variant":[
        "Kampong Larong"
    ],
    "wof:name":"Kampung Larong",
    "wof:placetype":"locality"
},
  "geometry": {"coordinates":[102.0752,2.9425],"type":"Point"}
}