{
  "type": "Feature",
  "properties": {
    "gn:admin1_code":"11",
    "gn:asciiname":"Kampong Pujut",
    "gn:cc2":"MY",
    "gn:country_code":"MY",
    "gn:dem":6,
    "gn:feature_class":"P",
    "gn:feature_code":"PPL",
    "gn:name":"Kampong Pujut",
    "gn:population":0,
    "gn:timezone":"Asia/Kuching",
    "iso:country":"MY",
    "name:und_x_variant":[
        "Pujut",
        "Kampong Pujut"
    ],
    "wof:name":"Kampong Pujut",
    "wof:placetype":"locality"
},
  "geometry": {"coordinates":[114.01667,4.41667],"type":"Point"}
}