{
  "type": "Feature",
  "properties": {
    "gn:admin1_code":"11",
    "gn:asciiname":"Kampong Mansika",
    "gn:country_code":"MY",
    "gn:dem":17,
    "gn:feature_class":"P",
    "gn:feature_code":"PPL",
    "gn:name":"Kampong Mansika",
    "gn:population":0,
    "gn:timezone":"Asia/Kuching",
    "iso:country":"MY",
    "wof:name":"Kampong Mansika",
    "wof:placetype":"locality"
},
  "geometry": {"coordinates":[110.83333,1.51667],"type":"Point"}
}