{
  "type": "Feature",
  "properties": {
    "gn:admin1_code":"16",
    "gn:asciiname":"Kampung Tangar",
    "gn:country_code":"MY",
    "gn:dem":223,
    "gn:feature_class":"P",
    "gn:feature_code":"PPL",
    "gn:name":"Kampung Tangar",
    "gn:population":0,
    "gn:timezone":"Asia/Kuching",
    "iso:country":"MY",
    "name:msa_x_preferred":[
        "Kampung Tangar"
    ],
    "name:und_x_variant":[
        "Kampong Tangar"
    ],
    "wof:name":"Kampung Tangar",
    "wof:placetype":"locality"
},
  "geometry": {"coordinates":[116.7971,6.162],"type":"Point"}
}