{
  "type": "Feature",
  "properties": {
    "gn:admin1_code":"4.0",
    "gn:asciiname":"Kampung Lapan",
    "gn:country_code":"MY",
    "gn:dem":6,
    "gn:feature_class":"P",
    "gn:feature_code":"PPL",
    "gn:name":"Kampung Lapan",
    "gn:population":0,
    "gn:timezone":"Asia/Kuala_Lumpur",
    "iso:country":"MY",
    "name:msa_x_preferred":[
        "Kampung Lapan"
    ],
    "wof:name":"Kampung Lapan",
    "wof:placetype":"locality"
},
  "geometry": {"coordinates":[102.2253,2.2112],"type":"Point"}
}