{
  "type": "Feature",
  "properties": {
    "gn:admin1_code":"1.0",
    "gn:asciiname":"Kemajuan Tanah Lok Heng",
    "gn:country_code":"MY",
    "gn:dem":20,
    "gn:feature_class":"P",
    "gn:feature_code":"PPL",
    "gn:name":"Kemajuan Tanah Lok Heng",
    "gn:population":0,
    "gn:timezone":"Asia/Kuala_Lumpur",
    "iso:country":"MY",
    "name:msa_x_preferred":[
        "Kemajuan Tanah Lok Heng"
    ],
    "wof:name":"Kemajuan Tanah Lok Heng",
    "wof:placetype":"locality"
},
  "geometry": {"coordinates":[104.11450000000001,1.6979],"type":"Point"}
}