{
  "type": "Feature",
  "properties": {
    "gn:admin1_code":"1.0",
    "gn:asciiname":"Perkampungan Hulu Belitung",
    "gn:country_code":"MY",
    "gn:dem":77,
    "gn:feature_class":"P",
    "gn:feature_code":"PPL",
    "gn:name":"Perkampungan Hulu Belitung",
    "gn:population":0,
    "gn:timezone":"Asia/Kuala_Lumpur",
    "iso:country":"MY",
    "name:msa_x_preferred":[
        "Perkampungan Hulu Belitung"
    ],
    "wof:name":"Perkampungan Hulu Belitung",
    "wof:placetype":"locality"
},
  "geometry": {"coordinates":[103.4646,1.9435],"type":"Point"}
}