{
  "type": "Feature",
  "properties": {
    "gn:admin1_code":"2",
    "gn:asciiname":"Kampung Pechah Batu",
    "gn:cc2":"MY",
    "gn:country_code":"MY",
    "gn:dem":19,
    "gn:feature_class":"P",
    "gn:feature_code":"PPL",
    "gn:name":"Kampung Pechah Batu",
    "gn:population":0,
    "gn:timezone":"Asia/Kuala_Lumpur",
    "iso:country":"MY",
    "name:msa_x_preferred":[
        "Kampung Pechah Batu"
    ],
    "name:und_x_variant":[
        "Kampong Pechah Batu"
    ],
    "wof:name":"Kampung Pechah Batu",
    "wof:placetype":"locality"
},
  "geometry": {"coordinates":[100.63675000000001,5.22009],"type":"Point"}
}