{
  "type": "Feature",
  "properties": {
    "gn:admin1_code":"2.0",
    "gn:asciiname":"Kampung Banggul Jenereh",
    "gn:country_code":"MY",
    "gn:dem":85,
    "gn:feature_class":"P",
    "gn:feature_code":"PPL",
    "gn:name":"Kampung Banggul Jenereh",
    "gn:population":0,
    "gn:timezone":"Asia/Kuala_Lumpur",
    "iso:country":"MY",
    "name:msa_x_preferred":[
        "Kampung Banggul Jenereh"
    ],
    "wof:name":"Kampung Banggul Jenereh",
    "wof:placetype":"locality"
},
  "geometry": {"coordinates":[100.76667,5.85],"type":"Point"}
}