{
  "type": "Feature",
  "properties": {
    "gn:admin1_code":"4.0",
    "gn:asciiname":"Solok Duku",
    "gn:country_code":"MY",
    "gn:dem":30,
    "gn:feature_class":"P",
    "gn:feature_code":"PPL",
    "gn:name":"Solok Duku",
    "gn:population":0,
    "gn:timezone":"Asia/Kuala_Lumpur",
    "iso:country":"MY",
    "wof:name":"Solok Duku",
    "wof:placetype":"locality"
},
  "geometry": {"coordinates":[102.25534,2.35602],"type":"Point"}
}