{
  "type": "Feature",
  "properties": {
    "gn:admin1_code":"6.0",
    "gn:asciiname":"Kampung Peramu Jaya Tiga",
    "gn:country_code":"MY",
    "gn:dem":9,
    "gn:feature_class":"P",
    "gn:feature_code":"PPL",
    "gn:name":"Kampung Peramu Jaya Tiga",
    "gn:population":0,
    "gn:timezone":"Asia/Kuala_Lumpur",
    "iso:country":"MY",
    "name:msa_x_preferred":[
        "Kampung Peramu Jaya Tiga"
    ],
    "wof:name":"Kampung Peramu Jaya Tiga",
    "wof:placetype":"locality"
},
  "geometry": {"coordinates":[103.3785,3.5636],"type":"Point"}
}