{
  "type": "Feature",
  "properties": {
    "gn:admin1_code":"1.0",
    "gn:asciiname":"Kampung Sungai Karang",
    "gn:country_code":"MY",
    "gn:dem":16,
    "gn:feature_class":"P",
    "gn:feature_code":"PPL",
    "gn:name":"Kampung Sungai Karang",
    "gn:population":0,
    "gn:timezone":"Asia/Kuala_Lumpur",
    "iso:country":"MY",
    "name:msa_x_preferred":[
        "Kampung Sungai Karang"
    ],
    "wof:name":"Kampung Sungai Karang",
    "wof:placetype":"locality"
},
  "geometry": {"coordinates":[103.4859,1.3862],"type":"Point"}
}