{
  "type": "Feature",
  "properties": {
    "gn:admin1_code":"11",
    "gn:asciiname":"Kampong Sebandi Matang",
    "gn:cc2":"MY",
    "gn:country_code":"MY",
    "gn:dem":8,
    "gn:feature_class":"P",
    "gn:feature_code":"PPL",
    "gn:name":"Kampong Sebandi Matang",
    "gn:population":0,
    "gn:timezone":"Asia/Kuching",
    "iso:country":"MY",
    "name:und_x_variant":[
        "Kampong Sebandi",
        "Kampong Semandi Matang",
        "Kampong Sebandi Matang"
    ],
    "wof:name":"Kampong Sebandi Matang",
    "wof:placetype":"locality"
},
  "geometry": {"coordinates":[110.55,1.58333],"type":"Point"}
}