{
  "type": "Feature",
  "properties": {
    "gn:admin1_code":"5.0",
    "gn:asciiname":"Kampung Punggul",
    "gn:country_code":"MY",
    "gn:dem":117,
    "gn:feature_class":"P",
    "gn:feature_code":"PPL",
    "gn:name":"Kampung Punggul",
    "gn:population":0,
    "gn:timezone":"Asia/Kuala_Lumpur",
    "iso:country":"MY",
    "name:msa_x_preferred":[
        "Kampung Punggul"
    ],
    "wof:name":"Kampung Punggul",
    "wof:placetype":"locality"
},
  "geometry": {"coordinates":[102.242,2.6378],"type":"Point"}
}