{
  "type": "Feature",
  "properties": {
    "gn:admin1_code":"16",
    "gn:asciiname":"Kampung Pintas",
    "gn:country_code":"MY",
    "gn:dem":11,
    "gn:feature_class":"P",
    "gn:feature_code":"PPL",
    "gn:name":"Kampung Pintas",
    "gn:population":0,
    "gn:timezone":"Asia/Kuching",
    "iso:country":"MY",
    "name:msa_x_preferred":[
        "Kampung Pintas"
    ],
    "name:und_x_variant":[
        "Kampong Pintas"
    ],
    "wof:name":"Kampung Pintas",
    "wof:placetype":"locality"
},
  "geometry": {"coordinates":[115.7068,5.3802],"type":"Point"}
}