{
  "type": "Feature",
  "properties": {
    "gn:admin1_code":"9",
    "gn:asciiname":"Kampung Datok",
    "gn:cc2":"MY",
    "gn:country_code":"MY",
    "gn:dem":11,
    "gn:feature_class":"P",
    "gn:feature_code":"PPL",
    "gn:name":"Kampung Datok",
    "gn:population":0,
    "gn:timezone":"Asia/Kuala_Lumpur",
    "iso:country":"MY",
    "name:msa_x_preferred":[
        "Kampung Datok"
    ],
    "name:und_x_variant":[
        "Kampong Dato\u2019"
    ],
    "wof:name":"Kampung Datok",
    "wof:placetype":"locality"
},
  "geometry": {"coordinates":[100.43165999999999,5.52418],"type":"Point"}
}