{
  "type": "Feature",
  "properties": {
    "gn:admin1_code":"16.0",
    "gn:asciiname":"Semendapi",
    "gn:country_code":"MY",
    "gn:dem":130,
    "gn:feature_class":"P",
    "gn:feature_code":"PPL",
    "gn:name":"Semendapi",
    "gn:population":0,
    "gn:timezone":"Asia/Kuching",
    "iso:country":"MY",
    "name:und_x_variant":[
        "Sememdapi",
        "Semendapi"
    ],
    "wof:name":"Semendapi",
    "wof:placetype":"locality"
},
  "geometry": {"coordinates":[116.43262,4.33172],"type":"Point"}
}