{
  "type": "Feature",
  "properties": {
    "gn:admin1_code":"6",
    "gn:asciiname":"Kampung Jong Berlabuh",
    "gn:country_code":"MY",
    "gn:dem":76,
    "gn:feature_class":"P",
    "gn:feature_code":"PPL",
    "gn:name":"Kampung Jong Berlabuh",
    "gn:population":0,
    "gn:timezone":"Asia/Kuala_Lumpur",
    "iso:country":"MY",
    "name:msa_x_preferred":[
        "Kampung Jong Berlabuh"
    ],
    "name:und_x_variant":[
        "Kampong Jong Berlaboh"
    ],
    "wof:name":"Kampung Jong Berlabuh",
    "wof:placetype":"locality"
},
  "geometry": {"coordinates":[102.3497,4.157],"type":"Point"}
}