{
  "type": "Feature",
  "properties": {
    "gn:country":"MY",
    "gn:fcode":"PPL",
    "gn:population":0,
    "iso:country":"MY",
    "name:ara_x_preferred":[
        "\u062a\u0627\u0645\u0628\u064a\u0646"
    ],
    "name:cat_x_preferred":[
        "Tampin"
    ],
    "name:ceb_x_preferred":[
        "Kampung Tampin"
    ],
    "name:deu_x_preferred":[
        "Tampin"
    ],
    "name:eng_x_preferred":[
        "Tampin"
    ],
    "name:fas_x_preferred":[
        "\u062a\u0645\u067e\u06cc\u0646"
    ],
    "name:fra_x_preferred":[
        "Tampin"
    ],
    "name:msa_x_preferred":[
        "Taman Bertam Jaya"
    ],
    "name:msa_x_variant":[
        "Tampin"
    ],
    "name:nld_x_preferred":[
        "Tampin"
    ],
    "name:spa_x_preferred":[
        "Tampin"
    ],
    "name:vie_x_preferred":[
        "Tampin"
    ],
    "qs:name":"Taman Pertam Jaya",
    "qs:name_adm0":"Malaysia",
    "qs:name_adm1":"Melaka",
    "qs:photos_9r":0,
    "qs:photos_sr":0,
    "qs:placetype":"Town",
    "qs:pop_sr":"0",
    "wd:wordcount":816,
    "wof:name":"Taman Pertam Jaya",
    "wof:placetype":"locality",
    "wof:population":0
},
  "geometry": {"coordinates":[102.2099,2.2815],"type":"Point"}
}