{
  "type": "Feature",
  "properties": {
    "gn:admin1_code":"16.0",
    "gn:asciiname":"Kampung Ramatai",
    "gn:country_code":"MY",
    "gn:dem":43,
    "gn:feature_class":"P",
    "gn:feature_code":"PPL",
    "gn:name":"Kampung Ramatai",
    "gn:population":0,
    "gn:timezone":"Asia/Kuching",
    "iso:country":"MY",
    "name:msa_x_preferred":[
        "Kampung Ramatai"
    ],
    "wof:name":"Kampung Ramatai",
    "wof:placetype":"locality"
},
  "geometry": {"coordinates":[117.155,6.1197],"type":"Point"}
}