{
  "type": "Feature",
  "properties": {
    "gn:admin1_code":"16.0",
    "gn:asciiname":"Kampung Genipis",
    "gn:country_code":"MY",
    "gn:dem":273,
    "gn:feature_class":"P",
    "gn:feature_code":"PPL",
    "gn:name":"Kampung Genipis",
    "gn:population":0,
    "gn:timezone":"Asia/Kuching",
    "iso:country":"MY",
    "name:msa_x_preferred":[
        "Kampung Genipis"
    ],
    "name:und_x_variant":[
        "Genipis",
        "Ginipis"
    ],
    "wof:name":"Kampung Genipis",
    "wof:placetype":"locality"
},
  "geometry": {"coordinates":[116.3163,5.9554],"type":"Point"}
}