{
  "type": "Feature",
  "properties": {
    "gn:admin1_code":"13.0",
    "gn:asciiname":"Kampung Gelugur Kedai",
    "gn:country_code":"MY",
    "gn:dem":13,
    "gn:feature_class":"P",
    "gn:feature_code":"PPL",
    "gn:name":"Kampung Gelugur Kedai",
    "gn:population":0,
    "gn:timezone":"Asia/Kuala_Lumpur",
    "iso:country":"MY",
    "name:msa_x_preferred":[
        "Kampung Gelugur Kedai"
    ],
    "wof:name":"Kampung Gelugur Kedai",
    "wof:placetype":"locality"
},
  "geometry": {"coordinates":[103.1135,5.2741],"type":"Point"}
}