{
  "type": "Feature",
  "properties": {
    "gn:admin1_code":"11",
    "gn:asciiname":"Kampung Tagar",
    "gn:country_code":"MY",
    "gn:dem":150,
    "gn:feature_class":"P",
    "gn:feature_code":"PPL",
    "gn:name":"Kampung Tagar",
    "gn:population":0,
    "gn:timezone":"Asia/Kuching",
    "iso:country":"MY",
    "name:msa_x_preferred":[
        "Kampung Tagar"
    ],
    "name:und_x_variant":[
        "Kampong Tagar"
    ],
    "wof:name":"Kampung Tagar",
    "wof:placetype":"locality"
},
  "geometry": {"coordinates":[115.5407,4.7588],"type":"Point"}
}