{
  "type": "Feature",
  "properties": {
    "gn:admin1_code":"13",
    "gn:asciiname":"Kampong Bukit Takar",
    "gn:cc2":"MY",
    "gn:country_code":"MY",
    "gn:dem":80,
    "gn:feature_class":"P",
    "gn:feature_code":"PPL",
    "gn:name":"Kampong Bukit Takar",
    "gn:population":0,
    "gn:timezone":"Asia/Kuala_Lumpur",
    "iso:country":"MY",
    "name:und_x_variant":[
        "Kampong Bukit Takai",
        "Kampong Bukit Takal",
        "Kampong Bukit Takar"
    ],
    "wof:name":"Kampong Bukit Takar",
    "wof:placetype":"locality"
},
  "geometry": {"coordinates":[103.40000000000001,4.28333],"type":"Point"}
}