{
  "type": "Feature",
  "properties": {
    "gn:admin1_code":"5.0",
    "gn:asciiname":"Kampung Serdai Hulu",
    "gn:country_code":"MY",
    "gn:dem":83,
    "gn:feature_class":"P",
    "gn:feature_code":"PPL",
    "gn:name":"Kampung Serdai Hulu",
    "gn:population":0,
    "gn:timezone":"Asia/Kuala_Lumpur",
    "iso:country":"MY",
    "name:msa_x_preferred":[
        "Kampung Serdai Hulu"
    ],
    "wof:name":"Kampung Serdai Hulu",
    "wof:placetype":"locality"
},
  "geometry": {"coordinates":[102.2075,3.1032],"type":"Point"}
}