{
  "type": "Feature",
  "properties": {
    "gn:admin1_code":"6",
    "gn:asciiname":"Kampong Teroh",
    "gn:cc2":"MY",
    "gn:country_code":"MY",
    "gn:dem":81,
    "gn:feature_class":"P",
    "gn:feature_code":"PPL",
    "gn:name":"Kampong Teroh",
    "gn:population":0,
    "gn:timezone":"Asia/Kuala_Lumpur",
    "iso:country":"MY",
    "name:und_x_variant":[
        "Kampong Troh",
        "Kampong Teroh"
    ],
    "wof:name":"Kampong Teroh",
    "wof:placetype":"locality"
},
  "geometry": {"coordinates":[102.08333,3.43333],"type":"Point"}
}