{
  "type": "Feature",
  "properties": {
    "gn:admin1_code":"12.0",
    "gn:asciiname":"Kampung Talu",
    "gn:country_code":"MY",
    "gn:dem":53,
    "gn:feature_class":"P",
    "gn:feature_code":"PPL",
    "gn:name":"Kampung Talu",
    "gn:population":0,
    "gn:timezone":"Asia/Kuala_Lumpur",
    "iso:country":"MY",
    "name:msa_x_preferred":[
        "Kampung Talu"
    ],
    "wof:name":"Kampung Talu",
    "wof:placetype":"locality"
},
  "geometry": {"coordinates":[101.6626,3.4343],"type":"Point"}
}