{
  "type": "Feature",
  "properties": {
    "gn:admin1_code":"7",
    "gn:asciiname":"Kampung Alor Semat",
    "gn:cc2":"MY",
    "gn:country_code":"MY",
    "gn:dem":10,
    "gn:feature_class":"P",
    "gn:feature_code":"PPL",
    "gn:name":"Kampung Alor Semat",
    "gn:population":0,
    "gn:timezone":"Asia/Kuala_Lumpur",
    "iso:country":"MY",
    "name:msa_x_preferred":[
        "Kampung Alor Semat"
    ],
    "name:und_x_variant":[
        "Kampong Alor Semat"
    ],
    "wof:name":"Kampung Alor Semat",
    "wof:placetype":"locality"
},
  "geometry": {"coordinates":[100.59702,5.05734],"type":"Point"}
}