{
  "type": "Feature",
  "properties": {
    "iso:country":"MY",
    "qs:name":"Sekinchan Dalam",
    "qs:name_adm0":"Malaysia",
    "qs:name_adm1":"Selangor",
    "qs:photos":390,
    "qs:photos_1k":79,
    "qs:photos_9k":2,
    "qs:photos_9r":5,
    "qs:photos_all":390,
    "qs:photos_sr":6,
    "qs:placetype":"Town",
    "qs:pop_sr":"0",
    "wof:name":"Sekinchan Dalam",
    "wof:placetype":"locality"
},
  "geometry": {"coordinates":[101.158332,3.536299],"type":"Point"}
}