{
  "type": "Feature",
  "properties": {
    "gn:admin1_code":"16",
    "gn:asciiname":"Lutong",
    "gn:country_code":"MY",
    "gn:dem":150,
    "gn:feature_class":"P",
    "gn:feature_code":"PPL",
    "gn:name":"Lutong",
    "gn:population":0,
    "gn:timezone":"Asia/Kuching",
    "iso:country":"MY",
    "wof:name":"Lutong",
    "wof:placetype":"locality"
},
  "geometry": {"coordinates":[116.81667,6.75],"type":"Point"}
}