{
  "type": "Feature",
  "properties": {
    "gn:admin1_code":"11",
    "gn:asciiname":"Panjai Ruai",
    "gn:country_code":"MY",
    "gn:dem":49,
    "gn:feature_class":"P",
    "gn:feature_code":"PPL",
    "gn:name":"Panjai Ruai",
    "gn:population":0,
    "gn:timezone":"Asia/Kuching",
    "iso:country":"MY",
    "wof:name":"Panjai Ruai",
    "wof:placetype":"locality"
},
  "geometry": {"coordinates":[111.81667,1.06667],"type":"Point"}
}