{
  "type": "Feature",
  "properties": {
    "gn:admin1_code":"1.0",
    "gn:asciiname":"Jagoh",
    "gn:country_code":"MY",
    "gn:dem":44,
    "gn:feature_class":"P",
    "gn:feature_code":"PPL",
    "gn:name":"Jagoh",
    "gn:population":0,
    "gn:timezone":"Asia/Kuala_Lumpur",
    "iso:country":"MY",
    "name:msa_x_preferred":[
        "Jagoh"
    ],
    "name:und_x_variant":[
        "Jaguh"
    ],
    "wof:name":"Jagoh",
    "wof:placetype":"locality"
},
  "geometry": {"coordinates":[103.14879999999999,2.2515],"type":"Point"}
}