{
  "type": "Feature",
  "properties": {
    "gn:admin1_code":"16.0",
    "gn:asciiname":"Kampung Gana Rumah Rehat",
    "gn:country_code":"MY",
    "gn:dem":700,
    "gn:feature_class":"P",
    "gn:feature_code":"PPL",
    "gn:name":"Kampung Gana Rumah Rehat",
    "gn:population":0,
    "gn:timezone":"Asia/Kuching",
    "iso:country":"MY",
    "name:msa_x_preferred":[
        "Kampung Gana Rumah Rehat"
    ],
    "wof:name":"Kampung Gana Rumah Rehat",
    "wof:placetype":"locality"
},
  "geometry": {"coordinates":[116.9316,6.344],"type":"Point"}
}