{
  "type": "Feature",
  "properties": {
    "iso:country":"MY",
    "name:rus_x_preferred":[
        "\u0413\u0430\u043b\u0430\u0442"
    ],
    "qs:name":"Galas",
    "qs:name_adm0":"Malaysia",
    "qs:name_adm1":"Kelantan",
    "qs:photos":23,
    "qs:photos_1k":5,
    "qs:photos_9k":1,
    "qs:photos_9r":3,
    "qs:photos_all":130,
    "qs:photos_sr":1,
    "qs:placetype":"LocalAdmin",
    "qs:pop_sr":"0",
    "wof:name":"Galas",
    "wof:placetype":"localadmin"
},
  "geometry": {"coordinates":[102.095775,4.94371],"type":"Point"}
}