{
  "type": "Feature",
  "properties": {
    "gn:admin1_code":"11",
    "gn:asciiname":"Rumah Aus",
    "gn:country_code":"MY",
    "gn:dem":0,
    "gn:feature_class":"P",
    "gn:feature_code":"PPL",
    "gn:name":"Rumah Aus",
    "gn:population":0,
    "gn:timezone":"Asia/Kuching",
    "iso:country":"MY",
    "wof:name":"Rumah Aus",
    "wof:placetype":"locality"
},
  "geometry": {"coordinates":[111.78333000000001,2.38333],"type":"Point"}
}