{
  "type": "Feature",
  "properties": {
    "gn:admin1_code":"2.0",
    "gn:asciiname":"Kampung Teluk Layang",
    "gn:country_code":"MY",
    "gn:dem":9,
    "gn:feature_class":"P",
    "gn:feature_code":"PPL",
    "gn:name":"Kampung Teluk Layang",
    "gn:population":0,
    "gn:timezone":"Asia/Kuala_Lumpur",
    "iso:country":"MY",
    "name:msa_x_preferred":[
        "Kampung Teluk Layang"
    ],
    "wof:name":"Kampung Teluk Layang",
    "wof:placetype":"locality"
},
  "geometry": {"coordinates":[100.31870000000001,6.10119],"type":"Point"}
}