{
  "type": "Feature",
  "properties": {
    "gn:admin1_code":"11",
    "gn:asciiname":"Rumah Jaul",
    "gn:cc2":"MY",
    "gn:country_code":"MY",
    "gn:dem":78,
    "gn:feature_class":"P",
    "gn:feature_code":"PPL",
    "gn:name":"Rumah Jaul",
    "gn:population":0,
    "gn:timezone":"Asia/Kuching",
    "iso:country":"MY",
    "name:und_x_variant":[
        "Rumah Jawl",
        "Rumah Jaul"
    ],
    "wof:name":"Rumah Jaul",
    "wof:placetype":"locality"
},
  "geometry": {"coordinates":[112.05,1.96667],"type":"Point"}
}