{
  "type": "Feature",
  "properties": {
    "gn:country":"MY",
    "gn:fcode":"PPL",
    "gn:pop":0,
    "iso:country":"MY",
    "qs:name":"Serdang Lama",
    "qs:name_adm0":"Malaysia",
    "qs:name_adm1":"Selangor",
    "qs:photos":127,
    "qs:photos_1k":26,
    "qs:photos_9k":1,
    "qs:photos_9r":3,
    "qs:photos_all":127,
    "qs:photos_sr":3,
    "qs:placetype":"Suburb",
    "qs:pop_sr":"0",
    "wof:name":"Serdang Lama",
    "wof:placetype":"neighbourhood",
    "wof:population":0
},
  "geometry": {"coordinates":[101.71666999999999,3.01667],"type":"Point"}
}