{
  "type": "Feature",
  "properties": {
    "gn:admin1_code":"2.0",
    "gn:asciiname":"Kampung Sungai Tok Pawang",
    "gn:country_code":"MY",
    "gn:dem":25,
    "gn:feature_class":"P",
    "gn:feature_code":"PPL",
    "gn:name":"Kampung Sungai Tok Pawang",
    "gn:population":0,
    "gn:timezone":"Asia/Kuala_Lumpur",
    "iso:country":"MY",
    "name:msa_x_preferred":[
        "Kampung Sungai Tok Pawang"
    ],
    "wof:name":"Kampung Sungai Tok Pawang",
    "wof:placetype":"locality"
},
  "geometry": {"coordinates":[100.50611000000001,5.7555],"type":"Point"}
}