{
  "type": "Feature",
  "properties": {
    "gn:admin1_code":"5",
    "gn:asciiname":"Kampung Perah",
    "gn:country_code":"MY",
    "gn:dem":44,
    "gn:feature_class":"P",
    "gn:feature_code":"PPL",
    "gn:name":"Kampung Perah",
    "gn:population":0,
    "gn:timezone":"Asia/Kuala_Lumpur",
    "iso:country":"MY",
    "name:msa_x_preferred":[
        "Kampung Perah"
    ],
    "name:und_x_variant":[
        "Kampong Perah"
    ],
    "wof:name":"Kampung Perah",
    "wof:placetype":"locality"
},
  "geometry": {"coordinates":[102.1601,2.5134],"type":"Point"}
}