{
  "type": "Feature",
  "properties": {
    "gn:admin1_code":"2.0",
    "gn:asciiname":"Kampung Huma Besar",
    "gn:country_code":"MY",
    "gn:dem":15,
    "gn:feature_class":"P",
    "gn:feature_code":"PPL",
    "gn:name":"Kampung Huma Besar",
    "gn:population":0,
    "gn:timezone":"Asia/Kuala_Lumpur",
    "iso:country":"MY",
    "name:msa_x_preferred":[
        "Kampung Huma Besar"
    ],
    "wof:name":"Kampung Huma Besar",
    "wof:placetype":"locality"
},
  "geometry": {"coordinates":[100.55318,6.10444],"type":"Point"}
}