{
  "type": "Feature",
  "properties": {
    "gn:admin1_code":"11",
    "gn:asciiname":"Sijingkat",
    "gn:cc2":"MY",
    "gn:country_code":"MY",
    "gn:dem":1,
    "gn:feature_class":"P",
    "gn:feature_code":"PPL",
    "gn:name":"Sijingkat",
    "gn:population":0,
    "gn:timezone":"Asia/Kuching",
    "iso:country":"MY",
    "name:und_x_variant":[
        "Kampong Sejingkat",
        "Kampong Sijingkat Batu",
        "Sijingkat"
    ],
    "wof:name":"Sijingkat",
    "wof:placetype":"locality"
},
  "geometry": {"coordinates":[110.43333,1.58333],"type":"Point"}
}