{
  "type": "Feature",
  "properties": {
    "gn:admin1_code":"16",
    "gn:asciiname":"Kampung Ladoh",
    "gn:country_code":"MY",
    "gn:dem":15,
    "gn:feature_class":"P",
    "gn:feature_code":"PPL",
    "gn:name":"Kampung Ladoh",
    "gn:population":0,
    "gn:timezone":"Asia/Kuching",
    "iso:country":"MY",
    "name:msa_x_preferred":[
        "Kampung Ladoh"
    ],
    "name:und_x_variant":[
        "Kampong Ladoh"
    ],
    "wof:name":"Kampung Ladoh",
    "wof:placetype":"locality"
},
  "geometry": {"coordinates":[116.16370000000001,6.0431],"type":"Point"}
}