{
  "type": "Feature",
  "properties": {
    "gn:admin1_code":"7.0",
    "gn:asciiname":"Taman Dovenby",
    "gn:country_code":"MY",
    "gn:dem":102,
    "gn:feature_class":"P",
    "gn:feature_code":"PPL",
    "gn:name":"Taman Dovenby",
    "gn:population":0,
    "gn:timezone":"Asia/Kuala_Lumpur",
    "iso:country":"MY",
    "name:msa_x_preferred":[
        "Taman Dovenby"
    ],
    "wof:name":"Taman Dovenby",
    "wof:placetype":"locality"
},
  "geometry": {"coordinates":[101.1174,4.7863],"type":"Point"}
}