{
  "type": "Feature",
  "properties": {
    "gn:admin1_code":"7.0",
    "gn:asciiname":"Kampung Perik",
    "gn:country_code":"MY",
    "gn:dem":62,
    "gn:feature_class":"P",
    "gn:feature_code":"PPL",
    "gn:name":"Kampung Perik",
    "gn:population":0,
    "gn:timezone":"Asia/Kuala_Lumpur",
    "iso:country":"MY",
    "name:msa_x_preferred":[
        "Kampung Perik"
    ],
    "wof:name":"Kampung Perik",
    "wof:placetype":"locality"
},
  "geometry": {"coordinates":[100.9854,4.8391],"type":"Point"}
}