{
  "type": "Feature",
  "properties": {
    "gn:country":"MY",
    "gn:fcode":"ADM3",
    "gn:pop":0,
    "iso:country":"MY",
    "name:msa_x_preferred":[
        "Kuala Balah"
    ],
    "qs:name":"Kuala Balah",
    "qs:photos_9r":0,
    "qs:photos_sr":0,
    "qs:pop_sr":"0",
    "wof:name":"Kuala Balah",
    "wof:placetype":"localadmin",
    "wof:population":0
},
  "geometry": {"coordinates":[101.87059000000001,5.49228],"type":"Point"}
}