{
  "type": "Feature",
  "properties": {
    "gn:admin1_code":"1",
    "gn:asciiname":"Kampung Tenggaham",
    "gn:country_code":"MY",
    "gn:dem":5,
    "gn:feature_class":"P",
    "gn:feature_code":"PPL",
    "gn:name":"Kampung Tenggaham",
    "gn:population":0,
    "gn:timezone":"Asia/Kuala_Lumpur",
    "iso:country":"MY",
    "name:und_x_variant":[
        "Kampong Tenggaham"
    ],
    "wof:name":"Kampung Tenggaham",
    "wof:placetype":"locality"
},
  "geometry": {"coordinates":[104.08333,1.95],"type":"Point"}
}