{
  "type": "Feature",
  "properties": {
    "gn:admin1_code":"1.0",
    "gn:asciiname":"Taman Tiram Baru",
    "gn:country_code":"MY",
    "gn:dem":28,
    "gn:feature_class":"P",
    "gn:feature_code":"PPL",
    "gn:name":"Taman Tiram Baru",
    "gn:population":0,
    "gn:timezone":"Asia/Kuala_Lumpur",
    "iso:country":"MY",
    "name:msa_x_preferred":[
        "Taman Tiram Baru"
    ],
    "wof:name":"Taman Tiram Baru",
    "wof:placetype":"locality"
},
  "geometry": {"coordinates":[103.8233,1.5981],"type":"Point"}
}