{
  "type": "Feature",
  "properties": {
    "gn:country":"MY",
    "gn:fcode":"PPL",
    "gn:pop":0,
    "iso:country":"MY",
    "name:unk_x_variant":[
        "Matang"
    ],
    "qs:name":"Kampung Matang",
    "qs:name_adm0":"Malaysia",
    "qs:name_adm1":"Sarawak",
    "qs:photos_9k":1,
    "qs:photos_9r":4,
    "qs:photos_all":186,
    "qs:photos_sr":0,
    "qs:placetype":"Town",
    "qs:pop_sr":"3",
    "wof:name":"Kampung Matang",
    "wof:placetype":"locality",
    "wof:population":0
},
  "geometry": {"coordinates":[110.23333,1.58333],"type":"Point"}
}