{
  "type": "Feature",
  "properties": {
    "iso:country":"MY",
    "name:eng_x_preferred":[
        "Kampong Makam"
    ],
    "qs:gn_adm0_cc":"MY",
    "qs:gn_fcode":"PPLX",
    "qs:gn_local":1735106,
    "qs:gn_namadm1":"09",
    "qs:gn_name":"Kampong Makam",
    "qs:local_max":5776,
    "qs:local_sum":22216,
    "qs:localhoods":25,
    "qs:name":"Kampong Makam",
    "qs:name_adm0":"Malaysia",
    "qs:name_adm1":"Pulau Pinang",
    "qs:name_adm2":"Timur Laut",
    "qs:name_lau":"George Town",
    "qs:name_local":"George Town",
    "qs:photo_max":82,
    "qs:photo_sum":276,
    "qs:placetype":"Suburb",
    "qs:quad_count":10,
    "qs:woe_adm0":23424901,
    "qs:woe_adm1":2346304,
    "qs:woe_adm2":56013581,
    "qs:woe_lau":56013803,
    "qs:woe_local":1141153,
    "qs:woe_ver":"7.10.0",
    "wof:lang":[
        "eng"
    ],
    "wof:name":"Kampong Makam",
    "wof:placetype":"neighbourhood"
},
  "geometry": {"coordinates":[100.31671799999999,5.415144],"type":"Point"}
}