{
  "type": "Feature",
  "properties": {
    "gn:admin1_code":"11",
    "gn:asciiname":"Kampung Sungai Pinang",
    "gn:country_code":"MY",
    "gn:dem":100,
    "gn:feature_class":"P",
    "gn:feature_code":"PPL",
    "gn:name":"Kampung Sungai Pinang",
    "gn:population":0,
    "gn:timezone":"Asia/Kuching",
    "iso:country":"MY",
    "name:und_x_variant":[
        "Kampong Sungai Pinang"
    ],
    "wof:name":"Kampung Sungai Pinang",
    "wof:placetype":"locality"
},
  "geometry": {"coordinates":[110.86985,1.08253],"type":"Point"}
}