{
  "type": "Feature",
  "properties": {
    "gn:admin1_code":"16.0",
    "gn:asciiname":"Kampung Manksulap",
    "gn:country_code":"MY",
    "gn:dem":538,
    "gn:feature_class":"P",
    "gn:feature_code":"PPL",
    "gn:name":"Kampung Manksulap",
    "gn:population":0,
    "gn:timezone":"Asia/Kuching",
    "iso:country":"MY",
    "name:msa_x_preferred":[
        "Kampung Manksulap"
    ],
    "wof:name":"Kampung Manksulap",
    "wof:placetype":"locality"
},
  "geometry": {"coordinates":[117.0215,6.3293],"type":"Point"}
}