{
  "type": "Feature",
  "properties": {
    "gn:admin1_code":"16",
    "gn:asciiname":"Kampung Kimangis",
    "gn:country_code":"MY",
    "gn:dem":166,
    "gn:feature_class":"P",
    "gn:feature_code":"PPL",
    "gn:name":"Kampung Kimangis",
    "gn:population":0,
    "gn:timezone":"Asia/Kuching",
    "iso:country":"MY",
    "name:msa_x_preferred":[
        "Kampung Kimangis"
    ],
    "name:und_x_variant":[
        "Kimangis",
        "Kampong Kimangis"
    ],
    "wof:name":"Kampung Kimangis",
    "wof:placetype":"locality"
},
  "geometry": {"coordinates":[116.9773,5.7225],"type":"Point"}
}