{
  "type": "Feature",
  "properties": {
    "gn:admin1_code":"5",
    "gn:asciiname":"Kampung Merual",
    "gn:country_code":"MY",
    "gn:dem":122,
    "gn:feature_class":"P",
    "gn:feature_code":"PPL",
    "gn:name":"Kampung Merual",
    "gn:population":0,
    "gn:timezone":"Asia/Kuala_Lumpur",
    "iso:country":"MY",
    "name:msa_x_preferred":[
        "Kampung Merual"
    ],
    "name:und_x_variant":[
        "Kampong Merual"
    ],
    "wof:name":"Kampung Merual",
    "wof:placetype":"locality"
},
  "geometry": {"coordinates":[102.1494,2.6812],"type":"Point"}
}