{
  "type": "Feature",
  "properties": {
    "gn:country":"MY",
    "gn:fcode":"PPL",
    "gn:population":0,
    "iso:country":"MY",
    "name:msa_x_preferred":[
        "Kampung Pelegong"
    ],
    "qs:name":"Kampong Pelegong",
    "qs:name_adm0":"Malaysia",
    "qs:name_adm1":"Negeri Sembilan",
    "qs:photos":24,
    "qs:photos_1k":5,
    "qs:photos_9k":1,
    "qs:photos_9r":1,
    "qs:photos_all":24,
    "qs:photos_sr":1,
    "qs:placetype":"Town",
    "qs:pop_sr":"0",
    "wof:name":"Kampong Pelegong",
    "wof:placetype":"locality",
    "wof:population":0
},
  "geometry": {"coordinates":[101.863,2.7515],"type":"Point"}
}