{
  "type": "Feature",
  "properties": {
    "gn:admin1_code":"8.0",
    "gn:asciiname":"Kampung Simpang Sanglang",
    "gn:cc2":"MY",
    "gn:country_code":"MY",
    "gn:dem":5,
    "gn:feature_class":"P",
    "gn:feature_code":"PPL",
    "gn:name":"Kampung Simpang Sanglang",
    "gn:population":0,
    "gn:timezone":"Asia/Kuala_Lumpur",
    "iso:country":"MY",
    "name:msa_x_preferred":[
        "Kampung Simpang Sanglang"
    ],
    "wof:name":"Kampung Simpang Sanglang",
    "wof:placetype":"locality"
},
  "geometry": {"coordinates":[100.19893999999999,6.27871],"type":"Point"}
}