{
  "type": "Feature",
  "properties": {
    "gn:admin1_code":"2",
    "gn:asciiname":"Kampung Banggol Lambak",
    "gn:cc2":"MY",
    "gn:country_code":"MY",
    "gn:dem":43,
    "gn:feature_class":"P",
    "gn:feature_code":"PPL",
    "gn:name":"Kampung Banggol Lambak",
    "gn:population":0,
    "gn:timezone":"Asia/Kuala_Lumpur",
    "iso:country":"MY",
    "name:msa_x_preferred":[
        "Kampung Banggol Lambak"
    ],
    "name:und_x_variant":[
        "Kampong Banggol Tambak"
    ],
    "wof:name":"Kampung Banggol Lambak",
    "wof:placetype":"locality"
},
  "geometry": {"coordinates":[100.73407,5.81451],"type":"Point"}
}