{
  "type": "Feature",
  "properties": {
    "gn:admin1_code":"1.0",
    "gn:asciiname":"Taman Chempaka Puteh",
    "gn:country_code":"MY",
    "gn:dem":19,
    "gn:feature_class":"P",
    "gn:feature_code":"PPL",
    "gn:name":"Taman Chempaka Puteh",
    "gn:population":0,
    "gn:timezone":"Asia/Kuala_Lumpur",
    "iso:country":"MY",
    "name:msa_x_preferred":[
        "Taman Chempaka Puteh"
    ],
    "wof:name":"Taman Chempaka Puteh",
    "wof:placetype":"locality"
},
  "geometry": {"coordinates":[102.97669999999999,1.8675],"type":"Point"}
}