{
  "type": "Feature",
  "properties": {
    "gn:admin1_code":"6.0",
    "gn:asciiname":"Kampung Gali",
    "gn:country_code":"MY",
    "gn:dem":121,
    "gn:feature_class":"P",
    "gn:feature_code":"PPL",
    "gn:name":"Kampung Gali",
    "gn:population":0,
    "gn:timezone":"Asia/Kuala_Lumpur",
    "iso:country":"MY",
    "name:msa_x_preferred":[
        "Kampung Gali"
    ],
    "wof:name":"Kampung Gali",
    "wof:placetype":"locality"
},
  "geometry": {"coordinates":[101.89230000000001,3.8539],"type":"Point"}
}