{
  "type": "Feature",
  "properties": {
    "gn:admin1_code":"6.0",
    "gn:asciiname":"Kampung Batu Satu Peramu",
    "gn:country_code":"MY",
    "gn:dem":11,
    "gn:feature_class":"P",
    "gn:feature_code":"PPL",
    "gn:name":"Kampung Batu Satu Peramu",
    "gn:population":0,
    "gn:timezone":"Asia/Kuala_Lumpur",
    "iso:country":"MY",
    "name:msa_x_preferred":[
        "Kampung Batu Satu Peramu"
    ],
    "wof:name":"Kampung Batu Satu Peramu",
    "wof:placetype":"locality"
},
  "geometry": {"coordinates":[103.3927,3.5188],"type":"Point"}
}