{
  "type": "Feature",
  "properties": {
    "gn:admin1_code":"2",
    "gn:asciiname":"Kampung Sungai Atu",
    "gn:cc2":"MY",
    "gn:country_code":"MY",
    "gn:dem":36,
    "gn:feature_class":"P",
    "gn:feature_code":"PPL",
    "gn:name":"Kampung Sungai Atu",
    "gn:population":0,
    "gn:timezone":"Asia/Kuala_Lumpur",
    "iso:country":"MY",
    "name:msa_x_preferred":[
        "Kampung Sungai Atu"
    ],
    "name:und_x_variant":[
        "Kampong Sungai Atun"
    ],
    "wof:name":"Kampung Sungai Atu",
    "wof:placetype":"locality"
},
  "geometry": {"coordinates":[100.38473,6.4486],"type":"Point"}
}