{
  "type": "Feature",
  "properties": {
    "gn:country":"MY",
    "gn:fcode":"PPL",
    "gn:pop":0,
    "iso:country":"MY",
    "name:msa_x_preferred":[
        "Taman Desa Jaya"
    ],
    "qs:name":"Taman Emas Jaya",
    "qs:name_adm0":"Malaysia",
    "qs:name_adm1":"Perak",
    "qs:photos_9r":0,
    "qs:photos_sr":0,
    "qs:placetype":"Town",
    "qs:pop_sr":"0",
    "wof:name":"Taman Emas Jaya",
    "wof:placetype":"locality",
    "wof:population":0
},
  "geometry": {"coordinates":[100.7534,4.2971],"type":"Point"}
}