{
  "type": "Feature",
  "properties": {
    "gn:admin1_code":"13",
    "gn:asciiname":"Kampung Masjid Haji Awang",
    "gn:country_code":"MY",
    "gn:dem":10,
    "gn:feature_class":"P",
    "gn:feature_code":"PPL",
    "gn:name":"Kampung Masjid Haji Awang",
    "gn:population":0,
    "gn:timezone":"Asia/Kuala_Lumpur",
    "iso:country":"MY",
    "name:msa_x_preferred":[
        "Kampung Masjid Haji Awang"
    ],
    "name:und_x_variant":[
        "Kampong Masjid Haji Awang"
    ],
    "wof:name":"Kampung Masjid Haji Awang",
    "wof:placetype":"locality"
},
  "geometry": {"coordinates":[103.2165,5.1992],"type":"Point"}
}