{
  "type": "Feature",
  "properties": {
    "gn:admin1_code":"16.0",
    "gn:asciiname":"Kampung Sakong Kecil",
    "gn:country_code":"MY",
    "gn:dem":3,
    "gn:feature_class":"P",
    "gn:feature_code":"PPL",
    "gn:name":"Kampung Sakong Kecil",
    "gn:population":0,
    "gn:timezone":"Asia/Kuching",
    "iso:country":"MY",
    "name:msa_x_preferred":[
        "Kampung Sakong Kecil"
    ],
    "wof:name":"Kampung Sakong Kecil",
    "wof:placetype":"locality"
},
  "geometry": {"coordinates":[118.5686,4.5202],"type":"Point"}
}