{
  "type": "Feature",
  "properties": {
    "gn:admin1_code":"7.0",
    "gn:asciiname":"Taman Bandaraya Utama",
    "gn:country_code":"MY",
    "gn:dem":52,
    "gn:feature_class":"P",
    "gn:feature_code":"PPL",
    "gn:name":"Taman Bandaraya Utama",
    "gn:population":0,
    "gn:timezone":"Asia/Kuala_Lumpur",
    "iso:country":"MY",
    "name:msa_x_preferred":[
        "Taman Bandaraya Utama"
    ],
    "wof:name":"Taman Bandaraya Utama",
    "wof:placetype":"locality"
},
  "geometry": {"coordinates":[101.10599999999999,4.6096],"type":"Point"}
}