{
  "type": "Feature",
  "properties": {
    "gn:admin1_code":"12.0",
    "gn:asciiname":"Taman Kanchong Laut",
    "gn:country_code":"MY",
    "gn:dem":6,
    "gn:feature_class":"P",
    "gn:feature_code":"PPL",
    "gn:name":"Taman Kanchong Laut",
    "gn:population":0,
    "gn:timezone":"Asia/Kuala_Lumpur",
    "iso:country":"MY",
    "name:msa_x_preferred":[
        "Taman Kanchong Laut"
    ],
    "wof:name":"Taman Kanchong Laut",
    "wof:placetype":"locality"
},
  "geometry": {"coordinates":[101.4662,2.7079],"type":"Point"}
}