{
  "type": "Feature",
  "properties": {
    "gn:admin1_code":"5.0",
    "gn:asciiname":"Orek",
    "gn:country_code":"MY",
    "gn:dem":106,
    "gn:feature_class":"P",
    "gn:feature_code":"PPL",
    "gn:name":"Orek",
    "gn:population":0,
    "gn:timezone":"Asia/Kuala_Lumpur",
    "iso:country":"MY",
    "name:aze_x_preferred":[
        "\u00d6r\u0259k"
    ],
    "name:bak_x_preferred":[
        "\u04e8\u0440\u04d9\u043a"
    ],
    "name:tat_x_preferred":[
        "\u04e8\u0440\u04d9\u043a"
    ],
    "name:tur_x_preferred":[
        "\u00d6rek"
    ],
    "wof:name":"Orek",
    "wof:placetype":"locality"
},
  "geometry": {"coordinates":[102.25,2.53333],"type":"Point"}
}