{
  "type": "Feature",
  "properties": {
    "gn:admin1_code":"6",
    "gn:asciiname":"Kampung Lubuk Lian",
    "gn:country_code":"MY",
    "gn:dem":39,
    "gn:feature_class":"P",
    "gn:feature_code":"PPL",
    "gn:name":"Kampung Lubuk Lian",
    "gn:population":0,
    "gn:timezone":"Asia/Kuala_Lumpur",
    "iso:country":"MY",
    "name:msa_x_preferred":[
        "Kampung Lubuk Lian"
    ],
    "name:und_x_variant":[
        "Kampong Lubok Lian"
    ],
    "wof:name":"Kampung Lubuk Lian",
    "wof:placetype":"locality"
},
  "geometry": {"coordinates":[102.5401,3.4008],"type":"Point"}
}