{
  "type": "Feature",
  "properties": {
    "gn:admin1_code":"16.0",
    "gn:asciiname":"Mansud",
    "gn:cc2":"MY",
    "gn:country_code":"MY",
    "gn:dem":14,
    "gn:feature_class":"P",
    "gn:feature_code":"PPL",
    "gn:name":"Mansud",
    "gn:population":0,
    "gn:timezone":"Asia/Kuching",
    "iso:country":"MY",
    "name:und_x_variant":[
        "Kampong Mansud",
        "Mansut",
        "Mansud"
    ],
    "wof:name":"Mansud",
    "wof:placetype":"locality"
},
  "geometry": {"coordinates":[115.48333,5.48333],"type":"Point"}
}