{
  "type": "Feature",
  "properties": {
    "gn:admin1_code":"1.0",
    "gn:asciiname":"Kampung Kenangan Dato' Abdullah Jaffar",
    "gn:country_code":"MY",
    "gn:dem":16,
    "gn:feature_class":"P",
    "gn:feature_code":"PPL",
    "gn:name":"Kampung Kenangan Dato\u2019 Abdullah Jaffar",
    "gn:population":0,
    "gn:timezone":"Asia/Kuala_Lumpur",
    "iso:country":"MY",
    "name:msa_x_preferred":[
        "Kampung Kenangan Dato\u2019 Abdullah Jaffar"
    ],
    "wof:name":"Kampung Kenangan Dato' Abdullah Jaffar",
    "wof:placetype":"locality"
},
  "geometry": {"coordinates":[102.6495,2.0445],"type":"Point"}
}