{
  "type": "Feature",
  "properties": {
    "gn:admin1_code":"7",
    "gn:asciiname":"Kampung Tanjung Sari",
    "gn:country_code":"MY",
    "gn:dem":4,
    "gn:feature_class":"P",
    "gn:feature_code":"PPL",
    "gn:name":"Kampung Tanjung Sari",
    "gn:population":0,
    "gn:timezone":"Asia/Kuala_Lumpur",
    "iso:country":"MY",
    "name:msa_x_preferred":[
        "Kampung Tanjung Sari"
    ],
    "name:und_x_variant":[
        "Kampong Tanjong Sari"
    ],
    "wof:name":"Kampung Tanjung Sari",
    "wof:placetype":"locality"
},
  "geometry": {"coordinates":[100.89870000000001,3.9683],"type":"Point"}
}