{
  "type": "Feature",
  "properties": {
    "gn:admin1_code":"1.0",
    "gn:asciiname":"Taman Chantik",
    "gn:country_code":"MY",
    "gn:dem":50,
    "gn:feature_class":"P",
    "gn:feature_code":"PPL",
    "gn:name":"Taman Chantik",
    "gn:population":0,
    "gn:timezone":"Asia/Kuala_Lumpur",
    "iso:country":"MY",
    "name:msa_x_preferred":[
        "Taman Chantik"
    ],
    "wof:name":"Taman Chantik",
    "wof:placetype":"locality"
},
  "geometry": {"coordinates":[103.61150000000001,1.6744],"type":"Point"}
}