{
  "type": "Feature",
  "properties": {
    "gn:admin1_code":"1.0",
    "gn:asciiname":"Kampung Pelentong",
    "gn:country_code":"MY",
    "gn:dem":18,
    "gn:feature_class":"P",
    "gn:feature_code":"PPL",
    "gn:name":"Kampung Pelentong",
    "gn:population":0,
    "gn:timezone":"Asia/Kuala_Lumpur",
    "iso:country":"MY",
    "name:msa_x_preferred":[
        "Kampung Pelentong"
    ],
    "wof:name":"Kampung Pelentong",
    "wof:placetype":"locality"
},
  "geometry": {"coordinates":[103.80589999999999,1.4943],"type":"Point"}
}