{
  "type": "Feature",
  "properties": {
    "gn:admin1_code":"5",
    "gn:asciiname":"Kampung Baharu",
    "gn:country_code":"MY",
    "gn:dem":30,
    "gn:feature_class":"P",
    "gn:feature_code":"PPL",
    "gn:name":"Kampung Baharu",
    "gn:population":0,
    "gn:timezone":"Asia/Kuala_Lumpur",
    "iso:country":"MY",
    "name:msa_x_preferred":[
        "Kampung Baharu"
    ],
    "name:und_x_variant":[
        "Kampong Baharu"
    ],
    "wof:name":"Kampung Baharu",
    "wof:placetype":"locality"
},
  "geometry": {"coordinates":[102.0889,2.4567],"type":"Point"}
}