{
  "type": "Feature",
  "properties": {
    "gn:admin1_code":"2.0",
    "gn:asciiname":"Kampung Bukit",
    "gn:country_code":"MY",
    "gn:dem":8,
    "gn:feature_class":"P",
    "gn:feature_code":"PPL",
    "gn:name":"Kampung Bukit",
    "gn:population":0,
    "gn:timezone":"Asia/Kuala_Lumpur",
    "iso:country":"MY",
    "name:msa_x_preferred":[
        "Kampung Bukit"
    ],
    "wof:name":"Kampung Bukit",
    "wof:placetype":"locality"
},
  "geometry": {"coordinates":[100.47593999999999,6.21791],"type":"Point"}
}