{
  "type": "Feature",
  "properties": {
    "gn:admin1_code":"1.0",
    "gn:asciiname":"Kampung Parit Haji Adnan",
    "gn:country_code":"MY",
    "gn:dem":13,
    "gn:feature_class":"P",
    "gn:feature_code":"PPL",
    "gn:name":"Kampung Parit Haji Adnan",
    "gn:population":0,
    "gn:timezone":"Asia/Kuala_Lumpur",
    "iso:country":"MY",
    "name:msa_x_preferred":[
        "Kampung Parit Haji Adnan"
    ],
    "wof:name":"Kampung Parit Haji Adnan",
    "wof:placetype":"locality"
},
  "geometry": {"coordinates":[103.4442,1.5801],"type":"Point"}
}