{
  "type": "Feature",
  "properties": {
    "gn:admin1_code":"16.0",
    "gn:asciiname":"Lumingi",
    "gn:country_code":"MY",
    "gn:dem":232,
    "gn:feature_class":"P",
    "gn:feature_code":"PPL",
    "gn:name":"Lumingi",
    "gn:population":0,
    "gn:timezone":"Asia/Kuching",
    "iso:country":"MY",
    "name:msa_x_preferred":[
        "Lumingi"
    ],
    "wof:name":"Lumingi",
    "wof:placetype":"locality"
},
  "geometry": {"coordinates":[116.42691000000001,4.38355],"type":"Point"}
}