{
  "type": "Feature",
  "properties": {
    "iso:country":"MY",
    "qs:name":"Kemumin",
    "qs:name_adm0":"Malaysia",
    "qs:name_adm1":"Kelantan",
    "qs:photos":42,
    "qs:photos_1k":9,
    "qs:photos_9k":1,
    "qs:photos_9r":5,
    "qs:photos_all":308,
    "qs:photos_sr":2,
    "qs:placetype":"LocalAdmin",
    "qs:pop_sr":"0",
    "wof:name":"Kemumin",
    "wof:placetype":"localadmin"
},
  "geometry": {"coordinates":[102.317562,6.151307],"type":"Point"}
}