{
  "type": "Feature",
  "properties": {
    "gn:admin1_code":"16",
    "gn:asciiname":"Kampung Kias",
    "gn:country_code":"MY",
    "gn:dem":612,
    "gn:feature_class":"P",
    "gn:feature_code":"PPL",
    "gn:name":"Kampung Kias",
    "gn:population":0,
    "gn:timezone":"Asia/Kuching",
    "iso:country":"MY",
    "name:msa_x_preferred":[
        "Kampung Kias"
    ],
    "name:und_x_variant":[
        "Kampong Kias"
    ],
    "wof:name":"Kampung Kias",
    "wof:placetype":"locality"
},
  "geometry": {"coordinates":[116.6773,6.3161],"type":"Point"}
}