{
  "type": "Feature",
  "properties": {
    "gn:admin1_code":"5",
    "gn:asciiname":"Kampung Seberang Paya",
    "gn:country_code":"MY",
    "gn:dem":41,
    "gn:feature_class":"P",
    "gn:feature_code":"PPL",
    "gn:name":"Kampung Seberang Paya",
    "gn:population":0,
    "gn:timezone":"Asia/Kuala_Lumpur",
    "iso:country":"MY",
    "name:msa_x_preferred":[
        "Kampung Seberang Paya"
    ],
    "name:und_x_variant":[
        "Kampong Seberang Paya"
    ],
    "wof:name":"Kampung Seberang Paya",
    "wof:placetype":"locality"
},
  "geometry": {"coordinates":[102.1729,2.5254],"type":"Point"}
}