{
  "type": "Feature",
  "properties": {
    "gn:admin1_code":"3.0",
    "gn:asciiname":"Kampung Pauh Butut",
    "gn:country_code":"MY",
    "gn:dem":15,
    "gn:feature_class":"P",
    "gn:feature_code":"PPL",
    "gn:name":"Kampung Pauh Butut",
    "gn:population":0,
    "gn:timezone":"Asia/Kuala_Lumpur",
    "iso:country":"MY",
    "name:msa_x_preferred":[
        "Kampung Pauh Butut"
    ],
    "wof:name":"Kampung Pauh Butut",
    "wof:placetype":"locality"
},
  "geometry": {"coordinates":[102.3473,5.9613],"type":"Point"}
}