{
  "type": "Feature",
  "properties": {
    "gn:admin1_code":"6.0",
    "gn:asciiname":"Kampung Ira",
    "gn:country_code":"MY",
    "gn:dem":39,
    "gn:feature_class":"P",
    "gn:feature_code":"PPL",
    "gn:name":"Kampung Ira",
    "gn:population":0,
    "gn:timezone":"Asia/Kuala_Lumpur",
    "iso:country":"MY",
    "name:msa_x_preferred":[
        "Kampung Ira"
    ],
    "name:und_x_variant":[
        "Kampong Ira",
        "Kampong Irek"
    ],
    "wof:name":"Kampung Ira",
    "wof:placetype":"locality"
},
  "geometry": {"coordinates":[102.44159999999999,3.4701],"type":"Point"}
}