{
  "type": "Feature",
  "properties": {
    "gn:admin1_code":"7.0",
    "gn:asciiname":"Taman Tasek Permai",
    "gn:country_code":"MY",
    "gn:dem":56,
    "gn:feature_class":"P",
    "gn:feature_code":"PPL",
    "gn:name":"Taman Tasek Permai",
    "gn:population":0,
    "gn:timezone":"Asia/Kuala_Lumpur",
    "iso:country":"MY",
    "name:msa_x_preferred":[
        "Taman Tasek Permai"
    ],
    "wof:name":"Taman Tasek Permai",
    "wof:placetype":"locality"
},
  "geometry": {"coordinates":[101.09529999999999,4.6559],"type":"Point"}
}