{
  "type": "Feature",
  "properties": {
    "gn:admin1_code":"16",
    "gn:asciiname":"Kampung Panandawan",
    "gn:country_code":"MY",
    "gn:dem":8,
    "gn:feature_class":"P",
    "gn:feature_code":"PPL",
    "gn:name":"Kampung Panandawan",
    "gn:population":0,
    "gn:timezone":"Asia/Kuching",
    "iso:country":"MY",
    "name:msa_x_preferred":[
        "Kampung Panandawan"
    ],
    "name:und_x_variant":[
        "Kampong Panandawan"
    ],
    "wof:name":"Kampung Panandawan",
    "wof:placetype":"locality"
},
  "geometry": {"coordinates":[116.2373,6.2327],"type":"Point"}
}