{
  "type": "Feature",
  "properties": {
    "gn:admin1_code":"11.0",
    "gn:asciiname":"Kampung Nanga Maruyu",
    "gn:cc2":"MY",
    "gn:country_code":"MY",
    "gn:dem":34,
    "gn:feature_class":"P",
    "gn:feature_code":"PPL",
    "gn:name":"Kampung Nanga Maruyu",
    "gn:population":0,
    "gn:timezone":"Asia/Kuching",
    "iso:country":"MY",
    "name:und_x_variant":[
        "Rumah Maruyu",
        "Rumah Brurt",
        "Kampung Nanga Maruyu"
    ],
    "wof:name":"Kampung Nanga Maruyu",
    "wof:placetype":"locality"
},
  "geometry": {"coordinates":[114.93333,4.38333],"type":"Point"}
}