{
  "type": "Feature",
  "properties": {
    "gn:admin1_code":"12.0",
    "gn:asciiname":"Kampung Batu Dua Jalan Ayer Hitam",
    "gn:country_code":"MY",
    "gn:dem":17,
    "gn:feature_class":"P",
    "gn:feature_code":"PPL",
    "gn:name":"Kampung Batu Dua Jalan Ayer Hitam",
    "gn:population":0,
    "gn:timezone":"Asia/Kuala_Lumpur",
    "iso:country":"MY",
    "name:msa_x_preferred":[
        "Kampung Batu Dua Jalan Ayer Hitam"
    ],
    "wof:name":"Kampung Batu Dua Jalan Ayer Hitam",
    "wof:placetype":"locality"
},
  "geometry": {"coordinates":[101.6688,2.8806],"type":"Point"}
}