{
  "type": "Feature",
  "properties": {
    "gn:admin1_code":"2",
    "gn:asciiname":"Kampung Bukit Aping",
    "gn:cc2":"MY",
    "gn:country_code":"MY",
    "gn:dem":15,
    "gn:feature_class":"P",
    "gn:feature_code":"PPL",
    "gn:name":"Kampung Bukit Aping",
    "gn:population":0,
    "gn:timezone":"Asia/Kuala_Lumpur",
    "iso:country":"MY",
    "name:msa_x_preferred":[
        "Kampung Bukit Aping"
    ],
    "name:und_x_variant":[
        "Kampong Bukit Aping"
    ],
    "wof:name":"Kampung Bukit Aping",
    "wof:placetype":"locality"
},
  "geometry": {"coordinates":[100.58659,5.13685],"type":"Point"}
}