{
  "type": "Feature",
  "properties": {
    "gn:admin1_code":"5.0",
    "gn:asciiname":"Kampung Geduhom Tengah",
    "gn:country_code":"MY",
    "gn:dem":103,
    "gn:feature_class":"P",
    "gn:feature_code":"PPL",
    "gn:name":"Kampung Geduhom Tengah",
    "gn:population":0,
    "gn:timezone":"Asia/Kuala_Lumpur",
    "iso:country":"MY",
    "name:msa_x_preferred":[
        "Kampung Geduhom Tengah"
    ],
    "wof:name":"Kampung Geduhom Tengah",
    "wof:placetype":"locality"
},
  "geometry": {"coordinates":[102.30759999999999,2.6526],"type":"Point"}
}