{
  "type": "Feature",
  "properties": {
    "gn:admin1_code":"1.0",
    "gn:asciiname":"Kampung Tenglu Batu Enam",
    "gn:country_code":"MY",
    "gn:dem":15,
    "gn:feature_class":"P",
    "gn:feature_code":"PPL",
    "gn:name":"Kampung Tenglu Batu Enam",
    "gn:population":0,
    "gn:timezone":"Asia/Kuala_Lumpur",
    "iso:country":"MY",
    "name:msa_x_preferred":[
        "Kampung Tenglu Batu Enam"
    ],
    "wof:name":"Kampung Tenglu Batu Enam",
    "wof:placetype":"locality"
},
  "geometry": {"coordinates":[103.7938,2.5112],"type":"Point"}
}