{
  "type": "Feature",
  "properties": {
    "gn:country":"MY",
    "gn:fcode":"ADM3",
    "gn:population":0,
    "iso:country":"MY",
    "name:ceb_x_preferred":[
        "Kubang Pasu"
    ],
    "name:msa_x_preferred":[
        "Kubang Pasu"
    ],
    "name:swe_x_preferred":[
        "Kubang Pasu"
    ],
    "qs:name":"Kubang Pasu",
    "qs:name_adm0":"Malaysia",
    "qs:name_adm1":"Kedah",
    "qs:photos":8,
    "qs:photos_1k":2,
    "qs:photos_9k":1,
    "qs:photos_9r":1,
    "qs:photos_all":8,
    "qs:photos_sr":1,
    "qs:placetype":"LocalAdmin",
    "qs:pop_sr":"0",
    "wd:wordcount":44,
    "wof:name":"Kubang Pasu",
    "wof:placetype":"localadmin",
    "wof:population":0
},
  "geometry": {"coordinates":[100.30177999999999,6.22908],"type":"Point"}
}