{
  "type": "Feature",
  "properties": {
    "gn:admin1_code":"16.0",
    "gn:asciiname":"Kampung Paradason",
    "gn:country_code":"MY",
    "gn:dem":57,
    "gn:feature_class":"P",
    "gn:feature_code":"PPL",
    "gn:name":"Kampung Paradason",
    "gn:population":0,
    "gn:timezone":"Asia/Kuching",
    "iso:country":"MY",
    "name:msa_x_preferred":[
        "Kampung Paradason"
    ],
    "wof:name":"Kampung Paradason",
    "wof:placetype":"locality"
},
  "geometry": {"coordinates":[116.7576,6.7742],"type":"Point"}
}