{
  "type": "Feature",
  "properties": {
    "gn:admin1_code":"1.0",
    "gn:asciiname":"Kampung Gelugor",
    "gn:country_code":"MY",
    "gn:dem":32,
    "gn:feature_class":"P",
    "gn:feature_code":"PPL",
    "gn:name":"Kampung Gelugor",
    "gn:population":0,
    "gn:timezone":"Asia/Kuala_Lumpur",
    "iso:country":"MY",
    "name:msa_x_preferred":[
        "Kampung Gelugor"
    ],
    "wof:name":"Kampung Gelugor",
    "wof:placetype":"locality"
},
  "geometry": {"coordinates":[102.6836,2.4483],"type":"Point"}
}