{
  "type": "Feature",
  "properties": {
    "gn:admin1_code":"3.0",
    "gn:asciiname":"Kampung Kalai",
    "gn:country_code":"MY",
    "gn:dem":109,
    "gn:feature_class":"P",
    "gn:feature_code":"PPL",
    "gn:name":"Kampung Kalai",
    "gn:population":0,
    "gn:timezone":"Asia/Kuala_Lumpur",
    "iso:country":"MY",
    "name:msa_x_preferred":[
        "Kampung Kalai"
    ],
    "wof:name":"Kampung Kalai",
    "wof:placetype":"locality"
},
  "geometry": {"coordinates":[101.73609999999999,5.7348],"type":"Point"}
}