{
  "type": "Feature",
  "properties": {
    "gn:admin1_code":"2.0",
    "gn:asciiname":"Padang Saga",
    "gn:country_code":"MY",
    "gn:dem":26,
    "gn:feature_class":"P",
    "gn:feature_code":"PPL",
    "gn:name":"Padang Saga",
    "gn:population":0,
    "gn:timezone":"Asia/Kuala_Lumpur",
    "iso:country":"MY",
    "wof:name":"Padang Saga",
    "wof:placetype":"locality"
},
  "geometry": {"coordinates":[99.76571,6.37365],"type":"Point"}
}