{
  "type": "Feature",
  "properties": {
    "gn:admin1_code":"2",
    "gn:asciiname":"Kampong Tanjong Seberang",
    "gn:country_code":"MY",
    "gn:dem":38,
    "gn:feature_class":"P",
    "gn:feature_code":"PPL",
    "gn:name":"Kampong Tanjong Seberang",
    "gn:population":0,
    "gn:timezone":"Asia/Kuala_Lumpur",
    "iso:country":"MY",
    "name:und_x_variant":[
        "Kampong Tanjong Sebrang",
        "Kampong Telok Seberang",
        "Kampong Tanjong Seberang"
    ],
    "wof:name":"Kampong Tanjong Seberang",
    "wof:placetype":"locality"
},
  "geometry": {"coordinates":[100.65372000000001,6.28285],"type":"Point"}
}