{
  "type": "Feature",
  "properties": {
    "gn:admin1_code":"4",
    "gn:asciiname":"Ramuan China Besar",
    "gn:country_code":"MY",
    "gn:dem":23,
    "gn:feature_class":"P",
    "gn:feature_code":"PPL",
    "gn:name":"Ramuan China Besar",
    "gn:population":0,
    "gn:timezone":"Asia/Kuala_Lumpur",
    "iso:country":"MY",
    "name:msa_x_preferred":[
        "Ramuan China Besar"
    ],
    "wof:name":"Ramuan China Besar",
    "wof:placetype":"locality"
},
  "geometry": {"coordinates":[102.08580000000001,2.3972],"type":"Point"}
}