{
  "type": "Feature",
  "properties": {
    "gn:admin1_code":"7.0",
    "gn:asciiname":"Taman Chong Kwee",
    "gn:country_code":"MY",
    "gn:dem":77,
    "gn:feature_class":"P",
    "gn:feature_code":"PPL",
    "gn:name":"Taman Chong Kwee",
    "gn:population":0,
    "gn:timezone":"Asia/Kuala_Lumpur",
    "iso:country":"MY",
    "name:msa_x_preferred":[
        "Taman Chong Kwee"
    ],
    "wof:name":"Taman Chong Kwee",
    "wof:placetype":"locality"
},
  "geometry": {"coordinates":[101.1652,4.6676],"type":"Point"}
}