{
  "type": "Feature",
  "properties": {
    "gn:admin1_code":"16.0",
    "gn:asciiname":"Kampung Mentalitip",
    "gn:country_code":"MY",
    "gn:dem":1,
    "gn:feature_class":"P",
    "gn:feature_code":"PPL",
    "gn:name":"Kampung Mentalitip",
    "gn:population":0,
    "gn:timezone":"Asia/Kuching",
    "iso:country":"MY",
    "name:und_x_variant":[
        "Mantilitip",
        "Kampung Mentalitip"
    ],
    "wof:name":"Kampung Mentalitip",
    "wof:placetype":"locality"
},
  "geometry": {"coordinates":[118.50839999999999,4.35659],"type":"Point"}
}