{
  "type": "Feature",
  "properties": {
    "gn:admin1_code":"6",
    "gn:asciiname":"Kampung Jeram Beserah",
    "gn:country_code":"MY",
    "gn:dem":12,
    "gn:feature_class":"P",
    "gn:feature_code":"PPL",
    "gn:name":"Kampung Jeram Beserah",
    "gn:population":0,
    "gn:timezone":"Asia/Kuala_Lumpur",
    "iso:country":"MY",
    "name:msa_x_preferred":[
        "Kampung Jeram Beserah"
    ],
    "name:und_x_variant":[
        "Kampong Jeram Beserah"
    ],
    "wof:name":"Kampung Jeram Beserah",
    "wof:placetype":"locality"
},
  "geometry": {"coordinates":[103.3631,3.8587],"type":"Point"}
}