{
  "type": "Feature",
  "properties": {
    "gn:admin1_code":"1.0",
    "gn:asciiname":"Kampung Baru Tengah",
    "gn:country_code":"MY",
    "gn:dem":19,
    "gn:feature_class":"P",
    "gn:feature_code":"PPL",
    "gn:name":"Kampung Baru Tengah",
    "gn:population":0,
    "gn:timezone":"Asia/Kuala_Lumpur",
    "iso:country":"MY",
    "name:msa_x_preferred":[
        "Kampung Baru Tengah"
    ],
    "wof:name":"Kampung Baru Tengah",
    "wof:placetype":"locality"
},
  "geometry": {"coordinates":[102.8272,2.5318],"type":"Point"}
}