{
  "type": "Feature",
  "properties": {
    "gn:admin1_code":"16",
    "gn:asciiname":"Lantas",
    "gn:country_code":"MY",
    "gn:dem":77,
    "gn:feature_class":"P",
    "gn:feature_code":"PPL",
    "gn:name":"Lantas",
    "gn:population":0,
    "gn:timezone":"Asia/Kuching",
    "iso:country":"MY",
    "name:msa_x_preferred":[
        "Lantas"
    ],
    "wof:name":"Lantas",
    "wof:placetype":"locality"
},
  "geometry": {"coordinates":[116.81793999999999,5.21962],"type":"Point"}
}