{
  "type": "Feature",
  "properties": {
    "gn:admin1_code":"11.0",
    "gn:asciiname":"Rumah Chok",
    "gn:country_code":"MY",
    "gn:dem":11,
    "gn:feature_class":"P",
    "gn:feature_code":"PPL",
    "gn:name":"Rumah Chok",
    "gn:population":0,
    "gn:timezone":"Asia/Kuching",
    "iso:country":"MY",
    "name:msa_x_preferred":[
        "Rumah Chok"
    ],
    "wof:name":"Rumah Chok",
    "wof:placetype":"locality"
},
  "geometry": {"coordinates":[112.15423,2.13992],"type":"Point"}
}