{
  "type": "Feature",
  "properties": {
    "gn:admin1_code":"11",
    "gn:asciiname":"Rumah Belayon",
    "gn:country_code":"MY",
    "gn:dem":74,
    "gn:feature_class":"P",
    "gn:feature_code":"PPL",
    "gn:name":"Rumah Belayon",
    "gn:population":0,
    "gn:timezone":"Asia/Kuching",
    "iso:country":"MY",
    "wof:name":"Rumah Belayon",
    "wof:placetype":"locality"
},
  "geometry": {"coordinates":[113.15000000000001,2.03333],"type":"Point"}
}