{
  "type": "Feature",
  "properties": {
    "gn:admin1_code":"12.0",
    "gn:asciiname":"Kampung Sungai Merbau",
    "gn:country_code":"MY",
    "gn:dem":52,
    "gn:feature_class":"P",
    "gn:feature_code":"PPL",
    "gn:name":"Kampung Sungai Merbau",
    "gn:population":0,
    "gn:timezone":"Asia/Kuala_Lumpur",
    "iso:country":"MY",
    "name:msa_x_preferred":[
        "Kampung Sungai Merbau"
    ],
    "wof:name":"Kampung Sungai Merbau",
    "wof:placetype":"locality"
},
  "geometry": {"coordinates":[101.5261,3.6689],"type":"Point"}
}