{
  "type": "Feature",
  "properties": {
    "gn:admin1_code":"16",
    "gn:asciiname":"Kampong Panglima",
    "gn:cc2":"MY",
    "gn:country_code":"MY",
    "gn:dem":33,
    "gn:feature_class":"P",
    "gn:feature_code":"PPL",
    "gn:name":"Kampong Panglima",
    "gn:population":0,
    "gn:timezone":"Asia/Kuching",
    "iso:country":"MY",
    "name:und_x_variant":[
        "Panglima",
        "Kampong Panglima"
    ],
    "wof:name":"Kampong Panglima",
    "wof:placetype":"locality"
},
  "geometry": {"coordinates":[117.28333000000001,6.23333],"type":"Point"}
}