{
  "type": "Feature",
  "properties": {
    "gn:admin1_code":"6",
    "gn:asciiname":"Kampung Pauh Bugis",
    "gn:country_code":"MY",
    "gn:dem":11,
    "gn:feature_class":"P",
    "gn:feature_code":"PPL",
    "gn:name":"Kampung Pauh Bugis",
    "gn:population":0,
    "gn:timezone":"Asia/Kuala_Lumpur",
    "iso:country":"MY",
    "name:und_x_variant":[
        "Kampong Pauh Bugis"
    ],
    "wof:name":"Kampung Pauh Bugis",
    "wof:placetype":"locality"
},
  "geometry": {"coordinates":[103.36758,3.03035],"type":"Point"}
}