{
  "type": "Feature",
  "properties": {
    "gn:admin1_code":"12",
    "gn:asciiname":"Kampung Sungai Merab Hulu",
    "gn:country_code":"MY",
    "gn:dem":52,
    "gn:feature_class":"P",
    "gn:feature_code":"PPL",
    "gn:name":"Kampung Sungai Merab Hulu",
    "gn:population":0,
    "gn:timezone":"Asia/Kuala_Lumpur",
    "iso:country":"MY",
    "name:msa_x_preferred":[
        "Kampung Sungai Merab Hulu"
    ],
    "name:und_x_variant":[
        "Kampong Bangkahulu",
        "Kampong Sungai Merab Hulu"
    ],
    "wof:name":"Kampung Sungai Merab Hulu",
    "wof:placetype":"locality"
},
  "geometry": {"coordinates":[101.7324,2.921],"type":"Point"}
}