{
  "type": "Feature",
  "properties": {
    "gn:admin1_code":"11",
    "gn:asciiname":"Rumah Biar",
    "gn:country_code":"MY",
    "gn:dem":13,
    "gn:feature_class":"P",
    "gn:feature_code":"PPL",
    "gn:name":"Rumah Biar",
    "gn:population":0,
    "gn:timezone":"Asia/Kuching",
    "iso:country":"MY",
    "name:msa_x_preferred":[
        "Rumah Biar"
    ],
    "wof:name":"Rumah Biar",
    "wof:placetype":"locality"
},
  "geometry": {"coordinates":[114.04940000000001,4.0258],"type":"Point"}
}