{
  "type": "Feature",
  "properties": {
    "gn:admin1_code":"16.0",
    "gn:asciiname":"Takon",
    "gn:country_code":"MY",
    "gn:dem":7,
    "gn:feature_class":"P",
    "gn:feature_code":"PPL",
    "gn:name":"Takon",
    "gn:population":0,
    "gn:timezone":"Asia/Kuching",
    "iso:country":"MY",
    "name:msa_x_preferred":[
        "Takon"
    ],
    "wof:name":"Takon",
    "wof:placetype":"locality"
},
  "geometry": {"coordinates":[118.65989999999999,4.9404],"type":"Point"}
}