{
  "type": "Feature",
  "properties": {
    "gn:admin1_code":"11.0",
    "gn:asciiname":"Rumah Jamba",
    "gn:country_code":"MY",
    "gn:dem":54,
    "gn:feature_class":"P",
    "gn:feature_code":"PPL",
    "gn:name":"Rumah Jamba",
    "gn:population":0,
    "gn:timezone":"Asia/Kuching",
    "iso:country":"MY",
    "wof:name":"Rumah Jamba",
    "wof:placetype":"locality"
},
  "geometry": {"coordinates":[112.95,2.68333],"type":"Point"}
}