{
  "type": "Feature",
  "properties": {
    "gn:admin1_code":"2",
    "gn:asciiname":"Kampung Lahar Pumpong",
    "gn:country_code":"MY",
    "gn:dem":5,
    "gn:feature_class":"P",
    "gn:feature_code":"PPL",
    "gn:name":"Kampung Lahar Pumpong",
    "gn:population":0,
    "gn:timezone":"Asia/Kuala_Lumpur",
    "iso:country":"MY",
    "name:msa_x_preferred":[
        "Kampung Lahar Pumpong"
    ],
    "name:und_x_variant":[
        "Kampong Lahar Pumpong"
    ],
    "wof:name":"Kampung Lahar Pumpong",
    "wof:placetype":"locality"
},
  "geometry": {"coordinates":[100.32843,6.06555],"type":"Point"}
}