{
  "type": "Feature",
  "properties": {
    "gn:admin1_code":"5.0",
    "gn:asciiname":"Ladang Sengkang",
    "gn:country_code":"MY",
    "gn:dem":16,
    "gn:feature_class":"P",
    "gn:feature_code":"PPL",
    "gn:name":"Ladang Sengkang",
    "gn:population":0,
    "gn:timezone":"Asia/Kuala_Lumpur",
    "iso:country":"MY",
    "name:msa_x_preferred":[
        "Ladang Sengkang"
    ],
    "wof:name":"Ladang Sengkang",
    "wof:placetype":"locality"
},
  "geometry": {"coordinates":[101.93429999999999,2.4261],"type":"Point"}
}