{
  "type": "Feature",
  "properties": {
    "iso:country":"MY",
    "name:eng_x_preferred":[
        "Brighton"
    ],
    "name:unk_x_variant":[
        "Brighton"
    ],
    "qs:gn_adm0_cc":"MY",
    "qs:gn_local":1738050,
    "qs:gn_nam_loc":"miri",
    "qs:gn_namadm1":"11",
    "qs:local_max":22,
    "qs:local_sum":37,
    "qs:localhoods":2,
    "qs:name":"Brighton",
    "qs:name_adm0":"Malaysia",
    "qs:name_adm1":"Sarawak",
    "qs:name_adm2":"Division Miri",
    "qs:name_lau":"Miri",
    "qs:name_local":"Miri",
    "qs:photo_max":7,
    "qs:photo_sum":22,
    "qs:placetype":"Suburb",
    "qs:quad_count":4,
    "qs:woe_adm0":23424901,
    "qs:woe_adm1":2346305,
    "qs:woe_adm2":56013598,
    "qs:woe_lau":56014633,
    "qs:woe_local":1154932,
    "qs:woe_ver":"7.10.0",
    "wof:lang":[
        "eng"
    ],
    "wof:name":"Brighton",
    "wof:placetype":"neighbourhood"
},
  "geometry": {"coordinates":[114.00487699999999,4.373549],"type":"Point"}
}