{
  "type": "Feature",
  "properties": {
    "gn:admin1_code":"13",
    "gn:asciiname":"Kampung Padang Mengkuang",
    "gn:country_code":"MY",
    "gn:dem":16,
    "gn:feature_class":"P",
    "gn:feature_code":"PPL",
    "gn:name":"Kampung Padang Mengkuang",
    "gn:population":0,
    "gn:timezone":"Asia/Kuala_Lumpur",
    "iso:country":"MY",
    "name:msa_x_preferred":[
        "Kampung Padang Mengkuang"
    ],
    "name:und_x_variant":[
        "Kampong Padang Mengkuang"
    ],
    "wof:name":"Kampung Padang Mengkuang",
    "wof:placetype":"locality"
},
  "geometry": {"coordinates":[103.1074,5.2103],"type":"Point"}
}