{
  "type": "Feature",
  "properties": {
    "gn:admin1_code":"11.0",
    "gn:asciiname":"Rumah Ngadan",
    "gn:country_code":"MY",
    "gn:dem":25,
    "gn:feature_class":"P",
    "gn:feature_code":"PPL",
    "gn:name":"Rumah Ngadan",
    "gn:population":0,
    "gn:timezone":"Asia/Kuching",
    "iso:country":"MY",
    "name:msa_x_preferred":[
        "Rumah Ngadan"
    ],
    "wof:name":"Rumah Ngadan",
    "wof:placetype":"locality"
},
  "geometry": {"coordinates":[113.76313,3.90029],"type":"Point"}
}