{
  "type": "Feature",
  "properties": {
    "gn:admin1_code":"3",
    "gn:asciiname":"Kampong Chedok",
    "gn:country_code":"MY",
    "gn:dem":39,
    "gn:feature_class":"P",
    "gn:feature_code":"PPL",
    "gn:name":"Kampong Chedok",
    "gn:population":0,
    "gn:timezone":"Asia/Kuala_Lumpur",
    "iso:country":"MY",
    "name:und_x_variant":[
        "Kampong Ceduk",
        "Kampong Chedok"
    ],
    "wof:name":"Kampong Chedok",
    "wof:placetype":"locality"
},
  "geometry": {"coordinates":[101.89505,5.81376],"type":"Point"}
}