{
  "type": "Feature",
  "properties": {
    "gn:admin1_code":"1",
    "gn:asciiname":"Kampung Pelantar",
    "gn:country_code":"MY",
    "gn:dem":2,
    "gn:feature_class":"P",
    "gn:feature_code":"PPL",
    "gn:name":"Kampung Pelantar",
    "gn:population":0,
    "gn:timezone":"Asia/Kuala_Lumpur",
    "iso:country":"MY",
    "name:msa_x_preferred":[
        "Kampung Pelantar"
    ],
    "name:und_x_variant":[
        "Kampong Pelantar"
    ],
    "wof:name":"Kampung Pelantar",
    "wof:placetype":"locality"
},
  "geometry": {"coordinates":[104.15560000000001,1.3953],"type":"Point"}
}