{
  "type": "Feature",
  "properties": {
    "iso:country":"MY",
    "qs:name":"Taman Central",
    "qs:name_adm0":"Malaysia",
    "qs:name_adm1":"Sarawak",
    "qs:photos":210,
    "qs:photos_1k":43,
    "qs:photos_9k":1,
    "qs:photos_9r":4,
    "qs:photos_all":210,
    "qs:photos_sr":4,
    "qs:placetype":"Town",
    "qs:pop_sr":"0",
    "wof:name":"Taman Central",
    "wof:placetype":"locality"
},
  "geometry": {"coordinates":[110.35890999999999,1.552975],"type":"Point"}
}