{
  "type": "Feature",
  "properties": {
    "gn:admin1_code":"11",
    "gn:asciiname":"Kampong Empila",
    "gn:cc2":"MY",
    "gn:country_code":"MY",
    "gn:dem":23,
    "gn:feature_class":"P",
    "gn:feature_code":"PPL",
    "gn:name":"Kampong Empila",
    "gn:population":0,
    "gn:timezone":"Asia/Kuching",
    "iso:country":"MY",
    "name:und_x_variant":[
        "Kampong Stila",
        "Kampong Empila"
    ],
    "wof:name":"Kampong Empila",
    "wof:placetype":"locality"
},
  "geometry": {"coordinates":[110.46666999999999,1.33333],"type":"Point"}
}