{
  "type": "Feature",
  "properties": {
    "gn:admin1_code":"5.0",
    "gn:asciiname":"Kampung Kepis Ilir",
    "gn:country_code":"MY",
    "gn:dem":89,
    "gn:feature_class":"P",
    "gn:feature_code":"PPL",
    "gn:name":"Kampung Kepis Ilir",
    "gn:population":0,
    "gn:timezone":"Asia/Kuala_Lumpur",
    "iso:country":"MY",
    "name:msa_x_preferred":[
        "Kampung Kepis Ilir"
    ],
    "wof:name":"Kampung Kepis Ilir",
    "wof:placetype":"locality"
},
  "geometry": {"coordinates":[102.3383,2.7054],"type":"Point"}
}