{
  "type": "Feature",
  "properties": {
    "gn:admin1_code":"2.0",
    "gn:asciiname":"Kampung Bukit Cham",
    "gn:cc2":"MY",
    "gn:country_code":"MY",
    "gn:dem":62,
    "gn:feature_class":"P",
    "gn:feature_code":"PPL",
    "gn:name":"Kampung Bukit Cham",
    "gn:population":0,
    "gn:timezone":"Asia/Kuala_Lumpur",
    "iso:country":"MY",
    "name:msa_x_preferred":[
        "Kampung Bukit Cham"
    ],
    "name:und_x_variant":[
        "Kampong Bukit Cham"
    ],
    "wof:name":"Kampung Bukit Cham",
    "wof:placetype":"locality"
},
  "geometry": {"coordinates":[100.62846999999999,5.88746],"type":"Point"}
}