{
  "type": "Feature",
  "properties": {
    "gn:admin1_code":"16.0",
    "gn:asciiname":"Kampung Kormangis",
    "gn:country_code":"MY",
    "gn:dem":77,
    "gn:feature_class":"P",
    "gn:feature_code":"PPL",
    "gn:name":"Kampung Kormangis",
    "gn:population":0,
    "gn:timezone":"Asia/Kuching",
    "iso:country":"MY",
    "name:msa_x_preferred":[
        "Kampung Kormangis"
    ],
    "wof:name":"Kampung Kormangis",
    "wof:placetype":"locality"
},
  "geometry": {"coordinates":[117.1024,6.2553],"type":"Point"}
}