{
  "type": "Feature",
  "properties": {
    "gn:admin1_code":"7",
    "gn:asciiname":"Kampong Ulu Simpol",
    "gn:country_code":"MY",
    "gn:dem":272,
    "gn:feature_class":"P",
    "gn:feature_code":"PPL",
    "gn:name":"Kampong Ulu Simpol",
    "gn:population":0,
    "gn:timezone":"Asia/Kuala_Lumpur",
    "iso:country":"MY",
    "wof:name":"Kampong Ulu Simpol",
    "wof:placetype":"locality"
},
  "geometry": {"coordinates":[100.88333,5.13333],"type":"Point"}
}