{
  "type": "Feature",
  "properties": {
    "gn:admin1_code":"6.0",
    "gn:asciiname":"Kampung Paya Pasir",
    "gn:country_code":"MY",
    "gn:dem":40,
    "gn:feature_class":"P",
    "gn:feature_code":"PPL",
    "gn:name":"Kampung Paya Pasir",
    "gn:population":0,
    "gn:timezone":"Asia/Kuala_Lumpur",
    "iso:country":"MY",
    "name:msa_x_preferred":[
        "Kampung Paya Pasir"
    ],
    "wof:name":"Kampung Paya Pasir",
    "wof:placetype":"locality"
},
  "geometry": {"coordinates":[102.7764,3.5754],"type":"Point"}
}