{
  "type": "Feature",
  "properties": {
    "gn:admin1_code":"16.0",
    "gn:asciiname":"Merotai",
    "gn:country_code":"MY",
    "gn:dem":22,
    "gn:elevation":"0.0",
    "gn:feature_class":"P",
    "gn:feature_code":"PPL",
    "gn:name":"Merotai",
    "gn:population":0,
    "gn:timezone":"Asia/Kuching",
    "iso:country":"MY",
    "name:und_x_variant":[
        "Kampong Merotai Besar",
        "Merotai",
        "Morutai",
        "Merutal",
        "Moratai",
        "Merutai"
    ],
    "wof:name":"Merotai",
    "wof:placetype":"locality"
},
  "geometry": {"coordinates":[117.77249999999999,4.4222],"type":"Point"}
}