{
  "type": "Feature",
  "properties": {
    "gn:admin1_code":"1.0",
    "gn:asciiname":"Calet Rawa",
    "gn:country_code":"MY",
    "gn:dem":7,
    "gn:feature_class":"P",
    "gn:feature_code":"PPL",
    "gn:name":"Calet Rawa",
    "gn:population":0,
    "gn:timezone":"Asia/Kuala_Lumpur",
    "iso:country":"MY",
    "name:msa_x_preferred":[
        "Calet Rawa"
    ],
    "wof:name":"Calet Rawa",
    "wof:placetype":"locality"
},
  "geometry": {"coordinates":[103.97618,2.51853],"type":"Point"}
}