{
  "type": "Feature",
  "properties": {
    "gn:admin1_code":"11.0",
    "gn:asciiname":"Kampung Nombor Dua",
    "gn:cc2":"MY",
    "gn:country_code":"MY",
    "gn:dem":8,
    "gn:feature_class":"P",
    "gn:feature_code":"PPL",
    "gn:name":"Kampung Nombor Dua",
    "gn:population":0,
    "gn:timezone":"Asia/Kuching",
    "iso:country":"MY",
    "name:und_x_variant":[
        "Kampung No 2",
        "Kampung Nombor Dua"
    ],
    "wof:name":"Kampung Nombor Dua",
    "wof:placetype":"locality"
},
  "geometry": {"coordinates":[110.33138999999998,1.56028],"type":"Point"}
}