{
  "type": "Feature",
  "properties": {
    "gn:admin1_code":"5.0",
    "gn:asciiname":"Kampung Ulu Rokan",
    "gn:country_code":"MY",
    "gn:dem":101,
    "gn:feature_class":"P",
    "gn:feature_code":"PPL",
    "gn:name":"Kampung Ulu Rokan",
    "gn:population":0,
    "gn:timezone":"Asia/Kuala_Lumpur",
    "iso:country":"MY",
    "name:msa_x_preferred":[
        "Kampung Ulu Rokan"
    ],
    "wof:name":"Kampung Ulu Rokan",
    "wof:placetype":"locality"
},
  "geometry": {"coordinates":[102.372,2.5761],"type":"Point"}
}