{
  "type": "Feature",
  "properties": {
    "iso:country":"MY",
    "name:eng_x_preferred":[
        "Pengerang"
    ],
    "name:epo_x_preferred":[
        "Pengerang"
    ],
    "name:jpn_x_preferred":[
        "\u30da\u30f3\u30b2\u30e9\u30f3"
    ],
    "name:msa_x_preferred":[
        "Pengerang"
    ],
    "name:nld_x_preferred":[
        "Pengerang"
    ],
    "name:zho_x_preferred":[
        "\u8fb9\u4f73\u5170"
    ],
    "qs:name":"Pengerang",
    "qs:name_adm0":"Malaysia",
    "qs:name_adm1":"Johor",
    "qs:photos":186,
    "qs:photos_1k":38,
    "qs:photos_9k":1,
    "qs:photos_9r":4,
    "qs:photos_all":219,
    "qs:photos_sr":4,
    "qs:placetype":"LocalAdmin",
    "qs:pop_sr":"0",
    "wd:wordcount":845,
    "wof:name":"Pengerang",
    "wof:placetype":"localadmin"
},
  "geometry": {"coordinates":[104.11159499999999,1.369611],"type":"Point"}
}