{
  "type": "Feature",
  "properties": {
    "iso:country":"MY",
    "qs:name":"Pengerang",
    "qs:name_adm0":"Malaysia",
    "qs:name_adm1":"Johor",
    "qs:photos":186,
    "qs:photos_1k":38,
    "qs:photos_9k":1,
    "qs:photos_9r":4,
    "qs:photos_all":219,
    "qs:photos_sr":4,
    "qs:placetype":"LocalAdmin",
    "qs:pop_sr":"0",
    "wd:wordcount":845,
    "wof:name":"Pengerang",
    "wof:placetype":"localadmin"
},
  "geometry": {"coordinates":[104.11159499999999,1.369611],"type":"Point"}
}