{
  "type": "Feature",
  "properties": {
    "gn:admin1_code":"2.0",
    "gn:asciiname":"Kampung Tok Ang",
    "gn:country_code":"MY",
    "gn:dem":23,
    "gn:feature_class":"P",
    "gn:feature_code":"PPL",
    "gn:name":"Kampung Tok Ang",
    "gn:population":0,
    "gn:timezone":"Asia/Kuala_Lumpur",
    "iso:country":"MY",
    "name:msa_x_preferred":[
        "Kampung Tok Ang"
    ],
    "wof:name":"Kampung Tok Ang",
    "wof:placetype":"locality"
},
  "geometry": {"coordinates":[100.38603000000001,5.80283],"type":"Point"}
}