{
  "type": "Feature",
  "properties": {
    "gn:admin1_code":"6",
    "gn:asciiname":"Kampung Kacu",
    "gn:country_code":"MY",
    "gn:dem":133,
    "gn:feature_class":"P",
    "gn:feature_code":"PPL",
    "gn:name":"Kampung Kacu",
    "gn:population":0,
    "gn:timezone":"Asia/Kuala_Lumpur",
    "iso:country":"MY",
    "name:und_x_variant":[
        "Kampong Kachu"
    ],
    "wof:name":"Kampung Kacu",
    "wof:placetype":"locality"
},
  "geometry": {"coordinates":[102.04051,4.37751],"type":"Point"}
}