{
  "type": "Feature",
  "properties": {
    "gn:admin1_code":"5",
    "gn:asciiname":"Kampung Kubu",
    "gn:country_code":"MY",
    "gn:dem":60,
    "gn:feature_class":"P",
    "gn:feature_code":"PPL",
    "gn:name":"Kampung Kubu",
    "gn:population":0,
    "gn:timezone":"Asia/Kuala_Lumpur",
    "iso:country":"MY",
    "name:msa_x_preferred":[
        "Kampung Kubu"
    ],
    "name:und_x_variant":[
        "Kampong Kubu"
    ],
    "wof:name":"Kampung Kubu",
    "wof:placetype":"locality"
},
  "geometry": {"coordinates":[102.0776,2.6018],"type":"Point"}
}