{
  "type": "Feature",
  "properties": {
    "gn:asciiname":"Fortune Park Kepong",
    "gn:country_code":"MY",
    "gn:dem":65,
    "gn:feature_class":"P",
    "gn:feature_code":"PPL",
    "gn:name":"Fortune Park Kepong",
    "gn:population":0,
    "gn:timezone":"Asia/Kuala_Lumpur",
    "iso:country":"MY",
    "wof:name":"Fortune Park Kepong",
    "wof:placetype":"locality"
},
  "geometry": {"coordinates":[101.64091999999999,3.21944],"type":"Point"}
}