{
  "type": "Feature",
  "properties": {
    "gn:admin1_code":"16.0",
    "gn:asciiname":"Limbahau",
    "gn:cc2":"MY",
    "gn:country_code":"MY",
    "gn:dem":9,
    "gn:feature_class":"P",
    "gn:feature_code":"PPL",
    "gn:name":"Limbahau",
    "gn:population":0,
    "gn:timezone":"Asia/Kuching",
    "iso:country":"MY",
    "name:und_x_variant":[
        "Kampong Limbahau",
        "Limbahau"
    ],
    "wof:name":"Limbahau",
    "wof:placetype":"locality"
},
  "geometry": {"coordinates":[115.95,5.71667],"type":"Point"}
}