{
  "type": "Feature",
  "properties": {
    "gn:admin1_code":"6",
    "gn:asciiname":"Kampung Durian Tawar",
    "gn:country_code":"MY",
    "gn:dem":38,
    "gn:feature_class":"P",
    "gn:feature_code":"PPL",
    "gn:name":"Kampung Durian Tawar",
    "gn:population":0,
    "gn:timezone":"Asia/Kuala_Lumpur",
    "iso:country":"MY",
    "name:msa_x_preferred":[
        "Kampung Durian Tawar"
    ],
    "name:und_x_variant":[
        "Kampong Durian Tawar"
    ],
    "wof:name":"Kampung Durian Tawar",
    "wof:placetype":"locality"
},
  "geometry": {"coordinates":[102.44410000000001,3.3473],"type":"Point"}
}