{
  "type": "Feature",
  "properties": {
    "gn:admin1_code":"4",
    "gn:asciiname":"Kampung Sungai Jerneh",
    "gn:country_code":"MY",
    "gn:dem":21,
    "gn:feature_class":"P",
    "gn:feature_code":"PPL",
    "gn:name":"Kampung Sungai Jerneh",
    "gn:population":0,
    "gn:timezone":"Asia/Kuala_Lumpur",
    "iso:country":"MY",
    "name:msa_x_preferred":[
        "Kampung Sungai Jerneh"
    ],
    "name:und_x_variant":[
        "Kampong Sungai Jerneh"
    ],
    "wof:name":"Kampung Sungai Jerneh",
    "wof:placetype":"locality"
},
  "geometry": {"coordinates":[102.0924,2.4369],"type":"Point"}
}