{
  "type": "Feature",
  "properties": {
    "gn:admin1_code":"7.0",
    "gn:asciiname":"Lake Town",
    "gn:country_code":"MY",
    "gn:dem":18,
    "gn:elevation":"0.0",
    "gn:feature_class":"P",
    "gn:feature_code":"PPLL",
    "gn:name":"Lake Town",
    "gn:population":0,
    "gn:timezone":"Asia/Kuala_Lumpur",
    "iso:country":"MY",
    "wof:name":"Lake Town",
    "wof:placetype":"locality"
},
  "geometry": {"coordinates":[100.66086,4.99437],"type":"Point"}
}