{
  "type": "Feature",
  "properties": {
    "gn:admin1_code":"13",
    "gn:asciiname":"Kampung Selat Beladau",
    "gn:country_code":"MY",
    "gn:dem":10,
    "gn:feature_class":"P",
    "gn:feature_code":"PPL",
    "gn:name":"Kampung Selat Beladau",
    "gn:population":0,
    "gn:timezone":"Asia/Kuala_Lumpur",
    "iso:country":"MY",
    "name:msa_x_preferred":[
        "Kampung Selat Beladau"
    ],
    "name:und_x_variant":[
        "Kampong Selat Beladau"
    ],
    "wof:name":"Kampung Selat Beladau",
    "wof:placetype":"locality"
},
  "geometry": {"coordinates":[103.086,5.2754],"type":"Point"}
}