{
  "type": "Feature",
  "properties": {
    "gn:admin1_code":"5.0",
    "gn:asciiname":"Kampung Kubang Rusa",
    "gn:country_code":"MY",
    "gn:dem":84,
    "gn:feature_class":"P",
    "gn:feature_code":"PPL",
    "gn:name":"Kampung Kubang Rusa",
    "gn:population":0,
    "gn:timezone":"Asia/Kuala_Lumpur",
    "iso:country":"MY",
    "name:msa_x_preferred":[
        "Kampung Kubang Rusa"
    ],
    "wof:name":"Kampung Kubang Rusa",
    "wof:placetype":"locality"
},
  "geometry": {"coordinates":[102.26439999999999,2.7648],"type":"Point"}
}