{
  "type": "Feature",
  "properties": {
    "iso:country":"MY",
    "name:und_x_preferred":[
        "Taman Seri Kemang"
    ],
    "name:unk_x_variant":[
        "Taman Seri Kemang"
    ],
    "qs:gn_adm0_cc":"MY",
    "qs:gn_local":1732738,
    "qs:gn_nam_loc":"Kota Tinggi, Kota Tinggi, Kota Tinggi, Johor, MY",
    "qs:gn_namadm1":"01",
    "qs:local_max":12,
    "qs:local_sum":12,
    "qs:localhoods":1,
    "qs:name":"Taman Seri Kemang",
    "qs:name_adm0":"Malaysia",
    "qs:name_adm1":"Johor",
    "qs:name_adm2":"Kota Tinggi",
    "qs:name_lau":"Kota Tinggi",
    "qs:name_local":"Kota Tinggi",
    "qs:photo_max":12,
    "qs:photo_sum":12,
    "qs:placetype":"Suburb",
    "qs:quad_count":1,
    "qs:woe_adm0":23424901,
    "qs:woe_adm1":2346296,
    "qs:woe_adm2":56013594,
    "qs:woe_lau":56013904,
    "qs:woe_local":1154764,
    "qs:woe_ver":"7.10.0",
    "wof:lang":[
        "unk"
    ],
    "wof:name":"Taman Seri Kemang",
    "wof:placetype":"neighbourhood"
},
  "geometry": {"coordinates":[103.900452,1.727338],"type":"Point"}
}