{
  "type": "Feature",
  "properties": {
    "gn:admin1_code":"5",
    "gn:asciiname":"Rahang Kechil",
    "gn:country_code":"MY",
    "gn:dem":49,
    "gn:feature_class":"P",
    "gn:feature_code":"PPL",
    "gn:name":"Rahang Kechil",
    "gn:population":0,
    "gn:timezone":"Asia/Kuala_Lumpur",
    "iso:country":"MY",
    "name:msa_x_preferred":[
        "Rahang Kechil"
    ],
    "wof:name":"Rahang Kechil",
    "wof:placetype":"locality"
},
  "geometry": {"coordinates":[101.95529999999999,2.7097],"type":"Point"}
}