{
  "type": "Feature",
  "properties": {
    "gn:admin1_code":"7",
    "gn:asciiname":"Kampung Sungai Batang",
    "gn:country_code":"MY",
    "gn:dem":6,
    "gn:feature_class":"P",
    "gn:feature_code":"PPL",
    "gn:name":"Kampung Sungai Batang",
    "gn:population":0,
    "gn:timezone":"Asia/Kuala_Lumpur",
    "iso:country":"MY",
    "name:msa_x_preferred":[
        "Kampung Sungai Batang"
    ],
    "name:und_x_variant":[
        "Kampong Sungai Batang"
    ],
    "wof:name":"Kampung Sungai Batang",
    "wof:placetype":"locality"
},
  "geometry": {"coordinates":[100.7906,3.8971],"type":"Point"}
}