{
  "type": "Feature",
  "properties": {
    "gn:admin1_code":"9.0",
    "gn:asciiname":"Titi Perupok",
    "gn:country_code":"MY",
    "gn:dem":41,
    "gn:feature_class":"P",
    "gn:feature_code":"PPL",
    "gn:name":"Titi Perupok",
    "gn:population":0,
    "gn:timezone":"Asia/Kuala_Lumpur",
    "iso:country":"MY",
    "name:msa_x_preferred":[
        "Titi Perupok"
    ],
    "name:msa_x_variant":[
        "Titi Prupo"
    ],
    "wof:name":"Titi Perupok",
    "wof:placetype":"locality"
},
  "geometry": {"coordinates":[100.23309999999999,5.35874],"type":"Point"}
}