{
  "type": "Feature",
  "properties": {
    "gn:admin1_code":"6",
    "gn:asciiname":"Kampong Kuala Tersang",
    "gn:country_code":"MY",
    "gn:dem":137,
    "gn:feature_class":"P",
    "gn:feature_code":"PPL",
    "gn:name":"Kampong Kuala Tersang",
    "gn:population":0,
    "gn:timezone":"Asia/Kuala_Lumpur",
    "iso:country":"MY",
    "wof:name":"Kampong Kuala Tersang",
    "wof:placetype":"locality"
},
  "geometry": {"coordinates":[101.83333,3.96667],"type":"Point"}
}