{
  "type": "Feature",
  "properties": {
    "gn:admin1_code":"3.0",
    "gn:asciiname":"Kampung Baru Batu Papan",
    "gn:country_code":"MY",
    "gn:dem":105,
    "gn:feature_class":"P",
    "gn:feature_code":"PPL",
    "gn:name":"Kampung Baru Batu Papan",
    "gn:population":0,
    "gn:timezone":"Asia/Kuala_Lumpur",
    "iso:country":"MY",
    "name:msa_x_preferred":[
        "Kampung Baru Batu Papan"
    ],
    "wof:name":"Kampung Baru Batu Papan",
    "wof:placetype":"locality"
},
  "geometry": {"coordinates":[101.94759999999999,4.8411],"type":"Point"}
}