{
  "type": "Feature",
  "properties": {
    "gn:admin1_code":"16.0",
    "gn:asciiname":"Kampung Dualog",
    "gn:country_code":"MY",
    "gn:dem":29,
    "gn:feature_class":"P",
    "gn:feature_code":"PPL",
    "gn:name":"Kampung Dualog",
    "gn:population":0,
    "gn:timezone":"Asia/Kuching",
    "iso:country":"MY",
    "name:msa_x_preferred":[
        "Kampung Dualog"
    ],
    "name:und_x_variant":[
        "Dualog"
    ],
    "wof:name":"Kampung Dualog",
    "wof:placetype":"locality"
},
  "geometry": {"coordinates":[116.7577,6.83],"type":"Point"}
}