{
  "type": "Feature",
  "properties": {
    "gn:admin1_code":"2.0",
    "gn:asciiname":"Pantai Ara",
    "gn:cc2":"MY",
    "gn:country_code":"MY",
    "gn:dem":21,
    "gn:feature_class":"P",
    "gn:feature_code":"PPL",
    "gn:name":"Pantai Ara",
    "gn:population":0,
    "gn:timezone":"Asia/Kuala_Lumpur",
    "iso:country":"MY",
    "name:msa_x_preferred":[
        "Pantai Ara"
    ],
    "wof:name":"Pantai Ara",
    "wof:placetype":"locality"
},
  "geometry": {"coordinates":[100.65586999999999,5.66067],"type":"Point"}
}