{
  "type": "Feature",
  "properties": {
    "gn:admin1_code":"11.0",
    "gn:asciiname":"Kampung Matu",
    "gn:country_code":"MY",
    "gn:dem":3,
    "gn:feature_class":"P",
    "gn:feature_code":"PPL",
    "gn:name":"Kampung Matu",
    "gn:population":0,
    "gn:timezone":"Asia/Kuching",
    "iso:country":"MY",
    "wof:name":"Kampung Matu",
    "wof:placetype":"locality"
},
  "geometry": {"coordinates":[110.37582999999999,1.56278],"type":"Point"}
}