{
  "type": "Feature",
  "properties": {
    "iso:country":"MY",
    "name:und_x_variant":[
        "Straits View"
    ],
    "qs:gn_adm0_cc":"MY",
    "qs:gn_local":1732752,
    "qs:local_max":681,
    "qs:local_sum":3607,
    "qs:localhoods":29,
    "qs:name":"Straits View",
    "qs:name_adm0":"Malaysia",
    "qs:name_adm1":"Johor",
    "qs:name_adm2":"Johor Bahru",
    "qs:name_lau":"Plentong",
    "qs:name_local":"Johor Baharu",
    "qs:photo_max":378,
    "qs:photo_sum":529,
    "qs:placetype":"Suburb",
    "qs:quad_count":12,
    "qs:woe_adm0":23424901,
    "qs:woe_adm1":2346296,
    "qs:woe_adm2":56013565,
    "qs:woe_lau":56014160,
    "qs:woe_local":1154698,
    "qs:woe_ver":"7.10.0",
    "wd:wordcount":57,
    "wof:lang":[
        "unk"
    ],
    "wof:name":"Straits View",
    "wof:placetype":"neighbourhood"
},
  "geometry": {"coordinates":[103.72280000000001,1.477043],"type":"Point"}
}