{
  "type": "Feature",
  "properties": {
    "gn:admin1_code":"5.0",
    "gn:asciiname":"Kampung Teluk Kemang",
    "gn:country_code":"MY",
    "gn:dem":21,
    "gn:feature_class":"P",
    "gn:feature_code":"PPL",
    "gn:name":"Kampung Teluk Kemang",
    "gn:population":0,
    "gn:timezone":"Asia/Kuala_Lumpur",
    "iso:country":"MY",
    "name:msa_x_preferred":[
        "Kampung Teluk Kemang"
    ],
    "name:und_x_variant":[
        "Kampong Telok Kemang",
        "Telok Kemang",
        "Kampung Teluk Kemang"
    ],
    "wof:name":"Kampung Teluk Kemang",
    "wof:placetype":"locality"
},
  "geometry": {"coordinates":[101.85951,2.46146],"type":"Point"}
}