{
  "type": "Feature",
  "properties": {
    "gn:admin1_code":"7",
    "gn:asciiname":"Kampung Teluk Nipah",
    "gn:country_code":"MY",
    "gn:dem":12,
    "gn:feature_class":"P",
    "gn:feature_code":"PPL",
    "gn:name":"Kampung Teluk Nipah",
    "gn:population":0,
    "gn:timezone":"Asia/Kuala_Lumpur",
    "iso:country":"MY",
    "name:msa_x_preferred":[
        "Kampung Teluk Nipah"
    ],
    "name:und_x_variant":[
        "Kampong Telok Nipah",
        "Kampung Teluk Nipah"
    ],
    "wof:name":"Kampung Teluk Nipah",
    "wof:placetype":"locality"
},
  "geometry": {"coordinates":[100.54730000000001,4.2326],"type":"Point"}
}