{
  "type": "Feature",
  "properties": {
    "gn:admin1_code":"5",
    "gn:asciiname":"Kampung Jeram",
    "gn:country_code":"MY",
    "gn:dem":128,
    "gn:feature_class":"P",
    "gn:feature_code":"PPL",
    "gn:name":"Kampung Jeram",
    "gn:population":0,
    "gn:timezone":"Asia/Kuala_Lumpur",
    "iso:country":"MY",
    "name:msa_x_preferred":[
        "Kampung Jeram"
    ],
    "name:und_x_variant":[
        "Kampong Jeram"
    ],
    "wof:name":"Kampung Jeram",
    "wof:placetype":"locality"
},
  "geometry": {"coordinates":[102.152,2.7876],"type":"Point"}
}