{
  "type": "Feature",
  "properties": {
    "gn:admin1_code":"16.0",
    "gn:asciiname":"Kampong Kulambat Dundau",
    "gn:country_code":"MY",
    "gn:dem":6,
    "gn:feature_class":"P",
    "gn:feature_code":"PPL",
    "gn:name":"Kampong Kulambat Dundau",
    "gn:population":0,
    "gn:timezone":"Asia/Kuching",
    "iso:country":"MY",
    "name:msa_x_preferred":[
        "Kampong Kulambat Dundau"
    ],
    "wof:name":"Kampong Kulambat Dundau",
    "wof:placetype":"locality"
},
  "geometry": {"coordinates":[116.386,6.3819],"type":"Point"}
}