{
  "type": "Feature",
  "properties": {
    "gn:admin1_code":"1",
    "gn:asciiname":"Kampung Baharu",
    "gn:country_code":"MY",
    "gn:dem":14,
    "gn:feature_class":"P",
    "gn:feature_code":"PPL",
    "gn:name":"Kampung Baharu",
    "gn:population":0,
    "gn:timezone":"Asia/Kuala_Lumpur",
    "iso:country":"MY",
    "name:msa_x_preferred":[
        "Kampung Baharu"
    ],
    "name:und_x_variant":[
        "Kampong Bahru",
        "Kampong Baharu",
        "Kampung Baharu"
    ],
    "wof:name":"Kampung Baharu",
    "wof:placetype":"locality"
},
  "geometry": {"coordinates":[104.0989,1.3688],"type":"Point"}
}