{
  "type": "Feature",
  "properties": {
    "gn:admin1_code":"5.0",
    "gn:asciiname":"Kampung Bukit Kelulut",
    "gn:country_code":"MY",
    "gn:dem":70,
    "gn:feature_class":"P",
    "gn:feature_code":"PPL",
    "gn:name":"Kampung Bukit Kelulut",
    "gn:population":0,
    "gn:timezone":"Asia/Kuala_Lumpur",
    "iso:country":"MY",
    "name:msa_x_preferred":[
        "Kampung Bukit Kelulut"
    ],
    "wof:name":"Kampung Bukit Kelulut",
    "wof:placetype":"locality"
},
  "geometry": {"coordinates":[102.3592,2.8138],"type":"Point"}
}