{
  "type": "Feature",
  "properties": {
    "gn:admin1_code":"6",
    "gn:asciiname":"Kampung Batu Bor",
    "gn:country_code":"MY",
    "gn:dem":29,
    "gn:feature_class":"P",
    "gn:feature_code":"PPL",
    "gn:name":"Kampung Batu Bor",
    "gn:population":0,
    "gn:timezone":"Asia/Kuala_Lumpur",
    "iso:country":"MY",
    "name:msa_x_preferred":[
        "Kampung Batu Bor"
    ],
    "name:und_x_variant":[
        "Kampong Batu Bor"
    ],
    "wof:name":"Kampung Batu Bor",
    "wof:placetype":"locality"
},
  "geometry": {"coordinates":[102.5789,3.4269],"type":"Point"}
}