{
  "type": "Feature",
  "properties": {
    "gn:admin1_code":"1.0",
    "gn:asciiname":"Kampung Ayer Puteri",
    "gn:country_code":"MY",
    "gn:dem":38,
    "gn:feature_class":"P",
    "gn:feature_code":"PPL",
    "gn:name":"Kampung Ayer Puteri",
    "gn:population":0,
    "gn:timezone":"Asia/Kuala_Lumpur",
    "iso:country":"MY",
    "name:msa_x_preferred":[
        "Kampung Ayer Puteri"
    ],
    "wof:name":"Kampung Ayer Puteri",
    "wof:placetype":"locality"
},
  "geometry": {"coordinates":[103.8563,2.4166],"type":"Point"}
}