{
  "type": "Feature",
  "properties": {
    "gn:admin1_code":"16",
    "gn:asciiname":"Kampung Kalibinatong",
    "gn:country_code":"MY",
    "gn:dem":301,
    "gn:feature_class":"P",
    "gn:feature_code":"PPL",
    "gn:name":"Kampung Kalibinatong",
    "gn:population":0,
    "gn:timezone":"Asia/Kuching",
    "iso:country":"MY",
    "name:msa_x_preferred":[
        "Kampung Kalibinatong"
    ],
    "name:und_x_variant":[
        "Kampong Kalibinatong"
    ],
    "wof:name":"Kampung Kalibinatong",
    "wof:placetype":"locality"
},
  "geometry": {"coordinates":[116.6148,6.5357],"type":"Point"}
}