{
  "type": "Feature",
  "properties": {
    "gn:admin1_code":"11.0",
    "gn:asciiname":"Kampung Tanjung Apong",
    "gn:country_code":"MY",
    "gn:dem":4,
    "gn:feature_class":"P",
    "gn:feature_code":"PPL",
    "gn:name":"Kampung Tanjung Apong",
    "gn:population":0,
    "gn:timezone":"Asia/Kuching",
    "iso:country":"MY",
    "name:und_x_variant":[
        "Kampong Tanjong Apong",
        "Kampung Tanjung Apong"
    ],
    "wof:name":"Kampung Tanjung Apong",
    "wof:placetype":"locality"
},
  "geometry": {"coordinates":[109.90898,1.67806],"type":"Point"}
}