{
  "type": "Feature",
  "properties": {
    "iso:country":"MY",
    "name:und_x_variant":[
        "Taman Selat"
    ],
    "qs:gn_adm0_cc":"MY",
    "qs:gn_fcode":"PPL",
    "qs:gn_local":1735076,
    "qs:gn_namadm1":"09",
    "qs:gn_name":"Taman Selamat",
    "qs:local_max":267,
    "qs:local_sum":384,
    "qs:localhoods":4,
    "qs:name":"Taman Selat",
    "qs:name_adm0":"Malaysia",
    "qs:name_adm1":"Pulau Pinang",
    "qs:name_adm2":"Seberang Perai Utara",
    "qs:name_lau":"Mukim 15",
    "qs:name_local":"Butterworth",
    "qs:photo_max":37,
    "qs:photo_sum":267,
    "qs:placetype":"Suburb",
    "qs:quad_count":23,
    "qs:woe_adm0":23424901,
    "qs:woe_adm1":2346304,
    "qs:woe_adm2":56013561,
    "qs:woe_lau":56013869,
    "qs:woe_local":1154632,
    "qs:woe_ver":"7.10.0",
    "wof:lang":[
        "unk"
    ],
    "wof:name":"Taman Selat",
    "wof:placetype":"neighbourhood"
},
  "geometry": {"coordinates":[100.36242300000001,5.402719],"type":"Point"}
}