{
  "type": "Feature",
  "properties": {
    "gn:admin1_code":"7",
    "gn:asciiname":"Kampung Sungai Sempit",
    "gn:country_code":"MY",
    "gn:dem":8,
    "gn:feature_class":"P",
    "gn:feature_code":"PPL",
    "gn:name":"Kampung Sungai Sempit",
    "gn:population":0,
    "gn:timezone":"Asia/Kuala_Lumpur",
    "iso:country":"MY",
    "name:msa_x_preferred":[
        "Kampung Sungai Sempit"
    ],
    "name:und_x_variant":[
        "Kampong Sungai Sempit"
    ],
    "wof:name":"Kampung Sungai Sempit",
    "wof:placetype":"locality"
},
  "geometry": {"coordinates":[100.62139999999999,4.2732],"type":"Point"}
}