{
  "type": "Feature",
  "properties": {
    "gn:admin1_code":"6.0",
    "gn:asciiname":"Kampung Lecir",
    "gn:country_code":"MY",
    "gn:dem":114,
    "gn:feature_class":"P",
    "gn:feature_code":"PPL",
    "gn:name":"Kampung Lecir",
    "gn:population":0,
    "gn:timezone":"Asia/Kuala_Lumpur",
    "iso:country":"MY",
    "name:msa_x_preferred":[
        "Kampung Lecir"
    ],
    "wof:name":"Kampung Lecir",
    "wof:placetype":"locality"
},
  "geometry": {"coordinates":[102.09220000000001,4.0099],"type":"Point"}
}