{
  "type": "Feature",
  "properties": {
    "gn:admin1_code":"4.0",
    "gn:asciiname":"Kampung Man Lok",
    "gn:country_code":"MY",
    "gn:dem":15,
    "gn:feature_class":"P",
    "gn:feature_code":"PPL",
    "gn:name":"Kampung Man Lok",
    "gn:population":0,
    "gn:timezone":"Asia/Kuala_Lumpur",
    "iso:country":"MY",
    "name:msa_x_preferred":[
        "Kampung Man Lok"
    ],
    "wof:name":"Kampung Man Lok",
    "wof:placetype":"locality"
},
  "geometry": {"coordinates":[102.0424,2.3697],"type":"Point"}
}