{
  "type": "Feature",
  "properties": {
    "gn:admin1_code":"9",
    "gn:asciiname":"Kampong Tanjong Putus",
    "gn:country_code":"MY",
    "gn:dem":10,
    "gn:feature_class":"P",
    "gn:feature_code":"PPL",
    "gn:name":"Kampong Tanjong Putus",
    "gn:population":0,
    "gn:timezone":"Asia/Kuala_Lumpur",
    "iso:country":"MY",
    "wof:name":"Kampong Tanjong Putus",
    "wof:placetype":"locality"
},
  "geometry": {"coordinates":[100.41667,5.43333],"type":"Point"}
}