{
  "type": "Feature",
  "properties": {
    "gn:admin1_code":"2",
    "gn:asciiname":"Kampung Banggul Berangan",
    "gn:cc2":"MY",
    "gn:country_code":"MY",
    "gn:dem":113,
    "gn:feature_class":"P",
    "gn:feature_code":"PPL",
    "gn:name":"Kampung Banggul Berangan",
    "gn:population":0,
    "gn:timezone":"Asia/Kuala_Lumpur",
    "iso:country":"MY",
    "name:msa_x_preferred":[
        "Kampung Banggul Berangan"
    ],
    "name:und_x_variant":[
        "Kampong Banggol Berangan"
    ],
    "wof:name":"Kampung Banggul Berangan",
    "wof:placetype":"locality"
},
  "geometry": {"coordinates":[100.85836,6.06041],"type":"Point"}
}