{
  "type": "Feature",
  "properties": {
    "gn:admin1_code":"2",
    "gn:asciiname":"Kampung Sungai Ular",
    "gn:cc2":"MY",
    "gn:country_code":"MY",
    "gn:dem":46,
    "gn:feature_class":"P",
    "gn:feature_code":"PPL",
    "gn:name":"Kampung Sungai Ular",
    "gn:population":0,
    "gn:timezone":"Asia/Kuala_Lumpur",
    "iso:country":"MY",
    "name:msa_x_preferred":[
        "Kampung Sungai Ular"
    ],
    "name:und_x_variant":[
        "Kampong Sungai Ular"
    ],
    "wof:name":"Kampung Sungai Ular",
    "wof:placetype":"locality"
},
  "geometry": {"coordinates":[100.58508,5.37623],"type":"Point"}
}