{
  "type": "Feature",
  "properties": {
    "gn:admin1_code":"5.0",
    "gn:asciiname":"Kampung Anak Ayer Kanji",
    "gn:country_code":"MY",
    "gn:dem":117,
    "gn:feature_class":"P",
    "gn:feature_code":"PPL",
    "gn:name":"Kampung Anak Ayer Kanji",
    "gn:population":0,
    "gn:timezone":"Asia/Kuala_Lumpur",
    "iso:country":"MY",
    "name:msa_x_preferred":[
        "Kampung Anak Ayer Kanji"
    ],
    "wof:name":"Kampung Anak Ayer Kanji",
    "wof:placetype":"locality"
},
  "geometry": {"coordinates":[102.3643,2.5773],"type":"Point"}
}