{
  "type": "Feature",
  "properties": {
    "gn:admin1_code":"16.0",
    "gn:asciiname":"Kampung Ligagon",
    "gn:country_code":"MY",
    "gn:dem":71,
    "gn:feature_class":"P",
    "gn:feature_code":"PPL",
    "gn:name":"Kampung Ligagon",
    "gn:population":0,
    "gn:timezone":"Asia/Kuching",
    "iso:country":"MY",
    "name:msa_x_preferred":[
        "Kampung Ligagon"
    ],
    "wof:name":"Kampung Ligagon",
    "wof:placetype":"locality"
},
  "geometry": {"coordinates":[115.83929999999999,5.4175],"type":"Point"}
}