{
  "type": "Feature",
  "properties": {
    "gn:admin1_code":"6.0",
    "gn:asciiname":"Taman Sri Semantan",
    "gn:country_code":"MY",
    "gn:dem":40,
    "gn:feature_class":"P",
    "gn:feature_code":"PPL",
    "gn:name":"Taman Sri Semantan",
    "gn:population":0,
    "gn:timezone":"Asia/Kuala_Lumpur",
    "iso:country":"MY",
    "name:msa_x_preferred":[
        "Taman Sri Semantan"
    ],
    "wof:name":"Taman Sri Semantan",
    "wof:placetype":"locality"
},
  "geometry": {"coordinates":[102.38330000000001,3.4734],"type":"Point"}
}