{
  "type": "Feature",
  "properties": {
    "gn:admin1_code":"11",
    "gn:asciiname":"Rumah Gerina",
    "gn:cc2":"MY",
    "gn:country_code":"MY",
    "gn:dem":65,
    "gn:feature_class":"P",
    "gn:feature_code":"PPL",
    "gn:name":"Rumah Gerina",
    "gn:population":0,
    "gn:timezone":"Asia/Kuching",
    "iso:country":"MY",
    "name:und_x_variant":[
        "Rumah Grina",
        "Rumah Grino",
        "Rumah Gerina"
    ],
    "wof:name":"Rumah Gerina",
    "wof:placetype":"locality"
},
  "geometry": {"coordinates":[111.95,1.76667],"type":"Point"}
}