{
  "type": "Feature",
  "properties": {
    "gn:admin1_code":"8.0",
    "gn:asciiname":"Kampung Tunjong",
    "gn:country_code":"MY",
    "gn:dem":21,
    "gn:feature_class":"P",
    "gn:feature_code":"PPL",
    "gn:name":"Kampung Tunjong",
    "gn:population":0,
    "gn:timezone":"Asia/Kuala_Lumpur",
    "iso:country":"MY",
    "name:msa_x_preferred":[
        "Kampung Tunjang"
    ],
    "name:msa_x_variant":[
        "Kampung Tunjong"
    ],
    "name:und_x_variant":[
        "Kampong Tunjang"
    ],
    "wof:name":"Kampung Tunjong",
    "wof:placetype":"locality"
},
  "geometry": {"coordinates":[100.24265,6.52236],"type":"Point"}
}