{
  "type": "Feature",
  "properties": {
    "gn:admin1_code":"11",
    "gn:asciiname":"Shop",
    "gn:country_code":"MY",
    "gn:dem":118,
    "gn:feature_class":"P",
    "gn:feature_code":"PPL",
    "gn:name":"Shop",
    "gn:population":0,
    "gn:timezone":"Asia/Kuching",
    "iso:country":"MY",
    "name:deu_x_preferred":[
        "Shop"
    ],
    "name:urd_x_preferred":[
        "\u062f\u06a9\u0627\u0646"
    ],
    "wof:name":"Shop",
    "wof:placetype":"locality"
},
  "geometry": {"coordinates":[111.81667,1.65],"type":"Point"}
}