{
  "type": "Feature",
  "properties": {
    "gn:admin1_code":"6",
    "gn:asciiname":"Kampung Legor",
    "gn:country_code":"MY",
    "gn:dem":26,
    "gn:feature_class":"P",
    "gn:feature_code":"PPL",
    "gn:name":"Kampung Legor",
    "gn:population":0,
    "gn:timezone":"Asia/Kuala_Lumpur",
    "iso:country":"MY",
    "name:und_x_variant":[
        "Kampong Legor"
    ],
    "wof:name":"Kampung Legor",
    "wof:placetype":"locality"
},
  "geometry": {"coordinates":[102.78433,3.52703],"type":"Point"}
}