{
  "type": "Feature",
  "properties": {
    "gn:admin1_code":"11",
    "gn:asciiname":"Kampong Sekeduk Baharu",
    "gn:cc2":"MY",
    "gn:country_code":"MY",
    "gn:dem":52,
    "gn:feature_class":"P",
    "gn:feature_code":"PPL",
    "gn:name":"Kampong Sekeduk Baharu",
    "gn:population":0,
    "gn:timezone":"Asia/Kuching",
    "iso:country":"MY",
    "name:und_x_variant":[
        "Kampong Skrak",
        "Kampong Skrak Baharu",
        "Kampong Sekeduk Baharu"
    ],
    "wof:name":"Kampong Sekeduk Baharu",
    "wof:placetype":"locality"
},
  "geometry": {"coordinates":[110.36667,1.38333],"type":"Point"}
}