{
  "type": "Feature",
  "properties": {
    "gn:admin1_code":"13",
    "gn:asciiname":"Kampung Nibung",
    "gn:country_code":"MY",
    "gn:dem":6,
    "gn:feature_class":"P",
    "gn:feature_code":"PPL",
    "gn:name":"Kampung Nibung",
    "gn:population":0,
    "gn:timezone":"Asia/Kuala_Lumpur",
    "iso:country":"MY",
    "name:msa_x_preferred":[
        "Kampung Nibung"
    ],
    "name:und_x_variant":[
        "Kampong Nibong"
    ],
    "wof:name":"Kampung Nibung",
    "wof:placetype":"locality"
},
  "geometry": {"coordinates":[103.14870000000001,5.3038],"type":"Point"}
}