{
  "type": "Feature",
  "properties": {
    "gn:admin1_code":"3",
    "gn:asciiname":"Pasir Tumboh",
    "gn:country_code":"MY",
    "gn:dem":14,
    "gn:feature_class":"P",
    "gn:feature_code":"PPL",
    "gn:name":"Pasir Tumboh",
    "gn:population":0,
    "gn:timezone":"Asia/Kuala_Lumpur",
    "iso:country":"MY",
    "wof:name":"Pasir Tumboh",
    "wof:placetype":"locality"
},
  "geometry": {"coordinates":[102.28333000000001,6.06667],"type":"Point"}
}