{
  "type": "Feature",
  "properties": {
    "gn:admin1_code":"16",
    "gn:asciiname":"Kampung Binturu",
    "gn:country_code":"MY",
    "gn:dem":9,
    "gn:feature_class":"P",
    "gn:feature_code":"PPL",
    "gn:name":"Kampung Binturu",
    "gn:population":0,
    "gn:timezone":"Asia/Kuching",
    "iso:country":"MY",
    "name:msa_x_preferred":[
        "Kampung Binturu"
    ],
    "name:und_x_variant":[
        "Kampong Binturu"
    ],
    "wof:name":"Kampung Binturu",
    "wof:placetype":"locality"
},
  "geometry": {"coordinates":[115.6082,5.5932],"type":"Point"}
}