{
  "type": "Feature",
  "properties": {
    "gn:admin1_code":"9",
    "gn:asciiname":"Permatang Rambai",
    "gn:cc2":"MY",
    "gn:country_code":"MY",
    "gn:dem":6,
    "gn:feature_class":"P",
    "gn:feature_code":"PPL",
    "gn:name":"Permatang Rambai",
    "gn:population":0,
    "gn:timezone":"Asia/Kuala_Lumpur",
    "iso:country":"MY",
    "name:msa_x_preferred":[
        "Permatang Rambai"
    ],
    "name:msa_x_variant":[
        "Kampung Permatang Rambai"
    ],
    "wof:name":"Permatang Rambai",
    "wof:placetype":"locality"
},
  "geometry": {"coordinates":[100.43521,5.41533],"type":"Point"}
}