{
  "type": "Feature",
  "properties": {
    "gn:admin1_code":"12.0",
    "gn:asciiname":"Permai Ampang",
    "gn:country_code":"MY",
    "gn:dem":80,
    "gn:feature_class":"P",
    "gn:feature_code":"PPL",
    "gn:name":"Permai Ampang",
    "gn:population":0,
    "gn:timezone":"Asia/Kuala_Lumpur",
    "iso:country":"MY",
    "name:msa_x_preferred":[
        "Permai Ampang"
    ],
    "wof:name":"Permai Ampang",
    "wof:placetype":"locality"
},
  "geometry": {"coordinates":[101.7791,3.1272],"type":"Point"}
}