{
  "type": "Feature",
  "properties": {
    "gn:admin1_code":"0.0",
    "gn:asciiname":"Permatang Damar Laut",
    "gn:country_code":"MY",
    "gn:dem":6,
    "gn:feature_class":"P",
    "gn:feature_code":"PPL",
    "gn:name":"Permatang Damar Laut",
    "gn:population":0,
    "gn:timezone":"Asia/Kuala_Lumpur",
    "iso:country":"MY",
    "wof:name":"Permatang Damar Laut",
    "wof:placetype":"locality"
},
  "geometry": {"coordinates":[100.28333000000001,5.28333],"type":"Point"}
}