{
  "type": "Feature",
  "properties": {
    "gn:admin1_code":"11.0",
    "gn:asciiname":"Rumah Ngalai",
    "gn:country_code":"MY",
    "gn:dem":253,
    "gn:feature_class":"P",
    "gn:feature_code":"PPL",
    "gn:name":"Rumah Ngalai",
    "gn:population":0,
    "gn:timezone":"Asia/Kuching",
    "iso:country":"MY",
    "wof:name":"Rumah Ngalai",
    "wof:placetype":"locality"
},
  "geometry": {"coordinates":[113.38333,2.03333],"type":"Point"}
}