{
  "type": "Feature",
  "properties": {
    "gn:admin1_code":"13.0",
    "gn:asciiname":"Kampung Banggul Pauh",
    "gn:country_code":"MY",
    "gn:dem":7,
    "gn:feature_class":"P",
    "gn:feature_code":"PPL",
    "gn:name":"Kampung Banggul Pauh",
    "gn:population":0,
    "gn:timezone":"Asia/Kuala_Lumpur",
    "iso:country":"MY",
    "name:msa_x_preferred":[
        "Kampung Banggul Pauh"
    ],
    "wof:name":"Kampung Banggul Pauh",
    "wof:placetype":"locality"
},
  "geometry": {"coordinates":[103.11660000000001,5.3472],"type":"Point"}
}