{
  "type": "Feature",
  "properties": {
    "gn:admin1_code":"3",
    "gn:asciiname":"Kampung Kubang Rambutan",
    "gn:country_code":"MY",
    "gn:dem":15,
    "gn:feature_class":"P",
    "gn:feature_code":"PPL",
    "gn:name":"Kampung Kubang Rambutan",
    "gn:population":0,
    "gn:timezone":"Asia/Kuala_Lumpur",
    "iso:country":"MY",
    "name:msa_x_preferred":[
        "Kampung Kubang Rambutan"
    ],
    "name:und_x_variant":[
        "Kampong Kubang Rambutan"
    ],
    "wof:name":"Kampung Kubang Rambutan",
    "wof:placetype":"locality"
},
  "geometry": {"coordinates":[101.9709,5.9964],"type":"Point"}
}