{
  "type": "Feature",
  "properties": {
    "iso:country":"MY",
    "name:und_x_variant":[
        "Bandaraya Ipoh"
    ],
    "qs:gn_adm0_cc":"MY",
    "qs:gn_local":1734634,
    "qs:local_max":376,
    "qs:local_sum":1287,
    "qs:localhoods":14,
    "qs:name":"Bandaraya Ipoh",
    "qs:name_adm0":"Malaysia",
    "qs:name_adm1":"Perak",
    "qs:name_adm2":"Kinta",
    "qs:name_lau":"Hulu Kinta",
    "qs:name_local":"Ipoh",
    "qs:photo_max":200,
    "qs:photo_sum":376,
    "qs:placetype":"Suburb",
    "qs:quad_count":12,
    "qs:woe_adm0":23424901,
    "qs:woe_adm1":2346302,
    "qs:woe_adm2":56013603,
    "qs:woe_lau":56014601,
    "qs:woe_local":1154679,
    "qs:woe_ver":"7.10.0",
    "wof:lang":[
        "unk"
    ],
    "wof:name":"Bandaraya Ipoh",
    "wof:placetype":"neighbourhood"
},
  "geometry": {"coordinates":[101.118054,4.598232],"type":"Point"}
}