{
  "type": "Feature",
  "properties": {
    "gn:admin1_code":"2",
    "gn:asciiname":"Kampung Ulu Sungai Daun",
    "gn:country_code":"MY",
    "gn:dem":7,
    "gn:feature_class":"P",
    "gn:feature_code":"PPL",
    "gn:name":"Kampung Ulu Sungai Daun",
    "gn:population":0,
    "gn:timezone":"Asia/Kuala_Lumpur",
    "iso:country":"MY",
    "name:und_x_variant":[
        "Kampong Ulu Sungai Daun",
        "Kampung Ulu Sungai Daun"
    ],
    "wof:name":"Kampung Ulu Sungai Daun",
    "wof:placetype":"locality"
},
  "geometry": {"coordinates":[100.4021,5.92396],"type":"Point"}
}