{
  "type": "Feature",
  "properties": {
    "gn:admin1_code":"6",
    "gn:asciiname":"Pulau Jerijak",
    "gn:country_code":"MY",
    "gn:dem":55,
    "gn:feature_class":"P",
    "gn:feature_code":"PPL",
    "gn:name":"Pulau Jerijak",
    "gn:population":0,
    "gn:timezone":"Asia/Kuala_Lumpur",
    "iso:country":"MY",
    "wof:name":"Pulau Jerijak",
    "wof:placetype":"locality"
},
  "geometry": {"coordinates":[102.56667,3.55],"type":"Point"}
}