{
  "type": "Feature",
  "properties": {
    "iso:country":"MY",
    "qs:name":"Dato' Kramat",
    "qs:name_adm0":"Malaysia",
    "qs:name_adm1":"Pulau Pinang",
    "qs:photos":151,
    "qs:photos_1k":31,
    "qs:photos_9k":1,
    "qs:photos_9r":4,
    "qs:photos_all":151,
    "qs:photos_sr":4,
    "qs:placetype":"Suburb",
    "qs:pop_sr":"0",
    "wof:name":"Dato' Kramat",
    "wof:placetype":"neighbourhood"
},
  "geometry": {"coordinates":[100.3129,5.419062],"type":"Point"}
}