{
  "type": "Feature",
  "properties": {
    "gn:admin1_code":"9",
    "gn:asciiname":"Permatang Lanjut",
    "gn:cc2":"MY",
    "gn:country_code":"MY",
    "gn:dem":9,
    "gn:feature_class":"P",
    "gn:feature_code":"PPL",
    "gn:name":"Permatang Lanjut",
    "gn:population":0,
    "gn:timezone":"Asia/Kuala_Lumpur",
    "iso:country":"MY",
    "name:msa_x_preferred":[
        "Permatang Lanjut"
    ],
    "wof:name":"Permatang Lanjut",
    "wof:placetype":"locality"
},
  "geometry": {"coordinates":[100.39042000000001,5.42713],"type":"Point"}
}