{
  "type": "Feature",
  "properties": {
    "gn:country":"MY",
    "gn:fcode":"PPL",
    "gn:population":0,
    "iso:country":"MY",
    "name:und_x_variant":[
        "Sapetang"
    ],
    "qs:name":"Kampung Sepetang",
    "qs:name_adm0":"Malaysia",
    "qs:name_adm1":"Perak",
    "qs:photos":18,
    "qs:photos_1k":4,
    "qs:photos_9k":1,
    "qs:photos_9r":1,
    "qs:photos_all":18,
    "qs:photos_sr":1,
    "qs:placetype":"Town",
    "qs:pop_sr":"0",
    "wof:name":"Kampung Sepetang",
    "wof:placetype":"locality",
    "wof:population":0
},
  "geometry": {"coordinates":[100.63333,4.83333],"type":"Point"}
}