{
  "type": "Feature",
  "properties": {
    "gn:admin1_code":"9",
    "gn:asciiname":"Kampung Ceruk Tok Kun Atas",
    "gn:cc2":"MY",
    "gn:country_code":"MY",
    "gn:dem":49,
    "gn:feature_class":"P",
    "gn:feature_code":"PPL",
    "gn:name":"Kampung Ceruk Tok Kun Atas",
    "gn:population":0,
    "gn:timezone":"Asia/Kuala_Lumpur",
    "iso:country":"MY",
    "name:msa_x_preferred":[
        "Kampung Ceruk Tok Kun Atas"
    ],
    "name:und_x_variant":[
        "Cherok To\u2019 Kun Atlas",
        "Kampong Cherok To\u2019 Kun Atas"
    ],
    "wof:name":"Kampung Ceruk Tok Kun Atas",
    "wof:placetype":"locality"
},
  "geometry": {"coordinates":[100.49729000000001,5.34685],"type":"Point"}
}