{
  "type": "Feature",
  "properties": {
    "gn:admin1_code":"12.0",
    "gn:asciiname":"Kampung Sungai Haji Durani",
    "gn:country_code":"MY",
    "gn:dem":8,
    "gn:feature_class":"P",
    "gn:feature_code":"PPL",
    "gn:name":"Kampung Sungai Haji Durani",
    "gn:population":0,
    "gn:timezone":"Asia/Kuala_Lumpur",
    "iso:country":"MY",
    "name:epo_x_preferred":[
        "Kampung Sungai Haji Dorani"
    ],
    "name:msa_x_preferred":[
        "Kampung Sungai Haji Durani"
    ],
    "wof:name":"Kampung Sungai Haji Durani",
    "wof:placetype":"locality"
},
  "geometry": {"coordinates":[101.02370000000001,3.6448],"type":"Point"}
}