{
  "type": "Feature",
  "properties": {
    "gn:admin1_code":"7",
    "gn:asciiname":"Kampung Selabak",
    "gn:country_code":"MY",
    "gn:dem":6,
    "gn:feature_class":"P",
    "gn:feature_code":"PPL",
    "gn:name":"Kampung Selabak",
    "gn:population":0,
    "gn:timezone":"Asia/Kuala_Lumpur",
    "iso:country":"MY",
    "name:msa_x_preferred":[
        "Kampung Selabak"
    ],
    "name:und_x_variant":[
        "Kampong Selabak"
    ],
    "wof:name":"Kampung Selabak",
    "wof:placetype":"locality"
},
  "geometry": {"coordinates":[101.04940000000001,3.9834],"type":"Point"}
}