{
  "type": "Feature",
  "properties": {
    "gn:admin1_code":"16",
    "gn:asciiname":"Kampong Lengan",
    "gn:cc2":"MY",
    "gn:country_code":"MY",
    "gn:dem":36,
    "gn:feature_class":"P",
    "gn:feature_code":"PPL",
    "gn:name":"Kampong Lengan",
    "gn:population":0,
    "gn:timezone":"Asia/Kuching",
    "iso:country":"MY",
    "name:und_x_variant":[
        "Lengan",
        "Lingan",
        "Kampong Lengan"
    ],
    "wof:name":"Kampong Lengan",
    "wof:placetype":"locality"
},
  "geometry": {"coordinates":[115.98333,5.63333],"type":"Point"}
}