{
  "type": "Feature",
  "properties": {
    "gn:admin1_code":"4.0",
    "gn:asciiname":"Kampung Abbey",
    "gn:country_code":"MY",
    "gn:dem":43,
    "gn:feature_class":"P",
    "gn:feature_code":"PPL",
    "gn:name":"Kampung Abbey",
    "gn:population":0,
    "gn:timezone":"Asia/Kuala_Lumpur",
    "iso:country":"MY",
    "name:msa_x_preferred":[
        "Kampung Abbey"
    ],
    "name:und_x_variant":[
        "Abbey Village"
    ],
    "wof:name":"Kampung Abbey",
    "wof:placetype":"locality"
},
  "geometry": {"coordinates":[102.49299999999999,2.3974],"type":"Point"}
}