{
  "type": "Feature",
  "properties": {
    "gn:admin1_code":"2.0",
    "gn:asciiname":"Kampung Paya Menora",
    "gn:country_code":"MY",
    "gn:dem":27,
    "gn:feature_class":"P",
    "gn:feature_code":"PPL",
    "gn:name":"Kampung Paya Menora",
    "gn:population":0,
    "gn:timezone":"Asia/Kuala_Lumpur",
    "iso:country":"MY",
    "name:msa_x_preferred":[
        "Kampung Paya Menora"
    ],
    "wof:name":"Kampung Paya Menora",
    "wof:placetype":"locality"
},
  "geometry": {"coordinates":[100.68998999999999,5.66318],"type":"Point"}
}