{
  "type": "Feature",
  "properties": {
    "gn:admin1_code":"4",
    "gn:asciiname":"Kampung Parit Lampong",
    "gn:country_code":"MY",
    "gn:dem":11,
    "gn:feature_class":"P",
    "gn:feature_code":"PPL",
    "gn:name":"Kampung Parit Lampong",
    "gn:population":0,
    "gn:timezone":"Asia/Kuala_Lumpur",
    "iso:country":"MY",
    "name:msa_x_preferred":[
        "Kampung Parit Lampong"
    ],
    "name:und_x_variant":[
        "Kampong Parit Pelampong"
    ],
    "wof:name":"Kampung Parit Lampong",
    "wof:placetype":"locality"
},
  "geometry": {"coordinates":[102.34,2.2479],"type":"Point"}
}