{
  "type": "Feature",
  "properties": {
    "gn:admin1_code":"6",
    "gn:asciiname":"Kampung Selamat",
    "gn:country_code":"MY",
    "gn:dem":8,
    "gn:feature_class":"P",
    "gn:feature_code":"PPL",
    "gn:name":"Kampung Selamat",
    "gn:population":0,
    "gn:timezone":"Asia/Kuala_Lumpur",
    "iso:country":"MY",
    "name:msa_x_preferred":[
        "Kampung Selamat"
    ],
    "name:und_x_variant":[
        "Kampong Selamat"
    ],
    "wof:name":"Kampung Selamat",
    "wof:placetype":"locality"
},
  "geometry": {"coordinates":[103.4097,3.9713],"type":"Point"}
}