{
  "type": "Feature",
  "properties": {
    "gn:admin1_code":"1",
    "gn:asciiname":"Kampung Simpang Lima Darat",
    "gn:country_code":"MY",
    "gn:dem":11,
    "gn:feature_class":"P",
    "gn:feature_code":"PPL",
    "gn:name":"Kampung Simpang Lima Darat",
    "gn:population":0,
    "gn:timezone":"Asia/Kuala_Lumpur",
    "iso:country":"MY",
    "name:msa_x_preferred":[
        "Kampung Simpang Lima Darat"
    ],
    "name:und_x_variant":[
        "Kampong Simpang Lima Darat"
    ],
    "wof:name":"Kampung Simpang Lima Darat",
    "wof:placetype":"locality"
},
  "geometry": {"coordinates":[102.6183,2.2339],"type":"Point"}
}