{
  "type": "Feature",
  "properties": {
    "gn:admin1_code":"8.0",
    "gn:asciiname":"Kampung Batu Dua",
    "gn:country_code":"MY",
    "gn:dem":9,
    "gn:feature_class":"P",
    "gn:feature_code":"PPL",
    "gn:name":"Kampung Batu Dua",
    "gn:population":0,
    "gn:timezone":"Asia/Kuala_Lumpur",
    "iso:country":"MY",
    "name:msa_x_preferred":[
        "Kampung Batu Dua"
    ],
    "wof:name":"Kampung Batu Dua",
    "wof:placetype":"locality"
},
  "geometry": {"coordinates":[100.21380000000001,6.47246],"type":"Point"}
}