{
  "type": "Feature",
  "properties": {
    "gn:admin1_code":"16.0",
    "gn:asciiname":"Kampung Lipantai",
    "gn:country_code":"MY",
    "gn:dem":352,
    "gn:feature_class":"P",
    "gn:feature_code":"PPL",
    "gn:name":"Kampung Lipantai",
    "gn:population":0,
    "gn:timezone":"Asia/Kuching",
    "iso:country":"MY",
    "name:msa_x_preferred":[
        "Kampung Lipantai"
    ],
    "wof:name":"Kampung Lipantai",
    "wof:placetype":"locality"
},
  "geometry": {"coordinates":[116.17570000000001,5.4354],"type":"Point"}
}