{
  "type": "Feature",
  "properties": {
    "gn:admin1_code":"7",
    "gn:asciiname":"Kampong Teras",
    "gn:cc2":"MY",
    "gn:country_code":"MY",
    "gn:dem":140,
    "gn:feature_class":"P",
    "gn:feature_code":"PPL",
    "gn:name":"Kampong Teras",
    "gn:population":0,
    "gn:timezone":"Asia/Kuala_Lumpur",
    "iso:country":"MY",
    "name:und_x_variant":[
        "Kampong Tras",
        "Kampong Teras"
    ],
    "wof:name":"Kampong Teras",
    "wof:placetype":"locality"
},
  "geometry": {"coordinates":[100.81667,5.13333],"type":"Point"}
}