{
  "type": "Feature",
  "properties": {
    "gn:admin1_code":"16",
    "gn:asciiname":"Kampung Papuan",
    "gn:country_code":"MY",
    "gn:dem":441,
    "gn:feature_class":"P",
    "gn:feature_code":"PPL",
    "gn:name":"Kampung Papuan",
    "gn:population":0,
    "gn:timezone":"Asia/Kuching",
    "iso:country":"MY",
    "name:msa_x_preferred":[
        "Kampung Papuan"
    ],
    "name:und_x_variant":[
        "Kampong Papuan"
    ],
    "wof:name":"Kampung Papuan",
    "wof:placetype":"locality"
},
  "geometry": {"coordinates":[116.65730000000001,6.5479],"type":"Point"}
}