{
  "type": "Feature",
  "properties": {
    "gn:admin1_code":"6.0",
    "gn:asciiname":"Kampung Buntut Pulau",
    "gn:country_code":"MY",
    "gn:dem":51,
    "gn:feature_class":"P",
    "gn:feature_code":"PPL",
    "gn:name":"Kampung Buntut Pulau",
    "gn:population":0,
    "gn:timezone":"Asia/Kuala_Lumpur",
    "iso:country":"MY",
    "name:msa_x_preferred":[
        "Kampung Buntut Pulau"
    ],
    "wof:name":"Kampung Buntut Pulau",
    "wof:placetype":"locality"
},
  "geometry": {"coordinates":[102.4329,3.9381],"type":"Point"}
}