{
  "type": "Feature",
  "properties": {
    "gn:admin1_code":"6",
    "gn:asciiname":"Kampung Pagi",
    "gn:country_code":"MY",
    "gn:dem":92,
    "gn:feature_class":"P",
    "gn:feature_code":"PPL",
    "gn:name":"Kampung Pagi",
    "gn:population":0,
    "gn:timezone":"Asia/Kuala_Lumpur",
    "iso:country":"MY",
    "name:msa_x_preferred":[
        "Kampung Pagi"
    ],
    "name:und_x_variant":[
        "Kampong Pagi"
    ],
    "wof:name":"Kampung Pagi",
    "wof:placetype":"locality"
},
  "geometry": {"coordinates":[102.4824,4.459],"type":"Point"}
}