{
  "type": "Feature",
  "properties": {
    "gn:admin1_code":"6.0",
    "gn:asciiname":"Kampung Tiat",
    "gn:country_code":"MY",
    "gn:dem":192,
    "gn:feature_class":"P",
    "gn:feature_code":"PPL",
    "gn:name":"Kampung Tiat",
    "gn:population":0,
    "gn:timezone":"Asia/Kuala_Lumpur",
    "iso:country":"MY",
    "name:msa_x_preferred":[
        "Kampung Tiat"
    ],
    "wof:name":"Kampung Tiat",
    "wof:placetype":"locality"
},
  "geometry": {"coordinates":[101.6057,4.4571],"type":"Point"}
}