{
  "type": "Feature",
  "properties": {
    "gn:admin1_code":"6",
    "gn:asciiname":"Kampung Langkap",
    "gn:country_code":"MY",
    "gn:dem":43,
    "gn:feature_class":"P",
    "gn:feature_code":"PPL",
    "gn:name":"Kampung Langkap",
    "gn:population":0,
    "gn:timezone":"Asia/Kuala_Lumpur",
    "iso:country":"MY",
    "name:und_x_variant":[
        "Kampong Langkap"
    ],
    "wof:name":"Kampung Langkap",
    "wof:placetype":"locality"
},
  "geometry": {"coordinates":[102.44293,3.2338],"type":"Point"}
}