{
  "type": "Feature",
  "properties": {
    "gn:admin1_code":"16",
    "gn:asciiname":"Kampung Bulong",
    "gn:country_code":"MY",
    "gn:dem":7,
    "gn:feature_class":"P",
    "gn:feature_code":"PPL",
    "gn:name":"Kampung Bulong",
    "gn:population":0,
    "gn:timezone":"Asia/Kuching",
    "iso:country":"MY",
    "name:msa_x_preferred":[
        "Kampung Bulong"
    ],
    "name:und_x_variant":[
        "Bulong",
        "Kampong Bulong"
    ],
    "wof:name":"Kampung Bulong",
    "wof:placetype":"locality"
},
  "geometry": {"coordinates":[116.2017,6.1875],"type":"Point"}
}