{
  "type": "Feature",
  "properties": {
    "gn:admin1_code":"1.0",
    "gn:asciiname":"Kompleks Penghulu",
    "gn:country_code":"MY",
    "gn:dem":10,
    "gn:feature_class":"P",
    "gn:feature_code":"PPL",
    "gn:name":"Kompleks Penghulu",
    "gn:population":0,
    "gn:timezone":"Asia/Kuala_Lumpur",
    "iso:country":"MY",
    "name:msa_x_preferred":[
        "Kompleks Penghulu"
    ],
    "wof:name":"Kompleks Penghulu",
    "wof:placetype":"locality"
},
  "geometry": {"coordinates":[103.63231,2.61276],"type":"Point"}
}