{
  "type": "Feature",
  "properties": {
    "gn:admin1_code":"16.0",
    "gn:asciiname":"Kampung Pandasan",
    "gn:country_code":"MY",
    "gn:dem":22,
    "gn:feature_class":"P",
    "gn:feature_code":"PPL",
    "gn:name":"Kampung Pandasan",
    "gn:population":0,
    "gn:timezone":"Asia/Kuching",
    "iso:country":"MY",
    "name:msa_x_preferred":[
        "Kampung Pandasan"
    ],
    "name:und_x_variant":[
        "Pandasan",
        "Pandassan",
        "Kampong Pandasan"
    ],
    "wof:name":"Kampung Pandasan",
    "wof:placetype":"locality"
},
  "geometry": {"coordinates":[116.5313,6.4674],"type":"Point"}
}