{
  "type": "Feature",
  "properties": {
    "gn:admin1_code":"6",
    "gn:asciiname":"Kampung Bangkung",
    "gn:country_code":"MY",
    "gn:dem":47,
    "gn:feature_class":"P",
    "gn:feature_code":"PPL",
    "gn:name":"Kampung Bangkung",
    "gn:population":0,
    "gn:timezone":"Asia/Kuala_Lumpur",
    "iso:country":"MY",
    "name:msa_x_preferred":[
        "Kampung Bangkung"
    ],
    "name:und_x_variant":[
        "Kampong Bangkong"
    ],
    "wof:name":"Kampung Bangkung",
    "wof:placetype":"locality"
},
  "geometry": {"coordinates":[103.12730000000001,3.2901],"type":"Point"}
}