{
  "type": "Feature",
  "properties": {
    "gn:admin1_code":"4",
    "gn:asciiname":"Kampung Padang Sebang",
    "gn:country_code":"MY",
    "gn:dem":36,
    "gn:feature_class":"P",
    "gn:feature_code":"PPL",
    "gn:name":"Kampung Padang Sebang",
    "gn:population":0,
    "gn:timezone":"Asia/Kuala_Lumpur",
    "iso:country":"MY",
    "name:msa_x_preferred":[
        "Kampung Padang Sebang"
    ],
    "name:und_x_variant":[
        "Kampong Padang Sebang"
    ],
    "wof:name":"Kampung Padang Sebang",
    "wof:placetype":"locality"
},
  "geometry": {"coordinates":[102.251,2.4273],"type":"Point"}
}