{
  "type": "Feature",
  "properties": {
    "iso:country":"MY",
    "name:eng_x_preferred":[
        "Kampong Baharu Sungai Way"
    ],
    "name:eng_x_variant":[
        "Sungai Way New Village"
    ],
    "name:unk_x_variant":[
        "Sungai Way New Village",
        "Kampong Baharu Sungai Way"
    ],
    "qs:gn_adm0_cc":"MY",
    "qs:gn_fcode":"PPL",
    "qs:gn_local":1735158,
    "qs:gn_namadm1":"00",
    "qs:gn_name":"Kampong Baharu Sungai Way",
    "qs:local_max":2115,
    "qs:local_sum":11887,
    "qs:localhoods":21,
    "qs:name":"Kampong Baharu Sungai Way",
    "qs:name_adm0":"Malaysia",
    "qs:name_adm1":"Selangor",
    "qs:name_adm2":"Petaling",
    "qs:name_lau":"Damansara",
    "qs:name_local":"Petaling Jaya",
    "qs:photo_max":38,
    "qs:photo_sum":209,
    "qs:placetype":"Suburb",
    "qs:quad_count":28,
    "qs:woe_adm0":23424901,
    "qs:woe_adm1":2346306,
    "qs:woe_adm2":56013632,
    "qs:woe_lau":56014224,
    "qs:woe_local":1155026,
    "qs:woe_ver":"7.10.0",
    "wof:lang":[
        "eng"
    ],
    "wof:name":"Kampong Baharu Sungai Way",
    "wof:placetype":"neighbourhood"
},
  "geometry": {"coordinates":[101.618081,3.09306],"type":"Point"}
}