{
  "type": "Feature",
  "properties": {
    "gn:admin1_code":"11.0",
    "gn:asciiname":"Long Lellang",
    "gn:country_code":"MY",
    "gn:dem":596,
    "gn:feature_class":"P",
    "gn:feature_code":"PPL",
    "gn:name":"Long Lellang",
    "gn:population":0,
    "gn:timezone":"Asia/Kuching",
    "iso:country":"MY",
    "name:msa_x_preferred":[
        "Long Lellang"
    ],
    "name:und_x_variant":[
        "Long Lelang"
    ],
    "wof:name":"Long Lellang",
    "wof:placetype":"locality"
},
  "geometry": {"coordinates":[115.18149,3.45882],"type":"Point"}
}