{
  "type": "Feature",
  "properties": {
    "gn:admin1_code":"13.0",
    "gn:asciiname":"Bukit Durian",
    "gn:country_code":"MY",
    "gn:dem":14,
    "gn:feature_class":"P",
    "gn:feature_code":"PPL",
    "gn:name":"Bukit Durian",
    "gn:population":0,
    "gn:timezone":"Asia/Kuala_Lumpur",
    "iso:country":"MY",
    "name:msa_x_preferred":[
        "Bukit Durian"
    ],
    "wof:name":"Bukit Durian",
    "wof:placetype":"locality"
},
  "geometry": {"coordinates":[103.07364,5.35503],"type":"Point"}
}