{
  "type": "Feature",
  "properties": {
    "gn:admin1_code":"13",
    "gn:asciiname":"Kongsi Dua",
    "gn:country_code":"MY",
    "gn:dem":71,
    "gn:feature_class":"P",
    "gn:feature_code":"PPL",
    "gn:name":"Kongsi Dua",
    "gn:population":0,
    "gn:timezone":"Asia/Kuala_Lumpur",
    "iso:country":"MY",
    "name:msa_x_preferred":[
        "Kongsi Dua"
    ],
    "wof:name":"Kongsi Dua",
    "wof:placetype":"locality"
},
  "geometry": {"coordinates":[103.3052,3.9161],"type":"Point"}
}