{
  "type": "Feature",
  "properties": {
    "iso:country":"MY",
    "qs:name":"Manir",
    "qs:name_adm0":"Malaysia",
    "qs:name_adm1":"Terengganu",
    "qs:photos":3,
    "qs:photos_1k":1,
    "qs:photos_9k":1,
    "qs:photos_9r":2,
    "qs:photos_all":47,
    "qs:photos_sr":1,
    "qs:placetype":"LocalAdmin",
    "qs:pop_sr":"0",
    "wof:name":"Manir",
    "wof:placetype":"localadmin"
},
  "geometry": {"coordinates":[103.096046,5.3187655],"type":"Point"}
}