{
  "type": "Feature",
  "properties": {
    "gn:admin1_code":"7.0",
    "gn:asciiname":"Kampung Tersusun Rancangan R.P.T. Batu Sepuluh Chemor",
    "gn:country_code":"MY",
    "gn:dem":80,
    "gn:feature_class":"P",
    "gn:feature_code":"PPL",
    "gn:name":"Kampung Tersusun Rancangan R.P.T. Batu Sepuluh Chemor",
    "gn:population":0,
    "gn:timezone":"Asia/Kuala_Lumpur",
    "iso:country":"MY",
    "name:msa_x_preferred":[
        "Kampung Tersusun Rancangan R.P.T. Batu Sepuluh Chemor"
    ],
    "name:und_x_variant":[
        "Kampung Tersusun Rancangan R.P.T. Batu 10 Chemor"
    ],
    "wof:name":"Kampung Tersusun Rancangan R.P.T. Batu Sepuluh Chemor",
    "wof:placetype":"locality"
},
  "geometry": {"coordinates":[101.1148,4.7282],"type":"Point"}
}