{
  "type": "Feature",
  "properties": {
    "gn:admin1_code":"3",
    "gn:asciiname":"Kampung Tua",
    "gn:country_code":"MY",
    "gn:dem":59,
    "gn:feature_class":"P",
    "gn:feature_code":"PPL",
    "gn:name":"Kampung Tua",
    "gn:population":0,
    "gn:timezone":"Asia/Kuala_Lumpur",
    "iso:country":"MY",
    "name:msa_x_preferred":[
        "Kampung Tua"
    ],
    "wof:name":"Kampung Tua",
    "wof:placetype":"locality"
},
  "geometry": {"coordinates":[101.86009,5.76642],"type":"Point"}
}