{
  "type": "Feature",
  "properties": {
    "gn:admin1_code":"16.0",
    "gn:asciiname":"Kampung Poring",
    "gn:country_code":"MY",
    "gn:dem":28,
    "gn:feature_class":"P",
    "gn:feature_code":"PPL",
    "gn:name":"Kampung Poring",
    "gn:population":0,
    "gn:timezone":"Asia/Kuching",
    "iso:country":"MY",
    "name:msa_x_preferred":[
        "Kampung Poring"
    ],
    "name:und_x_variant":[
        "Paring",
        "Kampong Poring"
    ],
    "wof:name":"Kampung Poring",
    "wof:placetype":"locality"
},
  "geometry": {"coordinates":[115.849,5.4415],"type":"Point"}
}