{
  "type": "Feature",
  "properties": {
    "gn:admin1_code":"2",
    "gn:asciiname":"Kampung Bukit Penjara",
    "gn:cc2":"MY",
    "gn:country_code":"MY",
    "gn:dem":5,
    "gn:feature_class":"P",
    "gn:feature_code":"PPL",
    "gn:name":"Kampung Bukit Penjara",
    "gn:population":0,
    "gn:timezone":"Asia/Kuala_Lumpur",
    "iso:country":"MY",
    "name:msa_x_preferred":[
        "Kampung Bukit Penjara"
    ],
    "name:und_x_variant":[
        "Kampong Bukit Penjara"
    ],
    "wof:name":"Kampung Bukit Penjara",
    "wof:placetype":"locality"
},
  "geometry": {"coordinates":[100.37441,5.66187],"type":"Point"}
}