{
  "type": "Feature",
  "properties": {
    "gn:admin1_code":"7.0",
    "gn:asciiname":"Rumah Pekerja Ladang Ulu Ayer Tawar",
    "gn:country_code":"MY",
    "gn:dem":15,
    "gn:feature_class":"P",
    "gn:feature_code":"PPL",
    "gn:name":"Rumah Pekerja Ladang Ulu Ayer Tawar",
    "gn:population":0,
    "gn:timezone":"Asia/Kuala_Lumpur",
    "iso:country":"MY",
    "name:msa_x_preferred":[
        "Rumah Pekerja Ladang Ulu Ayer Tawar"
    ],
    "wof:name":"Rumah Pekerja Ladang Ulu Ayer Tawar",
    "wof:placetype":"locality"
},
  "geometry": {"coordinates":[100.71510000000001,4.3317],"type":"Point"}
}