{
  "type": "Feature",
  "properties": {
    "gn:admin1_code":"1",
    "gn:asciiname":"Kampung Pekajang Lurus",
    "gn:country_code":"MY",
    "gn:dem":10,
    "gn:feature_class":"P",
    "gn:feature_code":"PPL",
    "gn:name":"Kampung Pekajang Lurus",
    "gn:population":0,
    "gn:timezone":"Asia/Kuala_Lumpur",
    "iso:country":"MY",
    "name:msa_x_preferred":[
        "Kampung Pekajang Lurus"
    ],
    "name:und_x_variant":[
        "Kampong Pekajang Lurus"
    ],
    "wof:name":"Kampung Pekajang Lurus",
    "wof:placetype":"locality"
},
  "geometry": {"coordinates":[103.56019999999999,1.3628],"type":"Point"}
}