{
  "type": "Feature",
  "properties": {
    "gn:admin1_code":"16",
    "gn:asciiname":"Kampong Litok Menangat",
    "gn:country_code":"MY",
    "gn:dem":17,
    "gn:feature_class":"P",
    "gn:feature_code":"PPL",
    "gn:name":"Kampong Litok Menangat",
    "gn:population":0,
    "gn:timezone":"Asia/Kuching",
    "iso:country":"MY",
    "name:und_x_variant":[
        "Litok Menangat",
        "Kampong Litok Menangat"
    ],
    "wof:name":"Kampong Litok Menangat",
    "wof:placetype":"locality"
},
  "geometry": {"coordinates":[118.84520000000001,5.061],"type":"Point"}
}