{
  "type": "Feature",
  "properties": {
    "gn:admin1_code":"1",
    "gn:asciiname":"Kampung Pantai Layang",
    "gn:country_code":"MY",
    "gn:dem":8,
    "gn:feature_class":"P",
    "gn:feature_code":"PPL",
    "gn:name":"Kampung Pantai Layang",
    "gn:population":0,
    "gn:timezone":"Asia/Kuala_Lumpur",
    "iso:country":"MY",
    "name:msa_x_preferred":[
        "Kampung Pantai Layang"
    ],
    "name:und_x_variant":[
        "Kampong Pantai Layang"
    ],
    "wof:name":"Kampung Pantai Layang",
    "wof:placetype":"locality"
},
  "geometry": {"coordinates":[102.57389999999999,2.1194],"type":"Point"}
}