{
  "type": "Feature",
  "properties": {
    "gn:admin1_code":"11.0",
    "gn:asciiname":"Kuli",
    "gn:country_code":"MY",
    "gn:dem":279,
    "gn:feature_class":"P",
    "gn:feature_code":"PPL",
    "gn:name":"Kuli",
    "gn:population":0,
    "gn:timezone":"Asia/Kuching",
    "iso:country":"MY",
    "name:msa_x_preferred":[
        "Kuli"
    ],
    "wof:name":"Kuli",
    "wof:placetype":"locality"
},
  "geometry": {"coordinates":[113.01613999999999,2.6831],"type":"Point"}
}