{
  "type": "Feature",
  "properties": {
    "gn:admin1_code":"11",
    "gn:asciiname":"Kampong Lobang Batu",
    "gn:country_code":"MY",
    "gn:dem":95,
    "gn:feature_class":"P",
    "gn:feature_code":"PPL",
    "gn:name":"Kampong Lobang Batu",
    "gn:population":0,
    "gn:timezone":"Asia/Kuching",
    "iso:country":"MY",
    "name:und_x_variant":[
        "Lobang Batu",
        "Kampong Lobang Batu"
    ],
    "wof:name":"Kampong Lobang Batu",
    "wof:placetype":"locality"
},
  "geometry": {"coordinates":[110.52177,0.9719],"type":"Point"}
}