{
  "type": "Feature",
  "properties": {
    "gn:admin1_code":"6.0",
    "gn:asciiname":"Puncak Emas",
    "gn:country_code":"MY",
    "gn:dem":151,
    "gn:feature_class":"P",
    "gn:feature_code":"PPL",
    "gn:name":"Puncak Emas",
    "gn:population":0,
    "gn:timezone":"Asia/Kuala_Lumpur",
    "iso:country":"MY",
    "name:msa_x_preferred":[
        "Puncak Emas"
    ],
    "wof:name":"Puncak Emas",
    "wof:placetype":"locality"
},
  "geometry": {"coordinates":[101.8463,3.811],"type":"Point"}
}