{
  "type": "Feature",
  "properties": {
    "gn:admin1_code":"13.0",
    "gn:asciiname":"Kampung Tok Jambal",
    "gn:country_code":"MY",
    "gn:dem":12,
    "gn:feature_class":"P",
    "gn:feature_code":"PPL",
    "gn:name":"Kampung Tok Jambal",
    "gn:population":0,
    "gn:timezone":"Asia/Kuala_Lumpur",
    "iso:country":"MY",
    "name:msa_x_preferred":[
        "Kampung Tok Jambal"
    ],
    "wof:name":"Kampung Tok Jambal",
    "wof:placetype":"locality"
},
  "geometry": {"coordinates":[103.0977,5.3915],"type":"Point"}
}