{
  "type": "Feature",
  "properties": {
    "gn:country":"MY",
    "gn:fcode":"PPL",
    "gn:population":0,
    "iso:country":"MY",
    "name:msa_x_preferred":[
        "Kampung Tekek"
    ],
    "name:rus_x_preferred":[
        "\u0422\u0435\u043a\u0435\u043a"
    ],
    "qs:name":"Kampung Tekek",
    "qs:name_adm0":"Malaysia",
    "qs:name_adm1":"Pahang",
    "qs:photos":424,
    "qs:photos_1k":86,
    "qs:photos_9k":2,
    "qs:photos_9r":5,
    "qs:photos_all":424,
    "qs:photos_sr":6,
    "qs:placetype":"Town",
    "qs:pop_sr":"0",
    "wof:name":"Kampung Tekek",
    "wof:placetype":"locality",
    "wof:population":0
},
  "geometry": {"coordinates":[104.1592,2.8147],"type":"Point"}
}