{
  "type": "Feature",
  "properties": {
    "iso:country":"MY",
    "name:eng_x_preferred":[
        "Peringgit"
    ],
    "name:msa_x_preferred":[
        "Peringgit"
    ],
    "name:nld_x_preferred":[
        "Peringgit"
    ],
    "name:tam_x_preferred":[
        "\u0baa\u0bbf\u0bb0\u0bbf\u0b99\u0bcd\u0b95\u0bbf\u0b9f\u0bcd"
    ],
    "name:zho_x_preferred":[
        "\u99ac\u767b\u5df4\u51b7\u7e23"
    ],
    "name:zho_x_variant":[
        "\u67cf\u7075\u7389"
    ],
    "qs:name":"Peringgit",
    "qs:name_adm0":"Malaysia",
    "qs:name_adm1":"Melaka",
    "qs:photos":156,
    "qs:photos_1k":32,
    "qs:photos_9k":1,
    "qs:photos_9r":4,
    "qs:photos_all":204,
    "qs:photos_sr":4,
    "qs:placetype":"LocalAdmin",
    "qs:pop_sr":"0",
    "wd:wordcount":57,
    "wof:name":"Peringgit",
    "wof:placetype":"localadmin"
},
  "geometry": {"coordinates":[102.247727,2.219796],"type":"Point"}
}