{
  "type": "Feature",
  "properties": {
    "iso:country":"MY",
    "name:eng_x_preferred":[
        "Peringgit"
    ],
    "name:msa_x_preferred":[
        "Peringgit"
    ],
    "name:nld_x_preferred":[
        "Peringgit"
    ],
    "name:zho_x_preferred":[
        "\u99ac\u767b\u5df4\u51b7\u7e23"
    ],
    "qs:name":"Peringgit",
    "qs:name_adm0":"Malaysia",
    "qs:name_adm1":"Melaka",
    "qs:photos":156,
    "qs:photos_1k":32,
    "qs:photos_9k":1,
    "qs:photos_9r":4,
    "qs:photos_all":204,
    "qs:photos_sr":4,
    "qs:placetype":"LocalAdmin",
    "qs:pop_sr":"0",
    "wd:wordcount":57,
    "wof:name":"Peringgit",
    "wof:placetype":"localadmin"
},
  "geometry": {"coordinates":[102.247727,2.2197955],"type":"Point"}
}