{
  "type": "Feature",
  "properties": {
    "gn:admin1_code":"6",
    "gn:asciiname":"Kampung Tanjong Pahang",
    "gn:country_code":"MY",
    "gn:dem":12,
    "gn:feature_class":"P",
    "gn:feature_code":"PPL",
    "gn:name":"Kampung Tanjong Pahang",
    "gn:population":0,
    "gn:timezone":"Asia/Kuala_Lumpur",
    "iso:country":"MY",
    "name:msa_x_preferred":[
        "Kampung Tanjong Pahang"
    ],
    "name:und_x_variant":[
        "Kampong Tanjong Pahang"
    ],
    "wof:name":"Kampung Tanjong Pahang",
    "wof:placetype":"locality"
},
  "geometry": {"coordinates":[103.63043,2.66788],"type":"Point"}
}