{
  "type": "Feature",
  "properties": {
    "gn:admin1_code":"16.0",
    "gn:asciiname":"Kampong Indarasabak",
    "gn:country_code":"MY",
    "gn:dem":16,
    "gn:feature_class":"P",
    "gn:feature_code":"PPL",
    "gn:name":"Kampong Indarasabak",
    "gn:population":0,
    "gn:timezone":"Asia/Kuching",
    "iso:country":"MY",
    "name:msa_x_preferred":[
        "Kampong Indarasabak"
    ],
    "name:und_x_variant":[
        "Kampong Indarasbak",
        "Indarasabak",
        "Kampung Indarasabak"
    ],
    "wof:name":"Kampong Indarasabak",
    "wof:placetype":"locality"
},
  "geometry": {"coordinates":[118.16725,4.2995],"type":"Point"}
}