{
  "type": "Feature",
  "properties": {
    "gn:admin1_code":"2",
    "gn:asciiname":"Kampung Machang Bubok",
    "gn:cc2":"MY",
    "gn:country_code":"MY",
    "gn:dem":33,
    "gn:feature_class":"P",
    "gn:feature_code":"PPL",
    "gn:name":"Kampung Machang Bubok",
    "gn:population":0,
    "gn:timezone":"Asia/Kuala_Lumpur",
    "iso:country":"MY",
    "name:msa_x_preferred":[
        "Kampung Machang Bubok"
    ],
    "name:und_x_variant":[
        "Kampong Machang Bubok"
    ],
    "wof:name":"Kampung Machang Bubok",
    "wof:placetype":"locality"
},
  "geometry": {"coordinates":[100.7047,5.53341],"type":"Point"}
}