{
  "type": "Feature",
  "properties": {
    "gn:admin1_code":"3",
    "gn:asciiname":"Ladang Pandrak",
    "gn:country_code":"MY",
    "gn:dem":280,
    "gn:feature_class":"P",
    "gn:feature_code":"PPL",
    "gn:name":"Ladang Pandrak",
    "gn:population":0,
    "gn:timezone":"Asia/Kuala_Lumpur",
    "iso:country":"MY",
    "name:und_x_variant":[
        "Ladang Panderak"
    ],
    "wof:name":"Ladang Pandrak",
    "wof:placetype":"locality"
},
  "geometry": {"coordinates":[101.57589,4.70573],"type":"Point"}
}