{
  "type": "Feature",
  "properties": {
    "gn:admin1_code":"16.0",
    "gn:asciiname":"Kampong Lebak Engad",
    "gn:country_code":"MY",
    "gn:dem":16,
    "gn:feature_class":"P",
    "gn:feature_code":"PPL",
    "gn:name":"Kampong Lebak Engad",
    "gn:population":0,
    "gn:timezone":"Asia/Kuching",
    "iso:country":"MY",
    "name:msa_x_preferred":[
        "Kampong Lebak Engad"
    ],
    "wof:name":"Kampong Lebak Engad",
    "wof:placetype":"locality"
},
  "geometry": {"coordinates":[116.4218,6.37],"type":"Point"}
}