{
  "type": "Feature",
  "properties": {
    "gn:admin1_code":"2.0",
    "gn:asciiname":"Kampung Kubu",
    "gn:cc2":"MY",
    "gn:country_code":"MY",
    "gn:dem":4,
    "gn:feature_class":"P",
    "gn:feature_code":"PPL",
    "gn:name":"Kampung Kubu",
    "gn:population":0,
    "gn:timezone":"Asia/Kuala_Lumpur",
    "iso:country":"MY",
    "name:msa_x_preferred":[
        "Kampung Kubu"
    ],
    "wof:name":"Kampung Kubu",
    "wof:placetype":"locality"
},
  "geometry": {"coordinates":[100.52795999999999,5.09831],"type":"Point"}
}