{
  "type": "Feature",
  "properties": {
    "gn:admin1_code":"16.0",
    "gn:asciiname":"Kampung Simbar",
    "gn:country_code":"MY",
    "gn:dem":45,
    "gn:feature_class":"P",
    "gn:feature_code":"PPL",
    "gn:name":"Kampung Simbar",
    "gn:population":0,
    "gn:timezone":"Asia/Kuching",
    "iso:country":"MY",
    "name:msa_x_preferred":[
        "Kampung Simbar"
    ],
    "wof:name":"Kampung Simbar",
    "wof:placetype":"locality"
},
  "geometry": {"coordinates":[117.2124,6.3139],"type":"Point"}
}