{
  "type": "Feature",
  "properties": {
    "gn:admin1_code":"2",
    "gn:asciiname":"Kampung Sungai Yu",
    "gn:cc2":"MY",
    "gn:country_code":"MY",
    "gn:dem":7,
    "gn:feature_class":"P",
    "gn:feature_code":"PPL",
    "gn:name":"Kampung Sungai Yu",
    "gn:population":0,
    "gn:timezone":"Asia/Kuala_Lumpur",
    "iso:country":"MY",
    "name:msa_x_preferred":[
        "Kampung Sungai Yu"
    ],
    "name:und_x_variant":[
        "Kampong Sungai Yu"
    ],
    "wof:name":"Kampung Sungai Yu",
    "wof:placetype":"locality"
},
  "geometry": {"coordinates":[100.34393,5.64018],"type":"Point"}
}