{
  "type": "Feature",
  "properties": {
    "gn:admin1_code":"4.0",
    "gn:asciiname":"Kampung Paya Gemoh",
    "gn:country_code":"MY",
    "gn:dem":30,
    "gn:feature_class":"P",
    "gn:feature_code":"PPL",
    "gn:name":"Kampung Paya Gemoh",
    "gn:population":0,
    "gn:timezone":"Asia/Kuala_Lumpur",
    "iso:country":"MY",
    "name:msa_x_preferred":[
        "Kampung Paya Gemoh"
    ],
    "wof:name":"Kampung Paya Gemoh",
    "wof:placetype":"locality"
},
  "geometry": {"coordinates":[102.4264,2.2587],"type":"Point"}
}