{
  "type": "Feature",
  "properties": {
    "gn:admin1_code":"16.0",
    "gn:asciiname":"Tiga Tiga",
    "gn:country_code":"MY",
    "gn:dem":24,
    "gn:feature_class":"P",
    "gn:feature_code":"PPL",
    "gn:name":"Tiga Tiga",
    "gn:population":0,
    "gn:timezone":"Asia/Kuching",
    "iso:country":"MY",
    "name:msa_x_preferred":[
        "Tiga Tiga"
    ],
    "wof:name":"Tiga Tiga",
    "wof:placetype":"locality"
},
  "geometry": {"coordinates":[116.9517,6.68],"type":"Point"}
}