{
  "type": "Feature",
  "properties": {
    "gn:admin1_code":"16.0",
    "gn:asciiname":"Kampung Bilangau Kecil",
    "gn:country_code":"MY",
    "gn:dem":321,
    "gn:feature_class":"P",
    "gn:feature_code":"PPL",
    "gn:name":"Kampung Bilangau Kecil",
    "gn:population":0,
    "gn:timezone":"Asia/Kuching",
    "iso:country":"MY",
    "name:msa_x_preferred":[
        "Kampung Bilangau Kecil"
    ],
    "wof:name":"Kampung Bilangau Kecil",
    "wof:placetype":"locality"
},
  "geometry": {"coordinates":[116.9562,6.6316],"type":"Point"}
}