{
  "type": "Feature",
  "properties": {
    "gn:admin1_code":"4",
    "gn:asciiname":"Kesang Tua",
    "gn:country_code":"MY",
    "gn:dem":51,
    "gn:feature_class":"P",
    "gn:feature_code":"PPL",
    "gn:name":"Kesang Tua",
    "gn:population":0,
    "gn:timezone":"Asia/Kuala_Lumpur",
    "iso:country":"MY",
    "name:msa_x_preferred":[
        "Kesang Tua"
    ],
    "wof:name":"Kesang Tua",
    "wof:placetype":"locality"
},
  "geometry": {"coordinates":[102.40009999999999,2.3183],"type":"Point"}
}