{
  "type": "Feature",
  "properties": {
    "gn:country":"MY",
    "gn:fcode":"PPL",
    "gn:population":0,
    "iso:country":"MY",
    "name:msa_x_preferred":[
        "Kampung Kuala Cini"
    ],
    "name:und_x_variant":[
        "Kampong Chini"
    ],
    "qs:name":"Kampung Kuala Cini",
    "qs:name_adm0":"Malaysia",
    "qs:name_adm1":"Pahang",
    "qs:photos":88,
    "qs:photos_1k":18,
    "qs:photos_9k":1,
    "qs:photos_9r":3,
    "qs:photos_all":88,
    "qs:photos_sr":3,
    "qs:placetype":"Town",
    "qs:pop_sr":"0",
    "wd:wordcount":56,
    "wof:name":"Kampung Kuala Cini",
    "wof:placetype":"locality",
    "wof:population":0
},
  "geometry": {"coordinates":[102.8929,3.4524],"type":"Point"}
}