{
  "type": "Feature",
  "properties": {
    "gn:admin1_code":"11",
    "gn:asciiname":"Rumah Belabun",
    "gn:country_code":"MY",
    "gn:dem":73,
    "gn:feature_class":"P",
    "gn:feature_code":"PPL",
    "gn:name":"Rumah Belabun",
    "gn:population":0,
    "gn:timezone":"Asia/Kuching",
    "iso:country":"MY",
    "wof:name":"Rumah Belabun",
    "wof:placetype":"locality"
},
  "geometry": {"coordinates":[111.59999999999999,1.98333],"type":"Point"}
}