{
  "type": "Feature",
  "properties": {
    "gn:admin1_code":"7.0",
    "gn:asciiname":"Taman Mujur",
    "gn:country_code":"MY",
    "gn:dem":63,
    "gn:feature_class":"P",
    "gn:feature_code":"PPL",
    "gn:name":"Taman Mujur",
    "gn:population":0,
    "gn:timezone":"Asia/Kuala_Lumpur",
    "iso:country":"MY",
    "name:msa_x_preferred":[
        "Taman Mujur"
    ],
    "wof:name":"Taman Mujur",
    "wof:placetype":"locality"
},
  "geometry": {"coordinates":[101.12909999999999,4.6471],"type":"Point"}
}