{
  "type": "Feature",
  "properties": {
    "gn:admin1_code":"3",
    "gn:asciiname":"Kampong Rotan Tawar",
    "gn:country_code":"MY",
    "gn:dem":38,
    "gn:feature_class":"P",
    "gn:feature_code":"PPL",
    "gn:name":"Kampong Rotan Tawar",
    "gn:population":0,
    "gn:timezone":"Asia/Kuala_Lumpur",
    "iso:country":"MY",
    "name:und_x_variant":[
        "Kampong Rotan Tawai",
        "Kampong Rotan Tawar"
    ],
    "wof:name":"Kampong Rotan Tawar",
    "wof:placetype":"locality"
},
  "geometry": {"coordinates":[101.96688,5.8254],"type":"Point"}
}