{
  "type": "Feature",
  "properties": {
    "gn:admin1_code":"6.0",
    "gn:asciiname":"Kampung Pucuk",
    "gn:country_code":"MY",
    "gn:dem":107,
    "gn:feature_class":"P",
    "gn:feature_code":"PPL",
    "gn:name":"Kampung Pucuk",
    "gn:population":0,
    "gn:timezone":"Asia/Kuala_Lumpur",
    "iso:country":"MY",
    "name:msa_x_preferred":[
        "Kampung Pucuk"
    ],
    "wof:name":"Kampung Pucuk",
    "wof:placetype":"locality"
},
  "geometry": {"coordinates":[102.08320000000001,4.0115],"type":"Point"}
}