{
  "type": "Feature",
  "properties": {
    "gn:admin1_code":"2",
    "gn:asciiname":"Kampung Lempuin",
    "gn:country_code":"MY",
    "gn:dem":4,
    "gn:feature_class":"P",
    "gn:feature_code":"PPL",
    "gn:name":"Kampung Lempuin",
    "gn:population":0,
    "gn:timezone":"Asia/Kuala_Lumpur",
    "iso:country":"MY",
    "name:msa_x_preferred":[
        "Kampung Lempuin"
    ],
    "name:und_x_variant":[
        "Kampong Lampuyan"
    ],
    "wof:name":"Kampung Lempuin",
    "wof:placetype":"locality"
},
  "geometry": {"coordinates":[100.3062,6.1252],"type":"Point"}
}