{
  "type": "Feature",
  "properties": {
    "gn:admin1_code":"7.0",
    "gn:asciiname":"Taman Kelebang Jaya",
    "gn:country_code":"MY",
    "gn:dem":62,
    "gn:feature_class":"P",
    "gn:feature_code":"PPL",
    "gn:name":"Taman Kelebang Jaya",
    "gn:population":0,
    "gn:timezone":"Asia/Kuala_Lumpur",
    "iso:country":"MY",
    "name:msa_x_preferred":[
        "Taman Kelebang Jaya"
    ],
    "wof:name":"Taman Kelebang Jaya",
    "wof:placetype":"locality"
},
  "geometry": {"coordinates":[101.1186,4.6762],"type":"Point"}
}