{
  "type": "Feature",
  "properties": {
    "gn:admin1_code":"13",
    "gn:asciiname":"Kampung Bukit Petiti",
    "gn:country_code":"MY",
    "gn:dem":15,
    "gn:feature_class":"P",
    "gn:feature_code":"PPL",
    "gn:name":"Kampung Bukit Petiti",
    "gn:population":0,
    "gn:timezone":"Asia/Kuala_Lumpur",
    "iso:country":"MY",
    "name:msa_x_preferred":[
        "Kampung Bukit Petiti"
    ],
    "name:und_x_variant":[
        "Kampong Bukit Betiti"
    ],
    "wof:name":"Kampung Bukit Petiti",
    "wof:placetype":"locality"
},
  "geometry": {"coordinates":[103.02679999999999,5.307],"type":"Point"}
}