{
  "type": "Feature",
  "properties": {
    "gn:admin1_code":"11",
    "gn:asciiname":"Keribau",
    "gn:cc2":"MY",
    "gn:country_code":"MY",
    "gn:dem":103,
    "gn:feature_class":"P",
    "gn:feature_code":"PPL",
    "gn:name":"Keribau",
    "gn:population":0,
    "gn:timezone":"Asia/Kuching",
    "iso:country":"MY",
    "name:und_x_variant":[
        "Rumah Danggat",
        "Rumah Dunggat",
        "Keribau"
    ],
    "wof:name":"Keribau",
    "wof:placetype":"locality"
},
  "geometry": {"coordinates":[111.48333,1.65],"type":"Point"}
}