{
  "type": "Feature",
  "properties": {
    "gn:admin1_code":"6",
    "gn:asciiname":"Pantai Hiboran",
    "gn:country_code":"MY",
    "gn:dem":31,
    "gn:feature_class":"P",
    "gn:feature_code":"PPL",
    "gn:name":"Pantai Hiboran",
    "gn:population":0,
    "gn:timezone":"Asia/Kuala_Lumpur",
    "iso:country":"MY",
    "wof:name":"Pantai Hiboran",
    "wof:placetype":"locality"
},
  "geometry": {"coordinates":[103.43333,3.28333],"type":"Point"}
}