{
  "type": "Feature",
  "properties": {
    "gn:admin1_code":"2",
    "gn:asciiname":"Kampung Tupai",
    "gn:cc2":"MY",
    "gn:country_code":"MY",
    "gn:dem":48,
    "gn:feature_class":"P",
    "gn:feature_code":"PPL",
    "gn:name":"Kampung Tupai",
    "gn:population":0,
    "gn:timezone":"Asia/Kuala_Lumpur",
    "iso:country":"MY",
    "name:msa_x_preferred":[
        "Kampung Tupai"
    ],
    "name:und_x_variant":[
        "Kampong Tupai"
    ],
    "wof:name":"Kampung Tupai",
    "wof:placetype":"locality"
},
  "geometry": {"coordinates":[100.71502,5.74946],"type":"Point"}
}