{
  "type": "Feature",
  "properties": {
    "gn:admin1_code":"1",
    "gn:asciiname":"Kampung Belemang",
    "gn:country_code":"MY",
    "gn:dem":10,
    "gn:feature_class":"P",
    "gn:feature_code":"PPL",
    "gn:name":"Kampung Belemang",
    "gn:population":0,
    "gn:timezone":"Asia/Kuala_Lumpur",
    "iso:country":"MY",
    "name:msa_x_preferred":[
        "Kampung Belemang"
    ],
    "name:und_x_variant":[
        "Kampong Blemang",
        "Kampong Belemang"
    ],
    "wof:name":"Kampung Belemang",
    "wof:placetype":"locality"
},
  "geometry": {"coordinates":[102.62430000000001,2.146],"type":"Point"}
}