{
  "type": "Feature",
  "properties": {
    "gn:admin1_code":"7.0",
    "gn:asciiname":"Kampung Sungai Balai",
    "gn:country_code":"MY",
    "gn:dem":6,
    "gn:feature_class":"P",
    "gn:feature_code":"PPL",
    "gn:name":"Kampung Sungai Balai",
    "gn:population":0,
    "gn:timezone":"Asia/Kuala_Lumpur",
    "iso:country":"MY",
    "name:msa_x_preferred":[
        "Kampung Sungai Balai"
    ],
    "wof:name":"Kampung Sungai Balai",
    "wof:placetype":"locality"
},
  "geometry": {"coordinates":[100.73260000000001,3.9747],"type":"Point"}
}