{
  "type": "Feature",
  "properties": {
    "iso:country":"MY",
    "qs:name":"Hulu Kinta",
    "qs:name_adm0":"Malaysia",
    "qs:name_adm1":"Perak",
    "qs:photos":3,
    "qs:photos_1k":1,
    "qs:photos_9k":19,
    "qs:photos_9r":13,
    "qs:photos_all":4390,
    "qs:photos_sr":1,
    "qs:placetype":"LocalAdmin",
    "qs:pop_sr":"0",
    "wof:name":"Hulu Kinta",
    "wof:placetype":"localadmin"
},
  "geometry": {"coordinates":[101.086975,4.597129],"type":"Point"}
}