{
  "type": "Feature",
  "properties": {
    "gn:admin1_code":"13",
    "gn:asciiname":"Kampung Serada",
    "gn:country_code":"MY",
    "gn:dem":11,
    "gn:feature_class":"P",
    "gn:feature_code":"PPL",
    "gn:name":"Kampung Serada",
    "gn:population":0,
    "gn:timezone":"Asia/Kuala_Lumpur",
    "iso:country":"MY",
    "name:msa_x_preferred":[
        "Kampung Serada"
    ],
    "name:und_x_variant":[
        "Kampong Serada"
    ],
    "wof:name":"Kampung Serada",
    "wof:placetype":"locality"
},
  "geometry": {"coordinates":[103.0414,5.2633],"type":"Point"}
}