{
  "type": "Feature",
  "properties": {
    "gn:admin1_code":"2",
    "gn:asciiname":"Kampung Sungai Bakong",
    "gn:country_code":"MY",
    "gn:dem":4,
    "gn:feature_class":"P",
    "gn:feature_code":"PPL",
    "gn:name":"Kampung Sungai Bakong",
    "gn:population":0,
    "gn:timezone":"Asia/Kuala_Lumpur",
    "iso:country":"MY",
    "name:und_x_variant":[
        "Kampong Sungai Bakong",
        "Kampung Sungai Bakong"
    ],
    "wof:name":"Kampung Sungai Bakong",
    "wof:placetype":"locality"
},
  "geometry": {"coordinates":[100.37394,5.80552],"type":"Point"}
}