{
  "type": "Feature",
  "properties": {
    "gn:admin1_code":"16.0",
    "gn:asciiname":"Kampong Tanjung Batu",
    "gn:country_code":"MY",
    "gn:dem":17,
    "gn:feature_class":"P",
    "gn:feature_code":"PPL",
    "gn:name":"Kampong Tanjung Batu",
    "gn:population":0,
    "gn:timezone":"Asia/Kuching",
    "iso:country":"MY",
    "name:msa_x_preferred":[
        "Kampong Tanjung Batu"
    ],
    "wof:name":"Kampong Tanjung Batu",
    "wof:placetype":"locality"
},
  "geometry": {"coordinates":[116.42310000000001,6.413],"type":"Point"}
}