{
  "type": "Feature",
  "properties": {
    "gn:admin1_code":"13.0",
    "gn:asciiname":"Kampung Binjai Manis",
    "gn:country_code":"MY",
    "gn:dem":17,
    "gn:feature_class":"P",
    "gn:feature_code":"PPL",
    "gn:name":"Kampung Binjai Manis",
    "gn:population":0,
    "gn:timezone":"Asia/Kuala_Lumpur",
    "iso:country":"MY",
    "name:msa_x_preferred":[
        "Kampung Binjai Manis"
    ],
    "wof:name":"Kampung Binjai Manis",
    "wof:placetype":"locality"
},
  "geometry": {"coordinates":[103.03530000000001,5.3898],"type":"Point"}
}