{
  "type": "Feature",
  "properties": {
    "gn:admin1_code":"16.0",
    "gn:asciiname":"Kg. Kipaliu Baru",
    "gn:country_code":"MY",
    "gn:dem":368,
    "gn:feature_class":"P",
    "gn:feature_code":"PPL",
    "gn:name":"Kg. Kipaliu Baru",
    "gn:population":0,
    "gn:timezone":"Asia/Kuching",
    "iso:country":"MY",
    "wof:name":"Kg. Kipaliu Baru",
    "wof:placetype":"locality"
},
  "geometry": {"coordinates":[116.37452999999999,5.25896],"type":"Point"}
}