{
  "type": "Feature",
  "properties": {
    "gn:admin1_code":"6",
    "gn:asciiname":"Kampong Penyor",
    "gn:country_code":"MY",
    "gn:dem":18,
    "gn:feature_class":"P",
    "gn:feature_code":"PPL",
    "gn:name":"Kampong Penyor",
    "gn:population":0,
    "gn:timezone":"Asia/Kuala_Lumpur",
    "iso:country":"MY",
    "name:und_x_variant":[
        "Kampong Penyu",
        "Kampong Penyor"
    ],
    "wof:name":"Kampong Penyor",
    "wof:placetype":"locality"
},
  "geometry": {"coordinates":[103.01667,3.46667],"type":"Point"}
}