{
  "type": "Feature",
  "properties": {
    "gn:admin1_code":"2",
    "gn:asciiname":"Singkir Laut",
    "gn:country_code":"MY",
    "gn:dem":10,
    "gn:feature_class":"P",
    "gn:feature_code":"PPL",
    "gn:name":"Singkir Laut",
    "gn:population":0,
    "gn:timezone":"Asia/Kuala_Lumpur",
    "iso:country":"MY",
    "name:und_x_variant":[
        "Singkir",
        "Singkir Laut"
    ],
    "wof:name":"Singkir Laut",
    "wof:placetype":"locality"
},
  "geometry": {"coordinates":[100.36457,5.73027],"type":"Point"}
}