{
  "type": "Feature",
  "properties": {
    "gn:admin1_code":"6.0",
    "gn:asciiname":"Kampung Hok Penyur",
    "gn:country_code":"MY",
    "gn:dem":26,
    "gn:feature_class":"P",
    "gn:feature_code":"PPL",
    "gn:name":"Kampung Hok Penyur",
    "gn:population":0,
    "gn:timezone":"Asia/Kuala_Lumpur",
    "iso:country":"MY",
    "name:msa_x_preferred":[
        "Kampung Hok Penyur"
    ],
    "wof:name":"Kampung Hok Penyur",
    "wof:placetype":"locality"
},
  "geometry": {"coordinates":[102.85339999999999,3.4674],"type":"Point"}
}