{
  "type": "Feature",
  "properties": {
    "gn:admin1_code":"3",
    "gn:asciiname":"Kampong Bukit Berapit",
    "gn:country_code":"MY",
    "gn:dem":98,
    "gn:feature_class":"P",
    "gn:feature_code":"PPL",
    "gn:name":"Kampong Bukit Berapit",
    "gn:population":0,
    "gn:timezone":"Asia/Kuala_Lumpur",
    "iso:country":"MY",
    "wof:name":"Kampong Bukit Berapit",
    "wof:placetype":"locality"
},
  "geometry": {"coordinates":[101.95914,5.79313],"type":"Point"}
}