{
  "type": "Feature",
  "properties": {
    "iso:country":"MY",
    "qs:name":"Palau Betong",
    "qs:name_adm0":"Malaysia",
    "qs:name_adm1":"Pulau Pinang",
    "qs:photos":18,
    "qs:photos_1k":4,
    "qs:photos_9k":1,
    "qs:photos_9r":1,
    "qs:photos_all":18,
    "qs:photos_sr":1,
    "qs:placetype":"Town",
    "qs:pop_sr":"0",
    "wof:name":"Palau Betong",
    "wof:placetype":"locality"
},
  "geometry": {"coordinates":[100.19915399999999,5.307119],"type":"Point"}
}