{
  "type": "Feature",
  "properties": {
    "iso:country":"MY",
    "qs:name":"Kongkoi",
    "qs:name_adm0":"Malaysia",
    "qs:name_adm1":"Negeri Sembilan",
    "qs:photos":1,
    "qs:photos_1k":1,
    "qs:photos_9k":1,
    "qs:photos_9r":1,
    "qs:photos_all":1,
    "qs:photos_sr":1,
    "qs:placetype":"Town",
    "qs:pop_sr":"0",
    "wof:name":"Kongkoi",
    "wof:placetype":"locality"
},
  "geometry": {"coordinates":[102.050628,3.097321],"type":"Point"}
}