{
  "type": "Feature",
  "properties": {
    "gn:admin1_code":"16.0",
    "gn:asciiname":"Kampung Komandar",
    "gn:country_code":"MY",
    "gn:dem":56,
    "gn:feature_class":"P",
    "gn:feature_code":"PPL",
    "gn:name":"Kampung Komandar",
    "gn:population":0,
    "gn:timezone":"Asia/Kuching",
    "iso:country":"MY",
    "name:msa_x_preferred":[
        "Kampung Komandar"
    ],
    "wof:name":"Kampung Komandar",
    "wof:placetype":"locality"
},
  "geometry": {"coordinates":[117.1465,6.1178],"type":"Point"}
}