{
  "type": "Feature",
  "properties": {
    "gn:admin1_code":"2.0",
    "gn:asciiname":"Kampung Kelang Lama",
    "gn:cc2":"MY",
    "gn:country_code":"MY",
    "gn:dem":29,
    "gn:feature_class":"P",
    "gn:feature_code":"PPL",
    "gn:name":"Kampung Kelang Lama",
    "gn:population":0,
    "gn:timezone":"Asia/Kuala_Lumpur",
    "iso:country":"MY",
    "name:msa_x_preferred":[
        "Kampung Kelang Lama"
    ],
    "name:und_x_variant":[
        "Kampong Kelang Lama",
        "Kelang Lama"
    ],
    "wof:name":"Kampung Kelang Lama",
    "wof:placetype":"locality"
},
  "geometry": {"coordinates":[100.56864,5.38823],"type":"Point"}
}