{
  "type": "Feature",
  "properties": {
    "gn:admin1_code":"6.0",
    "gn:asciiname":"Felda sungai kemahal",
    "gn:country_code":"MY",
    "gn:dem":67,
    "gn:feature_class":"P",
    "gn:feature_code":"PPL",
    "gn:name":"Felda sungai kemahal",
    "gn:population":0,
    "gn:timezone":"Asia/Kuala_Lumpur",
    "iso:country":"MY",
    "wof:name":"Felda sungai kemahal",
    "wof:placetype":"locality"
},
  "geometry": {"coordinates":[102.27216,3.1796],"type":"Point"}
}