{
  "type": "Feature",
  "properties": {
    "gn:admin1_code":"2",
    "gn:asciiname":"Kampung Tanjung Setar",
    "gn:cc2":"MY",
    "gn:country_code":"MY",
    "gn:dem":61,
    "gn:feature_class":"P",
    "gn:feature_code":"PPL",
    "gn:name":"Kampung Tanjung Setar",
    "gn:population":0,
    "gn:timezone":"Asia/Kuala_Lumpur",
    "iso:country":"MY",
    "name:msa_x_preferred":[
        "Kampung Tanjung Setar"
    ],
    "name:und_x_variant":[
        "Kampong Tanjong Star",
        "Kampong Tanjong Setar"
    ],
    "wof:name":"Kampung Tanjung Setar",
    "wof:placetype":"locality"
},
  "geometry": {"coordinates":[100.7687,5.82635],"type":"Point"}
}