{
  "type": "Feature",
  "properties": {
    "gn:admin1_code":"0",
    "gn:asciiname":"Sungai Tinggi",
    "gn:country_code":"MY",
    "gn:dem":52,
    "gn:feature_class":"P",
    "gn:feature_code":"PPL",
    "gn:name":"Sungai Tinggi",
    "gn:population":0,
    "gn:timezone":"Asia/Kuala_Lumpur",
    "iso:country":"MY",
    "name:msa_x_preferred":[
        "Sungai Tengi"
    ],
    "wof:name":"Sungai Tinggi",
    "wof:placetype":"locality"
},
  "geometry": {"coordinates":[101.46666999999999,3.41667],"type":"Point"}
}