{
  "type": "Feature",
  "properties": {
    "gn:admin1_code":"2",
    "gn:asciiname":"Kampung Kelompang",
    "gn:country_code":"MY",
    "gn:dem":6,
    "gn:feature_class":"P",
    "gn:feature_code":"PPL",
    "gn:name":"Kampung Kelompang",
    "gn:population":0,
    "gn:timezone":"Asia/Kuala_Lumpur",
    "iso:country":"MY",
    "name:msa_x_preferred":[
        "Kampung Kelompang"
    ],
    "name:und_x_variant":[
        "Kampong Kelompang"
    ],
    "wof:name":"Kampung Kelompang",
    "wof:placetype":"locality"
},
  "geometry": {"coordinates":[100.36233,6.13495],"type":"Point"}
}