{
  "type": "Feature",
  "properties": {
    "gn:country":"MY",
    "gn:fcode":"ADMD",
    "gn:population":0,
    "iso:country":"MY",
    "name:eng_x_preferred":[
        "Beseri"
    ],
    "name:epo_x_preferred":[
        "Beseri"
    ],
    "name:msa_x_preferred":[
        "Beseri"
    ],
    "name:nld_x_preferred":[
        "Beseri"
    ],
    "qs:name":"Beseri",
    "qs:name_adm0":"Malaysia",
    "qs:name_adm1":"Perlis",
    "qs:photos":2,
    "qs:photos_1k":1,
    "qs:photos_9k":1,
    "qs:photos_9r":1,
    "qs:photos_all":13,
    "qs:photos_sr":1,
    "qs:placetype":"LocalAdmin",
    "qs:pop_sr":"0",
    "wd:wordcount":53,
    "wof:name":"Beseri",
    "wof:placetype":"localadmin",
    "wof:population":0
},
  "geometry": {"coordinates":[100.21709,6.55394],"type":"Point"}
}