{
  "type": "Feature",
  "properties": {
    "gn:admin1_code":"13",
    "gn:asciiname":"Kampung Lingai",
    "gn:country_code":"MY",
    "gn:dem":22,
    "gn:feature_class":"P",
    "gn:feature_code":"PPL",
    "gn:name":"Kampung Lingai",
    "gn:population":0,
    "gn:timezone":"Asia/Kuala_Lumpur",
    "iso:country":"MY",
    "name:msa_x_preferred":[
        "Kampung Lingai"
    ],
    "name:und_x_variant":[
        "Kampong Lingai"
    ],
    "wof:name":"Kampung Lingai",
    "wof:placetype":"locality"
},
  "geometry": {"coordinates":[102.9995,5.4102],"type":"Point"}
}