{
  "type": "Feature",
  "properties": {
    "gn:admin1_code":"5.0",
    "gn:asciiname":"Gaong Panjang",
    "gn:country_code":"MY",
    "gn:dem":42,
    "gn:feature_class":"P",
    "gn:feature_code":"PPL",
    "gn:name":"Gaong Panjang",
    "gn:population":0,
    "gn:timezone":"Asia/Kuala_Lumpur",
    "iso:country":"MY",
    "name:msa_x_preferred":[
        "Gaong Panjang"
    ],
    "wof:name":"Gaong Panjang",
    "wof:placetype":"locality"
},
  "geometry": {"coordinates":[102.1262,2.5541],"type":"Point"}
}