{
  "type": "Feature",
  "properties": {
    "gn:admin1_code":"1.0",
    "gn:asciiname":"Kampung Jangka Beringin",
    "gn:country_code":"MY",
    "gn:dem":12,
    "gn:feature_class":"P",
    "gn:feature_code":"PPL",
    "gn:name":"Kampung Jangka Beringin",
    "gn:population":0,
    "gn:timezone":"Asia/Kuala_Lumpur",
    "iso:country":"MY",
    "name:msa_x_preferred":[
        "Kampung Jangka Beringin"
    ],
    "wof:name":"Kampung Jangka Beringin",
    "wof:placetype":"locality"
},
  "geometry": {"coordinates":[102.7647,2.1266],"type":"Point"}
}