{
  "type": "Feature",
  "properties": {
    "gn:admin1_code":"6.0",
    "gn:asciiname":"Kampung Gau",
    "gn:country_code":"MY",
    "gn:dem":46,
    "gn:feature_class":"P",
    "gn:feature_code":"PPL",
    "gn:name":"Kampung Gau",
    "gn:population":0,
    "gn:timezone":"Asia/Kuala_Lumpur",
    "iso:country":"MY",
    "name:msa_x_preferred":[
        "Kampung Gau"
    ],
    "wof:name":"Kampung Gau",
    "wof:placetype":"locality"
},
  "geometry": {"coordinates":[102.65519999999999,3.0252],"type":"Point"}
}