{
  "type": "Feature",
  "properties": {
    "gn:admin1_code":"1.0",
    "gn:asciiname":"Tanjung Pelepas",
    "gn:country_code":"MY",
    "gn:dem":4,
    "gn:feature_class":"P",
    "gn:feature_code":"PPL",
    "gn:name":"Tanjung Pelepas",
    "gn:population":0,
    "gn:timezone":"Asia/Kuala_Lumpur",
    "iso:country":"MY",
    "name:msa_x_preferred":[
        "Tanjung Pelepas"
    ],
    "wof:name":"Tanjung Pelepas",
    "wof:placetype":"locality"
},
  "geometry": {"coordinates":[103.5468,1.358],"type":"Point"}
}