{
  "type": "Feature",
  "properties": {
    "gn:admin1_code":"1.0",
    "gn:asciiname":"Tanjung Pelepas",
    "gn:country_code":"MY",
    "gn:dem":4,
    "gn:feature_class":"P",
    "gn:feature_code":"PPL",
    "gn:name":"Tanjung Pelepas",
    "gn:population":0,
    "gn:timezone":"Asia/Kuala_Lumpur",
    "iso:country":"MY",
    "name:ben_x_preferred":[
        "\u09a4\u09be\u09a8\u099c\u09c1\u0982 \u09aa\u09c7\u09b2\u09c7\u09aa\u09b8 \u09ac\u09a8\u09cd\u09a6\u09b0"
    ],
    "name:deu_x_preferred":[
        "Tanjung Pelepas"
    ],
    "name:ind_x_preferred":[
        "Pelabuhan Tanjung Pelepas"
    ],
    "name:msa_x_preferred":[
        "Tanjung Pelepas"
    ],
    "name:msa_x_variant":[
        "Pelabuhan Tanjung Pelepas"
    ],
    "name:nld_x_preferred":[
        "Tanjung Pelepas"
    ],
    "name:zho_x_preferred":[
        "\u4e39\u620e\u5e15\u62c9\u5e15\u65af\u6e2f"
    ],
    "wof:name":"Tanjung Pelepas",
    "wof:placetype":"locality"
},
  "geometry": {"coordinates":[103.5468,1.358],"type":"Point"}
}