{
  "type": "Feature",
  "properties": {
    "gn:admin1_code":"16.0",
    "gn:asciiname":"Kampung Patau",
    "gn:country_code":"MY",
    "gn:dem":831,
    "gn:feature_class":"P",
    "gn:feature_code":"PPL",
    "gn:name":"Kampung Patau",
    "gn:population":0,
    "gn:timezone":"Asia/Kuching",
    "iso:country":"MY",
    "name:msa_x_preferred":[
        "Kampung Patau"
    ],
    "name:und_x_variant":[
        "Kampong Patau",
        "Patau"
    ],
    "wof:name":"Kampung Patau",
    "wof:placetype":"locality"
},
  "geometry": {"coordinates":[116.4455,5.7613],"type":"Point"}
}