{
  "type": "Feature",
  "properties": {
    "gn:admin1_code":"13",
    "gn:asciiname":"Kampung Cepera",
    "gn:country_code":"MY",
    "gn:dem":95,
    "gn:feature_class":"P",
    "gn:feature_code":"PPL",
    "gn:name":"Kampung Cepera",
    "gn:population":0,
    "gn:timezone":"Asia/Kuala_Lumpur",
    "iso:country":"MY",
    "name:und_x_variant":[
        "Kampong Chepra",
        "Kampong Chepera",
        "Kampung Cepera"
    ],
    "wof:name":"Kampung Cepera",
    "wof:placetype":"locality"
},
  "geometry": {"coordinates":[102.94737000000001,4.52223],"type":"Point"}
}