{
  "type": "Feature",
  "properties": {
    "gn:admin1_code":"16",
    "gn:asciiname":"Kampung Tambilik",
    "gn:country_code":"MY",
    "gn:dem":12,
    "gn:feature_class":"P",
    "gn:feature_code":"PPL",
    "gn:name":"Kampung Tambilik",
    "gn:population":0,
    "gn:timezone":"Asia/Kuching",
    "iso:country":"MY",
    "name:msa_x_preferred":[
        "Kampung Tambilik"
    ],
    "name:und_x_variant":[
        "Tembilik",
        "Kampong Tambilik"
    ],
    "wof:name":"Kampung Tambilik",
    "wof:placetype":"locality"
},
  "geometry": {"coordinates":[115.5698,5.5747],"type":"Point"}
}