{
  "type": "Feature",
  "properties": {
    "gn:admin1_code":"13.0",
    "gn:asciiname":"Kampung Gertak Seratus",
    "gn:cc2":"MY",
    "gn:country_code":"MY",
    "gn:dem":6,
    "gn:feature_class":"P",
    "gn:feature_code":"PPL",
    "gn:name":"Kampung Gertak Seratus",
    "gn:population":0,
    "gn:timezone":"Asia/Kuala_Lumpur",
    "iso:country":"MY",
    "name:msa_x_preferred":[
        "Kampung Gertak Seratus"
    ],
    "wof:name":"Kampung Gertak Seratus",
    "wof:placetype":"locality"
},
  "geometry": {"coordinates":[102.54004999999999,5.82611],"type":"Point"}
}