{
  "type": "Feature",
  "properties": {
    "gn:admin1_code":"16",
    "gn:asciiname":"Sumangara",
    "gn:country_code":"MY",
    "gn:dem":371,
    "gn:feature_class":"P",
    "gn:feature_code":"PPL",
    "gn:name":"Sumangara",
    "gn:population":0,
    "gn:timezone":"Asia/Kuching",
    "iso:country":"MY",
    "wof:name":"Sumangara",
    "wof:placetype":"locality"
},
  "geometry": {"coordinates":[116.25,4.55],"type":"Point"}
}