{
  "type": "Feature",
  "properties": {
    "gn:admin1_code":"3",
    "gn:asciiname":"Kampong Pasir Kelang",
    "gn:country_code":"MY",
    "gn:dem":23,
    "gn:feature_class":"P",
    "gn:feature_code":"PPL",
    "gn:name":"Kampong Pasir Kelang",
    "gn:population":0,
    "gn:timezone":"Asia/Kuala_Lumpur",
    "iso:country":"MY",
    "wof:name":"Kampong Pasir Kelang",
    "wof:placetype":"locality"
},
  "geometry": {"coordinates":[102.15000000000001,5.61667],"type":"Point"}
}