{
  "type": "Feature",
  "properties": {
    "gn:admin1_code":"3.0",
    "gn:asciiname":"Kampung Kuala Balar",
    "gn:country_code":"MY",
    "gn:dem":674,
    "gn:feature_class":"P",
    "gn:feature_code":"PPL",
    "gn:name":"Kampung Kuala Balar",
    "gn:population":0,
    "gn:timezone":"Asia/Kuala_Lumpur",
    "iso:country":"MY",
    "name:msa_x_preferred":[
        "Kampung Kuala Balar"
    ],
    "wof:name":"Kampung Kuala Balar",
    "wof:placetype":"locality"
},
  "geometry": {"coordinates":[101.5201,4.9464],"type":"Point"}
}