{
  "type": "Feature",
  "properties": {
    "gn:country":"MY",
    "gn:fcode":"PPL",
    "gn:population":0,
    "iso:country":"MY",
    "name:msa_x_preferred":[
        "Kampung Peringgit"
    ],
    "name:und_x_variant":[
        "Kampong Pringgit"
    ],
    "qs:name":"Kampong Peringgit",
    "qs:name_adm0":"Malaysia",
    "qs:name_adm1":"Melaka",
    "qs:photos":2,
    "qs:photos_1k":1,
    "qs:photos_9k":1,
    "qs:photos_9r":2,
    "qs:photos_all":56,
    "qs:photos_sr":1,
    "qs:placetype":"Town",
    "qs:pop_sr":"0",
    "wd:wordcount":56,
    "wof:name":"Kampong Peringgit",
    "wof:placetype":"locality",
    "wof:population":0
},
  "geometry": {"coordinates":[102.2521,2.222],"type":"Point"}
}