{
  "type": "Feature",
  "properties": {
    "gn:admin1_code":"9",
    "gn:asciiname":"Tanjung Ketupat",
    "gn:country_code":"MY",
    "gn:dem":1,
    "gn:feature_class":"P",
    "gn:feature_code":"PPL",
    "gn:name":"Tanjung Ketupat",
    "gn:population":0,
    "gn:timezone":"Asia/Kuala_Lumpur",
    "iso:country":"MY",
    "name:und_x_variant":[
        "Tanjong Katupat",
        "Tanjong Ketupat",
        "Tanjung Ketupat"
    ],
    "wof:name":"Tanjung Ketupat",
    "wof:placetype":"locality"
},
  "geometry": {"coordinates":[100.446,5.2813],"type":"Point"}
}