{
  "type": "Feature",
  "properties": {
    "gn:admin1_code":"2",
    "gn:asciiname":"Kampung Hulu Sedim",
    "gn:country_code":"MY",
    "gn:dem":54,
    "gn:feature_class":"P",
    "gn:feature_code":"PPL",
    "gn:name":"Kampung Hulu Sedim",
    "gn:population":0,
    "gn:timezone":"Asia/Kuala_Lumpur",
    "iso:country":"MY",
    "name:msa_x_preferred":[
        "Kampung Ulu Sedim"
    ],
    "name:und_x_variant":[
        "Kampong Ulu Sedim",
        "Kampung Hulu Sedim"
    ],
    "wof:name":"Kampung Hulu Sedim",
    "wof:placetype":"locality"
},
  "geometry": {"coordinates":[100.74581000000001,5.4111],"type":"Point"}
}