{
  "type": "Feature",
  "properties": {
    "gn:country":"MY",
    "gn:fcode":"PPL",
    "gn:population":0,
    "iso:country":"MY",
    "name:msa_x_preferred":[
        "Kampung Tebengau"
    ],
    "name:und_x_variant":[
        "Kampong Tebengau"
    ],
    "qs:name":"Kampung Tebengau",
    "qs:name_adm0":"Malaysia",
    "qs:name_adm1":"Kedah",
    "qs:photos_9r":0,
    "qs:photos_sr":0,
    "qs:placetype":"Town",
    "qs:pop_sr":"0",
    "wof:name":"Kampung Tebengau",
    "wof:placetype":"locality",
    "wof:population":0
},
  "geometry": {"coordinates":[100.33137000000001,6.04603],"type":"Point"}
}