{
  "type": "Feature",
  "properties": {
    "iso:country":"MY",
    "qs:name":"Simpok",
    "qs:name_adm0":"Malaysia",
    "qs:name_adm1":"Sarawak",
    "qs:photos":151,
    "qs:photos_1k":31,
    "qs:photos_9k":1,
    "qs:photos_9r":4,
    "qs:photos_all":151,
    "qs:photos_sr":4,
    "qs:placetype":"Town",
    "qs:pop_sr":"0",
    "wof:name":"Simpok",
    "wof:placetype":"locality"
},
  "geometry": {"coordinates":[110.352172,1.2798],"type":"Point"}
}