{
  "type": "Feature",
  "properties": {
    "gn:admin1_code":"16.0",
    "gn:asciiname":"Kampung Merotai Besar",
    "gn:country_code":"MY",
    "gn:dem":14,
    "gn:elevation":"0.0",
    "gn:feature_class":"P",
    "gn:feature_code":"PPL",
    "gn:name":"Kampung Merotai Besar",
    "gn:population":0,
    "gn:timezone":"Asia/Kuching",
    "iso:country":"MY",
    "wof:name":"Kampung Merotai Besar",
    "wof:placetype":"locality"
},
  "geometry": {"coordinates":[117.77030000000001,4.4252],"type":"Point"}
}