{
  "type": "Feature",
  "properties": {
    "gn:admin1_code":"6.0",
    "gn:asciiname":"Kampung Datok Hamzah",
    "gn:country_code":"MY",
    "gn:dem":78,
    "gn:feature_class":"P",
    "gn:feature_code":"PPL",
    "gn:name":"Kampung Datok Hamzah",
    "gn:population":0,
    "gn:timezone":"Asia/Kuala_Lumpur",
    "iso:country":"MY",
    "name:msa_x_preferred":[
        "Kampung Datok Hamzah"
    ],
    "wof:name":"Kampung Datok Hamzah",
    "wof:placetype":"locality"
},
  "geometry": {"coordinates":[102.4068,3.1145],"type":"Point"}
}