{
  "type": "Feature",
  "properties": {
    "gn:country":"MY",
    "gn:fcode":"PPL",
    "gn:pop":0,
    "iso:country":"MY",
    "name:msa_x_preferred":[
        "Kampung Batu"
    ],
    "qs:name":"Kampung Bau",
    "qs:name_adm0":"Malaysia",
    "qs:name_adm1":"Pahang",
    "qs:photos_9r":0,
    "qs:photos_sr":0,
    "qs:placetype":"Town",
    "qs:pop_sr":"0",
    "wof:name":"Kampung Bau",
    "wof:placetype":"locality",
    "wof:population":0
},
  "geometry": {"coordinates":[102.3647,3.887],"type":"Point"}
}