{
  "type": "Feature",
  "properties": {
    "iso:country":"MY",
    "name:eng_x_preferred":[
        "Batu Maung"
    ],
    "name:fas_x_preferred":[
        "\u0628\u0627\u062a\u0648 \u0645\u0627\u0626\u0648\u0646\u06af"
    ],
    "name:msa_x_preferred":[
        "Batu Maung"
    ],
    "name:nld_x_preferred":[
        "Batu Maung"
    ],
    "name:tam_x_preferred":[
        "\u0baa\u0ba4\u0bcd\u0ba4\u0bc1 \u0bae\u0bbe\u0bb5\u0bc1\u0b99\u0bcd"
    ],
    "name:vie_x_preferred":[
        "Batu Maung"
    ],
    "name:zho_x_preferred":[
        "\u5cc7\u90fd\u8305"
    ],
    "qs:gn_adm0_cc":"MY",
    "qs:gn_fcode":"PPL",
    "qs:gn_local":1764027,
    "qs:gn_nam_loc":"Kampong Sungai Gelugor, Pulau Pinang, MY",
    "qs:gn_namadm1":"09",
    "qs:gn_name":"Batu Maung",
    "qs:local_max":422,
    "qs:local_sum":2726,
    "qs:localhoods":18,
    "qs:name":"Batu Maung",
    "qs:name_adm0":"Malaysia",
    "qs:name_adm1":"Pulau Pinang",
    "qs:name_adm2":"Barat Daya",
    "qs:name_lau":"Mukim 12",
    "qs:name_local":"Kampong Sungai Gelugor",
    "qs:photo_max":62,
    "qs:photo_sum":220,
    "qs:placetype":"Suburb",
    "qs:quad_count":12,
    "qs:woe_adm0":23424901,
    "qs:woe_adm1":2346304,
    "qs:woe_adm2":56013634,
    "qs:woe_lau":56014458,
    "qs:woe_local":1149014,
    "qs:woe_ver":"7.10.0",
    "wof:name":"Batu Maung",
    "wof:placetype":"neighbourhood"
},
  "geometry": {"coordinates":[100.28918,5.278928],"type":"Point"}
}