{
  "type": "Feature",
  "properties": {
    "iso:country":"MY",
    "name:eng_x_preferred":[
        "Batu Maung"
    ],
    "name:msa_x_preferred":[
        "Batu Maung"
    ],
    "name:unk_x_variant":[
        "Batu Maung"
    ],
    "qs:gn_adm0_cc":"MY",
    "qs:gn_fcode":"PPL",
    "qs:gn_local":1764027,
    "qs:gn_nam_loc":"Kampong Sungai Gelugor, Pulau Pinang, MY",
    "qs:gn_namadm1":"09",
    "qs:gn_name":"Batu Maung",
    "qs:local_max":422,
    "qs:local_sum":2726,
    "qs:localhoods":18,
    "qs:name":"Batu Maung",
    "qs:name_adm0":"Malaysia",
    "qs:name_adm1":"Pulau Pinang",
    "qs:name_adm2":"Barat Daya",
    "qs:name_lau":"Mukim 12",
    "qs:name_local":"Kampong Sungai Gelugor",
    "qs:photo_max":62,
    "qs:photo_sum":220,
    "qs:placetype":"Suburb",
    "qs:quad_count":12,
    "qs:woe_adm0":23424901,
    "qs:woe_adm1":2346304,
    "qs:woe_adm2":56013634,
    "qs:woe_lau":56014458,
    "qs:woe_local":1149014,
    "qs:woe_ver":"7.10.0",
    "wof:name":"Batu Maung",
    "wof:placetype":"neighbourhood"
},
  "geometry": {"coordinates":[100.28918,5.278928],"type":"Point"}
}