{
  "type": "Feature",
  "properties": {
    "gn:admin1_code":"11.0",
    "gn:asciiname":"Rumah Mantok",
    "gn:cc2":"MY",
    "gn:country_code":"MY",
    "gn:dem":112,
    "gn:feature_class":"P",
    "gn:feature_code":"PPL",
    "gn:name":"Rumah Mantok",
    "gn:population":0,
    "gn:timezone":"Asia/Kuching",
    "iso:country":"MY",
    "name:und_x_variant":[
        "Rumah Seti",
        "Rumah Mantok"
    ],
    "wof:name":"Rumah Mantok",
    "wof:placetype":"locality"
},
  "geometry": {"coordinates":[112.28333000000001,1.86667],"type":"Point"}
}