{
  "type": "Feature",
  "properties": {
    "gn:admin1_code":"16",
    "gn:asciiname":"Pingas",
    "gn:country_code":"MY",
    "gn:dem":109,
    "gn:feature_class":"P",
    "gn:feature_code":"PPL",
    "gn:name":"Pingas",
    "gn:population":0,
    "gn:timezone":"Asia/Kuching",
    "iso:country":"MY",
    "wof:name":"Pingas",
    "wof:placetype":"locality"
},
  "geometry": {"coordinates":[116.71105,5.19817],"type":"Point"}
}