{
  "type": "Feature",
  "properties": {
    "gn:admin1_code":"11",
    "gn:asciiname":"Kampong Peluntan",
    "gn:cc2":"MY",
    "gn:country_code":"MY",
    "gn:dem":23,
    "gn:feature_class":"P",
    "gn:feature_code":"PPL",
    "gn:name":"Kampong Peluntan",
    "gn:population":0,
    "gn:timezone":"Asia/Kuching",
    "iso:country":"MY",
    "name:und_x_variant":[
        "Kampong Pluntan",
        "Kampong Peluntan"
    ],
    "wof:name":"Kampong Peluntan",
    "wof:placetype":"locality"
},
  "geometry": {"coordinates":[110.28333000000001,1.43333],"type":"Point"}
}