{
  "type": "Feature",
  "properties": {
    "gn:admin1_code":"7.0",
    "gn:asciiname":"Kampung Cangkat Larah",
    "gn:country_code":"MY",
    "gn:dem":37,
    "gn:feature_class":"P",
    "gn:feature_code":"PPL",
    "gn:name":"Kampung Cangkat Larah",
    "gn:population":0,
    "gn:timezone":"Asia/Kuala_Lumpur",
    "iso:country":"MY",
    "name:msa_x_preferred":[
        "Kampung Cangkat Larah"
    ],
    "wof:name":"Kampung Cangkat Larah",
    "wof:placetype":"locality"
},
  "geometry": {"coordinates":[101.0658,4.558],"type":"Point"}
}