{
  "type": "Feature",
  "properties": {
    "gn:admin1_code":"13.0",
    "gn:asciiname":"Kampung Tok Motung",
    "gn:country_code":"MY",
    "gn:dem":21,
    "gn:feature_class":"P",
    "gn:feature_code":"PPL",
    "gn:name":"Kampung Tok Motung",
    "gn:population":0,
    "gn:timezone":"Asia/Kuala_Lumpur",
    "iso:country":"MY",
    "name:msa_x_preferred":[
        "Kampung Tok Motung"
    ],
    "name:und_x_variant":[
        "Kampung Tok Motong"
    ],
    "wof:name":"Kampung Tok Motung",
    "wof:placetype":"locality"
},
  "geometry": {"coordinates":[102.44497,5.7486],"type":"Point"}
}