{
  "type": "Feature",
  "properties": {
    "gn:admin1_code":"6.0",
    "gn:asciiname":"Taman Permatang Badak",
    "gn:country_code":"MY",
    "gn:dem":8,
    "gn:feature_class":"P",
    "gn:feature_code":"PPL",
    "gn:name":"Taman Permatang Badak",
    "gn:population":0,
    "gn:timezone":"Asia/Kuala_Lumpur",
    "iso:country":"MY",
    "name:msa_x_preferred":[
        "Taman Permatang Badak"
    ],
    "wof:name":"Taman Permatang Badak",
    "wof:placetype":"locality"
},
  "geometry": {"coordinates":[103.2647,3.7971],"type":"Point"}
}