{
  "type": "Feature",
  "properties": {
    "iso:country":"MY",
    "qs:name":"Labu",
    "qs:name_adm0":"Malaysia",
    "qs:name_adm1":"Selangor",
    "qs:photos":93,
    "qs:photos_1k":19,
    "qs:photos_9k":21,
    "qs:photos_9r":13,
    "qs:photos_all":4649,
    "qs:photos_sr":3,
    "qs:placetype":"LocalAdmin",
    "qs:pop_sr":"0",
    "wd:wordcount":17,
    "wof:name":"Labu",
    "wof:placetype":"localadmin"
},
  "geometry": {"coordinates":[101.737003,2.760299],"type":"Point"}
}