{
  "type": "Feature",
  "properties": {
    "gn:admin1_code":"6",
    "gn:asciiname":"Kampung Lobok",
    "gn:country_code":"MY",
    "gn:dem":22,
    "gn:feature_class":"P",
    "gn:feature_code":"PPL",
    "gn:name":"Kampung Lobok",
    "gn:population":0,
    "gn:timezone":"Asia/Kuala_Lumpur",
    "iso:country":"MY",
    "name:und_x_variant":[
        "Kampong Lobok"
    ],
    "wof:name":"Kampung Lobok",
    "wof:placetype":"locality"
},
  "geometry": {"coordinates":[103.25924000000001,3.25829],"type":"Point"}
}