{
  "type": "Feature",
  "properties": {
    "gn:admin1_code":"16.0",
    "gn:asciiname":"Kampung Tampat Tagas",
    "gn:country_code":"MY",
    "gn:dem":26,
    "gn:feature_class":"P",
    "gn:feature_code":"PPL",
    "gn:name":"Kampung Tampat Tagas",
    "gn:population":0,
    "gn:timezone":"Asia/Kuching",
    "iso:country":"MY",
    "name:msa_x_preferred":[
        "Kampung Tampat Tagas"
    ],
    "wof:name":"Kampung Tampat Tagas",
    "wof:placetype":"locality"
},
  "geometry": {"coordinates":[117.4725,6.2969],"type":"Point"}
}