{
  "type": "Feature",
  "properties": {
    "gn:admin1_code":"16.0",
    "gn:asciiname":"Kampung Patikang Ulu",
    "gn:country_code":"MY",
    "gn:dem":343,
    "gn:feature_class":"P",
    "gn:feature_code":"PPL",
    "gn:name":"Kampung Patikang Ulu",
    "gn:population":0,
    "gn:timezone":"Asia/Kuching",
    "iso:country":"MY",
    "wof:name":"Kampung Patikang Ulu",
    "wof:placetype":"locality"
},
  "geometry": {"coordinates":[116.12924,5.34376],"type":"Point"}
}