{
  "type": "Feature",
  "properties": {
    "gn:admin1_code":"2.0",
    "gn:asciiname":"Kampung Bongor",
    "gn:country_code":"MY",
    "gn:dem":72,
    "gn:feature_class":"P",
    "gn:feature_code":"PPL",
    "gn:name":"Kampung Bongor",
    "gn:population":0,
    "gn:timezone":"Asia/Kuala_Lumpur",
    "iso:country":"MY",
    "name:msa_x_preferred":[
        "Kampung Bongor"
    ],
    "wof:name":"Kampung Bongor",
    "wof:placetype":"locality"
},
  "geometry": {"coordinates":[100.91426,5.70397],"type":"Point"}
}