{
  "type": "Feature",
  "properties": {
    "gn:admin1_code":"2",
    "gn:asciiname":"Kampung Kangar",
    "gn:cc2":"MY",
    "gn:country_code":"MY",
    "gn:dem":84,
    "gn:feature_class":"P",
    "gn:feature_code":"PPL",
    "gn:name":"Kampung Kangar",
    "gn:population":0,
    "gn:timezone":"Asia/Kuala_Lumpur",
    "iso:country":"MY",
    "name:msa_x_preferred":[
        "Kampung Kangar"
    ],
    "name:und_x_variant":[
        "Kampong Kangar"
    ],
    "wof:name":"Kampung Kangar",
    "wof:placetype":"locality"
},
  "geometry": {"coordinates":[100.89440999999999,5.55861],"type":"Point"}
}