{
  "type": "Feature",
  "properties": {
    "gn:admin1_code":"16",
    "gn:asciiname":"Sebungali",
    "gn:country_code":"MY",
    "gn:dem":327,
    "gn:feature_class":"P",
    "gn:feature_code":"PPL",
    "gn:name":"Sebungali",
    "gn:population":0,
    "gn:timezone":"Asia/Kuching",
    "iso:country":"MY",
    "wof:name":"Sebungali",
    "wof:placetype":"locality"
},
  "geometry": {"coordinates":[116.26667,4.51667],"type":"Point"}
}