{
  "type": "Feature",
  "properties": {
    "gn:admin1_code":"16.0",
    "gn:asciiname":"Kampung Tudangan",
    "gn:country_code":"MY",
    "gn:dem":508,
    "gn:feature_class":"P",
    "gn:feature_code":"PPL",
    "gn:name":"Kampung Tudangan",
    "gn:population":0,
    "gn:timezone":"Asia/Kuching",
    "iso:country":"MY",
    "name:msa_x_preferred":[
        "Kampung Tudangan"
    ],
    "wof:name":"Kampung Tudangan",
    "wof:placetype":"locality"
},
  "geometry": {"coordinates":[116.69329999999999,5.9749],"type":"Point"}
}