{
  "type": "Feature",
  "properties": {
    "gn:admin1_code":"2.0",
    "gn:asciiname":"Kampung Banggul Kiat",
    "gn:country_code":"MY",
    "gn:dem":47,
    "gn:feature_class":"P",
    "gn:feature_code":"PPL",
    "gn:name":"Kampung Banggul Kiat",
    "gn:population":0,
    "gn:timezone":"Asia/Kuala_Lumpur",
    "iso:country":"MY",
    "name:msa_x_preferred":[
        "Kampung Banggul Kiat"
    ],
    "wof:name":"Kampung Banggul Kiat",
    "wof:placetype":"locality"
},
  "geometry": {"coordinates":[100.75415,5.82074],"type":"Point"}
}