{
  "type": "Feature",
  "properties": {
    "gn:admin1_code":"6",
    "gn:asciiname":"Kampong Lubok Gading",
    "gn:country_code":"MY",
    "gn:dem":96,
    "gn:feature_class":"P",
    "gn:feature_code":"PPL",
    "gn:name":"Kampong Lubok Gading",
    "gn:population":0,
    "gn:timezone":"Asia/Kuala_Lumpur",
    "iso:country":"MY",
    "wof:name":"Kampong Lubok Gading",
    "wof:placetype":"locality"
},
  "geometry": {"coordinates":[102.75,3.48333],"type":"Point"}
}