{
  "type": "Feature",
  "properties": {
    "gn:admin1_code":"11.0",
    "gn:asciiname":"Rumah Padang",
    "gn:country_code":"MY",
    "gn:dem":85,
    "gn:feature_class":"P",
    "gn:feature_code":"PPL",
    "gn:name":"Rumah Padang",
    "gn:population":0,
    "gn:timezone":"Asia/Kuching",
    "iso:country":"MY",
    "name:und_x_variant":[
        "Rumah Pandang",
        "Rumah Padang"
    ],
    "wof:name":"Rumah Padang",
    "wof:placetype":"locality"
},
  "geometry": {"coordinates":[111.88333,1.78333],"type":"Point"}
}