{
  "type": "Feature",
  "properties": {
    "gn:admin1_code":"4",
    "gn:asciiname":"Kampung Komong",
    "gn:country_code":"MY",
    "gn:dem":19,
    "gn:feature_class":"P",
    "gn:feature_code":"PPL",
    "gn:name":"Kampung Komong",
    "gn:population":0,
    "gn:timezone":"Asia/Kuala_Lumpur",
    "iso:country":"MY",
    "name:msa_x_preferred":[
        "Kampung Komong"
    ],
    "name:und_x_variant":[
        "Kampong Komong"
    ],
    "wof:name":"Kampung Komong",
    "wof:placetype":"locality"
},
  "geometry": {"coordinates":[102.5068,2.3298],"type":"Point"}
}