{
  "type": "Feature",
  "properties": {
    "gn:admin1_code":"16",
    "gn:asciiname":"Kampong Sinsara",
    "gn:country_code":"MY",
    "gn:dem":10,
    "gn:feature_class":"P",
    "gn:feature_code":"PPL",
    "gn:name":"Kampong Sinsara",
    "gn:population":0,
    "gn:timezone":"Asia/Kuching",
    "iso:country":"MY",
    "name:msa_x_preferred":[
        "Kampong Sinsara"
    ],
    "wof:name":"Kampong Sinsara",
    "wof:placetype":"locality"
},
  "geometry": {"coordinates":[116.31229999999999,6.2641],"type":"Point"}
}