{
  "type": "Feature",
  "properties": {
    "gn:admin1_code":"16.0",
    "gn:asciiname":"Kampung Menawo Laut",
    "gn:country_code":"MY",
    "gn:dem":310,
    "gn:feature_class":"P",
    "gn:feature_code":"PPL",
    "gn:name":"Kampung Menawo Laut",
    "gn:population":0,
    "gn:timezone":"Asia/Kuching",
    "iso:country":"MY",
    "name:msa_x_preferred":[
        "Kampung Menawo Laut"
    ],
    "wof:name":"Kampung Menawo Laut",
    "wof:placetype":"locality"
},
  "geometry": {"coordinates":[116.1832,5.3144],"type":"Point"}
}