{
  "type": "Feature",
  "properties": {
    "gn:admin1_code":"16",
    "gn:asciiname":"Kampung Simpangan",
    "gn:country_code":"MY",
    "gn:dem":9,
    "gn:feature_class":"P",
    "gn:feature_code":"PPL",
    "gn:name":"Kampung Simpangan",
    "gn:population":0,
    "gn:timezone":"Asia/Kuching",
    "iso:country":"MY",
    "name:msa_x_preferred":[
        "Kampung Simpangan"
    ],
    "name:und_x_variant":[
        "Kampong Simpangan"
    ],
    "wof:name":"Kampung Simpangan",
    "wof:placetype":"locality"
},
  "geometry": {"coordinates":[116.2029,6.2087],"type":"Point"}
}