{
  "type": "Feature",
  "properties": {
    "gn:admin1_code":"1.0",
    "gn:asciiname":"Kampung Lenek",
    "gn:country_code":"MY",
    "gn:dem":74,
    "gn:feature_class":"P",
    "gn:feature_code":"PPL",
    "gn:name":"Kampung Lenek",
    "gn:population":0,
    "gn:timezone":"Asia/Kuala_Lumpur",
    "iso:country":"MY",
    "name:msa_x_preferred":[
        "Kampung Lenek"
    ],
    "wof:name":"Kampung Lenek",
    "wof:placetype":"locality"
},
  "geometry": {"coordinates":[103.089,2.329],"type":"Point"}
}