{
  "type": "Feature",
  "properties": {
    "iso:country":"MY",
    "name:deu_x_preferred":[
        "Kampar"
    ],
    "name:fra_x_preferred":[
        "Kampar"
    ],
    "name:ind_x_preferred":[
        "Kampar"
    ],
    "name:min_x_preferred":[
        "Kampar"
    ],
    "name:nld_x_preferred":[
        "Kampar"
    ],
    "name:vie_x_preferred":[
        "Kampar"
    ],
    "qs:name":"Kampar",
    "qs:name_adm0":"Malaysia",
    "qs:name_adm1":"Perak",
    "qs:photos":1,
    "qs:photos_1k":1,
    "qs:photos_9k":1,
    "qs:photos_9r":4,
    "qs:photos_all":276,
    "qs:photos_sr":1,
    "qs:placetype":"LocalAdmin",
    "qs:pop_sr":"0",
    "wd:wordcount":42,
    "wof:name":"Kampar",
    "wof:placetype":"localadmin"
},
  "geometry": {"coordinates":[101.155242,4.34273],"type":"Point"}
}