{
  "type": "Feature",
  "properties": {
    "gn:admin1_code":"2",
    "gn:asciiname":"Kampung Nering",
    "gn:cc2":"MY",
    "gn:country_code":"MY",
    "gn:dem":63,
    "gn:feature_class":"P",
    "gn:feature_code":"PPL",
    "gn:name":"Kampung Nering",
    "gn:population":0,
    "gn:timezone":"Asia/Kuala_Lumpur",
    "iso:country":"MY",
    "name:msa_x_preferred":[
        "Kampung Nering"
    ],
    "name:und_x_variant":[
        "Kampong Nering"
    ],
    "wof:name":"Kampung Nering",
    "wof:placetype":"locality"
},
  "geometry": {"coordinates":[100.91845000000001,5.69563],"type":"Point"}
}