{
  "type": "Feature",
  "properties": {
    "gn:admin1_code":"6",
    "gn:asciiname":"Kampung Sungai Karang Pantai",
    "gn:country_code":"MY",
    "gn:dem":9,
    "gn:feature_class":"P",
    "gn:feature_code":"PPL",
    "gn:name":"Kampung Sungai Karang Pantai",
    "gn:population":0,
    "gn:timezone":"Asia/Kuala_Lumpur",
    "iso:country":"MY",
    "name:msa_x_preferred":[
        "Kampung Sungai Karang Pantai"
    ],
    "name:und_x_variant":[
        "Kampong Sungei Karang",
        "Kampong Pantai Sungai Karang"
    ],
    "wof:name":"Kampung Sungai Karang Pantai",
    "wof:placetype":"locality"
},
  "geometry": {"coordinates":[103.364,3.8945],"type":"Point"}
}