{
  "type": "Feature",
  "properties": {
    "gn:admin1_code":"16",
    "gn:asciiname":"Kampung Sambai",
    "gn:country_code":"MY",
    "gn:dem":6,
    "gn:feature_class":"P",
    "gn:feature_code":"PPL",
    "gn:name":"Kampung Sambai",
    "gn:population":0,
    "gn:timezone":"Asia/Kuching",
    "iso:country":"MY",
    "name:msa_x_preferred":[
        "Kampung Sambai"
    ],
    "name:und_x_variant":[
        "Kampong Sambai"
    ],
    "wof:name":"Kampung Sambai",
    "wof:placetype":"locality"
},
  "geometry": {"coordinates":[116.0384,5.8172],"type":"Point"}
}