{
  "type": "Feature",
  "properties": {
    "gn:admin1_code":"9.0",
    "gn:asciiname":"Titi Mukim",
    "gn:country_code":"MY",
    "gn:dem":3,
    "gn:feature_class":"P",
    "gn:feature_code":"PPL",
    "gn:name":"Titi Mukim",
    "gn:population":0,
    "gn:timezone":"Asia/Kuala_Lumpur",
    "iso:country":"MY",
    "name:msa_x_preferred":[
        "Titi Mukim"
    ],
    "wof:name":"Titi Mukim",
    "wof:placetype":"locality"
},
  "geometry": {"coordinates":[100.38523000000001,5.49389],"type":"Point"}
}