{
  "type": "Feature",
  "properties": {
    "gn:admin1_code":"4.0",
    "gn:asciiname":"Kampung Pulau Limbungan",
    "gn:country_code":"MY",
    "gn:dem":7,
    "gn:feature_class":"P",
    "gn:feature_code":"PPL",
    "gn:name":"Kampung Pulau Limbungan",
    "gn:population":0,
    "gn:timezone":"Asia/Kuala_Lumpur",
    "iso:country":"MY",
    "name:msa_x_preferred":[
        "Kampung Pulau Limbungan"
    ],
    "wof:name":"Kampung Pulau Limbungan",
    "wof:placetype":"locality"
},
  "geometry": {"coordinates":[102.218,2.2107],"type":"Point"}
}