{
  "type": "Feature",
  "properties": {
    "gn:admin1_code":"0.0",
    "gn:asciiname":"Kiatinu",
    "gn:country_code":"MY",
    "gn:dem":371,
    "gn:feature_class":"P",
    "gn:feature_code":"PPL",
    "gn:name":"Kiatinu",
    "gn:population":0,
    "gn:timezone":"Asia/Kuching",
    "iso:country":"MY",
    "wof:name":"Kiatinu",
    "wof:placetype":"locality"
},
  "geometry": {"coordinates":[116.71666999999999,5.38333],"type":"Point"}
}