{
  "type": "Feature",
  "properties": {
    "gn:admin1_code":"7",
    "gn:asciiname":"Kampong Raja Raya",
    "gn:country_code":"MY",
    "gn:dem":321,
    "gn:feature_class":"P",
    "gn:feature_code":"PPL",
    "gn:name":"Kampong Raja Raya",
    "gn:population":0,
    "gn:timezone":"Asia/Kuala_Lumpur",
    "iso:country":"MY",
    "wof:name":"Kampong Raja Raya",
    "wof:placetype":"locality"
},
  "geometry": {"coordinates":[101.01667,5.71667],"type":"Point"}
}