{
  "type": "Feature",
  "properties": {
    "gn:admin1_code":"16.0",
    "gn:asciiname":"Polar Park",
    "gn:country_code":"MY",
    "gn:dem":1577,
    "gn:feature_class":"P",
    "gn:feature_code":"PPL",
    "gn:name":"Polar Park",
    "gn:population":0,
    "gn:timezone":"Asia/Kuching",
    "iso:country":"MY",
    "name:msa_x_preferred":[
        "Polar Park"
    ],
    "wof:name":"Polar Park",
    "wof:placetype":"locality"
},
  "geometry": {"coordinates":[116.5446,6.00536],"type":"Point"}
}