{
  "type": "Feature",
  "properties": {
    "gn:admin1_code":"16.0",
    "gn:asciiname":"Bantangan",
    "gn:cc2":"MY",
    "gn:country_code":"MY",
    "gn:dem":264,
    "gn:feature_class":"P",
    "gn:feature_code":"PPL",
    "gn:name":"Bantangan",
    "gn:population":0,
    "gn:timezone":"Asia/Kuching",
    "iso:country":"MY",
    "name:und_x_variant":[
        "Bantangon",
        "Bantangan"
    ],
    "wof:name":"Bantangan",
    "wof:placetype":"locality"
},
  "geometry": {"coordinates":[116.25,4.48333],"type":"Point"}
}