{
  "type": "Feature",
  "properties": {
    "iso:country":"MY",
    "name:eng_x_preferred":[
        "Kampong Sekudai"
    ],
    "name:eng_x_variant":[
        "Kampong Skudai"
    ],
    "name:msa_x_preferred":[
        "Kampung Sekudai"
    ],
    "name:unk_x_variant":[
        "Kampong Skudai",
        "Kampong Sekudai"
    ],
    "qs:gn_adm0_cc":"MY",
    "qs:gn_fcode":"PPLX",
    "qs:gn_local":1732752,
    "qs:gn_namadm1":"01",
    "qs:gn_name":"Kampung Sekudai",
    "qs:local_max":681,
    "qs:local_sum":3607,
    "qs:localhoods":29,
    "qs:name":"Kampong Sekudai",
    "qs:name_adm0":"Malaysia",
    "qs:name_adm1":"Johor",
    "qs:name_adm2":"Johor Bahru",
    "qs:name_lau":"Plentong",
    "qs:name_local":"Johor Baharu",
    "qs:photo_max":85,
    "qs:photo_sum":85,
    "qs:placetype":"Suburb",
    "qs:quad_count":1,
    "qs:woe_adm0":23424901,
    "qs:woe_adm1":2346296,
    "qs:woe_adm2":56013565,
    "qs:woe_lau":56014160,
    "qs:woe_local":1154698,
    "qs:woe_ver":"7.10.0",
    "wof:lang":[
        "eng"
    ],
    "wof:name":"Kampong Sekudai",
    "wof:placetype":"neighbourhood"
},
  "geometry": {"coordinates":[103.72879,1.467888],"type":"Point"}
}