{
  "type": "Feature",
  "properties": {
    "gn:admin1_code":"5",
    "gn:asciiname":"Kampung Chembong Ulu",
    "gn:country_code":"MY",
    "gn:dem":64,
    "gn:feature_class":"P",
    "gn:feature_code":"PPL",
    "gn:name":"Kampung Chembong Ulu",
    "gn:population":0,
    "gn:timezone":"Asia/Kuala_Lumpur",
    "iso:country":"MY",
    "name:msa_x_preferred":[
        "Kampung Chembong Ulu"
    ],
    "name:und_x_variant":[
        "Kampong Chembong Ulu"
    ],
    "wof:name":"Kampung Chembong Ulu",
    "wof:placetype":"locality"
},
  "geometry": {"coordinates":[102.0926,2.6194],"type":"Point"}
}