{
  "type": "Feature",
  "properties": {
    "gn:admin1_code":"11.0",
    "gn:asciiname":"Kampung Baharu Telok Elas",
    "gn:country_code":"MY",
    "gn:dem":15,
    "gn:feature_class":"P",
    "gn:feature_code":"PPL",
    "gn:name":"Kampung Baharu Telok Elas",
    "gn:population":0,
    "gn:timezone":"Asia/Kuching",
    "iso:country":"MY",
    "name:msa_x_preferred":[
        "Kampung Baharu Telok Elas"
    ],
    "wof:name":"Kampung Baharu Telok Elas",
    "wof:placetype":"locality"
},
  "geometry": {"coordinates":[111.77987,2.77178],"type":"Point"}
}