{
  "type": "Feature",
  "properties": {
    "gn:admin1_code":"11.0",
    "gn:asciiname":"Long Tikan",
    "gn:country_code":"MY",
    "gn:dem":255,
    "gn:feature_class":"P",
    "gn:feature_code":"PPL",
    "gn:name":"Long Tikan",
    "gn:population":0,
    "gn:timezone":"Asia/Kuching",
    "iso:country":"MY",
    "name:msa_x_preferred":[
        "Long Tikan"
    ],
    "wof:name":"Long Tikan",
    "wof:placetype":"locality"
},
  "geometry": {"coordinates":[114.9058,2.86361],"type":"Point"}
}