{
  "type": "Feature",
  "properties": {
    "gn:admin1_code":"11",
    "gn:asciiname":"Kampung Lubok Nibong",
    "gn:country_code":"MY",
    "gn:dem":97,
    "gn:feature_class":"P",
    "gn:feature_code":"PPL",
    "gn:name":"Kampung Lubok Nibong",
    "gn:population":0,
    "gn:timezone":"Asia/Kuala_Lumpur",
    "iso:country":"MY",
    "name:und_x_variant":[
        "Kampong Lubok Nibong"
    ],
    "wof:name":"Kampung Lubok Nibong",
    "wof:placetype":"locality"
},
  "geometry": {"coordinates":[101.55575,3.70289],"type":"Point"}
}