{
  "type": "Feature",
  "properties": {
    "gn:admin1_code":"4.0",
    "gn:asciiname":"Solok Pasir",
    "gn:country_code":"MY",
    "gn:dem":8,
    "gn:feature_class":"P",
    "gn:feature_code":"PPL",
    "gn:name":"Solok Pasir",
    "gn:population":0,
    "gn:timezone":"Asia/Kuala_Lumpur",
    "iso:country":"MY",
    "name:msa_x_preferred":[
        "Solok Pasir"
    ],
    "wof:name":"Solok Pasir",
    "wof:placetype":"locality"
},
  "geometry": {"coordinates":[102.42959999999999,2.1458],"type":"Point"}
}