{
  "type": "Feature",
  "properties": {
    "gn:admin1_code":"1.0",
    "gn:asciiname":"Kampung Baharu Yap Tau Sah",
    "gn:country_code":"MY",
    "gn:dem":37,
    "gn:feature_class":"P",
    "gn:feature_code":"PPL",
    "gn:name":"Kampung Baharu Yap Tau Sah",
    "gn:population":0,
    "gn:timezone":"Asia/Kuala_Lumpur",
    "iso:country":"MY",
    "name:msa_x_preferred":[
        "Kampung Baharu Yap Tau Sah"
    ],
    "name:und_x_variant":[
        "Kampong Yap Tau Sah",
        "Kampung Yap Tow Sah"
    ],
    "wof:name":"Kampung Baharu Yap Tau Sah",
    "wof:placetype":"locality"
},
  "geometry": {"coordinates":[103.32980000000001,2.0172],"type":"Point"}
}