{
  "type": "Feature",
  "properties": {
    "gn:admin1_code":"11",
    "gn:asciiname":"Lengain",
    "gn:country_code":"MY",
    "gn:dem":88,
    "gn:feature_class":"P",
    "gn:feature_code":"PPL",
    "gn:name":"Lengain",
    "gn:population":0,
    "gn:timezone":"Asia/Kuching",
    "iso:country":"MY",
    "wof:name":"Lengain",
    "wof:placetype":"locality"
},
  "geometry": {"coordinates":[111.61667,1.05],"type":"Point"}
}