{
  "type": "Feature",
  "properties": {
    "gn:admin1_code":"1.0",
    "gn:asciiname":"Taman Tasik",
    "gn:country_code":"MY",
    "gn:dem":16,
    "gn:feature_class":"P",
    "gn:feature_code":"PPL",
    "gn:name":"Taman Tasik",
    "gn:population":0,
    "gn:timezone":"Asia/Kuala_Lumpur",
    "iso:country":"MY",
    "name:msa_x_preferred":[
        "Taman Tasik"
    ],
    "wof:name":"Taman Tasik",
    "wof:placetype":"locality"
},
  "geometry": {"coordinates":[102.8355,2.5086],"type":"Point"}
}