{
  "type": "Feature",
  "properties": {
    "gn:admin1_code":"2",
    "gn:asciiname":"Kampung Bendang Darat",
    "gn:cc2":"MY",
    "gn:country_code":"MY",
    "gn:dem":80,
    "gn:feature_class":"P",
    "gn:feature_code":"PPL",
    "gn:name":"Kampung Bendang Darat",
    "gn:population":0,
    "gn:timezone":"Asia/Kuala_Lumpur",
    "iso:country":"MY",
    "name:msa_x_preferred":[
        "Kampung Bendang Darat"
    ],
    "name:und_x_variant":[
        "Kampong Bendang Darat"
    ],
    "wof:name":"Kampung Bendang Darat",
    "wof:placetype":"locality"
},
  "geometry": {"coordinates":[100.89585,5.73445],"type":"Point"}
}