{
  "type": "Feature",
  "properties": {
    "iso:country":"MY",
    "qs:name":"Kertih",
    "qs:name_adm0":"Malaysia",
    "qs:name_adm1":"Terengganu",
    "qs:photos":1,
    "qs:photos_1k":1,
    "qs:photos_9k":1,
    "qs:photos_9r":4,
    "qs:photos_all":228,
    "qs:photos_sr":1,
    "qs:placetype":"LocalAdmin",
    "qs:pop_sr":"0",
    "wof:name":"Kertih",
    "wof:placetype":"localadmin"
},
  "geometry": {"coordinates":[103.42752400000001,4.537238],"type":"Point"}
}