{
  "type": "Feature",
  "properties": {
    "gn:admin1_code":"3.0",
    "gn:asciiname":"Kampung Gerak",
    "gn:cc2":"MY",
    "gn:country_code":"MY",
    "gn:dem":241,
    "gn:feature_class":"P",
    "gn:feature_code":"PPL",
    "gn:name":"Kampung Gerak",
    "gn:population":0,
    "gn:timezone":"Asia/Kuala_Lumpur",
    "iso:country":"MY",
    "name:und_x_variant":[
        "Kampong Grak",
        "Kampung Gerak"
    ],
    "wof:name":"Kampung Gerak",
    "wof:placetype":"locality"
},
  "geometry": {"coordinates":[101.86667,4.73333],"type":"Point"}
}