{
  "type": "Feature",
  "properties": {
    "gn:admin1_code":"7.0",
    "gn:asciiname":"Taman Teh Teng Seng",
    "gn:country_code":"MY",
    "gn:dem":63,
    "gn:feature_class":"P",
    "gn:feature_code":"PPL",
    "gn:name":"Taman Teh Teng Seng",
    "gn:population":0,
    "gn:timezone":"Asia/Kuala_Lumpur",
    "iso:country":"MY",
    "name:msa_x_preferred":[
        "Taman Teh Teng Seng"
    ],
    "wof:name":"Taman Teh Teng Seng",
    "wof:placetype":"locality"
},
  "geometry": {"coordinates":[101.12609999999999,4.6177],"type":"Point"}
}