{
  "type": "Feature",
  "properties": {
    "gn:admin1_code":"13.0",
    "gn:asciiname":"Wakaf Temesu",
    "gn:country_code":"MY",
    "gn:dem":7,
    "gn:feature_class":"P",
    "gn:feature_code":"PPL",
    "gn:name":"Wakaf Temesu",
    "gn:population":0,
    "gn:timezone":"Asia/Kuala_Lumpur",
    "iso:country":"MY",
    "name:msa_x_preferred":[
        "Wakaf Temesu"
    ],
    "wof:name":"Wakaf Temesu",
    "wof:placetype":"locality"
},
  "geometry": {"coordinates":[103.09520000000001,5.3531],"type":"Point"}
}