{
  "type": "Feature",
  "properties": {
    "gn:admin1_code":"12",
    "gn:asciiname":"Kampung Batu Empat",
    "gn:country_code":"MY",
    "gn:dem":9,
    "gn:feature_class":"P",
    "gn:feature_code":"PPL",
    "gn:name":"Kampung Batu Empat",
    "gn:population":0,
    "gn:timezone":"Asia/Kuala_Lumpur",
    "iso:country":"MY",
    "name:msa_x_preferred":[
        "Kampung Batu Empat"
    ],
    "name:und_x_variant":[
        "Kampong Batu Empat"
    ],
    "wof:name":"Kampung Batu Empat",
    "wof:placetype":"locality"
},
  "geometry": {"coordinates":[101.7266,2.6487],"type":"Point"}
}