{
  "type": "Feature",
  "properties": {
    "gn:admin1_code":"16",
    "gn:asciiname":"Kampong Naradaw",
    "gn:cc2":"MY",
    "gn:country_code":"MY",
    "gn:dem":1071,
    "gn:feature_class":"P",
    "gn:feature_code":"PPL",
    "gn:name":"Kampong Naradaw",
    "gn:population":0,
    "gn:timezone":"Asia/Kuching",
    "iso:country":"MY",
    "name:und_x_variant":[
        "Naradaw",
        "Kampong Naradaw"
    ],
    "wof:name":"Kampong Naradaw",
    "wof:placetype":"locality"
},
  "geometry": {"coordinates":[116.59477,5.96477],"type":"Point"}
}