{
  "type": "Feature",
  "properties": {
    "gn:admin1_code":"5.0",
    "gn:asciiname":"Kampung Gesek",
    "gn:country_code":"MY",
    "gn:dem":167,
    "gn:feature_class":"P",
    "gn:feature_code":"PPL",
    "gn:name":"Kampung Gesek",
    "gn:population":0,
    "gn:timezone":"Asia/Kuala_Lumpur",
    "iso:country":"MY",
    "name:msa_x_preferred":[
        "Kampung Gesek"
    ],
    "wof:name":"Kampung Gesek",
    "wof:placetype":"locality"
},
  "geometry": {"coordinates":[102.0857,2.9156],"type":"Point"}
}