{
  "type": "Feature",
  "properties": {
    "gn:admin1_code":"6",
    "gn:asciiname":"Kampung Aur",
    "gn:country_code":"MY",
    "gn:dem":58,
    "gn:feature_class":"P",
    "gn:feature_code":"PPL",
    "gn:name":"Kampung Aur",
    "gn:population":0,
    "gn:timezone":"Asia/Kuala_Lumpur",
    "iso:country":"MY",
    "name:msa_x_preferred":[
        "Kampung Aur"
    ],
    "name:und_x_variant":[
        "Kampong Aur"
    ],
    "wof:name":"Kampung Aur",
    "wof:placetype":"locality"
},
  "geometry": {"coordinates":[102.22580000000001,4.1131],"type":"Point"}
}