{
  "type": "Feature",
  "properties": {
    "gn:admin1_code":"2",
    "gn:asciiname":"Kampung Pulau Tembun",
    "gn:country_code":"MY",
    "gn:dem":5,
    "gn:feature_class":"P",
    "gn:feature_code":"PPL",
    "gn:name":"Kampung Pulau Tembun",
    "gn:population":0,
    "gn:timezone":"Asia/Kuala_Lumpur",
    "iso:country":"MY",
    "name:und_x_variant":[
        "Kampong Pulau Tembun",
        "Kampung Pulau Tembun"
    ],
    "wof:name":"Kampung Pulau Tembun",
    "wof:placetype":"locality"
},
  "geometry": {"coordinates":[100.40175000000001,5.91271],"type":"Point"}
}