{
  "type": "Feature",
  "properties": {
    "gn:admin1_code":"5.0",
    "gn:asciiname":"Kampung Sungai Chua Lebu",
    "gn:country_code":"MY",
    "gn:dem":130,
    "gn:feature_class":"P",
    "gn:feature_code":"PPL",
    "gn:name":"Kampung Sungai Chua Lebu",
    "gn:population":0,
    "gn:timezone":"Asia/Kuala_Lumpur",
    "iso:country":"MY",
    "name:msa_x_preferred":[
        "Kampung Sungai Chua Lebu"
    ],
    "wof:name":"Kampung Sungai Chua Lebu",
    "wof:placetype":"locality"
},
  "geometry": {"coordinates":[102.0688,3.0999],"type":"Point"}
}