{
  "type": "Feature",
  "properties": {
    "gn:admin1_code":"16",
    "gn:asciiname":"Kampung Tinonun",
    "gn:country_code":"MY",
    "gn:dem":761,
    "gn:feature_class":"P",
    "gn:feature_code":"PPL",
    "gn:name":"Kampung Tinonun",
    "gn:population":0,
    "gn:timezone":"Asia/Kuching",
    "iso:country":"MY",
    "name:msa_x_preferred":[
        "Kampung Tinonun"
    ],
    "name:und_x_variant":[
        "Kampong Tinonun"
    ],
    "wof:name":"Kampung Tinonun",
    "wof:placetype":"locality"
},
  "geometry": {"coordinates":[116.7253,5.7163],"type":"Point"}
}