{
  "type": "Feature",
  "properties": {
    "gn:admin1_code":"6.0",
    "gn:asciiname":"Simpang Pulau Manis",
    "gn:country_code":"MY",
    "gn:dem":41,
    "gn:feature_class":"P",
    "gn:feature_code":"PPL",
    "gn:name":"Simpang Pulau Manis",
    "gn:population":0,
    "gn:timezone":"Asia/Kuala_Lumpur",
    "iso:country":"MY",
    "name:msa_x_preferred":[
        "Simpang Pulau Manis"
    ],
    "wof:name":"Simpang Pulau Manis",
    "wof:placetype":"locality"
},
  "geometry": {"coordinates":[103.1152,3.7054],"type":"Point"}
}