{
  "type": "Feature",
  "properties": {
    "gn:admin1_code":"4",
    "gn:asciiname":"Kampung Balik Bukit",
    "gn:country_code":"MY",
    "gn:dem":13,
    "gn:feature_class":"P",
    "gn:feature_code":"PPL",
    "gn:name":"Kampung Balik Bukit",
    "gn:population":0,
    "gn:timezone":"Asia/Kuala_Lumpur",
    "iso:country":"MY",
    "name:msa_x_preferred":[
        "Kampung Balik Bukit"
    ],
    "name:und_x_variant":[
        "Kampong Balik Bukit"
    ],
    "wof:name":"Kampung Balik Bukit",
    "wof:placetype":"locality"
},
  "geometry": {"coordinates":[102.29989999999999,2.2064],"type":"Point"}
}