{
  "type": "Feature",
  "properties": {
    "iso:country":"MY",
    "qs:name":"Belanja",
    "qs:name_adm0":"Malaysia",
    "qs:name_adm1":"Perak",
    "qs:photos":19,
    "qs:photos_1k":4,
    "qs:photos_9k":1,
    "qs:photos_9r":2,
    "qs:photos_all":68,
    "qs:photos_sr":1,
    "qs:placetype":"LocalAdmin",
    "qs:pop_sr":"0",
    "wof:name":"Belanja",
    "wof:placetype":"localadmin"
},
  "geometry": {"coordinates":[100.916702,4.4833],"type":"Point"}
}