{
  "type": "Feature",
  "properties": {
    "gn:admin1_code":"0.0",
    "gn:asciiname":"Kampong Simparg Ampat Bagan Nakoda Omar",
    "gn:cc2":"MY",
    "gn:country_code":"MY",
    "gn:dem":6,
    "gn:feature_class":"P",
    "gn:feature_code":"PPL",
    "gn:name":"Kampong Simparg Ampat Bagan Nakoda Omar",
    "gn:population":0,
    "gn:timezone":"Asia/Kuala_Lumpur",
    "iso:country":"MY",
    "name:und_x_variant":[
        "Bughien Nakoda Omar",
        "Kampong Simparg Ampat Bagan Nakoda Omar"
    ],
    "wof:name":"Kampong Simparg Ampat Bagan Nakoda Omar",
    "wof:placetype":"locality"
},
  "geometry": {"coordinates":[100.88333,3.78333],"type":"Point"}
}