{
  "type": "Feature",
  "properties": {
    "gn:admin1_code":"16",
    "gn:asciiname":"Kampung Bangsal",
    "gn:country_code":"MY",
    "gn:dem":9,
    "gn:feature_class":"P",
    "gn:feature_code":"PPL",
    "gn:name":"Kampung Bangsal",
    "gn:population":0,
    "gn:timezone":"Asia/Kuching",
    "iso:country":"MY",
    "name:msa_x_preferred":[
        "Kampung Bangsal"
    ],
    "name:und_x_variant":[
        "Bangsal",
        "Kampong Bangsal"
    ],
    "wof:name":"Kampung Bangsal",
    "wof:placetype":"locality"
},
  "geometry": {"coordinates":[115.524,5.4771],"type":"Point"}
}