{
  "type": "Feature",
  "properties": {
    "gn:admin1_code":"7.0",
    "gn:asciiname":"Taman Bunga Tanjung",
    "gn:country_code":"MY",
    "gn:dem":6,
    "gn:feature_class":"P",
    "gn:feature_code":"PPL",
    "gn:name":"Taman Bunga Tanjung",
    "gn:population":0,
    "gn:timezone":"Asia/Kuala_Lumpur",
    "iso:country":"MY",
    "name:msa_x_preferred":[
        "Taman Bunga Tanjung"
    ],
    "wof:name":"Taman Bunga Tanjung",
    "wof:placetype":"locality"
},
  "geometry": {"coordinates":[100.7633,4.1272],"type":"Point"}
}