{
  "type": "Feature",
  "properties": {
    "gn:admin1_code":"5.0",
    "gn:asciiname":"Kemajuan Tanah Kepis",
    "gn:country_code":"MY",
    "gn:dem":92,
    "gn:feature_class":"P",
    "gn:feature_code":"PPL",
    "gn:name":"Kemajuan Tanah Kepis",
    "gn:population":0,
    "gn:timezone":"Asia/Kuala_Lumpur",
    "iso:country":"MY",
    "name:msa_x_preferred":[
        "Kemajuan Tanah Kepis"
    ],
    "wof:name":"Kemajuan Tanah Kepis",
    "wof:placetype":"locality"
},
  "geometry": {"coordinates":[102.3454,2.7409],"type":"Point"}
}