{
  "type": "Feature",
  "properties": {
    "gn:admin1_code":"2.0",
    "gn:asciiname":"Dusun Mambong",
    "gn:cc2":"MY",
    "gn:country_code":"MY",
    "gn:dem":60,
    "gn:feature_class":"P",
    "gn:feature_code":"PPL",
    "gn:name":"Dusun Mambong",
    "gn:population":0,
    "gn:timezone":"Asia/Kuala_Lumpur",
    "iso:country":"MY",
    "name:und_x_variant":[
        "Dusun Mambang",
        "Dusun Mambong"
    ],
    "wof:name":"Dusun Mambong",
    "wof:placetype":"locality"
},
  "geometry": {"coordinates":[100.63333,5.85],"type":"Point"}
}