{
  "type": "Feature",
  "properties": {
    "iso:country":"MY",
    "qs:name":"Sungai Buloh",
    "qs:name_adm0":"Malaysia",
    "qs:name_adm1":"Selangor",
    "qs:photos":186,
    "qs:photos_1k":38,
    "qs:photos_9k":40,
    "qs:photos_9r":15,
    "qs:photos_all":8931,
    "qs:photos_sr":4,
    "qs:placetype":"LocalAdmin",
    "qs:pop_sr":"0",
    "wd:wordcount":383,
    "wof:name":"Sungai Buloh",
    "wof:placetype":"localadmin"
},
  "geometry": {"coordinates":[101.60948500000001,3.118988],"type":"Point"}
}