{
  "type": "Feature",
  "properties": {
    "iso:country":"MY",
    "name:ceb_x_preferred":[
        "Sungai Buloh"
    ],
    "name:deu_x_preferred":[
        "Sungai Buloh"
    ],
    "name:eng_x_preferred":[
        "Sungai Buloh"
    ],
    "name:fra_x_preferred":[
        "Sungai Buloh"
    ],
    "name:ind_x_preferred":[
        "Sungai Buloh"
    ],
    "name:jav_x_preferred":[
        "Sungai Buloh"
    ],
    "name:jpn_x_preferred":[
        "\u30b9\u30f3\u30ac\u30a4\u30fb\u30d6\u30ed\u30fc"
    ],
    "name:msa_x_preferred":[
        "Sungai Buloh"
    ],
    "name:nld_x_preferred":[
        "Sungai Buloh"
    ],
    "name:tam_x_preferred":[
        "\u0b9a\u0bc1\u0b99\u0bcd\u0b95\u0bc8 \u0baa\u0bc2\u0bb2\u0bcb"
    ],
    "name:zho_x_preferred":[
        "\u53cc\u6eaa\u6bdb\u7cef"
    ],
    "qs:name":"Sungai Buloh",
    "qs:name_adm0":"Malaysia",
    "qs:name_adm1":"Selangor",
    "qs:photos":186,
    "qs:photos_1k":38,
    "qs:photos_9k":40,
    "qs:photos_9r":15,
    "qs:photos_all":8931,
    "qs:photos_sr":4,
    "qs:placetype":"LocalAdmin",
    "qs:pop_sr":"0",
    "wd:wordcount":383,
    "wof:name":"Sungai Buloh",
    "wof:placetype":"localadmin"
},
  "geometry": {"coordinates":[101.60948500000001,3.118988],"type":"Point"}
}