{
  "type": "Feature",
  "properties": {
    "gn:admin1_code":"13",
    "gn:asciiname":"Kampung Temala Hilir",
    "gn:country_code":"MY",
    "gn:dem":22,
    "gn:feature_class":"P",
    "gn:feature_code":"PPL",
    "gn:name":"Kampung Temala Hilir",
    "gn:population":0,
    "gn:timezone":"Asia/Kuala_Lumpur",
    "iso:country":"MY",
    "name:msa_x_preferred":[
        "Kampung Temala Hilir"
    ],
    "name:und_x_variant":[
        "Kampong Temala Hilir"
    ],
    "wof:name":"Kampung Temala Hilir",
    "wof:placetype":"locality"
},
  "geometry": {"coordinates":[103.1319,5.0847],"type":"Point"}
}