{
  "type": "Feature",
  "properties": {
    "gn:admin1_code":"11.0",
    "gn:asciiname":"Long Laput",
    "gn:country_code":"MY",
    "gn:dem":18,
    "gn:feature_class":"P",
    "gn:feature_code":"PPL",
    "gn:name":"Long Laput",
    "gn:population":0,
    "gn:timezone":"Asia/Kuching",
    "iso:country":"MY",
    "name:ceb_x_preferred":[
        "Long Laput"
    ],
    "name:und_x_variant":[
        "Laput"
    ],
    "wof:name":"Long Laput",
    "wof:placetype":"locality"
},
  "geometry": {"coordinates":[114.428,3.7348],"type":"Point"}
}