{
  "type": "Feature",
  "properties": {
    "gn:admin1_code":"16",
    "gn:asciiname":"Kampung Tagas",
    "gn:country_code":"MY",
    "gn:dem":10,
    "gn:feature_class":"P",
    "gn:feature_code":"PPL",
    "gn:name":"Kampung Tagas",
    "gn:population":0,
    "gn:timezone":"Asia/Kuching",
    "iso:country":"MY",
    "name:msa_x_preferred":[
        "Kampung Tagas"
    ],
    "name:und_x_variant":[
        "Kampong Tagas"
    ],
    "wof:name":"Kampung Tagas",
    "wof:placetype":"locality"
},
  "geometry": {"coordinates":[116.2223,6.1581],"type":"Point"}
}