{
  "type": "Feature",
  "properties": {
    "gn:admin1_code":"13",
    "gn:asciiname":"Kampung Jadih",
    "gn:country_code":"MY",
    "gn:dem":43,
    "gn:feature_class":"P",
    "gn:feature_code":"PPL",
    "gn:name":"Kampung Jadih",
    "gn:population":0,
    "gn:timezone":"Asia/Kuala_Lumpur",
    "iso:country":"MY",
    "name:msa_x_preferred":[
        "Kampung Jadih"
    ],
    "name:und_x_variant":[
        "Kampong Jedeh",
        "Kampong Jadeh"
    ],
    "wof:name":"Kampung Jadih",
    "wof:placetype":"locality"
},
  "geometry": {"coordinates":[102.99250000000001,4.5868],"type":"Point"}
}