{
  "type": "Feature",
  "properties": {
    "gn:admin1_code":"13",
    "gn:asciiname":"Kampung Ru Dua",
    "gn:country_code":"MY",
    "gn:dem":9,
    "gn:feature_class":"P",
    "gn:feature_code":"PPL",
    "gn:name":"Kampung Ru Dua",
    "gn:population":0,
    "gn:timezone":"Asia/Kuala_Lumpur",
    "iso:country":"MY",
    "name:msa_x_preferred":[
        "Kampung Ru Dua"
    ],
    "name:und_x_variant":[
        "Kampong Ru Dua"
    ],
    "wof:name":"Kampung Ru Dua",
    "wof:placetype":"locality"
},
  "geometry": {"coordinates":[103.19199999999999,5.236],"type":"Point"}
}