{
  "type": "Feature",
  "properties": {
    "gn:admin1_code":"1.0",
    "gn:asciiname":"Kemajuan Tanah Seri Jaya",
    "gn:country_code":"MY",
    "gn:dem":31,
    "gn:feature_class":"P",
    "gn:feature_code":"PPL",
    "gn:name":"Kemajuan Tanah Seri Jaya",
    "gn:population":0,
    "gn:timezone":"Asia/Kuala_Lumpur",
    "iso:country":"MY",
    "name:msa_x_preferred":[
        "Kemajuan Tanah Seri Jaya"
    ],
    "wof:name":"Kemajuan Tanah Seri Jaya",
    "wof:placetype":"locality"
},
  "geometry": {"coordinates":[102.79179999999999,2.3385],"type":"Point"}
}