{
  "type": "Feature",
  "properties": {
    "gn:admin1_code":"2",
    "gn:asciiname":"Kampung Durian Burong",
    "gn:cc2":"MY",
    "gn:country_code":"MY",
    "gn:dem":59,
    "gn:feature_class":"P",
    "gn:feature_code":"PPL",
    "gn:name":"Kampung Durian Burong",
    "gn:population":0,
    "gn:timezone":"Asia/Kuala_Lumpur",
    "iso:country":"MY",
    "name:msa_x_preferred":[
        "Kampung Durian Burong"
    ],
    "name:und_x_variant":[
        "Kampong Durian Burong"
    ],
    "wof:name":"Kampung Durian Burong",
    "wof:placetype":"locality"
},
  "geometry": {"coordinates":[100.74977,5.86316],"type":"Point"}
}