{
  "type": "Feature",
  "properties": {
    "gn:admin1_code":"1.0",
    "gn:asciiname":"Kangkar Lubok Pekan",
    "gn:country_code":"MY",
    "gn:dem":8,
    "gn:feature_class":"P",
    "gn:feature_code":"PPL",
    "gn:name":"Kangkar Lubok Pekan",
    "gn:population":0,
    "gn:timezone":"Asia/Kuala_Lumpur",
    "iso:country":"MY",
    "name:msa_x_preferred":[
        "Kangkar Lubok Pekan"
    ],
    "wof:name":"Kangkar Lubok Pekan",
    "wof:placetype":"locality"
},
  "geometry": {"coordinates":[103.8086,1.7404],"type":"Point"}
}