{
  "type": "Feature",
  "properties": {
    "gn:admin1_code":"7.0",
    "gn:asciiname":"Taman Mirindu",
    "gn:country_code":"MY",
    "gn:dem":48,
    "gn:feature_class":"P",
    "gn:feature_code":"PPL",
    "gn:name":"Taman Mirindu",
    "gn:population":0,
    "gn:timezone":"Asia/Kuala_Lumpur",
    "iso:country":"MY",
    "name:msa_x_preferred":[
        "Taman Mirindu"
    ],
    "wof:name":"Taman Mirindu",
    "wof:placetype":"locality"
},
  "geometry": {"coordinates":[101.108,4.6245],"type":"Point"}
}