{
  "type": "Feature",
  "properties": {
    "iso:country":"MY",
    "name:eng_x_preferred":[
        "Mutiara Damansara"
    ],
    "name:jpn_x_preferred":[
        "\u30e0\u30c6\u30a3\u30a2\u30e9 \u30c0\u30de\u30f3\u30b5\u30e9"
    ],
    "name:msa_x_preferred":[
        "Mutiara Damansara"
    ],
    "name:zho_x_preferred":[
        "\u73cd\u73e0\u767d\u6c99\u7f85"
    ],
    "qs:gn_adm0_cc":"MY",
    "qs:gn_local":1735158,
    "qs:gn_namadm1":"12",
    "qs:local_max":2115,
    "qs:local_sum":11887,
    "qs:localhoods":21,
    "qs:name":"Mutiara Damansara",
    "qs:name_adm0":"Malaysia",
    "qs:name_adm1":"Selangor",
    "qs:name_adm2":"Petaling",
    "qs:name_lau":"Sungai Buloh",
    "qs:name_local":"Petaling Jaya",
    "qs:photo_max":924,
    "qs:photo_sum":1675,
    "qs:placetype":"Suburb",
    "qs:quad_count":18,
    "qs:woe_adm0":23424901,
    "qs:woe_adm1":2346306,
    "qs:woe_adm2":56013632,
    "qs:woe_lau":56013919,
    "qs:woe_local":1155026,
    "qs:woe_ver":"7.10.0",
    "wd:wordcount":288,
    "wof:lang":[
        "unk"
    ],
    "wof:name":"Mutiara Damansara",
    "wof:placetype":"neighbourhood"
},
  "geometry": {"coordinates":[101.61122899999999,3.158678],"type":"Point"}
}