{
  "type": "Feature",
  "properties": {
    "gn:admin1_code":"9",
    "gn:asciiname":"Kampung Permatang Rambai",
    "gn:cc2":"MY",
    "gn:country_code":"MY",
    "gn:dem":6,
    "gn:feature_class":"P",
    "gn:feature_code":"PPL",
    "gn:name":"Kampung Permatang Rambai",
    "gn:population":0,
    "gn:timezone":"Asia/Kuala_Lumpur",
    "iso:country":"MY",
    "name:msa_x_preferred":[
        "Kampung Permatang Rambai"
    ],
    "name:und_x_variant":[
        "Permatang Rambai",
        "Kampong Permatang Rambai"
    ],
    "wof:name":"Kampung Permatang Rambai",
    "wof:placetype":"locality"
},
  "geometry": {"coordinates":[100.39496,5.53054],"type":"Point"}
}