{
  "type": "Feature",
  "properties": {
    "gn:admin1_code":"16",
    "gn:asciiname":"Kampung Sembulan",
    "gn:country_code":"MY",
    "gn:dem":1,
    "gn:feature_class":"P",
    "gn:feature_code":"PPL",
    "gn:name":"Kampung Sembulan",
    "gn:population":0,
    "gn:timezone":"Asia/Kuching",
    "iso:country":"MY",
    "name:msa_x_preferred":[
        "Kampung Sembulan"
    ],
    "name:und_x_variant":[
        "Sembulan",
        "Kampong Sembulan"
    ],
    "wof:name":"Kampung Sembulan",
    "wof:placetype":"locality"
},
  "geometry": {"coordinates":[116.06529999999999,5.966],"type":"Point"}
}