{
  "type": "Feature",
  "properties": {
    "gn:admin1_code":"7",
    "gn:asciiname":"Kampung Rambai Tujuh",
    "gn:country_code":"MY",
    "gn:dem":44,
    "gn:feature_class":"P",
    "gn:feature_code":"PPL",
    "gn:name":"Kampung Rambai Tujuh",
    "gn:population":0,
    "gn:timezone":"Asia/Kuala_Lumpur",
    "iso:country":"MY",
    "name:msa_x_preferred":[
        "Kampung Rambai Tujuh"
    ],
    "name:und_x_variant":[
        "Kampong Rambai Tujoh"
    ],
    "wof:name":"Kampung Rambai Tujuh",
    "wof:placetype":"locality"
},
  "geometry": {"coordinates":[100.9727,4.6875],"type":"Point"}
}