{
  "type": "Feature",
  "properties": {
    "gn:admin1_code":"1",
    "gn:asciiname":"Kampung Pulau Setindan",
    "gn:country_code":"MY",
    "gn:dem":8,
    "gn:feature_class":"P",
    "gn:feature_code":"PPL",
    "gn:name":"Kampung Pulau Setindan",
    "gn:population":0,
    "gn:timezone":"Asia/Kuala_Lumpur",
    "iso:country":"MY",
    "name:msa_x_preferred":[
        "Kampung Pulau Setindan"
    ],
    "name:und_x_variant":[
        "Kampong Pulau Stindan",
        "Kampong Pulau Setindan"
    ],
    "wof:name":"Kampung Pulau Setindan",
    "wof:placetype":"locality"
},
  "geometry": {"coordinates":[103.8466,2.4784],"type":"Point"}
}