{
  "type": "Feature",
  "properties": {
    "gn:admin1_code":"11",
    "gn:asciiname":"Kampong Entubu",
    "gn:country_code":"MY",
    "gn:dem":103,
    "gn:feature_class":"P",
    "gn:feature_code":"PPL",
    "gn:name":"Kampong Entubu",
    "gn:population":0,
    "gn:timezone":"Asia/Kuching",
    "iso:country":"MY",
    "wof:name":"Kampong Entubu",
    "wof:placetype":"locality"
},
  "geometry": {"coordinates":[110.35763,1.0009],"type":"Point"}
}