{
  "type": "Feature",
  "properties": {
    "gn:admin1_code":"16.0",
    "gn:asciiname":"Kampung Manggis",
    "gn:country_code":"MY",
    "gn:dem":60,
    "gn:feature_class":"P",
    "gn:feature_code":"PPL",
    "gn:name":"Kampung Manggis",
    "gn:population":0,
    "gn:timezone":"Asia/Kuching",
    "iso:country":"MY",
    "name:msa_x_preferred":[
        "Kampung Manggis"
    ],
    "name:msa_x_variant":[
        "Manggis"
    ],
    "wof:name":"Kampung Manggis",
    "wof:placetype":"locality"
},
  "geometry": {"coordinates":[116.0057,5.6949],"type":"Point"}
}