{
  "type": "Feature",
  "properties": {
    "gn:admin1_code":"8.0",
    "gn:asciiname":"Kampung Titi Tampang",
    "gn:country_code":"MY",
    "gn:dem":33,
    "gn:feature_class":"P",
    "gn:feature_code":"PPL",
    "gn:name":"Kampung Titi Tampang",
    "gn:population":0,
    "gn:timezone":"Asia/Kuala_Lumpur",
    "iso:country":"MY",
    "name:msa_x_preferred":[
        "Kampung Titi Tampang"
    ],
    "wof:name":"Kampung Titi Tampang",
    "wof:placetype":"locality"
},
  "geometry": {"coordinates":[100.26727,6.53485],"type":"Point"}
}