{
  "type": "Feature",
  "properties": {
    "gn:admin1_code":"16",
    "gn:asciiname":"Tataluan",
    "gn:country_code":"MY",
    "gn:dem":451,
    "gn:feature_class":"P",
    "gn:feature_code":"PPL",
    "gn:name":"Tataluan",
    "gn:population":0,
    "gn:timezone":"Asia/Kuching",
    "iso:country":"MY",
    "wof:name":"Tataluan",
    "wof:placetype":"locality"
},
  "geometry": {"coordinates":[116.48333,4.88333],"type":"Point"}
}