{
  "type": "Feature",
  "properties": {
    "gn:admin1_code":"6.0",
    "gn:asciiname":"Kampung Lubuk Rakit",
    "gn:country_code":"MY",
    "gn:dem":65,
    "gn:feature_class":"P",
    "gn:feature_code":"PPL",
    "gn:name":"Kampung Lubuk Rakit",
    "gn:population":0,
    "gn:timezone":"Asia/Kuala_Lumpur",
    "iso:country":"MY",
    "name:msa_x_preferred":[
        "Kampung Lubuk Rakit"
    ],
    "wof:name":"Kampung Lubuk Rakit",
    "wof:placetype":"locality"
},
  "geometry": {"coordinates":[102.4419,3.4224],"type":"Point"}
}