{
  "type": "Feature",
  "properties": {
    "gn:admin1_code":"6.0",
    "gn:asciiname":"Kemajuan Tanah Bukit Damar",
    "gn:country_code":"MY",
    "gn:dem":84,
    "gn:feature_class":"P",
    "gn:feature_code":"PPL",
    "gn:name":"Kemajuan Tanah Bukit Damar",
    "gn:population":0,
    "gn:timezone":"Asia/Kuala_Lumpur",
    "iso:country":"MY",
    "name:msa_x_preferred":[
        "Kemajuan Tanah Bukit Damar"
    ],
    "wof:name":"Kemajuan Tanah Bukit Damar",
    "wof:placetype":"locality"
},
  "geometry": {"coordinates":[102.1189,3.5397],"type":"Point"}
}