{
  "type": "Feature",
  "properties": {
    "gn:admin1_code":"6",
    "gn:asciiname":"Kampung Redan",
    "gn:country_code":"MY",
    "gn:dem":79,
    "gn:feature_class":"P",
    "gn:feature_code":"PPL",
    "gn:name":"Kampung Redan",
    "gn:population":0,
    "gn:timezone":"Asia/Kuala_Lumpur",
    "iso:country":"MY",
    "name:msa_x_preferred":[
        "Kampung Redan"
    ],
    "name:und_x_variant":[
        "Kampong Redan"
    ],
    "wof:name":"Kampung Redan",
    "wof:placetype":"locality"
},
  "geometry": {"coordinates":[102.2587,4.0625],"type":"Point"}
}