{
  "type": "Feature",
  "properties": {
    "gn:admin1_code":"16",
    "gn:asciiname":"Kampong Dudar",
    "gn:cc2":"MY",
    "gn:country_code":"MY",
    "gn:dem":1,
    "gn:feature_class":"P",
    "gn:feature_code":"PPL",
    "gn:name":"Kampong Dudar",
    "gn:population":0,
    "gn:timezone":"Asia/Kuching",
    "iso:country":"MY",
    "name:und_x_variant":[
        "Peladok Dudar",
        "Kampong Dudar"
    ],
    "wof:name":"Kampong Dudar",
    "wof:placetype":"locality"
},
  "geometry": {"coordinates":[116.55,6.61667],"type":"Point"}
}