{
  "type": "Feature",
  "properties": {
    "gn:admin1_code":"9",
    "gn:asciiname":"Simpang Empat",
    "gn:cc2":"MY",
    "gn:country_code":"MY",
    "gn:dem":7,
    "gn:feature_class":"P",
    "gn:feature_code":"PPL",
    "gn:name":"Simpang Empat",
    "gn:population":0,
    "gn:timezone":"Asia/Kuala_Lumpur",
    "iso:country":"MY",
    "name:ind_x_preferred":[
        "Simpang Empat"
    ],
    "name:msa_x_preferred":[
        "Simpang Empat"
    ],
    "name:nld_x_preferred":[
        "Simpang Empat"
    ],
    "name:und_x_variant":[
        "Sempang Ampat"
    ],
    "wof:name":"Simpang Empat",
    "wof:placetype":"locality"
},
  "geometry": {"coordinates":[100.42740000000001,5.36573],"type":"Point"}
}