{
  "type": "Feature",
  "properties": {
    "gn:admin1_code":"16",
    "gn:asciiname":"Kampung Kiporing",
    "gn:country_code":"MY",
    "gn:dem":1009,
    "gn:feature_class":"P",
    "gn:feature_code":"PPL",
    "gn:name":"Kampung Kiporing",
    "gn:population":0,
    "gn:timezone":"Asia/Kuching",
    "iso:country":"MY",
    "name:msa_x_preferred":[
        "Kampung Kiporing"
    ],
    "name:und_x_variant":[
        "Kampong Kiporing"
    ],
    "wof:name":"Kampung Kiporing",
    "wof:placetype":"locality"
},
  "geometry": {"coordinates":[116.4872,5.8921],"type":"Point"}
}