{
  "type": "Feature",
  "properties": {
    "gn:admin1_code":"16.0",
    "gn:asciiname":"Kampung Tagun",
    "gn:country_code":"MY",
    "gn:dem":338,
    "gn:feature_class":"P",
    "gn:feature_code":"PPL",
    "gn:name":"Kampung Tagun",
    "gn:population":0,
    "gn:timezone":"Asia/Kuching",
    "iso:country":"MY",
    "name:msa_x_preferred":[
        "Kampung Tagun"
    ],
    "wof:name":"Kampung Tagun",
    "wof:placetype":"locality"
},
  "geometry": {"coordinates":[116.1968,6.0321],"type":"Point"}
}