{
  "type": "Feature",
  "properties": {
    "gn:admin1_code":"9",
    "gn:asciiname":"Kampung Batak",
    "gn:country_code":"MY",
    "gn:dem":13,
    "gn:feature_class":"P",
    "gn:feature_code":"PPL",
    "gn:name":"Kampung Batak",
    "gn:population":0,
    "gn:timezone":"Asia/Kuala_Lumpur",
    "iso:country":"MY",
    "name:und_x_variant":[
        "Kampong Batak",
        "Kampung Batak"
    ],
    "wof:name":"Kampung Batak",
    "wof:placetype":"locality"
},
  "geometry": {"coordinates":[100.27736,5.33596],"type":"Point"}
}