{
  "type": "Feature",
  "properties": {
    "gn:admin1_code":"7.0",
    "gn:asciiname":"Taman Tasek",
    "gn:country_code":"MY",
    "gn:dem":60,
    "gn:feature_class":"P",
    "gn:feature_code":"PPL",
    "gn:name":"Taman Tasek",
    "gn:population":0,
    "gn:timezone":"Asia/Kuala_Lumpur",
    "iso:country":"MY",
    "name:msa_x_preferred":[
        "Taman Tasek"
    ],
    "wof:name":"Taman Tasek",
    "wof:placetype":"locality"
},
  "geometry": {"coordinates":[101.11369999999999,4.648],"type":"Point"}
}