{
  "type": "Feature",
  "properties": {
    "gn:admin1_code":"1.0",
    "gn:asciiname":"Kampung Punggai",
    "gn:country_code":"MY",
    "gn:dem":7,
    "gn:feature_class":"P",
    "gn:feature_code":"PPL",
    "gn:name":"Kampung Punggai",
    "gn:population":0,
    "gn:timezone":"Asia/Kuala_Lumpur",
    "iso:country":"MY",
    "name:msa_x_preferred":[
        "Kampung Punggai"
    ],
    "wof:name":"Kampung Punggai",
    "wof:placetype":"locality"
},
  "geometry": {"coordinates":[104.29170000000001,1.4383],"type":"Point"}
}