{
  "type": "Feature",
  "properties": {
    "gn:admin1_code":"4",
    "gn:asciiname":"Kampung Mantai",
    "gn:country_code":"MY",
    "gn:dem":62,
    "gn:feature_class":"P",
    "gn:feature_code":"PPL",
    "gn:name":"Kampung Mantai",
    "gn:population":0,
    "gn:timezone":"Asia/Kuala_Lumpur",
    "iso:country":"MY",
    "name:msa_x_preferred":[
        "Kampung Mantai"
    ],
    "name:und_x_variant":[
        "Kampong Mantai"
    ],
    "wof:name":"Kampung Mantai",
    "wof:placetype":"locality"
},
  "geometry": {"coordinates":[102.4735,2.439],"type":"Point"}
}