{
  "type": "Feature",
  "properties": {
    "gn:admin1_code":"7.0",
    "gn:asciiname":"Falim",
    "gn:country_code":"MY",
    "gn:dem":42,
    "gn:feature_class":"P",
    "gn:feature_code":"PPL",
    "gn:name":"Falim",
    "gn:population":0,
    "gn:timezone":"Asia/Kuala_Lumpur",
    "iso:country":"MY",
    "name:msa_x_preferred":[
        "Falim"
    ],
    "wof:name":"Falim",
    "wof:placetype":"locality"
},
  "geometry": {"coordinates":[101.0647,4.5821],"type":"Point"}
}