{
  "type": "Feature",
  "properties": {
    "gn:country":"MY",
    "gn:fcode":"PPL",
    "gn:population":0,
    "iso:country":"MY",
    "name:msa_x_preferred":[
        "Kampung Lama"
    ],
    "name:und_x_variant":[
        "Kampong Lama"
    ],
    "qs:name":"Kampung Aman",
    "qs:name_adm0":"Malaysia",
    "qs:name_adm1":"Johor",
    "qs:photos":45,
    "qs:photos_1k":9,
    "qs:photos_9k":1,
    "qs:photos_9r":2,
    "qs:photos_all":45,
    "qs:photos_sr":2,
    "qs:placetype":"Suburb",
    "qs:pop_sr":"0",
    "wof:name":"Kampung Aman",
    "wof:placetype":"neighbourhood",
    "wof:population":0
},
  "geometry": {"coordinates":[104.07599999999999,2.2118],"type":"Point"}
}