{
  "type": "Feature",
  "properties": {
    "gn:admin1_code":"2",
    "gn:asciiname":"Kampung Bukit",
    "gn:cc2":"MY",
    "gn:country_code":"MY",
    "gn:dem":65,
    "gn:feature_class":"P",
    "gn:feature_code":"PPL",
    "gn:name":"Kampung Bukit",
    "gn:population":0,
    "gn:timezone":"Asia/Kuala_Lumpur",
    "iso:country":"MY",
    "name:msa_x_preferred":[
        "Kampung Bukit"
    ],
    "name:und_x_variant":[
        "Kampong Bukik",
        "Kampong Bukit"
    ],
    "wof:name":"Kampung Bukit",
    "wof:placetype":"locality"
},
  "geometry": {"coordinates":[100.78137,5.83998],"type":"Point"}
}