{
  "type": "Feature",
  "properties": {
    "gn:admin1_code":"11",
    "gn:asciiname":"Kampong Mang",
    "gn:country_code":"MY",
    "gn:dem":8,
    "gn:feature_class":"P",
    "gn:feature_code":"PPL",
    "gn:name":"Kampong Mang",
    "gn:population":0,
    "gn:timezone":"Asia/Kuching",
    "iso:country":"MY",
    "wof:name":"Kampong Mang",
    "wof:placetype":"locality"
},
  "geometry": {"coordinates":[110.53333000000001,1.36667],"type":"Point"}
}