{
  "type": "Feature",
  "properties": {
    "gn:admin1_code":"6.0",
    "gn:asciiname":"Kampung Felda Tersang Dua",
    "gn:country_code":"MY",
    "gn:dem":139,
    "gn:feature_class":"P",
    "gn:feature_code":"PPL",
    "gn:name":"Kampung Felda Tersang Dua",
    "gn:population":0,
    "gn:timezone":"Asia/Kuala_Lumpur",
    "iso:country":"MY",
    "name:msa_x_preferred":[
        "Kampung Felda Tersang Dua"
    ],
    "wof:name":"Kampung Felda Tersang Dua",
    "wof:placetype":"locality"
},
  "geometry": {"coordinates":[101.8002,4.0641],"type":"Point"}
}