{
  "type": "Feature",
  "properties": {
    "gn:admin1_code":"1.0",
    "gn:asciiname":"Kemajuan Tanah Kampung Padang",
    "gn:country_code":"MY",
    "gn:dem":10,
    "gn:feature_class":"P",
    "gn:feature_code":"PPL",
    "gn:name":"Kemajuan Tanah Kampung Padang",
    "gn:population":0,
    "gn:timezone":"Asia/Kuala_Lumpur",
    "iso:country":"MY",
    "name:msa_x_preferred":[
        "Kemajuan Tanah Kampung Padang"
    ],
    "wof:name":"Kemajuan Tanah Kampung Padang",
    "wof:placetype":"locality"
},
  "geometry": {"coordinates":[104.0705,1.9198],"type":"Point"}
}