{
  "type": "Feature",
  "properties": {
    "gn:admin1_code":"16.0",
    "gn:asciiname":"Kampung Tanid",
    "gn:country_code":"MY",
    "gn:dem":113,
    "gn:feature_class":"P",
    "gn:feature_code":"PPL",
    "gn:name":"Kampung Tanid",
    "gn:population":0,
    "gn:timezone":"Asia/Kuching",
    "iso:country":"MY",
    "name:msa_x_preferred":[
        "Kampung Tanid"
    ],
    "wof:name":"Kampung Tanid",
    "wof:placetype":"locality"
},
  "geometry": {"coordinates":[116.926,6.1677],"type":"Point"}
}