{
  "type": "Feature",
  "properties": {
    "gn:admin1_code":"1",
    "gn:asciiname":"Kampung Teluk Penchu",
    "gn:country_code":"MY",
    "gn:dem":12,
    "gn:feature_class":"P",
    "gn:feature_code":"PPL",
    "gn:name":"Kampung Teluk Penchu",
    "gn:population":0,
    "gn:timezone":"Asia/Kuala_Lumpur",
    "iso:country":"MY",
    "name:msa_x_preferred":[
        "Kampung Teluk Penchu"
    ],
    "name:und_x_variant":[
        "Kampong Telok Penchu"
    ],
    "wof:name":"Kampung Teluk Penchu",
    "wof:placetype":"locality"
},
  "geometry": {"coordinates":[102.8069,2.2418],"type":"Point"}
}