{
  "type": "Feature",
  "properties": {
    "gn:admin1_code":"11",
    "gn:asciiname":"Rumah Nyambong",
    "gn:country_code":"MY",
    "gn:dem":148,
    "gn:feature_class":"P",
    "gn:feature_code":"PPL",
    "gn:name":"Rumah Nyambong",
    "gn:population":0,
    "gn:timezone":"Asia/Kuching",
    "iso:country":"MY",
    "wof:name":"Rumah Nyambong",
    "wof:placetype":"locality"
},
  "geometry": {"coordinates":[113.51667,2.18333],"type":"Point"}
}