{
  "type": "Feature",
  "properties": {
    "gn:admin1_code":"2",
    "gn:asciiname":"Kampung Whatt Dalam",
    "gn:country_code":"MY",
    "gn:dem":44,
    "gn:feature_class":"P",
    "gn:feature_code":"PPL",
    "gn:name":"Kampung Whatt Dalam",
    "gn:population":0,
    "gn:timezone":"Asia/Kuala_Lumpur",
    "iso:country":"MY",
    "name:msa_x_preferred":[
        "Kampung Whatt Dalam"
    ],
    "name:und_x_variant":[
        "Kampong Watt Dalam",
        "Kampong Whatt Dalam"
    ],
    "wof:name":"Kampung Whatt Dalam",
    "wof:placetype":"locality"
},
  "geometry": {"coordinates":[100.61492,6.01776],"type":"Point"}
}