{
  "type": "Feature",
  "properties": {
    "gn:admin1_code":"7",
    "gn:asciiname":"Kampung Jalan Kereta Api",
    "gn:cc2":"MY",
    "gn:country_code":"MY",
    "gn:dem":2,
    "gn:feature_class":"P",
    "gn:feature_code":"PPL",
    "gn:name":"Kampung Jalan Kereta Api",
    "gn:population":0,
    "gn:timezone":"Asia/Kuala_Lumpur",
    "iso:country":"MY",
    "name:msa_x_preferred":[
        "Kampung Jalan Kereta Api"
    ],
    "name:und_x_variant":[
        "Kampong Jalan Kereta Api"
    ],
    "wof:name":"Kampung Jalan Kereta Api",
    "wof:placetype":"locality"
},
  "geometry": {"coordinates":[100.61516,5.04117],"type":"Point"}
}