{
  "type": "Feature",
  "properties": {
    "gn:admin1_code":"9",
    "gn:asciiname":"Kampung Tanjung Berembang",
    "gn:country_code":"MY",
    "gn:dem":12,
    "gn:feature_class":"P",
    "gn:feature_code":"PPL",
    "gn:name":"Kampung Tanjung Berembang",
    "gn:population":0,
    "gn:timezone":"Asia/Kuala_Lumpur",
    "iso:country":"MY",
    "name:msa_x_preferred":[
        "Kampung Tanjung Berembang"
    ],
    "name:und_x_variant":[
        "Tanjong Berembang"
    ],
    "wof:name":"Kampung Tanjung Berembang",
    "wof:placetype":"locality"
},
  "geometry": {"coordinates":[100.46626999999999,5.15194],"type":"Point"}
}