{
  "type": "Feature",
  "properties": {
    "gn:admin1_code":"11",
    "gn:asciiname":"Kampong Gahat",
    "gn:country_code":"MY",
    "gn:dem":515,
    "gn:feature_class":"P",
    "gn:feature_code":"PPL",
    "gn:name":"Kampong Gahat",
    "gn:population":0,
    "gn:timezone":"Asia/Kuching",
    "iso:country":"MY",
    "wof:name":"Kampong Gahat",
    "wof:placetype":"locality"
},
  "geometry": {"coordinates":[110.46594,0.99009],"type":"Point"}
}