{
  "type": "Feature",
  "properties": {
    "gn:admin1_code":"11",
    "gn:asciiname":"Rumah Lalut",
    "gn:country_code":"MY",
    "gn:dem":159,
    "gn:feature_class":"P",
    "gn:feature_code":"PPL",
    "gn:name":"Rumah Lalut",
    "gn:population":0,
    "gn:timezone":"Asia/Kuching",
    "iso:country":"MY",
    "wof:name":"Rumah Lalut",
    "wof:placetype":"locality"
},
  "geometry": {"coordinates":[113.38333,1.81667],"type":"Point"}
}