{
  "type": "Feature",
  "properties": {
    "gn:admin1_code":"5",
    "gn:asciiname":"Sungai Salak",
    "gn:country_code":"MY",
    "gn:dem":55,
    "gn:feature_class":"P",
    "gn:feature_code":"PPL",
    "gn:name":"Sungai Salak",
    "gn:population":0,
    "gn:timezone":"Asia/Kuala_Lumpur",
    "iso:country":"MY",
    "name:msa_x_preferred":[
        "Sungai Salak"
    ],
    "wof:name":"Sungai Salak",
    "wof:placetype":"locality"
},
  "geometry": {"coordinates":[101.8792,2.5664],"type":"Point"}
}