{
  "type": "Feature",
  "properties": {
    "gn:admin1_code":"6",
    "gn:asciiname":"Kampung Kempas",
    "gn:country_code":"MY",
    "gn:dem":43,
    "gn:feature_class":"P",
    "gn:feature_code":"PPL",
    "gn:name":"Kampung Kempas",
    "gn:population":0,
    "gn:timezone":"Asia/Kuala_Lumpur",
    "iso:country":"MY",
    "name:msa_x_preferred":[
        "Kampung Kempas"
    ],
    "name:und_x_variant":[
        "Kampong Kempas"
    ],
    "wof:name":"Kampung Kempas",
    "wof:placetype":"locality"
},
  "geometry": {"coordinates":[102.4096,3.4393],"type":"Point"}
}