{
  "type": "Feature",
  "properties": {
    "gn:admin1_code":"1.0",
    "gn:asciiname":"Taman Seri Mersing",
    "gn:country_code":"MY",
    "gn:dem":29,
    "gn:feature_class":"P",
    "gn:feature_code":"PPL",
    "gn:name":"Taman Seri Mersing",
    "gn:population":0,
    "gn:timezone":"Asia/Kuala_Lumpur",
    "iso:country":"MY",
    "name:msa_x_preferred":[
        "Taman Seri Mersing"
    ],
    "wof:name":"Taman Seri Mersing",
    "wof:placetype":"locality"
},
  "geometry": {"coordinates":[103.85333,2.4164],"type":"Point"}
}