{
  "type": "Feature",
  "properties": {
    "gn:admin1_code":"1.0",
    "gn:asciiname":"Kampung Seri Rawa",
    "gn:country_code":"MY",
    "gn:dem":44,
    "gn:feature_class":"P",
    "gn:feature_code":"PPL",
    "gn:name":"Kampung Seri Rawa",
    "gn:population":0,
    "gn:timezone":"Asia/Kuala_Lumpur",
    "iso:country":"MY",
    "name:msa_x_preferred":[
        "Kampung Seri Rawa"
    ],
    "wof:name":"Kampung Seri Rawa",
    "wof:placetype":"locality"
},
  "geometry": {"coordinates":[102.7253,2.767],"type":"Point"}
}