{
  "type": "Feature",
  "properties": {
    "gn:admin1_code":"9",
    "gn:asciiname":"Kampung Sungai Semambu",
    "gn:cc2":"MY",
    "gn:country_code":"MY",
    "gn:dem":12,
    "gn:feature_class":"P",
    "gn:feature_code":"PPL",
    "gn:name":"Kampung Sungai Semambu",
    "gn:population":0,
    "gn:timezone":"Asia/Kuala_Lumpur",
    "iso:country":"MY",
    "name:msa_x_preferred":[
        "Kampung Sungai Semambu"
    ],
    "name:und_x_variant":[
        "Kampong Sungai Semambu"
    ],
    "wof:name":"Kampung Sungai Semambu",
    "wof:placetype":"locality"
},
  "geometry": {"coordinates":[100.46254999999999,5.39417],"type":"Point"}
}