{
  "type": "Feature",
  "properties": {
    "gn:admin1_code":"9",
    "gn:asciiname":"Kampung Sungai Malau Dalam",
    "gn:cc2":"MY",
    "gn:country_code":"MY",
    "gn:dem":17,
    "gn:feature_class":"P",
    "gn:feature_code":"PPL",
    "gn:name":"Kampung Sungai Malau Dalam",
    "gn:population":0,
    "gn:timezone":"Asia/Kuala_Lumpur",
    "iso:country":"MY",
    "name:msa_x_preferred":[
        "Kampung Sungai Malau Dalam"
    ],
    "name:und_x_variant":[
        "Kampong Sungai Marlow"
    ],
    "wof:name":"Kampung Sungai Malau Dalam",
    "wof:placetype":"locality"
},
  "geometry": {"coordinates":[100.66884,5.13719],"type":"Point"}
}