{
  "type": "Feature",
  "properties": {
    "gn:admin1_code":"6",
    "gn:asciiname":"Kampung Sungai Pasu",
    "gn:country_code":"MY",
    "gn:dem":114,
    "gn:feature_class":"P",
    "gn:feature_code":"PPL",
    "gn:name":"Kampung Sungai Pasu",
    "gn:population":0,
    "gn:timezone":"Asia/Kuala_Lumpur",
    "iso:country":"MY",
    "name:msa_x_preferred":[
        "Kampung Sungai Pasu"
    ],
    "name:und_x_variant":[
        "Kampong Sungai Pasu"
    ],
    "wof:name":"Kampung Sungai Pasu",
    "wof:placetype":"locality"
},
  "geometry": {"coordinates":[101.8907,3.8776],"type":"Point"}
}