{
  "type": "Feature",
  "properties": {
    "gn:admin1_code":"11.0",
    "gn:asciiname":"Sungai Pisang",
    "gn:country_code":"MY",
    "gn:dem":9,
    "gn:feature_class":"P",
    "gn:feature_code":"PPL",
    "gn:name":"Sungai Pisang",
    "gn:population":0,
    "gn:timezone":"Asia/Kuching",
    "iso:country":"MY",
    "wof:name":"Sungai Pisang",
    "wof:placetype":"locality"
},
  "geometry": {"coordinates":[111.15000000000001,1.36667],"type":"Point"}
}