{
  "type": "Feature",
  "properties": {
    "gn:admin1_code":"11",
    "gn:asciiname":"Rumah Kilat",
    "gn:country_code":"MY",
    "gn:dem":63,
    "gn:feature_class":"P",
    "gn:feature_code":"PPL",
    "gn:name":"Rumah Kilat",
    "gn:population":0,
    "gn:timezone":"Asia/Kuching",
    "iso:country":"MY",
    "wof:name":"Rumah Kilat",
    "wof:placetype":"locality"
},
  "geometry": {"coordinates":[113.05,2.01667],"type":"Point"}
}