{
  "type": "Feature",
  "properties": {
    "gn:admin1_code":"4.0",
    "gn:asciiname":"Kampung Duyong",
    "gn:country_code":"MY",
    "gn:dem":9,
    "gn:feature_class":"P",
    "gn:feature_code":"PPL",
    "gn:name":"Kampung Duyong",
    "gn:population":0,
    "gn:timezone":"Asia/Kuala_Lumpur",
    "iso:country":"MY",
    "name:msa_x_preferred":[
        "Kampung Duyong"
    ],
    "wof:name":"Kampung Duyong",
    "wof:placetype":"locality"
},
  "geometry": {"coordinates":[102.29170000000001,2.2014],"type":"Point"}
}