{
  "type": "Feature",
  "properties": {
    "gn:admin1_code":"13",
    "gn:asciiname":"Kampung Dusun",
    "gn:country_code":"MY",
    "gn:dem":23,
    "gn:feature_class":"P",
    "gn:feature_code":"PPL",
    "gn:name":"Kampung Dusun",
    "gn:population":0,
    "gn:timezone":"Asia/Kuala_Lumpur",
    "iso:country":"MY",
    "name:msa_x_preferred":[
        "Kampung Dusun"
    ],
    "name:und_x_variant":[
        "Kampong Dusun"
    ],
    "wof:name":"Kampung Dusun",
    "wof:placetype":"locality"
},
  "geometry": {"coordinates":[102.9512,5.0732],"type":"Point"}
}