{
  "type": "Feature",
  "properties": {
    "gn:admin1_code":"11",
    "gn:asciiname":"Rumah Dampa",
    "gn:country_code":"MY",
    "gn:dem":128,
    "gn:feature_class":"P",
    "gn:feature_code":"PPL",
    "gn:name":"Rumah Dampa",
    "gn:population":0,
    "gn:timezone":"Asia/Kuching",
    "iso:country":"MY",
    "wof:name":"Rumah Dampa",
    "wof:placetype":"locality"
},
  "geometry": {"coordinates":[113.75,1.81667],"type":"Point"}
}