{
  "type": "Feature",
  "properties": {
    "gn:admin1_code":"12.0",
    "gn:asciiname":"Bagan Sungai Tengar Kechil",
    "gn:country_code":"MY",
    "gn:dem":0,
    "gn:feature_class":"P",
    "gn:feature_code":"PPL",
    "gn:name":"Bagan Sungai Tengar Kechil",
    "gn:population":0,
    "gn:timezone":"Asia/Kuala_Lumpur",
    "iso:country":"MY",
    "name:msa_x_preferred":[
        "Bagan Sungai Tengar Kechil"
    ],
    "wof:name":"Bagan Sungai Tengar Kechil",
    "wof:placetype":"locality"
},
  "geometry": {"coordinates":[100.87050000000001,3.8511],"type":"Point"}
}