{
  "type": "Feature",
  "properties": {
    "iso:country":"MY",
    "qs:name":"Kampong Jawa",
    "qs:name_adm0":"Malaysia",
    "qs:name_adm1":"Johor",
    "qs:photos":199,
    "qs:photos_1k":40,
    "qs:photos_9k":1,
    "qs:photos_9r":4,
    "qs:photos_all":199,
    "qs:photos_sr":4,
    "qs:placetype":"Suburb",
    "qs:pop_sr":"0",
    "wof:name":"Kampong Jawa",
    "wof:placetype":"neighbourhood"
},
  "geometry": {"coordinates":[103.758172,1.474923],"type":"Point"}
}