{
  "type": "Feature",
  "properties": {
    "gn:admin1_code":"16.0",
    "gn:asciiname":"Kampung Bandukan Lama",
    "gn:country_code":"MY",
    "gn:dem":410,
    "gn:feature_class":"P",
    "gn:feature_code":"PPL",
    "gn:name":"Kampung Bandukan Lama",
    "gn:population":0,
    "gn:timezone":"Asia/Kuching",
    "iso:country":"MY",
    "name:msa_x_preferred":[
        "Kampung Bandukan Lama"
    ],
    "wof:name":"Kampung Bandukan Lama",
    "wof:placetype":"locality"
},
  "geometry": {"coordinates":[116.1649,5.4431],"type":"Point"}
}