{
  "type": "Feature",
  "properties": {
    "gn:admin1_code":"13.0",
    "gn:asciiname":"Kongsi Ladang Tebak",
    "gn:country_code":"MY",
    "gn:dem":39,
    "gn:feature_class":"P",
    "gn:feature_code":"PPL",
    "gn:name":"Kongsi Ladang Tebak",
    "gn:population":0,
    "gn:timezone":"Asia/Kuala_Lumpur",
    "iso:country":"MY",
    "name:msa_x_preferred":[
        "Kongsi Ladang Tebak"
    ],
    "wof:name":"Kongsi Ladang Tebak",
    "wof:placetype":"locality"
},
  "geometry": {"coordinates":[103.2286,4.4302],"type":"Point"}
}