{
  "type": "Feature",
  "properties": {
    "gn:admin1_code":"0.0",
    "gn:asciiname":"Kampung Batu Luar",
    "gn:country_code":"MY",
    "gn:dem":98,
    "gn:feature_class":"P",
    "gn:feature_code":"PPL",
    "gn:name":"Kampung Batu Luar",
    "gn:population":0,
    "gn:timezone":"Asia/Kuala_Lumpur",
    "iso:country":"MY",
    "wof:name":"Kampung Batu Luar",
    "wof:placetype":"locality"
},
  "geometry": {"coordinates":[102.01667,4.23333],"type":"Point"}
}