{
  "type": "Feature",
  "properties": {
    "gn:admin1_code":"7",
    "gn:asciiname":"Kampung Tebok Raja Semalon",
    "gn:country_code":"MY",
    "gn:dem":8,
    "gn:feature_class":"P",
    "gn:feature_code":"PPL",
    "gn:name":"Kampung Tebok Raja Semalon",
    "gn:population":0,
    "gn:timezone":"Asia/Kuala_Lumpur",
    "iso:country":"MY",
    "name:msa_x_preferred":[
        "Kampung Tebok Raja Semalon"
    ],
    "name:und_x_variant":[
        "Kampong Tebok Raja Semalon"
    ],
    "wof:name":"Kampung Tebok Raja Semalon",
    "wof:placetype":"locality"
},
  "geometry": {"coordinates":[100.6878,4.2676],"type":"Point"}
}