{
  "type": "Feature",
  "properties": {
    "gn:admin1_code":"13.0",
    "gn:asciiname":"Kampung Tanjung Ketung",
    "gn:country_code":"MY",
    "gn:dem":20,
    "gn:feature_class":"P",
    "gn:feature_code":"PPL",
    "gn:name":"Kampung Tanjung Ketung",
    "gn:population":0,
    "gn:timezone":"Asia/Kuala_Lumpur",
    "iso:country":"MY",
    "name:msa_x_preferred":[
        "Kampung Tanjung Ketung"
    ],
    "wof:name":"Kampung Tanjung Ketung",
    "wof:placetype":"locality"
},
  "geometry": {"coordinates":[103.0378,5.2465],"type":"Point"}
}