{
  "type": "Feature",
  "properties": {
    "gn:admin1_code":"9.0",
    "gn:asciiname":"Kampung Masjid Timah",
    "gn:country_code":"MY",
    "gn:dem":5,
    "gn:feature_class":"P",
    "gn:feature_code":"PPL",
    "gn:name":"Kampung Masjid Timah",
    "gn:population":0,
    "gn:timezone":"Asia/Kuala_Lumpur",
    "iso:country":"MY",
    "name:msa_x_preferred":[
        "Kampung Masjid Timah"
    ],
    "wof:name":"Kampung Masjid Timah",
    "wof:placetype":"locality"
},
  "geometry": {"coordinates":[100.41086,5.3817],"type":"Point"}
}