{
  "type": "Feature",
  "properties": {
    "gn:admin1_code":"16",
    "gn:asciiname":"Kampung Nosob",
    "gn:country_code":"MY",
    "gn:dem":11,
    "gn:feature_class":"P",
    "gn:feature_code":"PPL",
    "gn:name":"Kampung Nosob",
    "gn:population":0,
    "gn:timezone":"Asia/Kuching",
    "iso:country":"MY",
    "name:msa_x_preferred":[
        "Kampung Nosob"
    ],
    "name:und_x_variant":[
        "Nosob",
        "Kampong Nosob"
    ],
    "wof:name":"Kampung Nosob",
    "wof:placetype":"locality"
},
  "geometry": {"coordinates":[116.08320000000001,5.9233],"type":"Point"}
}