{
  "type": "Feature",
  "properties": {
    "gn:admin1_code":"4",
    "gn:asciiname":"Solok Minyak",
    "gn:country_code":"MY",
    "gn:dem":8,
    "gn:feature_class":"P",
    "gn:feature_code":"PPL",
    "gn:name":"Solok Minyak",
    "gn:population":0,
    "gn:timezone":"Asia/Kuala_Lumpur",
    "iso:country":"MY",
    "name:msa_x_preferred":[
        "Solok Minyak"
    ],
    "name:und_x_variant":[
        "Kampong Minyak",
        "Solok Minyak"
    ],
    "wof:name":"Solok Minyak",
    "wof:placetype":"locality"
},
  "geometry": {"coordinates":[102.3558,2.1483],"type":"Point"}
}