{
  "type": "Feature",
  "properties": {
    "gn:admin1_code":"1",
    "gn:asciiname":"Kampung Sungai Buntu",
    "gn:country_code":"MY",
    "gn:dem":5,
    "gn:feature_class":"P",
    "gn:feature_code":"PPL",
    "gn:name":"Kampung Sungai Buntu",
    "gn:population":0,
    "gn:timezone":"Asia/Kuala_Lumpur",
    "iso:country":"MY",
    "name:msa_x_preferred":[
        "Kampung Sungai Buntu"
    ],
    "name:und_x_variant":[
        "Kampong Sungai Buntu"
    ],
    "wof:name":"Kampung Sungai Buntu",
    "wof:placetype":"locality"
},
  "geometry": {"coordinates":[104.1998,1.3404],"type":"Point"}
}