{
  "type": "Feature",
  "properties": {
    "gn:admin1_code":"16.0",
    "gn:asciiname":"Kampung Bilit",
    "gn:country_code":"MY",
    "gn:dem":5,
    "gn:feature_class":"P",
    "gn:feature_code":"PPL",
    "gn:name":"Kampung Bilit",
    "gn:population":0,
    "gn:timezone":"Asia/Kuching",
    "iso:country":"MY",
    "name:msa_x_preferred":[
        "Kampung Bilit"
    ],
    "name:und_x_variant":[
        "Bilit"
    ],
    "wof:name":"Kampung Bilit",
    "wof:placetype":"locality"
},
  "geometry": {"coordinates":[118.2062,5.4957],"type":"Point"}
}