{
  "type": "Feature",
  "properties": {
    "gn:country":"MY",
    "gn:fcode":"PPL",
    "gn:population":0,
    "iso:country":"MY",
    "name:eng_x_preferred":[
        "Mambau"
    ],
    "name:epo_x_preferred":[
        "Mambau"
    ],
    "name:msa_x_preferred":[
        "Kampung Mambau"
    ],
    "name:msa_x_variant":[
        "Mambau"
    ],
    "name:nld_x_preferred":[
        "Mambau"
    ],
    "qs_pg:aaroncc":"MY",
    "qs_pg:gn_country":"MY",
    "qs_pg:gn_fcode":"PPL",
    "qs_pg:gn_pop":0,
    "qs_pg:name":"Kampong Mambau",
    "qs_pg:name_adm0":"Malaysia",
    "qs_pg:name_adm1":"Negeri Sembilan",
    "qs_pg:photos_9r":0,
    "qs_pg:photos_sr":0,
    "qs_pg:pop_sr":0,
    "qs_pg:qs_pg_placetype":"locality",
    "qs_pg:qs_pg_placetype_gp":"Town",
    "qs_pg:woe_adm0":23424901,
    "woe:adm0_id":23424901,
    "woe:name_adm0":"Malaysia",
    "woe:name_adm1":"Negeri Sembilan",
    "woe:placetype":"Town",
    "wof:name":"Kampong Mambau",
    "wof:placetype":"locality"
},
  "geometry": {"coordinates":[101.9149,2.663],"type":"Point"}
}