{
  "type": "Feature",
  "properties": {
    "gn:admin1_code":"12",
    "gn:asciiname":"Simpang Sungai Choh",
    "gn:country_code":"MY",
    "gn:dem":43,
    "gn:feature_class":"P",
    "gn:feature_code":"PPL",
    "gn:name":"Simpang Sungai Choh",
    "gn:population":0,
    "gn:timezone":"Asia/Kuala_Lumpur",
    "iso:country":"MY",
    "name:msa_x_preferred":[
        "Simpang Sungai Choh"
    ],
    "wof:name":"Simpang Sungai Choh",
    "wof:placetype":"locality"
},
  "geometry": {"coordinates":[101.59269999999999,3.3451],"type":"Point"}
}