{
  "type": "Feature",
  "properties": {
    "gn:admin1_code":"13.0",
    "gn:asciiname":"Kampung Paya Rawa",
    "gn:cc2":"MY",
    "gn:country_code":"MY",
    "gn:dem":5,
    "gn:feature_class":"P",
    "gn:feature_code":"PPL",
    "gn:name":"Kampung Paya Rawa",
    "gn:population":0,
    "gn:timezone":"Asia/Kuala_Lumpur",
    "iso:country":"MY",
    "name:msa_x_preferred":[
        "Kampung Paya Rawa"
    ],
    "wof:name":"Kampung Paya Rawa",
    "wof:placetype":"locality"
},
  "geometry": {"coordinates":[102.58616000000001,5.78177],"type":"Point"}
}