{
  "type": "Feature",
  "properties": {
    "gn:admin1_code":"5",
    "gn:asciiname":"Kampung Dusun Kubor",
    "gn:country_code":"MY",
    "gn:dem":189,
    "gn:feature_class":"P",
    "gn:feature_code":"PPL",
    "gn:name":"Kampung Dusun Kubor",
    "gn:population":0,
    "gn:timezone":"Asia/Kuala_Lumpur",
    "iso:country":"MY",
    "name:und_x_variant":[
        "Kampong Dusun Kubur",
        "Kampong Dusun Kubor",
        "Kampung Dusun Kubor"
    ],
    "wof:name":"Kampung Dusun Kubor",
    "wof:placetype":"locality"
},
  "geometry": {"coordinates":[102.07472,3.09769],"type":"Point"}
}