{
  "type": "Feature",
  "properties": {
    "gn:admin1_code":"6.0",
    "gn:asciiname":"Bandar Baru Peramu Jaya",
    "gn:country_code":"MY",
    "gn:dem":9,
    "gn:feature_class":"P",
    "gn:feature_code":"PPL",
    "gn:name":"Bandar Baru Peramu Jaya",
    "gn:population":0,
    "gn:timezone":"Asia/Kuala_Lumpur",
    "iso:country":"MY",
    "name:msa_x_preferred":[
        "Bandar Baru Peramu Jaya"
    ],
    "wof:name":"Bandar Baru Peramu Jaya",
    "wof:placetype":"locality"
},
  "geometry": {"coordinates":[103.38330000000001,3.5404],"type":"Point"}
}