{
  "type": "Feature",
  "properties": {
    "gn:admin1_code":"16",
    "gn:asciiname":"Kampong Siladan",
    "gn:cc2":"MY",
    "gn:country_code":"MY",
    "gn:dem":23,
    "gn:feature_class":"P",
    "gn:feature_code":"PPL",
    "gn:name":"Kampong Siladan",
    "gn:population":0,
    "gn:timezone":"Asia/Kuching",
    "iso:country":"MY",
    "name:und_x_variant":[
        "Saladan",
        "Kampong Siladan"
    ],
    "wof:name":"Kampong Siladan",
    "wof:placetype":"locality"
},
  "geometry": {"coordinates":[115.84999999999999,5.53333],"type":"Point"}
}