{
  "type": "Feature",
  "properties": {
    "gn:admin1_code":"11.0",
    "gn:asciiname":"Kampung Sungai Merapok",
    "gn:country_code":"MY",
    "gn:dem":29,
    "gn:feature_class":"P",
    "gn:feature_code":"PPL",
    "gn:name":"Kampung Sungai Merapok",
    "gn:population":0,
    "gn:timezone":"Asia/Kuching",
    "iso:country":"MY",
    "name:msa_x_preferred":[
        "Kampung Sungai Merapok"
    ],
    "wof:name":"Kampung Sungai Merapok",
    "wof:placetype":"locality"
},
  "geometry": {"coordinates":[115.5864,4.9725],"type":"Point"}
}