{
  "type": "Feature",
  "properties": {
    "gn:admin1_code":"1.0",
    "gn:asciiname":"Bukit Setajam",
    "gn:country_code":"MY",
    "gn:dem":14,
    "gn:feature_class":"P",
    "gn:feature_code":"PPL",
    "gn:name":"Bukit Setajam",
    "gn:population":0,
    "gn:timezone":"Asia/Kuala_Lumpur",
    "iso:country":"MY",
    "name:msa_x_preferred":[
        "Bukit Setajam"
    ],
    "wof:name":"Bukit Setajam",
    "wof:placetype":"locality"
},
  "geometry": {"coordinates":[104.29349999999999,1.4449],"type":"Point"}
}