{
  "type": "Feature",
  "properties": {
    "gn:admin1_code":"2.0",
    "gn:asciiname":"Kampung Buloh Lima Dalam",
    "gn:country_code":"MY",
    "gn:dem":4,
    "gn:feature_class":"P",
    "gn:feature_code":"PPL",
    "gn:name":"Kampung Buloh Lima Dalam",
    "gn:population":0,
    "gn:timezone":"Asia/Kuala_Lumpur",
    "iso:country":"MY",
    "name:msa_x_preferred":[
        "Kampung Buloh Lima Dalam"
    ],
    "wof:name":"Kampung Buloh Lima Dalam",
    "wof:placetype":"locality"
},
  "geometry": {"coordinates":[100.40367000000001,5.99242],"type":"Point"}
}