{
  "type": "Feature",
  "properties": {
    "gn:admin1_code":"13",
    "gn:asciiname":"Kampung Gong Gemia",
    "gn:country_code":"MY",
    "gn:dem":12,
    "gn:feature_class":"P",
    "gn:feature_code":"PPL",
    "gn:name":"Kampung Gong Gemia",
    "gn:population":0,
    "gn:timezone":"Asia/Kuala_Lumpur",
    "iso:country":"MY",
    "name:msa_x_preferred":[
        "Kampung Gong Gemia"
    ],
    "name:und_x_variant":[
        "Kampong Gong Gemia"
    ],
    "wof:name":"Kampung Gong Gemia",
    "wof:placetype":"locality"
},
  "geometry": {"coordinates":[103.43389999999999,4.6306],"type":"Point"}
}