{
  "type": "Feature",
  "properties": {
    "iso:country":"MY",
    "name:und_x_variant":[
        "Taman Dagang"
    ],
    "qs:gn_fcode":"PPL",
    "qs:gn_local":0,
    "qs:gn_namadm1":"12",
    "qs:gn_name":"Taman Dagang Jaya",
    "qs:local_max":1600,
    "qs:local_sum":2828,
    "qs:localhoods":16,
    "qs:name":"Taman Dagang",
    "qs:name_adm0":"Malaysia",
    "qs:name_adm1":"Selangor",
    "qs:name_adm2":"Hulu Langat",
    "qs:name_lau":"Ampang",
    "qs:name_local":"Pekan Ampang",
    "qs:photo_max":9,
    "qs:photo_sum":15,
    "qs:placetype":"Suburb",
    "qs:quad_count":5,
    "qs:woe_adm0":23424901,
    "qs:woe_adm1":2346306,
    "qs:woe_adm2":56013645,
    "qs:woe_lau":56013982,
    "qs:woe_local":1140655,
    "qs:woe_ver":"7.10.0",
    "wof:lang":[
        "unk"
    ],
    "wof:name":"Taman Dagang",
    "wof:placetype":"neighbourhood"
},
  "geometry": {"coordinates":[101.77862500000001,3.132654],"type":"Point"}
}