{
  "type": "Feature",
  "properties": {
    "gn:admin1_code":"13",
    "gn:asciiname":"Kampung Tok Lawit",
    "gn:country_code":"MY",
    "gn:dem":28,
    "gn:feature_class":"P",
    "gn:feature_code":"PPL",
    "gn:name":"Kampung Tok Lawit",
    "gn:population":0,
    "gn:timezone":"Asia/Kuala_Lumpur",
    "iso:country":"MY",
    "name:msa_x_preferred":[
        "Kampung Tok Lawit"
    ],
    "name:und_x_variant":[
        "Kampong Tok Lawit"
    ],
    "wof:name":"Kampung Tok Lawit",
    "wof:placetype":"locality"
},
  "geometry": {"coordinates":[102.9011,5.1642],"type":"Point"}
}