{
  "type": "Feature",
  "properties": {
    "gn:admin1_code":"12.0",
    "gn:asciiname":"Kampung Sungai Choh",
    "gn:country_code":"MY",
    "gn:dem":46,
    "gn:feature_class":"P",
    "gn:feature_code":"PPL",
    "gn:name":"Kampung Sungai Choh",
    "gn:population":0,
    "gn:timezone":"Asia/Kuala_Lumpur",
    "iso:country":"MY",
    "name:msa_x_preferred":[
        "Kampung Sungai Choh"
    ],
    "name:msa_x_variant":[
        "Sungai Choh"
    ],
    "name:und_x_variant":[
        "Sungai Coh"
    ],
    "wof:name":"Kampung Sungai Choh",
    "wof:placetype":"locality"
},
  "geometry": {"coordinates":[101.5926,3.347],"type":"Point"}
}