{
  "type": "Feature",
  "properties": {
    "gn:admin1_code":"4",
    "gn:asciiname":"Solok Bukit Tembakau",
    "gn:country_code":"MY",
    "gn:dem":10,
    "gn:feature_class":"P",
    "gn:feature_code":"PPL",
    "gn:name":"Solok Bukit Tembakau",
    "gn:population":0,
    "gn:timezone":"Asia/Kuala_Lumpur",
    "iso:country":"MY",
    "name:msa_x_preferred":[
        "Solok Bukit Tembakau"
    ],
    "name:und_x_variant":[
        "Kampong Bukit Tembakau",
        "Solok Bukit Tembakau"
    ],
    "wof:name":"Solok Bukit Tembakau",
    "wof:placetype":"locality"
},
  "geometry": {"coordinates":[102.3437,2.172],"type":"Point"}
}