{
  "type": "Feature",
  "properties": {
    "gn:admin1_code":"2",
    "gn:asciiname":"Kampung Bechah Pak Baharu",
    "gn:cc2":"MY",
    "gn:country_code":"MY",
    "gn:dem":59,
    "gn:feature_class":"P",
    "gn:feature_code":"PPL",
    "gn:name":"Kampung Bechah Pak Baharu",
    "gn:population":0,
    "gn:timezone":"Asia/Kuala_Lumpur",
    "iso:country":"MY",
    "name:msa_x_preferred":[
        "Kampung Bechah Pak Baharu"
    ],
    "name:und_x_variant":[
        "Kampong Bechah Pa\u2019 Baharu"
    ],
    "wof:name":"Kampung Bechah Pak Baharu",
    "wof:placetype":"locality"
},
  "geometry": {"coordinates":[100.74051,5.7971],"type":"Point"}
}