{
  "type": "Feature",
  "properties": {
    "gn:admin1_code":"1.0",
    "gn:asciiname":"Taman Tanjong",
    "gn:country_code":"MY",
    "gn:dem":18,
    "gn:feature_class":"P",
    "gn:feature_code":"PPL",
    "gn:name":"Taman Tanjong",
    "gn:population":0,
    "gn:timezone":"Asia/Kuala_Lumpur",
    "iso:country":"MY",
    "name:msa_x_preferred":[
        "Taman Tanjong"
    ],
    "wof:name":"Taman Tanjong",
    "wof:placetype":"locality"
},
  "geometry": {"coordinates":[102.93810000000001,1.8417],"type":"Point"}
}