{
  "type": "Feature",
  "properties": {
    "gn:admin1_code":"7",
    "gn:asciiname":"Kampung Suak Pelang",
    "gn:country_code":"MY",
    "gn:dem":71,
    "gn:feature_class":"P",
    "gn:feature_code":"PPL",
    "gn:name":"Kampung Suak Pelang",
    "gn:population":0,
    "gn:timezone":"Asia/Kuala_Lumpur",
    "iso:country":"MY",
    "name:msa_x_preferred":[
        "Kampung Suak Pelang"
    ],
    "name:und_x_variant":[
        "Kampong Suak Plang"
    ],
    "wof:name":"Kampung Suak Pelang",
    "wof:placetype":"locality"
},
  "geometry": {"coordinates":[101.0551,4.8688],"type":"Point"}
}