{
  "type": "Feature",
  "properties": {
    "gn:admin1_code":"7.0",
    "gn:asciiname":"Batu Lembu",
    "gn:country_code":"MY",
    "gn:dem":89,
    "gn:feature_class":"P",
    "gn:feature_code":"PPL",
    "gn:name":"Batu Lembu",
    "gn:population":0,
    "gn:timezone":"Asia/Kuala_Lumpur",
    "iso:country":"MY",
    "wof:name":"Batu Lembu",
    "wof:placetype":"locality"
},
  "geometry": {"coordinates":[100.95,5.03333],"type":"Point"}
}