{
  "type": "Feature",
  "properties": {
    "gn:admin1_code":"2.0",
    "gn:asciiname":"Kisap",
    "gn:country_code":"MY",
    "gn:dem":20,
    "gn:feature_class":"P",
    "gn:feature_code":"PPL",
    "gn:name":"Kisap",
    "gn:population":0,
    "gn:timezone":"Asia/Kuala_Lumpur",
    "iso:country":"MY",
    "name:und_x_variant":[
        "Rambutan",
        "Kisap"
    ],
    "wof:name":"Kisap",
    "wof:placetype":"locality"
},
  "geometry": {"coordinates":[99.86663,6.3665],"type":"Point"}
}