{
  "type": "Feature",
  "properties": {
    "iso:country":"MY",
    "qs:name":"Kg Salang",
    "qs:name_adm0":"Malaysia",
    "qs:name_adm1":"Pahang",
    "qs:photos":870,
    "qs:photos_1k":176,
    "qs:photos_9k":4,
    "qs:photos_9r":6,
    "qs:photos_all":870,
    "qs:photos_sr":10,
    "qs:placetype":"Town",
    "qs:pop_sr":"0",
    "wd:wordcount":996,
    "wof:name":"Kg Salang",
    "wof:placetype":"locality"
},
  "geometry": {"coordinates":[104.15348,2.875643],"type":"Point"}
}