{
  "type": "Feature",
  "properties": {
    "iso:country":"MY",
    "name:ben_x_preferred":[
        "\u09b8\u09c1\u0996-\u09b0\u09cb\u09a6 \u099c\u09c7\u09b2\u09be"
    ],
    "name:ces_x_preferred":[
        "Distrikt Sorch R\u00fad"
    ],
    "name:fas_x_preferred":[
        "\u0648\u0644\u0633\u0648\u0627\u0644\u06cc \u0633\u0631\u062e\u200c\u0631\u0648\u062f"
    ],
    "name:msa_x_preferred":[
        "Daerah Surkh Rod"
    ],
    "name:pnb_x_preferred":[
        "\u0636\u0644\u0639 \u0633\u0631\u062e \u0631\u0648\u062f"
    ],
    "name:pus_x_preferred":[
        "\u0633\u0631\u0647 \u0631\u0648\u062f \u0648\u0644\u0633\u0648\u0627\u0644\u06cd"
    ],
    "name:vie_x_preferred":[
        "Surkh Rod"
    ],
    "qs:name":"Kg Salang",
    "qs:name_adm0":"Malaysia",
    "qs:name_adm1":"Pahang",
    "qs:photos":870,
    "qs:photos_1k":176,
    "qs:photos_9k":4,
    "qs:photos_9r":6,
    "qs:photos_all":870,
    "qs:photos_sr":10,
    "qs:placetype":"Town",
    "qs:pop_sr":"0",
    "wd:wordcount":996,
    "wof:name":"Kg Salang",
    "wof:placetype":"locality"
},
  "geometry": {"coordinates":[104.15348,2.875643],"type":"Point"}
}