{
  "type": "Feature",
  "properties": {
    "gn:admin1_code":"13",
    "gn:asciiname":"Kampung Bukit Catuk",
    "gn:country_code":"MY",
    "gn:dem":12,
    "gn:feature_class":"P",
    "gn:feature_code":"PPL",
    "gn:name":"Kampung Bukit Catuk",
    "gn:population":0,
    "gn:timezone":"Asia/Kuala_Lumpur",
    "iso:country":"MY",
    "name:msa_x_preferred":[
        "Kampung Bukit Catuk"
    ],
    "name:und_x_variant":[
        "Kampong Bukit Chatok"
    ],
    "wof:name":"Kampung Bukit Catuk",
    "wof:placetype":"locality"
},
  "geometry": {"coordinates":[103.4098,4.7605],"type":"Point"}
}