{
  "type": "Feature",
  "properties": {
    "gn:country":"MY",
    "gn:fcode":"PPL",
    "gn:population":0,
    "iso:country":"MY",
    "name:msa_x_preferred":[
        "Pulai"
    ],
    "qs:name":"Pulai",
    "qs:name_adm0":"Malaysia",
    "qs:name_adm1":"Kedah",
    "qs:photos_9r":0,
    "qs:photos_sr":0,
    "qs:placetype":"Town",
    "qs:pop_sr":"0",
    "wof:name":"Pulai",
    "wof:placetype":"locality",
    "wof:population":0
},
  "geometry": {"coordinates":[100.89541,5.65489],"type":"Point"}
}