{
  "type": "Feature",
  "properties": {
    "gn:admin1_code":"11.0",
    "gn:asciiname":"Kampung Kasenduh",
    "gn:country_code":"MY",
    "gn:dem":139,
    "gn:feature_class":"P",
    "gn:feature_code":"PPL",
    "gn:name":"Kampung Kasenduh",
    "gn:population":0,
    "gn:timezone":"Asia/Kuching",
    "iso:country":"MY",
    "wof:name":"Kampung Kasenduh",
    "wof:placetype":"locality"
},
  "geometry": {"coordinates":[110.86667,1.48333],"type":"Point"}
}