{
  "type": "Feature",
  "properties": {
    "gn:admin1_code":"5",
    "gn:asciiname":"Kampung Solok",
    "gn:country_code":"MY",
    "gn:dem":35,
    "gn:feature_class":"P",
    "gn:feature_code":"PPL",
    "gn:name":"Kampung Solok",
    "gn:population":0,
    "gn:timezone":"Asia/Kuala_Lumpur",
    "iso:country":"MY",
    "name:msa_x_preferred":[
        "Kampung Solok"
    ],
    "name:und_x_variant":[
        "Kampong Solok"
    ],
    "wof:name":"Kampung Solok",
    "wof:placetype":"locality"
},
  "geometry": {"coordinates":[101.9695,2.601],"type":"Point"}
}