{
  "type": "Feature",
  "properties": {
    "gn:admin1_code":"1.0",
    "gn:asciiname":"Kampung Melayu Kuala Kabong",
    "gn:country_code":"MY",
    "gn:dem":8,
    "gn:feature_class":"P",
    "gn:feature_code":"PPL",
    "gn:name":"Kampung Melayu Kuala Kabong",
    "gn:population":0,
    "gn:timezone":"Asia/Kuala_Lumpur",
    "iso:country":"MY",
    "name:msa_x_preferred":[
        "Kampung Melayu Kuala Kabong"
    ],
    "name:und_x_variant":[
        "Kampung Kuala Kabong"
    ],
    "wof:name":"Kampung Melayu Kuala Kabong",
    "wof:placetype":"locality"
},
  "geometry": {"coordinates":[103.4633,1.6285],"type":"Point"}
}