{
  "type": "Feature",
  "properties": {
    "gn:admin1_code":"11.0",
    "gn:asciiname":"Kampung Sarabang",
    "gn:country_code":"MY",
    "gn:dem":3,
    "gn:feature_class":"P",
    "gn:feature_code":"PPL",
    "gn:name":"Kampung Sarabang",
    "gn:population":0,
    "gn:timezone":"Asia/Kuching",
    "iso:country":"MY",
    "name:msa_x_preferred":[
        "Kampung Sarabang"
    ],
    "wof:name":"Kampung Sarabang",
    "wof:placetype":"locality"
},
  "geometry": {"coordinates":[111.34177,1.56614],"type":"Point"}
}