{
  "type": "Feature",
  "properties": {
    "gn:admin1_code":"3",
    "gn:asciiname":"Kampong Setol Seratus",
    "gn:country_code":"MY",
    "gn:dem":33,
    "gn:feature_class":"P",
    "gn:feature_code":"PPL",
    "gn:name":"Kampong Setol Seratus",
    "gn:population":0,
    "gn:timezone":"Asia/Kuala_Lumpur",
    "iso:country":"MY",
    "wof:name":"Kampong Setol Seratus",
    "wof:placetype":"locality"
},
  "geometry": {"coordinates":[102.40000000000001,5.78333],"type":"Point"}
}