{
  "type": "Feature",
  "properties": {
    "gn:admin1_code":"7.0",
    "gn:asciiname":"Taman Kinta",
    "gn:country_code":"MY",
    "gn:dem":51,
    "gn:feature_class":"P",
    "gn:feature_code":"PPL",
    "gn:name":"Taman Kinta",
    "gn:population":0,
    "gn:timezone":"Asia/Kuala_Lumpur",
    "iso:country":"MY",
    "name:msa_x_preferred":[
        "Taman Kinta"
    ],
    "wof:name":"Taman Kinta",
    "wof:placetype":"locality"
},
  "geometry": {"coordinates":[101.1028,4.6159],"type":"Point"}
}