{
  "type": "Feature",
  "properties": {
    "gn:admin1_code":"13",
    "gn:asciiname":"Kampung Nyatoh",
    "gn:cc2":"MY",
    "gn:country_code":"MY",
    "gn:dem":11,
    "gn:feature_class":"P",
    "gn:feature_code":"PPL",
    "gn:name":"Kampung Nyatoh",
    "gn:population":0,
    "gn:timezone":"Asia/Kuala_Lumpur",
    "iso:country":"MY",
    "name:msa_x_preferred":[
        "Kampung Nyatoh"
    ],
    "name:und_x_variant":[
        "Kampong Nyatoh"
    ],
    "wof:name":"Kampung Nyatoh",
    "wof:placetype":"locality"
},
  "geometry": {"coordinates":[102.80065999999999,5.58963],"type":"Point"}
}