{
  "type": "Feature",
  "properties": {
    "gn:admin1_code":"2",
    "gn:asciiname":"Kampung Padang Penyangga",
    "gn:cc2":"MY",
    "gn:country_code":"MY",
    "gn:dem":27,
    "gn:feature_class":"P",
    "gn:feature_code":"PPL",
    "gn:name":"Kampung Padang Penyangga",
    "gn:population":0,
    "gn:timezone":"Asia/Kuala_Lumpur",
    "iso:country":"MY",
    "name:msa_x_preferred":[
        "Kampung Padang Penyangga"
    ],
    "name:und_x_variant":[
        "Kampong Padang Penyangga"
    ],
    "wof:name":"Kampung Padang Penyangga",
    "wof:placetype":"locality"
},
  "geometry": {"coordinates":[100.53998,5.30504],"type":"Point"}
}