{
  "type": "Feature",
  "properties": {
    "gn:admin1_code":"1.0",
    "gn:asciiname":"Taman Anjariah",
    "gn:country_code":"MY",
    "gn:dem":58,
    "gn:feature_class":"P",
    "gn:feature_code":"PPL",
    "gn:name":"Taman Anjariah",
    "gn:population":0,
    "gn:timezone":"Asia/Kuala_Lumpur",
    "iso:country":"MY",
    "name:msa_x_preferred":[
        "Taman Anjariah"
    ],
    "wof:name":"Taman Anjariah",
    "wof:placetype":"locality"
},
  "geometry": {"coordinates":[103.643,1.7304],"type":"Point"}
}