{
  "type": "Feature",
  "properties": {
    "gn:admin1_code":"6.0",
    "gn:asciiname":"Kampung Petuh",
    "gn:country_code":"MY",
    "gn:dem":22,
    "gn:feature_class":"P",
    "gn:feature_code":"PPL",
    "gn:name":"Kampung Petuh",
    "gn:population":0,
    "gn:timezone":"Asia/Kuala_Lumpur",
    "iso:country":"MY",
    "name:msa_x_preferred":[
        "Kampung Petuh"
    ],
    "name:und_x_variant":[
        "Kampung Petoh"
    ],
    "wof:name":"Kampung Petuh",
    "wof:placetype":"locality"
},
  "geometry": {"coordinates":[103.2636,2.8739],"type":"Point"}
}