{
  "type": "Feature",
  "properties": {
    "gn:admin1_code":"3.0",
    "gn:asciiname":"Kampung Telok Bayu",
    "gn:country_code":"MY",
    "gn:dem":82,
    "gn:feature_class":"P",
    "gn:feature_code":"PPL",
    "gn:name":"Kampung Telok Bayu",
    "gn:population":0,
    "gn:timezone":"Asia/Kuala_Lumpur",
    "iso:country":"MY",
    "name:msa_x_preferred":[
        "Kampung Telok Bayu"
    ],
    "wof:name":"Kampung Telok Bayu",
    "wof:placetype":"locality"
},
  "geometry": {"coordinates":[101.872,5.667],"type":"Point"}
}