{
  "type": "Feature",
  "properties": {
    "iso:country":"MY",
    "name:eng_x_preferred":[
        "Kampong Telok Gadong Besar"
    ],
    "qs:gn_adm0_cc":"MY",
    "qs:gn_fcode":"PPLX",
    "qs:gn_local":1732905,
    "qs:gn_nam_loc":"Klang, Kelang, Klang, Selangor, MY",
    "qs:gn_namadm1":"00",
    "qs:gn_name":"Kampong Telok Gadong Besar",
    "qs:local_max":212,
    "qs:local_sum":314,
    "qs:localhoods":3,
    "qs:name":"Kampong Telok Gadong Besar",
    "qs:name_adm0":"Malaysia",
    "qs:name_adm1":"Selangor",
    "qs:name_adm2":"Klang",
    "qs:name_lau":"Kelang",
    "qs:name_local":"Klang",
    "qs:photo_max":20,
    "qs:photo_sum":74,
    "qs:placetype":"Suburb",
    "qs:quad_count":14,
    "qs:woe_adm0":23424901,
    "qs:woe_adm1":2346306,
    "qs:woe_adm2":56013613,
    "qs:woe_lau":56014433,
    "qs:woe_local":1154726,
    "qs:woe_ver":"7.10.0",
    "wof:lang":[
        "eng"
    ],
    "wof:name":"Kampong Telok Gadong Besar",
    "wof:placetype":"neighbourhood"
},
  "geometry": {"coordinates":[101.439515,3.008573],"type":"Point"}
}