{
  "type": "Feature",
  "properties": {
    "iso:country":"MY",
    "qs:name":"Taman Setia",
    "qs:name_adm0":"Malaysia",
    "qs:name_adm1":"Johor",
    "qs:photos":3,
    "qs:photos_1k":1,
    "qs:photos_9k":1,
    "qs:photos_9r":1,
    "qs:photos_all":3,
    "qs:photos_sr":1,
    "qs:placetype":"Suburb",
    "qs:pop_sr":"0",
    "wof:name":"Taman Setia",
    "wof:placetype":"neighbourhood"
},
  "geometry": {"coordinates":[103.52949099999999,1.503066],"type":"Point"}
}