{
  "type": "Feature",
  "properties": {
    "gn:admin1_code":"1.0",
    "gn:asciiname":"Kampung Teluk Rimba",
    "gn:country_code":"MY",
    "gn:dem":7,
    "gn:feature_class":"P",
    "gn:feature_code":"PPL",
    "gn:name":"Kampung Teluk Rimba",
    "gn:population":0,
    "gn:timezone":"Asia/Kuala_Lumpur",
    "iso:country":"MY",
    "name:msa_x_preferred":[
        "Kampung Teluk Rimba"
    ],
    "wof:name":"Kampung Teluk Rimba",
    "wof:placetype":"locality"
},
  "geometry": {"coordinates":[102.517,2.1788],"type":"Point"}
}