{
  "type": "Feature",
  "properties": {
    "gn:admin1_code":"16.0",
    "gn:asciiname":"Amboi",
    "gn:country_code":"MY",
    "gn:dem":254,
    "gn:feature_class":"P",
    "gn:feature_code":"PPL",
    "gn:name":"Amboi",
    "gn:population":0,
    "gn:timezone":"Asia/Kuching",
    "iso:country":"MY",
    "wof:name":"Amboi",
    "wof:placetype":"locality"
},
  "geometry": {"coordinates":[115.91667,5.11667],"type":"Point"}
}