{
  "type": "Feature",
  "properties": {
    "gn:admin1_code":"16",
    "gn:asciiname":"Kampung Tinompok Ulu",
    "gn:country_code":"MY",
    "gn:dem":617,
    "gn:feature_class":"P",
    "gn:feature_code":"PPL",
    "gn:name":"Kampung Tinompok Ulu",
    "gn:population":0,
    "gn:timezone":"Asia/Kuching",
    "iso:country":"MY",
    "name:msa_x_preferred":[
        "Kampung Tinompok Ulu"
    ],
    "name:und_x_variant":[
        "Kampong Tinompok"
    ],
    "wof:name":"Kampung Tinompok Ulu",
    "wof:placetype":"locality"
},
  "geometry": {"coordinates":[116.2889,5.9926],"type":"Point"}
}