{
  "type": "Feature",
  "properties": {
    "gn:admin1_code":"7.0",
    "gn:asciiname":"Rancangan Rumah Awam Sungai Dulang",
    "gn:country_code":"MY",
    "gn:dem":5,
    "gn:feature_class":"P",
    "gn:feature_code":"PPL",
    "gn:name":"Rancangan Rumah Awam Sungai Dulang",
    "gn:population":0,
    "gn:timezone":"Asia/Kuala_Lumpur",
    "iso:country":"MY",
    "name:msa_x_preferred":[
        "Rancangan Rumah Awam Sungai Dulang"
    ],
    "wof:name":"Rancangan Rumah Awam Sungai Dulang",
    "wof:placetype":"locality"
},
  "geometry": {"coordinates":[100.869,3.9475],"type":"Point"}
}