{
  "type": "Feature",
  "properties": {
    "gn:admin1_code":"16",
    "gn:asciiname":"Kampong Sumbilangan",
    "gn:country_code":"MY",
    "gn:dem":31,
    "gn:feature_class":"P",
    "gn:feature_code":"PPL",
    "gn:name":"Kampong Sumbilangan",
    "gn:population":0,
    "gn:timezone":"Asia/Kuching",
    "iso:country":"MY",
    "name:msa_x_preferred":[
        "Kampong Sumbilangan"
    ],
    "name:und_x_variant":[
        "Kampong Sambilingan"
    ],
    "wof:name":"Kampong Sumbilangan",
    "wof:placetype":"locality"
},
  "geometry": {"coordinates":[116.3621,6.3138],"type":"Point"}
}