{
  "type": "Feature",
  "properties": {
    "iso:country":"MY",
    "qs:name":"Bukit Baru",
    "qs:name_adm0":"Malaysia",
    "qs:name_adm1":"Melaka",
    "qs:photos":5,
    "qs:photos_1k":1,
    "qs:photos_9k":3,
    "qs:photos_9r":5,
    "qs:photos_all":586,
    "qs:photos_sr":1,
    "qs:placetype":"LocalAdmin",
    "qs:pop_sr":"0",
    "wof:name":"Bukit Baru",
    "wof:placetype":"localadmin"
},
  "geometry": {"coordinates":[102.30221899999999,2.281109],"type":"Point"}
}