{
  "type": "Feature",
  "properties": {
    "gn:admin1_code":"7.0",
    "gn:asciiname":"Kampung Sungai Batu",
    "gn:country_code":"MY",
    "gn:dem":10,
    "gn:feature_class":"P",
    "gn:feature_code":"PPL",
    "gn:name":"Kampung Sungai Batu",
    "gn:population":0,
    "gn:timezone":"Asia/Kuala_Lumpur",
    "iso:country":"MY",
    "name:msa_x_preferred":[
        "Kampung Sungai Batu"
    ],
    "name:und_x_variant":[
        "Sungai Batu"
    ],
    "wof:name":"Kampung Sungai Batu",
    "wof:placetype":"locality"
},
  "geometry": {"coordinates":[100.6262,4.4325],"type":"Point"}
}