{
  "type": "Feature",
  "properties": {
    "gn:country":"MY",
    "gn:fcode":"PPL",
    "gn:population":0,
    "iso:country":"MY",
    "name:msa_x_preferred":[
        "Kampung Lumut Kiri"
    ],
    "qs:name":"Kampong Lumut Kiri",
    "qs:name_adm0":"Malaysia",
    "qs:name_adm1":"Perak",
    "qs:photos":21,
    "qs:photos_1k":4,
    "qs:photos_9k":1,
    "qs:photos_9r":1,
    "qs:photos_all":21,
    "qs:photos_sr":1,
    "qs:placetype":"Town",
    "qs:pop_sr":"0",
    "wof:name":"Kampong Lumut Kiri",
    "wof:placetype":"locality",
    "wof:population":0
},
  "geometry": {"coordinates":[100.67740000000001,4.2256],"type":"Point"}
}