{
  "type": "Feature",
  "properties": {
    "gn:admin1_code":"16.0",
    "gn:asciiname":"Kampung Kankoduan",
    "gn:country_code":"MY",
    "gn:dem":52,
    "gn:feature_class":"P",
    "gn:feature_code":"PPL",
    "gn:name":"Kampung Kankoduan",
    "gn:population":0,
    "gn:timezone":"Asia/Kuching",
    "iso:country":"MY",
    "name:msa_x_preferred":[
        "Kampung Kankoduan"
    ],
    "wof:name":"Kampung Kankoduan",
    "wof:placetype":"locality"
},
  "geometry": {"coordinates":[117.1773,6.1275],"type":"Point"}
}