{
  "type": "Feature",
  "properties": {
    "gn:admin1_code":"5",
    "gn:asciiname":"Kuala Jelai",
    "gn:country_code":"MY",
    "gn:dem":60,
    "gn:feature_class":"P",
    "gn:feature_code":"PPL",
    "gn:name":"Kuala Jelai",
    "gn:population":0,
    "gn:timezone":"Asia/Kuala_Lumpur",
    "iso:country":"MY",
    "name:msa_x_preferred":[
        "Kuala Jelai"
    ],
    "name:und_x_variant":[
        "Kampong Kuala Jelei",
        "Kuala Jelei"
    ],
    "wof:name":"Kuala Jelai",
    "wof:placetype":"locality"
},
  "geometry": {"coordinates":[102.39960000000001,2.7586],"type":"Point"}
}