{
  "type": "Feature",
  "properties": {
    "gn:admin1_code":"1",
    "gn:asciiname":"Kampung Sungai Ekor",
    "gn:country_code":"MY",
    "gn:dem":7,
    "gn:feature_class":"P",
    "gn:feature_code":"PPL",
    "gn:name":"Kampung Sungai Ekor",
    "gn:population":0,
    "gn:timezone":"Asia/Kuala_Lumpur",
    "iso:country":"MY",
    "name:msa_x_preferred":[
        "Kampung Sungai Ekor"
    ],
    "name:und_x_variant":[
        "Kampong Sungai Ikor"
    ],
    "wof:name":"Kampung Sungai Ekor",
    "wof:placetype":"locality"
},
  "geometry": {"coordinates":[102.6712,2.2209],"type":"Point"}
}