{
  "type": "Feature",
  "properties": {
    "gn:admin1_code":"13.0",
    "gn:asciiname":"Kampung Banggul Tok Lib",
    "gn:country_code":"MY",
    "gn:dem":14,
    "gn:feature_class":"P",
    "gn:feature_code":"PPL",
    "gn:name":"Kampung Banggul Tok Lib",
    "gn:population":0,
    "gn:timezone":"Asia/Kuala_Lumpur",
    "iso:country":"MY",
    "name:msa_x_preferred":[
        "Kampung Banggul Tok Lib"
    ],
    "wof:name":"Kampung Banggul Tok Lib",
    "wof:placetype":"locality"
},
  "geometry": {"coordinates":[103.0733,5.4204],"type":"Point"}
}