{
  "type": "Feature",
  "properties": {
    "gn:admin1_code":"1.0",
    "gn:asciiname":"Kampung Kahang Selatan",
    "gn:country_code":"MY",
    "gn:dem":28,
    "gn:feature_class":"P",
    "gn:feature_code":"PPL",
    "gn:name":"Kampung Kahang Selatan",
    "gn:population":0,
    "gn:timezone":"Asia/Kuala_Lumpur",
    "iso:country":"MY",
    "name:msa_x_preferred":[
        "Kampung Kahang Selatan"
    ],
    "wof:name":"Kampung Kahang Selatan",
    "wof:placetype":"locality"
},
  "geometry": {"coordinates":[103.545,2.2098],"type":"Point"}
}