{
  "type": "Feature",
  "properties": {
    "gn:admin1_code":"9.0",
    "gn:asciiname":"Kampung Bagan Serai",
    "gn:country_code":"MY",
    "gn:dem":1,
    "gn:feature_class":"P",
    "gn:feature_code":"PPL",
    "gn:name":"Kampung Bagan Serai",
    "gn:population":0,
    "gn:timezone":"Asia/Kuala_Lumpur",
    "iso:country":"MY",
    "name:msa_x_preferred":[
        "Kampung Bagan Serai"
    ],
    "name:und_x_variant":[
        "Bagan Serai",
        "Kampong Bagan Serai"
    ],
    "wof:name":"Kampung Bagan Serai",
    "wof:placetype":"locality"
},
  "geometry": {"coordinates":[100.40957,5.40347],"type":"Point"}
}