{
  "type": "Feature",
  "properties": {
    "gn:admin1_code":"7",
    "gn:asciiname":"Kampung Sira Kulim",
    "gn:country_code":"MY",
    "gn:dem":135,
    "gn:feature_class":"P",
    "gn:feature_code":"PPL",
    "gn:name":"Kampung Sira Kulim",
    "gn:population":0,
    "gn:timezone":"Asia/Kuala_Lumpur",
    "iso:country":"MY",
    "name:und_x_variant":[
        "Kampong Sira Kulim"
    ],
    "wof:name":"Kampung Sira Kulim",
    "wof:placetype":"locality"
},
  "geometry": {"coordinates":[101.11217000000001,5.39356],"type":"Point"}
}