{
  "type": "Feature",
  "properties": {
    "iso:country":"MY",
    "qs:name":"Mukim 14 Bt. Paya Terubung",
    "qs:name_adm0":"Malaysia",
    "qs:name_adm1":"Pulau Pinang",
    "qs:photos":2,
    "qs:photos_1k":1,
    "qs:photos_9k":1,
    "qs:photos_9r":4,
    "qs:photos_all":202,
    "qs:photos_sr":1,
    "qs:placetype":"LocalAdmin",
    "qs:pop_sr":"0",
    "wof:name":"Mukim 14 Bt. Paya Terubung",
    "wof:placetype":"localadmin"
},
  "geometry": {"coordinates":[100.247497,5.384284],"type":"Point"}
}