{
  "type": "Feature",
  "properties": {
    "gn:admin1_code":"2.0",
    "gn:asciiname":"Kampung Bukit Rawa",
    "gn:country_code":"MY",
    "gn:dem":125,
    "gn:feature_class":"P",
    "gn:feature_code":"PPL",
    "gn:name":"Kampung Bukit Rawa",
    "gn:population":0,
    "gn:timezone":"Asia/Kuala_Lumpur",
    "iso:country":"MY",
    "name:msa_x_preferred":[
        "Kampung Bukit Rawa"
    ],
    "wof:name":"Kampung Bukit Rawa",
    "wof:placetype":"locality"
},
  "geometry": {"coordinates":[100.89476000000001,5.84177],"type":"Point"}
}