{
  "type": "Feature",
  "properties": {
    "gn:admin1_code":"11",
    "gn:asciiname":"Long Komap",
    "gn:country_code":"MY",
    "gn:dem":1363,
    "gn:feature_class":"P",
    "gn:feature_code":"PPL",
    "gn:name":"Long Komap",
    "gn:population":0,
    "gn:timezone":"Asia/Kuching",
    "iso:country":"MY",
    "wof:name":"Long Komap",
    "wof:placetype":"locality"
},
  "geometry": {"coordinates":[115.54088,3.96906],"type":"Point"}
}