{
  "type": "Feature",
  "properties": {
    "gn:admin1_code":"13.0",
    "gn:asciiname":"Taman Bukit Payung",
    "gn:country_code":"MY",
    "gn:dem":10,
    "gn:feature_class":"P",
    "gn:feature_code":"PPL",
    "gn:name":"Taman Bukit Payung",
    "gn:population":0,
    "gn:timezone":"Asia/Kuala_Lumpur",
    "iso:country":"MY",
    "name:msa_x_preferred":[
        "Taman Bukit Payung"
    ],
    "wof:name":"Taman Bukit Payung",
    "wof:placetype":"locality"
},
  "geometry": {"coordinates":[103.1028,5.2088],"type":"Point"}
}