{
  "type": "Feature",
  "properties": {
    "gn:admin1_code":"12",
    "gn:asciiname":"Kampung Batu Tiga Puloh Sembilan",
    "gn:country_code":"MY",
    "gn:dem":5,
    "gn:feature_class":"P",
    "gn:feature_code":"PPL",
    "gn:name":"Kampung Batu Tiga Puloh Sembilan",
    "gn:population":0,
    "gn:timezone":"Asia/Kuala_Lumpur",
    "iso:country":"MY",
    "name:msa_x_preferred":[
        "Kampung Batu Tiga Puloh Sembilan"
    ],
    "name:und_x_variant":[
        "Kampong Batu",
        "Kampong Batu Thirty-nine"
    ],
    "wof:name":"Kampung Batu Tiga Puloh Sembilan",
    "wof:placetype":"locality"
},
  "geometry": {"coordinates":[100.96510000000001,3.7599],"type":"Point"}
}