{
  "type": "Feature",
  "properties": {
    "gn:admin1_code":"12",
    "gn:asciiname":"Kampung Keliang",
    "gn:country_code":"MY",
    "gn:dem":49,
    "gn:feature_class":"P",
    "gn:feature_code":"PPL",
    "gn:name":"Kampung Keliang",
    "gn:population":0,
    "gn:timezone":"Asia/Kuala_Lumpur",
    "iso:country":"MY",
    "name:msa_x_preferred":[
        "Kampung Keliang"
    ],
    "name:und_x_variant":[
        "Kampong Kliang",
        "Kampong Keliang"
    ],
    "wof:name":"Kampung Keliang",
    "wof:placetype":"locality"
},
  "geometry": {"coordinates":[101.5466,3.6581],"type":"Point"}
}