{
  "type": "Feature",
  "properties": {
    "gn:admin1_code":"3.0",
    "gn:asciiname":"Bukit Lada",
    "gn:country_code":"MY",
    "gn:dem":61,
    "gn:feature_class":"P",
    "gn:feature_code":"PPL",
    "gn:name":"Bukit Lada",
    "gn:population":0,
    "gn:timezone":"Asia/Kuala_Lumpur",
    "iso:country":"MY",
    "wof:name":"Bukit Lada",
    "wof:placetype":"locality"
},
  "geometry": {"coordinates":[102.26667,5.76667],"type":"Point"}
}