{
  "type": "Feature",
  "properties": {
    "gn:admin1_code":"13.0",
    "gn:asciiname":"Kemajuan Tanah Jerangau Barat",
    "gn:country_code":"MY",
    "gn:dem":38,
    "gn:feature_class":"P",
    "gn:feature_code":"PPL",
    "gn:name":"Kemajuan Tanah Jerangau Barat",
    "gn:population":0,
    "gn:timezone":"Asia/Kuala_Lumpur",
    "iso:country":"MY",
    "name:msa_x_preferred":[
        "Kemajuan Tanah Jerangau Barat"
    ],
    "wof:name":"Kemajuan Tanah Jerangau Barat",
    "wof:placetype":"locality"
},
  "geometry": {"coordinates":[103.1104,4.9244],"type":"Point"}
}