{
  "type": "Feature",
  "properties": {
    "gn:admin1_code":"3.0",
    "gn:asciiname":"Kampung Bharu Tanjung Duff",
    "gn:country_code":"MY",
    "gn:dem":4,
    "gn:feature_class":"P",
    "gn:feature_code":"PPL",
    "gn:name":"Kampung Bharu Tanjung Duff",
    "gn:population":0,
    "gn:timezone":"Asia/Kuala_Lumpur",
    "iso:country":"MY",
    "name:msa_x_preferred":[
        "Kampung Bharu Tanjung Duff"
    ],
    "wof:name":"Kampung Bharu Tanjung Duff",
    "wof:placetype":"locality"
},
  "geometry": {"coordinates":[102.17623,6.20147],"type":"Point"}
}