{
  "type": "Feature",
  "properties": {
    "gn:admin1_code":"16.0",
    "gn:asciiname":"Kampong Mundas",
    "gn:country_code":"MY",
    "gn:dem":10,
    "gn:feature_class":"P",
    "gn:feature_code":"PPL",
    "gn:name":"Kampong Mundas",
    "gn:population":0,
    "gn:timezone":"Asia/Kuching",
    "iso:country":"MY",
    "name:und_x_variant":[
        "Mundas",
        "Kampong Mundas"
    ],
    "wof:name":"Kampong Mundas",
    "wof:placetype":"locality"
},
  "geometry": {"coordinates":[118.8931,5.0241],"type":"Point"}
}