{
  "type": "Feature",
  "properties": {
    "gn:admin1_code":"2.0",
    "gn:asciiname":"Kampung Lubok Perong",
    "gn:country_code":"MY",
    "gn:dem":40,
    "gn:feature_class":"P",
    "gn:feature_code":"PPL",
    "gn:name":"Kampung Lubok Perong",
    "gn:population":0,
    "gn:timezone":"Asia/Kuala_Lumpur",
    "iso:country":"MY",
    "name:msa_x_preferred":[
        "Kampung Lubok Perong"
    ],
    "wof:name":"Kampung Lubok Perong",
    "wof:placetype":"locality"
},
  "geometry": {"coordinates":[100.6425,6.20666],"type":"Point"}
}