{
  "type": "Feature",
  "properties": {
    "gn:admin1_code":"6.0",
    "gn:asciiname":"Kampung Baharu Lubuk Kawah",
    "gn:country_code":"MY",
    "gn:dem":42,
    "gn:feature_class":"P",
    "gn:feature_code":"PPL",
    "gn:name":"Kampung Baharu Lubuk Kawah",
    "gn:population":0,
    "gn:timezone":"Asia/Kuala_Lumpur",
    "iso:country":"MY",
    "name:msa_x_preferred":[
        "Kampung Baharu Lubuk Kawah"
    ],
    "wof:name":"Kampung Baharu Lubuk Kawah",
    "wof:placetype":"locality"
},
  "geometry": {"coordinates":[102.4171,3.4872],"type":"Point"}
}