{
  "type": "Feature",
  "properties": {
    "gn:admin1_code":"2",
    "gn:asciiname":"Kampung Bendang Temingat",
    "gn:cc2":"MY",
    "gn:country_code":"MY",
    "gn:dem":57,
    "gn:feature_class":"P",
    "gn:feature_code":"PPL",
    "gn:name":"Kampung Bendang Temingat",
    "gn:population":0,
    "gn:timezone":"Asia/Kuala_Lumpur",
    "iso:country":"MY",
    "name:msa_x_preferred":[
        "Kampung Bendang Temingat"
    ],
    "name:und_x_variant":[
        "Kampong Bendang Penyengat"
    ],
    "wof:name":"Kampung Bendang Temingat",
    "wof:placetype":"locality"
},
  "geometry": {"coordinates":[100.76656,5.83476],"type":"Point"}
}