{
  "type": "Feature",
  "properties": {
    "gn:admin1_code":"5.0",
    "gn:asciiname":"Pulau Pokong",
    "gn:country_code":"MY",
    "gn:dem":49,
    "gn:feature_class":"P",
    "gn:feature_code":"PPL",
    "gn:name":"Pulau Pokong",
    "gn:population":0,
    "gn:timezone":"Asia/Kuala_Lumpur",
    "iso:country":"MY",
    "name:msa_x_preferred":[
        "Pulau Pokong"
    ],
    "wof:name":"Pulau Pokong",
    "wof:placetype":"locality"
},
  "geometry": {"coordinates":[102.1264,2.5828],"type":"Point"}
}