{
  "type": "Feature",
  "properties": {
    "gn:admin1_code":"1",
    "gn:asciiname":"Kampung Gemereh",
    "gn:country_code":"MY",
    "gn:dem":9,
    "gn:feature_class":"P",
    "gn:feature_code":"PPL",
    "gn:name":"Kampung Gemereh",
    "gn:population":0,
    "gn:timezone":"Asia/Kuala_Lumpur",
    "iso:country":"MY",
    "name:und_x_variant":[
        "Kangkar Gemriah",
        "Kampong Gemereh",
        "Kampung Gemereh"
    ],
    "wof:name":"Kampung Gemereh",
    "wof:placetype":"locality"
},
  "geometry": {"coordinates":[104.03610999999999,1.91638],"type":"Point"}
}