{
  "type": "Feature",
  "properties": {
    "iso:country":"MY",
    "name:und_x_preferred":[
        "Kg. Melayu Sungai Sering"
    ],
    "name:unk_x_variant":[
        "Kg. Melayu Sungai Sering"
    ],
    "qs:gn_local":0,
    "qs:local_max":1600,
    "qs:local_sum":2828,
    "qs:localhoods":16,
    "qs:name":"Kg. Melayu Sungai Sering",
    "qs:name_adm0":"Malaysia",
    "qs:name_adm1":"Selangor",
    "qs:name_adm2":"Gombak",
    "qs:name_lau":"Hulu Kelang",
    "qs:name_local":"Pekan Ampang",
    "qs:photo_max":5,
    "qs:photo_sum":8,
    "qs:placetype":"Suburb",
    "qs:quad_count":4,
    "qs:woe_adm0":23424901,
    "qs:woe_adm1":2346306,
    "qs:woe_adm2":56013604,
    "qs:woe_lau":56014343,
    "qs:woe_local":1140655,
    "qs:woe_ver":"7.10.0",
    "wof:lang":[
        "unk"
    ],
    "wof:name":"Kg. Melayu Sungai Sering",
    "wof:placetype":"neighbourhood"
},
  "geometry": {"coordinates":[101.78833,3.204962],"type":"Point"}
}