{
  "type": "Feature",
  "properties": {
    "gn:admin1_code":"5.0",
    "gn:asciiname":"Kampung Ayer Sepam",
    "gn:country_code":"MY",
    "gn:dem":111,
    "gn:feature_class":"P",
    "gn:feature_code":"PPL",
    "gn:name":"Kampung Ayer Sepam",
    "gn:population":0,
    "gn:timezone":"Asia/Kuala_Lumpur",
    "iso:country":"MY",
    "name:msa_x_preferred":[
        "Kampung Ayer Sepam"
    ],
    "wof:name":"Kampung Ayer Sepam",
    "wof:placetype":"locality"
},
  "geometry": {"coordinates":[102.304,2.7552],"type":"Point"}
}