{
  "type": "Feature",
  "properties": {
    "gn:admin1_code":"7",
    "gn:asciiname":"Kampong Talang Ulu",
    "gn:country_code":"MY",
    "gn:dem":51,
    "gn:feature_class":"P",
    "gn:feature_code":"PPL",
    "gn:name":"Kampong Talang Ulu",
    "gn:population":0,
    "gn:timezone":"Asia/Kuala_Lumpur",
    "iso:country":"MY",
    "wof:name":"Kampong Talang Ulu",
    "wof:placetype":"locality"
},
  "geometry": {"coordinates":[100.91667,4.76667],"type":"Point"}
}