{
  "type": "Feature",
  "properties": {
    "gn:admin1_code":"16.0",
    "gn:asciiname":"Tapai",
    "gn:country_code":"MY",
    "gn:dem":853,
    "gn:feature_class":"P",
    "gn:feature_code":"PPL",
    "gn:name":"Tapai",
    "gn:population":0,
    "gn:timezone":"Asia/Kuching",
    "iso:country":"MY",
    "name:ind_x_preferred":[
        "Tapai"
    ],
    "name:jav_x_preferred":[
        "Tap\u00e9"
    ],
    "name:jpn_x_preferred":[
        "\u30bf\u30d1\u30a4"
    ],
    "name:msa_x_preferred":[
        "Tapai"
    ],
    "name:spa_x_preferred":[
        "Tapai"
    ],
    "name:sun_x_preferred":[
        "Peuyeum"
    ],
    "wof:name":"Tapai",
    "wof:placetype":"locality"
},
  "geometry": {"coordinates":[116.3763,5.7535],"type":"Point"}
}