{
  "type": "Feature",
  "properties": {
    "gn:admin1_code":"16",
    "gn:asciiname":"Kampung Limputong",
    "gn:country_code":"MY",
    "gn:dem":88,
    "gn:feature_class":"P",
    "gn:feature_code":"PPL",
    "gn:name":"Kampung Limputong",
    "gn:population":0,
    "gn:timezone":"Asia/Kuching",
    "iso:country":"MY",
    "name:msa_x_preferred":[
        "Kampung Limputong"
    ],
    "name:und_x_variant":[
        "Kampong Limputong"
    ],
    "wof:name":"Kampung Limputong",
    "wof:placetype":"locality"
},
  "geometry": {"coordinates":[116.0787,5.814],"type":"Point"}
}