{
  "type": "Feature",
  "properties": {
    "gn:admin1_code":"6.0",
    "gn:asciiname":"Kampung Lubuk Paku",
    "gn:country_code":"MY",
    "gn:dem":30,
    "gn:feature_class":"P",
    "gn:feature_code":"PPL",
    "gn:name":"Kampung Lubuk Paku",
    "gn:population":0,
    "gn:timezone":"Asia/Kuala_Lumpur",
    "iso:country":"MY",
    "name:msa_x_preferred":[
        "Kampung Lubuk Paku"
    ],
    "name:und_x_variant":[
        "Kampong Lubok Paku",
        "Kampung Lubuk"
    ],
    "wof:name":"Kampung Lubuk Paku",
    "wof:placetype":"locality"
},
  "geometry": {"coordinates":[102.77509999999999,3.504],"type":"Point"}
}