{
  "type": "Feature",
  "properties": {
    "iso:country":"MY",
    "name:eng_x_preferred":[
        "Tanjong"
    ],
    "name:fra_x_preferred":[
        "Tanjong"
    ],
    "name:msa_x_preferred":[
        "Tanjong PLC"
    ],
    "qs:name":"Tanjong",
    "qs:name_adm0":"Malaysia",
    "qs:name_adm1":"Perak",
    "qs:photos":1,
    "qs:photos_1k":1,
    "qs:photos_9k":1,
    "qs:photos_9r":1,
    "qs:photos_all":1,
    "qs:photos_sr":1,
    "qs:placetype":"Town",
    "qs:pop_sr":"0",
    "wd:wordcount":115,
    "wof:name":"Tanjong",
    "wof:placetype":"locality"
},
  "geometry": {"coordinates":[101.53339099999999,3.746775],"type":"Point"}
}