{
  "type": "Feature",
  "properties": {
    "gn:admin1_code":"16.0",
    "gn:asciiname":"Kampung Biabas",
    "gn:country_code":"MY",
    "gn:dem":142,
    "gn:feature_class":"P",
    "gn:feature_code":"PPL",
    "gn:name":"Kampung Biabas",
    "gn:population":0,
    "gn:timezone":"Asia/Kuching",
    "iso:country":"MY",
    "name:msa_x_preferred":[
        "Kampung Biabas"
    ],
    "wof:name":"Kampung Biabas",
    "wof:placetype":"locality"
},
  "geometry": {"coordinates":[116.86969999999999,6.5761],"type":"Point"}
}