{
  "type": "Feature",
  "properties": {
    "gn:admin1_code":"16",
    "gn:asciiname":"Kampung Nalapak",
    "gn:country_code":"MY",
    "gn:dem":347,
    "gn:feature_class":"P",
    "gn:feature_code":"PPL",
    "gn:name":"Kampung Nalapak",
    "gn:population":0,
    "gn:timezone":"Asia/Kuching",
    "iso:country":"MY",
    "name:msa_x_preferred":[
        "Kampung Nalapak"
    ],
    "name:und_x_variant":[
        "Kampong Nalapak",
        "Nalapak"
    ],
    "wof:name":"Kampung Nalapak",
    "wof:placetype":"locality"
},
  "geometry": {"coordinates":[116.7753,5.9375],"type":"Point"}
}