{
  "type": "Feature",
  "properties": {
    "gn:admin1_code":"2.0",
    "gn:asciiname":"Kampung Pengkalan Tok Puteh",
    "gn:cc2":"MY",
    "gn:country_code":"MY",
    "gn:dem":44,
    "gn:feature_class":"P",
    "gn:feature_code":"PPL",
    "gn:name":"Kampung Pengkalan Tok Puteh",
    "gn:population":0,
    "gn:timezone":"Asia/Kuala_Lumpur",
    "iso:country":"MY",
    "name:msa_x_preferred":[
        "Kampung Pengkalan Tok Puteh"
    ],
    "name:und_x_variant":[
        "Kampong Pengkalan Tok Puteh",
        "Pengkalan Tok Putih"
    ],
    "wof:name":"Kampung Pengkalan Tok Puteh",
    "wof:placetype":"locality"
},
  "geometry": {"coordinates":[100.59238999999999,6.31822],"type":"Point"}
}