{
  "type": "Feature",
  "properties": {
    "gn:admin1_code":"1.0",
    "gn:asciiname":"Kampung Temiang",
    "gn:country_code":"MY",
    "gn:dem":6,
    "gn:feature_class":"P",
    "gn:feature_code":"PPL",
    "gn:name":"Kampung Temiang",
    "gn:population":0,
    "gn:timezone":"Asia/Kuala_Lumpur",
    "iso:country":"MY",
    "name:msa_x_preferred":[
        "Kampung Temiang"
    ],
    "name:und_x_variant":[
        "Kampung Temang"
    ],
    "wof:name":"Kampung Temiang",
    "wof:placetype":"locality"
},
  "geometry": {"coordinates":[102.59050000000001,2.0851],"type":"Point"}
}