{
  "type": "Feature",
  "properties": {
    "gn:admin1_code":"2",
    "gn:asciiname":"Kampung Charok Pendiat",
    "gn:cc2":"MY",
    "gn:country_code":"MY",
    "gn:dem":99,
    "gn:feature_class":"P",
    "gn:feature_code":"PPL",
    "gn:name":"Kampung Charok Pendiat",
    "gn:population":0,
    "gn:timezone":"Asia/Kuala_Lumpur",
    "iso:country":"MY",
    "name:msa_x_preferred":[
        "Kampung Charok Pendiat"
    ],
    "name:und_x_variant":[
        "Kampong Charok Pendiat"
    ],
    "wof:name":"Kampung Charok Pendiat",
    "wof:placetype":"locality"
},
  "geometry": {"coordinates":[100.9117,5.54564],"type":"Point"}
}