{
  "type": "Feature",
  "properties": {
    "gn:admin1_code":"16.0",
    "gn:asciiname":"Bukit Geram",
    "gn:country_code":"MY",
    "gn:dem":22,
    "gn:feature_class":"P",
    "gn:feature_code":"PPL",
    "gn:name":"Bukit Geram",
    "gn:population":0,
    "gn:timezone":"Asia/Kuching",
    "iso:country":"MY",
    "name:msa_x_preferred":[
        "Bukit Geram"
    ],
    "name:und_x_variant":[
        "Bukit Garam"
    ],
    "wof:name":"Bukit Geram",
    "wof:placetype":"locality"
},
  "geometry": {"coordinates":[117.8335,5.4935],"type":"Point"}
}