{
  "type": "Feature",
  "properties": {
    "gn:admin1_code":"5.0",
    "gn:asciiname":"Kampung Ulu Sungai Dua Besar",
    "gn:country_code":"MY",
    "gn:dem":140,
    "gn:feature_class":"P",
    "gn:feature_code":"PPL",
    "gn:name":"Kampung Ulu Sungai Dua Besar",
    "gn:population":0,
    "gn:timezone":"Asia/Kuala_Lumpur",
    "iso:country":"MY",
    "name:msa_x_preferred":[
        "Kampung Ulu Sungai Dua Besar"
    ],
    "wof:name":"Kampung Ulu Sungai Dua Besar",
    "wof:placetype":"locality"
},
  "geometry": {"coordinates":[102.2873,2.7239],"type":"Point"}
}