{
  "type": "Feature",
  "properties": {
    "gn:admin1_code":"11",
    "gn:asciiname":"Kampong Tebia Kiding",
    "gn:country_code":"MY",
    "gn:dem":171,
    "gn:feature_class":"P",
    "gn:feature_code":"PPL",
    "gn:name":"Kampong Tebia Kiding",
    "gn:population":0,
    "gn:timezone":"Asia/Kuching",
    "iso:country":"MY",
    "name:und_x_variant":[
        "Kampong Kiding",
        "Kampong Tebia Kiding"
    ],
    "wof:name":"Kampong Tebia Kiding",
    "wof:placetype":"locality"
},
  "geometry": {"coordinates":[110.21547,1.19853],"type":"Point"}
}