{
  "type": "Feature",
  "properties": {
    "gn:admin1_code":"16",
    "gn:asciiname":"Kampung Karang",
    "gn:country_code":"MY",
    "gn:dem":8,
    "gn:feature_class":"P",
    "gn:feature_code":"PPL",
    "gn:name":"Kampung Karang",
    "gn:population":0,
    "gn:timezone":"Asia/Kuching",
    "iso:country":"MY",
    "name:msa_x_preferred":[
        "Kampung Karang"
    ],
    "name:und_x_variant":[
        "Kampong Karang"
    ],
    "wof:name":"Kampung Karang",
    "wof:placetype":"locality"
},
  "geometry": {"coordinates":[116.0359,5.8315],"type":"Point"}
}