{
  "type": "Feature",
  "properties": {
    "gn:admin1_code":"16.0",
    "gn:asciiname":"Limpada",
    "gn:country_code":"MY",
    "gn:dem":155,
    "gn:feature_class":"P",
    "gn:feature_code":"PPL",
    "gn:name":"Limpada",
    "gn:population":0,
    "gn:timezone":"Asia/Kuching",
    "iso:country":"MY",
    "wof:name":"Limpada",
    "wof:placetype":"locality"
},
  "geometry": {"coordinates":[116.72006,5.2232],"type":"Point"}
}