{
  "type": "Feature",
  "properties": {
    "iso:country":"MY",
    "qs:name":"Bandar Bt. Mertajam",
    "qs:name_adm0":"Malaysia",
    "qs:name_adm1":"Pulau Pinang",
    "qs:photos":8,
    "qs:photos_1k":2,
    "qs:photos_9k":2,
    "qs:photos_9r":5,
    "qs:photos_all":505,
    "qs:photos_sr":1,
    "qs:placetype":"LocalAdmin",
    "qs:pop_sr":"0",
    "wof:name":"Bandar Bt. Mertajam",
    "wof:placetype":"localadmin"
},
  "geometry": {"coordinates":[100.46258899999999,5.36137],"type":"Point"}
}