{
  "type": "Feature",
  "properties": {
    "gn:admin1_code":"6.0",
    "gn:asciiname":"Kemajuan Tanah Tembangau",
    "gn:country_code":"MY",
    "gn:dem":52,
    "gn:feature_class":"P",
    "gn:feature_code":"PPL",
    "gn:name":"Kemajuan Tanah Tembangau",
    "gn:population":0,
    "gn:timezone":"Asia/Kuala_Lumpur",
    "iso:country":"MY",
    "name:msa_x_preferred":[
        "Kemajuan Tanah Tembangau"
    ],
    "wof:name":"Kemajuan Tanah Tembangau",
    "wof:placetype":"locality"
},
  "geometry": {"coordinates":[102.5228,3.0321],"type":"Point"}
}