{
  "type": "Feature",
  "properties": {
    "gn:admin1_code":"13",
    "gn:asciiname":"Kampung Amir",
    "gn:cc2":"MY",
    "gn:country_code":"MY",
    "gn:dem":12,
    "gn:feature_class":"P",
    "gn:feature_code":"PPL",
    "gn:name":"Kampung Amir",
    "gn:population":0,
    "gn:timezone":"Asia/Kuala_Lumpur",
    "iso:country":"MY",
    "name:msa_x_preferred":[
        "Kampong Amir"
    ],
    "name:msa_x_variant":[
        "Kampung Amir"
    ],
    "wof:name":"Kampung Amir",
    "wof:placetype":"locality"
},
  "geometry": {"coordinates":[102.53859,5.78525],"type":"Point"}
}