{
  "type": "Feature",
  "properties": {
    "gn:admin1_code":"5",
    "gn:asciiname":"Kampung Batu Lapan",
    "gn:country_code":"MY",
    "gn:dem":53,
    "gn:feature_class":"P",
    "gn:feature_code":"PPL",
    "gn:name":"Kampung Batu Lapan",
    "gn:population":0,
    "gn:timezone":"Asia/Kuala_Lumpur",
    "iso:country":"MY",
    "name:msa_x_preferred":[
        "Kampung Batu Lapan"
    ],
    "name:und_x_variant":[
        "Kampong Batu Lapan"
    ],
    "wof:name":"Kampung Batu Lapan",
    "wof:placetype":"locality"
},
  "geometry": {"coordinates":[101.85639999999999,2.7419],"type":"Point"}
}