{
  "type": "Feature",
  "properties": {
    "gn:admin1_code":"16",
    "gn:asciiname":"Kampung Menedai",
    "gn:country_code":"MY",
    "gn:dem":132,
    "gn:feature_class":"P",
    "gn:feature_code":"PPL",
    "gn:name":"Kampung Menedai",
    "gn:population":0,
    "gn:timezone":"Asia/Kuching",
    "iso:country":"MY",
    "name:msa_x_preferred":[
        "Kampung Menedai"
    ],
    "name:und_x_variant":[
        "Kampong Menedai"
    ],
    "wof:name":"Kampung Menedai",
    "wof:placetype":"locality"
},
  "geometry": {"coordinates":[116.917,6.1718],"type":"Point"}
}