{
  "type": "Feature",
  "properties": {
    "gn:gn_country":"MY",
    "gn:gn_fcode":"PPL",
    "gn:gn_pop":0,
    "iso:country":"MY",
    "name:deu_x_preferred":[
        "Changkat Keruing"
    ],
    "name:eng_x_preferred":[
        "Changkat Keruing"
    ],
    "name:fra_x_preferred":[
        "Changkat Keruing"
    ],
    "name:ind_x_preferred":[
        "Changkat Keruing"
    ],
    "name:msa_x_preferred":[
        "Kampung Cangkat Keruing"
    ],
    "name:msa_x_variant":[
        "Changkat Keruing"
    ],
    "name:nld_x_preferred":[
        "Changkat Keruing"
    ],
    "name:unk_x_variant":[
        "Changkat Kruing"
    ],
    "qs_pg:aaroncc":"MY",
    "qs_pg:gn_country":"MY",
    "qs_pg:gn_fcode":"PPL",
    "qs_pg:gn_pop":0,
    "qs_pg:name":"Kampong Changkat Keruing",
    "qs_pg:name_adm0":"Malaysia",
    "qs_pg:name_adm1":"Perak",
    "qs_pg:photos_9k":1,
    "qs_pg:photos_9r":1,
    "qs_pg:photos_all":14,
    "qs_pg:photos_sr":0,
    "qs_pg:pop_sr":5,
    "qs_pg:qs_pg_placetype":"locality",
    "qs_pg:qs_pg_placetype_gp":"Town",
    "qs_pg:woe_adm0":23424901,
    "woe:adm0_id":23424901,
    "woe:name_adm0":"Malaysia",
    "woe:name_adm1":"Perak",
    "woe:placetype":"Town",
    "wof:name":"Kampong Changkat Keruing",
    "wof:placetype":"locality"
},
  "geometry": {"coordinates":[100.6891,4.3775],"type":"Point"}
}