{
  "type": "Feature",
  "properties": {
    "gn:admin1_code":"7.0",
    "gn:asciiname":"Taman Desa Melintang Baru",
    "gn:country_code":"MY",
    "gn:dem":5,
    "gn:feature_class":"P",
    "gn:feature_code":"PPL",
    "gn:name":"Taman Desa Melintang Baru",
    "gn:population":0,
    "gn:timezone":"Asia/Kuala_Lumpur",
    "iso:country":"MY",
    "name:msa_x_preferred":[
        "Taman Desa Melintang Baru"
    ],
    "wof:name":"Taman Desa Melintang Baru",
    "wof:placetype":"locality"
},
  "geometry": {"coordinates":[100.9367,3.8855],"type":"Point"}
}