{
  "type": "Feature",
  "properties": {
    "gn:admin1_code":"1",
    "gn:asciiname":"Kampung Serpang",
    "gn:country_code":"MY",
    "gn:dem":13,
    "gn:feature_class":"P",
    "gn:feature_code":"PPL",
    "gn:name":"Kampung Serpang",
    "gn:population":0,
    "gn:timezone":"Asia/Kuala_Lumpur",
    "iso:country":"MY",
    "name:msa_x_preferred":[
        "Kampung Serpang"
    ],
    "name:und_x_variant":[
        "Kampong Serpang"
    ],
    "wof:name":"Kampung Serpang",
    "wof:placetype":"locality"
},
  "geometry": {"coordinates":[102.6407,2.122],"type":"Point"}
}