{
  "type": "Feature",
  "properties": {
    "gn:admin1_code":"3.0",
    "gn:asciiname":"Kampung Tunku Abdul Rahman",
    "gn:country_code":"MY",
    "gn:dem":59,
    "gn:feature_class":"P",
    "gn:feature_code":"PPL",
    "gn:name":"Kampung Tunku Abdul Rahman",
    "gn:population":0,
    "gn:timezone":"Asia/Kuala_Lumpur",
    "iso:country":"MY",
    "name:msa_x_preferred":[
        "Kampung Tunku Abdul Rahman"
    ],
    "wof:name":"Kampung Tunku Abdul Rahman",
    "wof:placetype":"locality"
},
  "geometry": {"coordinates":[101.9145,5.4443],"type":"Point"}
}