{
  "type": "Feature",
  "properties": {
    "gn:admin1_code":"16.0",
    "gn:asciiname":"Polar",
    "gn:country_code":"MY",
    "gn:dem":15,
    "gn:feature_class":"P",
    "gn:feature_code":"PPL",
    "gn:name":"Polar",
    "gn:population":0,
    "gn:timezone":"Asia/Kuching",
    "iso:country":"MY",
    "name:cat_x_preferred":[
        "Polar"
    ],
    "name:ces_x_preferred":[
        "Pol\u00e1rn\u00ed"
    ],
    "name:deu_x_preferred":[
        "Polar"
    ],
    "name:eus_x_preferred":[
        "Polar"
    ],
    "name:fin_x_preferred":[
        "Polar"
    ],
    "name:fra_x_preferred":[
        "Polar"
    ],
    "name:hun_x_preferred":[
        "Polar"
    ],
    "name:ita_x_preferred":[
        "Polar"
    ],
    "name:jpn_x_preferred":[
        "Polar"
    ],
    "name:msa_x_preferred":[
        "Polar"
    ],
    "name:nld_x_preferred":[
        "Polar"
    ],
    "name:nno_x_preferred":[
        "Polar"
    ],
    "name:nor_x_preferred":[
        "Polar"
    ],
    "name:pol_x_preferred":[
        "Polar"
    ],
    "name:por_x_preferred":[
        "Polar"
    ],
    "name:spa_x_preferred":[
        "Polar"
    ],
    "name:swe_x_preferred":[
        "Polar"
    ],
    "wof:name":"Polar",
    "wof:placetype":"locality"
},
  "geometry": {"coordinates":[115.7259,5.3564],"type":"Point"}
}