{
  "type": "Feature",
  "properties": {
    "gn:admin1_code":"16.0",
    "gn:asciiname":"Polar",
    "gn:country_code":"MY",
    "gn:dem":15,
    "gn:feature_class":"P",
    "gn:feature_code":"PPL",
    "gn:name":"Polar",
    "gn:population":0,
    "gn:timezone":"Asia/Kuching",
    "iso:country":"MY",
    "name:msa_x_preferred":[
        "Polar"
    ],
    "wof:name":"Polar",
    "wof:placetype":"locality"
},
  "geometry": {"coordinates":[115.7259,5.3564],"type":"Point"}
}