{
  "type": "Feature",
  "properties": {
    "gn:admin1_code":"16",
    "gn:asciiname":"Ouluk",
    "gn:country_code":"MY",
    "gn:dem":191,
    "gn:feature_class":"P",
    "gn:feature_code":"PPL",
    "gn:name":"Ouluk",
    "gn:population":0,
    "gn:timezone":"Asia/Kuching",
    "iso:country":"MY",
    "wof:name":"Ouluk",
    "wof:placetype":"locality"
},
  "geometry": {"coordinates":[115.98333,5.18333],"type":"Point"}
}