{
  "type": "Feature",
  "properties": {
    "gn:admin1_code":"12.0",
    "gn:asciiname":"Taman Murni",
    "gn:country_code":"MY",
    "gn:dem":7,
    "gn:feature_class":"P",
    "gn:feature_code":"PPL",
    "gn:name":"Taman Murni",
    "gn:population":0,
    "gn:timezone":"Asia/Kuala_Lumpur",
    "iso:country":"MY",
    "name:msa_x_preferred":[
        "Taman Murni"
    ],
    "wof:name":"Taman Murni",
    "wof:placetype":"locality"
},
  "geometry": {"coordinates":[101.75,2.6831],"type":"Point"}
}