{
  "type": "Feature",
  "properties": {
    "gn:admin1_code":"16.0",
    "gn:asciiname":"Kampung Tanjung Aru",
    "gn:country_code":"MY",
    "gn:dem":9,
    "gn:feature_class":"P",
    "gn:feature_code":"PPL",
    "gn:name":"Kampung Tanjung Aru",
    "gn:population":0,
    "gn:timezone":"Asia/Kuching",
    "iso:country":"MY",
    "name:msa_x_preferred":[
        "Kampung Tanjung Aru"
    ],
    "name:und_x_variant":[
        "Kampong Tanjong Aru",
        "Aru Tangong",
        "Tanjong Aru Town",
        "Tanjong Aru"
    ],
    "wof:name":"Kampung Tanjung Aru",
    "wof:placetype":"locality"
},
  "geometry": {"coordinates":[116.0528,5.9569],"type":"Point"}
}