{
  "type": "Feature",
  "properties": {
    "gn:admin1_code":"11",
    "gn:asciiname":"Rumah Inting",
    "gn:country_code":"MY",
    "gn:dem":0,
    "gn:feature_class":"P",
    "gn:feature_code":"PPL",
    "gn:name":"Rumah Inting",
    "gn:population":0,
    "gn:timezone":"Asia/Kuching",
    "iso:country":"MY",
    "wof:name":"Rumah Inting",
    "wof:placetype":"locality"
},
  "geometry": {"coordinates":[111.88333,2.23333],"type":"Point"}
}