{
  "type": "Feature",
  "properties": {
    "gn:admin1_code":"4.0",
    "gn:asciiname":"Solok Paya Meranti",
    "gn:country_code":"MY",
    "gn:dem":25,
    "gn:feature_class":"P",
    "gn:feature_code":"PPL",
    "gn:name":"Solok Paya Meranti",
    "gn:population":0,
    "gn:timezone":"Asia/Kuala_Lumpur",
    "iso:country":"MY",
    "name:msa_x_preferred":[
        "Solok Paya Meranti"
    ],
    "wof:name":"Solok Paya Meranti",
    "wof:placetype":"locality"
},
  "geometry": {"coordinates":[102.3571,2.2082],"type":"Point"}
}