{
  "type": "Feature",
  "properties": {
    "gn:admin1_code":"5",
    "gn:asciiname":"Kampung Sawah",
    "gn:country_code":"MY",
    "gn:dem":14,
    "gn:feature_class":"P",
    "gn:feature_code":"PPL",
    "gn:name":"Kampung Sawah",
    "gn:population":0,
    "gn:timezone":"Asia/Kuala_Lumpur",
    "iso:country":"MY",
    "name:msa_x_preferred":[
        "Kampung Sawah"
    ],
    "name:und_x_variant":[
        "Kampong Sawah"
    ],
    "wof:name":"Kampung Sawah",
    "wof:placetype":"locality"
},
  "geometry": {"coordinates":[101.7595,2.6285],"type":"Point"}
}