{
  "type": "Feature",
  "properties": {
    "gn:admin1_code":"2",
    "gn:asciiname":"Simpang Empat Sungai Limau",
    "gn:country_code":"MY",
    "gn:dem":8,
    "gn:feature_class":"P",
    "gn:feature_code":"PPL",
    "gn:name":"Simpang Empat Sungai Limau",
    "gn:population":0,
    "gn:timezone":"Asia/Kuala_Lumpur",
    "iso:country":"MY",
    "name:und_x_variant":[
        "Simpang Ampat",
        "Simpang Empat",
        "Simpang Empat Sungai Limau"
    ],
    "wof:name":"Simpang Empat Sungai Limau",
    "wof:placetype":"locality"
},
  "geometry": {"coordinates":[100.37868,5.8966],"type":"Point"}
}