{
  "type": "Feature",
  "properties": {
    "gn:admin1_code":"8",
    "gn:asciiname":"Kampung Behor Kurong Ayam",
    "gn:cc2":"MY",
    "gn:country_code":"MY",
    "gn:dem":6,
    "gn:feature_class":"P",
    "gn:feature_code":"PPL",
    "gn:name":"Kampung Behor Kurong Ayam",
    "gn:population":0,
    "gn:timezone":"Asia/Kuala_Lumpur",
    "iso:country":"MY",
    "name:msa_x_preferred":[
        "Kampung Behor Kurong Ayam"
    ],
    "name:und_x_variant":[
        "Kampong Behor"
    ],
    "wof:name":"Kampung Behor Kurong Ayam",
    "wof:placetype":"locality"
},
  "geometry": {"coordinates":[100.26537,6.43516],"type":"Point"}
}