{
  "type": "Feature",
  "properties": {
    "gn:admin1_code":"6.0",
    "gn:asciiname":"Kampung Permatang Lembing",
    "gn:country_code":"MY",
    "gn:dem":14,
    "gn:feature_class":"P",
    "gn:feature_code":"PPL",
    "gn:name":"Kampung Permatang Lembing",
    "gn:population":0,
    "gn:timezone":"Asia/Kuala_Lumpur",
    "iso:country":"MY",
    "name:msa_x_preferred":[
        "Kampung Permatang Lembing"
    ],
    "wof:name":"Kampung Permatang Lembing",
    "wof:placetype":"locality"
},
  "geometry": {"coordinates":[103.4015,3.4667],"type":"Point"}
}