{
  "type": "Feature",
  "properties": {
    "iso:country":"MY",
    "name:eng_x_preferred":[
        "Pantai Aceh"
    ],
    "name:epo_x_preferred":[
        "Pantai Aceh"
    ],
    "name:msa_x_preferred":[
        "Taman Koperasi"
    ],
    "name:msa_x_variant":[
        "Pantai Aceh"
    ],
    "qs:name":"Pantai Acheh",
    "qs:name_adm0":"Malaysia",
    "qs:name_adm1":"Pulau Pinang",
    "qs:photos":71,
    "qs:photos_1k":14,
    "qs:photos_9k":1,
    "qs:photos_9r":2,
    "qs:photos_all":71,
    "qs:photos_sr":2,
    "qs:placetype":"Town",
    "qs:pop_sr":"0",
    "wd:wordcount":269,
    "wof:name":"Pantai Acheh",
    "wof:placetype":"locality"
},
  "geometry": {"coordinates":[100.217456,5.421519],"type":"Point"}
}