{
  "type": "Feature",
  "properties": {
    "gn:admin1_code":"1.0",
    "gn:asciiname":"Ladang Pengkalan Bukit",
    "gn:country_code":"MY",
    "gn:dem":21,
    "gn:feature_class":"P",
    "gn:feature_code":"PPL",
    "gn:name":"Ladang Pengkalan Bukit",
    "gn:population":0,
    "gn:timezone":"Asia/Kuala_Lumpur",
    "iso:country":"MY",
    "name:msa_x_preferred":[
        "Ladang Pengkalan Bukit"
    ],
    "wof:name":"Ladang Pengkalan Bukit",
    "wof:placetype":"locality"
},
  "geometry": {"coordinates":[102.74299999999999,2.1266],"type":"Point"}
}