{
  "type": "Feature",
  "properties": {
    "iso:country":"MY",
    "qs:name":"Canglun",
    "qs:name_adm0":"Malaysia",
    "qs:name_adm1":"Kedah",
    "qs:photos":130,
    "qs:photos_1k":26,
    "qs:photos_9k":1,
    "qs:photos_9r":3,
    "qs:photos_all":130,
    "qs:photos_sr":3,
    "qs:placetype":"Town",
    "qs:pop_sr":"0",
    "wof:name":"Canglun",
    "wof:placetype":"locality"
},
  "geometry": {"coordinates":[100.44108799999999,6.4370315],"type":"Point"}
}