{
  "type": "Feature",
  "properties": {
    "gn:admin1_code":"13",
    "gn:asciiname":"Kampung Sungai Bari",
    "gn:country_code":"MY",
    "gn:dem":17,
    "gn:feature_class":"P",
    "gn:feature_code":"PPL",
    "gn:name":"Kampung Sungai Bari",
    "gn:population":0,
    "gn:timezone":"Asia/Kuala_Lumpur",
    "iso:country":"MY",
    "name:msa_x_preferred":[
        "Kampung Sungai Bari"
    ],
    "name:und_x_variant":[
        "Kampong Sungai Bari"
    ],
    "wof:name":"Kampung Sungai Bari",
    "wof:placetype":"locality"
},
  "geometry": {"coordinates":[102.85599999999999,5.4066],"type":"Point"}
}