{
  "type": "Feature",
  "properties": {
    "gn:admin1_code":"16.0",
    "gn:asciiname":"Kampung Kabanau",
    "gn:country_code":"MY",
    "gn:dem":15,
    "gn:feature_class":"P",
    "gn:feature_code":"PPL",
    "gn:name":"Kampung Kabanau",
    "gn:population":0,
    "gn:timezone":"Asia/Kuching",
    "iso:country":"MY",
    "name:msa_x_preferred":[
        "Kampung Kabanau"
    ],
    "wof:name":"Kampung Kabanau",
    "wof:placetype":"locality"
},
  "geometry": {"coordinates":[115.6122,5.3756],"type":"Point"}
}