{
  "type": "Feature",
  "properties": {
    "iso:country":"MY",
    "qs:name":"Terachi",
    "qs:name_adm0":"Malaysia",
    "qs:name_adm1":"Negeri Sembilan",
    "qs:photos":26,
    "qs:photos_1k":5,
    "qs:photos_9k":1,
    "qs:photos_9r":2,
    "qs:photos_all":26,
    "qs:photos_sr":2,
    "qs:placetype":"Town",
    "qs:pop_sr":"0",
    "wof:name":"Terachi",
    "wof:placetype":"locality"
},
  "geometry": {"coordinates":[102.16564099999999,2.74313],"type":"Point"}
}