{
  "type": "Feature",
  "properties": {
    "gn:admin1_code":"13",
    "gn:asciiname":"Kampung Batu Itik",
    "gn:country_code":"MY",
    "gn:dem":14,
    "gn:feature_class":"P",
    "gn:feature_code":"PPL",
    "gn:name":"Kampung Batu Itik",
    "gn:population":0,
    "gn:timezone":"Asia/Kuala_Lumpur",
    "iso:country":"MY",
    "name:msa_x_preferred":[
        "Kampung Batu Itik"
    ],
    "name:und_x_variant":[
        "Kampong Batu Itek"
    ],
    "wof:name":"Kampung Batu Itik",
    "wof:placetype":"locality"
},
  "geometry": {"coordinates":[103.1426,5.1148],"type":"Point"}
}