{
  "type": "Feature",
  "properties": {
    "gn:admin1_code":"1.0",
    "gn:asciiname":"Taman Nasib",
    "gn:country_code":"MY",
    "gn:dem":32,
    "gn:feature_class":"P",
    "gn:feature_code":"PPL",
    "gn:name":"Taman Nasib",
    "gn:population":0,
    "gn:timezone":"Asia/Kuala_Lumpur",
    "iso:country":"MY",
    "name:msa_x_preferred":[
        "Taman Nasib"
    ],
    "wof:name":"Taman Nasib",
    "wof:placetype":"locality"
},
  "geometry": {"coordinates":[103.342,2.0471],"type":"Point"}
}