{
  "type": "Feature",
  "properties": {
    "gn:admin1_code":"3",
    "gn:asciiname":"Kampong Naga Ibu",
    "gn:country_code":"MY",
    "gn:dem":7,
    "gn:feature_class":"P",
    "gn:feature_code":"PPL",
    "gn:name":"Kampong Naga Ibu",
    "gn:population":0,
    "gn:timezone":"Asia/Kuala_Lumpur",
    "iso:country":"MY",
    "name:und_x_variant":[
        "Kampong Nakho-Iyu",
        "Kampong Nakoibu",
        "Kampong Nakho-Ibu",
        "Kampong Naga Jbu",
        "Kampong Naga Ibu"
    ],
    "wof:name":"Kampong Naga Ibu",
    "wof:placetype":"locality"
},
  "geometry": {"coordinates":[102.08591,6.16128],"type":"Point"}
}