{
  "type": "Feature",
  "properties": {
    "gn:admin1_code":"16",
    "gn:asciiname":"Kampung Tajau",
    "gn:country_code":"MY",
    "gn:dem":79,
    "gn:feature_class":"P",
    "gn:feature_code":"PPL",
    "gn:name":"Kampung Tajau",
    "gn:population":0,
    "gn:timezone":"Asia/Kuching",
    "iso:country":"MY",
    "name:msa_x_preferred":[
        "Kampung Tajau"
    ],
    "name:und_x_variant":[
        "Tajau"
    ],
    "wof:name":"Kampung Tajau",
    "wof:placetype":"locality"
},
  "geometry": {"coordinates":[116.78585,6.94731],"type":"Point"}
}