{
  "type": "Feature",
  "properties": {
    "gn:admin1_code":"5.0",
    "gn:asciiname":"Kampung Baharu Ulu Bayai",
    "gn:country_code":"MY",
    "gn:dem":109,
    "gn:feature_class":"P",
    "gn:feature_code":"PPL",
    "gn:name":"Kampung Baharu Ulu Bayai",
    "gn:population":0,
    "gn:timezone":"Asia/Kuala_Lumpur",
    "iso:country":"MY",
    "name:msa_x_preferred":[
        "Kampung Baharu Ulu Bayai"
    ],
    "wof:name":"Kampung Baharu Ulu Bayai",
    "wof:placetype":"locality"
},
  "geometry": {"coordinates":[102.2843,2.8898],"type":"Point"}
}