{
  "type": "Feature",
  "properties": {
    "gn:country":"MY",
    "gn:fcode":"PPL",
    "gn:population":0,
    "iso:country":"MY",
    "name:msa_x_preferred":[
        "Kampung Setol"
    ],
    "qs:name":"Kampung Setol",
    "qs:name_adm0":"Malaysia",
    "qs:name_adm1":"Pulau Pinang",
    "qs:photos_9r":0,
    "qs:photos_sr":0,
    "qs:placetype":"Town",
    "qs:pop_sr":"0",
    "wof:name":"Kampung Setol",
    "wof:placetype":"locality",
    "wof:population":0
},
  "geometry": {"coordinates":[100.39155,5.79871],"type":"Point"}
}