{
  "type": "Feature",
  "properties": {
    "gn:admin1_code":"16.0",
    "gn:asciiname":"Bilai",
    "gn:cc2":"MY",
    "gn:country_code":"MY",
    "gn:dem":41,
    "gn:feature_class":"P",
    "gn:feature_code":"PPL",
    "gn:name":"Bilai",
    "gn:population":0,
    "gn:timezone":"Asia/Kuching",
    "iso:country":"MY",
    "name:und_x_variant":[
        "Kampong Bilai"
    ],
    "wof:name":"Bilai",
    "wof:placetype":"locality"
},
  "geometry": {"coordinates":[117.21666999999999,5.78333],"type":"Point"}
}