{
  "type": "Feature",
  "properties": {
    "gn:admin1_code":"5",
    "gn:asciiname":"Kampung Cheluteh",
    "gn:country_code":"MY",
    "gn:dem":76,
    "gn:feature_class":"P",
    "gn:feature_code":"PPL",
    "gn:name":"Kampung Cheluteh",
    "gn:population":0,
    "gn:timezone":"Asia/Kuala_Lumpur",
    "iso:country":"MY",
    "name:und_x_variant":[
        "Kampong Chelugeh"
    ],
    "wof:name":"Kampung Cheluteh",
    "wof:placetype":"locality"
},
  "geometry": {"coordinates":[101.94047999999999,2.89581],"type":"Point"}
}