{
  "type": "Feature",
  "properties": {
    "gn:admin1_code":"2",
    "gn:asciiname":"Kampung Pondok Labu",
    "gn:cc2":"MY",
    "gn:country_code":"MY",
    "gn:dem":22,
    "gn:feature_class":"P",
    "gn:feature_code":"PPL",
    "gn:name":"Kampung Pondok Labu",
    "gn:population":0,
    "gn:timezone":"Asia/Kuala_Lumpur",
    "iso:country":"MY",
    "name:msa_x_preferred":[
        "Kampung Pondok Labu"
    ],
    "name:und_x_variant":[
        "Kampong Pandok Labu"
    ],
    "wof:name":"Kampung Pondok Labu",
    "wof:placetype":"locality"
},
  "geometry": {"coordinates":[100.53645,5.38947],"type":"Point"}
}