{
  "type": "Feature",
  "properties": {
    "gn:admin1_code":"5.0",
    "gn:asciiname":"Kampung Minching",
    "gn:country_code":"MY",
    "gn:dem":57,
    "gn:feature_class":"P",
    "gn:feature_code":"PPL",
    "gn:name":"Kampung Minching",
    "gn:population":0,
    "gn:timezone":"Asia/Kuala_Lumpur",
    "iso:country":"MY",
    "name:msa_x_preferred":[
        "Kampung Minching"
    ],
    "wof:name":"Kampung Minching",
    "wof:placetype":"locality"
},
  "geometry": {"coordinates":[102.0564,2.5771],"type":"Point"}
}