{
  "type": "Feature",
  "properties": {
    "gn:admin1_code":"16.0",
    "gn:asciiname":"Kampung Ulu Kota Klias",
    "gn:country_code":"MY",
    "gn:dem":12,
    "gn:feature_class":"P",
    "gn:feature_code":"PPL",
    "gn:name":"Kampung Ulu Kota Klias",
    "gn:population":0,
    "gn:timezone":"Asia/Kuching",
    "iso:country":"MY",
    "name:msa_x_preferred":[
        "Kampung Ulu Kota Klias"
    ],
    "wof:name":"Kampung Ulu Kota Klias",
    "wof:placetype":"locality"
},
  "geometry": {"coordinates":[115.6446,5.4473],"type":"Point"}
}