{
  "type": "Feature",
  "properties": {
    "iso:country":"MY",
    "qs:name":"Taman Tasik Taiping",
    "qs:name_adm0":"Malaysia",
    "qs:name_adm1":"Perak",
    "qs:photos":340,
    "qs:photos_1k":69,
    "qs:photos_9k":2,
    "qs:photos_9r":5,
    "qs:photos_all":340,
    "qs:photos_sr":5,
    "qs:placetype":"Town",
    "qs:pop_sr":"0",
    "wof:name":"Taman Tasik Taiping",
    "wof:placetype":"locality"
},
  "geometry": {"coordinates":[100.747933,4.857252],"type":"Point"}
}