{
  "type": "Feature",
  "properties": {
    "gn:admin1_code":"5",
    "gn:asciiname":"Tanjung Melintang",
    "gn:country_code":"MY",
    "gn:dem":229,
    "gn:feature_class":"P",
    "gn:feature_code":"PPL",
    "gn:name":"Tanjung Melintang",
    "gn:population":0,
    "gn:timezone":"Asia/Kuala_Lumpur",
    "iso:country":"MY",
    "name:msa_x_preferred":[
        "Tanjung Melintang"
    ],
    "name:und_x_variant":[
        "Tanjong Melintang"
    ],
    "wof:name":"Tanjung Melintang",
    "wof:placetype":"locality"
},
  "geometry": {"coordinates":[102.053,2.8974],"type":"Point"}
}