{
  "type": "Feature",
  "properties": {
    "gn:admin1_code":"1",
    "gn:asciiname":"Kampung Lapis Jiden",
    "gn:country_code":"MY",
    "gn:dem":10,
    "gn:feature_class":"P",
    "gn:feature_code":"PPL",
    "gn:name":"Kampung Lapis Jiden",
    "gn:population":0,
    "gn:timezone":"Asia/Kuala_Lumpur",
    "iso:country":"MY",
    "name:msa_x_preferred":[
        "Kampung Lapis Jiden"
    ],
    "name:und_x_variant":[
        "Kampong Lapis Jiden"
    ],
    "wof:name":"Kampung Lapis Jiden",
    "wof:placetype":"locality"
},
  "geometry": {"coordinates":[102.8862,1.9857],"type":"Point"}
}