{
  "type": "Feature",
  "properties": {
    "iso:country":"MY",
    "qs:name":"Taman Maja Jaya",
    "qs:name_adm0":"Malaysia",
    "qs:name_adm1":"Selangor",
    "qs:photos":1,
    "qs:photos_1k":1,
    "qs:photos_9k":1,
    "qs:photos_9r":1,
    "qs:photos_all":1,
    "qs:photos_sr":1,
    "qs:placetype":"Suburb",
    "qs:pop_sr":"0",
    "wof:name":"Taman Maja Jaya",
    "wof:placetype":"neighbourhood"
},
  "geometry": {"coordinates":[101.7508,3.156285],"type":"Point"}
}