{
  "type": "Feature",
  "properties": {
    "gn:admin1_code":"3.0",
    "gn:asciiname":"Kampung Baharu Mek Mas",
    "gn:country_code":"MY",
    "gn:dem":9,
    "gn:feature_class":"P",
    "gn:feature_code":"PPL",
    "gn:name":"Kampung Baharu Mek Mas",
    "gn:population":0,
    "gn:timezone":"Asia/Kuala_Lumpur",
    "iso:country":"MY",
    "name:msa_x_preferred":[
        "Kampung Baharu Mek Mas"
    ],
    "wof:name":"Kampung Baharu Mek Mas",
    "wof:placetype":"locality"
},
  "geometry": {"coordinates":[102.2383,6.21437],"type":"Point"}
}