{
  "type": "Feature",
  "properties": {
    "gn:admin1_code":"6",
    "gn:asciiname":"Kampung Gumai",
    "gn:country_code":"MY",
    "gn:dem":57,
    "gn:feature_class":"P",
    "gn:feature_code":"PPL",
    "gn:name":"Kampung Gumai",
    "gn:population":0,
    "gn:timezone":"Asia/Kuala_Lumpur",
    "iso:country":"MY",
    "name:msa_x_preferred":[
        "Kampung Gumai"
    ],
    "name:und_x_variant":[
        "Kampong Gumai"
    ],
    "wof:name":"Kampung Gumai",
    "wof:placetype":"locality"
},
  "geometry": {"coordinates":[102.5659,3.4676],"type":"Point"}
}