{
  "type": "Feature",
  "properties": {
    "iso:country":"MY",
    "qs:name":"Bagan Tiang",
    "qs:name_adm0":"Malaysia",
    "qs:name_adm1":"Perak",
    "qs:photos":1,
    "qs:photos_1k":1,
    "qs:photos_9k":1,
    "qs:photos_9r":2,
    "qs:photos_all":62,
    "qs:photos_sr":1,
    "qs:placetype":"LocalAdmin",
    "qs:pop_sr":"0",
    "wof:name":"Bagan Tiang",
    "wof:placetype":"localadmin"
},
  "geometry": {"coordinates":[100.38002,5.079317],"type":"Point"}
}