{
  "type": "Feature",
  "properties": {
    "gn:admin1_code":"6",
    "gn:asciiname":"Kampung Makit",
    "gn:country_code":"MY",
    "gn:dem":120,
    "gn:feature_class":"P",
    "gn:feature_code":"PPL",
    "gn:name":"Kampung Makit",
    "gn:population":0,
    "gn:timezone":"Asia/Kuala_Lumpur",
    "iso:country":"MY",
    "name:und_x_variant":[
        "Kampong Makit"
    ],
    "wof:name":"Kampung Makit",
    "wof:placetype":"locality"
},
  "geometry": {"coordinates":[102.10907,4.3566],"type":"Point"}
}