{
  "type": "Feature",
  "properties": {
    "gn:admin1_code":"1",
    "gn:asciiname":"Kampung Bakek",
    "gn:country_code":"MY",
    "gn:dem":7,
    "gn:feature_class":"P",
    "gn:feature_code":"PPL",
    "gn:name":"Kampung Bakek",
    "gn:population":0,
    "gn:timezone":"Asia/Kuala_Lumpur",
    "iso:country":"MY",
    "name:msa_x_preferred":[
        "Kampung Bakek"
    ],
    "name:und_x_variant":[
        "Kampong Bakek"
    ],
    "wof:name":"Kampung Bakek",
    "wof:placetype":"locality"
},
  "geometry": {"coordinates":[103.39319999999999,1.4801],"type":"Point"}
}