{
  "type": "Feature",
  "properties": {
    "gn:admin1_code":"13",
    "gn:asciiname":"Kampung Bukit Berangan",
    "gn:country_code":"MY",
    "gn:dem":28,
    "gn:feature_class":"P",
    "gn:feature_code":"PPL",
    "gn:name":"Kampung Bukit Berangan",
    "gn:population":0,
    "gn:timezone":"Asia/Kuala_Lumpur",
    "iso:country":"MY",
    "name:msa_x_preferred":[
        "Kampung Bukit Berangan"
    ],
    "name:und_x_variant":[
        "Kampong Bukit Berangan"
    ],
    "wof:name":"Kampung Bukit Berangan",
    "wof:placetype":"locality"
},
  "geometry": {"coordinates":[102.83880000000001,5.3153],"type":"Point"}
}