{
  "type": "Feature",
  "properties": {
    "gn:admin1_code":"12",
    "gn:asciiname":"Kampung Sungai Tamu",
    "gn:country_code":"MY",
    "gn:dem":112,
    "gn:feature_class":"P",
    "gn:feature_code":"PPL",
    "gn:name":"Kampung Sungai Tamu",
    "gn:population":0,
    "gn:timezone":"Asia/Kuala_Lumpur",
    "iso:country":"MY",
    "name:msa_x_preferred":[
        "Kampung Sungai Tamu"
    ],
    "name:und_x_variant":[
        "Kampong Sungai Tamu"
    ],
    "wof:name":"Kampung Sungai Tamu",
    "wof:placetype":"locality"
},
  "geometry": {"coordinates":[101.7032,3.4585],"type":"Point"}
}