{
  "type": "Feature",
  "properties": {
    "gn:admin1_code":"2.0",
    "gn:asciiname":"Kampung Baru",
    "gn:country_code":"MY",
    "gn:dem":95,
    "gn:feature_class":"P",
    "gn:feature_code":"PPL",
    "gn:name":"Kampung Baru",
    "gn:population":0,
    "gn:timezone":"Asia/Kuala_Lumpur",
    "iso:country":"MY",
    "name:msa_x_preferred":[
        "Kampung Baru"
    ],
    "wof:name":"Kampung Baru",
    "wof:placetype":"locality"
},
  "geometry": {"coordinates":[100.90049999999999,5.78721],"type":"Point"}
}