{
  "type": "Feature",
  "properties": {
    "gn:admin1_code":"7",
    "gn:asciiname":"Kampung Padang Lalang",
    "gn:cc2":"MY",
    "gn:country_code":"MY",
    "gn:dem":11,
    "gn:feature_class":"P",
    "gn:feature_code":"PPL",
    "gn:name":"Kampung Padang Lalang",
    "gn:population":0,
    "gn:timezone":"Asia/Kuala_Lumpur",
    "iso:country":"MY",
    "name:msa_x_preferred":[
        "Kampung Padang Lalang"
    ],
    "name:und_x_variant":[
        "Kampong Padang Lalang"
    ],
    "wof:name":"Kampung Padang Lalang",
    "wof:placetype":"locality"
},
  "geometry": {"coordinates":[100.61654,5.0162],"type":"Point"}
}