{
  "type": "Feature",
  "properties": {
    "gn:admin1_code":"16.0",
    "gn:asciiname":"Kampung Mangkabong",
    "gn:country_code":"MY",
    "gn:dem":6,
    "gn:feature_class":"P",
    "gn:feature_code":"PPL",
    "gn:name":"Kampung Mangkabong",
    "gn:population":0,
    "gn:timezone":"Asia/Kuching",
    "iso:country":"MY",
    "name:msa_x_preferred":[
        "Kampung Mangkabong"
    ],
    "name:und_x_variant":[
        "Kampong Mangkabong",
        "Mangkabong",
        "Kampong Mengkabong",
        "Mengkabong"
    ],
    "wof:name":"Kampung Mangkabong",
    "wof:placetype":"locality"
},
  "geometry": {"coordinates":[116.2047,6.1441],"type":"Point"}
}