{
  "type": "Feature",
  "properties": {
    "gn:admin1_code":"16",
    "gn:asciiname":"Kampung Ketanun",
    "gn:country_code":"MY",
    "gn:dem":536,
    "gn:feature_class":"P",
    "gn:feature_code":"PPL",
    "gn:name":"Kampung Ketanun",
    "gn:population":0,
    "gn:timezone":"Asia/Kuching",
    "iso:country":"MY",
    "name:msa_x_preferred":[
        "Kampung Ketanun"
    ],
    "name:und_x_variant":[
        "Ketanun"
    ],
    "wof:name":"Kampung Ketanun",
    "wof:placetype":"locality"
},
  "geometry": {"coordinates":[115.78740000000001,4.77],"type":"Point"}
}