{
  "type": "Feature",
  "properties": {
    "gn:admin1_code":"16",
    "gn:asciiname":"Kampung Karangawan Laut",
    "gn:country_code":"MY",
    "gn:dem":47,
    "gn:feature_class":"P",
    "gn:feature_code":"PPL",
    "gn:name":"Kampung Karangawan Laut",
    "gn:population":0,
    "gn:timezone":"Asia/Kuching",
    "iso:country":"MY",
    "name:msa_x_preferred":[
        "Kampung Karangawan Laut"
    ],
    "name:und_x_variant":[
        "Karangawan",
        "Kampong Karangawan Laut"
    ],
    "wof:name":"Kampung Karangawan Laut",
    "wof:placetype":"locality"
},
  "geometry": {"coordinates":[116.72239999999999,6.6165],"type":"Point"}
}