{
  "type": "Feature",
  "properties": {
    "iso:country":"MY",
    "qs:name":"Taman Orchad",
    "qs:name_adm0":"Malaysia",
    "qs:name_adm1":"Sarawak",
    "qs:photos":29,
    "qs:photos_1k":6,
    "qs:photos_9k":1,
    "qs:photos_9r":2,
    "qs:photos_all":29,
    "qs:photos_sr":2,
    "qs:placetype":"Town",
    "qs:pop_sr":"0",
    "wof:name":"Taman Orchad",
    "wof:placetype":"locality"
},
  "geometry": {"coordinates":[110.369167,1.516794],"type":"Point"}
}