{
  "type": "Feature",
  "properties": {
    "iso:country":"MY",
    "name:deu_x_preferred":[
        "Istana Negara"
    ],
    "name:ita_x_preferred":[
        "Istana Negara"
    ],
    "name:msa_x_preferred":[
        "Istana Negara"
    ],
    "qs:name":"Istana Negara",
    "qs:name_adm0":"Malaysia",
    "qs:name_adm1":"Kuala Lumpur",
    "qs:photos":377,
    "qs:photos_1k":76,
    "qs:photos_9k":2,
    "qs:photos_9r":5,
    "qs:photos_all":377,
    "qs:photos_sr":6,
    "qs:placetype":"Suburb",
    "qs:pop_sr":"0",
    "wd:wordcount":43,
    "wof:name":"Istana Negara",
    "wof:placetype":"neighbourhood"
},
  "geometry": {"coordinates":[101.692938,3.136274],"type":"Point"}
}