{
  "type": "Feature",
  "properties": {
    "gn:admin1_code":"11",
    "gn:asciiname":"Kampong Temung Tembawang",
    "gn:country_code":"MY",
    "gn:dem":152,
    "gn:feature_class":"P",
    "gn:feature_code":"PPL",
    "gn:name":"Kampong Temung Tembawang",
    "gn:population":0,
    "gn:timezone":"Asia/Kuching",
    "iso:country":"MY",
    "name:und_x_variant":[
        "Kampong Temung",
        "Kampong Temung Tembawang"
    ],
    "wof:name":"Kampong Temung Tembawang",
    "wof:placetype":"locality"
},
  "geometry": {"coordinates":[110.32273000000001,1.03523],"type":"Point"}
}