{
  "type": "Feature",
  "properties": {
    "gn:admin1_code":"1.0",
    "gn:asciiname":"Rumah Pekerja",
    "gn:country_code":"MY",
    "gn:dem":25,
    "gn:feature_class":"P",
    "gn:feature_code":"PPL",
    "gn:name":"Rumah Pekerja",
    "gn:population":0,
    "gn:timezone":"Asia/Kuala_Lumpur",
    "iso:country":"MY",
    "name:msa_x_preferred":[
        "Rumah Pekerja"
    ],
    "wof:name":"Rumah Pekerja",
    "wof:placetype":"locality"
},
  "geometry": {"coordinates":[103.0021,2.1479],"type":"Point"}
}