{
  "type": "Feature",
  "properties": {
    "gn:admin1_code":"5",
    "gn:asciiname":"Kampung Dhobi",
    "gn:country_code":"MY",
    "gn:dem":11,
    "gn:feature_class":"P",
    "gn:feature_code":"PPL",
    "gn:name":"Kampung Dhobi",
    "gn:population":0,
    "gn:timezone":"Asia/Kuala_Lumpur",
    "iso:country":"MY",
    "name:msa_x_preferred":[
        "Kampung Dhobi"
    ],
    "name:und_x_variant":[
        "Kampong Dhobi"
    ],
    "wof:name":"Kampung Dhobi",
    "wof:placetype":"locality"
},
  "geometry": {"coordinates":[101.7966,2.5302],"type":"Point"}
}