{
  "type": "Feature",
  "properties": {
    "gn:admin1_code":"16.0",
    "gn:asciiname":"Kampung Alab",
    "gn:country_code":"MY",
    "gn:dem":363,
    "gn:feature_class":"P",
    "gn:feature_code":"PPL",
    "gn:name":"Kampung Alab",
    "gn:population":0,
    "gn:timezone":"Asia/Kuching",
    "iso:country":"MY",
    "name:msa_x_preferred":[
        "Kampung Alab"
    ],
    "wof:name":"Kampung Alab",
    "wof:placetype":"locality"
},
  "geometry": {"coordinates":[116.50060000000001,5.332],"type":"Point"}
}