{
  "type": "Feature",
  "properties": {
    "gn:admin1_code":"7",
    "gn:asciiname":"Kammpung Gerik",
    "gn:country_code":"MY",
    "gn:dem":158,
    "gn:feature_class":"P",
    "gn:feature_code":"PPL",
    "gn:name":"Kammpung Gerik",
    "gn:population":0,
    "gn:timezone":"Asia/Kuala_Lumpur",
    "iso:country":"MY",
    "name:und_x_variant":[
        "Kampong Grik",
        "Kampong Gerik",
        "Kammpung Gerik"
    ],
    "wof:name":"Kammpung Gerik",
    "wof:placetype":"locality"
},
  "geometry": {"coordinates":[101.11499000000001,5.43424],"type":"Point"}
}