{
  "type": "Feature",
  "properties": {
    "gn:admin1_code":"16.0",
    "gn:asciiname":"Sonsogon Suyad",
    "gn:country_code":"MY",
    "gn:dem":291,
    "gn:feature_class":"P",
    "gn:feature_code":"PPL",
    "gn:name":"Sonsogon Suyad",
    "gn:population":0,
    "gn:timezone":"Asia/Kuching",
    "iso:country":"MY",
    "name:msa_x_preferred":[
        "Sonsogon Suyad"
    ],
    "wof:name":"Sonsogon Suyad",
    "wof:placetype":"locality"
},
  "geometry": {"coordinates":[117.0612,6.4165],"type":"Point"}
}