{
  "type": "Feature",
  "properties": {
    "gn:admin1_code":"6.0",
    "gn:asciiname":"Kampung Cancai",
    "gn:country_code":"MY",
    "gn:dem":68,
    "gn:feature_class":"P",
    "gn:feature_code":"PPL",
    "gn:name":"Kampung Cancai",
    "gn:population":0,
    "gn:timezone":"Asia/Kuala_Lumpur",
    "iso:country":"MY",
    "name:msa_x_preferred":[
        "Kampung Cancai"
    ],
    "wof:name":"Kampung Cancai",
    "wof:placetype":"locality"
},
  "geometry": {"coordinates":[102.3447,4.1311],"type":"Point"}
}