{
  "type": "Feature",
  "properties": {
    "gn:admin1_code":"3",
    "gn:asciiname":"Kampung Repuh",
    "gn:country_code":"MY",
    "gn:dem":45,
    "gn:feature_class":"P",
    "gn:feature_code":"PPL",
    "gn:name":"Kampung Repuh",
    "gn:population":0,
    "gn:timezone":"Asia/Kuala_Lumpur",
    "iso:country":"MY",
    "name:msa_x_preferred":[
        "Kampung Repuh"
    ],
    "name:und_x_variant":[
        "Kampong Repoh"
    ],
    "wof:name":"Kampung Repuh",
    "wof:placetype":"locality"
},
  "geometry": {"coordinates":[101.98177,5.79216],"type":"Point"}
}