{
  "type": "Feature",
  "properties": {
    "gn:admin1_code":"9.0",
    "gn:asciiname":"Ara Rendang",
    "gn:cc2":"MY",
    "gn:country_code":"MY",
    "gn:dem":13,
    "gn:feature_class":"P",
    "gn:feature_code":"PPL",
    "gn:name":"Ara Rendang",
    "gn:population":0,
    "gn:timezone":"Asia/Kuala_Lumpur",
    "iso:country":"MY",
    "name:msa_x_preferred":[
        "Ara Rendang"
    ],
    "wof:name":"Ara Rendang",
    "wof:placetype":"locality"
},
  "geometry": {"coordinates":[100.45604,5.48896],"type":"Point"}
}