{
  "type": "Feature",
  "properties": {
    "gn:admin1_code":"12.0",
    "gn:asciiname":"Kampung Kilang Papan",
    "gn:country_code":"MY",
    "gn:dem":53,
    "gn:feature_class":"P",
    "gn:feature_code":"PPL",
    "gn:name":"Kampung Kilang Papan",
    "gn:population":0,
    "gn:timezone":"Asia/Kuala_Lumpur",
    "iso:country":"MY",
    "name:msa_x_preferred":[
        "Kampung Kilang Papan"
    ],
    "wof:name":"Kampung Kilang Papan",
    "wof:placetype":"locality"
},
  "geometry": {"coordinates":[101.5277,3.6711],"type":"Point"}
}