{
  "type": "Feature",
  "properties": {
    "gn:admin1_code":"1.0",
    "gn:asciiname":"Pasir Gogok",
    "gn:country_code":"MY",
    "gn:dem":10,
    "gn:feature_class":"P",
    "gn:feature_code":"PPL",
    "gn:name":"Pasir Gogok",
    "gn:population":0,
    "gn:timezone":"Asia/Kuala_Lumpur",
    "iso:country":"MY",
    "name:msa_x_preferred":[
        "Pasir Gogok"
    ],
    "name:und_x_variant":[
        "Kampong Pasir Goh",
        "Pasir Goh",
        "Pasir Gogok"
    ],
    "wof:name":"Pasir Gogok",
    "wof:placetype":"locality"
},
  "geometry": {"coordinates":[104.10169999999999,1.4201],"type":"Point"}
}