{
  "type": "Feature",
  "properties": {
    "gn:admin1_code":"6",
    "gn:asciiname":"Kampung Kuala Reman",
    "gn:country_code":"MY",
    "gn:dem":17,
    "gn:feature_class":"P",
    "gn:feature_code":"PPL",
    "gn:name":"Kampung Kuala Reman",
    "gn:population":0,
    "gn:timezone":"Asia/Kuala_Lumpur",
    "iso:country":"MY",
    "name:msa_x_preferred":[
        "Kampung Kuala Reman"
    ],
    "name:und_x_variant":[
        "Kampong Kuala Reman"
    ],
    "wof:name":"Kampung Kuala Reman",
    "wof:placetype":"locality"
},
  "geometry": {"coordinates":[103.1665,3.9056],"type":"Point"}
}