{
  "type": "Feature",
  "properties": {
    "gn:admin1_code":"6",
    "gn:asciiname":"Kampung Keluang",
    "gn:country_code":"MY",
    "gn:dem":74,
    "gn:feature_class":"P",
    "gn:feature_code":"PPL",
    "gn:name":"Kampung Keluang",
    "gn:population":0,
    "gn:timezone":"Asia/Kuala_Lumpur",
    "iso:country":"MY",
    "name:msa_x_preferred":[
        "Kampung Keluang"
    ],
    "name:und_x_variant":[
        "Kampong Keluang"
    ],
    "wof:name":"Kampung Keluang",
    "wof:placetype":"locality"
},
  "geometry": {"coordinates":[102.3296,4.0745],"type":"Point"}
}