{
  "type": "Feature",
  "properties": {
    "gn:admin1_code":"7",
    "gn:asciiname":"Kampung Lubok Salak Lima",
    "gn:country_code":"MY",
    "gn:dem":44,
    "gn:feature_class":"P",
    "gn:feature_code":"PPL",
    "gn:name":"Kampung Lubok Salak Lima",
    "gn:population":0,
    "gn:timezone":"Asia/Kuala_Lumpur",
    "iso:country":"MY",
    "name:msa_x_preferred":[
        "Kampung Lubok Salak Lima"
    ],
    "name:und_x_variant":[
        "Kampong Lubok Salak"
    ],
    "wof:name":"Kampung Lubok Salak Lima",
    "wof:placetype":"locality"
},
  "geometry": {"coordinates":[101.50830000000001,3.6931],"type":"Point"}
}