{
  "type": "Feature",
  "properties": {
    "gn:admin1_code":"7",
    "gn:asciiname":"Kampong Sungai Gedong",
    "gn:cc2":"MY",
    "gn:country_code":"MY",
    "gn:dem":4,
    "gn:feature_class":"P",
    "gn:feature_code":"PPL",
    "gn:name":"Kampong Sungai Gedong",
    "gn:population":0,
    "gn:timezone":"Asia/Kuala_Lumpur",
    "iso:country":"MY",
    "name:und_x_variant":[
        "Sungei Gedong",
        "Kampong Sungai Gedong"
    ],
    "wof:name":"Kampong Sungai Gedong",
    "wof:placetype":"locality"
},
  "geometry": {"coordinates":[100.59999999999999,4.98333],"type":"Point"}
}