{
  "type": "Feature",
  "properties": {
    "gn:admin1_code":"6.0",
    "gn:asciiname":"Kampung Pemulihan Banjir Batu Lapun",
    "gn:country_code":"MY",
    "gn:dem":24,
    "gn:feature_class":"P",
    "gn:feature_code":"PPL",
    "gn:name":"Kampung Pemulihan Banjir Batu Lapun",
    "gn:population":0,
    "gn:timezone":"Asia/Kuala_Lumpur",
    "iso:country":"MY",
    "name:msa_x_preferred":[
        "Kampung Pemulihan Banjir Batu Lapun"
    ],
    "wof:name":"Kampung Pemulihan Banjir Batu Lapun",
    "wof:placetype":"locality"
},
  "geometry": {"coordinates":[103.0988,3.5648],"type":"Point"}
}