{
  "type": "Feature",
  "properties": {
    "gn:admin1_code":"4",
    "gn:asciiname":"Kampung Lendu",
    "gn:country_code":"MY",
    "gn:dem":43,
    "gn:feature_class":"P",
    "gn:feature_code":"PPL",
    "gn:name":"Kampung Lendu",
    "gn:population":0,
    "gn:timezone":"Asia/Kuala_Lumpur",
    "iso:country":"MY",
    "name:msa_x_preferred":[
        "Kampung Lendu"
    ],
    "name:und_x_variant":[
        "Kampong Lendu"
    ],
    "wof:name":"Kampung Lendu",
    "wof:placetype":"locality"
},
  "geometry": {"coordinates":[102.17359999999999,2.3571],"type":"Point"}
}