{
  "type": "Feature",
  "properties": {
    "gn:admin1_code":"7.0",
    "gn:asciiname":"Taman Sun Brite Jaya",
    "gn:country_code":"MY",
    "gn:dem":81,
    "gn:feature_class":"P",
    "gn:feature_code":"PPL",
    "gn:name":"Taman Sun Brite Jaya",
    "gn:population":0,
    "gn:timezone":"Asia/Kuala_Lumpur",
    "iso:country":"MY",
    "name:msa_x_preferred":[
        "Taman Sun Brite Jaya"
    ],
    "wof:name":"Taman Sun Brite Jaya",
    "wof:placetype":"locality"
},
  "geometry": {"coordinates":[101.1649,4.6652],"type":"Point"}
}