{
  "type": "Feature",
  "properties": {
    "gn:admin1_code":"6",
    "gn:asciiname":"Kampung Paya Banir",
    "gn:country_code":"MY",
    "gn:dem":38,
    "gn:feature_class":"P",
    "gn:feature_code":"PPL",
    "gn:name":"Kampung Paya Banir",
    "gn:population":0,
    "gn:timezone":"Asia/Kuala_Lumpur",
    "iso:country":"MY",
    "name:msa_x_preferred":[
        "Kampung Paya Banir"
    ],
    "name:und_x_variant":[
        "Kampong Paya Banir"
    ],
    "wof:name":"Kampung Paya Banir",
    "wof:placetype":"locality"
},
  "geometry": {"coordinates":[102.4297,3.4992],"type":"Point"}
}