{
  "type": "Feature",
  "properties": {
    "gn:admin1_code":"13.0",
    "gn:asciiname":"Kampung Tok Fakir",
    "gn:country_code":"MY",
    "gn:dem":11,
    "gn:feature_class":"P",
    "gn:feature_code":"PPL",
    "gn:name":"Kampung Tok Fakir",
    "gn:population":0,
    "gn:timezone":"Asia/Kuala_Lumpur",
    "iso:country":"MY",
    "name:msa_x_preferred":[
        "Kampung Tok Fakir"
    ],
    "wof:name":"Kampung Tok Fakir",
    "wof:placetype":"locality"
},
  "geometry": {"coordinates":[103.30289999999999,5.0077],"type":"Point"}
}