{
  "type": "Feature",
  "properties": {
    "gn:admin1_code":"6",
    "gn:asciiname":"Kampung Cemetung",
    "gn:country_code":"MY",
    "gn:dem":69,
    "gn:feature_class":"P",
    "gn:feature_code":"PPL",
    "gn:name":"Kampung Cemetung",
    "gn:population":0,
    "gn:timezone":"Asia/Kuala_Lumpur",
    "iso:country":"MY",
    "name:msa_x_preferred":[
        "Kampung Cemetung"
    ],
    "name:und_x_variant":[
        "Kampong Chematong",
        "Kampong Chemetong"
    ],
    "wof:name":"Kampung Cemetung",
    "wof:placetype":"locality"
},
  "geometry": {"coordinates":[102.3717,4.267],"type":"Point"}
}