{
  "type": "Feature",
  "properties": {
    "gn:country":"MY",
    "gn:fcode":"PPL",
    "gn:population":0,
    "iso:country":"MY",
    "name:ceb_x_preferred":[
        "Rantau Panjang"
    ],
    "name:deu_x_preferred":[
        "Rantau Panjang"
    ],
    "name:eng_x_preferred":[
        "Rantau Panjang"
    ],
    "name:epo_x_preferred":[
        "Rantau Panjang"
    ],
    "name:ind_x_preferred":[
        "Rantau Panjang"
    ],
    "name:jpn_x_preferred":[
        "\u30e9\u30f3\u30bf\u30a6\u30fb\u30d1\u30f3\u30b8\u30e3\u30f3"
    ],
    "name:msa_x_preferred":[
        "Rantau Panjang"
    ],
    "name:nld_x_preferred":[
        "Rantau Panjang"
    ],
    "name:rus_x_preferred":[
        "\u0420\u0430\u043d\u0442\u0430\u0443-\u041f\u0430\u043d\u0434\u0436\u0430\u043d\u0433"
    ],
    "name:tha_x_preferred":[
        "\u0e23\u0e31\u0e19\u0e40\u0e15\u0e32\u0e1b\u0e31\u0e19\u0e08\u0e31\u0e07"
    ],
    "qs_pg:aaroncc":"MY",
    "qs_pg:gn_country":"MY",
    "qs_pg:gn_fcode":"PPL",
    "qs_pg:gn_pop":0,
    "qs_pg:name":"Rata Panyang",
    "qs_pg:name_adm0":"Thailand",
    "qs_pg:name_adm1":"Pattani",
    "qs_pg:photos_9r":0,
    "qs_pg:photos_sr":0,
    "qs_pg:pop_sr":0,
    "qs_pg:qs_pg_placetype":"locality",
    "qs_pg:qs_pg_placetype_gp":"Town",
    "qs_pg:woe_adm0":23424960,
    "woe:adm0_id":23424960,
    "woe:name_adm0":"Thailand",
    "woe:name_adm1":"Pattani",
    "woe:placetype":"Town",
    "wof:name":"Rata Panyang",
    "wof:placetype":"locality",
    "wof:population":500
},
  "geometry": {"coordinates":[101.97669999999999,6.0219],"type":"Point"}
}