{
  "type": "Feature",
  "properties": {
    "gn:admin1_code":"3.0",
    "gn:asciiname":"Kampung Lalang Pepuyu",
    "gn:country_code":"MY",
    "gn:dem":30,
    "gn:feature_class":"P",
    "gn:feature_code":"PPL",
    "gn:name":"Kampung Lalang Pepuyu",
    "gn:population":0,
    "gn:timezone":"Asia/Kuala_Lumpur",
    "iso:country":"MY",
    "name:msa_x_preferred":[
        "Kampung Lalang Pepuyu"
    ],
    "wof:name":"Kampung Lalang Pepuyu",
    "wof:placetype":"locality"
},
  "geometry": {"coordinates":[101.9494,5.87398],"type":"Point"}
}