{
  "type": "Feature",
  "properties": {
    "gn:admin1_code":"3.0",
    "gn:asciiname":"Pasir Biak",
    "gn:country_code":"MY",
    "gn:dem":45,
    "gn:feature_class":"P",
    "gn:feature_code":"PPL",
    "gn:name":"Pasir Biak",
    "gn:population":0,
    "gn:timezone":"Asia/Kuala_Lumpur",
    "iso:country":"MY",
    "name:msa_x_preferred":[
        "Pasir Biak"
    ],
    "wof:name":"Pasir Biak",
    "wof:placetype":"locality"
},
  "geometry": {"coordinates":[101.9631,5.4133],"type":"Point"}
}