{
  "type": "Feature",
  "properties": {
    "gn:admin1_code":"5.0",
    "gn:asciiname":"Kampung A",
    "gn:country_code":"MY",
    "gn:dem":70,
    "gn:feature_class":"P",
    "gn:feature_code":"PPL",
    "gn:name":"Kampung A",
    "gn:population":0,
    "gn:timezone":"Asia/Kuala_Lumpur",
    "iso:country":"MY",
    "name:msa_x_preferred":[
        "Kampung A"
    ],
    "name:und_x_variant":[
        "A Village"
    ],
    "wof:name":"Kampung A",
    "wof:placetype":"locality"
},
  "geometry": {"coordinates":[102.5025,2.8429],"type":"Point"}
}