{
  "type": "Feature",
  "properties": {
    "gn:admin1_code":"13.0",
    "gn:asciiname":"Api Rokok",
    "gn:cc2":"MY",
    "gn:country_code":"MY",
    "gn:dem":12,
    "gn:feature_class":"P",
    "gn:feature_code":"PPL",
    "gn:name":"Api Rokok",
    "gn:population":0,
    "gn:timezone":"Asia/Kuala_Lumpur",
    "iso:country":"MY",
    "name:und_x_variant":[
        "Kampong Api Rokok",
        "Api Rokok"
    ],
    "wof:name":"Api Rokok",
    "wof:placetype":"locality"
},
  "geometry": {"coordinates":[103.43333,4.55],"type":"Point"}
}