{
  "type": "Feature",
  "properties": {
    "gn:admin1_code":"16",
    "gn:asciiname":"Kampung Giring",
    "gn:country_code":"MY",
    "gn:dem":95,
    "gn:feature_class":"P",
    "gn:feature_code":"PPL",
    "gn:name":"Kampung Giring",
    "gn:population":0,
    "gn:timezone":"Asia/Kuching",
    "iso:country":"MY",
    "name:msa_x_preferred":[
        "Kampung Giring"
    ],
    "name:und_x_variant":[
        "Kampong Giring"
    ],
    "wof:name":"Kampung Giring",
    "wof:placetype":"locality"
},
  "geometry": {"coordinates":[116.9436,6.0644],"type":"Point"}
}