{
  "type": "Feature",
  "properties": {
    "gn:admin1_code":"9",
    "gn:asciiname":"Kampung Sungai Udang Besar",
    "gn:country_code":"MY",
    "gn:dem":5,
    "gn:feature_class":"P",
    "gn:feature_code":"PPL",
    "gn:name":"Kampung Sungai Udang Besar",
    "gn:population":0,
    "gn:timezone":"Asia/Kuala_Lumpur",
    "iso:country":"MY",
    "name:msa_x_preferred":[
        "Kampung Sungai Udang Besar"
    ],
    "name:und_x_variant":[
        "Sungei Udang Besar",
        "Kampong Sungai Udang Besar"
    ],
    "wof:name":"Kampung Sungai Udang Besar",
    "wof:placetype":"locality"
},
  "geometry": {"coordinates":[100.42677,5.16129],"type":"Point"}
}