{
  "type": "Feature",
  "properties": {
    "gn:admin1_code":"16.0",
    "gn:asciiname":"Kampung Menunuk",
    "gn:country_code":"MY",
    "gn:dem":37,
    "gn:feature_class":"P",
    "gn:feature_code":"PPL",
    "gn:name":"Kampung Menunuk",
    "gn:population":0,
    "gn:timezone":"Asia/Kuching",
    "iso:country":"MY",
    "name:msa_x_preferred":[
        "Kampung Menunuk"
    ],
    "wof:name":"Kampung Menunuk",
    "wof:placetype":"locality"
},
  "geometry": {"coordinates":[115.7616,5.3219],"type":"Point"}
}