{
  "type": "Feature",
  "properties": {
    "gn:admin1_code":"7.0",
    "gn:asciiname":"Kampung Lambak",
    "gn:country_code":"MY",
    "gn:dem":47,
    "gn:feature_class":"P",
    "gn:feature_code":"PPL",
    "gn:name":"Kampung Lambak",
    "gn:population":0,
    "gn:timezone":"Asia/Kuala_Lumpur",
    "iso:country":"MY",
    "name:msa_x_preferred":[
        "Kampung Lambak"
    ],
    "wof:name":"Kampung Lambak",
    "wof:placetype":"locality"
},
  "geometry": {"coordinates":[101.5153,3.6892],"type":"Point"}
}