{
  "type": "Feature",
  "properties": {
    "gn:admin1_code":"11.0",
    "gn:asciiname":"Kuching",
    "gn:country_code":"MY",
    "gn:dem":5,
    "gn:feature_class":"P",
    "gn:feature_code":"PPL",
    "gn:name":"Kuching",
    "gn:population":0,
    "gn:timezone":"Asia/Kuching",
    "iso:country":"MY",
    "name:ara_x_preferred":[
        "\u0643\u0648\u062a\u0634\u064a\u0646\u063a"
    ],
    "name:ast_x_preferred":[
        "Kuching"
    ],
    "name:azb_x_preferred":[
        "\u06a9\u0648\u0686\u06cc\u0646\u0642"
    ],
    "name:bjn_x_preferred":[
        "Kuching"
    ],
    "name:bul_x_preferred":[
        "\u041a\u0443\u0447\u0438\u043d\u0433"
    ],
    "name:ceb_x_preferred":[
        "Kuching"
    ],
    "name:ces_x_preferred":[
        "Kuching"
    ],
    "name:dan_x_preferred":[
        "Kuching"
    ],
    "name:deu_x_preferred":[
        "Kuching"
    ],
    "name:epo_x_preferred":[
        "Kuching"
    ],
    "name:fas_x_preferred":[
        "\u06a9\u0648\u0686\u06cc\u0646\u06af"
    ],
    "name:fin_x_preferred":[
        "Kuching"
    ],
    "name:fra_x_preferred":[
        "Kuching"
    ],
    "name:heb_x_preferred":[
        "\u05e7\u05d5\u05e6'\u05d9\u05e0\u05d2"
    ],
    "name:hin_x_preferred":[
        "\u0915\u0941\u091a\u093f\u0902\u0917"
    ],
    "name:hun_x_preferred":[
        "Kuching"
    ],
    "name:ind_x_preferred":[
        "Kuching"
    ],
    "name:ita_x_preferred":[
        "Kuching"
    ],
    "name:jpn_x_preferred":[
        "\u30af\u30c1\u30f3"
    ],
    "name:lit_x_preferred":[
        "Ku\u010dingas"
    ],
    "name:mal_x_preferred":[
        "\u0d15\u0d41\u0d1a\u0d4d\u0d1a\u0d3f\u0d19\u0d4d\u0d19\u0d4d"
    ],
    "name:mar_x_preferred":[
        "\u0915\u0941\u091a\u093f\u0902\u0917"
    ],
    "name:mkd_x_preferred":[
        "\u041a\u0443\u0447\u0438\u043d\u0433"
    ],
    "name:mri_x_preferred":[
        "Kuching"
    ],
    "name:msa_x_preferred":[
        "Kuching"
    ],
    "name:mya_x_preferred":[
        "\u1000\u1030\u1001\u103b\u1004\u103a\u1038\u1019\u103c\u102d\u102f\u1037"
    ],
    "name:nld_x_preferred":[
        "Kuching Utara"
    ],
    "name:nor_x_preferred":[
        "Kuching"
    ],
    "name:pol_x_preferred":[
        "Kuching"
    ],
    "name:por_x_preferred":[
        "Kuching"
    ],
    "name:ron_x_preferred":[
        "Kuching"
    ],
    "name:rus_x_preferred":[
        "\u041a\u0443\u0447\u0438\u043d\u0433"
    ],
    "name:sco_x_preferred":[
        "Kuching"
    ],
    "name:spa_x_preferred":[
        "Kuching"
    ],
    "name:swe_x_preferred":[
        "Kuching"
    ],
    "name:tgl_x_preferred":[
        "Kuching"
    ],
    "name:tha_x_preferred":[
        "\u0e01\u0e39\u0e0a\u0e34\u0e07"
    ],
    "name:tur_x_preferred":[
        "Kuching"
    ],
    "name:ukr_x_preferred":[
        "\u041a\u0443\u0447\u0438\u043d\u0433"
    ],
    "name:urd_x_preferred":[
        "\u06a9\u0648\u0686\u06cc\u0646\u06af"
    ],
    "name:uzb_x_preferred":[
        "Kuching"
    ],
    "name:vie_x_preferred":[
        "Kuching"
    ],
    "name:war_x_preferred":[
        "Kuching"
    ],
    "wof:name":"Kuching",
    "wof:placetype":"locality"
},
  "geometry": {"coordinates":[110.34187,1.52143],"type":"Point"}
}