{
  "type": "Feature",
  "properties": {
    "gn:admin1_code":"16.0",
    "gn:asciiname":"Kampung Gansa",
    "gn:country_code":"MY",
    "gn:dem":53,
    "gn:feature_class":"P",
    "gn:feature_code":"PPL",
    "gn:name":"Kampung Gansa",
    "gn:population":0,
    "gn:timezone":"Asia/Kuching",
    "iso:country":"MY",
    "name:msa_x_preferred":[
        "Kampung Gansa"
    ],
    "wof:name":"Kampung Gansa",
    "wof:placetype":"locality"
},
  "geometry": {"coordinates":[117.16070000000001,6.1295],"type":"Point"}
}