{
  "type": "Feature",
  "properties": {
    "gn:admin1_code":"11",
    "gn:asciiname":"Kampong Serampang",
    "gn:cc2":"MY",
    "gn:country_code":"MY",
    "gn:dem":16,
    "gn:feature_class":"P",
    "gn:feature_code":"PPL",
    "gn:name":"Kampong Serampang",
    "gn:population":0,
    "gn:timezone":"Asia/Kuching",
    "iso:country":"MY",
    "name:und_x_variant":[
        "Serampang",
        "Kampong Serampang"
    ],
    "wof:name":"Kampong Serampang",
    "wof:placetype":"locality"
},
  "geometry": {"coordinates":[115.25,4.81667],"type":"Point"}
}