{
  "type": "Feature",
  "properties": {
    "iso:country":"MY",
    "name:und_x_preferred":[
        "Taman Lip Sin"
    ],
    "name:unk_x_variant":[
        "Taman Lip Sin"
    ],
    "qs:gn_adm0_cc":"MY",
    "qs:gn_local":1735106,
    "qs:local_max":5776,
    "qs:local_sum":22216,
    "qs:localhoods":25,
    "qs:name":"Taman Lip Sin",
    "qs:name_adm0":"Malaysia",
    "qs:name_adm1":"Pulau Pinang",
    "qs:name_adm2":"Timur Laut",
    "qs:name_lau":"Mukim 13 Paya Terubung",
    "qs:name_local":"George Town",
    "qs:photo_max":30,
    "qs:photo_sum":97,
    "qs:placetype":"Suburb",
    "qs:quad_count":9,
    "qs:woe_adm0":23424901,
    "qs:woe_adm1":2346304,
    "qs:woe_adm2":56013581,
    "qs:woe_funk":"Parented by a neighborhood",
    "qs:woe_lau":56013984,
    "qs:woe_local":1141153,
    "qs:woe_ver":"7.10.0",
    "wof:lang":[
        "unk"
    ],
    "wof:name":"Taman Lip Sin",
    "wof:placetype":"neighbourhood"
},
  "geometry": {"coordinates":[100.300557,5.344217],"type":"Point"}
}