{
  "type": "Feature",
  "properties": {
    "gn:admin1_code":"16.0",
    "gn:asciiname":"Kampung Toliduson",
    "gn:country_code":"MY",
    "gn:dem":79,
    "gn:feature_class":"P",
    "gn:feature_code":"PPL",
    "gn:name":"Kampung Toliduson",
    "gn:population":0,
    "gn:timezone":"Asia/Kuching",
    "iso:country":"MY",
    "name:msa_x_preferred":[
        "Kampung Toliduson"
    ],
    "wof:name":"Kampung Toliduson",
    "wof:placetype":"locality"
},
  "geometry": {"coordinates":[116.9333,6.6194],"type":"Point"}
}