{
  "type": "Feature",
  "properties": {
    "gn:admin1_code":"5",
    "gn:asciiname":"Kampung Ayer Melana",
    "gn:country_code":"MY",
    "gn:dem":93,
    "gn:feature_class":"P",
    "gn:feature_code":"PPL",
    "gn:name":"Kampung Ayer Melana",
    "gn:population":0,
    "gn:timezone":"Asia/Kuala_Lumpur",
    "iso:country":"MY",
    "name:msa_x_preferred":[
        "Kampung Ayer Melana"
    ],
    "name:und_x_variant":[
        "Kampong Melana"
    ],
    "wof:name":"Kampung Ayer Melana",
    "wof:placetype":"locality"
},
  "geometry": {"coordinates":[102.3199,2.7569],"type":"Point"}
}