{
  "type": "Feature",
  "properties": {
    "gn:admin1_code":"5",
    "gn:asciiname":"Kampong Tanjong Melintang",
    "gn:country_code":"MY",
    "gn:dem":67,
    "gn:feature_class":"P",
    "gn:feature_code":"PPL",
    "gn:name":"Kampong Tanjong Melintang",
    "gn:population":0,
    "gn:timezone":"Asia/Kuala_Lumpur",
    "iso:country":"MY",
    "wof:name":"Kampong Tanjong Melintang",
    "wof:placetype":"locality"
},
  "geometry": {"coordinates":[102.40000000000001,2.55],"type":"Point"}
}