{
  "type": "Feature",
  "properties": {
    "gn:admin1_code":"16",
    "gn:asciiname":"Kampung Waang",
    "gn:country_code":"MY",
    "gn:dem":955,
    "gn:feature_class":"P",
    "gn:feature_code":"PPL",
    "gn:name":"Kampung Waang",
    "gn:population":0,
    "gn:timezone":"Asia/Kuching",
    "iso:country":"MY",
    "name:msa_x_preferred":[
        "Kampung Waang"
    ],
    "name:und_x_variant":[
        "Kampong Wang"
    ],
    "wof:name":"Kampung Waang",
    "wof:placetype":"locality"
},
  "geometry": {"coordinates":[116.57640000000001,5.9374],"type":"Point"}
}