{
  "type": "Feature",
  "properties": {
    "gn:admin1_code":"2",
    "gn:asciiname":"Kampong Bagan",
    "gn:country_code":"MY",
    "gn:dem":5,
    "gn:feature_class":"P",
    "gn:feature_code":"PPL",
    "gn:name":"Kampong Bagan",
    "gn:population":0,
    "gn:timezone":"Asia/Kuala_Lumpur",
    "iso:country":"MY",
    "wof:name":"Kampong Bagan",
    "wof:placetype":"locality"
},
  "geometry": {"coordinates":[100.34999999999999,6.26667],"type":"Point"}
}