{
  "type": "Feature",
  "properties": {
    "gn:admin1_code":"6",
    "gn:asciiname":"Kampung Pamah Dusun",
    "gn:country_code":"MY",
    "gn:dem":61,
    "gn:feature_class":"P",
    "gn:feature_code":"PPL",
    "gn:name":"Kampung Pamah Dusun",
    "gn:population":0,
    "gn:timezone":"Asia/Kuala_Lumpur",
    "iso:country":"MY",
    "name:msa_x_preferred":[
        "Kampung Pamah Dusun"
    ],
    "name:und_x_variant":[
        "Kampong Pamah Duson",
        "Kampong Pamah Dusun"
    ],
    "wof:name":"Kampung Pamah Dusun",
    "wof:placetype":"locality"
},
  "geometry": {"coordinates":[102.4267,3.9395],"type":"Point"}
}