{
  "type": "Feature",
  "properties": {
    "gn:admin1_code":"12.0",
    "gn:asciiname":"Taman Utama Kuala Kubu",
    "gn:country_code":"MY",
    "gn:dem":73,
    "gn:feature_class":"P",
    "gn:feature_code":"PPL",
    "gn:name":"Taman Utama Kuala Kubu",
    "gn:population":0,
    "gn:timezone":"Asia/Kuala_Lumpur",
    "iso:country":"MY",
    "name:msa_x_preferred":[
        "Taman Utama Kuala Kubu"
    ],
    "wof:name":"Taman Utama Kuala Kubu",
    "wof:placetype":"locality"
},
  "geometry": {"coordinates":[101.6472,3.56],"type":"Point"}
}