{
  "type": "Feature",
  "properties": {
    "gn:country":"MY",
    "gn:fcode":"PPLA3",
    "gn:population":0,
    "iso:country":"MY",
    "name:msa_x_preferred":[
        "Pulai Chondong"
    ],
    "name:und_x_variant":[
        "Pulai Chongdong"
    ],
    "qs:name":"Pulai Chondong",
    "qs:name_adm0":"Malaysia",
    "qs:name_adm1":"Kelantan",
    "qs:photos_9k":1,
    "qs:photos_9r":2,
    "qs:photos_all":40,
    "qs:photos_sr":0,
    "qs:placetype":"LocalAdmin",
    "qs:pop_sr":"0",
    "wof:name":"Pulai Chondong",
    "wof:placetype":"localadmin",
    "wof:population":0
},
  "geometry": {"coordinates":[102.23177,5.87133],"type":"Point"}
}