{
  "type": "Feature",
  "properties": {
    "gn:admin1_code":"8.0",
    "gn:asciiname":"Kampung Jejawi",
    "gn:cc2":"MY",
    "gn:country_code":"MY",
    "gn:dem":15,
    "gn:feature_class":"P",
    "gn:feature_code":"PPL",
    "gn:name":"Kampung Jejawi",
    "gn:population":0,
    "gn:timezone":"Asia/Kuala_Lumpur",
    "iso:country":"MY",
    "name:msa_x_preferred":[
        "Kampung Jejawi"
    ],
    "wof:name":"Kampung Jejawi",
    "wof:placetype":"locality"
},
  "geometry": {"coordinates":[100.23090000000001,6.44732],"type":"Point"}
}