{
  "type": "Feature",
  "properties": {
    "gn:admin1_code":"11",
    "gn:asciiname":"Rumah Jantau",
    "gn:cc2":"MY",
    "gn:country_code":"MY",
    "gn:dem":19,
    "gn:feature_class":"P",
    "gn:feature_code":"PPL",
    "gn:name":"Rumah Jantau",
    "gn:population":0,
    "gn:timezone":"Asia/Kuching",
    "iso:country":"MY",
    "name:und_x_variant":[
        "Rumah Jantan",
        "Rumah Jantau"
    ],
    "wof:name":"Rumah Jantau",
    "wof:placetype":"locality"
},
  "geometry": {"coordinates":[111.88333,2.21667],"type":"Point"}
}