{
  "type": "Feature",
  "properties": {
    "gn:country":"MY",
    "gn:fcode":"ADMD",
    "gn:population":0,
    "iso:country":"MY",
    "name:msa_x_preferred":[
        "Titi Tinggi"
    ],
    "qs:name":"Titi Tinggi",
    "qs:name_adm0":"Malaysia",
    "qs:name_adm1":"Perlis",
    "qs:photos":10,
    "qs:photos_1k":2,
    "qs:photos_9k":1,
    "qs:photos_9r":1,
    "qs:photos_all":10,
    "qs:photos_sr":1,
    "qs:placetype":"LocalAdmin",
    "qs:pop_sr":"0",
    "wof:name":"Titi Tinggi",
    "wof:placetype":"localadmin",
    "wof:population":0
},
  "geometry": {"coordinates":[100.24496000000001,6.63599],"type":"Point"}
}