{
  "type": "Feature",
  "properties": {
    "gn:admin1_code":"12",
    "gn:asciiname":"Kampong Serdang Belah",
    "gn:country_code":"MY",
    "gn:dem":6,
    "gn:feature_class":"P",
    "gn:feature_code":"PPL",
    "gn:name":"Kampong Serdang Belah",
    "gn:population":0,
    "gn:timezone":"Asia/Kuala_Lumpur",
    "iso:country":"MY",
    "name:msa_x_preferred":[
        "Kampung Serdang Belah"
    ],
    "wof:name":"Kampong Serdang Belah",
    "wof:placetype":"locality"
},
  "geometry": {"coordinates":[101.50166,2.82421],"type":"Point"}
}