{
  "type": "Feature",
  "properties": {
    "gn:gn_country":"MY",
    "gn:gn_fcode":"PPL",
    "gn:gn_pop":73176,
    "gn:population":73176,
    "iso:country":"MY",
    "name:eng_x_preferred":[
        "Senai"
    ],
    "name:msa_x_preferred":[
        "Taman Senai"
    ],
    "name:msa_x_variant":[
        "Senai"
    ],
    "name:nld_x_preferred":[
        "Senai"
    ],
    "name:pol_x_preferred":[
        "Senai"
    ],
    "name:rus_x_preferred":[
        "\u0421\u0435\u043d\u0430\u0438"
    ],
    "name:spa_x_preferred":[
        "Senai"
    ],
    "name:unk_x_variant":[
        "Senai"
    ],
    "name:zho_x_preferred":[
        "\u58eb\u4e43"
    ],
    "qs_pg:aaroncc":"MY",
    "qs_pg:gn_country":"MY",
    "qs_pg:gn_fcode":"PPL",
    "qs_pg:gn_pop":73176,
    "qs_pg:name":"Taman Sawi",
    "qs_pg:name_adm0":"Malaysia",
    "qs_pg:name_adm1":"Johor",
    "qs_pg:photos_9r":0,
    "qs_pg:photos_sr":0,
    "qs_pg:pop_sr":8,
    "qs_pg:qs_pg_placetype":"locality",
    "qs_pg:qs_pg_placetype_gp":"Town",
    "qs_pg:woe_adm0":23424901,
    "woe:adm0_id":23424901,
    "woe:name_adm0":"Malaysia",
    "woe:name_adm1":"Johor",
    "woe:placetype":"Town",
    "wof:name":"Taman Sawi",
    "wof:placetype":"locality",
    "wof:population":73176
},
  "geometry": {"coordinates":[103.64190000000001,1.6006],"type":"Point"}
}