{
  "type": "Feature",
  "properties": {
    "gn:admin1_code":"1.0",
    "gn:asciiname":"Kampung Sungai Buntu",
    "gn:country_code":"MY",
    "gn:dem":8,
    "gn:feature_class":"P",
    "gn:feature_code":"PPL",
    "gn:name":"Kampung Sungai Buntu",
    "gn:population":0,
    "gn:timezone":"Asia/Kuala_Lumpur",
    "iso:country":"MY",
    "name:msa_x_preferred":[
        "Kampung Sungai Buntu"
    ],
    "wof:name":"Kampung Sungai Buntu",
    "wof:placetype":"locality"
},
  "geometry": {"coordinates":[103.43680000000001,1.3652],"type":"Point"}
}