{
  "type": "Feature",
  "properties": {
    "gn:admin1_code":"8.0",
    "gn:asciiname":"Kampung Tebok Jin",
    "gn:cc2":"MY",
    "gn:country_code":"MY",
    "gn:dem":9,
    "gn:feature_class":"P",
    "gn:feature_code":"PPL",
    "gn:name":"Kampung Tebok Jin",
    "gn:population":0,
    "gn:timezone":"Asia/Kuala_Lumpur",
    "iso:country":"MY",
    "name:msa_x_preferred":[
        "Kampung Tebok Jin"
    ],
    "name:und_x_variant":[
        "Kampung Tebok"
    ],
    "wof:name":"Kampung Tebok Jin",
    "wof:placetype":"locality"
},
  "geometry": {"coordinates":[100.22019,6.34777],"type":"Point"}
}