{
  "type": "Feature",
  "properties": {
    "gn:admin1_code":"6.0",
    "gn:asciiname":"Kampung Gambut",
    "gn:country_code":"MY",
    "gn:dem":116,
    "gn:feature_class":"P",
    "gn:feature_code":"PPL",
    "gn:name":"Kampung Gambut",
    "gn:population":0,
    "gn:timezone":"Asia/Kuala_Lumpur",
    "iso:country":"MY",
    "name:msa_x_preferred":[
        "Kampung Gambut"
    ],
    "wof:name":"Kampung Gambut",
    "wof:placetype":"locality"
},
  "geometry": {"coordinates":[101.9128,4.0209],"type":"Point"}
}