{
  "type": "Feature",
  "properties": {
    "gn:admin1_code":"16",
    "gn:asciiname":"Kampung Tamonong",
    "gn:country_code":"MY",
    "gn:dem":11,
    "gn:feature_class":"P",
    "gn:feature_code":"PPL",
    "gn:name":"Kampung Tamonong",
    "gn:population":0,
    "gn:timezone":"Asia/Kuching",
    "iso:country":"MY",
    "name:msa_x_preferred":[
        "Kampung Tamonong"
    ],
    "name:und_x_variant":[
        "Tamonong",
        "Kampong Tamonong"
    ],
    "wof:name":"Kampung Tamonong",
    "wof:placetype":"locality"
},
  "geometry": {"coordinates":[116.2161,6.2263],"type":"Point"}
}