{
  "type": "Feature",
  "properties": {
    "gn:admin1_code":"1.0",
    "gn:asciiname":"Kampung Johor Lama",
    "gn:country_code":"MY",
    "gn:dem":10,
    "gn:feature_class":"P",
    "gn:feature_code":"PPL",
    "gn:name":"Kampung Johor Lama",
    "gn:population":0,
    "gn:timezone":"Asia/Kuala_Lumpur",
    "iso:country":"MY",
    "name:epo_x_preferred":[
        "Johor Lama"
    ],
    "name:msa_x_preferred":[
        "Kampung Johor Lama"
    ],
    "name:msa_x_variant":[
        "Johor Lama"
    ],
    "name:tam_x_preferred":[
        "\u0b9c\u0bca\u0b95\u0bc2\u0bb0\u0bcd \u0bb2\u0bbe\u0bae\u0bbe"
    ],
    "name:und_x_variant":[
        "Kampong Johore Lama",
        "Johore Lama",
        "Kampung Johor Lama"
    ],
    "wof:name":"Kampung Johor Lama",
    "wof:placetype":"locality"
},
  "geometry": {"coordinates":[104.0137,1.5862],"type":"Point"}
}