{
  "type": "Feature",
  "properties": {
    "gn:admin1_code":"16",
    "gn:asciiname":"Kampong Lapasan",
    "gn:country_code":"MY",
    "gn:dem":15,
    "gn:feature_class":"P",
    "gn:feature_code":"PPL",
    "gn:name":"Kampong Lapasan",
    "gn:population":0,
    "gn:timezone":"Asia/Kuching",
    "iso:country":"MY",
    "name:und_x_variant":[
        "Lapasan",
        "Kampong Lapasan"
    ],
    "wof:name":"Kampong Lapasan",
    "wof:placetype":"locality"
},
  "geometry": {"coordinates":[118.8646,5.0083],"type":"Point"}
}