{
  "type": "Feature",
  "properties": {
    "gn:admin1_code":"1.0",
    "gn:asciiname":"Chamek",
    "gn:country_code":"MY",
    "gn:dem":66,
    "gn:feature_class":"P",
    "gn:feature_code":"PPL",
    "gn:name":"Chamek",
    "gn:population":0,
    "gn:timezone":"Asia/Kuala_Lumpur",
    "iso:country":"MY",
    "name:msa_x_preferred":[
        "Chamek"
    ],
    "name:und_x_variant":[
        "Camik"
    ],
    "wof:name":"Chamek",
    "wof:placetype":"locality"
},
  "geometry": {"coordinates":[103.2406,2.1398],"type":"Point"}
}