{
  "type": "Feature",
  "properties": {
    "gn:admin1_code":"8.0",
    "gn:asciiname":"Padang Linching",
    "gn:country_code":"MY",
    "gn:dem":16,
    "gn:feature_class":"P",
    "gn:feature_code":"PPL",
    "gn:name":"Padang Linching",
    "gn:population":0,
    "gn:timezone":"Asia/Kuala_Lumpur",
    "iso:country":"MY",
    "name:msa_x_preferred":[
        "Padang Linching"
    ],
    "wof:name":"Padang Linching",
    "wof:placetype":"locality"
},
  "geometry": {"coordinates":[100.16889999999999,6.48867],"type":"Point"}
}