{
  "type": "Feature",
  "properties": {
    "gn:admin1_code":"16.0",
    "gn:asciiname":"Kampung Limantak",
    "gn:country_code":"MY",
    "gn:dem":21,
    "gn:feature_class":"P",
    "gn:feature_code":"PPL",
    "gn:name":"Kampung Limantak",
    "gn:population":0,
    "gn:timezone":"Asia/Kuching",
    "iso:country":"MY",
    "name:msa_x_preferred":[
        "Kampung Limantak"
    ],
    "wof:name":"Kampung Limantak",
    "wof:placetype":"locality"
},
  "geometry": {"coordinates":[115.81229999999999,5.4667],"type":"Point"}
}