{
  "type": "Feature",
  "properties": {
    "gn:admin1_code":"11",
    "gn:asciiname":"Kampung Rakut",
    "gn:country_code":"MY",
    "gn:dem":89,
    "gn:feature_class":"P",
    "gn:feature_code":"PPL",
    "gn:name":"Kampung Rakut",
    "gn:population":0,
    "gn:timezone":"Asia/Kuching",
    "iso:country":"MY",
    "name:und_x_variant":[
        "Rakut"
    ],
    "wof:name":"Kampung Rakut",
    "wof:placetype":"locality"
},
  "geometry": {"coordinates":[111.85469000000001,1.06073],"type":"Point"}
}