{
  "type": "Feature",
  "properties": {
    "gn:country":"MY",
    "gn:fcode":"PPL",
    "gn:population":0,
    "iso:country":"MY",
    "name:ast_x_preferred":[
        "Ganqing"
    ],
    "name:eng_x_preferred":[
        "Ganqing"
    ],
    "name:ind_x_preferred":[
        "Ganqing"
    ],
    "name:nld_x_preferred":[
        "Ganqing"
    ],
    "name:nob_x_preferred":[
        "Ganqing"
    ],
    "name:spa_x_preferred":[
        "Ganqing"
    ],
    "name:und_x_variant":[
        "Taik Hing"
    ],
    "name:vie_x_preferred":[
        "C\u1ea3m t\u00ecnh"
    ],
    "qs:name":"Kanching",
    "qs:name_adm0":"Malaysia",
    "qs:name_adm1":"Selangor",
    "qs:photos":24,
    "qs:photos_1k":5,
    "qs:photos_9k":1,
    "qs:photos_9r":1,
    "qs:photos_all":24,
    "qs:photos_sr":1,
    "qs:placetype":"Town",
    "qs:pop_sr":"0",
    "wd:wordcount":182,
    "wof:name":"Kanching",
    "wof:placetype":"locality",
    "wof:population":0
},
  "geometry": {"coordinates":[101.63333,3.28333],"type":"Point"}
}