{
  "type": "Feature",
  "properties": {
    "gn:admin1_code":"16",
    "gn:asciiname":"Sulopon",
    "gn:country_code":"MY",
    "gn:dem":298,
    "gn:feature_class":"P",
    "gn:feature_code":"PPL",
    "gn:name":"Sulopon",
    "gn:population":0,
    "gn:timezone":"Asia/Kuching",
    "iso:country":"MY",
    "wof:name":"Sulopon",
    "wof:placetype":"locality"
},
  "geometry": {"coordinates":[116.41667,4.55],"type":"Point"}
}