{
  "type": "Feature",
  "properties": {
    "gn:admin1_code":"16",
    "gn:asciiname":"Kampung Dungun Tunjong",
    "gn:country_code":"MY",
    "gn:dem":20,
    "gn:feature_class":"P",
    "gn:feature_code":"PPL",
    "gn:name":"Kampung Dungun Tunjong",
    "gn:population":0,
    "gn:timezone":"Asia/Kuching",
    "iso:country":"MY",
    "name:msa_x_preferred":[
        "Kampung Dungun Tunjong"
    ],
    "name:und_x_variant":[
        "Kampong Jung Tunjong"
    ],
    "wof:name":"Kampung Dungun Tunjong",
    "wof:placetype":"locality"
},
  "geometry": {"coordinates":[115.6009,5.4466],"type":"Point"}
}