{
  "type": "Feature",
  "properties": {
    "gn:admin1_code":"6",
    "gn:asciiname":"Paya Putat",
    "gn:country_code":"MY",
    "gn:dem":61,
    "gn:feature_class":"P",
    "gn:feature_code":"PPL",
    "gn:name":"Paya Putat",
    "gn:population":0,
    "gn:timezone":"Asia/Kuala_Lumpur",
    "iso:country":"MY",
    "wof:name":"Paya Putat",
    "wof:placetype":"locality"
},
  "geometry": {"coordinates":[102.21666999999999,3.51667],"type":"Point"}
}