{
  "type": "Feature",
  "properties": {
    "gn:admin1_code":"16",
    "gn:asciiname":"Kampong Kaung Malawan",
    "gn:country_code":"MY",
    "gn:dem":232,
    "gn:feature_class":"P",
    "gn:feature_code":"PPL",
    "gn:name":"Kampong Kaung Malawan",
    "gn:population":0,
    "gn:timezone":"Asia/Kuching",
    "iso:country":"MY",
    "name:msa_x_preferred":[
        "Kampong Kaung Malawan"
    ],
    "name:und_x_variant":[
        "Kaung Melawan"
    ],
    "wof:name":"Kampong Kaung Malawan",
    "wof:placetype":"locality"
},
  "geometry": {"coordinates":[116.4782,6.2541],"type":"Point"}
}