{
  "type": "Feature",
  "properties": {
    "gn:admin1_code":"1.0",
    "gn:asciiname":"Kampung Parit Seri Bengkal",
    "gn:country_code":"MY",
    "gn:dem":10,
    "gn:feature_class":"P",
    "gn:feature_code":"PPL",
    "gn:name":"Kampung Parit Seri Bengkal",
    "gn:population":0,
    "gn:timezone":"Asia/Kuala_Lumpur",
    "iso:country":"MY",
    "name:msa_x_preferred":[
        "Kampung Parit Seri Bengkal"
    ],
    "wof:name":"Kampung Parit Seri Bengkal",
    "wof:placetype":"locality"
},
  "geometry": {"coordinates":[103.0308,1.9123],"type":"Point"}
}