{
  "type": "Feature",
  "properties": {
    "gn:admin1_code":"16.0",
    "gn:asciiname":"Kampung Angkawangan",
    "gn:country_code":"MY",
    "gn:dem":353,
    "gn:feature_class":"P",
    "gn:feature_code":"PPL",
    "gn:name":"Kampung Angkawangan",
    "gn:population":0,
    "gn:timezone":"Asia/Kuching",
    "iso:country":"MY",
    "name:msa_x_preferred":[
        "Kampung Angkawangan"
    ],
    "wof:name":"Kampung Angkawangan",
    "wof:placetype":"locality"
},
  "geometry": {"coordinates":[116.19889999999999,5.0639],"type":"Point"}
}