{
  "type": "Feature",
  "properties": {
    "gn:admin1_code":"4",
    "gn:asciiname":"Kampung Tasek",
    "gn:country_code":"MY",
    "gn:dem":8,
    "gn:feature_class":"P",
    "gn:feature_code":"PPL",
    "gn:name":"Kampung Tasek",
    "gn:population":0,
    "gn:timezone":"Asia/Kuala_Lumpur",
    "iso:country":"MY",
    "name:msa_x_preferred":[
        "Kampung Tasek"
    ],
    "name:und_x_variant":[
        "Kampong Tasek"
    ],
    "wof:name":"Kampung Tasek",
    "wof:placetype":"locality"
},
  "geometry": {"coordinates":[102.5337,2.1366],"type":"Point"}
}