{
  "type": "Feature",
  "properties": {
    "gn:admin1_code":"11",
    "gn:asciiname":"Rumah Dadom",
    "gn:country_code":"MY",
    "gn:dem":88,
    "gn:feature_class":"P",
    "gn:feature_code":"PPL",
    "gn:name":"Rumah Dadom",
    "gn:population":0,
    "gn:timezone":"Asia/Kuching",
    "iso:country":"MY",
    "wof:name":"Rumah Dadom",
    "wof:placetype":"locality"
},
  "geometry": {"coordinates":[112.33333,1.83333],"type":"Point"}
}