{
  "type": "Feature",
  "properties": {
    "iso:country":"MY",
    "qs:name":"Taman Pinggir Taman Dr. Ismail",
    "qs:name_adm0":"Malaysia",
    "qs:name_adm1":"Kuala Lumpur",
    "qs:photos":45,
    "qs:photos_1k":9,
    "qs:photos_9k":1,
    "qs:photos_9r":2,
    "qs:photos_all":45,
    "qs:photos_sr":2,
    "qs:placetype":"Suburb",
    "qs:pop_sr":"0",
    "wof:name":"Taman Pinggir Taman Dr. Ismail",
    "wof:placetype":"neighbourhood"
},
  "geometry": {"coordinates":[101.627697,3.158684],"type":"Point"}
}