{
  "type": "Feature",
  "properties": {
    "gn:admin1_code":"6.0",
    "gn:asciiname":"Kampung Manggis",
    "gn:country_code":"MY",
    "gn:dem":54,
    "gn:feature_class":"P",
    "gn:feature_code":"PPL",
    "gn:name":"Kampung Manggis",
    "gn:population":0,
    "gn:timezone":"Asia/Kuala_Lumpur",
    "iso:country":"MY",
    "name:msa_x_preferred":[
        "Kampung Manggis"
    ],
    "wof:name":"Kampung Manggis",
    "wof:placetype":"locality"
},
  "geometry": {"coordinates":[103.0712,3.3569],"type":"Point"}
}