{
  "type": "Feature",
  "properties": {
    "gn:admin1_code":"1",
    "gn:asciiname":"Hock Moh Sawmill Quarters",
    "gn:cc2":"MY",
    "gn:country_code":"MY",
    "gn:dem":9,
    "gn:feature_class":"P",
    "gn:feature_code":"PPL",
    "gn:name":"Hock Moh Sawmill Quarters",
    "gn:population":0,
    "gn:timezone":"Asia/Kuala_Lumpur",
    "iso:country":"MY",
    "name:und_x_variant":[
        "Hock Mo Saw Mill",
        "Hock Moh Sawmill Quarters"
    ],
    "wof:name":"Hock Moh Sawmill Quarters",
    "wof:placetype":"locality"
},
  "geometry": {"coordinates":[103.91667,1.91667],"type":"Point"}
}