{
  "type": "Feature",
  "properties": {
    "gn:admin1_code":"4",
    "gn:asciiname":"Kampung Sungai Ayer Tawar",
    "gn:country_code":"MY",
    "gn:dem":11,
    "gn:feature_class":"P",
    "gn:feature_code":"PPL",
    "gn:name":"Kampung Sungai Ayer Tawar",
    "gn:population":0,
    "gn:timezone":"Asia/Kuala_Lumpur",
    "iso:country":"MY",
    "name:msa_x_preferred":[
        "Kampung Sungai Ayer Tawar"
    ],
    "name:und_x_variant":[
        "Kampong Sungai Ayer Tawar"
    ],
    "wof:name":"Kampung Sungai Ayer Tawar",
    "wof:placetype":"locality"
},
  "geometry": {"coordinates":[102.45140000000001,2.1379],"type":"Point"}
}