{
  "type": "Feature",
  "properties": {
    "gn:admin1_code":"3",
    "gn:asciiname":"Kampong Bukit Abal",
    "gn:country_code":"MY",
    "gn:dem":9,
    "gn:feature_class":"P",
    "gn:feature_code":"PPL",
    "gn:name":"Kampong Bukit Abal",
    "gn:population":0,
    "gn:timezone":"Asia/Kuala_Lumpur",
    "iso:country":"MY",
    "wof:name":"Kampong Bukit Abal",
    "wof:placetype":"locality"
},
  "geometry": {"coordinates":[102.34999999999999,5.86667],"type":"Point"}
}