{
  "type": "Feature",
  "properties": {
    "gn:admin1_code":"1.0",
    "gn:asciiname":"Kampung Tanjung Sengkawang",
    "gn:country_code":"MY",
    "gn:dem":39,
    "gn:feature_class":"P",
    "gn:feature_code":"PPL",
    "gn:name":"Kampung Tanjung Sengkawang",
    "gn:population":0,
    "gn:timezone":"Asia/Kuala_Lumpur",
    "iso:country":"MY",
    "name:msa_x_preferred":[
        "Kampung Tanjung Sengkawang"
    ],
    "wof:name":"Kampung Tanjung Sengkawang",
    "wof:placetype":"locality"
},
  "geometry": {"coordinates":[102.79510000000001,2.505],"type":"Point"}
}