{
  "type": "Feature",
  "properties": {
    "gn:admin1_code":"9.0",
    "gn:asciiname":"Taman Bukit",
    "gn:country_code":"MY",
    "gn:dem":10,
    "gn:feature_class":"P",
    "gn:feature_code":"PPL",
    "gn:name":"Taman Bukit",
    "gn:population":0,
    "gn:timezone":"Asia/Kuala_Lumpur",
    "iso:country":"MY",
    "name:msa_x_preferred":[
        "Taman Bukit"
    ],
    "wof:name":"Taman Bukit",
    "wof:placetype":"locality"
},
  "geometry": {"coordinates":[100.45996,5.35273],"type":"Point"}
}