{
  "type": "Feature",
  "properties": {
    "gn:admin1_code":"16",
    "gn:asciiname":"Kampung Madsangoh",
    "gn:country_code":"MY",
    "gn:dem":671,
    "gn:feature_class":"P",
    "gn:feature_code":"PPL",
    "gn:name":"Kampung Madsangoh",
    "gn:population":0,
    "gn:timezone":"Asia/Kuching",
    "iso:country":"MY",
    "name:msa_x_preferred":[
        "Kampung Madsangoh"
    ],
    "name:und_x_variant":[
        "Kampong Mensangoh"
    ],
    "wof:name":"Kampung Madsangoh",
    "wof:placetype":"locality"
},
  "geometry": {"coordinates":[116.53019999999999,5.8672],"type":"Point"}
}