{
  "type": "Feature",
  "properties": {
    "gn:admin1_code":"4",
    "gn:asciiname":"Kampung Ulu Jasin",
    "gn:country_code":"MY",
    "gn:dem":23,
    "gn:feature_class":"P",
    "gn:feature_code":"PPL",
    "gn:name":"Kampung Ulu Jasin",
    "gn:population":0,
    "gn:timezone":"Asia/Kuala_Lumpur",
    "iso:country":"MY",
    "name:msa_x_preferred":[
        "Kampung Ulu Jasin"
    ],
    "name:und_x_variant":[
        "Kampong Ulu Jasin"
    ],
    "wof:name":"Kampung Ulu Jasin",
    "wof:placetype":"locality"
},
  "geometry": {"coordinates":[102.4401,2.2961],"type":"Point"}
}