{
  "type": "Feature",
  "properties": {
    "gn:admin1_code":"4",
    "gn:asciiname":"Kampung Lebok",
    "gn:country_code":"MY",
    "gn:dem":23,
    "gn:feature_class":"P",
    "gn:feature_code":"PPL",
    "gn:name":"Kampung Lebok",
    "gn:population":0,
    "gn:timezone":"Asia/Kuala_Lumpur",
    "iso:country":"MY",
    "name:msa_x_preferred":[
        "Kampung Lebok"
    ],
    "name:und_x_variant":[
        "Kampong Lekok"
    ],
    "wof:name":"Kampung Lebok",
    "wof:placetype":"locality"
},
  "geometry": {"coordinates":[102.1113,2.3623],"type":"Point"}
}