{
  "type": "Feature",
  "properties": {
    "gn:admin1_code":"6",
    "gn:asciiname":"Kampung Sentang",
    "gn:country_code":"MY",
    "gn:dem":106,
    "gn:feature_class":"P",
    "gn:feature_code":"PPL",
    "gn:name":"Kampung Sentang",
    "gn:population":0,
    "gn:timezone":"Asia/Kuala_Lumpur",
    "iso:country":"MY",
    "name:msa_x_preferred":[
        "Kampung Sentang"
    ],
    "name:und_x_variant":[
        "Kampong Sentang"
    ],
    "wof:name":"Kampung Sentang",
    "wof:placetype":"locality"
},
  "geometry": {"coordinates":[102.0565,4.3774],"type":"Point"}
}