{
  "type": "Feature",
  "properties": {
    "gn:admin1_code":"13",
    "gn:asciiname":"Kampung Kubang Tangga",
    "gn:country_code":"MY",
    "gn:dem":7,
    "gn:feature_class":"P",
    "gn:feature_code":"PPL",
    "gn:name":"Kampung Kubang Tangga",
    "gn:population":0,
    "gn:timezone":"Asia/Kuala_Lumpur",
    "iso:country":"MY",
    "name:msa_x_preferred":[
        "Kampung Kubang Tangga"
    ],
    "name:und_x_variant":[
        "Kampong Kubang Tangga"
    ],
    "wof:name":"Kampung Kubang Tangga",
    "wof:placetype":"locality"
},
  "geometry": {"coordinates":[103.0994,5.2936],"type":"Point"}
}