{
  "type": "Feature",
  "properties": {
    "gn:admin1_code":"2",
    "gn:asciiname":"Kampung Kubang Rotan",
    "gn:country_code":"MY",
    "gn:dem":6,
    "gn:feature_class":"P",
    "gn:feature_code":"PPL",
    "gn:name":"Kampung Kubang Rotan",
    "gn:population":0,
    "gn:timezone":"Asia/Kuala_Lumpur",
    "iso:country":"MY",
    "name:msa_x_preferred":[
        "Kampung Kubang Rotan"
    ],
    "name:und_x_variant":[
        "Kampong Kubang Rotan"
    ],
    "wof:name":"Kampung Kubang Rotan",
    "wof:placetype":"locality"
},
  "geometry": {"coordinates":[100.30799,6.13868],"type":"Point"}
}