{
  "type": "Feature",
  "properties": {
    "gn:admin1_code":"7",
    "gn:asciiname":"Kampong Pasir Besar",
    "gn:country_code":"MY",
    "gn:dem":100,
    "gn:feature_class":"P",
    "gn:feature_code":"PPL",
    "gn:name":"Kampong Pasir Besar",
    "gn:population":0,
    "gn:timezone":"Asia/Kuala_Lumpur",
    "iso:country":"MY",
    "wof:name":"Kampong Pasir Besar",
    "wof:placetype":"locality"
},
  "geometry": {"coordinates":[100.78333000000001,4.78333],"type":"Point"}
}