{
  "type": "Feature",
  "properties": {
    "gn:admin1_code":"2.0",
    "gn:asciiname":"Kota Kuala Muda",
    "gn:country_code":"MY",
    "gn:dem":4,
    "gn:feature_class":"P",
    "gn:feature_code":"PPL",
    "gn:name":"Kota Kuala Muda",
    "gn:population":0,
    "gn:timezone":"Asia/Kuala_Lumpur",
    "iso:country":"MY",
    "name:msa_x_preferred":[
        "Kota Kuala Muda"
    ],
    "wof:name":"Kota Kuala Muda",
    "wof:placetype":"locality"
},
  "geometry": {"coordinates":[100.37085,5.58822],"type":"Point"}
}