{
  "type": "Feature",
  "properties": {
    "gn:admin1_code":"9.0",
    "gn:asciiname":"Kampung Pulau Betung",
    "gn:country_code":"MY",
    "gn:dem":8,
    "gn:feature_class":"P",
    "gn:feature_code":"PPL",
    "gn:name":"Kampung Pulau Betung",
    "gn:population":0,
    "gn:timezone":"Asia/Kuala_Lumpur",
    "iso:country":"MY",
    "name:und_x_variant":[
        "Bagan Pulau Betang",
        "Bagan Pulau Betong",
        "Pulau Betong",
        "Kampung Pulau Betung"
    ],
    "wof:name":"Kampung Pulau Betung",
    "wof:placetype":"locality"
},
  "geometry": {"coordinates":[100.20287999999999,5.3054],"type":"Point"}
}