{
  "type": "Feature",
  "properties": {
    "gn:admin1_code":"16.0",
    "gn:asciiname":"Marintaman",
    "gn:cc2":"MY",
    "gn:country_code":"MY",
    "gn:dem":145,
    "gn:feature_class":"P",
    "gn:feature_code":"PPL",
    "gn:name":"Marintaman",
    "gn:population":0,
    "gn:timezone":"Asia/Kuching",
    "iso:country":"MY",
    "name:und_x_variant":[
        "Kampong Merintaman",
        "Merintaman",
        "Marintaman"
    ],
    "wof:name":"Marintaman",
    "wof:placetype":"locality"
},
  "geometry": {"coordinates":[115.56667,5.03333],"type":"Point"}
}