{
  "type": "Feature",
  "properties": {
    "gn:admin1_code":"5.0",
    "gn:asciiname":"Kampung Solok Bagoh",
    "gn:country_code":"MY",
    "gn:dem":141,
    "gn:feature_class":"P",
    "gn:feature_code":"PPL",
    "gn:name":"Kampung Solok Bagoh",
    "gn:population":0,
    "gn:timezone":"Asia/Kuala_Lumpur",
    "iso:country":"MY",
    "name:msa_x_preferred":[
        "Kampung Solok Bagoh"
    ],
    "wof:name":"Kampung Solok Bagoh",
    "wof:placetype":"locality"
},
  "geometry": {"coordinates":[102.2401,2.6422],"type":"Point"}
}