{
  "type": "Feature",
  "properties": {
    "gn:country":"MY",
    "iso:country":"MY",
    "name:ara_x_preferred":[
        "\u062a\u0627\u0648\u0627\u0648"
    ],
    "name:ben_x_preferred":[
        "\u09a4\u09be\u09ac\u09be\u0989"
    ],
    "name:bug_x_preferred":[
        "Tawau"
    ],
    "name:bul_x_preferred":[
        "\u0422\u0430\u0432\u0430\u0443"
    ],
    "name:dan_x_preferred":[
        "Tawau"
    ],
    "name:deu_x_preferred":[
        "Tawau"
    ],
    "name:ell_x_preferred":[
        "\u03a4\u03b1\u03b2\u03ac\u03bf\u03c5"
    ],
    "name:eng_x_preferred":[
        "Tawau"
    ],
    "name:epo_x_preferred":[
        "Tawau"
    ],
    "name:fin_x_preferred":[
        "Tawau"
    ],
    "name:fra_x_preferred":[
        "Tawau"
    ],
    "name:guj_x_preferred":[
        "\u0aa4\u0abe\u0ab5\u0acc"
    ],
    "name:hin_x_preferred":[
        "\u0924\u0935\u094c"
    ],
    "name:ind_x_preferred":[
        "Tawau"
    ],
    "name:ita_x_preferred":[
        "Tawau"
    ],
    "name:jpn_x_preferred":[
        "\u30bf\u30ef\u30a6"
    ],
    "name:kan_x_preferred":[
        "\u0ca4\u0cb5\u0cbe\u0cb5\u0cc1"
    ],
    "name:kor_x_preferred":[
        "\ud0c0\uc640\uc6b0"
    ],
    "name:lav_x_preferred":[
        "Tavau"
    ],
    "name:lit_x_preferred":[
        "Tavau"
    ],
    "name:mar_x_preferred":[
        "\u0924\u093e\u0935\u094c"
    ],
    "name:msa_x_preferred":[
        "Tawau"
    ],
    "name:nld_x_preferred":[
        "Tawau"
    ],
    "name:nob_x_preferred":[
        "Tawau"
    ],
    "name:pol_x_preferred":[
        "Tawau"
    ],
    "name:por_x_preferred":[
        "Tawau"
    ],
    "name:rus_x_preferred":[
        "\u0422\u0430\u0432\u0430\u0443"
    ],
    "name:sco_x_preferred":[
        "Tawau"
    ],
    "name:sin_x_preferred":[
        "\u0da7\u0dc0\u0dde"
    ],
    "name:spa_x_preferred":[
        "Tawau"
    ],
    "name:swe_x_preferred":[
        "Tawau"
    ],
    "name:tam_x_preferred":[
        "\u0ba4\u0bbe\u0bb5\u0bbe\u0bb5\u0bcd"
    ],
    "name:tel_x_preferred":[
        "\u0c24\u0c3e\u0c35\u0c4c"
    ],
    "name:tha_x_preferred":[
        "\u0e15\u0e32\u0e40\u0e27\u0e32"
    ],
    "name:tur_x_preferred":[
        "Tawau"
    ],
    "name:ukr_x_preferred":[
        "\u0422\u0430\u0432\u0430\u0443"
    ],
    "name:urd_x_preferred":[
        "\u062a\u0627\u0648\u0627\u0648"
    ],
    "name:vie_x_preferred":[
        "Tawau"
    ],
    "name:zho_x_preferred":[
        "\u6597\u6e56"
    ],
    "qs:name":"Tawau",
    "qs:name_adm0":"Malaysia",
    "qs:name_adm1":"Sabah",
    "qs:photos":6,
    "qs:photos_1k":1,
    "qs:photos_9k":3,
    "qs:photos_9r":6,
    "qs:photos_all":768,
    "qs:photos_sr":1,
    "qs:placetype":"LocalAdmin",
    "qs:pop_sr":"0",
    "wd:elevation":8.0,
    "wd:population":113809,
    "wd:wordcount":6493,
    "wof:name":"Tawau",
    "wof:placetype":"localadmin",
    "wof:population":113809
},
  "geometry": {"coordinates":[117.888278,4.246956],"type":"Point"}
}