{
  "type": "Feature",
  "properties": {
    "gn:country":"MY",
    "iso:country":"MY",
    "qs:name":"Tawau",
    "qs:name_adm0":"Malaysia",
    "qs:name_adm1":"Sabah",
    "qs:photos":6,
    "qs:photos_1k":1,
    "qs:photos_9k":3,
    "qs:photos_9r":6,
    "qs:photos_all":768,
    "qs:photos_sr":1,
    "qs:placetype":"LocalAdmin",
    "qs:pop_sr":"0",
    "wd:elevation":8.0,
    "wd:population":113809,
    "wd:wordcount":6493,
    "wof:name":"Tawau",
    "wof:placetype":"localadmin",
    "wof:population":113809
},
  "geometry": {"coordinates":[117.888278,4.246956],"type":"Point"}
}