{
  "type": "Feature",
  "properties": {
    "gn:admin1_code":"6.0",
    "gn:asciiname":"Pusat Pelancong Kampung Sepat",
    "gn:country_code":"MY",
    "gn:dem":7,
    "gn:feature_class":"P",
    "gn:feature_code":"PPL",
    "gn:name":"Pusat Pelancong Kampung Sepat",
    "gn:population":0,
    "gn:timezone":"Asia/Kuala_Lumpur",
    "iso:country":"MY",
    "name:msa_x_preferred":[
        "Pusat Pelancong Kampung Sepat"
    ],
    "wof:name":"Pusat Pelancong Kampung Sepat",
    "wof:placetype":"locality"
},
  "geometry": {"coordinates":[103.3366,3.6977],"type":"Point"}
}