{
  "type": "Feature",
  "properties": {
    "gn:admin1_code":"2.0",
    "gn:asciiname":"Kampung Tengah Yan Kechil",
    "gn:country_code":"MY",
    "gn:dem":3,
    "gn:feature_class":"P",
    "gn:feature_code":"PPL",
    "gn:name":"Kampung Tengah Yan Kechil",
    "gn:population":0,
    "gn:timezone":"Asia/Kuala_Lumpur",
    "iso:country":"MY",
    "name:msa_x_preferred":[
        "Kampung Tengah Yan Kechil"
    ],
    "wof:name":"Kampung Tengah Yan Kechil",
    "wof:placetype":"locality"
},
  "geometry": {"coordinates":[100.38185,5.82654],"type":"Point"}
}