{
  "type": "Feature",
  "properties": {
    "gn:admin1_code":"6",
    "gn:asciiname":"Kampung Temau",
    "gn:country_code":"MY",
    "gn:dem":108,
    "gn:feature_class":"P",
    "gn:feature_code":"PPL",
    "gn:name":"Kampung Temau",
    "gn:population":0,
    "gn:timezone":"Asia/Kuala_Lumpur",
    "iso:country":"MY",
    "name:msa_x_preferred":[
        "Kampung Temau"
    ],
    "name:und_x_variant":[
        "Kampong Temau"
    ],
    "wof:name":"Kampung Temau",
    "wof:placetype":"locality"
},
  "geometry": {"coordinates":[101.89100000000001,3.9318],"type":"Point"}
}