{
  "type": "Feature",
  "properties": {
    "gn:admin1_code":"16",
    "gn:asciiname":"Kampung Nong Koulod",
    "gn:country_code":"MY",
    "gn:dem":11,
    "gn:feature_class":"P",
    "gn:feature_code":"PPL",
    "gn:name":"Kampung Nong Koulod",
    "gn:population":0,
    "gn:timezone":"Asia/Kuching",
    "iso:country":"MY",
    "name:msa_x_preferred":[
        "Kampung Nong Koulod"
    ],
    "name:und_x_variant":[
        "Kampong Nong Koulod"
    ],
    "wof:name":"Kampung Nong Koulod",
    "wof:placetype":"locality"
},
  "geometry": {"coordinates":[116.21120000000001,6.1318],"type":"Point"}
}