{
  "type": "Feature",
  "properties": {
    "gn:admin1_code":"5.0",
    "gn:asciiname":"Kampung Batang Peradong",
    "gn:country_code":"MY",
    "gn:dem":162,
    "gn:feature_class":"P",
    "gn:feature_code":"PPL",
    "gn:name":"Kampung Batang Peradong",
    "gn:population":0,
    "gn:timezone":"Asia/Kuala_Lumpur",
    "iso:country":"MY",
    "name:msa_x_preferred":[
        "Kampung Batang Peradong"
    ],
    "wof:name":"Kampung Batang Peradong",
    "wof:placetype":"locality"
},
  "geometry": {"coordinates":[102.1284,2.9617],"type":"Point"}
}