{
  "type": "Feature",
  "properties": {
    "gn:admin1_code":"16.0",
    "gn:asciiname":"Kampung Rokom",
    "gn:country_code":"MY",
    "gn:dem":33,
    "gn:feature_class":"P",
    "gn:feature_code":"PPL",
    "gn:name":"Kampung Rokom",
    "gn:population":0,
    "gn:timezone":"Asia/Kuching",
    "iso:country":"MY",
    "name:msa_x_preferred":[
        "Kampung Rokom"
    ],
    "wof:name":"Kampung Rokom",
    "wof:placetype":"locality"
},
  "geometry": {"coordinates":[117.0919,6.6931],"type":"Point"}
}