{
  "type": "Feature",
  "properties": {
    "gn:admin1_code":"16",
    "gn:asciiname":"Kampung Lumanggas",
    "gn:country_code":"MY",
    "gn:dem":7,
    "gn:feature_class":"P",
    "gn:feature_code":"PPL",
    "gn:name":"Kampung Lumanggas",
    "gn:population":0,
    "gn:timezone":"Asia/Kuching",
    "iso:country":"MY",
    "name:msa_x_preferred":[
        "Kampung Lumanggas"
    ],
    "name:und_x_variant":[
        "Kampong Lumangas"
    ],
    "wof:name":"Kampung Lumanggas",
    "wof:placetype":"locality"
},
  "geometry": {"coordinates":[118.5744,4.5489],"type":"Point"}
}