{
  "type": "Feature",
  "properties": {
    "gn:admin1_code":"2",
    "gn:asciiname":"Kampung Tanah Liat",
    "gn:cc2":"MY",
    "gn:country_code":"MY",
    "gn:dem":60,
    "gn:feature_class":"P",
    "gn:feature_code":"PPL",
    "gn:name":"Kampung Tanah Liat",
    "gn:population":0,
    "gn:timezone":"Asia/Kuala_Lumpur",
    "iso:country":"MY",
    "name:msa_x_preferred":[
        "Kampung Tanah Liat"
    ],
    "name:und_x_variant":[
        "Kampong Tanah Liat"
    ],
    "wof:name":"Kampung Tanah Liat",
    "wof:placetype":"locality"
},
  "geometry": {"coordinates":[100.72920000000001,5.75326],"type":"Point"}
}