{
  "type": "Feature",
  "properties": {
    "gn:admin1_code":"4.0",
    "gn:asciiname":"Anak Ayer Kepong",
    "gn:country_code":"MY",
    "gn:dem":27,
    "gn:feature_class":"P",
    "gn:feature_code":"PPL",
    "gn:name":"Anak Ayer Kepong",
    "gn:population":0,
    "gn:timezone":"Asia/Kuala_Lumpur",
    "iso:country":"MY",
    "name:msa_x_preferred":[
        "Anak Ayer Kepong"
    ],
    "wof:name":"Anak Ayer Kepong",
    "wof:placetype":"locality"
},
  "geometry": {"coordinates":[102.38590000000001,2.2327],"type":"Point"}
}