{
  "type": "Feature",
  "properties": {
    "gn:admin1_code":"5.0",
    "gn:asciiname":"Kampung Jawa Serting Tengah",
    "gn:country_code":"MY",
    "gn:dem":78,
    "gn:feature_class":"P",
    "gn:feature_code":"PPL",
    "gn:name":"Kampung Jawa Serting Tengah",
    "gn:population":0,
    "gn:timezone":"Asia/Kuala_Lumpur",
    "iso:country":"MY",
    "name:msa_x_preferred":[
        "Kampung Jawa Serting Tengah"
    ],
    "wof:name":"Kampung Jawa Serting Tengah",
    "wof:placetype":"locality"
},
  "geometry": {"coordinates":[102.3301,2.8612],"type":"Point"}
}