{
  "type": "Feature",
  "properties": {
    "gn:admin1_code":"7.0",
    "gn:asciiname":"Kampung Rahmat",
    "gn:country_code":"MY",
    "gn:dem":8,
    "gn:feature_class":"P",
    "gn:feature_code":"PPL",
    "gn:name":"Kampung Rahmat",
    "gn:population":0,
    "gn:timezone":"Asia/Kuala_Lumpur",
    "iso:country":"MY",
    "name:msa_x_preferred":[
        "Kampung Rahmat"
    ],
    "wof:name":"Kampung Rahmat",
    "wof:placetype":"locality"
},
  "geometry": {"coordinates":[100.786,4.1145],"type":"Point"}
}