{
  "type": "Feature",
  "properties": {
    "gn:admin1_code":"6.0",
    "gn:asciiname":"Kampung Hayat",
    "gn:country_code":"MY",
    "gn:dem":76,
    "gn:feature_class":"P",
    "gn:feature_code":"PPL",
    "gn:name":"Kampung Hayat",
    "gn:population":0,
    "gn:timezone":"Asia/Kuala_Lumpur",
    "iso:country":"MY",
    "name:msa_x_preferred":[
        "Kampung Hayat"
    ],
    "wof:name":"Kampung Hayat",
    "wof:placetype":"locality"
},
  "geometry": {"coordinates":[102.20489999999999,3.1711],"type":"Point"}
}