{
  "type": "Feature",
  "properties": {
    "gn:admin1_code":"9.0",
    "gn:asciiname":"Kampung Bukit Jelutong",
    "gn:country_code":"MY",
    "gn:dem":13,
    "gn:feature_class":"P",
    "gn:feature_code":"PPL",
    "gn:name":"Kampung Bukit Jelutong",
    "gn:population":0,
    "gn:timezone":"Asia/Kuala_Lumpur",
    "iso:country":"MY",
    "name:msa_x_preferred":[
        "Kampung Bukit Jelutong"
    ],
    "wof:name":"Kampung Bukit Jelutong",
    "wof:placetype":"locality"
},
  "geometry": {"coordinates":[100.44313,5.42288],"type":"Point"}
}