{
  "type": "Feature",
  "properties": {
    "gn:admin1_code":"2",
    "gn:asciiname":"Kampung Selarong Batang",
    "gn:country_code":"MY",
    "gn:dem":5,
    "gn:feature_class":"P",
    "gn:feature_code":"PPL",
    "gn:name":"Kampung Selarong Batang",
    "gn:population":0,
    "gn:timezone":"Asia/Kuala_Lumpur",
    "iso:country":"MY",
    "name:msa_x_preferred":[
        "Kampung Selarong Batang"
    ],
    "name:und_x_variant":[
        "Kampong Selarong Batang"
    ],
    "wof:name":"Kampung Selarong Batang",
    "wof:placetype":"locality"
},
  "geometry": {"coordinates":[100.38800999999999,6.00922],"type":"Point"}
}