{
  "type": "Feature",
  "properties": {
    "gn:admin1_code":"7.0",
    "gn:asciiname":"Kampung Damar Laut",
    "gn:country_code":"MY",
    "gn:dem":8,
    "gn:feature_class":"P",
    "gn:feature_code":"PPL",
    "gn:name":"Kampung Damar Laut",
    "gn:population":0,
    "gn:timezone":"Asia/Kuala_Lumpur",
    "iso:country":"MY",
    "name:msa_x_preferred":[
        "Kampung Damar Laut"
    ],
    "name:und_x_variant":[
        "Damar Laut",
        "Kampung Damar Laut"
    ],
    "wof:name":"Kampung Damar Laut",
    "wof:placetype":"locality"
},
  "geometry": {"coordinates":[100.63760000000001,4.2532],"type":"Point"}
}