{
  "type": "Feature",
  "properties": {
    "gn:admin1_code":"1",
    "gn:asciiname":"Kampung Parit Rambai",
    "gn:country_code":"MY",
    "gn:dem":10,
    "gn:feature_class":"P",
    "gn:feature_code":"PPL",
    "gn:name":"Kampung Parit Rambai",
    "gn:population":0,
    "gn:timezone":"Asia/Kuala_Lumpur",
    "iso:country":"MY",
    "name:msa_x_preferred":[
        "Kampung Parit Rambai"
    ],
    "name:und_x_variant":[
        "Kampong Parit Rambai"
    ],
    "wof:name":"Kampung Parit Rambai",
    "wof:placetype":"locality"
},
  "geometry": {"coordinates":[102.65089999999999,2.2005],"type":"Point"}
}