{
  "type": "Feature",
  "properties": {
    "gn:admin1_code":"11",
    "gn:asciiname":"Rumah Sungai Medalam",
    "gn:country_code":"MY",
    "gn:dem":42,
    "gn:feature_class":"P",
    "gn:feature_code":"PPL",
    "gn:name":"Rumah Sungai Medalam",
    "gn:population":0,
    "gn:timezone":"Asia/Kuching",
    "iso:country":"MY",
    "wof:name":"Rumah Sungai Medalam",
    "wof:placetype":"locality"
},
  "geometry": {"coordinates":[114.90000000000001,4.31667],"type":"Point"}
}