{
  "type": "Feature",
  "properties": {
    "gn:admin1_code":"6",
    "gn:asciiname":"Kampung Padang",
    "gn:country_code":"MY",
    "gn:dem":20,
    "gn:feature_class":"P",
    "gn:feature_code":"PPL",
    "gn:name":"Kampung Padang",
    "gn:population":0,
    "gn:timezone":"Asia/Kuala_Lumpur",
    "iso:country":"MY",
    "name:msa_x_preferred":[
        "Kampung Padang"
    ],
    "name:und_x_variant":[
        "Kampong Padang"
    ],
    "wof:name":"Kampung Padang",
    "wof:placetype":"locality"
},
  "geometry": {"coordinates":[103.00839999999999,3.0621],"type":"Point"}
}