{
  "type": "Feature",
  "properties": {
    "gn:admin1_code":"9.0",
    "gn:asciiname":"Taman Penanti",
    "gn:cc2":"MY",
    "gn:country_code":"MY",
    "gn:dem":11,
    "gn:feature_class":"P",
    "gn:feature_code":"PPL",
    "gn:name":"Taman Penanti",
    "gn:population":0,
    "gn:timezone":"Asia/Kuala_Lumpur",
    "iso:country":"MY",
    "name:msa_x_preferred":[
        "Taman Penanti"
    ],
    "wof:name":"Taman Penanti",
    "wof:placetype":"locality"
},
  "geometry": {"coordinates":[100.45911,5.40718],"type":"Point"}
}