{
  "type": "Feature",
  "properties": {
    "gn:admin1_code":"16.0",
    "gn:asciiname":"Lakai Lakai",
    "gn:country_code":"MY",
    "gn:dem":237,
    "gn:feature_class":"P",
    "gn:feature_code":"PPL",
    "gn:name":"Lakai Lakai",
    "gn:population":0,
    "gn:timezone":"Asia/Kuching",
    "iso:country":"MY",
    "wof:name":"Lakai Lakai",
    "wof:placetype":"locality"
},
  "geometry": {"coordinates":[118.45,4.68333],"type":"Point"}
}