{
  "type": "Feature",
  "properties": {
    "gn:admin1_code":"13",
    "gn:asciiname":"Kampung Tanjung Lali",
    "gn:cc2":"MY",
    "gn:country_code":"MY",
    "gn:dem":9,
    "gn:feature_class":"P",
    "gn:feature_code":"PPL",
    "gn:name":"Kampung Tanjung Lali",
    "gn:population":0,
    "gn:timezone":"Asia/Kuala_Lumpur",
    "iso:country":"MY",
    "name:msa_x_preferred":[
        "Kampung Tanjung Lali"
    ],
    "name:und_x_variant":[
        "Kampong Tanjong Lali"
    ],
    "wof:name":"Kampung Tanjung Lali",
    "wof:placetype":"locality"
},
  "geometry": {"coordinates":[102.56995999999999,5.82291],"type":"Point"}
}