{
  "type": "Feature",
  "properties": {
    "gn:admin1_code":"6",
    "gn:asciiname":"Kampung Runcang",
    "gn:country_code":"MY",
    "gn:dem":25,
    "gn:feature_class":"P",
    "gn:feature_code":"PPL",
    "gn:name":"Kampung Runcang",
    "gn:population":0,
    "gn:timezone":"Asia/Kuala_Lumpur",
    "iso:country":"MY",
    "name:msa_x_preferred":[
        "Kampung Runcang"
    ],
    "name:und_x_variant":[
        "Kampong Unchang"
    ],
    "wof:name":"Kampung Runcang",
    "wof:placetype":"locality"
},
  "geometry": {"coordinates":[103.1836,3.2866],"type":"Point"}
}