{
  "type": "Feature",
  "properties": {
    "gn:admin1_code":"2.0",
    "gn:asciiname":"Kampung Baharu Padang Lembu",
    "gn:cc2":"MY",
    "gn:country_code":"MY",
    "gn:dem":34,
    "gn:feature_class":"P",
    "gn:feature_code":"PPL",
    "gn:name":"Kampung Baharu Padang Lembu",
    "gn:population":0,
    "gn:timezone":"Asia/Kuala_Lumpur",
    "iso:country":"MY",
    "name:msa_x_preferred":[
        "Kampung Baharu Padang Lembu"
    ],
    "wof:name":"Kampung Baharu Padang Lembu",
    "wof:placetype":"locality"
},
  "geometry": {"coordinates":[100.53579999999999,5.84339],"type":"Point"}
}