{
  "type": "Feature",
  "properties": {
    "gn:admin1_code":"11.0",
    "gn:asciiname":"Rumah Ribai",
    "gn:country_code":"MY",
    "gn:dem":43,
    "gn:feature_class":"P",
    "gn:feature_code":"PPL",
    "gn:name":"Rumah Ribai",
    "gn:population":0,
    "gn:timezone":"Asia/Kuching",
    "iso:country":"MY",
    "name:msa_x_preferred":[
        "Rumah Ribai"
    ],
    "wof:name":"Rumah Ribai",
    "wof:placetype":"locality"
},
  "geometry": {"coordinates":[113.51912,1.87302],"type":"Point"}
}