{
  "type": "Feature",
  "properties": {
    "gn:admin1_code":"6.0",
    "gn:asciiname":"Kampung Sungai Kepung",
    "gn:country_code":"MY",
    "gn:dem":62,
    "gn:feature_class":"P",
    "gn:feature_code":"PPL",
    "gn:name":"Kampung Sungai Kepung",
    "gn:population":0,
    "gn:timezone":"Asia/Kuala_Lumpur",
    "iso:country":"MY",
    "name:msa_x_preferred":[
        "Kampung Sungai Kepung"
    ],
    "wof:name":"Kampung Sungai Kepung",
    "wof:placetype":"locality"
},
  "geometry": {"coordinates":[102.24979999999999,3.4943],"type":"Point"}
}