{
  "type": "Feature",
  "properties": {
    "gn:admin1_code":"5.0",
    "gn:asciiname":"Kampung Gedang",
    "gn:country_code":"MY",
    "gn:dem":79,
    "gn:feature_class":"P",
    "gn:feature_code":"PPL",
    "gn:name":"Kampung Gedang",
    "gn:population":0,
    "gn:timezone":"Asia/Kuala_Lumpur",
    "iso:country":"MY",
    "name:msa_x_preferred":[
        "Kampung Gedang"
    ],
    "wof:name":"Kampung Gedang",
    "wof:placetype":"locality"
},
  "geometry": {"coordinates":[101.99169999999999,2.7758],"type":"Point"}
}