{
  "type": "Feature",
  "properties": {
    "gn:admin1_code":"11",
    "gn:asciiname":"Rumah Geramong",
    "gn:cc2":"MY",
    "gn:country_code":"MY",
    "gn:dem":52,
    "gn:feature_class":"P",
    "gn:feature_code":"PPL",
    "gn:name":"Rumah Geramong",
    "gn:population":0,
    "gn:timezone":"Asia/Kuching",
    "iso:country":"MY",
    "name:und_x_variant":[
        "Rumah Gramong",
        "Rumah Geramong"
    ],
    "wof:name":"Rumah Geramong",
    "wof:placetype":"locality"
},
  "geometry": {"coordinates":[112.48333,2.08333],"type":"Point"}
}