{
  "type": "Feature",
  "properties": {
    "gn:admin1_code":"6",
    "gn:asciiname":"Kampung Pulau Macang",
    "gn:country_code":"MY",
    "gn:dem":24,
    "gn:feature_class":"P",
    "gn:feature_code":"PPL",
    "gn:name":"Kampung Pulau Macang",
    "gn:population":0,
    "gn:timezone":"Asia/Kuala_Lumpur",
    "iso:country":"MY",
    "name:msa_x_preferred":[
        "Kampung Pulau Macang"
    ],
    "name:und_x_variant":[
        "Kampong Pulau Machang"
    ],
    "wof:name":"Kampung Pulau Macang",
    "wof:placetype":"locality"
},
  "geometry": {"coordinates":[103.3216,2.8998],"type":"Point"}
}