{
  "type": "Feature",
  "properties": {
    "gn:admin1_code":"2.0",
    "gn:asciiname":"Kampung Bukit Lalang",
    "gn:country_code":"MY",
    "gn:dem":9,
    "gn:feature_class":"P",
    "gn:feature_code":"PPL",
    "gn:name":"Kampung Bukit Lalang",
    "gn:population":0,
    "gn:timezone":"Asia/Kuala_Lumpur",
    "iso:country":"MY",
    "name:msa_x_preferred":[
        "Kampung Bukit Lalang"
    ],
    "wof:name":"Kampung Bukit Lalang",
    "wof:placetype":"locality"
},
  "geometry": {"coordinates":[100.45182,5.5732],"type":"Point"}
}