{
  "type": "Feature",
  "properties": {
    "gn:admin1_code":"6.0",
    "gn:asciiname":"Kampung Tanjung Aur",
    "gn:country_code":"MY",
    "gn:dem":109,
    "gn:feature_class":"P",
    "gn:feature_code":"PPL",
    "gn:name":"Kampung Tanjung Aur",
    "gn:population":0,
    "gn:timezone":"Asia/Kuala_Lumpur",
    "iso:country":"MY",
    "name:msa_x_preferred":[
        "Kampung Tanjung Aur"
    ],
    "wof:name":"Kampung Tanjung Aur",
    "wof:placetype":"locality"
},
  "geometry": {"coordinates":[101.91079999999999,4.0034],"type":"Point"}
}