{
  "type": "Feature",
  "properties": {
    "gn:admin1_code":"16",
    "gn:asciiname":"Kampung Bundu",
    "gn:country_code":"MY",
    "gn:dem":9,
    "gn:feature_class":"P",
    "gn:feature_code":"PPL",
    "gn:name":"Kampung Bundu",
    "gn:population":0,
    "gn:timezone":"Asia/Kuching",
    "iso:country":"MY",
    "name:msa_x_preferred":[
        "Kampung Bundu"
    ],
    "name:und_x_variant":[
        "Bundu",
        "Kampong Bundu"
    ],
    "wof:name":"Kampung Bundu",
    "wof:placetype":"locality"
},
  "geometry": {"coordinates":[115.5706,5.5226],"type":"Point"}
}