{
  "type": "Feature",
  "properties": {
    "gn:admin1_code":"12.0",
    "gn:asciiname":"Kampung Gerachi",
    "gn:country_code":"MY",
    "gn:dem":140,
    "gn:feature_class":"P",
    "gn:feature_code":"PPL",
    "gn:name":"Kampung Gerachi",
    "gn:population":0,
    "gn:timezone":"Asia/Kuala_Lumpur",
    "iso:country":"MY",
    "name:msa_x_preferred":[
        "Kampung Gerachi"
    ],
    "wof:name":"Kampung Gerachi",
    "wof:placetype":"locality"
},
  "geometry": {"coordinates":[101.7058,3.5795],"type":"Point"}
}