{
  "type": "Feature",
  "properties": {
    "gn:admin1_code":"1.0",
    "gn:asciiname":"Kawasan Penempatan Sungai Paloh Dua",
    "gn:country_code":"MY",
    "gn:dem":53,
    "gn:feature_class":"P",
    "gn:feature_code":"PPL",
    "gn:name":"Kawasan Penempatan Sungai Paloh Dua",
    "gn:population":0,
    "gn:timezone":"Asia/Kuala_Lumpur",
    "iso:country":"MY",
    "name:msa_x_preferred":[
        "Kawasan Penempatan Sungai Paloh Dua"
    ],
    "wof:name":"Kawasan Penempatan Sungai Paloh Dua",
    "wof:placetype":"locality"
},
  "geometry": {"coordinates":[103.256,2.19],"type":"Point"}
}