{
  "type": "Feature",
  "properties": {
    "gn:admin1_code":"12.0",
    "gn:asciiname":"Pekan Batu",
    "gn:country_code":"MY",
    "gn:dem":98,
    "gn:feature_class":"P",
    "gn:feature_code":"PPL",
    "gn:name":"Pekan Batu",
    "gn:population":0,
    "gn:timezone":"Asia/Kuala_Lumpur",
    "iso:country":"MY",
    "name:msa_x_preferred":[
        "Pekan Batu"
    ],
    "wof:name":"Pekan Batu",
    "wof:placetype":"locality"
},
  "geometry": {"coordinates":[101.8475,3.1667],"type":"Point"}
}