{
  "type": "Feature",
  "properties": {
    "gn:admin1_code":"6.0",
    "gn:asciiname":"Kampung Paya Keladi",
    "gn:country_code":"MY",
    "gn:dem":86,
    "gn:feature_class":"P",
    "gn:feature_code":"PPL",
    "gn:name":"Kampung Paya Keladi",
    "gn:population":0,
    "gn:timezone":"Asia/Kuala_Lumpur",
    "iso:country":"MY",
    "name:msa_x_preferred":[
        "Kampung Paya Keladi"
    ],
    "wof:name":"Kampung Paya Keladi",
    "wof:placetype":"locality"
},
  "geometry": {"coordinates":[101.92570000000001,4.3942],"type":"Point"}
}