{
  "type": "Feature",
  "properties": {
    "gn:country":"MY",
    "gn:fcode":"PPL",
    "gn:population":0,
    "iso:country":"MY",
    "name:eng_x_preferred":[
        "Bukit Beruang"
    ],
    "name:msa_x_preferred":[
        "Kampung Bukit Beruang"
    ],
    "name:msa_x_variant":[
        "Bukit Beruang"
    ],
    "name:nld_x_preferred":[
        "Bukit Beruang"
    ],
    "name:und_x_variant":[
        "Kampong Bukit Bruang"
    ],
    "name:zho_x_preferred":[
        "\u6b66\u5409\u6ce2\u6d6a"
    ],
    "qs:name":"Kampong Bukit Beruang",
    "qs:name_adm0":"Malaysia",
    "qs:name_adm1":"Melaka",
    "qs:photos":2,
    "qs:photos_1k":1,
    "qs:photos_9k":1,
    "qs:photos_9r":1,
    "qs:photos_all":2,
    "qs:photos_sr":1,
    "qs:placetype":"Suburb",
    "qs:pop_sr":"0",
    "wd:wordcount":268,
    "wof:name":"Kampong Bukit Beruang",
    "wof:placetype":"neighbourhood",
    "wof:population":0
},
  "geometry": {"coordinates":[102.2792,2.2414],"type":"Point"}
}