{
  "type": "Feature",
  "properties": {
    "gn:admin1_code":"6",
    "gn:asciiname":"Kampung Lubuk Kawah",
    "gn:country_code":"MY",
    "gn:dem":49,
    "gn:feature_class":"P",
    "gn:feature_code":"PPL",
    "gn:name":"Kampung Lubuk Kawah",
    "gn:population":0,
    "gn:timezone":"Asia/Kuala_Lumpur",
    "iso:country":"MY",
    "name:msa_x_preferred":[
        "Kampung Lubuk Kawah"
    ],
    "name:und_x_variant":[
        "Kampong Lubok Kawah"
    ],
    "wof:name":"Kampung Lubuk Kawah",
    "wof:placetype":"locality"
},
  "geometry": {"coordinates":[102.4268,3.4939],"type":"Point"}
}