{
  "type": "Feature",
  "properties": {
    "gn:admin1_code":"6.0",
    "gn:asciiname":"Kampung Kaduk",
    "gn:country_code":"MY",
    "gn:dem":113,
    "gn:feature_class":"P",
    "gn:feature_code":"PPL",
    "gn:name":"Kampung Kaduk",
    "gn:population":0,
    "gn:timezone":"Asia/Kuala_Lumpur",
    "iso:country":"MY",
    "name:msa_x_preferred":[
        "Kampung Kaduk"
    ],
    "wof:name":"Kampung Kaduk",
    "wof:placetype":"locality"
},
  "geometry": {"coordinates":[102.04049999999999,4.0179],"type":"Point"}
}