{
  "type": "Feature",
  "properties": {
    "gn:admin1_code":"13",
    "gn:asciiname":"Kampung Kicap",
    "gn:country_code":"MY",
    "gn:dem":23,
    "gn:feature_class":"P",
    "gn:feature_code":"PPL",
    "gn:name":"Kampung Kicap",
    "gn:population":0,
    "gn:timezone":"Asia/Kuala_Lumpur",
    "iso:country":"MY",
    "name:msa_x_preferred":[
        "Kampung Kicap"
    ],
    "name:und_x_variant":[
        "Kampong Kichap"
    ],
    "wof:name":"Kampung Kicap",
    "wof:placetype":"locality"
},
  "geometry": {"coordinates":[103.38679999999999,4.3446],"type":"Point"}
}