{
  "type": "Feature",
  "properties": {
    "gn:admin1_code":"6.0",
    "gn:asciiname":"Kampung Kundur",
    "gn:country_code":"MY",
    "gn:dem":102,
    "gn:feature_class":"P",
    "gn:feature_code":"PPL",
    "gn:name":"Kampung Kundur",
    "gn:population":0,
    "gn:timezone":"Asia/Kuala_Lumpur",
    "iso:country":"MY",
    "name:msa_x_preferred":[
        "Kampung Kundur"
    ],
    "wof:name":"Kampung Kundur",
    "wof:placetype":"locality"
},
  "geometry": {"coordinates":[102.1224,3.9988],"type":"Point"}
}