{
  "type": "Feature",
  "properties": {
    "gn:admin1_code":"13",
    "gn:asciiname":"Kampung Telaga Mengkudu",
    "gn:country_code":"MY",
    "gn:dem":14,
    "gn:feature_class":"P",
    "gn:feature_code":"PPL",
    "gn:name":"Kampung Telaga Mengkudu",
    "gn:population":0,
    "gn:timezone":"Asia/Kuala_Lumpur",
    "iso:country":"MY",
    "name:msa_x_preferred":[
        "Kampung Telaga Mengkudu"
    ],
    "name:und_x_variant":[
        "Kampong Telaga Mengkudu"
    ],
    "wof:name":"Kampung Telaga Mengkudu",
    "wof:placetype":"locality"
},
  "geometry": {"coordinates":[103.095,5.2478],"type":"Point"}
}