{
  "type": "Feature",
  "properties": {
    "gn:admin1_code":"5",
    "gn:asciiname":"Kampung Sungai Bioh",
    "gn:country_code":"MY",
    "gn:dem":48,
    "gn:feature_class":"P",
    "gn:feature_code":"PPL",
    "gn:name":"Kampung Sungai Bioh",
    "gn:population":0,
    "gn:timezone":"Asia/Kuala_Lumpur",
    "iso:country":"MY",
    "name:msa_x_preferred":[
        "Kampung Sungai Bioh"
    ],
    "name:und_x_variant":[
        "Kampong Sungai Bioh"
    ],
    "wof:name":"Kampung Sungai Bioh",
    "wof:placetype":"locality"
},
  "geometry": {"coordinates":[101.8913,2.862],"type":"Point"}
}