{
  "type": "Feature",
  "properties": {
    "gn:admin1_code":"1.0",
    "gn:asciiname":"Kampung Sungai Meda Luar",
    "gn:country_code":"MY",
    "gn:dem":12,
    "gn:feature_class":"P",
    "gn:feature_code":"PPL",
    "gn:name":"Kampung Sungai Meda Luar",
    "gn:population":0,
    "gn:timezone":"Asia/Kuala_Lumpur",
    "iso:country":"MY",
    "name:msa_x_preferred":[
        "Kampung Sungai Meda Luar"
    ],
    "wof:name":"Kampung Sungai Meda Luar",
    "wof:placetype":"locality"
},
  "geometry": {"coordinates":[102.81950000000001,2.3319],"type":"Point"}
}