{
  "type": "Feature",
  "properties": {
    "gn:admin1_code":"5",
    "gn:asciiname":"Kampung Ayer Kuning",
    "gn:country_code":"MY",
    "gn:dem":52,
    "gn:feature_class":"P",
    "gn:feature_code":"PPL",
    "gn:name":"Kampung Ayer Kuning",
    "gn:population":0,
    "gn:timezone":"Asia/Kuala_Lumpur",
    "iso:country":"MY",
    "name:msa_x_preferred":[
        "Kampung Ayer Kuning"
    ],
    "name:und_x_variant":[
        "Kampong Ayer Kuning"
    ],
    "wof:name":"Kampung Ayer Kuning",
    "wof:placetype":"locality"
},
  "geometry": {"coordinates":[102.4774,2.5069],"type":"Point"}
}