{
  "type": "Feature",
  "properties": {
    "gn:admin1_code":"4",
    "gn:asciiname":"Kampong Kemangkang",
    "gn:country_code":"MY",
    "gn:dem":36,
    "gn:feature_class":"P",
    "gn:feature_code":"PPL",
    "gn:name":"Kampong Kemangkang",
    "gn:population":0,
    "gn:timezone":"Asia/Kuala_Lumpur",
    "iso:country":"MY",
    "wof:name":"Kampong Kemangkang",
    "wof:placetype":"locality"
},
  "geometry": {"coordinates":[102.38333,2.33333],"type":"Point"}
}