{
  "type": "Feature",
  "properties": {
    "gn:admin1_code":"6.0",
    "gn:asciiname":"Kampung Sol",
    "gn:country_code":"MY",
    "gn:dem":143,
    "gn:feature_class":"P",
    "gn:feature_code":"PPL",
    "gn:name":"Kampung Sol",
    "gn:population":0,
    "gn:timezone":"Asia/Kuala_Lumpur",
    "iso:country":"MY",
    "name:msa_x_preferred":[
        "Kampung Sol"
    ],
    "wof:name":"Kampung Sol",
    "wof:placetype":"locality"
},
  "geometry": {"coordinates":[102.0107,3.9307],"type":"Point"}
}