{
  "type": "Feature",
  "properties": {
    "gn:admin1_code":"5.0",
    "gn:asciiname":"Kampung Benal",
    "gn:country_code":"MY",
    "gn:dem":146,
    "gn:feature_class":"P",
    "gn:feature_code":"PPL",
    "gn:name":"Kampung Benal",
    "gn:population":0,
    "gn:timezone":"Asia/Kuala_Lumpur",
    "iso:country":"MY",
    "name:msa_x_preferred":[
        "Kampung Benal"
    ],
    "wof:name":"Kampung Benal",
    "wof:placetype":"locality"
},
  "geometry": {"coordinates":[102.0316,2.9069],"type":"Point"}
}