{
  "type": "Feature",
  "properties": {
    "gn:admin1_code":"1.0",
    "gn:asciiname":"Taman Sri Lalang",
    "gn:country_code":"MY",
    "gn:dem":26,
    "gn:feature_class":"P",
    "gn:feature_code":"PPL",
    "gn:name":"Taman Sri Lalang",
    "gn:population":0,
    "gn:timezone":"Asia/Kuala_Lumpur",
    "iso:country":"MY",
    "name:msa_x_preferred":[
        "Taman Sri Lalang"
    ],
    "wof:name":"Taman Sri Lalang",
    "wof:placetype":"locality"
},
  "geometry": {"coordinates":[103.8905,1.7227],"type":"Point"}
}