{
  "type": "Feature",
  "properties": {
    "gn:gn_country":"MY",
    "gn:gn_fcode":"PPL",
    "gn:gn_pop":0,
    "iso:country":"MY",
    "name:dut_x_preferred":[
        "Kuala Pahang"
    ],
    "name:eng_x_preferred":[
        "Kuala Pahang"
    ],
    "name:may_x_preferred":[
        "Kuala Pahang"
    ],
    "name:msa_x_preferred":[
        "Kuala Pahang"
    ],
    "name:unk_x_variant":[
        "Kampong Pahang"
    ],
    "qs_pg:aaroncc":"MY",
    "qs_pg:gn_country":"MY",
    "qs_pg:gn_fcode":"PPL",
    "qs_pg:gn_pop":0,
    "qs_pg:name":"Kuala Pahang",
    "qs_pg:name_adm0":"Malaysia",
    "qs_pg:name_adm1":"Pahang",
    "qs_pg:photos_9k":1,
    "qs_pg:photos_9r":1,
    "qs_pg:photos_all":9,
    "qs_pg:photos_sr":0,
    "qs_pg:pop_sr":3,
    "qs_pg:qs_pg_placetype":"locality",
    "qs_pg:qs_pg_placetype_gp":"Town",
    "qs_pg:woe_adm0":23424901,
    "woe:adm0_id":23424901,
    "woe:name_adm0":"Malaysia",
    "woe:name_adm1":"Pahang",
    "woe:placetype":"Town",
    "wof:name":"Kuala Pahang",
    "wof:placetype":"locality"
},
  "geometry": {"coordinates":[103.4619,3.5321],"type":"Point"}
}