{
  "type": "Feature",
  "properties": {
    "gn:admin1_code":"16.0",
    "gn:asciiname":"Kampung Rita",
    "gn:country_code":"MY",
    "gn:dem":35,
    "gn:feature_class":"P",
    "gn:feature_code":"PPL",
    "gn:name":"Kampung Rita",
    "gn:population":0,
    "gn:timezone":"Asia/Kuching",
    "iso:country":"MY",
    "name:msa_x_preferred":[
        "Kampung Rita"
    ],
    "wof:name":"Kampung Rita",
    "wof:placetype":"locality"
},
  "geometry": {"coordinates":[116.66200000000001,6.7533],"type":"Point"}
}