{
  "type": "Feature",
  "properties": {
    "gn:admin1_code":"5.0",
    "gn:asciiname":"Kampung Bahru Cina",
    "gn:country_code":"MY",
    "gn:dem":8,
    "gn:feature_class":"P",
    "gn:feature_code":"PPL",
    "gn:name":"Kampung Bahru Cina",
    "gn:population":0,
    "gn:timezone":"Asia/Kuala_Lumpur",
    "iso:country":"MY",
    "name:msa_x_preferred":[
        "Kampung Bahru Cina"
    ],
    "wof:name":"Kampung Bahru Cina",
    "wof:placetype":"locality"
},
  "geometry": {"coordinates":[101.7479,2.6479],"type":"Point"}
}