{
  "type": "Feature",
  "properties": {
    "gn:country":"MY",
    "gn:fcode":"PPL",
    "gn:population":29185,
    "iso:country":"MY",
    "qs:name":"Kampong Masjid Tanah",
    "qs:photos_9r":0,
    "qs:photos_sr":0,
    "qs:pop_sr":"7",
    "wof:name":"Kampong Masjid Tanah",
    "wof:placetype":"locality",
    "wof:population":29185
},
  "geometry": {"coordinates":[102.11667,2.35],"type":"Point"}
}