{
  "type": "Feature",
  "properties": {
    "gn:admin1_code":"3",
    "gn:asciiname":"Kampong Gertak Panjang",
    "gn:country_code":"MY",
    "gn:dem":42,
    "gn:feature_class":"P",
    "gn:feature_code":"PPL",
    "gn:name":"Kampong Gertak Panjang",
    "gn:population":0,
    "gn:timezone":"Asia/Kuala_Lumpur",
    "iso:country":"MY",
    "name:und_x_variant":[
        "Kampong Geftak Panjang",
        "Kampong Gertak Panjang"
    ],
    "wof:name":"Kampong Gertak Panjang",
    "wof:placetype":"locality"
},
  "geometry": {"coordinates":[101.89597000000001,5.80805],"type":"Point"}
}