{
  "type": "Feature",
  "properties": {
    "gn:admin1_code":"6.0",
    "gn:asciiname":"Kamjuan Tanah Lepar Hilir Empat Enam dan Tujuh",
    "gn:country_code":"MY",
    "gn:dem":41,
    "gn:feature_class":"P",
    "gn:feature_code":"PPL",
    "gn:name":"Kamjuan Tanah Lepar Hilir Empat Enam dan Tujuh",
    "gn:population":0,
    "gn:timezone":"Asia/Kuala_Lumpur",
    "iso:country":"MY",
    "name:msa_x_preferred":[
        "Kamjuan Tanah Lepar Hilir Empat Enam dan Tujuh"
    ],
    "wof:name":"Kamjuan Tanah Lepar Hilir Empat Enam dan Tujuh",
    "wof:placetype":"locality"
},
  "geometry": {"coordinates":[103.0098,3.5964],"type":"Point"}
}