{
  "type": "Feature",
  "properties": {
    "gn:admin1_code":"6.0",
    "gn:asciiname":"Kampung Kacah",
    "gn:cc2":"MY",
    "gn:country_code":"MY",
    "gn:dem":32,
    "gn:feature_class":"P",
    "gn:feature_code":"PPL",
    "gn:name":"Kampung Kacah",
    "gn:population":0,
    "gn:timezone":"Asia/Kuala_Lumpur",
    "iso:country":"MY",
    "name:und_x_variant":[
        "Kampong Kachah",
        "Kampung Kacah"
    ],
    "wof:name":"Kampung Kacah",
    "wof:placetype":"locality"
},
  "geometry": {"coordinates":[103.21666999999999,2.83333],"type":"Point"}
}