{
  "type": "Feature",
  "properties": {
    "gn:admin1_code":"16.0",
    "gn:asciiname":"Kampung Komontodon",
    "gn:country_code":"MY",
    "gn:dem":47,
    "gn:feature_class":"P",
    "gn:feature_code":"PPL",
    "gn:name":"Kampung Komontodon",
    "gn:population":0,
    "gn:timezone":"Asia/Kuching",
    "iso:country":"MY",
    "name:msa_x_preferred":[
        "Kampung Komontodon"
    ],
    "wof:name":"Kampung Komontodon",
    "wof:placetype":"locality"
},
  "geometry": {"coordinates":[117.1895,6.1376],"type":"Point"}
}