{
  "type": "Feature",
  "properties": {
    "gn:country":"MY",
    "gn:fcode":"PPL",
    "gn:population":0,
    "iso:country":"MY",
    "name:ara_x_preferred":[
        "\u062f\u0627\u0626\u0631\u0629 \u0628\u0648\u0646\u062a\u064a\u0627\u0646"
    ],
    "name:ceb_x_preferred":[
        "Daerah Pontian"
    ],
    "name:eng_x_preferred":[
        "Pontian District"
    ],
    "name:fas_x_preferred":[
        "\u067e\u0648\u0646\u062a\u06cc\u0627\u0646 \u06a9\u0686\u06cc\u0644"
    ],
    "name:ind_x_preferred":[
        "Pontian"
    ],
    "name:ind_x_variant":[
        "Distrik Pontian"
    ],
    "name:jav_x_preferred":[
        "Kabupat\u00e8n Pontian"
    ],
    "name:jpn_x_preferred":[
        "\u30dd\u30f3\u30c6\u30a3\u30a2\u30f3\u90e1"
    ],
    "name:msa_x_preferred":[
        "Kampung Teluk Kerang"
    ],
    "name:msa_x_variant":[
        "Pontian"
    ],
    "name:nan_x_preferred":[
        "Pontian Ko\u0101n"
    ],
    "name:nld_x_preferred":[
        "Pontian"
    ],
    "name:sun_x_preferred":[
        "Kabupat\u00e9n Pontian"
    ],
    "name:tam_x_preferred":[
        "\u0baa\u0bca\u0ba8\u0bcd\u0ba4\u0bbf\u0baf\u0bbe\u0ba9\u0bcd"
    ],
    "name:tet_x_preferred":[
        "Distritu Pontian"
    ],
    "name:und_x_variant":[
        "Kampong Telok Kerang"
    ],
    "name:zho_x_preferred":[
        "Taman Pelangi"
    ],
    "name:zho_x_variant":[
        "\u7b28\u73cd\u53bf"
    ],
    "qs:name":"Telok Kerang",
    "qs:name_adm0":"Malaysia",
    "qs:name_adm1":"Johor",
    "qs:photos":2,
    "qs:photos_1k":1,
    "qs:photos_9k":1,
    "qs:photos_9r":1,
    "qs:photos_all":2,
    "qs:photos_sr":1,
    "qs:placetype":"Town",
    "qs:pop_sr":"0",
    "wd:wordcount":760,
    "wof:name":"Telok Kerang",
    "wof:placetype":"locality",
    "wof:population":0
},
  "geometry": {"coordinates":[103.4226,1.418],"type":"Point"}
}