{
  "type": "Feature",
  "properties": {
    "gn:country":"MY",
    "gn:fcode":"PPL",
    "gn:pop":0,
    "iso:country":"MY",
    "name:msa_x_preferred":[
        "Kampung Teluk Kerang"
    ],
    "name:unk_x_variant":[
        "Kampong Telok Kerang"
    ],
    "qs:name":"Telok Kerang",
    "qs:name_adm0":"Malaysia",
    "qs:name_adm1":"Johor",
    "qs:photos":2,
    "qs:photos_1k":1,
    "qs:photos_9k":1,
    "qs:photos_9r":1,
    "qs:photos_all":2,
    "qs:photos_sr":1,
    "qs:placetype":"Town",
    "qs:pop_sr":"0",
    "wd:wordcount":760,
    "wof:name":"Telok Kerang",
    "wof:placetype":"locality",
    "wof:population":0
},
  "geometry": {"coordinates":[103.4226,1.418],"type":"Point"}
}