{
  "type": "Feature",
  "properties": {
    "gn:admin1_code":"4",
    "gn:asciiname":"Kampung Parit Sidang Seman",
    "gn:country_code":"MY",
    "gn:dem":12,
    "gn:feature_class":"P",
    "gn:feature_code":"PPL",
    "gn:name":"Kampung Parit Sidang Seman",
    "gn:population":0,
    "gn:timezone":"Asia/Kuala_Lumpur",
    "iso:country":"MY",
    "name:msa_x_preferred":[
        "Kampung Parit Sidang Seman"
    ],
    "name:und_x_variant":[
        "Kampong Parit Sidang Seman"
    ],
    "wof:name":"Kampung Parit Sidang Seman",
    "wof:placetype":"locality"
},
  "geometry": {"coordinates":[102.49679999999999,2.1406],"type":"Point"}
}