{
  "type": "Feature",
  "properties": {
    "gn:admin1_code":"5",
    "gn:asciiname":"Kampung Masjid",
    "gn:country_code":"MY",
    "gn:dem":34,
    "gn:feature_class":"P",
    "gn:feature_code":"PPL",
    "gn:name":"Kampung Masjid",
    "gn:population":0,
    "gn:timezone":"Asia/Kuala_Lumpur",
    "iso:country":"MY",
    "name:msa_x_preferred":[
        "Kampung Masjid"
    ],
    "name:und_x_variant":[
        "Kampong Masjid"
    ],
    "wof:name":"Kampung Masjid",
    "wof:placetype":"locality"
},
  "geometry": {"coordinates":[101.96720000000001,2.6012],"type":"Point"}
}