{
  "type": "Feature",
  "properties": {
    "gn:country":"MY",
    "iso:country":"MY",
    "qs:name":"Padang Mat Sirat",
    "qs:name_adm0":"Malaysia",
    "qs:name_adm1":"Kedah",
    "qs:photos":3,
    "qs:photos_1k":1,
    "qs:photos_9k":1,
    "qs:photos_9r":5,
    "qs:photos_all":312,
    "qs:photos_sr":1,
    "qs:placetype":"LocalAdmin",
    "qs:pop_sr":"0",
    "wof:name":"Padang Mat Sirat",
    "wof:placetype":"localadmin"
},
  "geometry": {"coordinates":[99.68513400000001,6.364158],"type":"Point"}
}