{
  "type": "Feature",
  "properties": {
    "gn:admin1_code":"5.0",
    "gn:asciiname":"Ladang Bahau Penari Village",
    "gn:country_code":"MY",
    "gn:dem":72,
    "gn:feature_class":"P",
    "gn:feature_code":"PPL",
    "gn:name":"Ladang Bahau Penari Village",
    "gn:population":0,
    "gn:timezone":"Asia/Kuala_Lumpur",
    "iso:country":"MY",
    "name:msa_x_preferred":[
        "Ladang Bahau Penari Village"
    ],
    "wof:name":"Ladang Bahau Penari Village",
    "wof:placetype":"locality"
},
  "geometry": {"coordinates":[102.4286,2.8166],"type":"Point"}
}