{
  "type": "Feature",
  "properties": {
    "iso:country":"MY",
    "name:ast_x_preferred":[
        "Bidor"
    ],
    "name:eng_x_preferred":[
        "Bidor"
    ],
    "name:fra_x_preferred":[
        "Bidor"
    ],
    "name:msa_x_preferred":[
        "Bidor"
    ],
    "name:nld_x_preferred":[
        "Bidor"
    ],
    "name:tam_x_preferred":[
        "\u0baa\u0bc0\u0b9f\u0bcb\u0bb0\u0bcd"
    ],
    "name:zho_x_preferred":[
        "\u7f8e\u7f57"
    ],
    "qs:name":"Bidor",
    "qs:name_adm0":"Malaysia",
    "qs:name_adm1":"Perak",
    "qs:photos":1,
    "qs:photos_1k":1,
    "qs:photos_9k":1,
    "qs:photos_9r":2,
    "qs:photos_all":71,
    "qs:photos_sr":1,
    "qs:placetype":"LocalAdmin",
    "qs:pop_sr":"0",
    "wd:wordcount":1392,
    "wof:name":"Bidor",
    "wof:placetype":"localadmin"
},
  "geometry": {"coordinates":[101.24824,4.091628],"type":"Point"}
}