{
  "type": "Feature",
  "properties": {
    "iso:country":"MY",
    "name:eng_x_preferred":[
        "Sedenak"
    ],
    "name:msa_x_preferred":[
        "Sedenak"
    ],
    "name:nld_x_preferred":[
        "Sedenak"
    ],
    "name:zho_x_preferred":[
        "\u58eb\u5e74\u7eb3"
    ],
    "qs:name":"Sedenak",
    "qs:name_adm0":"Malaysia",
    "qs:name_adm1":"Johor",
    "qs:photos":1,
    "qs:photos_1k":1,
    "qs:photos_9k":1,
    "qs:photos_9r":4,
    "qs:photos_all":185,
    "qs:photos_sr":1,
    "qs:placetype":"LocalAdmin",
    "qs:pop_sr":"0",
    "wd:wordcount":46,
    "wof:name":"Sedenak",
    "wof:placetype":"localadmin"
},
  "geometry": {"coordinates":[103.529191,1.67539],"type":"Point"}
}