{
  "type": "Feature",
  "properties": {
    "gn:admin1_code":"5.0",
    "gn:asciiname":"Kampung Teking",
    "gn:country_code":"MY",
    "gn:dem":214,
    "gn:feature_class":"P",
    "gn:feature_code":"PPL",
    "gn:name":"Kampung Teking",
    "gn:population":0,
    "gn:timezone":"Asia/Kuala_Lumpur",
    "iso:country":"MY",
    "name:msa_x_preferred":[
        "Kampung Teking"
    ],
    "wof:name":"Kampung Teking",
    "wof:placetype":"locality"
},
  "geometry": {"coordinates":[101.99769999999999,3.159],"type":"Point"}
}