{
  "type": "Feature",
  "properties": {
    "gn:admin1_code":"1.0",
    "gn:asciiname":"Kampung Sin Lik",
    "gn:country_code":"MY",
    "gn:dem":27,
    "gn:feature_class":"P",
    "gn:feature_code":"PPL",
    "gn:name":"Kampung Sin Lik",
    "gn:population":0,
    "gn:timezone":"Asia/Kuala_Lumpur",
    "iso:country":"MY",
    "name:msa_x_preferred":[
        "Kampung Sin Lik"
    ],
    "wof:name":"Kampung Sin Lik",
    "wof:placetype":"locality"
},
  "geometry": {"coordinates":[103.1434,2.071],"type":"Point"}
}