{
  "type": "Feature",
  "properties": {
    "gn:admin1_code":"7",
    "gn:asciiname":"Kampong Bertai",
    "gn:country_code":"MY",
    "gn:dem":56,
    "gn:feature_class":"P",
    "gn:feature_code":"PPL",
    "gn:name":"Kampong Bertai",
    "gn:population":0,
    "gn:timezone":"Asia/Kuala_Lumpur",
    "iso:country":"MY",
    "wof:name":"Kampong Bertai",
    "wof:placetype":"locality"
},
  "geometry": {"coordinates":[101.03333000000001,4.88333],"type":"Point"}
}