{
  "type": "Feature",
  "properties": {
    "gn:admin1_code":"13.0",
    "gn:asciiname":"Kampung Pengkalan Setar",
    "gn:country_code":"MY",
    "gn:dem":27,
    "gn:feature_class":"P",
    "gn:feature_code":"PPL",
    "gn:name":"Kampung Pengkalan Setar",
    "gn:population":0,
    "gn:timezone":"Asia/Kuala_Lumpur",
    "iso:country":"MY",
    "name:msa_x_preferred":[
        "Kampung Pengkalan Setar"
    ],
    "wof:name":"Kampung Pengkalan Setar",
    "wof:placetype":"locality"
},
  "geometry": {"coordinates":[102.917,5.1648],"type":"Point"}
}