{
  "type": "Feature",
  "properties": {
    "gn:admin1_code":"2",
    "gn:asciiname":"Kampung Charok Semerliang",
    "gn:cc2":"MY",
    "gn:country_code":"MY",
    "gn:dem":113,
    "gn:feature_class":"P",
    "gn:feature_code":"PPL",
    "gn:name":"Kampung Charok Semerliang",
    "gn:population":0,
    "gn:timezone":"Asia/Kuala_Lumpur",
    "iso:country":"MY",
    "name:msa_x_preferred":[
        "Kampung Charok Semerliang"
    ],
    "name:und_x_variant":[
        "Kampong Charok Semerliang"
    ],
    "wof:name":"Kampung Charok Semerliang",
    "wof:placetype":"locality"
},
  "geometry": {"coordinates":[100.88494,5.83561],"type":"Point"}
}