{
  "type": "Feature",
  "properties": {
    "gn:admin1_code":"1.0",
    "gn:asciiname":"Kemajuan Tanah Gugusan Peta Temalek",
    "gn:country_code":"MY",
    "gn:dem":83,
    "gn:feature_class":"P",
    "gn:feature_code":"PPL",
    "gn:name":"Kemajuan Tanah Gugusan Peta Temalek",
    "gn:population":0,
    "gn:timezone":"Asia/Kuala_Lumpur",
    "iso:country":"MY",
    "name:msa_x_preferred":[
        "Kemajuan Tanah Gugusan Peta Temalek"
    ],
    "wof:name":"Kemajuan Tanah Gugusan Peta Temalek",
    "wof:placetype":"locality"
},
  "geometry": {"coordinates":[103.05419999999999,2.4934],"type":"Point"}
}