{
  "type": "Feature",
  "properties": {
    "gn:admin1_code":"1",
    "gn:asciiname":"Kampong Selanchar",
    "gn:cc2":"MY",
    "gn:country_code":"MY",
    "gn:dem":13,
    "gn:feature_class":"P",
    "gn:feature_code":"PPL",
    "gn:name":"Kampong Selanchar",
    "gn:population":0,
    "gn:timezone":"Asia/Kuala_Lumpur",
    "iso:country":"MY",
    "name:und_x_variant":[
        "Kampong Selanchor",
        "Kampong Selanchar"
    ],
    "wof:name":"Kampong Selanchar",
    "wof:placetype":"locality"
},
  "geometry": {"coordinates":[102.76667,2.15],"type":"Point"}
}