{
  "type": "Feature",
  "properties": {
    "gn:admin1_code":"2.0",
    "gn:asciiname":"Bagan Samak",
    "gn:cc2":"MY",
    "gn:country_code":"MY",
    "gn:dem":7,
    "gn:feature_class":"P",
    "gn:feature_code":"PPL",
    "gn:name":"Bagan Samak",
    "gn:population":0,
    "gn:timezone":"Asia/Kuala_Lumpur",
    "iso:country":"MY",
    "name:msa_x_preferred":[
        "Bagan Samak"
    ],
    "wof:name":"Bagan Samak",
    "wof:placetype":"locality"
},
  "geometry": {"coordinates":[100.56191,5.0895],"type":"Point"}
}