{
  "type": "Feature",
  "properties": {
    "gn:admin1_code":"5",
    "gn:asciiname":"Kampung Tanjong",
    "gn:country_code":"MY",
    "gn:dem":41,
    "gn:feature_class":"P",
    "gn:feature_code":"PPL",
    "gn:name":"Kampung Tanjong",
    "gn:population":0,
    "gn:timezone":"Asia/Kuala_Lumpur",
    "iso:country":"MY",
    "name:msa_x_preferred":[
        "Kampung Tanjong"
    ],
    "name:und_x_variant":[
        "Kampong Tanjong"
    ],
    "wof:name":"Kampung Tanjong",
    "wof:placetype":"locality"
},
  "geometry": {"coordinates":[102.139,2.5121],"type":"Point"}
}