{
  "type": "Feature",
  "properties": {
    "gn:admin1_code":"2.0",
    "gn:asciiname":"Kampung Insun",
    "gn:cc2":"MY",
    "gn:country_code":"MY",
    "gn:dem":42,
    "gn:feature_class":"P",
    "gn:feature_code":"PPL",
    "gn:name":"Kampung Insun",
    "gn:population":0,
    "gn:timezone":"Asia/Kuala_Lumpur",
    "iso:country":"MY",
    "name:msa_x_preferred":[
        "Kampung Insun"
    ],
    "wof:name":"Kampung Insun",
    "wof:placetype":"locality"
},
  "geometry": {"coordinates":[100.52945,5.89098],"type":"Point"}
}