{
  "type": "Feature",
  "properties": {
    "gn:admin1_code":"2",
    "gn:asciiname":"Kampung Sala Kechil",
    "gn:country_code":"MY",
    "gn:dem":5,
    "gn:feature_class":"P",
    "gn:feature_code":"PPL",
    "gn:name":"Kampung Sala Kechil",
    "gn:population":0,
    "gn:timezone":"Asia/Kuala_Lumpur",
    "iso:country":"MY",
    "name:msa_x_preferred":[
        "Kampung Sala Kechil"
    ],
    "name:und_x_variant":[
        "Kampong Sala Kechil"
    ],
    "wof:name":"Kampung Sala Kechil",
    "wof:placetype":"locality"
},
  "geometry": {"coordinates":[100.34923000000001,5.98425],"type":"Point"}
}