{
  "type": "Feature",
  "properties": {
    "gn:admin1_code":"13.0",
    "gn:asciiname":"Kampung Lak Lok",
    "gn:country_code":"MY",
    "gn:dem":18,
    "gn:feature_class":"P",
    "gn:feature_code":"PPL",
    "gn:name":"Kampung Lak Lok",
    "gn:population":0,
    "gn:timezone":"Asia/Kuala_Lumpur",
    "iso:country":"MY",
    "name:msa_x_preferred":[
        "Kampung Lak Lok"
    ],
    "wof:name":"Kampung Lak Lok",
    "wof:placetype":"locality"
},
  "geometry": {"coordinates":[102.45064000000001,5.74652],"type":"Point"}
}