{
  "type": "Feature",
  "properties": {
    "iso:country":"MY",
    "name:und_x_preferred":[
        "Taman Pekaka"
    ],
    "name:unk_x_variant":[
        "Taman Pekaka"
    ],
    "qs:gn_adm0_cc":"MY",
    "qs:gn_fcode":"PPL",
    "qs:gn_local":1764027,
    "qs:gn_nam_loc":"Kampong Sungai Gelugor, Pulau Pinang, MY",
    "qs:gn_namadm1":"09",
    "qs:gn_name":"Taman Pekaka",
    "qs:local_max":422,
    "qs:local_sum":2726,
    "qs:localhoods":18,
    "qs:name":"Taman Pekaka",
    "qs:name_adm0":"Malaysia",
    "qs:name_adm1":"Pulau Pinang",
    "qs:name_adm2":"Timur Laut",
    "qs:name_lau":"Mukim 13 Paya Terubung",
    "qs:name_local":"Kampong Sungai Gelugor",
    "qs:photo_max":66,
    "qs:photo_sum":248,
    "qs:placetype":"Suburb",
    "qs:quad_count":15,
    "qs:woe_adm0":23424901,
    "qs:woe_adm1":2346304,
    "qs:woe_adm2":56013581,
    "qs:woe_lau":56013984,
    "qs:woe_local":1149014,
    "qs:woe_ver":"7.10.0",
    "wof:lang":[
        "unk"
    ],
    "wof:name":"Taman Pekaka",
    "wof:placetype":"neighbourhood"
},
  "geometry": {"coordinates":[100.292002,5.356369],"type":"Point"}
}