{
  "type": "Feature",
  "properties": {
    "gn:admin1_code":"7",
    "gn:asciiname":"Kampung Segari",
    "gn:country_code":"MY",
    "gn:dem":14,
    "gn:feature_class":"P",
    "gn:feature_code":"PPL",
    "gn:name":"Kampung Segari",
    "gn:population":0,
    "gn:timezone":"Asia/Kuala_Lumpur",
    "iso:country":"MY",
    "name:msa_x_preferred":[
        "Kampung Segari"
    ],
    "name:und_x_variant":[
        "Kampong Segari"
    ],
    "wof:name":"Kampung Segari",
    "wof:placetype":"locality"
},
  "geometry": {"coordinates":[100.6399,4.3544],"type":"Point"}
}