{
  "type": "Feature",
  "properties": {
    "gn:admin1_code":"2.0",
    "gn:asciiname":"Kampung Bukit Sebelah",
    "gn:country_code":"MY",
    "gn:dem":127,
    "gn:feature_class":"P",
    "gn:feature_code":"PPL",
    "gn:name":"Kampung Bukit Sebelah",
    "gn:population":0,
    "gn:timezone":"Asia/Kuala_Lumpur",
    "iso:country":"MY",
    "name:msa_x_preferred":[
        "Kampung Bukit Sebelah"
    ],
    "wof:name":"Kampung Bukit Sebelah",
    "wof:placetype":"locality"
},
  "geometry": {"coordinates":[100.89041,5.86217],"type":"Point"}
}