{
  "type": "Feature",
  "properties": {
    "gn:admin1_code":"16",
    "gn:asciiname":"Kampung Kopimpinan",
    "gn:country_code":"MY",
    "gn:dem":21,
    "gn:feature_class":"P",
    "gn:feature_code":"PPL",
    "gn:name":"Kampung Kopimpinan",
    "gn:population":0,
    "gn:timezone":"Asia/Kuching",
    "iso:country":"MY",
    "name:msa_x_preferred":[
        "Kampung Kopimpinan"
    ],
    "name:und_x_variant":[
        "Kampong Kopindenan"
    ],
    "wof:name":"Kampung Kopimpinan",
    "wof:placetype":"locality"
},
  "geometry": {"coordinates":[116.0698,5.8903],"type":"Point"}
}