{
  "type": "Feature",
  "properties": {
    "gn:admin1_code":"2.0",
    "gn:asciiname":"Kampung Batu Dua Puloh Dua",
    "gn:cc2":"MY",
    "gn:country_code":"MY",
    "gn:dem":2,
    "gn:feature_class":"P",
    "gn:feature_code":"PPL",
    "gn:name":"Kampung Batu Dua Puloh Dua",
    "gn:population":0,
    "gn:timezone":"Asia/Kuala_Lumpur",
    "iso:country":"MY",
    "name:msa_x_preferred":[
        "Kampung Batu Dua Puloh Dua"
    ],
    "wof:name":"Kampung Batu Dua Puloh Dua",
    "wof:placetype":"locality"
},
  "geometry": {"coordinates":[100.42026,5.83895],"type":"Point"}
}