{
  "type": "Feature",
  "properties": {
    "gn:admin1_code":"7",
    "gn:asciiname":"Kampong Dusun",
    "gn:country_code":"MY",
    "gn:dem":17,
    "gn:feature_class":"P",
    "gn:feature_code":"PPL",
    "gn:name":"Kampong Dusun",
    "gn:population":0,
    "gn:timezone":"Asia/Kuala_Lumpur",
    "iso:country":"MY",
    "wof:name":"Kampong Dusun",
    "wof:placetype":"locality"
},
  "geometry": {"coordinates":[100.88333,4.38333],"type":"Point"}
}