{
  "type": "Feature",
  "properties": {
    "gn:admin1_code":"5",
    "gn:asciiname":"Kampung Mempas Kechil",
    "gn:country_code":"MY",
    "gn:dem":120,
    "gn:feature_class":"P",
    "gn:feature_code":"PPL",
    "gn:name":"Kampung Mempas Kechil",
    "gn:population":0,
    "gn:timezone":"Asia/Kuala_Lumpur",
    "iso:country":"MY",
    "name:msa_x_preferred":[
        "Kampung Mempas Kechil"
    ],
    "name:und_x_variant":[
        "Kampong Mempas Kechil"
    ],
    "wof:name":"Kampung Mempas Kechil",
    "wof:placetype":"locality"
},
  "geometry": {"coordinates":[102.1433,2.7533],"type":"Point"}
}