{
  "type": "Feature",
  "properties": {
    "gn:admin1_code":"9",
    "gn:asciiname":"Kampung Belah Dua",
    "gn:cc2":"MY",
    "gn:country_code":"MY",
    "gn:dem":9,
    "gn:feature_class":"P",
    "gn:feature_code":"PPL",
    "gn:name":"Kampung Belah Dua",
    "gn:population":0,
    "gn:timezone":"Asia/Kuala_Lumpur",
    "iso:country":"MY",
    "name:msa_x_preferred":[
        "Kampung Belah Dua"
    ],
    "name:und_x_variant":[
        "Kampong Belah Dua"
    ],
    "wof:name":"Kampung Belah Dua",
    "wof:placetype":"locality"
},
  "geometry": {"coordinates":[100.42149000000001,5.37911],"type":"Point"}
}