{
  "type": "Feature",
  "properties": {
    "gn:admin1_code":"16",
    "gn:asciiname":"Kampong Liwatong-pau",
    "gn:cc2":"MY",
    "gn:country_code":"MY",
    "gn:dem":94,
    "gn:feature_class":"P",
    "gn:feature_code":"PPL",
    "gn:name":"Kampong Liwatong-pau",
    "gn:population":0,
    "gn:timezone":"Asia/Kuching",
    "iso:country":"MY",
    "name:und_x_variant":[
        "Liwatumpau",
        "Liwantumpau",
        "Kampong Liwatong-pau"
    ],
    "wof:name":"Kampong Liwatong-pau",
    "wof:placetype":"locality"
},
  "geometry": {"coordinates":[117.03333000000001,5.43333],"type":"Point"}
}