{
  "type": "Feature",
  "properties": {
    "gn:admin1_code":"16",
    "gn:asciiname":"Kampung Dudar",
    "gn:country_code":"MY",
    "gn:dem":20,
    "gn:feature_class":"P",
    "gn:feature_code":"PPL",
    "gn:name":"Kampung Dudar",
    "gn:population":0,
    "gn:timezone":"Asia/Kuching",
    "iso:country":"MY",
    "name:msa_x_preferred":[
        "Kampung Dudar"
    ],
    "name:und_x_variant":[
        "Kampong Dudar"
    ],
    "wof:name":"Kampung Dudar",
    "wof:placetype":"locality"
},
  "geometry": {"coordinates":[116.5732,6.5901],"type":"Point"}
}