{
  "type": "Feature",
  "properties": {
    "gn:admin1_code":"16.0",
    "gn:asciiname":"Kampung Godingan",
    "gn:country_code":"MY",
    "gn:dem":51,
    "gn:feature_class":"P",
    "gn:feature_code":"PPL",
    "gn:name":"Kampung Godingan",
    "gn:population":0,
    "gn:timezone":"Asia/Kuching",
    "iso:country":"MY",
    "name:msa_x_preferred":[
        "Kampung Godingan"
    ],
    "wof:name":"Kampung Godingan",
    "wof:placetype":"locality"
},
  "geometry": {"coordinates":[117.06359999999999,6.107],"type":"Point"}
}