{
  "type": "Feature",
  "properties": {
    "gn:admin1_code":"1",
    "gn:asciiname":"Kampung Seri Jadi",
    "gn:country_code":"MY",
    "gn:dem":12,
    "gn:feature_class":"P",
    "gn:feature_code":"PPL",
    "gn:name":"Kampung Seri Jadi",
    "gn:population":0,
    "gn:timezone":"Asia/Kuala_Lumpur",
    "iso:country":"MY",
    "name:msa_x_preferred":[
        "Kampung Seri Jadi"
    ],
    "name:und_x_variant":[
        "Kampong Sri Jadi",
        "Kampong Seri Jadi"
    ],
    "wof:name":"Kampung Seri Jadi",
    "wof:placetype":"locality"
},
  "geometry": {"coordinates":[104.05070000000001,1.4595],"type":"Point"}
}