{
  "type": "Feature",
  "properties": {
    "gn:admin1_code":"11",
    "gn:asciiname":"Kampung Tagai Bangkor",
    "gn:country_code":"MY",
    "gn:dem":6,
    "gn:feature_class":"P",
    "gn:feature_code":"PPL",
    "gn:name":"Kampung Tagai Bangkor",
    "gn:population":0,
    "gn:timezone":"Asia/Kuching",
    "iso:country":"MY",
    "name:msa_x_preferred":[
        "Kampung Tagai Bangkor"
    ],
    "name:und_x_variant":[
        "Tagai",
        "Kampong Tagai Bankor",
        "Tagal Saw Mill",
        "Kampong Tagai Bangkor"
    ],
    "wof:name":"Kampung Tagai Bangkor",
    "wof:placetype":"locality"
},
  "geometry": {"coordinates":[115.437,4.9235],"type":"Point"}
}