{
  "type": "Feature",
  "properties": {
    "gn:admin1_code":"1.0",
    "gn:asciiname":"Kampung Belemang Tengah",
    "gn:country_code":"MY",
    "gn:dem":12,
    "gn:feature_class":"P",
    "gn:feature_code":"PPL",
    "gn:name":"Kampung Belemang Tengah",
    "gn:population":0,
    "gn:timezone":"Asia/Kuala_Lumpur",
    "iso:country":"MY",
    "name:msa_x_preferred":[
        "Kampung Belemang Tengah"
    ],
    "wof:name":"Kampung Belemang Tengah",
    "wof:placetype":"locality"
},
  "geometry": {"coordinates":[102.6228,2.1361],"type":"Point"}
}