{
  "type": "Feature",
  "properties": {
    "gn:admin1_code":"6.0",
    "gn:asciiname":"Perumahan Sungai Isap Satu",
    "gn:country_code":"MY",
    "gn:dem":6,
    "gn:feature_class":"P",
    "gn:feature_code":"PPL",
    "gn:name":"Perumahan Sungai Isap Satu",
    "gn:population":0,
    "gn:timezone":"Asia/Kuala_Lumpur",
    "iso:country":"MY",
    "name:msa_x_preferred":[
        "Perumahan Sungai Isap Satu"
    ],
    "wof:name":"Perumahan Sungai Isap Satu",
    "wof:placetype":"locality"
},
  "geometry": {"coordinates":[103.28360000000001,3.7875],"type":"Point"}
}