{
  "type": "Feature",
  "properties": {
    "gn:admin1_code":"6",
    "gn:asciiname":"Kampung Temai Hulu",
    "gn:country_code":"MY",
    "gn:dem":17,
    "gn:feature_class":"P",
    "gn:feature_code":"PPL",
    "gn:name":"Kampung Temai Hulu",
    "gn:population":0,
    "gn:timezone":"Asia/Kuala_Lumpur",
    "iso:country":"MY",
    "name:msa_x_preferred":[
        "Kampung Temai Hulu"
    ],
    "name:und_x_variant":[
        "Kampong Temai Hulu"
    ],
    "wof:name":"Kampung Temai Hulu",
    "wof:placetype":"locality"
},
  "geometry": {"coordinates":[103.2159,3.5475],"type":"Point"}
}