{
  "type": "Feature",
  "properties": {
    "gn:admin1_code":"16",
    "gn:asciiname":"Kampung Layan",
    "gn:country_code":"MY",
    "gn:dem":10,
    "gn:feature_class":"P",
    "gn:feature_code":"PPL",
    "gn:name":"Kampung Layan",
    "gn:population":0,
    "gn:timezone":"Asia/Kuching",
    "iso:country":"MY",
    "name:msa_x_preferred":[
        "Kampung Layan"
    ],
    "name:und_x_variant":[
        "Kampong Layan"
    ],
    "wof:name":"Kampung Layan",
    "wof:placetype":"locality"
},
  "geometry": {"coordinates":[116.10890000000001,6.0268],"type":"Point"}
}