{
  "type": "Feature",
  "properties": {
    "gn:admin1_code":"2",
    "gn:asciiname":"Kampong Sira",
    "gn:country_code":"MY",
    "gn:dem":72,
    "gn:feature_class":"P",
    "gn:feature_code":"PPL",
    "gn:name":"Kampong Sira",
    "gn:population":0,
    "gn:timezone":"Asia/Kuala_Lumpur",
    "iso:country":"MY",
    "wof:name":"Kampong Sira",
    "wof:placetype":"locality"
},
  "geometry": {"coordinates":[100.75,5.88333],"type":"Point"}
}