{
  "type": "Feature",
  "properties": {
    "gn:admin1_code":"12.0",
    "gn:asciiname":"Teluk Bunut",
    "gn:country_code":"MY",
    "gn:dem":8,
    "gn:feature_class":"P",
    "gn:feature_code":"PPL",
    "gn:name":"Teluk Bunut",
    "gn:population":0,
    "gn:timezone":"Asia/Kuala_Lumpur",
    "iso:country":"MY",
    "name:msa_x_preferred":[
        "Teluk Bunut"
    ],
    "name:und_x_variant":[
        "Telok Bunut"
    ],
    "wof:name":"Teluk Bunut",
    "wof:placetype":"locality"
},
  "geometry": {"coordinates":[101.5136,2.8362],"type":"Point"}
}