{
  "type": "Feature",
  "properties": {
    "iso:country":"MY",
    "qs:name":"Klia",
    "qs:name_adm0":"Malaysia",
    "qs:name_adm1":"Selangor",
    "qs:photos":146,
    "qs:photos_1k":30,
    "qs:photos_9k":1,
    "qs:photos_9r":3,
    "qs:photos_all":146,
    "qs:photos_sr":3,
    "qs:placetype":"Town",
    "qs:pop_sr":"0",
    "wof:name":"Klia",
    "wof:placetype":"locality"
},
  "geometry": {"coordinates":[101.715459,2.747052],"type":"Point"}
}