{
  "type": "Feature",
  "properties": {
    "gn:country":"MY",
    "gn:fcode":"PPL",
    "gn:pop":0,
    "iso:country":"MY",
    "name:msa_x_preferred":[
        "Gerisek"
    ],
    "name:unk_x_variant":[
        "Grisek"
    ],
    "qs:name":"Gerisik",
    "qs:name_adm0":"Malaysia",
    "qs:name_adm1":"Johor",
    "qs:photos_9k":1,
    "qs:photos_9r":1,
    "qs:photos_all":4,
    "qs:photos_sr":0,
    "qs:placetype":"Town",
    "qs:pop_sr":"0",
    "wd:wordcount":67,
    "wof:name":"Gerisik",
    "wof:placetype":"locality",
    "wof:population":0
},
  "geometry": {"coordinates":[102.70950000000001,2.2097],"type":"Point"}
}