{
  "type": "Feature",
  "properties": {
    "gn:admin1_code":"16",
    "gn:asciiname":"Kampung Bako",
    "gn:country_code":"MY",
    "gn:dem":-9999,
    "gn:feature_class":"P",
    "gn:feature_code":"PPL",
    "gn:name":"Kampung Bako",
    "gn:population":0,
    "gn:timezone":"Asia/Kuching",
    "iso:country":"MY",
    "name:und_x_variant":[
        "Kampong Bako",
        "Kampung Bako"
    ],
    "wof:name":"Kampung Bako",
    "wof:placetype":"locality"
},
  "geometry": {"coordinates":[118.45059999999999,4.5849],"type":"Point"}
}