{
  "type": "Feature",
  "properties": {
    "iso:country":"MY",
    "name:und_x_variant":[
        "Taman Kelana Idaman"
    ],
    "qs:gn_adm0_cc":"MY",
    "qs:gn_local":1735158,
    "qs:gn_namadm1":"12",
    "qs:local_max":2115,
    "qs:local_sum":11887,
    "qs:localhoods":21,
    "qs:name":"Taman Kelana Idaman",
    "qs:name_adm0":"Malaysia",
    "qs:name_adm1":"Selangor",
    "qs:name_adm2":"Petaling",
    "qs:name_lau":"Damansara",
    "qs:name_local":"Petaling Jaya",
    "qs:photo_max":224,
    "qs:photo_sum":707,
    "qs:placetype":"Suburb",
    "qs:quad_count":31,
    "qs:woe_adm0":23424901,
    "qs:woe_adm1":2346306,
    "qs:woe_adm2":56013632,
    "qs:woe_lau":56014224,
    "qs:woe_local":1155026,
    "qs:woe_ver":"7.10.0",
    "wof:lang":[
        "unk"
    ],
    "wof:name":"Taman Kelana Idaman",
    "wof:placetype":"neighbourhood"
},
  "geometry": {"coordinates":[101.589033,3.099822],"type":"Point"}
}