{
  "type": "Feature",
  "properties": {
    "gn:admin1_code":"2.0",
    "gn:asciiname":"Kampung Charok Pelam",
    "gn:cc2":"MY",
    "gn:country_code":"MY",
    "gn:dem":22,
    "gn:feature_class":"P",
    "gn:feature_code":"PPL",
    "gn:name":"Kampung Charok Pelam",
    "gn:population":0,
    "gn:timezone":"Asia/Kuala_Lumpur",
    "iso:country":"MY",
    "name:msa_x_preferred":[
        "Kampung Charok Pelam"
    ],
    "wof:name":"Kampung Charok Pelam",
    "wof:placetype":"locality"
},
  "geometry": {"coordinates":[100.54516,5.88273],"type":"Point"}
}