{
  "type": "Feature",
  "properties": {
    "gn:admin1_code":"5",
    "gn:asciiname":"Kampong Pedas Hilir",
    "gn:cc2":"MY",
    "gn:country_code":"MY",
    "gn:dem":30,
    "gn:feature_class":"P",
    "gn:feature_code":"PPL",
    "gn:name":"Kampong Pedas Hilir",
    "gn:population":0,
    "gn:timezone":"Asia/Kuala_Lumpur",
    "iso:country":"MY",
    "name:und_x_variant":[
        "Kampong Pedas Kechil",
        "Kampong Pedas Hilir"
    ],
    "wof:name":"Kampong Pedas Hilir",
    "wof:placetype":"locality"
},
  "geometry": {"coordinates":[102.05,2.58333],"type":"Point"}
}