{
  "type": "Feature",
  "properties": {
    "iso:country":"MY",
    "qs:name":"Pertang",
    "qs:name_adm0":"Malaysia",
    "qs:name_adm1":"Negeri Sembilan",
    "qs:photos":24,
    "qs:photos_1k":5,
    "qs:photos_9k":1,
    "qs:photos_9r":2,
    "qs:photos_all":50,
    "qs:photos_sr":1,
    "qs:placetype":"LocalAdmin",
    "qs:pop_sr":"0",
    "wd:wordcount":45,
    "wof:name":"Pertang",
    "wof:placetype":"localadmin"
},
  "geometry": {"coordinates":[102.22958300000001,2.9492705],"type":"Point"}
}