{
  "type": "Feature",
  "properties": {
    "gn:admin1_code":"7",
    "gn:asciiname":"Kampung Kuala Sempit",
    "gn:country_code":"MY",
    "gn:dem":4,
    "gn:feature_class":"P",
    "gn:feature_code":"PPL",
    "gn:name":"Kampung Kuala Sempit",
    "gn:population":0,
    "gn:timezone":"Asia/Kuala_Lumpur",
    "iso:country":"MY",
    "name:msa_x_preferred":[
        "Kampung Kuala Sempit"
    ],
    "name:und_x_variant":[
        "Kampong Kuala Sempit"
    ],
    "wof:name":"Kampung Kuala Sempit",
    "wof:placetype":"locality"
},
  "geometry": {"coordinates":[100.6003,4.2545],"type":"Point"}
}