{
  "type": "Feature",
  "properties": {
    "gn:admin1_code":"11",
    "gn:asciiname":"Kampong Baharu",
    "gn:cc2":"MY",
    "gn:country_code":"MY",
    "gn:dem":17,
    "gn:feature_class":"P",
    "gn:feature_code":"PPL",
    "gn:name":"Kampong Baharu",
    "gn:population":0,
    "gn:timezone":"Asia/Kuching",
    "iso:country":"MY",
    "name:und_x_variant":[
        "Baru",
        "Kampong Baru",
        "Kampong Baharu"
    ],
    "wof:name":"Kampong Baharu",
    "wof:placetype":"locality"
},
  "geometry": {"coordinates":[115.21666999999999,4.88333],"type":"Point"}
}