{
  "type": "Feature",
  "properties": {
    "gn:admin1_code":"7",
    "gn:asciiname":"Kampong Ayer Puteh",
    "gn:cc2":"MY",
    "gn:country_code":"MY",
    "gn:dem":10,
    "gn:feature_class":"P",
    "gn:feature_code":"PPL",
    "gn:name":"Kampong Ayer Puteh",
    "gn:population":0,
    "gn:timezone":"Asia/Kuala_Lumpur",
    "iso:country":"MY",
    "name:und_x_variant":[
        "Ayer Puteh",
        "Kampong Ayer Puteh"
    ],
    "wof:name":"Kampong Ayer Puteh",
    "wof:placetype":"locality"
},
  "geometry": {"coordinates":[100.68333,4.88333],"type":"Point"}
}