{
  "type": "Feature",
  "properties": {
    "gn:admin1_code":"16",
    "gn:asciiname":"Kampung Linsok",
    "gn:country_code":"MY",
    "gn:dem":17,
    "gn:feature_class":"P",
    "gn:feature_code":"PPL",
    "gn:name":"Kampung Linsok",
    "gn:population":0,
    "gn:timezone":"Asia/Kuching",
    "iso:country":"MY",
    "name:msa_x_preferred":[
        "Kampung Linsok"
    ],
    "name:und_x_variant":[
        "Belisan",
        "Kampong Linsok"
    ],
    "wof:name":"Kampung Linsok",
    "wof:placetype":"locality"
},
  "geometry": {"coordinates":[115.59139999999999,5.6229],"type":"Point"}
}