{
  "type": "Feature",
  "properties": {
    "gn:country":"MY",
    "gn:fcode":"ADM3",
    "gn:pop":0,
    "iso:country":"MY",
    "name:unk_x_variant":[
        "Lawas District"
    ],
    "qs:name":"Lawas",
    "qs:photos_9r":0,
    "qs:photos_sr":0,
    "qs:pop_sr":"0",
    "wd:wordcount":1011,
    "wof:name":"Lawas",
    "wof:placetype":"localadmin",
    "wof:population":0
},
  "geometry": {"coordinates":[115.41667,4.5],"type":"Point"}
}