{
  "type": "Feature",
  "properties": {
    "gn:country":"MY",
    "gn:fcode":"ADM3",
    "gn:population":0,
    "iso:country":"MY",
    "name:ast_x_preferred":[
        "Lawas"
    ],
    "name:cat_x_preferred":[
        "Lawas"
    ],
    "name:eng_x_preferred":[
        "Lawas"
    ],
    "name:fra_x_preferred":[
        "Lawas"
    ],
    "name:msa_x_preferred":[
        "Lawas"
    ],
    "name:nld_x_preferred":[
        "Lawas"
    ],
    "name:tam_x_preferred":[
        "\u0b87\u0bb2\u0bbe\u0bb5\u0bbe\u0b9a\u0bc1"
    ],
    "name:ukr_x_preferred":[
        "\u041b\u0430\u0432\u0430\u0441"
    ],
    "name:und_x_variant":[
        "Lawas District"
    ],
    "name:vie_x_preferred":[
        "Lawas"
    ],
    "name:zho_x_preferred":[
        "\u8001\u8d8a"
    ],
    "qs:name":"Lawas",
    "qs:photos_9r":0,
    "qs:photos_sr":0,
    "qs:pop_sr":"0",
    "wd:wordcount":1011,
    "wof:name":"Lawas",
    "wof:placetype":"localadmin",
    "wof:population":0
},
  "geometry": {"coordinates":[115.41667,4.5],"type":"Point"}
}