{
  "type": "Feature",
  "properties": {
    "gn:admin1_code":"5",
    "gn:asciiname":"Kampung Sungai Tawang",
    "gn:country_code":"MY",
    "gn:dem":95,
    "gn:feature_class":"P",
    "gn:feature_code":"PPL",
    "gn:name":"Kampung Sungai Tawang",
    "gn:population":0,
    "gn:timezone":"Asia/Kuala_Lumpur",
    "iso:country":"MY",
    "name:msa_x_preferred":[
        "Kampung Sungai Tawang"
    ],
    "name:und_x_variant":[
        "Kampong Sungai Tawang"
    ],
    "wof:name":"Kampung Sungai Tawang",
    "wof:placetype":"locality"
},
  "geometry": {"coordinates":[102.2657,2.7793],"type":"Point"}
}