{
  "type": "Feature",
  "properties": {
    "gn:admin1_code":"2",
    "gn:asciiname":"Kampung Kebun Tembakau",
    "gn:cc2":"MY",
    "gn:country_code":"MY",
    "gn:dem":36,
    "gn:feature_class":"P",
    "gn:feature_code":"PPL",
    "gn:name":"Kampung Kebun Tembakau",
    "gn:population":0,
    "gn:timezone":"Asia/Kuala_Lumpur",
    "iso:country":"MY",
    "name:msa_x_preferred":[
        "Kampung Kebun Tembakau"
    ],
    "name:und_x_variant":[
        "Kampong Kebon Tembakau"
    ],
    "wof:name":"Kampung Kebun Tembakau",
    "wof:placetype":"locality"
},
  "geometry": {"coordinates":[100.58974000000001,5.4403],"type":"Point"}
}