{
  "type": "Feature",
  "properties": {
    "gn:admin1_code":"1",
    "gn:asciiname":"Kampung Kebun Teh",
    "gn:country_code":"MY",
    "gn:dem":17,
    "gn:feature_class":"P",
    "gn:feature_code":"PPL",
    "gn:name":"Kampung Kebun Teh",
    "gn:population":0,
    "gn:timezone":"Asia/Kuala_Lumpur",
    "iso:country":"MY",
    "name:msa_x_preferred":[
        "Kampung Kebun Teh"
    ],
    "name:und_x_variant":[
        "Kampong Kebun Teh"
    ],
    "wof:name":"Kampung Kebun Teh",
    "wof:placetype":"locality"
},
  "geometry": {"coordinates":[103.7527,1.4938],"type":"Point"}
}