{
  "type": "Feature",
  "properties": {
    "gn:country":"MY",
    "gn:fcode":"ADM3",
    "gn:population":0,
    "iso:country":"MY",
    "name:ast_x_preferred":[
        "Kuala Krai"
    ],
    "name:ceb_x_preferred":[
        "Kuala Krai"
    ],
    "name:deu_x_preferred":[
        "Kuala Krai"
    ],
    "name:eng_x_preferred":[
        "Kuala Krai"
    ],
    "name:fas_x_preferred":[
        "\u06a9\u0648\u0627\u0644\u0627 \u06a9\u0631\u0627\u06cc"
    ],
    "name:jpn_x_preferred":[
        "\u30af\u30a2\u30e9\u30fb\u30af\u30e9\u30a4"
    ],
    "name:msa_x_preferred":[
        "Batu Mengkebang"
    ],
    "name:msa_x_variant":[
        "Kuala Krai"
    ],
    "name:nan_x_preferred":[
        "Kuala Krai Ko\u0101n"
    ],
    "name:nld_x_preferred":[
        "Kuala Krai"
    ],
    "name:spa_x_preferred":[
        "Kuala Krai"
    ],
    "name:tam_x_preferred":[
        "\u0b95\u0bcb\u0bb2\u0bbe \u0b95\u0bbf\u0bb0\u0bbe\u0baf\u0bcd \u0bae\u0bbe\u0bb5\u0b9f\u0bcd\u0b9f\u0bae\u0bcd"
    ],
    "name:vie_x_preferred":[
        "Kuala Krai"
    ],
    "name:zho_x_preferred":[
        "\u74dc\u62c9\u5409\u8d56\u53bf"
    ],
    "qs:name":"Batu Mengkebang",
    "qs:photos_9r":0,
    "qs:photos_sr":0,
    "qs:pop_sr":"0",
    "wd:wordcount":2281,
    "wof:name":"Batu Mengkebang",
    "wof:placetype":"localadmin",
    "wof:population":0
},
  "geometry": {"coordinates":[102.22933999999999,5.57837],"type":"Point"}
}