{
  "type": "Feature",
  "properties": {
    "gn:country":"MY",
    "gn:fcode":"ADM3",
    "gn:pop":0,
    "iso:country":"MY",
    "name:msa_x_preferred":[
        "Batu Mengkebang"
    ],
    "qs:name":"Batu Mengkebang",
    "qs:photos_9r":0,
    "qs:photos_sr":0,
    "qs:pop_sr":"0",
    "wd:wordcount":2281,
    "wof:name":"Batu Mengkebang",
    "wof:placetype":"localadmin",
    "wof:population":0
},
  "geometry": {"coordinates":[102.22933999999999,5.57837],"type":"Point"}
}