{
  "type": "Feature",
  "properties": {
    "gn:admin1_code":"0",
    "gn:asciiname":"Rumah Murah Sungai Lui",
    "gn:country_code":"MY",
    "gn:dem":98,
    "gn:feature_class":"P",
    "gn:feature_code":"PPL",
    "gn:name":"Rumah Murah Sungai Lui",
    "gn:population":0,
    "gn:timezone":"Asia/Kuala_Lumpur",
    "iso:country":"MY",
    "name:und_x_variant":[
        "Kampong Lui",
        "Lui",
        "Kampong Sungai Lui",
        "Rumah Murah Sungai Lui"
    ],
    "wof:name":"Rumah Murah Sungai Lui",
    "wof:placetype":"locality"
},
  "geometry": {"coordinates":[101.88929,3.16063],"type":"Point"}
}