{
  "type": "Feature",
  "properties": {
    "gn:admin1_code":"1",
    "gn:asciiname":"Kampung Baharu Seri Lahang",
    "gn:country_code":"MY",
    "gn:dem":38,
    "gn:feature_class":"P",
    "gn:feature_code":"PPL",
    "gn:name":"Kampung Baharu Seri Lahang",
    "gn:population":0,
    "gn:timezone":"Asia/Kuala_Lumpur",
    "iso:country":"MY",
    "name:msa_x_preferred":[
        "Kampung Baharu Seri Lahang"
    ],
    "name:und_x_variant":[
        "Sri Lalang New Village",
        "Sri Lallang",
        "Seri Lalang"
    ],
    "wof:name":"Kampung Baharu Seri Lahang",
    "wof:placetype":"locality"
},
  "geometry": {"coordinates":[103.25279999999999,1.994],"type":"Point"}
}