{
  "type": "Feature",
  "properties": {
    "gn:admin1_code":"6.0",
    "gn:asciiname":"Kampung Tualang",
    "gn:country_code":"MY",
    "gn:dem":125,
    "gn:feature_class":"P",
    "gn:feature_code":"PPL",
    "gn:name":"Kampung Tualang",
    "gn:population":0,
    "gn:timezone":"Asia/Kuala_Lumpur",
    "iso:country":"MY",
    "name:msa_x_preferred":[
        "Kampung Tualang"
    ],
    "wof:name":"Kampung Tualang",
    "wof:placetype":"locality"
},
  "geometry": {"coordinates":[101.9417,4.0498],"type":"Point"}
}