{
  "type": "Feature",
  "properties": {
    "gn:admin1_code":"6",
    "gn:asciiname":"Kampung Jeruk",
    "gn:country_code":"MY",
    "gn:dem":106,
    "gn:feature_class":"P",
    "gn:feature_code":"PPL",
    "gn:name":"Kampung Jeruk",
    "gn:population":0,
    "gn:timezone":"Asia/Kuala_Lumpur",
    "iso:country":"MY",
    "name:msa_x_preferred":[
        "Kampung Jeruk"
    ],
    "name:und_x_variant":[
        "Kampong Jerok"
    ],
    "wof:name":"Kampung Jeruk",
    "wof:placetype":"locality"
},
  "geometry": {"coordinates":[101.9577,4.057],"type":"Point"}
}