{
  "type": "Feature",
  "properties": {
    "gn:admin1_code":"11.0",
    "gn:asciiname":"San Semanju",
    "gn:country_code":"MY",
    "gn:dem":102,
    "gn:feature_class":"P",
    "gn:feature_code":"PPL",
    "gn:name":"San Semanju",
    "gn:population":0,
    "gn:timezone":"Asia/Kuching",
    "iso:country":"MY",
    "name:und_x_variant":[
        "Nanga San Semanju"
    ],
    "wof:name":"San Semanju",
    "wof:placetype":"locality"
},
  "geometry": {"coordinates":[111.70907,1.23604],"type":"Point"}
}