{
  "type": "Feature",
  "properties": {
    "gn:admin1_code":"8.0",
    "gn:asciiname":"Kampung Syed Abdan",
    "gn:country_code":"MY",
    "gn:dem":59,
    "gn:feature_class":"P",
    "gn:feature_code":"PPL",
    "gn:name":"Kampung Syed Abdan",
    "gn:population":0,
    "gn:timezone":"Asia/Kuala_Lumpur",
    "iso:country":"MY",
    "name:msa_x_preferred":[
        "Kampung Syed Abdan"
    ],
    "wof:name":"Kampung Syed Abdan",
    "wof:placetype":"locality"
},
  "geometry": {"coordinates":[100.29395,6.65504],"type":"Point"}
}