{
  "type": "Feature",
  "properties": {
    "gn:admin1_code":"16",
    "gn:asciiname":"Kampung Kohopis",
    "gn:country_code":"MY",
    "gn:dem":22,
    "gn:feature_class":"P",
    "gn:feature_code":"PPL",
    "gn:name":"Kampung Kohopis",
    "gn:population":0,
    "gn:timezone":"Asia/Kuching",
    "iso:country":"MY",
    "name:msa_x_preferred":[
        "Kampung Kohopis"
    ],
    "name:und_x_variant":[
        "Kampong Kelopis"
    ],
    "wof:name":"Kampung Kohopis",
    "wof:placetype":"locality"
},
  "geometry": {"coordinates":[116.1401,5.9226],"type":"Point"}
}