{
  "type": "Feature",
  "properties": {
    "gn:admin1_code":"1.0",
    "gn:asciiname":"Kampung Ulu Tiram",
    "gn:country_code":"MY",
    "gn:dem":32,
    "gn:feature_class":"P",
    "gn:feature_code":"PPL",
    "gn:name":"Kampung Ulu Tiram",
    "gn:population":0,
    "gn:timezone":"Asia/Kuala_Lumpur",
    "iso:country":"MY",
    "name:msa_x_preferred":[
        "Kampung Ulu Tiram"
    ],
    "name:und_x_variant":[
        "Kampung Hulu Tiram",
        "Ulu Tiram",
        "Ulu Tiram Village"
    ],
    "wof:name":"Kampung Ulu Tiram",
    "wof:placetype":"locality"
},
  "geometry": {"coordinates":[103.8214,1.5999],"type":"Point"}
}