{
  "type": "Feature",
  "properties": {
    "gn:admin1_code":"6.0",
    "gn:asciiname":"Permatang Bedun",
    "gn:country_code":"MY",
    "gn:dem":12,
    "gn:feature_class":"P",
    "gn:feature_code":"PPL",
    "gn:name":"Permatang Bedun",
    "gn:population":0,
    "gn:timezone":"Asia/Kuala_Lumpur",
    "iso:country":"MY",
    "name:msa_x_preferred":[
        "Permatang Bedun"
    ],
    "wof:name":"Permatang Bedun",
    "wof:placetype":"locality"
},
  "geometry": {"coordinates":[103.3839,2.967],"type":"Point"}
}