{
  "type": "Feature",
  "properties": {
    "gn:admin1_code":"7.0",
    "gn:asciiname":"Sungai Keruh",
    "gn:cc2":"MY",
    "gn:country_code":"MY",
    "gn:dem":29,
    "gn:feature_class":"P",
    "gn:feature_code":"PPL",
    "gn:name":"Sungai Keruh",
    "gn:population":0,
    "gn:timezone":"Asia/Kuala_Lumpur",
    "iso:country":"MY",
    "name:und_x_variant":[
        "Kampong Sungei Kroh",
        "Sungai Keroh",
        "Sungai Kroh",
        "Sungei Kerok",
        "Sungai Keruh"
    ],
    "wof:name":"Sungai Keruh",
    "wof:placetype":"locality"
},
  "geometry": {"coordinates":[101.15000000000001,4.21667],"type":"Point"}
}