{
  "type": "Feature",
  "properties": {
    "gn:admin1_code":"16.0",
    "gn:asciiname":"Kampung Bak Bak",
    "gn:country_code":"MY",
    "gn:dem":30,
    "gn:feature_class":"P",
    "gn:feature_code":"PPL",
    "gn:name":"Kampung Bak Bak",
    "gn:population":0,
    "gn:timezone":"Asia/Kuching",
    "iso:country":"MY",
    "name:msa_x_preferred":[
        "Kampung Bak Bak"
    ],
    "wof:name":"Kampung Bak Bak",
    "wof:placetype":"locality"
},
  "geometry": {"coordinates":[116.8082,6.9681],"type":"Point"}
}