{
  "type": "Feature",
  "properties": {
    "gn:admin1_code":"2.0",
    "gn:asciiname":"Kampung Padang Setol",
    "gn:country_code":"MY",
    "gn:dem":49,
    "gn:feature_class":"P",
    "gn:feature_code":"PPL",
    "gn:name":"Kampung Padang Setol",
    "gn:population":0,
    "gn:timezone":"Asia/Kuala_Lumpur",
    "iso:country":"MY",
    "name:msa_x_preferred":[
        "Kampung Padang Setol"
    ],
    "wof:name":"Kampung Padang Setol",
    "wof:placetype":"locality"
},
  "geometry": {"coordinates":[100.77715000000001,5.57988],"type":"Point"}
}