{
  "type": "Feature",
  "properties": {
    "gn:admin1_code":"1",
    "gn:asciiname":"Kampung Parit Simpang",
    "gn:country_code":"MY",
    "gn:dem":12,
    "gn:feature_class":"P",
    "gn:feature_code":"PPL",
    "gn:name":"Kampung Parit Simpang",
    "gn:population":0,
    "gn:timezone":"Asia/Kuala_Lumpur",
    "iso:country":"MY",
    "name:msa_x_preferred":[
        "Kampung Parit Simpang"
    ],
    "name:und_x_variant":[
        "Kampong Parit Simpang"
    ],
    "wof:name":"Kampung Parit Simpang",
    "wof:placetype":"locality"
},
  "geometry": {"coordinates":[102.62820000000001,2.0639],"type":"Point"}
}