{
  "type": "Feature",
  "properties": {
    "gn:admin1_code":"2",
    "gn:asciiname":"Kampung Bechah Tualang",
    "gn:cc2":"MY",
    "gn:country_code":"MY",
    "gn:dem":111,
    "gn:feature_class":"P",
    "gn:feature_code":"PPL",
    "gn:name":"Kampung Bechah Tualang",
    "gn:population":0,
    "gn:timezone":"Asia/Kuala_Lumpur",
    "iso:country":"MY",
    "name:msa_x_preferred":[
        "Kampung Bechah Tualang"
    ],
    "name:und_x_variant":[
        "Kampong Bechah Tualang",
        "Kampong Benchah Tulang",
        "Kampong Benchah Tualang"
    ],
    "wof:name":"Kampung Bechah Tualang",
    "wof:placetype":"locality"
},
  "geometry": {"coordinates":[100.90881,5.76091],"type":"Point"}
}