{
  "type": "Feature",
  "properties": {
    "gn:admin1_code":"5",
    "gn:asciiname":"Kampung Sawah Raja",
    "gn:country_code":"MY",
    "gn:dem":33,
    "gn:feature_class":"P",
    "gn:feature_code":"PPL",
    "gn:name":"Kampung Sawah Raja",
    "gn:population":0,
    "gn:timezone":"Asia/Kuala_Lumpur",
    "iso:country":"MY",
    "name:msa_x_preferred":[
        "Kampung Sawah Raja"
    ],
    "name:und_x_variant":[
        "Kampong Sawah Raja",
        "Kampong Sawah Rajah"
    ],
    "wof:name":"Kampung Sawah Raja",
    "wof:placetype":"locality"
},
  "geometry": {"coordinates":[102.1054,2.4831],"type":"Point"}
}