{
  "type": "Feature",
  "properties": {
    "gn:admin1_code":"1",
    "gn:asciiname":"Kampung Tiram Duku",
    "gn:country_code":"MY",
    "gn:dem":14,
    "gn:feature_class":"P",
    "gn:feature_code":"PPL",
    "gn:name":"Kampung Tiram Duku",
    "gn:population":0,
    "gn:timezone":"Asia/Kuala_Lumpur",
    "iso:country":"MY",
    "name:msa_x_preferred":[
        "Kampung Tiram Duku"
    ],
    "name:und_x_variant":[
        "Kampong Tiram Duku"
    ],
    "wof:name":"Kampung Tiram Duku",
    "wof:placetype":"locality"
},
  "geometry": {"coordinates":[103.5685,1.382],"type":"Point"}
}