{
  "type": "Feature",
  "properties": {
    "gn:country":"MY",
    "gn:fcode":"PPL",
    "gn:population":0,
    "iso:country":"MY",
    "name:msa_x_preferred":[
        "Kampung Sungai Buah"
    ],
    "qs:name":"Kampong Sungai Buah",
    "qs:name_adm0":"Malaysia",
    "qs:name_adm1":"Selangor",
    "qs:photos_9r":0,
    "qs:photos_sr":0,
    "qs:placetype":"Town",
    "qs:pop_sr":"0",
    "wof:name":"Kampong Sungai Buah",
    "wof:placetype":"locality",
    "wof:population":0
},
  "geometry": {"coordinates":[101.7641,2.88],"type":"Point"}
}