{
  "type": "Feature",
  "properties": {
    "gn:admin1_code":"1",
    "gn:asciiname":"Kampung Tanah Abang",
    "gn:country_code":"MY",
    "gn:dem":32,
    "gn:feature_class":"P",
    "gn:feature_code":"PPL",
    "gn:name":"Kampung Tanah Abang",
    "gn:population":0,
    "gn:timezone":"Asia/Kuala_Lumpur",
    "iso:country":"MY",
    "name:msa_x_preferred":[
        "Kampung Tanah Abang"
    ],
    "name:und_x_variant":[
        "Kampong Tanah Abang"
    ],
    "wof:name":"Kampung Tanah Abang",
    "wof:placetype":"locality"
},
  "geometry": {"coordinates":[103.63075000000001,2.46616],"type":"Point"}
}