{
  "type": "Feature",
  "properties": {
    "gn:admin1_code":"13.0",
    "gn:asciiname":"Kampung Fikri Sungai Tong",
    "gn:country_code":"MY",
    "gn:dem":23,
    "gn:feature_class":"P",
    "gn:feature_code":"PPL",
    "gn:name":"Kampung Fikri Sungai Tong",
    "gn:population":0,
    "gn:timezone":"Asia/Kuala_Lumpur",
    "iso:country":"MY",
    "name:msa_x_preferred":[
        "Kampung Fikri Sungai Tong"
    ],
    "wof:name":"Kampung Fikri Sungai Tong",
    "wof:placetype":"locality"
},
  "geometry": {"coordinates":[102.89870000000001,5.32],"type":"Point"}
}