{
  "type": "Feature",
  "properties": {
    "gn:admin1_code":"11.0",
    "gn:asciiname":"Kampung Merapok Ulu",
    "gn:country_code":"MY",
    "gn:dem":35,
    "gn:feature_class":"P",
    "gn:feature_code":"PPL",
    "gn:name":"Kampung Merapok Ulu",
    "gn:population":0,
    "gn:timezone":"Asia/Kuching",
    "iso:country":"MY",
    "name:msa_x_preferred":[
        "Kampung Merapok Ulu"
    ],
    "name:und_x_variant":[
        "Kampung Merapok Hulu"
    ],
    "wof:name":"Kampung Merapok Ulu",
    "wof:placetype":"locality"
},
  "geometry": {"coordinates":[115.5896,4.9612],"type":"Point"}
}