{
  "type": "Feature",
  "properties": {
    "gn:admin1_code":"2",
    "gn:asciiname":"Kampung Malau",
    "gn:country_code":"MY",
    "gn:dem":26,
    "gn:feature_class":"P",
    "gn:feature_code":"PPL",
    "gn:name":"Kampung Malau",
    "gn:population":0,
    "gn:timezone":"Asia/Kuala_Lumpur",
    "iso:country":"MY",
    "name:msa_x_preferred":[
        "Kampung Malau"
    ],
    "name:und_x_variant":[
        "Kampong Malau"
    ],
    "wof:name":"Kampung Malau",
    "wof:placetype":"locality"
},
  "geometry": {"coordinates":[100.45023999999999,6.2779],"type":"Point"}
}