{
  "type": "Feature",
  "properties": {
    "gn:admin1_code":"2",
    "gn:asciiname":"Kampung Hulu Tawar",
    "gn:cc2":"MY",
    "gn:country_code":"MY",
    "gn:dem":50,
    "gn:feature_class":"P",
    "gn:feature_code":"PPL",
    "gn:name":"Kampung Hulu Tawar",
    "gn:population":0,
    "gn:timezone":"Asia/Kuala_Lumpur",
    "iso:country":"MY",
    "name:msa_x_preferred":[
        "Kampung Hulu Tawar"
    ],
    "name:und_x_variant":[
        "Kampong Ulu Tawar"
    ],
    "wof:name":"Kampung Hulu Tawar",
    "wof:placetype":"locality"
},
  "geometry": {"coordinates":[100.73636,5.45665],"type":"Point"}
}