{
  "type": "Feature",
  "properties": {
    "gn:admin1_code":"16",
    "gn:asciiname":"Kampong Tamu Darat",
    "gn:country_code":"MY",
    "gn:dem":64,
    "gn:feature_class":"P",
    "gn:feature_code":"PPL",
    "gn:name":"Kampong Tamu Darat",
    "gn:population":0,
    "gn:timezone":"Asia/Kuching",
    "iso:country":"MY",
    "name:msa_x_preferred":[
        "Kampong Tamu Darat"
    ],
    "name:und_x_variant":[
        "Tamu Darat"
    ],
    "wof:name":"Kampong Tamu Darat",
    "wof:placetype":"locality"
},
  "geometry": {"coordinates":[116.4554,6.2654],"type":"Point"}
}