{
  "type": "Feature",
  "properties": {
    "gn:admin1_code":"7.0",
    "gn:asciiname":"Kampung Permatang Raja",
    "gn:country_code":"MY",
    "gn:dem":9,
    "gn:feature_class":"P",
    "gn:feature_code":"PPL",
    "gn:name":"Kampung Permatang Raja",
    "gn:population":0,
    "gn:timezone":"Asia/Kuala_Lumpur",
    "iso:country":"MY",
    "name:msa_x_preferred":[
        "Kampung Permatang Raja"
    ],
    "wof:name":"Kampung Permatang Raja",
    "wof:placetype":"locality"
},
  "geometry": {"coordinates":[100.6686,4.5458],"type":"Point"}
}