{
  "type": "Feature",
  "properties": {
    "gn:admin1_code":"6.0",
    "gn:asciiname":"Kampung Seberang Lipis",
    "gn:country_code":"MY",
    "gn:dem":90,
    "gn:feature_class":"P",
    "gn:feature_code":"PPL",
    "gn:name":"Kampung Seberang Lipis",
    "gn:population":0,
    "gn:timezone":"Asia/Kuala_Lumpur",
    "iso:country":"MY",
    "name:msa_x_preferred":[
        "Kampung Seberang Lipis"
    ],
    "wof:name":"Kampung Seberang Lipis",
    "wof:placetype":"locality"
},
  "geometry": {"coordinates":[101.9646,4.0188],"type":"Point"}
}