{
  "type": "Feature",
  "properties": {
    "gn:admin1_code":"0",
    "gn:asciiname":"Kampong Pasir Panjang",
    "gn:country_code":"MY",
    "gn:dem":2,
    "gn:feature_class":"P",
    "gn:feature_code":"PPL",
    "gn:name":"Kampong Pasir Panjang",
    "gn:population":0,
    "gn:timezone":"Asia/Kuala_Lumpur",
    "iso:country":"MY",
    "wof:name":"Kampong Pasir Panjang",
    "wof:placetype":"locality"
},
  "geometry": {"coordinates":[101.25,3.35],"type":"Point"}
}