{
  "type": "Feature",
  "properties": {
    "gn:admin1_code":"6.0",
    "gn:asciiname":"Kampung Pulau Lipan",
    "gn:country_code":"MY",
    "gn:dem":39,
    "gn:feature_class":"P",
    "gn:feature_code":"PPL",
    "gn:name":"Kampung Pulau Lipan",
    "gn:population":0,
    "gn:timezone":"Asia/Kuala_Lumpur",
    "iso:country":"MY",
    "name:msa_x_preferred":[
        "Kampung Pulau Lipan"
    ],
    "wof:name":"Kampung Pulau Lipan",
    "wof:placetype":"locality"
},
  "geometry": {"coordinates":[102.62009999999999,3.4753],"type":"Point"}
}