{
  "type": "Feature",
  "properties": {
    "gn:admin1_code":"3.0",
    "gn:asciiname":"Kampung Sungai Terah",
    "gn:country_code":"MY",
    "gn:dem":91,
    "gn:feature_class":"P",
    "gn:feature_code":"PPL",
    "gn:name":"Kampung Sungai Terah",
    "gn:population":0,
    "gn:timezone":"Asia/Kuala_Lumpur",
    "iso:country":"MY",
    "name:msa_x_preferred":[
        "Kampung Sungai Terah"
    ],
    "wof:name":"Kampung Sungai Terah",
    "wof:placetype":"locality"
},
  "geometry": {"coordinates":[101.97024999999999,4.89655],"type":"Point"}
}