{
  "type": "Feature",
  "properties": {
    "gn:admin1_code":"13",
    "gn:asciiname":"Kampung Teluk Putat",
    "gn:country_code":"MY",
    "gn:dem":19,
    "gn:feature_class":"P",
    "gn:feature_code":"PPL",
    "gn:name":"Kampung Teluk Putat",
    "gn:population":0,
    "gn:timezone":"Asia/Kuala_Lumpur",
    "iso:country":"MY",
    "name:msa_x_preferred":[
        "Kampung Teluk Putat"
    ],
    "name:und_x_variant":[
        "Kampong Tanjong Putat"
    ],
    "wof:name":"Kampung Teluk Putat",
    "wof:placetype":"locality"
},
  "geometry": {"coordinates":[103.0142,5.0623],"type":"Point"}
}