{
  "type": "Feature",
  "properties": {
    "gn:admin1_code":"12",
    "gn:asciiname":"Kampung Banting",
    "gn:country_code":"MY",
    "gn:dem":5,
    "gn:feature_class":"P",
    "gn:feature_code":"PPL",
    "gn:name":"Kampung Banting",
    "gn:population":0,
    "gn:timezone":"Asia/Kuala_Lumpur",
    "iso:country":"MY",
    "name:msa_x_preferred":[
        "Kampong Banting"
    ],
    "name:und_x_variant":[
        "Tanah Permatang",
        "Kampong Banting",
        "Kampung Banting"
    ],
    "wof:name":"Kampung Banting",
    "wof:placetype":"locality"
},
  "geometry": {"coordinates":[100.92310000000001,3.7577],"type":"Point"}
}