{
  "type": "Feature",
  "properties": {
    "gn:admin1_code":"3.0",
    "gn:asciiname":"Lubuk Bemban",
    "gn:country_code":"MY",
    "gn:dem":11,
    "gn:feature_class":"P",
    "gn:feature_code":"PPL",
    "gn:name":"Lubuk Bemban",
    "gn:population":0,
    "gn:timezone":"Asia/Kuala_Lumpur",
    "iso:country":"MY",
    "name:msa_x_preferred":[
        "Lubuk Bemban"
    ],
    "wof:name":"Lubuk Bemban",
    "wof:placetype":"locality"
},
  "geometry": {"coordinates":[102.49451000000001,5.78194],"type":"Point"}
}