{
  "type": "Feature",
  "properties": {
    "gn:admin1_code":"9.0",
    "gn:asciiname":"Kampung Sepuluh Kongsi",
    "gn:country_code":"MY",
    "gn:dem":123,
    "gn:feature_class":"P",
    "gn:feature_code":"PPL",
    "gn:name":"Kampung Sepuluh Kongsi",
    "gn:population":0,
    "gn:timezone":"Asia/Kuala_Lumpur",
    "iso:country":"MY",
    "name:msa_x_preferred":[
        "Kampung Sepuluh Kongsi"
    ],
    "wof:name":"Kampung Sepuluh Kongsi",
    "wof:placetype":"locality"
},
  "geometry": {"coordinates":[100.52979999999999,5.25107],"type":"Point"}
}