{
  "type": "Feature",
  "properties": {
    "gn:admin1_code":"0",
    "gn:asciiname":"Kampong Sungai Sekamat",
    "gn:cc2":"MY",
    "gn:country_code":"MY",
    "gn:dem":41,
    "gn:feature_class":"P",
    "gn:feature_code":"PPL",
    "gn:name":"Kampong Sungai Sekamat",
    "gn:population":0,
    "gn:timezone":"Asia/Kuala_Lumpur",
    "iso:country":"MY",
    "name:und_x_variant":[
        "Kampong Sekamat",
        "Kampong Sungai Sekamat"
    ],
    "wof:name":"Kampong Sungai Sekamat",
    "wof:placetype":"locality"
},
  "geometry": {"coordinates":[101.78333000000001,3.01667],"type":"Point"}
}