{
  "type": "Feature",
  "properties": {
    "gn:admin1_code":"16",
    "gn:asciiname":"Kampong Tugasan",
    "gn:country_code":"MY",
    "gn:dem":184,
    "gn:feature_class":"P",
    "gn:feature_code":"PPL",
    "gn:name":"Kampong Tugasan",
    "gn:population":0,
    "gn:timezone":"Asia/Kuching",
    "iso:country":"MY",
    "wof:name":"Kampong Tugasan",
    "wof:placetype":"locality"
},
  "geometry": {"coordinates":[116.43333,6.23333],"type":"Point"}
}