{
  "type": "Feature",
  "properties": {
    "gn:admin1_code":"7.0",
    "gn:asciiname":"Kampung Sungai Road Terap",
    "gn:cc2":"MY",
    "gn:country_code":"MY",
    "gn:dem":23,
    "gn:feature_class":"P",
    "gn:feature_code":"PPL",
    "gn:name":"Kampung Sungai Road Terap",
    "gn:population":0,
    "gn:timezone":"Asia/Kuala_Lumpur",
    "iso:country":"MY",
    "name:msa_x_preferred":[
        "Kampung Sungai Road Terap"
    ],
    "wof:name":"Kampung Sungai Road Terap",
    "wof:placetype":"locality"
},
  "geometry": {"coordinates":[100.67478,5.19705],"type":"Point"}
}