{
  "type": "Feature",
  "properties": {
    "gn:admin1_code":"13.0",
    "gn:asciiname":"Kampung Gong Kemunting",
    "gn:country_code":"MY",
    "gn:dem":10,
    "gn:feature_class":"P",
    "gn:feature_code":"PPL",
    "gn:name":"Kampung Gong Kemunting",
    "gn:population":0,
    "gn:timezone":"Asia/Kuala_Lumpur",
    "iso:country":"MY",
    "name:msa_x_preferred":[
        "Kampung Gong Kemunting"
    ],
    "wof:name":"Kampung Gong Kemunting",
    "wof:placetype":"locality"
},
  "geometry": {"coordinates":[103.16330000000001,5.2866],"type":"Point"}
}