{
  "type": "Feature",
  "properties": {
    "gn:admin1_code":"2",
    "gn:asciiname":"Kampung Selarong",
    "gn:cc2":"MY",
    "gn:country_code":"MY",
    "gn:dem":23,
    "gn:feature_class":"P",
    "gn:feature_code":"PPL",
    "gn:name":"Kampung Selarong",
    "gn:population":0,
    "gn:timezone":"Asia/Kuala_Lumpur",
    "iso:country":"MY",
    "name:msa_x_preferred":[
        "Kampung Selarong"
    ],
    "name:und_x_variant":[
        "Kampong Selarong"
    ],
    "wof:name":"Kampung Selarong",
    "wof:placetype":"locality"
},
  "geometry": {"coordinates":[100.57752000000001,5.47542],"type":"Point"}
}