{
  "type": "Feature",
  "properties": {
    "gn:admin1_code":"4",
    "gn:asciiname":"Kampung Bertam",
    "gn:country_code":"MY",
    "gn:dem":14,
    "gn:feature_class":"P",
    "gn:feature_code":"PPL",
    "gn:name":"Kampung Bertam",
    "gn:population":0,
    "gn:timezone":"Asia/Kuala_Lumpur",
    "iso:country":"MY",
    "name:msa_x_preferred":[
        "Kampung Bertam"
    ],
    "name:und_x_variant":[
        "Kampong Bertam"
    ],
    "wof:name":"Kampung Bertam",
    "wof:placetype":"locality"
},
  "geometry": {"coordinates":[102.22199999999999,2.2481],"type":"Point"}
}