{
  "type": "Feature",
  "properties": {
    "gn:admin1_code":"2.0",
    "gn:asciiname":"Ladang Kelang Lama",
    "gn:country_code":"MY",
    "gn:dem":66,
    "gn:feature_class":"P",
    "gn:feature_code":"PPL",
    "gn:name":"Ladang Kelang Lama",
    "gn:population":0,
    "gn:timezone":"Asia/Kuala_Lumpur",
    "iso:country":"MY",
    "name:msa_x_preferred":[
        "Ladang Kelang Lama"
    ],
    "wof:name":"Ladang Kelang Lama",
    "wof:placetype":"locality"
},
  "geometry": {"coordinates":[100.56878,5.40441],"type":"Point"}
}