{
  "type": "Feature",
  "properties": {
    "gn:admin1_code":"3.0",
    "gn:asciiname":"Kampung Pulau Chegar Atas",
    "gn:country_code":"MY",
    "gn:dem":98,
    "gn:feature_class":"P",
    "gn:feature_code":"PPL",
    "gn:name":"Kampung Pulau Chegar Atas",
    "gn:population":0,
    "gn:timezone":"Asia/Kuala_Lumpur",
    "iso:country":"MY",
    "name:msa_x_preferred":[
        "Kampung Pulau Chegar Atas"
    ],
    "wof:name":"Kampung Pulau Chegar Atas",
    "wof:placetype":"locality"
},
  "geometry": {"coordinates":[101.97450000000001,5.1078],"type":"Point"}
}