{
  "type": "Feature",
  "properties": {
    "gn:admin1_code":"2.0",
    "gn:asciiname":"Kampung Charok Suda",
    "gn:country_code":"MY",
    "gn:dem":70,
    "gn:feature_class":"P",
    "gn:feature_code":"PPL",
    "gn:name":"Kampung Charok Suda",
    "gn:population":0,
    "gn:timezone":"Asia/Kuala_Lumpur",
    "iso:country":"MY",
    "name:msa_x_preferred":[
        "Kampung Charok Suda"
    ],
    "wof:name":"Kampung Charok Suda",
    "wof:placetype":"locality"
},
  "geometry": {"coordinates":[100.75861999999999,5.7853],"type":"Point"}
}