{
  "type": "Feature",
  "properties": {
    "gn:admin1_code":"6.0",
    "gn:asciiname":"Kemajuan Tanah Jengka Sembilan",
    "gn:country_code":"MY",
    "gn:dem":57,
    "gn:feature_class":"P",
    "gn:feature_code":"PPL",
    "gn:name":"Kemajuan Tanah Jengka Sembilan",
    "gn:population":0,
    "gn:timezone":"Asia/Kuala_Lumpur",
    "iso:country":"MY",
    "name:msa_x_preferred":[
        "Kemajuan Tanah Jengka Sembilan"
    ],
    "wof:name":"Kemajuan Tanah Jengka Sembilan",
    "wof:placetype":"locality"
},
  "geometry": {"coordinates":[102.46939999999999,3.8164],"type":"Point"}
}