{
  "type": "Feature",
  "properties": {
    "gn:admin1_code":"16",
    "gn:asciiname":"Kampung Kalimbata",
    "gn:country_code":"MY",
    "gn:dem":12,
    "gn:feature_class":"P",
    "gn:feature_code":"PPL",
    "gn:name":"Kampung Kalimbata",
    "gn:population":0,
    "gn:timezone":"Asia/Kuching",
    "iso:country":"MY",
    "name:msa_x_preferred":[
        "Kampung Kalimbata"
    ],
    "name:und_x_variant":[
        "Kampong Kalimbata"
    ],
    "wof:name":"Kampung Kalimbata",
    "wof:placetype":"locality"
},
  "geometry": {"coordinates":[115.55710000000001,5.5531],"type":"Point"}
}