{
  "type": "Feature",
  "properties": {
    "gn:admin1_code":"13",
    "gn:asciiname":"Kampung Binjai Kertas",
    "gn:country_code":"MY",
    "gn:dem":25,
    "gn:feature_class":"P",
    "gn:feature_code":"PPL",
    "gn:name":"Kampung Binjai Kertas",
    "gn:population":0,
    "gn:timezone":"Asia/Kuala_Lumpur",
    "iso:country":"MY",
    "name:msa_x_preferred":[
        "Kampung Binjai Kertas"
    ],
    "name:und_x_variant":[
        "Kampong Binjai Kertas"
    ],
    "wof:name":"Kampung Binjai Kertas",
    "wof:placetype":"locality"
},
  "geometry": {"coordinates":[103.0313,5.1319],"type":"Point"}
}