{
  "type": "Feature",
  "properties": {
    "gn:admin1_code":"4",
    "gn:asciiname":"Kampung Tengah",
    "gn:country_code":"MY",
    "gn:dem":29,
    "gn:feature_class":"P",
    "gn:feature_code":"PPL",
    "gn:name":"Kampung Tengah",
    "gn:population":0,
    "gn:timezone":"Asia/Kuala_Lumpur",
    "iso:country":"MY",
    "name:msa_x_preferred":[
        "Kampung Tengah"
    ],
    "name:und_x_variant":[
        "Kampong Tengah"
    ],
    "wof:name":"Kampung Tengah",
    "wof:placetype":"locality"
},
  "geometry": {"coordinates":[102.20659999999999,2.3528],"type":"Point"}
}