{
  "type": "Feature",
  "properties": {
    "gn:admin1_code":"16",
    "gn:asciiname":"Kampung Ginan",
    "gn:country_code":"MY",
    "gn:dem":906,
    "gn:feature_class":"P",
    "gn:feature_code":"PPL",
    "gn:name":"Kampung Ginan",
    "gn:population":0,
    "gn:timezone":"Asia/Kuching",
    "iso:country":"MY",
    "name:msa_x_preferred":[
        "Kampung Ginan"
    ],
    "name:und_x_variant":[
        "Kampong Ginan"
    ],
    "wof:name":"Kampung Ginan",
    "wof:placetype":"locality"
},
  "geometry": {"coordinates":[116.2616,5.9034],"type":"Point"}
}