{
  "type": "Feature",
  "properties": {
    "iso:country":"MY",
    "qs:name":"Lestari Sanctuary Lestari Mansions",
    "qs:name_adm0":"Malaysia",
    "qs:name_adm1":"Selangor",
    "qs:photos":51,
    "qs:photos_1k":10,
    "qs:photos_9k":1,
    "qs:photos_9r":2,
    "qs:photos_all":51,
    "qs:photos_sr":2,
    "qs:placetype":"Suburb",
    "qs:pop_sr":"0",
    "wof:name":"Lestari Sanctuary Lestari Mansions",
    "wof:placetype":"neighbourhood"
},
  "geometry": {"coordinates":[101.67060600000001,3.013315],"type":"Point"}
}