{
  "type": "Feature",
  "properties": {
    "gn:admin1_code":"11.0",
    "gn:asciiname":"Bukong",
    "gn:country_code":"MY",
    "gn:dem":29,
    "gn:feature_class":"P",
    "gn:feature_code":"PPL",
    "gn:name":"Bukong",
    "gn:population":0,
    "gn:timezone":"Asia/Kuching",
    "iso:country":"MY",
    "wof:name":"Bukong",
    "wof:placetype":"locality"
},
  "geometry": {"coordinates":[111.56667,1.33333],"type":"Point"}
}