{
  "type": "Feature",
  "properties": {
    "gn:admin1_code":"11.0",
    "gn:asciiname":"Batu Kawa",
    "gn:cc2":"MY",
    "gn:country_code":"MY",
    "gn:dem":19,
    "gn:feature_class":"P",
    "gn:feature_code":"PPL",
    "gn:name":"Batu Kawa",
    "gn:population":0,
    "gn:timezone":"Asia/Kuching",
    "iso:country":"MY",
    "name:und_x_variant":[
        "Batu Kaua",
        "Batu Kawa"
    ],
    "wof:name":"Batu Kawa",
    "wof:placetype":"locality"
},
  "geometry": {"coordinates":[110.26667,1.51667],"type":"Point"}
}