{
  "type": "Feature",
  "properties": {
    "gn:admin1_code":"5",
    "gn:asciiname":"Kampung Mentaus",
    "gn:country_code":"MY",
    "gn:dem":85,
    "gn:feature_class":"P",
    "gn:feature_code":"PPL",
    "gn:name":"Kampung Mentaus",
    "gn:population":0,
    "gn:timezone":"Asia/Kuala_Lumpur",
    "iso:country":"MY",
    "name:msa_x_preferred":[
        "Kampung Mentaus"
    ],
    "name:und_x_variant":[
        "Kampong Mentaus"
    ],
    "wof:name":"Kampung Mentaus",
    "wof:placetype":"locality"
},
  "geometry": {"coordinates":[102.2316,3.1198],"type":"Point"}
}