{
  "type": "Feature",
  "properties": {
    "gn:admin1_code":"2.0",
    "gn:asciiname":"Kampung Tok Golok",
    "gn:country_code":"MY",
    "gn:dem":73,
    "gn:feature_class":"P",
    "gn:feature_code":"PPL",
    "gn:name":"Kampung Tok Golok",
    "gn:population":0,
    "gn:timezone":"Asia/Kuala_Lumpur",
    "iso:country":"MY",
    "name:msa_x_preferred":[
        "Kampung Tok Golok"
    ],
    "wof:name":"Kampung Tok Golok",
    "wof:placetype":"locality"
},
  "geometry": {"coordinates":[100.90344,5.72476],"type":"Point"}
}