{
  "type": "Feature",
  "properties": {
    "gn:admin1_code":"5",
    "gn:asciiname":"Kampung Batang Merbok",
    "gn:country_code":"MY",
    "gn:dem":24,
    "gn:feature_class":"P",
    "gn:feature_code":"PPL",
    "gn:name":"Kampung Batang Merbok",
    "gn:population":0,
    "gn:timezone":"Asia/Kuala_Lumpur",
    "iso:country":"MY",
    "name:msa_x_preferred":[
        "Kampung Batang Merbok"
    ],
    "name:und_x_variant":[
        "Kampong Batang Merbok",
        "Kampong Batang Merebok"
    ],
    "wof:name":"Kampung Batang Merbok",
    "wof:placetype":"locality"
},
  "geometry": {"coordinates":[102.1309,2.4785],"type":"Point"}
}