{
  "type": "Feature",
  "properties": {
    "gn:country":"MY",
    "iso:country":"MY",
    "qs:name":"Pantai Timor",
    "qs:name_adm0":"Malaysia",
    "qs:name_adm1":"Johor",
    "qs:photos":9,
    "qs:photos_1k":2,
    "qs:photos_9k":2,
    "qs:photos_9r":5,
    "qs:photos_all":342,
    "qs:photos_sr":1,
    "qs:placetype":"LocalAdmin",
    "qs:pop_sr":"0",
    "wof:name":"Pantai Timor",
    "wof:placetype":"localadmin"
},
  "geometry": {"coordinates":[104.241833,1.369727],"type":"Point"}
}