{
  "type": "Feature",
  "properties": {
    "gn:admin1_code":"4.0",
    "gn:asciiname":"Kampung Solok Musai",
    "gn:country_code":"MY",
    "gn:dem":7,
    "gn:feature_class":"P",
    "gn:feature_code":"PPL",
    "gn:name":"Kampung Solok Musai",
    "gn:population":0,
    "gn:timezone":"Asia/Kuala_Lumpur",
    "iso:country":"MY",
    "name:msa_x_preferred":[
        "Kampung Solok Musai"
    ],
    "wof:name":"Kampung Solok Musai",
    "wof:placetype":"locality"
},
  "geometry": {"coordinates":[102.26090000000001,2.2111],"type":"Point"}
}