{
  "type": "Feature",
  "properties": {
    "gn:admin1_code":"13",
    "gn:asciiname":"Kampung Cik Ibrahim",
    "gn:country_code":"MY",
    "gn:dem":33,
    "gn:feature_class":"P",
    "gn:feature_code":"PPL",
    "gn:name":"Kampung Cik Ibrahim",
    "gn:population":0,
    "gn:timezone":"Asia/Kuala_Lumpur",
    "iso:country":"MY",
    "name:msa_x_preferred":[
        "Kampung Cik Ibrahim"
    ],
    "name:und_x_variant":[
        "Kampong Che Ibrahim"
    ],
    "wof:name":"Kampung Cik Ibrahim",
    "wof:placetype":"locality"
},
  "geometry": {"coordinates":[103.11199999999999,5.0899],"type":"Point"}
}