{
  "type": "Feature",
  "properties": {
    "gn:country":"MY",
    "gn:fcode":"PPL",
    "gn:pop":0,
    "iso:country":"MY",
    "name:bar_x_preferred":[
        "Keladi"
    ],
    "name:cat_x_preferred":[
        "Keladi"
    ],
    "name:deu_x_preferred":[
        "Keladi"
    ],
    "name:ita_x_preferred":[
        "Keladi"
    ],
    "name:jpn_x_preferred":[
        "\u30b1\u30e9\u30c7\u30a3"
    ],
    "name:kan_x_preferred":[
        "\u0c95\u0cc6\u0cb3\u0ca6\u0cbf"
    ],
    "name:msa_x_preferred":[
        "Keladi"
    ],
    "name:spa_x_preferred":[
        "Keladi"
    ],
    "name:tam_x_preferred":[
        "\u0b95\u0bc7\u0bb3\u0b9f\u0bbf"
    ],
    "name:unk_x_variant":[
        "Kampong Keladi"
    ],
    "qs:name":"Keladi",
    "qs:name_adm0":"Malaysia",
    "qs:name_adm1":"Kedah",
    "qs:photos_9k":1,
    "qs:photos_9r":1,
    "qs:photos_all":1,
    "qs:photos_sr":0,
    "qs:placetype":"Town",
    "qs:pop_sr":"0",
    "wd:wordcount":599,
    "wof:name":"Keladi",
    "wof:placetype":"locality",
    "wof:population":0
},
  "geometry": {"coordinates":[100.5393,5.38432],"type":"Point"}
}