{
  "type": "Feature",
  "properties": {
    "gn:country":"MY",
    "gn:fcode":"PPL",
    "gn:pop":0,
    "iso:country":"MY",
    "name:msa_x_preferred":[
        "Keladi"
    ],
    "name:unk_x_variant":[
        "Kampong Keladi"
    ],
    "qs:name":"Keladi",
    "qs:name_adm0":"Malaysia",
    "qs:name_adm1":"Kedah",
    "qs:photos_9k":1,
    "qs:photos_9r":1,
    "qs:photos_all":1,
    "qs:photos_sr":0,
    "qs:placetype":"Town",
    "qs:pop_sr":"0",
    "wd:wordcount":599,
    "wof:name":"Keladi",
    "wof:placetype":"locality",
    "wof:population":0
},
  "geometry": {"coordinates":[100.5393,5.38432],"type":"Point"}
}