{
  "type": "Feature",
  "properties": {
    "gn:admin1_code":"4",
    "gn:asciiname":"Kampung Bukit Golot",
    "gn:country_code":"MY",
    "gn:dem":30,
    "gn:feature_class":"P",
    "gn:feature_code":"PPL",
    "gn:name":"Kampung Bukit Golot",
    "gn:population":0,
    "gn:timezone":"Asia/Kuala_Lumpur",
    "iso:country":"MY",
    "name:msa_x_preferred":[
        "Kampung Bukit Golot"
    ],
    "name:und_x_variant":[
        "Kampong Bukit Golot"
    ],
    "wof:name":"Kampung Bukit Golot",
    "wof:placetype":"locality"
},
  "geometry": {"coordinates":[102.50409999999999,2.3016],"type":"Point"}
}