{
  "type": "Feature",
  "properties": {
    "gn:admin1_code":"6",
    "gn:asciiname":"Kampung Bongkok",
    "gn:country_code":"MY",
    "gn:dem":50,
    "gn:feature_class":"P",
    "gn:feature_code":"PPL",
    "gn:name":"Kampung Bongkok",
    "gn:population":0,
    "gn:timezone":"Asia/Kuala_Lumpur",
    "iso:country":"MY",
    "name:msa_x_preferred":[
        "Kampung Bongkok"
    ],
    "name:und_x_variant":[
        "Kampong Bongkok"
    ],
    "wof:name":"Kampung Bongkok",
    "wof:placetype":"locality"
},
  "geometry": {"coordinates":[102.7753,3.5171],"type":"Point"}
}