{
  "type": "Feature",
  "properties": {
    "gn:admin1_code":"13",
    "gn:asciiname":"Kampong Tepus",
    "gn:cc2":"MY",
    "gn:country_code":"MY",
    "gn:dem":20,
    "gn:feature_class":"P",
    "gn:feature_code":"PPL",
    "gn:name":"Kampong Tepus",
    "gn:population":0,
    "gn:timezone":"Asia/Kuala_Lumpur",
    "iso:country":"MY",
    "name:und_x_variant":[
        "Kampong Tepas",
        "Kampong Tepus"
    ],
    "wof:name":"Kampong Tepus",
    "wof:placetype":"locality"
},
  "geometry": {"coordinates":[103.15000000000001,4.81667],"type":"Point"}
}