{
  "type": "Feature",
  "properties": {
    "gn:admin1_code":"6.0",
    "gn:asciiname":"Kampung Pulau Lanjut",
    "gn:country_code":"MY",
    "gn:dem":33,
    "gn:feature_class":"P",
    "gn:feature_code":"PPL",
    "gn:name":"Kampung Pulau Lanjut",
    "gn:population":0,
    "gn:timezone":"Asia/Kuala_Lumpur",
    "iso:country":"MY",
    "name:msa_x_preferred":[
        "Kampung Pulau Lanjut"
    ],
    "name:und_x_variant":[
        "Kampong Pulau Lanjot"
    ],
    "wof:name":"Kampung Pulau Lanjut",
    "wof:placetype":"locality"
},
  "geometry": {"coordinates":[103.1669,3.3788],"type":"Point"}
}