{
  "type": "Feature",
  "properties": {
    "gn:admin1_code":"11",
    "gn:asciiname":"Rumah Mamat",
    "gn:country_code":"MY",
    "gn:dem":22,
    "gn:feature_class":"P",
    "gn:feature_code":"PPL",
    "gn:name":"Rumah Mamat",
    "gn:population":0,
    "gn:timezone":"Asia/Kuching",
    "iso:country":"MY",
    "wof:name":"Rumah Mamat",
    "wof:placetype":"locality"
},
  "geometry": {"coordinates":[113.61667,3.55],"type":"Point"}
}