{
  "type": "Feature",
  "properties": {
    "gn:admin1_code":"16",
    "gn:asciiname":"Kampung Ranis Penilau",
    "gn:country_code":"MY",
    "gn:dem":838,
    "gn:feature_class":"P",
    "gn:feature_code":"PPL",
    "gn:name":"Kampung Ranis Penilau",
    "gn:population":0,
    "gn:timezone":"Asia/Kuching",
    "iso:country":"MY",
    "name:msa_x_preferred":[
        "Kampung Ranis Penilau"
    ],
    "name:und_x_variant":[
        "Kampong Ranis Penilau"
    ],
    "wof:name":"Kampung Ranis Penilau",
    "wof:placetype":"locality"
},
  "geometry": {"coordinates":[116.3411,5.9572],"type":"Point"}
}