{
  "type": "Feature",
  "properties": {
    "gn:admin1_code":"13.0",
    "gn:asciiname":"Kampung Bukit Mok Mek",
    "gn:country_code":"MY",
    "gn:dem":31,
    "gn:feature_class":"P",
    "gn:feature_code":"PPL",
    "gn:name":"Kampung Bukit Mok Mek",
    "gn:population":0,
    "gn:timezone":"Asia/Kuala_Lumpur",
    "iso:country":"MY",
    "name:msa_x_preferred":[
        "Kampung Bukit Mok Mek"
    ],
    "wof:name":"Kampung Bukit Mok Mek",
    "wof:placetype":"locality"
},
  "geometry": {"coordinates":[103.14230000000001,5.0015],"type":"Point"}
}