{
  "type": "Feature",
  "properties": {
    "gn:country":"MY",
    "gn:fcode":"PPL",
    "gn:pop":11879,
    "iso:country":"MY",
    "name:dut_x_preferred":[
        "Pulau Sebang"
    ],
    "name:eng_x_preferred":[
        "Pulau Sebang"
    ],
    "name:may_x_preferred":[
        "Pulau Sebang"
    ],
    "name:msa_x_preferred":[
        "Pulau Sebang"
    ],
    "name:spa_x_preferred":[
        "Pulau Sebang"
    ],
    "qs:name":"Pulau Sebang",
    "qs:name_adm0":"Malaysia",
    "qs:name_adm1":"Melaka",
    "qs:photos_9k":1,
    "qs:photos_9r":1,
    "qs:photos_all":1,
    "qs:photos_sr":0,
    "qs:placetype":"Town",
    "qs:pop_sr":"6",
    "wd:wordcount":78,
    "wof:name":"Pulau Sebang",
    "wof:placetype":"locality",
    "wof:population":11879
},
  "geometry": {"coordinates":[102.2329,2.455],"type":"Point"}
}