{
  "type": "Feature",
  "properties": {
    "gn:admin1_code":"12",
    "gn:asciiname":"Kampung Teluk Pulai",
    "gn:country_code":"MY",
    "gn:dem":4,
    "gn:feature_class":"P",
    "gn:feature_code":"PPL",
    "gn:name":"Kampung Teluk Pulai",
    "gn:population":0,
    "gn:timezone":"Asia/Kuala_Lumpur",
    "iso:country":"MY",
    "wof:name":"Kampung Teluk Pulai",
    "wof:placetype":"locality"
},
  "geometry": {"coordinates":[101.43333,3.05],"type":"Point"}
}