{
  "type": "Feature",
  "properties": {
    "gn:admin1_code":"11",
    "gn:asciiname":"Rumah Narok",
    "gn:country_code":"MY",
    "gn:dem":85,
    "gn:feature_class":"P",
    "gn:feature_code":"PPL",
    "gn:name":"Rumah Narok",
    "gn:population":0,
    "gn:timezone":"Asia/Kuching",
    "iso:country":"MY",
    "wof:name":"Rumah Narok",
    "wof:placetype":"locality"
},
  "geometry": {"coordinates":[113.28333000000001,2.11667],"type":"Point"}
}