{
  "type": "Feature",
  "properties": {
    "gn:admin1_code":"13.0",
    "gn:asciiname":"Kampung Cina",
    "gn:country_code":"MY",
    "gn:dem":46,
    "gn:feature_class":"P",
    "gn:feature_code":"PPL",
    "gn:name":"Kampung Cina",
    "gn:population":0,
    "gn:timezone":"Asia/Kuala_Lumpur",
    "iso:country":"MY",
    "name:msa_x_preferred":[
        "Kampung Cina"
    ],
    "wof:name":"Kampung Cina",
    "wof:placetype":"locality"
},
  "geometry": {"coordinates":[103.306,3.9322],"type":"Point"}
}