{
  "type": "Feature",
  "properties": {
    "gn:admin1_code":"11",
    "gn:asciiname":"Rumah Sigau",
    "gn:country_code":"MY",
    "gn:dem":87,
    "gn:feature_class":"P",
    "gn:feature_code":"PPL",
    "gn:name":"Rumah Sigau",
    "gn:population":0,
    "gn:timezone":"Asia/Kuching",
    "iso:country":"MY",
    "wof:name":"Rumah Sigau",
    "wof:placetype":"locality"
},
  "geometry": {"coordinates":[113.31667,1.95],"type":"Point"}
}