{
  "type": "Feature",
  "properties": {
    "gn:admin1_code":"16.0",
    "gn:asciiname":"Kampung Merungin",
    "gn:country_code":"MY",
    "gn:dem":145,
    "gn:feature_class":"P",
    "gn:feature_code":"PPL",
    "gn:name":"Kampung Merungin",
    "gn:population":0,
    "gn:timezone":"Asia/Kuching",
    "iso:country":"MY",
    "name:msa_x_preferred":[
        "Kampung Merungin"
    ],
    "name:und_x_variant":[
        "Merungin",
        "Kampong Merungin"
    ],
    "wof:name":"Kampung Merungin",
    "wof:placetype":"locality"
},
  "geometry": {"coordinates":[116.8767,6.1279],"type":"Point"}
}