{
  "type": "Feature",
  "properties": {
    "gn:admin1_code":"2",
    "gn:asciiname":"Kampung Sungai Daun Tengah",
    "gn:country_code":"MY",
    "gn:dem":5,
    "gn:feature_class":"P",
    "gn:feature_code":"PPL",
    "gn:name":"Kampung Sungai Daun Tengah",
    "gn:population":0,
    "gn:timezone":"Asia/Kuala_Lumpur",
    "iso:country":"MY",
    "name:und_x_variant":[
        "Kampong Sungai Daun Tengah",
        "Kampung Sungai Daun Tengah"
    ],
    "wof:name":"Kampung Sungai Daun Tengah",
    "wof:placetype":"locality"
},
  "geometry": {"coordinates":[100.38278,5.92391],"type":"Point"}
}