{
  "type": "Feature",
  "properties": {
    "gn:admin1_code":"16.0",
    "gn:asciiname":"Kampung Komin",
    "gn:country_code":"MY",
    "gn:dem":12,
    "gn:feature_class":"P",
    "gn:feature_code":"PPL",
    "gn:name":"Kampung Komin",
    "gn:population":0,
    "gn:timezone":"Asia/Kuching",
    "iso:country":"MY",
    "name:msa_x_preferred":[
        "Kampung Komin"
    ],
    "wof:name":"Kampung Komin",
    "wof:placetype":"locality"
},
  "geometry": {"coordinates":[117.06740000000001,6.699],"type":"Point"}
}