{
  "type": "Feature",
  "properties": {
    "gn:country":"MY",
    "iso:country":"MY",
    "name:eng_x_preferred":[
        "Teluk Batik"
    ],
    "name:msa_x_preferred":[
        "Teluk Batik"
    ],
    "name:nld_x_preferred":[
        "Teluk Batik"
    ],
    "name:zho_x_preferred":[
        "\u76f4\u843d\u5cc7\u8fea"
    ],
    "qs:name":"Teluk Batik",
    "qs:name_adm0":"Malaysia",
    "qs:name_adm1":"Perak",
    "qs:photos":262,
    "qs:photos_1k":53,
    "qs:photos_9k":1,
    "qs:photos_9r":4,
    "qs:photos_all":262,
    "qs:photos_sr":5,
    "qs:placetype":"Town",
    "qs:pop_sr":"0",
    "wd:wordcount":37,
    "wof:name":"Teluk Batik",
    "wof:placetype":"locality"
},
  "geometry": {"coordinates":[100.60884,4.18892],"type":"Point"}
}