{
  "type": "Feature",
  "properties": {
    "gn:admin1_code":"2",
    "gn:asciiname":"Kampong Kuala Janing",
    "gn:country_code":"MY",
    "gn:dem":33,
    "gn:feature_class":"P",
    "gn:feature_code":"PPL",
    "gn:name":"Kampong Kuala Janing",
    "gn:population":0,
    "gn:timezone":"Asia/Kuala_Lumpur",
    "iso:country":"MY",
    "wof:name":"Kampong Kuala Janing",
    "wof:placetype":"locality"
},
  "geometry": {"coordinates":[100.59766999999999,6.27983],"type":"Point"}
}