{
  "type": "Feature",
  "properties": {
    "gn:admin1_code":"6",
    "gn:asciiname":"Kampung Asah",
    "gn:country_code":"MY",
    "gn:dem":4,
    "gn:feature_class":"P",
    "gn:feature_code":"PPL",
    "gn:name":"Kampung Asah",
    "gn:population":0,
    "gn:timezone":"Asia/Kuala_Lumpur",
    "iso:country":"MY",
    "name:msa_x_preferred":[
        "Kampung Asah"
    ],
    "name:und_x_variant":[
        "Kampong Asah"
    ],
    "wof:name":"Kampung Asah",
    "wof:placetype":"locality"
},
  "geometry": {"coordinates":[104.19329999999999,2.7209],"type":"Point"}
}