{
  "type": "Feature",
  "properties": {
    "iso:country":"MY",
    "qs:name":"Kampung Baru Ayer Keroh",
    "qs:name_adm0":"Malaysia",
    "qs:name_adm1":"Melaka",
    "qs:photos":127,
    "qs:photos_1k":26,
    "qs:photos_9k":1,
    "qs:photos_9r":3,
    "qs:photos_all":127,
    "qs:photos_sr":3,
    "qs:placetype":"Suburb",
    "qs:pop_sr":"0",
    "wd:wordcount":816,
    "wof:name":"Kampung Baru Ayer Keroh",
    "wof:placetype":"neighbourhood"
},
  "geometry": {"coordinates":[102.2801,2.2654],"type":"Point"}
}