{
  "type": "Feature",
  "properties": {
    "gn:admin1_code":"6",
    "gn:asciiname":"Kampung Murai",
    "gn:country_code":"MY",
    "gn:dem":109,
    "gn:feature_class":"P",
    "gn:feature_code":"PPL",
    "gn:name":"Kampung Murai",
    "gn:population":0,
    "gn:timezone":"Asia/Kuala_Lumpur",
    "iso:country":"MY",
    "name:msa_x_preferred":[
        "Kampung Murai"
    ],
    "name:und_x_variant":[
        "Kampong Murai"
    ],
    "wof:name":"Kampung Murai",
    "wof:placetype":"locality"
},
  "geometry": {"coordinates":[102.58159999999999,4.5203],"type":"Point"}
}