{
  "type": "Feature",
  "properties": {
    "gn:admin1_code":"16.0",
    "gn:asciiname":"Lingkungan",
    "gn:country_code":"MY",
    "gn:dem":672,
    "gn:feature_class":"P",
    "gn:feature_code":"PPL",
    "gn:name":"Lingkungan",
    "gn:population":0,
    "gn:timezone":"Asia/Kuching",
    "iso:country":"MY",
    "wof:name":"Lingkungan",
    "wof:placetype":"locality"
},
  "geometry": {"coordinates":[116.08333,4.58333],"type":"Point"}
}