{
  "type": "Feature",
  "properties": {
    "gn:admin1_code":"6.0",
    "gn:asciiname":"Kampung Batu Temelian",
    "gn:country_code":"MY",
    "gn:dem":39,
    "gn:feature_class":"P",
    "gn:feature_code":"PPL",
    "gn:name":"Kampung Batu Temelian",
    "gn:population":0,
    "gn:timezone":"Asia/Kuala_Lumpur",
    "iso:country":"MY",
    "name:msa_x_preferred":[
        "Kampung Batu Temelian"
    ],
    "wof:name":"Kampung Batu Temelian",
    "wof:placetype":"locality"
},
  "geometry": {"coordinates":[102.4928,3.3454],"type":"Point"}
}