{
  "type": "Feature",
  "properties": {
    "gn:admin1_code":"12",
    "gn:asciiname":"Kampung Ampar Tenang",
    "gn:country_code":"MY",
    "gn:dem":18,
    "gn:feature_class":"P",
    "gn:feature_code":"PPL",
    "gn:name":"Kampung Ampar Tenang",
    "gn:population":0,
    "gn:timezone":"Asia/Kuala_Lumpur",
    "iso:country":"MY",
    "name:msa_x_preferred":[
        "Kampung Ampar Tenang"
    ],
    "name:und_x_variant":[
        "Kampong Ampar Tenang"
    ],
    "wof:name":"Kampung Ampar Tenang",
    "wof:placetype":"locality"
},
  "geometry": {"coordinates":[101.6955,2.8681],"type":"Point"}
}