{
  "type": "Feature",
  "properties": {
    "gn:admin1_code":"6.0",
    "gn:asciiname":"Kampung Menteling",
    "gn:country_code":"MY",
    "gn:dem":13,
    "gn:feature_class":"P",
    "gn:feature_code":"PPL",
    "gn:name":"Kampung Menteling",
    "gn:population":0,
    "gn:timezone":"Asia/Kuala_Lumpur",
    "iso:country":"MY",
    "name:msa_x_preferred":[
        "Kampung Menteling"
    ],
    "name:und_x_variant":[
        "Mentelung"
    ],
    "wof:name":"Kampung Menteling",
    "wof:placetype":"locality"
},
  "geometry": {"coordinates":[103.58322,2.52437],"type":"Point"}
}