{
  "type": "Feature",
  "properties": {
    "gn:admin1_code":"7.0",
    "gn:asciiname":"Kampung Orang Asli Ulu Suluh",
    "gn:country_code":"MY",
    "gn:dem":224,
    "gn:feature_class":"P",
    "gn:feature_code":"PPL",
    "gn:name":"Kampung Orang Asli Ulu Suluh",
    "gn:population":0,
    "gn:timezone":"Asia/Kuala_Lumpur",
    "iso:country":"MY",
    "name:msa_x_preferred":[
        "Kampung Orang Asli Ulu Suluh"
    ],
    "wof:name":"Kampung Orang Asli Ulu Suluh",
    "wof:placetype":"locality"
},
  "geometry": {"coordinates":[101.2101,4.6738],"type":"Point"}
}