{
  "type": "Feature",
  "properties": {
    "gn:admin1_code":"16",
    "gn:asciiname":"Kampung Tambuluran",
    "gn:country_code":"MY",
    "gn:dem":15,
    "gn:feature_class":"P",
    "gn:feature_code":"PPL",
    "gn:name":"Kampung Tambuluran",
    "gn:population":0,
    "gn:timezone":"Asia/Kuching",
    "iso:country":"MY",
    "name:msa_x_preferred":[
        "Kampung Tambuluran"
    ],
    "name:und_x_variant":[
        "Tambuluran"
    ],
    "wof:name":"Kampung Tambuluran",
    "wof:placetype":"locality"
},
  "geometry": {"coordinates":[116.7064,6.7992],"type":"Point"}
}