{
  "type": "Feature",
  "properties": {
    "gn:admin1_code":"11",
    "gn:asciiname":"Kampong Bai",
    "gn:cc2":"MY",
    "gn:country_code":"MY",
    "gn:dem":10,
    "gn:feature_class":"P",
    "gn:feature_code":"PPL",
    "gn:name":"Kampong Bai",
    "gn:population":0,
    "gn:timezone":"Asia/Kuching",
    "iso:country":"MY",
    "name:und_x_variant":[
        "Kampong Bai-i",
        "Kampong Bai"
    ],
    "wof:name":"Kampong Bai",
    "wof:placetype":"locality"
},
  "geometry": {"coordinates":[110.48333,1.55],"type":"Point"}
}