{
  "type": "Feature",
  "properties": {
    "gn:admin1_code":"11",
    "gn:asciiname":"Kampong Masjid",
    "gn:cc2":"MY",
    "gn:country_code":"MY",
    "gn:dem":12,
    "gn:feature_class":"P",
    "gn:feature_code":"PPL",
    "gn:name":"Kampong Masjid",
    "gn:population":0,
    "gn:timezone":"Asia/Kuching",
    "iso:country":"MY",
    "name:und_x_variant":[
        "Kampong Mesjid",
        "Kampong Masjid"
    ],
    "wof:name":"Kampong Masjid",
    "wof:placetype":"locality"
},
  "geometry": {"coordinates":[111.43333,2.53333],"type":"Point"}
}