{
  "type": "Feature",
  "properties": {
    "gn:admin1_code":"7.0",
    "gn:asciiname":"Kampung Belangkor",
    "gn:country_code":"MY",
    "gn:dem":26,
    "gn:feature_class":"P",
    "gn:feature_code":"PPL",
    "gn:name":"Kampung Belangkor",
    "gn:population":0,
    "gn:timezone":"Asia/Kuala_Lumpur",
    "iso:country":"MY",
    "name:msa_x_preferred":[
        "Kampung Belangkor"
    ],
    "name:msa_x_variant":[
        "Kampung Belengkor"
    ],
    "wof:name":"Kampung Belangkor",
    "wof:placetype":"locality"
},
  "geometry": {"coordinates":[101.04600000000001,4.464],"type":"Point"}
}