{
  "type": "Feature",
  "properties": {
    "gn:admin1_code":"6",
    "gn:asciiname":"Kampung Terubin",
    "gn:country_code":"MY",
    "gn:dem":31,
    "gn:feature_class":"P",
    "gn:feature_code":"PPL",
    "gn:name":"Kampung Terubin",
    "gn:population":0,
    "gn:timezone":"Asia/Kuala_Lumpur",
    "iso:country":"MY",
    "name:msa_x_preferred":[
        "Kampung Terubin"
    ],
    "name:und_x_variant":[
        "Kampong Terubin"
    ],
    "wof:name":"Kampung Terubin",
    "wof:placetype":"locality"
},
  "geometry": {"coordinates":[103.17140000000001,3.1878],"type":"Point"}
}