{
  "type": "Feature",
  "properties": {
    "gn:admin1_code":"16.0",
    "gn:asciiname":"Kampung Masuyu",
    "gn:country_code":"MY",
    "gn:dem":719,
    "gn:feature_class":"P",
    "gn:feature_code":"PPL",
    "gn:name":"Kampung Masuyu",
    "gn:population":0,
    "gn:timezone":"Asia/Kuching",
    "iso:country":"MY",
    "name:msa_x_preferred":[
        "Kampung Masuyu"
    ],
    "wof:name":"Kampung Masuyu",
    "wof:placetype":"locality"
},
  "geometry": {"coordinates":[117.00060000000001,6.3478],"type":"Point"}
}