{
  "type": "Feature",
  "properties": {
    "gn:admin1_code":"16.0",
    "gn:asciiname":"Kampung Mandalipau",
    "gn:country_code":"MY",
    "gn:dem":48,
    "gn:feature_class":"P",
    "gn:feature_code":"PPL",
    "gn:name":"Kampung Mandalipau",
    "gn:population":0,
    "gn:timezone":"Asia/Kuching",
    "iso:country":"MY",
    "name:msa_x_preferred":[
        "Kampung Mandalipau"
    ],
    "name:und_x_variant":[
        "Mondolipo",
        "Mandalipau"
    ],
    "wof:name":"Kampung Mandalipau",
    "wof:placetype":"locality"
},
  "geometry": {"coordinates":[116.0693,5.7294],"type":"Point"}
}