{
  "type": "Feature",
  "properties": {
    "gn:admin1_code":"7",
    "gn:asciiname":"Kampung Suak Punggor",
    "gn:country_code":"MY",
    "gn:dem":68,
    "gn:feature_class":"P",
    "gn:feature_code":"PPL",
    "gn:name":"Kampung Suak Punggor",
    "gn:population":0,
    "gn:timezone":"Asia/Kuala_Lumpur",
    "iso:country":"MY",
    "name:msa_x_preferred":[
        "Kampung Suak Punggor"
    ],
    "name:und_x_variant":[
        "Kampong Tok Punggoh"
    ],
    "wof:name":"Kampung Suak Punggor",
    "wof:placetype":"locality"
},
  "geometry": {"coordinates":[100.9954,4.8703],"type":"Point"}
}