{
  "type": "Feature",
  "properties": {
    "gn:admin1_code":"16",
    "gn:asciiname":"Kampong Pinasang",
    "gn:cc2":"MY",
    "gn:country_code":"MY",
    "gn:dem":346,
    "gn:feature_class":"P",
    "gn:feature_code":"PPL",
    "gn:name":"Kampong Pinasang",
    "gn:population":0,
    "gn:timezone":"Asia/Kuching",
    "iso:country":"MY",
    "name:und_x_variant":[
        "Pinasang",
        "Kampong Pinasang"
    ],
    "wof:name":"Kampong Pinasang",
    "wof:placetype":"locality"
},
  "geometry": {"coordinates":[116.40000000000001,6.26667],"type":"Point"}
}