{
  "type": "Feature",
  "properties": {
    "gn:admin1_code":"3.0",
    "gn:asciiname":"Kampung Lalang",
    "gn:country_code":"MY",
    "gn:dem":183,
    "gn:feature_class":"P",
    "gn:feature_code":"PPL",
    "gn:name":"Kampung Lalang",
    "gn:population":0,
    "gn:timezone":"Asia/Kuala_Lumpur",
    "iso:country":"MY",
    "name:msa_x_preferred":[
        "Kampung Lalang"
    ],
    "wof:name":"Kampung Lalang",
    "wof:placetype":"locality"
},
  "geometry": {"coordinates":[101.8224,4.9066],"type":"Point"}
}