{
  "type": "Feature",
  "properties": {
    "gn:admin1_code":"5",
    "gn:asciiname":"Kampung Landas",
    "gn:country_code":"MY",
    "gn:dem":38,
    "gn:feature_class":"P",
    "gn:feature_code":"PPL",
    "gn:name":"Kampung Landas",
    "gn:population":0,
    "gn:timezone":"Asia/Kuala_Lumpur",
    "iso:country":"MY",
    "name:msa_x_preferred":[
        "Kampung Landas"
    ],
    "name:und_x_variant":[
        "Kampong Landas"
    ],
    "wof:name":"Kampung Landas",
    "wof:placetype":"locality"
},
  "geometry": {"coordinates":[101.96939999999999,2.6094],"type":"Point"}
}