{
  "type": "Feature",
  "properties": {
    "gn:admin1_code":"11",
    "gn:asciiname":"Kampong Sinkarei",
    "gn:cc2":"MY",
    "gn:country_code":"MY",
    "gn:dem":6,
    "gn:feature_class":"P",
    "gn:feature_code":"PPL",
    "gn:name":"Kampong Sinkarei",
    "gn:population":0,
    "gn:timezone":"Asia/Kuching",
    "iso:country":"MY",
    "name:und_x_variant":[
        "Kampong Sinkaray",
        "Kampong Sinkarei"
    ],
    "wof:name":"Kampong Sinkarei",
    "wof:placetype":"locality"
},
  "geometry": {"coordinates":[114.96666999999999,4.76667],"type":"Point"}
}