{
  "type": "Feature",
  "properties": {
    "gn:admin1_code":"1.0",
    "gn:asciiname":"Taman Bon Bon",
    "gn:country_code":"MY",
    "gn:dem":26,
    "gn:feature_class":"P",
    "gn:feature_code":"PPL",
    "gn:name":"Taman Bon Bon",
    "gn:population":0,
    "gn:timezone":"Asia/Kuala_Lumpur",
    "iso:country":"MY",
    "name:msa_x_preferred":[
        "Taman Bon Bon"
    ],
    "wof:name":"Taman Bon Bon",
    "wof:placetype":"locality"
},
  "geometry": {"coordinates":[102.7668,2.5492],"type":"Point"}
}