{
  "type": "Feature",
  "properties": {
    "gn:admin1_code":"6",
    "gn:asciiname":"Kampung Gancung Hulu",
    "gn:country_code":"MY",
    "gn:dem":16,
    "gn:feature_class":"P",
    "gn:feature_code":"PPL",
    "gn:name":"Kampung Gancung Hulu",
    "gn:population":0,
    "gn:timezone":"Asia/Kuala_Lumpur",
    "iso:country":"MY",
    "name:msa_x_preferred":[
        "Kampung Gancung Hulu"
    ],
    "name:und_x_variant":[
        "Kampong Ganchong Hulu",
        "Kampong Ganchong Ulu"
    ],
    "wof:name":"Kampung Gancung Hulu",
    "wof:placetype":"locality"
},
  "geometry": {"coordinates":[103.283,3.5477],"type":"Point"}
}