{
  "type": "Feature",
  "properties": {
    "gn:admin1_code":"6.0",
    "gn:asciiname":"Teman Seroja",
    "gn:country_code":"MY",
    "gn:dem":194,
    "gn:feature_class":"P",
    "gn:feature_code":"PPL",
    "gn:name":"Teman Seroja",
    "gn:population":0,
    "gn:timezone":"Asia/Kuala_Lumpur",
    "iso:country":"MY",
    "name:msa_x_preferred":[
        "Teman Seroja"
    ],
    "wof:name":"Teman Seroja",
    "wof:placetype":"locality"
},
  "geometry": {"coordinates":[101.809,3.7376],"type":"Point"}
}