{
  "type": "Feature",
  "properties": {
    "gn:admin1_code":"5.0",
    "gn:asciiname":"Kampung Pondoi",
    "gn:country_code":"MY",
    "gn:dem":71,
    "gn:feature_class":"P",
    "gn:feature_code":"PPL",
    "gn:name":"Kampung Pondoi",
    "gn:population":0,
    "gn:timezone":"Asia/Kuala_Lumpur",
    "iso:country":"MY",
    "name:msa_x_preferred":[
        "Kampung Pondoi"
    ],
    "name:und_x_variant":[
        "Pondoi",
        "Kampung Pondoi"
    ],
    "wof:name":"Kampung Pondoi",
    "wof:placetype":"locality"
},
  "geometry": {"coordinates":[102.3289,2.4846],"type":"Point"}
}