{
  "type": "Feature",
  "properties": {
    "gn:admin1_code":"16.0",
    "gn:asciiname":"Kampung Kuala Binuou",
    "gn:country_code":"MY",
    "gn:dem":361,
    "gn:feature_class":"P",
    "gn:feature_code":"PPL",
    "gn:name":"Kampung Kuala Binuou",
    "gn:population":0,
    "gn:timezone":"Asia/Kuching",
    "iso:country":"MY",
    "name:msa_x_preferred":[
        "Kampung Kuala Binuou"
    ],
    "wof:name":"Kampung Kuala Binuou",
    "wof:placetype":"locality"
},
  "geometry": {"coordinates":[116.3222,5.1484],"type":"Point"}
}