{
  "type": "Feature",
  "properties": {
    "gn:admin1_code":"16.0",
    "gn:asciiname":"Sampugan",
    "gn:country_code":"MY",
    "gn:dem":257,
    "gn:feature_class":"P",
    "gn:feature_code":"PPL",
    "gn:name":"Sampugan",
    "gn:population":0,
    "gn:timezone":"Asia/Kuching",
    "iso:country":"MY",
    "wof:name":"Sampugan",
    "wof:placetype":"locality"
},
  "geometry": {"coordinates":[116.25,4.51667],"type":"Point"}
}