{
  "type": "Feature",
  "properties": {
    "gn:admin1_code":"1.0",
    "gn:asciiname":"Kampung Baru Seluyut",
    "gn:country_code":"MY",
    "gn:dem":28,
    "gn:feature_class":"P",
    "gn:feature_code":"PPL",
    "gn:name":"Kampung Baru Seluyut",
    "gn:population":0,
    "gn:timezone":"Asia/Kuala_Lumpur",
    "iso:country":"MY",
    "name:msa_x_preferred":[
        "Kampung Baru Seluyut"
    ],
    "wof:name":"Kampung Baru Seluyut",
    "wof:placetype":"locality"
},
  "geometry": {"coordinates":[103.9756,1.7061],"type":"Point"}
}