{
  "type": "Feature",
  "properties": {
    "gn:admin1_code":"1",
    "gn:asciiname":"Kampung Tungku Tiga",
    "gn:country_code":"MY",
    "gn:dem":25,
    "gn:feature_class":"P",
    "gn:feature_code":"PPL",
    "gn:name":"Kampung Tungku Tiga",
    "gn:population":0,
    "gn:timezone":"Asia/Kuala_Lumpur",
    "iso:country":"MY",
    "name:msa_x_preferred":[
        "Kampung Tungku Tiga"
    ],
    "name:und_x_variant":[
        "Kampong Tungku Tiga"
    ],
    "wof:name":"Kampung Tungku Tiga",
    "wof:placetype":"locality"
},
  "geometry": {"coordinates":[102.8811,2.5499],"type":"Point"}
}