{
  "type": "Feature",
  "properties": {
    "iso:country":"MY",
    "qs:name":"Kamunting",
    "qs:name_adm0":"Malaysia",
    "qs:name_adm1":"Perak",
    "qs:photos":3,
    "qs:photos_1k":1,
    "qs:photos_9k":1,
    "qs:photos_9r":2,
    "qs:photos_all":60,
    "qs:photos_sr":1,
    "qs:placetype":"LocalAdmin",
    "qs:pop_sr":"0",
    "wd:wordcount":1087,
    "wof:name":"Kamunting",
    "wof:placetype":"localadmin"
},
  "geometry": {"coordinates":[100.741297,4.882395],"type":"Point"}
}