{
  "type": "Feature",
  "properties": {
    "iso:country":"MY",
    "name:eng_x_preferred":[
        "Kamunting"
    ],
    "name:jpn_x_preferred":[
        "\u30ab\u30e0\u30f3\u30c6\u30a3\u30f3"
    ],
    "name:msa_x_preferred":[
        "Kamunting"
    ],
    "name:nld_x_preferred":[
        "Kamunting"
    ],
    "name:tam_x_preferred":[
        "\u0b95\u0bae\u0bc1\u0ba8\u0bcd\u0ba4\u0bbf\u0b99\u0bcd"
    ],
    "name:zho_x_preferred":[
        "\u7518\u6587\u4e01"
    ],
    "qs:name":"Kamunting",
    "qs:name_adm0":"Malaysia",
    "qs:name_adm1":"Perak",
    "qs:photos":3,
    "qs:photos_1k":1,
    "qs:photos_9k":1,
    "qs:photos_9r":2,
    "qs:photos_all":60,
    "qs:photos_sr":1,
    "qs:placetype":"LocalAdmin",
    "qs:pop_sr":"0",
    "wd:wordcount":1087,
    "wof:name":"Kamunting",
    "wof:placetype":"localadmin"
},
  "geometry": {"coordinates":[100.741297,4.882395],"type":"Point"}
}