{
  "type": "Feature",
  "properties": {
    "gn:admin1_code":"16.0",
    "gn:asciiname":"Tiger",
    "gn:country_code":"MY",
    "gn:dem":94,
    "gn:elevation":"0.0",
    "gn:feature_class":"P",
    "gn:feature_code":"PPL",
    "gn:name":"Tiger",
    "gn:population":0,
    "gn:timezone":"Asia/Kuching",
    "iso:country":"MY",
    "wof:name":"Tiger",
    "wof:placetype":"locality"
},
  "geometry": {"coordinates":[117.8188,4.4094],"type":"Point"}
}