{
  "type": "Feature",
  "properties": {
    "gn:admin1_code":"0.0",
    "gn:asciiname":"Kampung Sunjai Gapoi",
    "gn:country_code":"MY",
    "gn:dem":115,
    "gn:feature_class":"P",
    "gn:feature_code":"PPL",
    "gn:name":"Kampung Sunjai Gapoi",
    "gn:population":0,
    "gn:timezone":"Asia/Kuala_Lumpur",
    "iso:country":"MY",
    "name:msa_x_preferred":[
        "Kampung Sunjai Gapoi"
    ],
    "wof:name":"Kampung Sunjai Gapoi",
    "wof:placetype":"locality"
},
  "geometry": {"coordinates":[102.105,3.2716],"type":"Point"}
}