{
  "type": "Feature",
  "properties": {
    "gn:admin1_code":"2",
    "gn:asciiname":"Kampung Bukit Kechik",
    "gn:cc2":"MY",
    "gn:country_code":"MY",
    "gn:dem":11,
    "gn:feature_class":"P",
    "gn:feature_code":"PPL",
    "gn:name":"Kampung Bukit Kechik",
    "gn:population":0,
    "gn:timezone":"Asia/Kuala_Lumpur",
    "iso:country":"MY",
    "name:msa_x_preferred":[
        "Kampung Bukit Kechik"
    ],
    "name:und_x_variant":[
        "Kampong Bukit Kechik"
    ],
    "wof:name":"Kampung Bukit Kechik",
    "wof:placetype":"locality"
},
  "geometry": {"coordinates":[100.36024999999999,5.63394],"type":"Point"}
}