{
  "type": "Feature",
  "properties": {
    "gn:admin1_code":"7",
    "gn:asciiname":"Kampung Batang Poyan",
    "gn:country_code":"MY",
    "gn:dem":6,
    "gn:feature_class":"P",
    "gn:feature_code":"PPL",
    "gn:name":"Kampung Batang Poyan",
    "gn:population":0,
    "gn:timezone":"Asia/Kuala_Lumpur",
    "iso:country":"MY",
    "name:msa_x_preferred":[
        "Kampung Batang Poyan"
    ],
    "name:und_x_variant":[
        "Kampong Batung Poyan",
        "Kampong Batang Poyan"
    ],
    "wof:name":"Kampung Batang Poyan",
    "wof:placetype":"locality"
},
  "geometry": {"coordinates":[101.1133,3.9766],"type":"Point"}
}