{
  "type": "Feature",
  "properties": {
    "gn:admin1_code":"6.0",
    "gn:asciiname":"Kampung Renggul",
    "gn:country_code":"MY",
    "gn:dem":113,
    "gn:feature_class":"P",
    "gn:feature_code":"PPL",
    "gn:name":"Kampung Renggul",
    "gn:population":0,
    "gn:timezone":"Asia/Kuala_Lumpur",
    "iso:country":"MY",
    "name:msa_x_preferred":[
        "Kampung Renggul"
    ],
    "wof:name":"Kampung Renggul",
    "wof:placetype":"locality"
},
  "geometry": {"coordinates":[101.8998,4.0034],"type":"Point"}
}