{
  "type": "Feature",
  "properties": {
    "gn:admin1_code":"2.0",
    "gn:asciiname":"Kampung Kastam",
    "gn:country_code":"MY",
    "gn:dem":14,
    "gn:feature_class":"P",
    "gn:feature_code":"PPL",
    "gn:name":"Kampung Kastam",
    "gn:population":0,
    "gn:timezone":"Asia/Kuala_Lumpur",
    "iso:country":"MY",
    "wof:name":"Kampung Kastam",
    "wof:placetype":"locality"
},
  "geometry": {"coordinates":[99.81577,6.33614],"type":"Point"}
}