{
  "type": "Feature",
  "properties": {
    "gn:admin1_code":"13",
    "gn:asciiname":"Kampung Che Selamah",
    "gn:cc2":"MY",
    "gn:country_code":"MY",
    "gn:dem":13,
    "gn:feature_class":"P",
    "gn:feature_code":"PPL",
    "gn:name":"Kampung Che Selamah",
    "gn:population":0,
    "gn:timezone":"Asia/Kuala_Lumpur",
    "iso:country":"MY",
    "name:msa_x_preferred":[
        "Kampung Che Selamah"
    ],
    "name:und_x_variant":[
        "Kampong Che Selamah"
    ],
    "wof:name":"Kampung Che Selamah",
    "wof:placetype":"locality"
},
  "geometry": {"coordinates":[102.7831,5.59117],"type":"Point"}
}