{
  "type": "Feature",
  "properties": {
    "gn:admin1_code":"16",
    "gn:asciiname":"Kampung Pinatau",
    "gn:country_code":"MY",
    "gn:dem":50,
    "gn:feature_class":"P",
    "gn:feature_code":"PPL",
    "gn:name":"Kampung Pinatau",
    "gn:population":0,
    "gn:timezone":"Asia/Kuching",
    "iso:country":"MY",
    "name:msa_x_preferred":[
        "Kampung Pinatau"
    ],
    "name:und_x_variant":[
        "Kampong Pinatan"
    ],
    "wof:name":"Kampung Pinatau",
    "wof:placetype":"locality"
},
  "geometry": {"coordinates":[116.68770000000001,6.4955],"type":"Point"}
}