{
  "type": "Feature",
  "properties": {
    "gn:admin1_code":"5.0",
    "gn:asciiname":"Kampung Baharu Semin",
    "gn:country_code":"MY",
    "gn:dem":32,
    "gn:feature_class":"P",
    "gn:feature_code":"PPL",
    "gn:name":"Kampung Baharu Semin",
    "gn:population":0,
    "gn:timezone":"Asia/Kuala_Lumpur",
    "iso:country":"MY",
    "name:msa_x_preferred":[
        "Kampung Baharu Semin"
    ],
    "wof:name":"Kampung Baharu Semin",
    "wof:placetype":"locality"
},
  "geometry": {"coordinates":[102.07689999999999,2.4859],"type":"Point"}
}