{
  "type": "Feature",
  "properties": {
    "gn:admin1_code":"11",
    "gn:asciiname":"Tanjong",
    "gn:country_code":"MY",
    "gn:dem":15,
    "gn:feature_class":"P",
    "gn:feature_code":"PPL",
    "gn:name":"Tanjong",
    "gn:population":0,
    "gn:timezone":"Asia/Kuching",
    "iso:country":"MY",
    "name:msa_x_preferred":[
        "Tanjong"
    ],
    "wof:name":"Tanjong",
    "wof:placetype":"locality"
},
  "geometry": {"coordinates":[111.51667,1.53333],"type":"Point"}
}