{
  "type": "Feature",
  "properties": {
    "gn:admin1_code":"6",
    "gn:asciiname":"Kampung Gelang",
    "gn:country_code":"MY",
    "gn:dem":13,
    "gn:feature_class":"P",
    "gn:feature_code":"PPL",
    "gn:name":"Kampung Gelang",
    "gn:population":0,
    "gn:timezone":"Asia/Kuala_Lumpur",
    "iso:country":"MY",
    "name:msa_x_preferred":[
        "Kampung Gelang"
    ],
    "name:und_x_variant":[
        "Kampong Gelang"
    ],
    "wof:name":"Kampung Gelang",
    "wof:placetype":"locality"
},
  "geometry": {"coordinates":[103.3921,3.4828],"type":"Point"}
}