{
  "type": "Feature",
  "properties": {
    "iso:country":"MY",
    "qs:name":"Ayer Panas",
    "qs:name_adm0":"Malaysia",
    "qs:name_adm1":"Melaka",
    "qs:photos":1,
    "qs:photos_1k":1,
    "qs:photos_9k":1,
    "qs:photos_9r":1,
    "qs:photos_all":6,
    "qs:photos_sr":1,
    "qs:placetype":"LocalAdmin",
    "qs:pop_sr":"0",
    "wof:name":"Ayer Panas",
    "wof:placetype":"localadmin"
},
  "geometry": {"coordinates":[102.38806099999999,2.284177],"type":"Point"}
}