{
  "type": "Feature",
  "properties": {
    "gn:admin1_code":"6",
    "gn:asciiname":"Kampung Sengkela",
    "gn:country_code":"MY",
    "gn:dem":114,
    "gn:feature_class":"P",
    "gn:feature_code":"PPL",
    "gn:name":"Kampung Sengkela",
    "gn:population":0,
    "gn:timezone":"Asia/Kuala_Lumpur",
    "iso:country":"MY",
    "name:msa_x_preferred":[
        "Kampung Sengkela"
    ],
    "name:und_x_variant":[
        "Kampong Sinkla",
        "Kampong Sengkela"
    ],
    "wof:name":"Kampung Sengkela",
    "wof:placetype":"locality"
},
  "geometry": {"coordinates":[101.86579999999999,3.9593],"type":"Point"}
}