{
  "type": "Feature",
  "properties": {
    "gn:admin1_code":"5",
    "gn:asciiname":"Kampong Batu Puteh",
    "gn:country_code":"MY",
    "gn:dem":98,
    "gn:feature_class":"P",
    "gn:feature_code":"PPL",
    "gn:name":"Kampong Batu Puteh",
    "gn:population":0,
    "gn:timezone":"Asia/Kuala_Lumpur",
    "iso:country":"MY",
    "wof:name":"Kampong Batu Puteh",
    "wof:placetype":"locality"
},
  "geometry": {"coordinates":[102.26667,2.78333],"type":"Point"}
}