{
  "type": "Feature",
  "properties": {
    "gn:admin1_code":"2.0",
    "gn:asciiname":"Kampung Sungai Baharu",
    "gn:cc2":"MY",
    "gn:country_code":"MY",
    "gn:dem":5,
    "gn:feature_class":"P",
    "gn:feature_code":"PPL",
    "gn:name":"Kampung Sungai Baharu",
    "gn:population":0,
    "gn:timezone":"Asia/Kuala_Lumpur",
    "iso:country":"MY",
    "name:msa_x_preferred":[
        "Kampung Sungai Baharu"
    ],
    "name:und_x_variant":[
        "Kampong Sungai Baru"
    ],
    "wof:name":"Kampung Sungai Baharu",
    "wof:placetype":"locality"
},
  "geometry": {"coordinates":[100.45702,5.88083],"type":"Point"}
}