{
  "type": "Feature",
  "properties": {
    "gn:admin1_code":"11.0",
    "gn:asciiname":"Rumah Patu",
    "gn:country_code":"MY",
    "gn:dem":27,
    "gn:feature_class":"P",
    "gn:feature_code":"PPL",
    "gn:name":"Rumah Patu",
    "gn:population":0,
    "gn:timezone":"Asia/Kuching",
    "iso:country":"MY",
    "wof:name":"Rumah Patu",
    "wof:placetype":"locality"
},
  "geometry": {"coordinates":[111.33333,1.78333],"type":"Point"}
}