{
  "type": "Feature",
  "properties": {
    "gn:country":"MY",
    "gn:fcode":"PPL",
    "gn:population":0,
    "iso:country":"MY",
    "name:eng_x_preferred":[
        "Bandar Al-Muktafi Billah Shah"
    ],
    "name:ind_x_preferred":[
        "Bandar Al-Muktafi Billah Shah"
    ],
    "name:msa_x_preferred":[
        "Bandar Al-Muktafi Billah Shah"
    ],
    "name:nld_x_preferred":[
        "Bandar Al-Muktafi Billah Shah"
    ],
    "qs:name":"Bandar Al-Muktafi Billah Shah",
    "qs:name_adm0":"Malaysia",
    "qs:name_adm1":"Terengganu",
    "qs:photos_9r":0,
    "qs:photos_sr":0,
    "qs:placetype":"Town",
    "qs:pop_sr":"0",
    "wd:wordcount":129,
    "wof:name":"Bandar Al-Muktafi Billah Shah",
    "wof:placetype":"locality",
    "wof:population":0
},
  "geometry": {"coordinates":[103.2092,4.6111],"type":"Point"}
}