{
  "type": "Feature",
  "properties": {
    "gn:admin1_code":"16",
    "gn:asciiname":"Kampung Pandat",
    "gn:country_code":"MY",
    "gn:dem":453,
    "gn:feature_class":"P",
    "gn:feature_code":"PPL",
    "gn:name":"Kampung Pandat",
    "gn:population":0,
    "gn:timezone":"Asia/Kuching",
    "iso:country":"MY",
    "name:msa_x_preferred":[
        "Kampung Pandat"
    ],
    "name:und_x_variant":[
        "Kampong Pandat"
    ],
    "wof:name":"Kampung Pandat",
    "wof:placetype":"locality"
},
  "geometry": {"coordinates":[116.6039,6.3007],"type":"Point"}
}