{
  "type": "Feature",
  "properties": {
    "gn:admin1_code":"16.0",
    "gn:asciiname":"Kampung Masolog",
    "gn:country_code":"MY",
    "gn:dem":11,
    "gn:feature_class":"P",
    "gn:feature_code":"PPL",
    "gn:name":"Kampung Masolog",
    "gn:population":0,
    "gn:timezone":"Asia/Kuching",
    "iso:country":"MY",
    "name:msa_x_preferred":[
        "Kampung Masolog"
    ],
    "wof:name":"Kampung Masolog",
    "wof:placetype":"locality"
},
  "geometry": {"coordinates":[116.8398,6.4813],"type":"Point"}
}