{
  "type": "Feature",
  "properties": {
    "gn:admin1_code":"2",
    "gn:asciiname":"Kampung Telok Kechai",
    "gn:country_code":"MY",
    "gn:dem":6,
    "gn:feature_class":"P",
    "gn:feature_code":"PPL",
    "gn:name":"Kampung Telok Kechai",
    "gn:population":0,
    "gn:timezone":"Asia/Kuala_Lumpur",
    "iso:country":"MY",
    "name:msa_x_preferred":[
        "Kampung Telok Kechai"
    ],
    "name:und_x_variant":[
        "Kampong Telok Kechai"
    ],
    "wof:name":"Kampung Telok Kechai",
    "wof:placetype":"locality"
},
  "geometry": {"coordinates":[100.31923,6.09043],"type":"Point"}
}