{
  "type": "Feature",
  "properties": {
    "gn:admin1_code":"1.0",
    "gn:asciiname":"Kampung Paya Jakas",
    "gn:country_code":"MY",
    "gn:dem":40,
    "gn:feature_class":"P",
    "gn:feature_code":"PPL",
    "gn:name":"Kampung Paya Jakas",
    "gn:population":0,
    "gn:timezone":"Asia/Kuala_Lumpur",
    "iso:country":"MY",
    "name:msa_x_preferred":[
        "Kampung Paya Jakas"
    ],
    "wof:name":"Kampung Paya Jakas",
    "wof:placetype":"locality"
},
  "geometry": {"coordinates":[102.67440000000001,2.4232],"type":"Point"}
}