{
  "type": "Feature",
  "properties": {
    "gn:admin1_code":"2",
    "gn:asciiname":"Kampung Charok Sik",
    "gn:cc2":"MY",
    "gn:country_code":"MY",
    "gn:dem":66,
    "gn:feature_class":"P",
    "gn:feature_code":"PPL",
    "gn:name":"Kampung Charok Sik",
    "gn:population":0,
    "gn:timezone":"Asia/Kuala_Lumpur",
    "iso:country":"MY",
    "name:msa_x_preferred":[
        "Kampung Charok Sik"
    ],
    "name:und_x_variant":[
        "Kampong Charok Sik"
    ],
    "wof:name":"Kampung Charok Sik",
    "wof:placetype":"locality"
},
  "geometry": {"coordinates":[100.83495000000001,5.69938],"type":"Point"}
}