{
  "type": "Feature",
  "properties": {
    "gn:admin1_code":"2.0",
    "gn:asciiname":"Kampung Alor Biak",
    "gn:country_code":"MY",
    "gn:dem":6,
    "gn:feature_class":"P",
    "gn:feature_code":"PPL",
    "gn:name":"Kampung Alor Biak",
    "gn:population":0,
    "gn:timezone":"Asia/Kuala_Lumpur",
    "iso:country":"MY",
    "name:msa_x_preferred":[
        "Kampung Alor Biak"
    ],
    "wof:name":"Kampung Alor Biak",
    "wof:placetype":"locality"
},
  "geometry": {"coordinates":[100.32442,6.23852],"type":"Point"}
}