{
  "type": "Feature",
  "properties": {
    "gn:admin1_code":"2",
    "gn:asciiname":"Kampung Ruat",
    "gn:country_code":"MY",
    "gn:dem":18,
    "gn:feature_class":"P",
    "gn:feature_code":"PPL",
    "gn:name":"Kampung Ruat",
    "gn:population":0,
    "gn:timezone":"Asia/Kuala_Lumpur",
    "iso:country":"MY",
    "name:und_x_variant":[
        "Kampong Ruat",
        "Kampung Ruat"
    ],
    "wof:name":"Kampung Ruat",
    "wof:placetype":"locality"
},
  "geometry": {"coordinates":[100.37343,5.76703],"type":"Point"}
}