{
  "type": "Feature",
  "properties": {
    "gn:admin1_code":"12.0",
    "gn:asciiname":"Ladang Bute Salak",
    "gn:country_code":"MY",
    "gn:dem":29,
    "gn:feature_class":"P",
    "gn:feature_code":"PPL",
    "gn:name":"Ladang Bute Salak",
    "gn:population":0,
    "gn:timezone":"Asia/Kuala_Lumpur",
    "iso:country":"MY",
    "name:msa_x_preferred":[
        "Ladang Bute Salak"
    ],
    "wof:name":"Ladang Bute Salak",
    "wof:placetype":"locality"
},
  "geometry": {"coordinates":[101.7474,2.7555],"type":"Point"}
}