{
  "type": "Feature",
  "properties": {
    "gn:admin1_code":"6",
    "gn:asciiname":"Kampung Buan",
    "gn:country_code":"MY",
    "gn:dem":39,
    "gn:feature_class":"P",
    "gn:feature_code":"PPL",
    "gn:name":"Kampung Buan",
    "gn:population":0,
    "gn:timezone":"Asia/Kuala_Lumpur",
    "iso:country":"MY",
    "name:und_x_variant":[
        "Kampong Buan"
    ],
    "wof:name":"Kampung Buan",
    "wof:placetype":"locality"
},
  "geometry": {"coordinates":[102.90406,3.04128],"type":"Point"}
}