{
  "type": "Feature",
  "properties": {
    "gn:admin1_code":"6",
    "gn:asciiname":"Kampung Pulau Penanjung",
    "gn:country_code":"MY",
    "gn:dem":30,
    "gn:feature_class":"P",
    "gn:feature_code":"PPL",
    "gn:name":"Kampung Pulau Penanjung",
    "gn:population":0,
    "gn:timezone":"Asia/Kuala_Lumpur",
    "iso:country":"MY",
    "name:msa_x_preferred":[
        "Kampung Pulau Penanjung"
    ],
    "name:und_x_variant":[
        "Kampong Pulau Penanjung"
    ],
    "wof:name":"Kampung Pulau Penanjung",
    "wof:placetype":"locality"
},
  "geometry": {"coordinates":[103.1502,3.411],"type":"Point"}
}