{
  "type": "Feature",
  "properties": {
    "gn:admin1_code":"16",
    "gn:asciiname":"Tekeban",
    "gn:country_code":"MY",
    "gn:dem":116,
    "gn:feature_class":"P",
    "gn:feature_code":"PPL",
    "gn:name":"Tekeban",
    "gn:population":0,
    "gn:timezone":"Asia/Kuching",
    "iso:country":"MY",
    "wof:name":"Tekeban",
    "wof:placetype":"locality"
},
  "geometry": {"coordinates":[117.28333000000001,6.38333],"type":"Point"}
}