{
  "type": "Feature",
  "properties": {
    "gn:admin1_code":"11",
    "gn:asciiname":"Kampong Limpaku Pinang",
    "gn:cc2":"MY",
    "gn:country_code":"MY",
    "gn:dem":19,
    "gn:feature_class":"P",
    "gn:feature_code":"PPL",
    "gn:name":"Kampong Limpaku Pinang",
    "gn:population":0,
    "gn:timezone":"Asia/Kuching",
    "iso:country":"MY",
    "name:und_x_variant":[
        "Limpaku",
        "Kampong Limpaku Pinang"
    ],
    "wof:name":"Kampong Limpaku Pinang",
    "wof:placetype":"locality"
},
  "geometry": {"coordinates":[115.01667,4.88333],"type":"Point"}
}