{
  "type": "Feature",
  "properties": {
    "gn:admin1_code":"2.0",
    "gn:asciiname":"Kampung Teluk Banu",
    "gn:country_code":"MY",
    "gn:dem":7,
    "gn:feature_class":"P",
    "gn:feature_code":"PPL",
    "gn:name":"Kampung Teluk Banu",
    "gn:population":0,
    "gn:timezone":"Asia/Kuala_Lumpur",
    "iso:country":"MY",
    "name:msa_x_preferred":[
        "Kampung Teluk Banu"
    ],
    "wof:name":"Kampung Teluk Banu",
    "wof:placetype":"locality"
},
  "geometry": {"coordinates":[100.55831999999999,5.5183],"type":"Point"}
}