{
  "type": "Feature",
  "properties": {
    "gn:admin1_code":"13.0",
    "gn:asciiname":"Kampung Gong Pok Wil",
    "gn:cc2":"MY",
    "gn:country_code":"MY",
    "gn:dem":10,
    "gn:feature_class":"P",
    "gn:feature_code":"PPL",
    "gn:name":"Kampung Gong Pok Wil",
    "gn:population":0,
    "gn:timezone":"Asia/Kuala_Lumpur",
    "iso:country":"MY",
    "name:msa_x_preferred":[
        "Kampung Gong Pok Wil"
    ],
    "wof:name":"Kampung Gong Pok Wil",
    "wof:placetype":"locality"
},
  "geometry": {"coordinates":[102.94588,5.52229],"type":"Point"}
}