{
  "type": "Feature",
  "properties": {
    "gn:admin1_code":"6.0",
    "gn:asciiname":"Kampung Terakit",
    "gn:country_code":"MY",
    "gn:dem":256,
    "gn:feature_class":"P",
    "gn:feature_code":"PPL",
    "gn:name":"Kampung Terakit",
    "gn:population":0,
    "gn:timezone":"Asia/Kuala_Lumpur",
    "iso:country":"MY",
    "name:msa_x_preferred":[
        "Kampung Terakit"
    ],
    "wof:name":"Kampung Terakit",
    "wof:placetype":"locality"
},
  "geometry": {"coordinates":[101.59,4.4683],"type":"Point"}
}