{
  "type": "Feature",
  "properties": {
    "gn:admin1_code":"2.0",
    "gn:asciiname":"Kampung Batu Sepuluh",
    "gn:cc2":"MY",
    "gn:country_code":"MY",
    "gn:dem":51,
    "gn:feature_class":"P",
    "gn:feature_code":"PPL",
    "gn:name":"Kampung Batu Sepuluh",
    "gn:population":0,
    "gn:timezone":"Asia/Kuala_Lumpur",
    "iso:country":"MY",
    "name:msa_x_preferred":[
        "Kampung Batu Sepuluh"
    ],
    "name:und_x_variant":[
        "Kampung Batu 10"
    ],
    "wof:name":"Kampung Batu Sepuluh",
    "wof:placetype":"locality"
},
  "geometry": {"coordinates":[100.62203,5.30168],"type":"Point"}
}