{
  "type": "Feature",
  "properties": {
    "gn:admin1_code":"11",
    "gn:asciiname":"Nanga Anggan",
    "gn:country_code":"MY",
    "gn:dem":337,
    "gn:feature_class":"P",
    "gn:feature_code":"PPL",
    "gn:name":"Nanga Anggan",
    "gn:population":0,
    "gn:timezone":"Asia/Pontianak",
    "iso:country":"MY",
    "wof:name":"Nanga Anggan",
    "wof:placetype":"locality"
},
  "geometry": {"coordinates":[111.66965,1.01002],"type":"Point"}
}