{
  "type": "Feature",
  "properties": {
    "gn:admin1_code":"1",
    "gn:asciiname":"Kampung Air Masin",
    "gn:country_code":"MY",
    "gn:dem":9,
    "gn:feature_class":"P",
    "gn:feature_code":"PPL",
    "gn:name":"Kampung Air Masin",
    "gn:population":0,
    "gn:timezone":"Asia/Kuala_Lumpur",
    "iso:country":"MY",
    "name:msa_x_preferred":[
        "Kampung Air Masin"
    ],
    "name:und_x_variant":[
        "Kampong Ayer Masin"
    ],
    "wof:name":"Kampung Air Masin",
    "wof:placetype":"locality"
},
  "geometry": {"coordinates":[103.44970000000001,1.3457],"type":"Point"}
}