{
  "type": "Feature",
  "properties": {
    "gn:admin1_code":"5.0",
    "gn:asciiname":"Pelabuhan Kelang Utara",
    "gn:country_code":"MY",
    "gn:dem":4,
    "gn:feature_class":"P",
    "gn:feature_code":"PPL",
    "gn:name":"Pelabuhan Kelang Utara",
    "gn:population":0,
    "gn:timezone":"Asia/Kuala_Lumpur",
    "iso:country":"MY",
    "wof:name":"Pelabuhan Kelang Utara",
    "wof:placetype":"locality"
},
  "geometry": {"coordinates":[101.42083,3.07361],"type":"Point"}
}