{
  "type": "Feature",
  "properties": {
    "gn:admin1_code":"8.0",
    "gn:asciiname":"Taman Utara",
    "gn:country_code":"MY",
    "gn:dem":12,
    "gn:feature_class":"P",
    "gn:feature_code":"PPL",
    "gn:name":"Taman Utara",
    "gn:population":0,
    "gn:timezone":"Asia/Kuala_Lumpur",
    "iso:country":"MY",
    "name:msa_x_preferred":[
        "Taman Utara"
    ],
    "wof:name":"Taman Utara",
    "wof:placetype":"locality"
},
  "geometry": {"coordinates":[100.23544,6.44303],"type":"Point"}
}