{
  "type": "Feature",
  "properties": {
    "gn:admin1_code":"16.0",
    "gn:asciiname":"Kampung Panikawan Laut",
    "gn:country_code":"MY",
    "gn:dem":54,
    "gn:feature_class":"P",
    "gn:feature_code":"PPL",
    "gn:name":"Kampung Panikawan Laut",
    "gn:population":0,
    "gn:timezone":"Asia/Kuching",
    "iso:country":"MY",
    "name:msa_x_preferred":[
        "Kampung Panikawan Laut"
    ],
    "name:und_x_variant":[
        "Panikawan",
        "Kampong Panikawan Laut"
    ],
    "wof:name":"Kampung Panikawan Laut",
    "wof:placetype":"locality"
},
  "geometry": {"coordinates":[116.7444,6.6745],"type":"Point"}
}