{
  "type": "Feature",
  "properties": {
    "gn:admin1_code":"6",
    "gn:asciiname":"Kampung Permatang Pauh",
    "gn:country_code":"MY",
    "gn:dem":10,
    "gn:feature_class":"P",
    "gn:feature_code":"PPL",
    "gn:name":"Kampung Permatang Pauh",
    "gn:population":0,
    "gn:timezone":"Asia/Kuala_Lumpur",
    "iso:country":"MY",
    "name:msa_x_preferred":[
        "Kampung Permatang Pauh"
    ],
    "name:und_x_variant":[
        "Kampong Permatang Pauh"
    ],
    "wof:name":"Kampung Permatang Pauh",
    "wof:placetype":"locality"
},
  "geometry": {"coordinates":[103.36969999999999,3.4829],"type":"Point"}
}