{
  "type": "Feature",
  "properties": {
    "gn:admin1_code":"9.0",
    "gn:asciiname":"Titi Panjang",
    "gn:cc2":"MY",
    "gn:country_code":"MY",
    "gn:dem":6,
    "gn:feature_class":"P",
    "gn:feature_code":"PPL",
    "gn:name":"Titi Panjang",
    "gn:population":0,
    "gn:timezone":"Asia/Kuala_Lumpur",
    "iso:country":"MY",
    "name:msa_x_preferred":[
        "Titi Panjang"
    ],
    "wof:name":"Titi Panjang",
    "wof:placetype":"locality"
},
  "geometry": {"coordinates":[100.44283,5.33025],"type":"Point"}
}