{
  "type": "Feature",
  "properties": {
    "gn:admin1_code":"7.0",
    "gn:asciiname":"Telok Piyai",
    "gn:country_code":"MY",
    "gn:dem":6,
    "gn:feature_class":"P",
    "gn:feature_code":"PPL",
    "gn:name":"Telok Piyai",
    "gn:population":0,
    "gn:timezone":"Asia/Kuala_Lumpur",
    "iso:country":"MY",
    "name:msa_x_preferred":[
        "Telok Piyai"
    ],
    "wof:name":"Telok Piyai",
    "wof:placetype":"locality"
},
  "geometry": {"coordinates":[100.8772,4.0036],"type":"Point"}
}