{
  "type": "Feature",
  "properties": {
    "gn:admin1_code":"6.0",
    "gn:asciiname":"Kampung Pagar Sasak",
    "gn:country_code":"MY",
    "gn:dem":105,
    "gn:feature_class":"P",
    "gn:feature_code":"PPL",
    "gn:name":"Kampung Pagar Sasak",
    "gn:population":0,
    "gn:timezone":"Asia/Kuala_Lumpur",
    "iso:country":"MY",
    "name:msa_x_preferred":[
        "Kampung Pagar Sasak"
    ],
    "wof:name":"Kampung Pagar Sasak",
    "wof:placetype":"locality"
},
  "geometry": {"coordinates":[102.06189999999999,4.3852],"type":"Point"}
}