{
  "type": "Feature",
  "properties": {
    "gn:admin1_code":"13",
    "gn:asciiname":"Kampung Padang Terik",
    "gn:country_code":"MY",
    "gn:dem":18,
    "gn:feature_class":"P",
    "gn:feature_code":"PPL",
    "gn:name":"Kampung Padang Terik",
    "gn:population":0,
    "gn:timezone":"Asia/Kuala_Lumpur",
    "iso:country":"MY",
    "name:msa_x_preferred":[
        "Kampung Padang Terik"
    ],
    "name:und_x_variant":[
        "Kampong Padang Terik"
    ],
    "wof:name":"Kampung Padang Terik",
    "wof:placetype":"locality"
},
  "geometry": {"coordinates":[103.1499,5.1436],"type":"Point"}
}