{
  "type": "Feature",
  "properties": {
    "gn:admin1_code":"6",
    "gn:asciiname":"Kampung Gemuruh",
    "gn:country_code":"MY",
    "gn:dem":25,
    "gn:feature_class":"P",
    "gn:feature_code":"PPL",
    "gn:name":"Kampung Gemuruh",
    "gn:population":0,
    "gn:timezone":"Asia/Kuala_Lumpur",
    "iso:country":"MY",
    "name:und_x_variant":[
        "Kampong Gemuroh"
    ],
    "wof:name":"Kampung Gemuruh",
    "wof:placetype":"locality"
},
  "geometry": {"coordinates":[103.06449000000001,3.58298],"type":"Point"}
}