{
  "type": "Feature",
  "properties": {
    "gn:admin1_code":"6.0",
    "gn:asciiname":"Kampung Pengkalan Jaya",
    "gn:country_code":"MY",
    "gn:dem":45,
    "gn:feature_class":"P",
    "gn:feature_code":"PPL",
    "gn:name":"Kampung Pengkalan Jaya",
    "gn:population":0,
    "gn:timezone":"Asia/Kuala_Lumpur",
    "iso:country":"MY",
    "name:msa_x_preferred":[
        "Kampung Pengkalan Jaya"
    ],
    "wof:name":"Kampung Pengkalan Jaya",
    "wof:placetype":"locality"
},
  "geometry": {"coordinates":[102.4237,3.3969],"type":"Point"}
}