{
  "type": "Feature",
  "properties": {
    "gn:admin1_code":"8.0",
    "gn:asciiname":"Kampung Hutan Arau",
    "gn:country_code":"MY",
    "gn:dem":13,
    "gn:feature_class":"P",
    "gn:feature_code":"PPL",
    "gn:name":"Kampung Hutan Arau",
    "gn:population":0,
    "gn:timezone":"Asia/Kuala_Lumpur",
    "iso:country":"MY",
    "name:msa_x_preferred":[
        "Kampung Hutan Arau"
    ],
    "wof:name":"Kampung Hutan Arau",
    "wof:placetype":"locality"
},
  "geometry": {"coordinates":[100.28977,6.43108],"type":"Point"}
}