{
  "type": "Feature",
  "properties": {
    "gn:admin1_code":"2",
    "gn:asciiname":"Kampung Paya",
    "gn:cc2":"MY",
    "gn:country_code":"MY",
    "gn:dem":89,
    "gn:feature_class":"P",
    "gn:feature_code":"PPL",
    "gn:name":"Kampung Paya",
    "gn:population":0,
    "gn:timezone":"Asia/Kuala_Lumpur",
    "iso:country":"MY",
    "name:msa_x_preferred":[
        "Kampung Paya"
    ],
    "name:und_x_variant":[
        "Kampong Paya"
    ],
    "wof:name":"Kampung Paya",
    "wof:placetype":"locality"
},
  "geometry": {"coordinates":[100.79951,5.95339],"type":"Point"}
}