{
  "type": "Feature",
  "properties": {
    "gn:admin1_code":"7",
    "gn:asciiname":"Kampung Ayer Tawar",
    "gn:country_code":"MY",
    "gn:dem":20,
    "gn:feature_class":"P",
    "gn:feature_code":"PPL",
    "gn:name":"Kampung Ayer Tawar",
    "gn:population":0,
    "gn:timezone":"Asia/Kuala_Lumpur",
    "iso:country":"MY",
    "name:msa_x_preferred":[
        "Kampung Ayer Tawar"
    ],
    "name:und_x_variant":[
        "Kampong Ayer Tawar"
    ],
    "wof:name":"Kampung Ayer Tawar",
    "wof:placetype":"locality"
},
  "geometry": {"coordinates":[100.7837,4.334],"type":"Point"}
}