{
  "type": "Feature",
  "properties": {
    "gn:admin1_code":"4",
    "gn:asciiname":"Kampung Kandang",
    "gn:country_code":"MY",
    "gn:dem":7,
    "gn:feature_class":"P",
    "gn:feature_code":"PPL",
    "gn:name":"Kampung Kandang",
    "gn:population":0,
    "gn:timezone":"Asia/Kuala_Lumpur",
    "iso:country":"MY",
    "name:msa_x_preferred":[
        "Kampung Kandang"
    ],
    "name:und_x_variant":[
        "Kandang",
        "Kampong Kandang"
    ],
    "wof:name":"Kampung Kandang",
    "wof:placetype":"locality"
},
  "geometry": {"coordinates":[102.3031,2.1889],"type":"Point"}
}