{
  "type": "Feature",
  "properties": {
    "gn:admin1_code":"11",
    "gn:asciiname":"Rumah Linei",
    "gn:country_code":"MY",
    "gn:dem":90,
    "gn:feature_class":"P",
    "gn:feature_code":"PPL",
    "gn:name":"Rumah Linei",
    "gn:population":0,
    "gn:timezone":"Asia/Kuching",
    "iso:country":"MY",
    "wof:name":"Rumah Linei",
    "wof:placetype":"locality"
},
  "geometry": {"coordinates":[114.48333,4.08333],"type":"Point"}
}