{
  "type": "Feature",
  "properties": {
    "gn:admin1_code":"7",
    "gn:asciiname":"Kampung Sungai Durian",
    "gn:country_code":"MY",
    "gn:dem":7,
    "gn:feature_class":"P",
    "gn:feature_code":"PPL",
    "gn:name":"Kampung Sungai Durian",
    "gn:population":0,
    "gn:timezone":"Asia/Kuala_Lumpur",
    "iso:country":"MY",
    "name:msa_x_preferred":[
        "Kampung Sungai Durian"
    ],
    "name:und_x_variant":[
        "Kampong Sungei Durien",
        "Kampong Sungai Durian"
    ],
    "wof:name":"Kampung Sungai Durian",
    "wof:placetype":"locality"
},
  "geometry": {"coordinates":[100.96550000000001,4.0046],"type":"Point"}
}