{
  "type": "Feature",
  "properties": {
    "gn:admin1_code":"12",
    "gn:asciiname":"Kampung Tanjong Paoh",
    "gn:country_code":"MY",
    "gn:dem":95,
    "gn:feature_class":"P",
    "gn:feature_code":"PPL",
    "gn:name":"Kampung Tanjong Paoh",
    "gn:population":0,
    "gn:timezone":"Asia/Kuala_Lumpur",
    "iso:country":"MY",
    "name:msa_x_preferred":[
        "Kampung Tanjong Paoh"
    ],
    "name:und_x_variant":[
        "Kampong Tanjong Paoh"
    ],
    "wof:name":"Kampung Tanjong Paoh",
    "wof:placetype":"locality"
},
  "geometry": {"coordinates":[101.8784,3.1693],"type":"Point"}
}