{
  "type": "Feature",
  "properties": {
    "gn:country":"MY",
    "gn:fcode":"PPL",
    "gn:population":0,
    "iso:country":"MY",
    "name:eng_x_preferred":[
        "Bukit Jambul"
    ],
    "name:msa_x_preferred":[
        "Bukit Jambul"
    ],
    "name:nld_x_preferred":[
        "Bukit Jambul"
    ],
    "name:vie_x_preferred":[
        "Bukit Jambul"
    ],
    "name:zho_x_preferred":[
        "\u6b66\u5409\u5360\u59c6"
    ],
    "qs:name":"Batu Jambul",
    "qs:name_adm0":"Malaysia",
    "qs:name_adm1":"Pulau Pinang",
    "qs:photos":1,
    "qs:photos_1k":1,
    "qs:photos_9k":1,
    "qs:photos_9r":1,
    "qs:photos_all":1,
    "qs:photos_sr":1,
    "qs:placetype":"Suburb",
    "qs:pop_sr":"0",
    "wd:wordcount":129,
    "wof:name":"Batu Jambul",
    "wof:placetype":"neighbourhood",
    "wof:population":0
},
  "geometry": {"coordinates":[100.26667,5.2625],"type":"Point"}
}