{
  "type": "Feature",
  "properties": {
    "gn:admin1_code":"2",
    "gn:asciiname":"Kampung Bagan Jermai",
    "gn:country_code":"MY",
    "gn:dem":26,
    "gn:feature_class":"P",
    "gn:feature_code":"PPL",
    "gn:name":"Kampung Bagan Jermai",
    "gn:population":0,
    "gn:timezone":"Asia/Kuala_Lumpur",
    "iso:country":"MY",
    "name:und_x_variant":[
        "Kampong Bagan Jermai",
        "Kampung Bagan Jermai"
    ],
    "wof:name":"Kampung Bagan Jermai",
    "wof:placetype":"locality"
},
  "geometry": {"coordinates":[100.71666999999999,5.26452],"type":"Point"}
}