{
  "type": "Feature",
  "properties": {
    "gn:admin1_code":"9",
    "gn:asciiname":"Kampung Bagan Ajam",
    "gn:cc2":"MY",
    "gn:country_code":"MY",
    "gn:dem":12,
    "gn:feature_class":"P",
    "gn:feature_code":"PPL",
    "gn:name":"Kampung Bagan Ajam",
    "gn:population":0,
    "gn:timezone":"Asia/Kuala_Lumpur",
    "iso:country":"MY",
    "name:msa_x_preferred":[
        "Kampung Bagan Ajam"
    ],
    "name:und_x_variant":[
        "Kampong Bagan Ajam"
    ],
    "wof:name":"Kampung Bagan Ajam",
    "wof:placetype":"locality"
},
  "geometry": {"coordinates":[100.37958,5.4429],"type":"Point"}
}