{
  "type": "Feature",
  "properties": {
    "gn:admin1_code":"13.0",
    "gn:asciiname":"Kampung Baharu Tok Dor",
    "gn:country_code":"MY",
    "gn:dem":17,
    "gn:feature_class":"P",
    "gn:feature_code":"PPL",
    "gn:name":"Kampung Baharu Tok Dor",
    "gn:population":0,
    "gn:timezone":"Asia/Kuala_Lumpur",
    "iso:country":"MY",
    "name:msa_x_preferred":[
        "Kampung Baharu Tok Dor"
    ],
    "wof:name":"Kampung Baharu Tok Dor",
    "wof:placetype":"locality"
},
  "geometry": {"coordinates":[102.64606000000001,5.66889],"type":"Point"}
}