{
  "type": "Feature",
  "properties": {
    "gn:admin1_code":"2",
    "gn:asciiname":"Kampung Kota",
    "gn:cc2":"MY",
    "gn:country_code":"MY",
    "gn:dem":79,
    "gn:feature_class":"P",
    "gn:feature_code":"PPL",
    "gn:name":"Kampung Kota",
    "gn:population":0,
    "gn:timezone":"Asia/Kuala_Lumpur",
    "iso:country":"MY",
    "name:msa_x_preferred":[
        "Kampung Kota"
    ],
    "name:und_x_variant":[
        "Kampong Kota"
    ],
    "wof:name":"Kampung Kota",
    "wof:placetype":"locality"
},
  "geometry": {"coordinates":[100.8955,5.75772],"type":"Point"}
}