{
  "type": "Feature",
  "properties": {
    "gn:admin1_code":"16",
    "gn:asciiname":"Kampong Podi",
    "gn:country_code":"MY",
    "gn:dem":411,
    "gn:feature_class":"P",
    "gn:feature_code":"PPL",
    "gn:name":"Kampong Podi",
    "gn:population":0,
    "gn:timezone":"Asia/Kuching",
    "iso:country":"MY",
    "wof:name":"Kampong Podi",
    "wof:placetype":"locality"
},
  "geometry": {"coordinates":[116.61667,6.33333],"type":"Point"}
}