{
  "type": "Feature",
  "properties": {
    "gn:admin1_code":"13",
    "gn:asciiname":"Kampung Banggul Binjai",
    "gn:country_code":"MY",
    "gn:dem":10,
    "gn:feature_class":"P",
    "gn:feature_code":"PPL",
    "gn:name":"Kampung Banggul Binjai",
    "gn:population":0,
    "gn:timezone":"Asia/Kuala_Lumpur",
    "iso:country":"MY",
    "name:msa_x_preferred":[
        "Kampung Banggul Binjai"
    ],
    "name:und_x_variant":[
        "Kampong Banggol Binjai"
    ],
    "wof:name":"Kampung Banggul Binjai",
    "wof:placetype":"locality"
},
  "geometry": {"coordinates":[103.0523,5.3417],"type":"Point"}
}