{
  "type": "Feature",
  "properties": {
    "gn:admin1_code":"5.0",
    "gn:asciiname":"Kampung Tampin",
    "gn:country_code":"MY",
    "gn:dem":128,
    "gn:feature_class":"P",
    "gn:feature_code":"PPL",
    "gn:name":"Kampung Tampin",
    "gn:population":0,
    "gn:timezone":"Asia/Kuala_Lumpur",
    "iso:country":"MY",
    "name:msa_x_preferred":[
        "Kampung Tampin"
    ],
    "wof:name":"Kampung Tampin",
    "wof:placetype":"locality"
},
  "geometry": {"coordinates":[102.2094,2.8644],"type":"Point"}
}