{
  "type": "Feature",
  "properties": {
    "iso:country":"MY",
    "qs:name":"Jorak",
    "qs:name_adm0":"Malaysia",
    "qs:name_adm1":"Johor",
    "qs:photos":71,
    "qs:photos_1k":14,
    "qs:photos_9k":1,
    "qs:photos_9r":3,
    "qs:photos_all":136,
    "qs:photos_sr":2,
    "qs:placetype":"LocalAdmin",
    "qs:pop_sr":"0",
    "wd:wordcount":78,
    "wof:name":"Jorak",
    "wof:placetype":"localadmin"
},
  "geometry": {"coordinates":[102.78160800000001,2.129628],"type":"Point"}
}