{
  "type": "Feature",
  "properties": {
    "gn:admin1_code":"11",
    "gn:asciiname":"Rumah Nakat",
    "gn:country_code":"MY",
    "gn:dem":9,
    "gn:feature_class":"P",
    "gn:feature_code":"PPL",
    "gn:name":"Rumah Nakat",
    "gn:population":0,
    "gn:timezone":"Asia/Kuching",
    "iso:country":"MY",
    "name:msa_x_preferred":[
        "Rumah Nakat"
    ],
    "name:und_x_variant":[
        "Rumah Belat"
    ],
    "wof:name":"Rumah Nakat",
    "wof:placetype":"locality"
},
  "geometry": {"coordinates":[114.0968,4.1787],"type":"Point"}
}