{
  "type": "Feature",
  "properties": {
    "gn:admin1_code":"2",
    "gn:asciiname":"Kampung Kelian Dalam",
    "gn:cc2":"MY",
    "gn:country_code":"MY",
    "gn:dem":104,
    "gn:feature_class":"P",
    "gn:feature_code":"PPL",
    "gn:name":"Kampung Kelian Dalam",
    "gn:population":0,
    "gn:timezone":"Asia/Kuala_Lumpur",
    "iso:country":"MY",
    "name:msa_x_preferred":[
        "Kampung Kelian Dalam"
    ],
    "name:und_x_variant":[
        "Kampong Klian Dalam",
        "Kampong Kalian Dalam",
        "Kampong Kelian Dalam"
    ],
    "wof:name":"Kampung Kelian Dalam",
    "wof:placetype":"locality"
},
  "geometry": {"coordinates":[100.86975,5.76689],"type":"Point"}
}