{
  "type": "Feature",
  "properties": {
    "gn:admin1_code":"2.0",
    "gn:asciiname":"Kampung Rendang Pasir",
    "gn:country_code":"MY",
    "gn:dem":8,
    "gn:feature_class":"P",
    "gn:feature_code":"PPL",
    "gn:name":"Kampung Rendang Pasir",
    "gn:population":0,
    "gn:timezone":"Asia/Kuala_Lumpur",
    "iso:country":"MY",
    "name:msa_x_preferred":[
        "Kampung Rendang Pasir"
    ],
    "wof:name":"Kampung Rendang Pasir",
    "wof:placetype":"locality"
},
  "geometry": {"coordinates":[100.3809,5.8043],"type":"Point"}
}