{
  "type": "Feature",
  "properties": {
    "gn:admin1_code":"16",
    "gn:asciiname":"Takiau",
    "gn:country_code":"MY",
    "gn:dem":152,
    "gn:feature_class":"P",
    "gn:feature_code":"PPL",
    "gn:name":"Takiau",
    "gn:population":0,
    "gn:timezone":"Asia/Kuching",
    "iso:country":"MY",
    "wof:name":"Takiau",
    "wof:placetype":"locality"
},
  "geometry": {"coordinates":[116.81667,5.36667],"type":"Point"}
}