{
  "type": "Feature",
  "properties": {
    "gn:admin1_code":"0.0",
    "gn:asciiname":"Kampung Lubok Lasat",
    "gn:country_code":"MY",
    "gn:dem":31,
    "gn:feature_class":"P",
    "gn:feature_code":"PPL",
    "gn:name":"Kampung Lubok Lasat",
    "gn:population":0,
    "gn:timezone":"Asia/Kuching",
    "iso:country":"MY",
    "wof:name":"Kampung Lubok Lasat",
    "wof:placetype":"locality"
},
  "geometry": {"coordinates":[114.88333,4.55],"type":"Point"}
}