{
  "type": "Feature",
  "properties": {
    "gn:admin1_code":"1",
    "gn:asciiname":"Kampung Sungai Keladi",
    "gn:country_code":"MY",
    "gn:dem":10,
    "gn:feature_class":"P",
    "gn:feature_code":"PPL",
    "gn:name":"Kampung Sungai Keladi",
    "gn:population":0,
    "gn:timezone":"Asia/Kuala_Lumpur",
    "iso:country":"MY",
    "name:msa_x_preferred":[
        "Kampung Sungai Keladi"
    ],
    "name:und_x_variant":[
        "Kampong Sungai Keladi"
    ],
    "wof:name":"Kampung Sungai Keladi",
    "wof:placetype":"locality"
},
  "geometry": {"coordinates":[102.5907,2.1405],"type":"Point"}
}