{
  "type": "Feature",
  "properties": {
    "gn:admin1_code":"9",
    "gn:asciiname":"Merbau Kudung",
    "gn:cc2":"MY",
    "gn:country_code":"MY",
    "gn:dem":6,
    "gn:feature_class":"P",
    "gn:feature_code":"PPL",
    "gn:name":"Merbau Kudung",
    "gn:population":0,
    "gn:timezone":"Asia/Kuala_Lumpur",
    "iso:country":"MY",
    "name:msa_x_preferred":[
        "Merbau Kudung"
    ],
    "name:und_x_variant":[
        "Marbau Kudong",
        "Merbau Kudong"
    ],
    "wof:name":"Merbau Kudung",
    "wof:placetype":"locality"
},
  "geometry": {"coordinates":[100.44145,5.45593],"type":"Point"}
}