{
  "type": "Feature",
  "properties": {
    "gn:admin1_code":"11.0",
    "gn:asciiname":"Kampung Siburak",
    "gn:country_code":"MY",
    "gn:dem":36,
    "gn:feature_class":"P",
    "gn:feature_code":"PPL",
    "gn:name":"Kampung Siburak",
    "gn:population":0,
    "gn:timezone":"Asia/Kuching",
    "iso:country":"MY",
    "name:msa_x_preferred":[
        "Kampung Siburak"
    ],
    "wof:name":"Kampung Siburak",
    "wof:placetype":"locality"
},
  "geometry": {"coordinates":[115.3283,4.6745],"type":"Point"}
}