{
  "type": "Feature",
  "properties": {
    "gn:admin1_code":"5",
    "gn:asciiname":"Kampung Panglang",
    "gn:country_code":"MY",
    "gn:dem":119,
    "gn:feature_class":"P",
    "gn:feature_code":"PPL",
    "gn:name":"Kampung Panglang",
    "gn:population":0,
    "gn:timezone":"Asia/Kuala_Lumpur",
    "iso:country":"MY",
    "name:msa_x_preferred":[
        "Kampung Panglang"
    ],
    "name:und_x_variant":[
        "Kampong Panglang"
    ],
    "wof:name":"Kampung Panglang",
    "wof:placetype":"locality"
},
  "geometry": {"coordinates":[102.17619999999999,2.7192],"type":"Point"}
}