{
  "type": "Feature",
  "properties": {
    "gn:admin1_code":"7.0",
    "gn:asciiname":"Kampung Tengah Teluk Murok",
    "gn:country_code":"MY",
    "gn:dem":20,
    "gn:feature_class":"P",
    "gn:feature_code":"PPL",
    "gn:name":"Kampung Tengah Teluk Murok",
    "gn:population":0,
    "gn:timezone":"Asia/Kuala_Lumpur",
    "iso:country":"MY",
    "name:msa_x_preferred":[
        "Kampung Tengah Teluk Murok"
    ],
    "wof:name":"Kampung Tengah Teluk Murok",
    "wof:placetype":"locality"
},
  "geometry": {"coordinates":[100.61799999999999,4.2086],"type":"Point"}
}