{
  "type": "Feature",
  "properties": {
    "gn:admin1_code":"11.0",
    "gn:asciiname":"Rumah Suri",
    "gn:country_code":"MY",
    "gn:dem":212,
    "gn:feature_class":"P",
    "gn:feature_code":"PPL",
    "gn:name":"Rumah Suri",
    "gn:population":0,
    "gn:timezone":"Asia/Kuching",
    "iso:country":"MY",
    "name:msa_x_preferred":[
        "Rumah Suri"
    ],
    "wof:name":"Rumah Suri",
    "wof:placetype":"locality"
},
  "geometry": {"coordinates":[111.02155999999999,1.20122],"type":"Point"}
}