{
  "type": "Feature",
  "properties": {
    "gn:admin1_code":"3",
    "gn:asciiname":"Kampong Pak Ya'akob",
    "gn:country_code":"MY",
    "gn:dem":4,
    "gn:feature_class":"P",
    "gn:feature_code":"PPL",
    "gn:name":"Kampong Pak Ya\u2019akob",
    "gn:population":0,
    "gn:timezone":"Asia/Kuala_Lumpur",
    "iso:country":"MY",
    "wof:name":"Kampong Pak Ya'akob",
    "wof:placetype":"locality"
},
  "geometry": {"coordinates":[102.46666999999999,5.91667],"type":"Point"}
}