{
  "type": "Feature",
  "properties": {
    "gn:admin1_code":"11.0",
    "gn:asciiname":"Rumah Jambai",
    "gn:cc2":"MY",
    "gn:country_code":"MY",
    "gn:dem":16,
    "gn:feature_class":"P",
    "gn:feature_code":"PPL",
    "gn:name":"Rumah Jambai",
    "gn:population":0,
    "gn:timezone":"Asia/Kuching",
    "iso:country":"MY",
    "name:und_x_variant":[
        "Rumah Sigam",
        "Rumah Jambai"
    ],
    "wof:name":"Rumah Jambai",
    "wof:placetype":"locality"
},
  "geometry": {"coordinates":[113.33333,3.13333],"type":"Point"}
}