{
  "type": "Feature",
  "properties": {
    "gn:admin1_code":"13",
    "gn:asciiname":"Kampung Baharu",
    "gn:country_code":"MY",
    "gn:dem":68,
    "gn:feature_class":"P",
    "gn:feature_code":"PPL",
    "gn:name":"Kampung Baharu",
    "gn:population":0,
    "gn:timezone":"Asia/Kuala_Lumpur",
    "iso:country":"MY",
    "name:und_x_variant":[
        "Kampong Baharu"
    ],
    "wof:name":"Kampung Baharu",
    "wof:placetype":"locality"
},
  "geometry": {"coordinates":[103.08889000000001,4.71773],"type":"Point"}
}