{
  "type": "Feature",
  "properties": {
    "gn:admin1_code":"9",
    "gn:asciiname":"Kampung Besar",
    "gn:cc2":"MY",
    "gn:country_code":"MY",
    "gn:dem":11,
    "gn:feature_class":"P",
    "gn:feature_code":"PPL",
    "gn:name":"Kampung Besar",
    "gn:population":0,
    "gn:timezone":"Asia/Kuala_Lumpur",
    "iso:country":"MY",
    "name:msa_x_preferred":[
        "Kampung Besar"
    ],
    "name:und_x_variant":[
        "Kampong Besar"
    ],
    "wof:name":"Kampung Besar",
    "wof:placetype":"locality"
},
  "geometry": {"coordinates":[100.50799000000001,5.48394],"type":"Point"}
}