{
  "type": "Feature",
  "properties": {
    "gn:admin1_code":"16.0",
    "gn:asciiname":"Kampung Sebangan",
    "gn:country_code":"MY",
    "gn:dem":22,
    "gn:feature_class":"P",
    "gn:feature_code":"PPL",
    "gn:name":"Kampung Sebangan",
    "gn:population":0,
    "gn:timezone":"Asia/Kuching",
    "iso:country":"MY",
    "name:und_x_variant":[
        "Sebangan"
    ],
    "wof:name":"Kampung Sebangan",
    "wof:placetype":"locality"
},
  "geometry": {"coordinates":[117.81496,5.49741],"type":"Point"}
}