{
  "type": "Feature",
  "properties": {
    "gn:admin1_code":"7",
    "gn:asciiname":"Kampung Sungai Rubana",
    "gn:country_code":"MY",
    "gn:dem":8,
    "gn:feature_class":"P",
    "gn:feature_code":"PPL",
    "gn:name":"Kampung Sungai Rubana",
    "gn:population":0,
    "gn:timezone":"Asia/Kuala_Lumpur",
    "iso:country":"MY",
    "name:msa_x_preferred":[
        "Kampung Sungai Rubana"
    ],
    "name:und_x_variant":[
        "Kampong Sungei Rebana",
        "Kampong Sungai Rubana"
    ],
    "wof:name":"Kampung Sungai Rubana",
    "wof:placetype":"locality"
},
  "geometry": {"coordinates":[100.9126,3.9925],"type":"Point"}
}