{
  "type": "Feature",
  "properties": {
    "gn:admin1_code":"13.0",
    "gn:asciiname":"Kampung Pulau Kerengga",
    "gn:country_code":"MY",
    "gn:dem":18,
    "gn:feature_class":"P",
    "gn:feature_code":"PPL",
    "gn:name":"Kampung Pulau Kerengga",
    "gn:population":0,
    "gn:timezone":"Asia/Kuala_Lumpur",
    "iso:country":"MY",
    "name:msa_x_preferred":[
        "Kampung Pulau Kerengga"
    ],
    "name:und_x_variant":[
        "Kampong Pulau Kerangga",
        "Kampong Pulau Krengga"
    ],
    "wof:name":"Kampung Pulau Kerengga",
    "wof:placetype":"locality"
},
  "geometry": {"coordinates":[103.2474,5.1294],"type":"Point"}
}