{
  "type": "Feature",
  "properties": {
    "gn:admin1_code":"16.0",
    "gn:asciiname":"Kampung Selingsing",
    "gn:country_code":"MY",
    "gn:dem":11,
    "gn:feature_class":"P",
    "gn:feature_code":"PPL",
    "gn:name":"Kampung Selingsing",
    "gn:population":0,
    "gn:timezone":"Asia/Kuching",
    "iso:country":"MY",
    "name:msa_x_preferred":[
        "Kampung Selingsing"
    ],
    "wof:name":"Kampung Selingsing",
    "wof:placetype":"locality"
},
  "geometry": {"coordinates":[115.628,5.3657],"type":"Point"}
}