{
  "type": "Feature",
  "properties": {
    "gn:admin1_code":"6.0",
    "gn:asciiname":"Kampung Kuala Kecau",
    "gn:country_code":"MY",
    "gn:dem":78,
    "gn:feature_class":"P",
    "gn:feature_code":"PPL",
    "gn:name":"Kampung Kuala Kecau",
    "gn:population":0,
    "gn:timezone":"Asia/Kuala_Lumpur",
    "iso:country":"MY",
    "name:msa_x_preferred":[
        "Kampung Kuala Kecau"
    ],
    "name:und_x_variant":[
        "Kampung Kuala Kechau"
    ],
    "wof:name":"Kampung Kuala Kecau",
    "wof:placetype":"locality"
},
  "geometry": {"coordinates":[102.0911,4.1923],"type":"Point"}
}