{
  "type": "Feature",
  "properties": {
    "gn:admin1_code":"2",
    "gn:asciiname":"Kampung Sungai Badak",
    "gn:cc2":"MY",
    "gn:country_code":"MY",
    "gn:dem":33,
    "gn:feature_class":"P",
    "gn:feature_code":"PPL",
    "gn:name":"Kampung Sungai Badak",
    "gn:population":0,
    "gn:timezone":"Asia/Kuala_Lumpur",
    "iso:country":"MY",
    "name:msa_x_preferred":[
        "Kampung Sungai Badak"
    ],
    "name:und_x_variant":[
        "Kampong Sungai Badak"
    ],
    "wof:name":"Kampung Sungai Badak",
    "wof:placetype":"locality"
},
  "geometry": {"coordinates":[100.55775,5.39655],"type":"Point"}
}