{
  "type": "Feature",
  "properties": {
    "gn:admin1_code":"1",
    "gn:asciiname":"Kampung Pasir",
    "gn:country_code":"MY",
    "gn:dem":11,
    "gn:feature_class":"P",
    "gn:feature_code":"PPL",
    "gn:name":"Kampung Pasir",
    "gn:population":0,
    "gn:timezone":"Asia/Kuala_Lumpur",
    "iso:country":"MY",
    "name:msa_x_preferred":[
        "Kampung Pasir"
    ],
    "name:und_x_variant":[
        "Kampong Pasir"
    ],
    "wof:name":"Kampung Pasir",
    "wof:placetype":"locality"
},
  "geometry": {"coordinates":[103.6972,1.4971],"type":"Point"}
}