{
  "type": "Feature",
  "properties": {
    "gn:admin1_code":"11",
    "gn:asciiname":"Kampong Tematu",
    "gn:cc2":"MY",
    "gn:country_code":"MY",
    "gn:dem":18,
    "gn:feature_class":"P",
    "gn:feature_code":"PPL",
    "gn:name":"Kampong Tematu",
    "gn:population":0,
    "gn:timezone":"Asia/Kuching",
    "iso:country":"MY",
    "name:und_x_variant":[
        "Kampong Semarang",
        "Kampong Tematu"
    ],
    "wof:name":"Kampong Tematu",
    "wof:placetype":"locality"
},
  "geometry": {"coordinates":[110.28333000000001,1.46667],"type":"Point"}
}