{
  "type": "Feature",
  "properties": {
    "gn:admin1_code":"2",
    "gn:asciiname":"Kampung Kepala Kerbau",
    "gn:cc2":"MY",
    "gn:country_code":"MY",
    "gn:dem":27,
    "gn:feature_class":"P",
    "gn:feature_code":"PPL",
    "gn:name":"Kampung Kepala Kerbau",
    "gn:population":0,
    "gn:timezone":"Asia/Kuala_Lumpur",
    "iso:country":"MY",
    "name:msa_x_preferred":[
        "Kampung Kepala Kerbau"
    ],
    "name:und_x_variant":[
        "Kampong Kepala Kerbau"
    ],
    "wof:name":"Kampung Kepala Kerbau",
    "wof:placetype":"locality"
},
  "geometry": {"coordinates":[100.40106,6.4227],"type":"Point"}
}