{
  "type": "Feature",
  "properties": {
    "gn:admin1_code":"7",
    "gn:asciiname":"Kampung Sungai Manik",
    "gn:country_code":"MY",
    "gn:dem":4,
    "gn:feature_class":"P",
    "gn:feature_code":"PPL",
    "gn:name":"Kampung Sungai Manik",
    "gn:population":0,
    "gn:timezone":"Asia/Kuala_Lumpur",
    "iso:country":"MY",
    "name:msa_x_preferred":[
        "Kampung Sungai Manik"
    ],
    "name:und_x_variant":[
        "Kampong Sungai Manik"
    ],
    "wof:name":"Kampung Sungai Manik",
    "wof:placetype":"locality"
},
  "geometry": {"coordinates":[101.0273,4.0481],"type":"Point"}
}