{
  "type": "Feature",
  "properties": {
    "gn:admin1_code":"5.0",
    "gn:asciiname":"Rumah Rakyat Sungai Rotan Dua",
    "gn:country_code":"MY",
    "gn:dem":106,
    "gn:feature_class":"P",
    "gn:feature_code":"PPL",
    "gn:name":"Rumah Rakyat Sungai Rotan Dua",
    "gn:population":0,
    "gn:timezone":"Asia/Kuala_Lumpur",
    "iso:country":"MY",
    "name:msa_x_preferred":[
        "Rumah Rakyat Sungai Rotan Dua"
    ],
    "wof:name":"Rumah Rakyat Sungai Rotan Dua",
    "wof:placetype":"locality"
},
  "geometry": {"coordinates":[102.1084,3.0045],"type":"Point"}
}