{
  "type": "Feature",
  "properties": {
    "gn:admin1_code":"16",
    "gn:asciiname":"Kampung Sulad",
    "gn:country_code":"MY",
    "gn:dem":552,
    "gn:feature_class":"P",
    "gn:feature_code":"PPL",
    "gn:name":"Kampung Sulad",
    "gn:population":0,
    "gn:timezone":"Asia/Kuching",
    "iso:country":"MY",
    "name:msa_x_preferred":[
        "Kampung Sulad"
    ],
    "name:und_x_variant":[
        "Kampong Sulad"
    ],
    "wof:name":"Kampung Sulad",
    "wof:placetype":"locality"
},
  "geometry": {"coordinates":[116.2499,5.8766],"type":"Point"}
}