{
  "type": "Feature",
  "properties": {
    "gn:admin1_code":"13.0",
    "gn:asciiname":"Kampung Ru Renggeh",
    "gn:country_code":"MY",
    "gn:dem":6,
    "gn:feature_class":"P",
    "gn:feature_code":"PPL",
    "gn:name":"Kampung Ru Renggeh",
    "gn:population":0,
    "gn:timezone":"Asia/Kuala_Lumpur",
    "iso:country":"MY",
    "name:msa_x_preferred":[
        "Kampung Ru Renggeh"
    ],
    "wof:name":"Kampung Ru Renggeh",
    "wof:placetype":"locality"
},
  "geometry": {"coordinates":[103.18219999999999,5.256],"type":"Point"}
}