{
  "type": "Feature",
  "properties": {
    "gn:admin1_code":"4",
    "gn:asciiname":"Kampung Jasin",
    "gn:country_code":"MY",
    "gn:dem":45,
    "gn:feature_class":"P",
    "gn:feature_code":"PPL",
    "gn:name":"Kampung Jasin",
    "gn:population":0,
    "gn:timezone":"Asia/Kuala_Lumpur",
    "iso:country":"MY",
    "name:msa_x_preferred":[
        "Kampung Jasin"
    ],
    "name:und_x_variant":[
        "Kampong Jasin"
    ],
    "wof:name":"Kampung Jasin",
    "wof:placetype":"locality"
},
  "geometry": {"coordinates":[102.4289,2.3061],"type":"Point"}
}