{
  "type": "Feature",
  "properties": {
    "gn:admin1_code":"13.0",
    "gn:asciiname":"Kampung Ajil",
    "gn:country_code":"MY",
    "gn:dem":26,
    "gn:feature_class":"P",
    "gn:feature_code":"PPL",
    "gn:name":"Kampung Ajil",
    "gn:population":0,
    "gn:timezone":"Asia/Kuala_Lumpur",
    "iso:country":"MY",
    "name:msa_x_preferred":[
        "Kampung Ajil"
    ],
    "wof:name":"Kampung Ajil",
    "wof:placetype":"locality"
},
  "geometry": {"coordinates":[103.0933,5.0895],"type":"Point"}
}