{
  "type": "Feature",
  "properties": {
    "gn:admin1_code":"11",
    "gn:asciiname":"Kampung Bayur",
    "gn:country_code":"MY",
    "gn:dem":95,
    "gn:feature_class":"P",
    "gn:feature_code":"PPL",
    "gn:name":"Kampung Bayur",
    "gn:population":0,
    "gn:timezone":"Asia/Kuching",
    "iso:country":"MY",
    "name:und_x_variant":[
        "Kampong Braang Bayur",
        "Kampong Brang Payong",
        "Kampong Brang Payang",
        "Kampong Braang Payang",
        "Kampong Beraang Bayur",
        "Kampung Bayur"
    ],
    "wof:name":"Kampung Bayur",
    "wof:placetype":"locality"
},
  "geometry": {"coordinates":[110.29344,1.24248],"type":"Point"}
}