{
  "type": "Feature",
  "properties": {
    "gn:admin1_code":"13.0",
    "gn:asciiname":"Kampung Penarik",
    "gn:cc2":"MY",
    "gn:country_code":"MY",
    "gn:dem":9,
    "gn:feature_class":"P",
    "gn:feature_code":"PPL",
    "gn:name":"Kampung Penarik",
    "gn:population":0,
    "gn:timezone":"Asia/Kuala_Lumpur",
    "iso:country":"MY",
    "name:msa_x_preferred":[
        "Kampung Penarik"
    ],
    "name:und_x_variant":[
        "Kampong Penarek",
        "Kampong Penarik"
    ],
    "wof:name":"Kampung Penarik",
    "wof:placetype":"locality"
},
  "geometry": {"coordinates":[102.81556999999999,5.60501],"type":"Point"}
}