{
  "type": "Feature",
  "properties": {
    "gn:admin1_code":"16",
    "gn:asciiname":"Kampung Ratu",
    "gn:country_code":"MY",
    "gn:dem":22,
    "gn:feature_class":"P",
    "gn:feature_code":"PPL",
    "gn:name":"Kampung Ratu",
    "gn:population":0,
    "gn:timezone":"Asia/Kuching",
    "iso:country":"MY",
    "name:msa_x_preferred":[
        "Kampung Ratu"
    ],
    "name:und_x_variant":[
        "Kampong Ratu"
    ],
    "wof:name":"Kampung Ratu",
    "wof:placetype":"locality"
},
  "geometry": {"coordinates":[116.1703,6.0578],"type":"Point"}
}