{
  "type": "Feature",
  "properties": {
    "gn:admin1_code":"1.0",
    "gn:asciiname":"Kampung Perpat Pasir",
    "gn:country_code":"MY",
    "gn:dem":11,
    "gn:feature_class":"P",
    "gn:feature_code":"PPL",
    "gn:name":"Kampung Perpat Pasir",
    "gn:population":0,
    "gn:timezone":"Asia/Kuala_Lumpur",
    "iso:country":"MY",
    "name:msa_x_preferred":[
        "Kampung Perpat Pasir"
    ],
    "wof:name":"Kampung Perpat Pasir",
    "wof:placetype":"locality"
},
  "geometry": {"coordinates":[103.501,1.2943],"type":"Point"}
}