{
  "type": "Feature",
  "properties": {
    "gn:admin1_code":"7",
    "gn:asciiname":"Kampung Sungai Nipah Baroh",
    "gn:country_code":"MY",
    "gn:dem":7,
    "gn:feature_class":"P",
    "gn:feature_code":"PPL",
    "gn:name":"Kampung Sungai Nipah Baroh",
    "gn:population":0,
    "gn:timezone":"Asia/Kuala_Lumpur",
    "iso:country":"MY",
    "name:msa_x_preferred":[
        "Kampung Sungai Nipah Baroh"
    ],
    "name:und_x_variant":[
        "Kampong Sungei Nipah",
        "Kampong Sungai Nipah Baroh"
    ],
    "wof:name":"Kampung Sungai Nipah Baroh",
    "wof:placetype":"locality"
},
  "geometry": {"coordinates":[100.7454,3.9831],"type":"Point"}
}