{
  "type": "Feature",
  "properties": {
    "gn:admin1_code":"11",
    "gn:asciiname":"Rumah Imba",
    "gn:country_code":"MY",
    "gn:dem":94,
    "gn:feature_class":"P",
    "gn:feature_code":"PPL",
    "gn:name":"Rumah Imba",
    "gn:population":0,
    "gn:timezone":"Asia/Kuching",
    "iso:country":"MY",
    "wof:name":"Rumah Imba",
    "wof:placetype":"locality"
},
  "geometry": {"coordinates":[112.66667,1.71667],"type":"Point"}
}