{
  "type": "Feature",
  "properties": {
    "gn:admin1_code":"8",
    "gn:asciiname":"Kampung Kubang Bodoh",
    "gn:cc2":"MY",
    "gn:country_code":"MY",
    "gn:dem":8,
    "gn:feature_class":"P",
    "gn:feature_code":"PPL",
    "gn:name":"Kampung Kubang Bodoh",
    "gn:population":0,
    "gn:timezone":"Asia/Kuala_Lumpur",
    "iso:country":"MY",
    "name:msa_x_preferred":[
        "Kampung Kubang Bodoh"
    ],
    "name:und_x_variant":[
        "Kampong Kubang Badak"
    ],
    "wof:name":"Kampung Kubang Bodoh",
    "wof:placetype":"locality"
},
  "geometry": {"coordinates":[100.26967,6.39035],"type":"Point"}
}