{
  "type": "Feature",
  "properties": {
    "gn:admin1_code":"6.0",
    "gn:asciiname":"Kampung Tanjung Agas",
    "gn:country_code":"MY",
    "gn:dem":44,
    "gn:feature_class":"P",
    "gn:feature_code":"PPL",
    "gn:name":"Kampung Tanjung Agas",
    "gn:population":0,
    "gn:timezone":"Asia/Kuala_Lumpur",
    "iso:country":"MY",
    "name:msa_x_preferred":[
        "Kampung Tanjung Agas"
    ],
    "wof:name":"Kampung Tanjung Agas",
    "wof:placetype":"locality"
},
  "geometry": {"coordinates":[103.02809999999999,3.9024],"type":"Point"}
}