{
  "type": "Feature",
  "properties": {
    "gn:admin1_code":"5.0",
    "gn:asciiname":"New Village",
    "gn:country_code":"MY",
    "gn:dem":12,
    "gn:feature_class":"P",
    "gn:feature_code":"PPL",
    "gn:name":"New Village",
    "gn:population":0,
    "gn:timezone":"Asia/Kuala_Lumpur",
    "iso:country":"MY",
    "name:msa_x_preferred":[
        "New Village"
    ],
    "wof:name":"New Village",
    "wof:placetype":"locality"
},
  "geometry": {"coordinates":[101.7633,2.6746],"type":"Point"}
}