{
  "type": "Feature",
  "properties": {
    "gn:admin1_code":"13.0",
    "gn:asciiname":"Kampung Wakaf Kembar",
    "gn:country_code":"MY",
    "gn:dem":10,
    "gn:feature_class":"P",
    "gn:feature_code":"PPL",
    "gn:name":"Kampung Wakaf Kembar",
    "gn:population":0,
    "gn:timezone":"Asia/Kuala_Lumpur",
    "iso:country":"MY",
    "name:msa_x_preferred":[
        "Kampung Wakaf Kembar"
    ],
    "wof:name":"Kampung Wakaf Kembar",
    "wof:placetype":"locality"
},
  "geometry": {"coordinates":[103.1099,5.3118],"type":"Point"}
}