{
  "type": "Feature",
  "properties": {
    "gn:admin1_code":"6",
    "gn:asciiname":"Kampong Malim",
    "gn:country_code":"MY",
    "gn:dem":165,
    "gn:feature_class":"P",
    "gn:feature_code":"PPL",
    "gn:name":"Kampong Malim",
    "gn:population":0,
    "gn:timezone":"Asia/Kuala_Lumpur",
    "iso:country":"MY",
    "wof:name":"Kampong Malim",
    "wof:placetype":"locality"
},
  "geometry": {"coordinates":[101.96666999999999,4.11667],"type":"Point"}
}