{
  "type": "Feature",
  "properties": {
    "gn:country":"MY",
    "gn:fcode":"PPL",
    "gn:pop":30280,
    "iso:country":"MY",
    "name:chi_x_preferred":[
        "\u5df4\u53e3"
    ],
    "name:dut_x_preferred":[
        "Bukit Bakri"
    ],
    "name:eng_x_preferred":[
        "Bukit Bakri"
    ],
    "name:jpn_x_preferred":[
        "\u30d0\u30af\u30ea"
    ],
    "name:may_x_preferred":[
        "Bakri"
    ],
    "name:msa_x_preferred":[
        "Bakri"
    ],
    "name:rus_x_preferred":[
        "\u0411\u0430\u043a\u0440\u0438"
    ],
    "name:spa_x_preferred":[
        "Bukit Bakri"
    ],
    "name:unk_x_variant":[
        "Bukit Bakri"
    ],
    "qs:name":"Bakri",
    "qs:name_adm0":"Malaysia",
    "qs:name_adm1":"Johor",
    "qs:photos":11,
    "qs:photos_1k":2,
    "qs:photos_9k":1,
    "qs:photos_9r":1,
    "qs:photos_all":11,
    "qs:photos_sr":1,
    "qs:placetype":"Town",
    "qs:pop_sr":"7",
    "wd:wordcount":52,
    "wof:name":"Bakri",
    "wof:placetype":"locality",
    "wof:population":30280
},
  "geometry": {"coordinates":[102.6527,2.0441],"type":"Point"}
}