{
  "type": "Feature",
  "properties": {
    "gn:country":"MY",
    "gn:fcode":"PPL",
    "gn:pop":0,
    "iso:country":"MY",
    "name:msa_x_preferred":[
        "Kampung Kepayang"
    ],
    "name:unk_x_variant":[
        "Kampong Kebayang"
    ],
    "qs:name":"Kampung Kepayang",
    "qs:name_adm0":"Malaysia",
    "qs:name_adm1":"Perak",
    "qs:photos":1,
    "qs:photos_1k":1,
    "qs:photos_9k":1,
    "qs:photos_9r":1,
    "qs:photos_all":1,
    "qs:photos_sr":1,
    "qs:placetype":"Suburb",
    "qs:pop_sr":"0",
    "wof:name":"Kampung Kepayang",
    "wof:placetype":"neighbourhood",
    "wof:population":0
},
  "geometry": {"coordinates":[101.1005,4.6124],"type":"Point"}
}