{
  "type": "Feature",
  "properties": {
    "gn:admin1_code":"2.0",
    "gn:asciiname":"Kampung Pokok Asam",
    "gn:country_code":"MY",
    "gn:dem":25,
    "gn:feature_class":"P",
    "gn:feature_code":"PPL",
    "gn:name":"Kampung Pokok Asam",
    "gn:population":0,
    "gn:timezone":"Asia/Kuala_Lumpur",
    "iso:country":"MY",
    "wof:name":"Kampung Pokok Asam",
    "wof:placetype":"locality"
},
  "geometry": {"coordinates":[99.84105,6.3301],"type":"Point"}
}