{
  "type": "Feature",
  "properties": {
    "gn:admin1_code":"16",
    "gn:asciiname":"Kampung Tambulaung",
    "gn:country_code":"MY",
    "gn:dem":74,
    "gn:feature_class":"P",
    "gn:feature_code":"PPL",
    "gn:name":"Kampung Tambulaung",
    "gn:population":0,
    "gn:timezone":"Asia/Kuching",
    "iso:country":"MY",
    "name:msa_x_preferred":[
        "Kampung Tambulaung"
    ],
    "name:und_x_variant":[
        "Kampong Tambulaung"
    ],
    "wof:name":"Kampung Tambulaung",
    "wof:placetype":"locality"
},
  "geometry": {"coordinates":[116.2317,6.0951],"type":"Point"}
}