{
  "type": "Feature",
  "properties": {
    "gn:country":"MY",
    "gn:fcode":"ADM3",
    "gn:population":0,
    "iso:country":"MY",
    "name:ceb_x_preferred":[
        "Serdang"
    ],
    "name:ind_x_preferred":[
        "Serdang"
    ],
    "name:msa_x_preferred":[
        "Serdang"
    ],
    "name:nld_x_preferred":[
        "Serdang"
    ],
    "name:swe_x_preferred":[
        "Serdang"
    ],
    "qs_pg:aaroncc":"MY",
    "qs_pg:gn_country":"MY",
    "qs_pg:gn_fcode":"ADM3",
    "qs_pg:gn_pop":0,
    "qs_pg:name":"Serdang",
    "qs_pg:photos_9r":0,
    "qs_pg:photos_sr":0,
    "qs_pg:pop_sr":0,
    "qs_pg:qs_pg_placetype":"localadmin",
    "wof:name":"Serdang",
    "wof:placetype":"localadmin"
},
  "geometry": {"coordinates":[100.63287,5.21002],"type":"Point"}
}