{
  "type": "Feature",
  "properties": {
    "gn:admin1_code":"12.0",
    "gn:asciiname":"Taman Ampang Pechah",
    "gn:country_code":"MY",
    "gn:dem":54,
    "gn:feature_class":"P",
    "gn:feature_code":"PPL",
    "gn:name":"Taman Ampang Pechah",
    "gn:population":0,
    "gn:timezone":"Asia/Kuala_Lumpur",
    "iso:country":"MY",
    "name:msa_x_preferred":[
        "Taman Ampang Pechah"
    ],
    "wof:name":"Taman Ampang Pechah",
    "wof:placetype":"locality"
},
  "geometry": {"coordinates":[101.6592,3.548],"type":"Point"}
}