{
  "type": "Feature",
  "properties": {
    "gn:admin1_code":"16",
    "gn:asciiname":"Kampong Pairgon",
    "gn:country_code":"MY",
    "gn:dem":78,
    "gn:feature_class":"P",
    "gn:feature_code":"PPL",
    "gn:name":"Kampong Pairgon",
    "gn:population":0,
    "gn:timezone":"Asia/Kuching",
    "iso:country":"MY",
    "wof:name":"Kampong Pairgon",
    "wof:placetype":"locality"
},
  "geometry": {"coordinates":[117.31667,4.35],"type":"Point"}
}