{
  "type": "Feature",
  "properties": {
    "gn:admin1_code":"16.0",
    "gn:asciiname":"Bambangan",
    "gn:cc2":"MY",
    "gn:country_code":"MY",
    "gn:dem":17,
    "gn:feature_class":"P",
    "gn:feature_code":"PPL",
    "gn:name":"Bambangan",
    "gn:population":0,
    "gn:timezone":"Asia/Kuching",
    "iso:country":"MY",
    "name:und_x_variant":[
        "Kampong Bambangan",
        "Bambangan"
    ],
    "wof:name":"Bambangan",
    "wof:placetype":"locality"
},
  "geometry": {"coordinates":[115.38333,5.33333],"type":"Point"}
}