{
  "type": "Feature",
  "properties": {
    "gn:admin1_code":"11.0",
    "gn:asciiname":"Batu Bebini Atas",
    "gn:country_code":"MY",
    "gn:dem":72,
    "gn:feature_class":"P",
    "gn:feature_code":"PPL",
    "gn:name":"Batu Bebini Atas",
    "gn:population":0,
    "gn:timezone":"Asia/Kuching",
    "iso:country":"MY",
    "name:und_x_variant":[
        "Batu Bebini"
    ],
    "wof:name":"Batu Bebini Atas",
    "wof:placetype":"locality"
},
  "geometry": {"coordinates":[111.8057,1.04011],"type":"Point"}
}