{
  "type": "Feature",
  "properties": {
    "gn:admin1_code":"6.0",
    "gn:asciiname":"Kampung Kubang Rusa",
    "gn:country_code":"MY",
    "gn:dem":147,
    "gn:feature_class":"P",
    "gn:feature_code":"PPL",
    "gn:name":"Kampung Kubang Rusa",
    "gn:population":0,
    "gn:timezone":"Asia/Kuala_Lumpur",
    "iso:country":"MY",
    "name:msa_x_preferred":[
        "Kampung Kubang Rusa"
    ],
    "wof:name":"Kampung Kubang Rusa",
    "wof:placetype":"locality"
},
  "geometry": {"coordinates":[101.9901,4.598],"type":"Point"}
}