{
  "type": "Feature",
  "properties": {
    "gn:admin1_code":"1.0",
    "gn:asciiname":"Kampung Burok Bakul",
    "gn:country_code":"MY",
    "gn:dem":12,
    "gn:feature_class":"P",
    "gn:feature_code":"PPL",
    "gn:name":"Kampung Burok Bakul",
    "gn:population":0,
    "gn:timezone":"Asia/Kuala_Lumpur",
    "iso:country":"MY",
    "name:msa_x_preferred":[
        "Kampung Burok Bakul"
    ],
    "wof:name":"Kampung Burok Bakul",
    "wof:placetype":"locality"
},
  "geometry": {"coordinates":[102.7884,2.1174],"type":"Point"}
}