{
  "type": "Feature",
  "properties": {
    "gn:admin1_code":"6",
    "gn:asciiname":"Kampung Bukit Dinding",
    "gn:country_code":"MY",
    "gn:dem":53,
    "gn:feature_class":"P",
    "gn:feature_code":"PPL",
    "gn:name":"Kampung Bukit Dinding",
    "gn:population":0,
    "gn:timezone":"Asia/Kuala_Lumpur",
    "iso:country":"MY",
    "name:msa_x_preferred":[
        "Kampung Bukit Dinding"
    ],
    "name:und_x_variant":[
        "Kampong Bukit Dinding"
    ],
    "wof:name":"Kampung Bukit Dinding",
    "wof:placetype":"locality"
},
  "geometry": {"coordinates":[102.3785,3.8458],"type":"Point"}
}