{
  "type": "Feature",
  "properties": {
    "gn:admin1_code":"7",
    "gn:asciiname":"Kampung Sumpitan",
    "gn:cc2":"MY",
    "gn:country_code":"MY",
    "gn:dem":95,
    "gn:feature_class":"P",
    "gn:feature_code":"PPL",
    "gn:name":"Kampung Sumpitan",
    "gn:population":0,
    "gn:timezone":"Asia/Kuala_Lumpur",
    "iso:country":"MY",
    "name:msa_x_preferred":[
        "Kampung Sumpitan"
    ],
    "name:und_x_variant":[
        "Kampong Sumpitan"
    ],
    "wof:name":"Kampung Sumpitan",
    "wof:placetype":"locality"
},
  "geometry": {"coordinates":[100.99124,5.16657],"type":"Point"}
}