{
  "type": "Feature",
  "properties": {
    "gn:admin1_code":"13.0",
    "gn:asciiname":"Kampung Pusu Tinggi",
    "gn:country_code":"MY",
    "gn:dem":12,
    "gn:feature_class":"P",
    "gn:feature_code":"PPL",
    "gn:name":"Kampung Pusu Tinggi",
    "gn:population":0,
    "gn:timezone":"Asia/Kuala_Lumpur",
    "iso:country":"MY",
    "name:msa_x_preferred":[
        "Kampung Pusu Tinggi"
    ],
    "wof:name":"Kampung Pusu Tinggi",
    "wof:placetype":"locality"
},
  "geometry": {"coordinates":[102.49527,5.77947],"type":"Point"}
}