{
  "type": "Feature",
  "properties": {
    "gn:admin1_code":"7",
    "gn:asciiname":"Sakai Village",
    "gn:country_code":"MY",
    "gn:dem":105,
    "gn:feature_class":"P",
    "gn:feature_code":"PPL",
    "gn:name":"Sakai Village",
    "gn:population":0,
    "gn:timezone":"Asia/Kuala_Lumpur",
    "iso:country":"MY",
    "wof:name":"Sakai Village",
    "wof:placetype":"locality"
},
  "geometry": {"coordinates":[101.18333,4.46667],"type":"Point"}
}