{
  "type": "Feature",
  "properties": {
    "gn:country":"MY",
    "gn:fcode":"PPL",
    "gn:population":0,
    "iso:country":"MY",
    "name:und_x_variant":[
        "Sungei Burong"
    ],
    "qs:name":"Kampong Sungai Burong",
    "qs:name_adm0":"Malaysia",
    "qs:name_adm1":"Pulau Pinang",
    "qs:photos":25,
    "qs:photos_1k":5,
    "qs:photos_9k":1,
    "qs:photos_9r":1,
    "qs:photos_all":25,
    "qs:photos_sr":1,
    "qs:placetype":"Town",
    "qs:pop_sr":"0",
    "wof:name":"Kampong Sungai Burong",
    "wof:placetype":"locality",
    "wof:population":0
},
  "geometry": {"coordinates":[100.20732,5.34367],"type":"Point"}
}