{
  "type": "Feature",
  "properties": {
    "gn:admin1_code":"0.0",
    "gn:asciiname":"Kampung Perlis",
    "gn:country_code":"MY",
    "gn:dem":56,
    "gn:feature_class":"P",
    "gn:feature_code":"PPL",
    "gn:name":"Kampung Perlis",
    "gn:population":0,
    "gn:timezone":"Asia/Kuala_Lumpur",
    "iso:country":"MY",
    "wof:name":"Kampung Perlis",
    "wof:placetype":"locality"
},
  "geometry": {"coordinates":[103.03333000000001,4.61667],"type":"Point"}
}