{
  "type": "Feature",
  "properties": {
    "gn:admin1_code":"7.0",
    "gn:asciiname":"Kampung Parit Delapan Utara",
    "gn:country_code":"MY",
    "gn:dem":7,
    "gn:feature_class":"P",
    "gn:feature_code":"PPL",
    "gn:name":"Kampung Parit Delapan Utara",
    "gn:population":0,
    "gn:timezone":"Asia/Kuala_Lumpur",
    "iso:country":"MY",
    "name:msa_x_preferred":[
        "Kampung Parit Delapan Utara"
    ],
    "name:und_x_variant":[
        "Kampung Parit 8 Utara"
    ],
    "wof:name":"Kampung Parit Delapan Utara",
    "wof:placetype":"locality"
},
  "geometry": {"coordinates":[100.71299999999999,3.9575],"type":"Point"}
}