{
  "type": "Feature",
  "properties": {
    "gn:admin1_code":"1.0",
    "gn:asciiname":"Kampung Parit Haji Alias",
    "gn:country_code":"MY",
    "gn:dem":10,
    "gn:feature_class":"P",
    "gn:feature_code":"PPL",
    "gn:name":"Kampung Parit Haji Alias",
    "gn:population":0,
    "gn:timezone":"Asia/Kuala_Lumpur",
    "iso:country":"MY",
    "name:msa_x_preferred":[
        "Kampung Parit Haji Alias"
    ],
    "wof:name":"Kampung Parit Haji Alias",
    "wof:placetype":"locality"
},
  "geometry": {"coordinates":[103.35809999999999,1.602],"type":"Point"}
}