{
  "type": "Feature",
  "properties": {
    "gn:country":"MY",
    "gn:fcode":"PPL",
    "gn:pop":0,
    "iso:country":"MY",
    "name:msa_x_preferred":[
        "Kampung Datuk"
    ],
    "name:unk_x_variant":[
        "Kampong Datoh"
    ],
    "qs:name":"Kampong Datok",
    "qs:name_adm0":"Malaysia",
    "qs:name_adm1":"Kuala Lumpur",
    "qs:photos":11,
    "qs:photos_1k":2,
    "qs:photos_9k":1,
    "qs:photos_9r":1,
    "qs:photos_all":11,
    "qs:photos_sr":1,
    "qs:placetype":"Suburb",
    "qs:pop_sr":"0",
    "wof:name":"Kampong Datok",
    "wof:placetype":"neighbourhood",
    "wof:population":0
},
  "geometry": {"coordinates":[102.66670000000001,3.0074],"type":"Point"}
}