{
  "type": "Feature",
  "properties": {
    "gn:admin1_code":"16.0",
    "gn:asciiname":"Kampung Panitian",
    "gn:country_code":"MY",
    "gn:dem":38,
    "gn:feature_class":"P",
    "gn:feature_code":"PPL",
    "gn:name":"Kampung Panitian",
    "gn:population":0,
    "gn:timezone":"Asia/Kuching",
    "iso:country":"MY",
    "name:msa_x_preferred":[
        "Kampung Panitian"
    ],
    "name:und_x_variant":[
        "Panitian"
    ],
    "wof:name":"Kampung Panitian",
    "wof:placetype":"locality"
},
  "geometry": {"coordinates":[115.8395,5.4162],"type":"Point"}
}