{
  "type": "Feature",
  "properties": {
    "gn:admin1_code":"5",
    "gn:asciiname":"Kampung Pelangai Ulu",
    "gn:country_code":"MY",
    "gn:dem":89,
    "gn:feature_class":"P",
    "gn:feature_code":"PPL",
    "gn:name":"Kampung Pelangai Ulu",
    "gn:population":0,
    "gn:timezone":"Asia/Kuala_Lumpur",
    "iso:country":"MY",
    "name:msa_x_preferred":[
        "Kampung Pelangai Ulu"
    ],
    "name:und_x_variant":[
        "Kampong Pelangai Ulu"
    ],
    "wof:name":"Kampung Pelangai Ulu",
    "wof:placetype":"locality"
},
  "geometry": {"coordinates":[102.2568,2.7665],"type":"Point"}
}