{
  "type": "Feature",
  "properties": {
    "gn:admin1_code":"11",
    "gn:asciiname":"Rumah Jandah",
    "gn:country_code":"MY",
    "gn:dem":14,
    "gn:feature_class":"P",
    "gn:feature_code":"PPL",
    "gn:name":"Rumah Jandah",
    "gn:population":0,
    "gn:timezone":"Asia/Kuching",
    "iso:country":"MY",
    "wof:name":"Rumah Jandah",
    "wof:placetype":"locality"
},
  "geometry": {"coordinates":[111.98333,2.15],"type":"Point"}
}