{
  "type": "Feature",
  "properties": {
    "gn:admin1_code":"1.0",
    "gn:asciiname":"Kampung Parit Rambai",
    "gn:country_code":"MY",
    "gn:dem":12,
    "gn:feature_class":"P",
    "gn:feature_code":"PPL",
    "gn:name":"Kampung Parit Rambai",
    "gn:population":0,
    "gn:timezone":"Asia/Kuala_Lumpur",
    "iso:country":"MY",
    "name:msa_x_preferred":[
        "Kampung Parit Rambai"
    ],
    "wof:name":"Kampung Parit Rambai",
    "wof:placetype":"locality"
},
  "geometry": {"coordinates":[103.43680000000001,1.4459],"type":"Point"}
}