{
  "type": "Feature",
  "properties": {
    "gn:admin1_code":"7.0",
    "gn:asciiname":"Taman Hijau",
    "gn:country_code":"MY",
    "gn:dem":7,
    "gn:feature_class":"P",
    "gn:feature_code":"PPL",
    "gn:name":"Taman Hijau",
    "gn:population":0,
    "gn:timezone":"Asia/Kuala_Lumpur",
    "iso:country":"MY",
    "name:msa_x_preferred":[
        "Taman Hijau"
    ],
    "wof:name":"Taman Hijau",
    "wof:placetype":"locality"
},
  "geometry": {"coordinates":[100.6964,4.2012],"type":"Point"}
}