{
  "type": "Feature",
  "properties": {
    "gn:admin1_code":"1",
    "gn:asciiname":"Kampung Sengkang Batu Lapan Belas",
    "gn:country_code":"MY",
    "gn:dem":13,
    "gn:feature_class":"P",
    "gn:feature_code":"PPL",
    "gn:name":"Kampung Sengkang Batu Lapan Belas",
    "gn:population":0,
    "gn:timezone":"Asia/Kuala_Lumpur",
    "iso:country":"MY",
    "name:msa_x_preferred":[
        "Kampung Sengkang Batu Lapan Belas"
    ],
    "name:und_x_variant":[
        "Kampong Sengkang Batu Nineteen",
        "Kampung Sengkang Batu 18"
    ],
    "wof:name":"Kampung Sengkang Batu Lapan Belas",
    "wof:placetype":"locality"
},
  "geometry": {"coordinates":[102.67570000000001,2.2468],"type":"Point"}
}