{
  "type": "Feature",
  "properties": {
    "gn:admin1_code":"1.0",
    "gn:asciiname":"Kemajuan Tanah Pasak",
    "gn:country_code":"MY",
    "gn:dem":16,
    "gn:feature_class":"P",
    "gn:feature_code":"PPL",
    "gn:name":"Kemajuan Tanah Pasak",
    "gn:population":0,
    "gn:timezone":"Asia/Kuala_Lumpur",
    "iso:country":"MY",
    "name:msa_x_preferred":[
        "Kemajuan Tanah Pasak"
    ],
    "wof:name":"Kemajuan Tanah Pasak",
    "wof:placetype":"locality"
},
  "geometry": {"coordinates":[103.958,1.71],"type":"Point"}
}