{
  "type": "Feature",
  "properties": {
    "gn:admin1_code":"1.0",
    "gn:asciiname":"Beradin",
    "gn:country_code":"MY",
    "gn:dem":43,
    "gn:feature_class":"P",
    "gn:feature_code":"PPL",
    "gn:name":"Beradin",
    "gn:population":0,
    "gn:timezone":"Asia/Kuala_Lumpur",
    "iso:country":"MY",
    "name:msa_x_preferred":[
        "Beradin"
    ],
    "wof:name":"Beradin",
    "wof:placetype":"locality"
},
  "geometry": {"coordinates":[103.17319999999999,2.2117],"type":"Point"}
}