{
  "type": "Feature",
  "properties": {
    "gn:admin1_code":"6.0",
    "gn:asciiname":"Kampung Merang",
    "gn:country_code":"MY",
    "gn:dem":110,
    "gn:feature_class":"P",
    "gn:feature_code":"PPL",
    "gn:name":"Kampung Merang",
    "gn:population":0,
    "gn:timezone":"Asia/Kuala_Lumpur",
    "iso:country":"MY",
    "name:msa_x_preferred":[
        "Kampung Merang"
    ],
    "wof:name":"Kampung Merang",
    "wof:placetype":"locality"
},
  "geometry": {"coordinates":[101.90779999999999,4.0342],"type":"Point"}
}