{
  "type": "Feature",
  "properties": {
    "gn:admin1_code":"13",
    "gn:asciiname":"Kampung Rantau Abang",
    "gn:country_code":"MY",
    "gn:dem":12,
    "gn:feature_class":"P",
    "gn:feature_code":"PPL",
    "gn:name":"Kampung Rantau Abang",
    "gn:population":0,
    "gn:timezone":"Asia/Kuala_Lumpur",
    "iso:country":"MY",
    "name:msa_x_preferred":[
        "Kampung Rantau Abang"
    ],
    "name:und_x_variant":[
        "Kampong Rantau Abang"
    ],
    "wof:name":"Kampung Rantau Abang",
    "wof:placetype":"locality"
},
  "geometry": {"coordinates":[103.39360000000001,4.8648],"type":"Point"}
}