{
  "type": "Feature",
  "properties": {
    "gn:admin1_code":"11",
    "gn:asciiname":"Kampung Selabat",
    "gn:country_code":"MY",
    "gn:dem":-9999,
    "gn:feature_class":"P",
    "gn:feature_code":"PPL",
    "gn:name":"Kampung Selabat",
    "gn:population":0,
    "gn:timezone":"Asia/Kuching",
    "iso:country":"MY",
    "name:und_x_variant":[
        "Kampong Selabat",
        "Kampung Selaba"
    ],
    "wof:name":"Kampung Selabat",
    "wof:placetype":"locality"
},
  "geometry": {"coordinates":[110.48038,1.67908],"type":"Point"}
}