{
  "type": "Feature",
  "properties": {
    "gn:admin1_code":"1",
    "gn:asciiname":"Kampung Serong Darat",
    "gn:country_code":"MY",
    "gn:dem":12,
    "gn:feature_class":"P",
    "gn:feature_code":"PPL",
    "gn:name":"Kampung Serong Darat",
    "gn:population":0,
    "gn:timezone":"Asia/Kuala_Lumpur",
    "iso:country":"MY",
    "name:msa_x_preferred":[
        "Kampung Serong Darat"
    ],
    "name:und_x_variant":[
        "Kampong Serong"
    ],
    "wof:name":"Kampung Serong Darat",
    "wof:placetype":"locality"
},
  "geometry": {"coordinates":[103.498,1.3005],"type":"Point"}
}