{
  "type": "Feature",
  "properties": {
    "gn:admin1_code":"16.0",
    "gn:asciiname":"Kampung Tagibang",
    "gn:country_code":"MY",
    "gn:dem":702,
    "gn:feature_class":"P",
    "gn:feature_code":"PPL",
    "gn:name":"Kampung Tagibang",
    "gn:population":0,
    "gn:timezone":"Asia/Kuching",
    "iso:country":"MY",
    "name:msa_x_preferred":[
        "Kampung Tagibang"
    ],
    "wof:name":"Kampung Tagibang",
    "wof:placetype":"locality"
},
  "geometry": {"coordinates":[116.9442,6.342],"type":"Point"}
}