{
  "type": "Feature",
  "properties": {
    "gn:admin1_code":"2",
    "gn:asciiname":"Kampung Tanjung Setul",
    "gn:cc2":"MY",
    "gn:country_code":"MY",
    "gn:dem":13,
    "gn:feature_class":"P",
    "gn:feature_code":"PPL",
    "gn:name":"Kampung Tanjung Setul",
    "gn:population":0,
    "gn:timezone":"Asia/Kuala_Lumpur",
    "iso:country":"MY",
    "name:msa_x_preferred":[
        "Kampung Tanjung Setul"
    ],
    "name:und_x_variant":[
        "Kampong Tanjong Setul"
    ],
    "wof:name":"Kampung Tanjung Setul",
    "wof:placetype":"locality"
},
  "geometry": {"coordinates":[100.47789,5.91033],"type":"Point"}
}