{
  "type": "Feature",
  "properties": {
    "gn:admin1_code":"5",
    "gn:asciiname":"Kampung Sega",
    "gn:country_code":"MY",
    "gn:dem":36,
    "gn:feature_class":"P",
    "gn:feature_code":"PPL",
    "gn:name":"Kampung Sega",
    "gn:population":0,
    "gn:timezone":"Asia/Kuala_Lumpur",
    "iso:country":"MY",
    "name:msa_x_preferred":[
        "Kampung Sega"
    ],
    "name:und_x_variant":[
        "Kampong Sega"
    ],
    "wof:name":"Kampung Sega",
    "wof:placetype":"locality"
},
  "geometry": {"coordinates":[101.9344,2.6115],"type":"Point"}
}