{
  "type": "Feature",
  "properties": {
    "gn:country":"MY",
    "iso:country":"MY",
    "qs:name":"Taman Nlfcs",
    "qs:name_adm0":"Malaysia",
    "qs:name_adm1":"Negeri Sembilan",
    "qs:photos":153,
    "qs:photos_1k":31,
    "qs:photos_9k":1,
    "qs:photos_9r":4,
    "qs:photos_all":153,
    "qs:photos_sr":4,
    "qs:placetype":"Town",
    "qs:pop_sr":"0",
    "wof:name":"Taman Nlfcs",
    "wof:placetype":"locality"
},
  "geometry": {"coordinates":[101.796666,2.551111],"type":"Point"}
}