{
  "type": "Feature",
  "properties": {
    "gn:admin1_code":"16",
    "gn:asciiname":"Kampung Porrein",
    "gn:country_code":"MY",
    "gn:dem":758,
    "gn:feature_class":"P",
    "gn:feature_code":"PPL",
    "gn:name":"Kampung Porrein",
    "gn:population":0,
    "gn:timezone":"Asia/Kuching",
    "iso:country":"MY",
    "name:msa_x_preferred":[
        "Kampung Porrein"
    ],
    "name:und_x_variant":[
        "Kampong Porrein"
    ],
    "wof:name":"Kampung Porrein",
    "wof:placetype":"locality"
},
  "geometry": {"coordinates":[116.2504,5.9687],"type":"Point"}
}