{
  "type": "Feature",
  "properties": {
    "gn:admin1_code":"6.0",
    "gn:asciiname":"Perumahan Awam Sri Kemuning",
    "gn:country_code":"MY",
    "gn:dem":55,
    "gn:feature_class":"P",
    "gn:feature_code":"PPL",
    "gn:name":"Perumahan Awam Sri Kemuning",
    "gn:population":0,
    "gn:timezone":"Asia/Kuala_Lumpur",
    "iso:country":"MY",
    "name:msa_x_preferred":[
        "Perumahan Awam Sri Kemuning"
    ],
    "wof:name":"Perumahan Awam Sri Kemuning",
    "wof:placetype":"locality"
},
  "geometry": {"coordinates":[102.37569999999999,3.4601],"type":"Point"}
}