{
  "type": "Feature",
  "properties": {
    "gn:admin1_code":"2",
    "gn:asciiname":"Kampung Kelang Sagu",
    "gn:cc2":"MY",
    "gn:country_code":"MY",
    "gn:dem":28,
    "gn:feature_class":"P",
    "gn:feature_code":"PPL",
    "gn:name":"Kampung Kelang Sagu",
    "gn:population":0,
    "gn:timezone":"Asia/Kuala_Lumpur",
    "iso:country":"MY",
    "name:msa_x_preferred":[
        "Kampung Kelang Sagu"
    ],
    "name:und_x_variant":[
        "Kampong Kelang Sagu"
    ],
    "wof:name":"Kampung Kelang Sagu",
    "wof:placetype":"locality"
},
  "geometry": {"coordinates":[100.55242,5.37682],"type":"Point"}
}