{
  "type": "Feature",
  "properties": {
    "gn:admin1_code":"13",
    "gn:asciiname":"Kampong Wa Lama",
    "gn:cc2":"MY",
    "gn:country_code":"MY",
    "gn:dem":48,
    "gn:feature_class":"P",
    "gn:feature_code":"PPL",
    "gn:name":"Kampong Wa Lama",
    "gn:population":0,
    "gn:timezone":"Asia/Kuala_Lumpur",
    "iso:country":"MY",
    "name:und_x_variant":[
        "Kampong Wa",
        "Kampong Wah",
        "Kampong Wa Lama"
    ],
    "wof:name":"Kampong Wa Lama",
    "wof:placetype":"locality"
},
  "geometry": {"coordinates":[103.23333,4.81667],"type":"Point"}
}