{
  "type": "Feature",
  "properties": {
    "gn:admin1_code":"1",
    "gn:asciiname":"Kangkar Dohol",
    "gn:country_code":"MY",
    "gn:dem":31,
    "gn:feature_class":"P",
    "gn:feature_code":"PPL",
    "gn:name":"Kangkar Dohol",
    "gn:population":0,
    "gn:timezone":"Asia/Kuala_Lumpur",
    "iso:country":"MY",
    "name:msa_x_preferred":[
        "Kangkar Dohol"
    ],
    "wof:name":"Kangkar Dohol",
    "wof:placetype":"locality"
},
  "geometry": {"coordinates":[103.90309999999999,1.8954],"type":"Point"}
}