{
  "type": "Feature",
  "properties": {
    "gn:admin1_code":"16",
    "gn:asciiname":"Kampung Japar",
    "gn:country_code":"MY",
    "gn:dem":10,
    "gn:feature_class":"P",
    "gn:feature_code":"PPL",
    "gn:name":"Kampung Japar",
    "gn:population":0,
    "gn:timezone":"Asia/Kuching",
    "iso:country":"MY",
    "name:msa_x_preferred":[
        "Kampung Japar"
    ],
    "name:und_x_variant":[
        "Kampong Japar"
    ],
    "wof:name":"Kampung Japar",
    "wof:placetype":"locality"
},
  "geometry": {"coordinates":[115.58369999999999,5.4411],"type":"Point"}
}