{
  "type": "Feature",
  "properties": {
    "gn:admin1_code":"13",
    "gn:asciiname":"Kampung Telaga Papan",
    "gn:cc2":"MY",
    "gn:country_code":"MY",
    "gn:dem":10,
    "gn:feature_class":"P",
    "gn:feature_code":"PPL",
    "gn:name":"Kampung Telaga Papan",
    "gn:population":0,
    "gn:timezone":"Asia/Kuala_Lumpur",
    "iso:country":"MY",
    "name:msa_x_preferred":[
        "Kampung Telaga Papan"
    ],
    "name:und_x_variant":[
        "Kampong Telaga Papan"
    ],
    "wof:name":"Kampung Telaga Papan",
    "wof:placetype":"locality"
},
  "geometry": {"coordinates":[102.90557,5.53495],"type":"Point"}
}