{
  "type": "Feature",
  "properties": {
    "gn:admin1_code":"11",
    "gn:asciiname":"Rumah Sukang",
    "gn:cc2":"MY",
    "gn:country_code":"MY",
    "gn:dem":176,
    "gn:feature_class":"P",
    "gn:feature_code":"PPL",
    "gn:name":"Rumah Sukang",
    "gn:population":0,
    "gn:timezone":"Asia/Kuching",
    "iso:country":"MY",
    "name:und_x_variant":[
        "Rumah Sulang",
        "Rumah Sukang"
    ],
    "wof:name":"Rumah Sukang",
    "wof:placetype":"locality"
},
  "geometry": {"coordinates":[112.48333,1.86667],"type":"Point"}
}