{
  "type": "Feature",
  "properties": {
    "gn:admin1_code":"7",
    "gn:asciiname":"Kampung Matang Pasir",
    "gn:cc2":"MY",
    "gn:country_code":"MY",
    "gn:dem":15,
    "gn:feature_class":"P",
    "gn:feature_code":"PPL",
    "gn:name":"Kampung Matang Pasir",
    "gn:population":0,
    "gn:timezone":"Asia/Kuala_Lumpur",
    "iso:country":"MY",
    "name:msa_x_preferred":[
        "Kampung Matang Pasir"
    ],
    "name:und_x_variant":[
        "Kampong Matang Pasir"
    ],
    "wof:name":"Kampung Matang Pasir",
    "wof:placetype":"locality"
},
  "geometry": {"coordinates":[100.60167,5.07445],"type":"Point"}
}