{
  "type": "Feature",
  "properties": {
    "gn:admin1_code":"2",
    "gn:asciiname":"Kampung Tebok Sungai Kob",
    "gn:cc2":"MY",
    "gn:country_code":"MY",
    "gn:dem":47,
    "gn:feature_class":"P",
    "gn:feature_code":"PPL",
    "gn:name":"Kampung Tebok Sungai Kob",
    "gn:population":0,
    "gn:timezone":"Asia/Kuala_Lumpur",
    "iso:country":"MY",
    "name:msa_x_preferred":[
        "Kampung Tebok Sungai Kob"
    ],
    "name:und_x_variant":[
        "Kampong Tebok Sungai Kob"
    ],
    "wof:name":"Kampung Tebok Sungai Kob",
    "wof:placetype":"locality"
},
  "geometry": {"coordinates":[100.63139,5.43112],"type":"Point"}
}