{
  "type": "Feature",
  "properties": {
    "gn:admin1_code":"2",
    "gn:asciiname":"Kampung Sayak",
    "gn:cc2":"MY",
    "gn:country_code":"MY",
    "gn:dem":46,
    "gn:feature_class":"P",
    "gn:feature_code":"PPL",
    "gn:name":"Kampung Sayak",
    "gn:population":0,
    "gn:timezone":"Asia/Kuala_Lumpur",
    "iso:country":"MY",
    "name:msa_x_preferred":[
        "Kampung Sayak"
    ],
    "name:und_x_variant":[
        "Kampong Sayak"
    ],
    "wof:name":"Kampung Sayak",
    "wof:placetype":"locality"
},
  "geometry": {"coordinates":[100.72951,5.63977],"type":"Point"}
}