{
  "type": "Feature",
  "properties": {
    "gn:admin1_code":"13.0",
    "gn:asciiname":"Kampung Lubuk Susun",
    "gn:country_code":"MY",
    "gn:dem":25,
    "gn:feature_class":"P",
    "gn:feature_code":"PPL",
    "gn:name":"Kampung Lubuk Susun",
    "gn:population":0,
    "gn:timezone":"Asia/Kuala_Lumpur",
    "iso:country":"MY",
    "name:msa_x_preferred":[
        "Kampung Lubuk Susun"
    ],
    "wof:name":"Kampung Lubuk Susun",
    "wof:placetype":"locality"
},
  "geometry": {"coordinates":[102.47705000000001,5.61898],"type":"Point"}
}