{
  "type": "Feature",
  "properties": {
    "gn:admin1_code":"1.0",
    "gn:asciiname":"Kampung Batu Empat",
    "gn:country_code":"MY",
    "gn:dem":74,
    "gn:feature_class":"P",
    "gn:feature_code":"PPL",
    "gn:name":"Kampung Batu Empat",
    "gn:population":0,
    "gn:timezone":"Asia/Kuala_Lumpur",
    "iso:country":"MY",
    "name:msa_x_preferred":[
        "Kampung Batu Empat"
    ],
    "wof:name":"Kampung Batu Empat",
    "wof:placetype":"locality"
},
  "geometry": {"coordinates":[103.16549999999999,2.3287],"type":"Point"}
}