{
  "type": "Feature",
  "properties": {
    "gn:admin1_code":"1",
    "gn:asciiname":"Kampung Serkat Timor",
    "gn:country_code":"MY",
    "gn:dem":10,
    "gn:feature_class":"P",
    "gn:feature_code":"PPL",
    "gn:name":"Kampung Serkat Timor",
    "gn:population":0,
    "gn:timezone":"Asia/Kuala_Lumpur",
    "iso:country":"MY",
    "name:msa_x_preferred":[
        "Kampung Serkat Timor"
    ],
    "name:und_x_variant":[
        "Kampong Serkat"
    ],
    "wof:name":"Kampung Serkat Timor",
    "wof:placetype":"locality"
},
  "geometry": {"coordinates":[103.4926,1.3022],"type":"Point"}
}