{
  "type": "Feature",
  "properties": {
    "gn:admin1_code":"15",
    "gn:asciiname":"Kampung Kerupang",
    "gn:country_code":"MY",
    "gn:dem":15,
    "gn:feature_class":"P",
    "gn:feature_code":"PPL",
    "gn:name":"Kampung Kerupang",
    "gn:population":0,
    "gn:timezone":"Asia/Kuching",
    "iso:country":"MY",
    "wof:name":"Kampung Kerupang",
    "wof:placetype":"locality"
},
  "geometry": {"coordinates":[115.25,5.31667],"type":"Point"}
}