{
  "type": "Feature",
  "properties": {
    "gn:admin1_code":"8.0",
    "gn:asciiname":"Kampung Behor Inai",
    "gn:cc2":"MY",
    "gn:country_code":"MY",
    "gn:dem":13,
    "gn:feature_class":"P",
    "gn:feature_code":"PPL",
    "gn:name":"Kampung Behor Inai",
    "gn:population":0,
    "gn:timezone":"Asia/Kuala_Lumpur",
    "iso:country":"MY",
    "name:msa_x_preferred":[
        "Kampung Behor Inai"
    ],
    "wof:name":"Kampung Behor Inai",
    "wof:placetype":"locality"
},
  "geometry": {"coordinates":[100.21294,6.48187],"type":"Point"}
}