{
  "type": "Feature",
  "properties": {
    "gn:admin1_code":"11",
    "gn:asciiname":"Pelaman Baki",
    "gn:cc2":"MY",
    "gn:country_code":"MY",
    "gn:dem":39,
    "gn:feature_class":"P",
    "gn:feature_code":"PPL",
    "gn:name":"Pelaman Baki",
    "gn:population":0,
    "gn:timezone":"Asia/Kuching",
    "iso:country":"MY",
    "name:und_x_variant":[
        "Kampong Baki",
        "Plaman Baki",
        "Pelaman Baki"
    ],
    "wof:name":"Pelaman Baki",
    "wof:placetype":"locality"
},
  "geometry": {"coordinates":[110.51667,1.23333],"type":"Point"}
}