{
  "type": "Feature",
  "properties": {
    "gn:admin1_code":"11",
    "gn:asciiname":"Kampong Engkaru",
    "gn:cc2":"MY",
    "gn:country_code":"MY",
    "gn:dem":75,
    "gn:feature_class":"P",
    "gn:feature_code":"PPL",
    "gn:name":"Kampong Engkaru",
    "gn:population":0,
    "gn:timezone":"Asia/Kuching",
    "iso:country":"MY",
    "name:und_x_variant":[
        "Engkroh",
        "Kampong Engkroh",
        "Kampong Engkaru"
    ],
    "wof:name":"Kampong Engkaru",
    "wof:placetype":"locality"
},
  "geometry": {"coordinates":[110.53333000000001,1.01667],"type":"Point"}
}