{
  "type": "Feature",
  "properties": {
    "gn:admin1_code":"6.0",
    "gn:asciiname":"Kampung Tanjung Kerayung",
    "gn:country_code":"MY",
    "gn:dem":51,
    "gn:feature_class":"P",
    "gn:feature_code":"PPL",
    "gn:name":"Kampung Tanjung Kerayung",
    "gn:population":0,
    "gn:timezone":"Asia/Kuala_Lumpur",
    "iso:country":"MY",
    "name:msa_x_preferred":[
        "Kampung Tanjung Kerayung"
    ],
    "wof:name":"Kampung Tanjung Kerayung",
    "wof:placetype":"locality"
},
  "geometry": {"coordinates":[102.627,3.5689],"type":"Point"}
}