{
  "type": "Feature",
  "properties": {
    "gn:admin1_code":"11.0",
    "gn:asciiname":"Rumah Tindia",
    "gn:country_code":"MY",
    "gn:dem":26,
    "gn:feature_class":"P",
    "gn:feature_code":"PPL",
    "gn:name":"Rumah Tindia",
    "gn:population":0,
    "gn:timezone":"Asia/Kuching",
    "iso:country":"MY",
    "name:msa_x_preferred":[
        "Rumah Tindia"
    ],
    "wof:name":"Rumah Tindia",
    "wof:placetype":"locality"
},
  "geometry": {"coordinates":[112.1854,2.64148],"type":"Point"}
}