{
  "type": "Feature",
  "properties": {
    "gn:admin1_code":"6.0",
    "gn:asciiname":"Kampung Paya Ara",
    "gn:country_code":"MY",
    "gn:dem":45,
    "gn:feature_class":"P",
    "gn:feature_code":"PPL",
    "gn:name":"Kampung Paya Ara",
    "gn:population":0,
    "gn:timezone":"Asia/Kuala_Lumpur",
    "iso:country":"MY",
    "name:msa_x_preferred":[
        "Kampung Paya Ara"
    ],
    "wof:name":"Kampung Paya Ara",
    "wof:placetype":"locality"
},
  "geometry": {"coordinates":[102.3844,3.4065],"type":"Point"}
}