{
  "type": "Feature",
  "properties": {
    "gn:admin1_code":"3.0",
    "gn:asciiname":"Kampung Kuala Melawi",
    "gn:country_code":"MY",
    "gn:dem":11,
    "gn:feature_class":"P",
    "gn:feature_code":"PPL",
    "gn:name":"Kampung Kuala Melawi",
    "gn:population":0,
    "gn:timezone":"Asia/Kuala_Lumpur",
    "iso:country":"MY",
    "name:msa_x_preferred":[
        "Kampung Kuala Melawi"
    ],
    "wof:name":"Kampung Kuala Melawi",
    "wof:placetype":"locality"
},
  "geometry": {"coordinates":[102.41634000000001,6.01988],"type":"Point"}
}