{
  "type": "Feature",
  "properties": {
    "gn:admin1_code":"7.0",
    "gn:asciiname":"Taman Tasek Jaya",
    "gn:country_code":"MY",
    "gn:dem":61,
    "gn:feature_class":"P",
    "gn:feature_code":"PPL",
    "gn:name":"Taman Tasek Jaya",
    "gn:population":0,
    "gn:timezone":"Asia/Kuala_Lumpur",
    "iso:country":"MY",
    "name:msa_x_preferred":[
        "Taman Tasek Jaya"
    ],
    "wof:name":"Taman Tasek Jaya",
    "wof:placetype":"locality"
},
  "geometry": {"coordinates":[101.1078,4.6516],"type":"Point"}
}