{
  "type": "Feature",
  "properties": {
    "gn:admin1_code":"16.0",
    "gn:asciiname":"Kampung Marigat",
    "gn:country_code":"MY",
    "gn:dem":107,
    "gn:feature_class":"P",
    "gn:feature_code":"PPL",
    "gn:name":"Kampung Marigat",
    "gn:population":0,
    "gn:timezone":"Asia/Kuching",
    "iso:country":"MY",
    "name:msa_x_preferred":[
        "Kampung Marigat"
    ],
    "wof:name":"Kampung Marigat",
    "wof:placetype":"locality"
},
  "geometry": {"coordinates":[116.9483,6.1488],"type":"Point"}
}