{
  "type": "Feature",
  "properties": {
    "gn:admin1_code":"6.0",
    "gn:asciiname":"Kampung Berhala Gantang",
    "gn:country_code":"MY",
    "gn:dem":40,
    "gn:feature_class":"P",
    "gn:feature_code":"PPL",
    "gn:name":"Kampung Berhala Gantang",
    "gn:population":0,
    "gn:timezone":"Asia/Kuala_Lumpur",
    "iso:country":"MY",
    "name:msa_x_preferred":[
        "Kampung Berhala Gantang"
    ],
    "wof:name":"Kampung Berhala Gantang",
    "wof:placetype":"locality"
},
  "geometry": {"coordinates":[102.4286,3.4884],"type":"Point"}
}