{
  "type": "Feature",
  "properties": {
    "gn:admin1_code":"16",
    "gn:asciiname":"Kampong Melati",
    "gn:country_code":"MY",
    "gn:dem":21,
    "gn:elevation":"0.0",
    "gn:feature_class":"P",
    "gn:feature_code":"PPL",
    "gn:name":"Kampong Melati",
    "gn:population":0,
    "gn:timezone":"Asia/Kuching",
    "iso:country":"MY",
    "wof:name":"Kampong Melati",
    "wof:placetype":"locality"
},
  "geometry": {"coordinates":[117.8168,4.3708],"type":"Point"}
}