{
  "type": "Feature",
  "properties": {
    "gn:admin1_code":"16.0",
    "gn:asciiname":"Kampung Tong Gulangan",
    "gn:country_code":"MY",
    "gn:dem":16,
    "gn:feature_class":"P",
    "gn:feature_code":"PPL",
    "gn:name":"Kampung Tong Gulangan",
    "gn:population":0,
    "gn:timezone":"Asia/Kuching",
    "iso:country":"MY",
    "wof:name":"Kampung Tong Gulangan",
    "wof:placetype":"locality"
},
  "geometry": {"coordinates":[118.5269,4.49748],"type":"Point"}
}