{
  "type": "Feature",
  "properties": {
    "gn:admin1_code":"7.0",
    "gn:asciiname":"Kampung Simpang Jalong Baharu",
    "gn:country_code":"MY",
    "gn:dem":78,
    "gn:feature_class":"P",
    "gn:feature_code":"PPL",
    "gn:name":"Kampung Simpang Jalong Baharu",
    "gn:population":0,
    "gn:timezone":"Asia/Kuala_Lumpur",
    "iso:country":"MY",
    "name:msa_x_preferred":[
        "Kampung Simpang Jalong Baharu"
    ],
    "wof:name":"Kampung Simpang Jalong Baharu",
    "wof:placetype":"locality"
},
  "geometry": {"coordinates":[101.0975,4.8282],"type":"Point"}
}