{
  "type": "Feature",
  "properties": {
    "gn:admin1_code":"11.0",
    "gn:asciiname":"Rumah Debu",
    "gn:country_code":"MY",
    "gn:dem":82,
    "gn:feature_class":"P",
    "gn:feature_code":"PPL",
    "gn:name":"Rumah Debu",
    "gn:population":0,
    "gn:timezone":"Asia/Kuching",
    "iso:country":"MY",
    "wof:name":"Rumah Debu",
    "wof:placetype":"locality"
},
  "geometry": {"coordinates":[113.46666999999999,2.15],"type":"Point"}
}