{
  "type": "Feature",
  "properties": {
    "gn:admin1_code":"12",
    "gn:asciiname":"Kampung Sungai Ramal Luar",
    "gn:country_code":"MY",
    "gn:dem":46,
    "gn:feature_class":"P",
    "gn:feature_code":"PPL",
    "gn:name":"Kampung Sungai Ramal Luar",
    "gn:population":0,
    "gn:timezone":"Asia/Kuala_Lumpur",
    "iso:country":"MY",
    "name:msa_x_preferred":[
        "Kampung Sungai Ramal Luar"
    ],
    "name:und_x_variant":[
        "Kampong Sungai Ramal Luar"
    ],
    "wof:name":"Kampung Sungai Ramal Luar",
    "wof:placetype":"locality"
},
  "geometry": {"coordinates":[101.7598,2.9796],"type":"Point"}
}