{
  "type": "Feature",
  "properties": {
    "gn:admin1_code":"11.0",
    "gn:asciiname":"Sengkuang",
    "gn:cc2":"MY",
    "gn:country_code":"MY",
    "gn:dem":32,
    "gn:feature_class":"P",
    "gn:feature_code":"PPL",
    "gn:name":"Sengkuang",
    "gn:population":0,
    "gn:timezone":"Asia/Kuching",
    "iso:country":"MY",
    "name:und_x_variant":[
        "Tapang Tumbang",
        "Sengkuang"
    ],
    "wof:name":"Sengkuang",
    "wof:placetype":"locality"
},
  "geometry": {"coordinates":[111.53333000000001,1.08333],"type":"Point"}
}