{
  "type": "Feature",
  "properties": {
    "gn:admin1_code":"16.0",
    "gn:asciiname":"Kalibatang",
    "gn:country_code":"MY",
    "gn:dem":222,
    "gn:feature_class":"P",
    "gn:feature_code":"PPL",
    "gn:name":"Kalibatang",
    "gn:population":0,
    "gn:timezone":"Asia/Kuching",
    "iso:country":"MY",
    "name:msa_x_preferred":[
        "Kalibatang"
    ],
    "wof:name":"Kalibatang",
    "wof:placetype":"locality"
},
  "geometry": {"coordinates":[115.896,4.863],"type":"Point"}
}