{
  "type": "Feature",
  "properties": {
    "iso:country":"MY",
    "qs:name":"Pekan Pangkor",
    "qs:name_adm0":"Malaysia",
    "qs:name_adm1":"Perak",
    "qs:photos":35,
    "qs:photos_1k":7,
    "qs:photos_9k":1,
    "qs:photos_9r":2,
    "qs:photos_all":35,
    "qs:photos_sr":2,
    "qs:placetype":"Town",
    "qs:pop_sr":"0",
    "wof:name":"Pekan Pangkor",
    "wof:placetype":"locality"
},
  "geometry": {"coordinates":[100.54630899999999,4.253285],"type":"Point"}
}