{
  "type": "Feature",
  "properties": {
    "gn:admin1_code":"5",
    "gn:asciiname":"Kampung Kubang",
    "gn:country_code":"MY",
    "gn:dem":24,
    "gn:feature_class":"P",
    "gn:feature_code":"PPL",
    "gn:name":"Kampung Kubang",
    "gn:population":0,
    "gn:timezone":"Asia/Kuala_Lumpur",
    "iso:country":"MY",
    "name:msa_x_preferred":[
        "Kampung Kubang"
    ],
    "name:und_x_variant":[
        "Kampong Kubang"
    ],
    "wof:name":"Kampung Kubang",
    "wof:placetype":"locality"
},
  "geometry": {"coordinates":[101.7683,2.7913],"type":"Point"}
}