{
  "type": "Feature",
  "properties": {
    "gn:admin1_code":"6.0",
    "gn:asciiname":"Kampung Garung",
    "gn:country_code":"MY",
    "gn:dem":6,
    "gn:feature_class":"P",
    "gn:feature_code":"PPL",
    "gn:name":"Kampung Garung",
    "gn:population":0,
    "gn:timezone":"Asia/Kuala_Lumpur",
    "iso:country":"MY",
    "name:msa_x_preferred":[
        "Kampung Garung"
    ],
    "wof:name":"Kampung Garung",
    "wof:placetype":"locality"
},
  "geometry": {"coordinates":[103.57814999999999,2.68078],"type":"Point"}
}