{
  "type": "Feature",
  "properties": {
    "gn:admin1_code":"1.0",
    "gn:asciiname":"Kawasan Penempatan Ulu Sungai Benut",
    "gn:country_code":"MY",
    "gn:dem":13,
    "gn:feature_class":"P",
    "gn:feature_code":"PPL",
    "gn:name":"Kawasan Penempatan Ulu Sungai Benut",
    "gn:population":0,
    "gn:timezone":"Asia/Kuala_Lumpur",
    "iso:country":"MY",
    "name:msa_x_preferred":[
        "Kawasan Penempatan Ulu Sungai Benut"
    ],
    "wof:name":"Kawasan Penempatan Ulu Sungai Benut",
    "wof:placetype":"locality"
},
  "geometry": {"coordinates":[103.27979999999999,1.7541],"type":"Point"}
}