{
  "type": "Feature",
  "properties": {
    "gn:admin1_code":"3",
    "gn:asciiname":"Kampung Air Merah",
    "gn:country_code":"MY",
    "gn:dem":41,
    "gn:feature_class":"P",
    "gn:feature_code":"PPL",
    "gn:name":"Kampung Air Merah",
    "gn:population":0,
    "gn:timezone":"Asia/Kuala_Lumpur",
    "iso:country":"MY",
    "name:msa_x_preferred":[
        "Kampung Air Merah"
    ],
    "name:und_x_variant":[
        "Kampong Ayer Merah"
    ],
    "wof:name":"Kampung Air Merah",
    "wof:placetype":"locality"
},
  "geometry": {"coordinates":[101.97823,5.79665],"type":"Point"}
}