{
  "type": "Feature",
  "properties": {
    "gn:admin1_code":"4",
    "gn:asciiname":"Kampung Chohong",
    "gn:country_code":"MY",
    "gn:dem":18,
    "gn:feature_class":"P",
    "gn:feature_code":"PPL",
    "gn:name":"Kampung Chohong",
    "gn:population":0,
    "gn:timezone":"Asia/Kuala_Lumpur",
    "iso:country":"MY",
    "name:msa_x_preferred":[
        "Kampung Chohong"
    ],
    "name:und_x_variant":[
        "Kampong Chohong"
    ],
    "wof:name":"Kampung Chohong",
    "wof:placetype":"locality"
},
  "geometry": {"coordinates":[102.50360000000001,2.2971],"type":"Point"}
}