{
  "type": "Feature",
  "properties": {
    "gn:admin1_code":"16",
    "gn:asciiname":"Kampung Gayang",
    "gn:country_code":"MY",
    "gn:dem":12,
    "gn:feature_class":"P",
    "gn:feature_code":"PPL",
    "gn:name":"Kampung Gayang",
    "gn:population":0,
    "gn:timezone":"Asia/Kuching",
    "iso:country":"MY",
    "name:msa_x_preferred":[
        "Kampung Gayang"
    ],
    "name:und_x_variant":[
        "Kampong Gayang"
    ],
    "wof:name":"Kampung Gayang",
    "wof:placetype":"locality"
},
  "geometry": {"coordinates":[116.1486,6.1369],"type":"Point"}
}