{
  "type": "Feature",
  "properties": {
    "gn:admin1_code":"16.0",
    "gn:asciiname":"Kuala Menggalong",
    "gn:cc2":"MY",
    "gn:country_code":"MY",
    "gn:dem":8,
    "gn:feature_class":"P",
    "gn:feature_code":"PPL",
    "gn:name":"Kuala Menggalong",
    "gn:population":0,
    "gn:timezone":"Asia/Kuching",
    "iso:country":"MY",
    "name:und_x_variant":[
        "Kampong Kuala Mengalong",
        "Kuala Mengalong",
        "Kuala Menggalong"
    ],
    "wof:name":"Kuala Menggalong",
    "wof:placetype":"locality"
},
  "geometry": {"coordinates":[115.46729999999999,5.01049],"type":"Point"}
}