{
  "type": "Feature",
  "properties": {
    "gn:admin1_code":"16",
    "gn:asciiname":"Talidus",
    "gn:country_code":"MY",
    "gn:dem":681,
    "gn:feature_class":"P",
    "gn:feature_code":"PPL",
    "gn:name":"Talidus",
    "gn:population":0,
    "gn:timezone":"Asia/Kuching",
    "iso:country":"MY",
    "wof:name":"Talidus",
    "wof:placetype":"locality"
},
  "geometry": {"coordinates":[116.33333,5.58333],"type":"Point"}
}