{
  "type": "Feature",
  "properties": {
    "gn:admin1_code":"7.0",
    "gn:asciiname":"Kampung Sungai Balai Barat",
    "gn:country_code":"MY",
    "gn:dem":10,
    "gn:feature_class":"P",
    "gn:feature_code":"PPL",
    "gn:name":"Kampung Sungai Balai Barat",
    "gn:population":0,
    "gn:timezone":"Asia/Kuala_Lumpur",
    "iso:country":"MY",
    "name:msa_x_preferred":[
        "Kampung Sungai Balai Barat"
    ],
    "wof:name":"Kampung Sungai Balai Barat",
    "wof:placetype":"locality"
},
  "geometry": {"coordinates":[100.7302,3.9357],"type":"Point"}
}