{
  "type": "Feature",
  "properties": {
    "gn:admin1_code":"4.0",
    "gn:asciiname":"Tanjung Dahan",
    "gn:country_code":"MY",
    "gn:dem":8,
    "gn:feature_class":"P",
    "gn:feature_code":"PPL",
    "gn:name":"Tanjung Dahan",
    "gn:population":0,
    "gn:timezone":"Asia/Kuala_Lumpur",
    "iso:country":"MY",
    "name:msa_x_preferred":[
        "Tanjung Dahan"
    ],
    "wof:name":"Tanjung Dahan",
    "wof:placetype":"locality"
},
  "geometry": {"coordinates":[102.00757,2.37167],"type":"Point"}
}