{
  "type": "Feature",
  "properties": {
    "gn:admin1_code":"4",
    "gn:asciiname":"Sempang Gading",
    "gn:country_code":"MY",
    "gn:dem":21,
    "gn:feature_class":"P",
    "gn:feature_code":"PPL",
    "gn:name":"Sempang Gading",
    "gn:population":0,
    "gn:timezone":"Asia/Kuala_Lumpur",
    "iso:country":"MY",
    "name:msa_x_preferred":[
        "Sempang Gading"
    ],
    "name:und_x_variant":[
        "Ayer Resam Simpang Gading",
        "Simpang Gading"
    ],
    "wof:name":"Sempang Gading",
    "wof:placetype":"locality"
},
  "geometry": {"coordinates":[102.3073,2.3311],"type":"Point"}
}