{
  "type": "Feature",
  "properties": {
    "gn:admin1_code":"16.0",
    "gn:asciiname":"Kampung Panikawan Darat",
    "gn:country_code":"MY",
    "gn:dem":107,
    "gn:feature_class":"P",
    "gn:feature_code":"PPL",
    "gn:name":"Kampung Panikawan Darat",
    "gn:population":0,
    "gn:timezone":"Asia/Kuching",
    "iso:country":"MY",
    "name:msa_x_preferred":[
        "Kampung Panikawan Darat"
    ],
    "name:und_x_variant":[
        "Kampong Panikawan Darat"
    ],
    "wof:name":"Kampung Panikawan Darat",
    "wof:placetype":"locality"
},
  "geometry": {"coordinates":[116.7111,6.6854],"type":"Point"}
}