{
  "type": "Feature",
  "properties": {
    "gn:admin1_code":"16",
    "gn:asciiname":"Kampong Taginambur",
    "gn:country_code":"MY",
    "gn:dem":84,
    "gn:feature_class":"P",
    "gn:feature_code":"PPL",
    "gn:name":"Kampong Taginambur",
    "gn:population":0,
    "gn:timezone":"Asia/Kuching",
    "iso:country":"MY",
    "wof:name":"Kampong Taginambur",
    "wof:placetype":"locality"
},
  "geometry": {"coordinates":[116.45,6.25],"type":"Point"}
}