{
  "type": "Feature",
  "properties": {
    "gn:admin1_code":"3.0",
    "gn:asciiname":"Pos Mering",
    "gn:country_code":"MY",
    "gn:dem":240,
    "gn:feature_class":"P",
    "gn:feature_code":"PPL",
    "gn:name":"Pos Mering",
    "gn:population":0,
    "gn:timezone":"Asia/Kuala_Lumpur",
    "iso:country":"MY",
    "name:msa_x_preferred":[
        "Pos Mering"
    ],
    "wof:name":"Pos Mering",
    "wof:placetype":"locality"
},
  "geometry": {"coordinates":[101.62350000000001,4.6983],"type":"Point"}
}