{
  "type": "Feature",
  "properties": {
    "gn:admin1_code":"13",
    "gn:asciiname":"Kampung Alur Fatimah",
    "gn:cc2":"MY",
    "gn:country_code":"MY",
    "gn:dem":10,
    "gn:feature_class":"P",
    "gn:feature_code":"PPL",
    "gn:name":"Kampung Alur Fatimah",
    "gn:population":0,
    "gn:timezone":"Asia/Kuala_Lumpur",
    "iso:country":"MY",
    "name:msa_x_preferred":[
        "Kampung Alur Fatimah"
    ],
    "name:und_x_variant":[
        "Kampong Alor Fatimah"
    ],
    "wof:name":"Kampung Alur Fatimah",
    "wof:placetype":"locality"
},
  "geometry": {"coordinates":[102.75162,5.58266],"type":"Point"}
}