{
  "type": "Feature",
  "properties": {
    "gn:admin1_code":"5",
    "gn:asciiname":"Kampung Kelaka",
    "gn:country_code":"MY",
    "gn:dem":168,
    "gn:feature_class":"P",
    "gn:feature_code":"PPL",
    "gn:name":"Kampung Kelaka",
    "gn:population":0,
    "gn:timezone":"Asia/Kuala_Lumpur",
    "iso:country":"MY",
    "name:msa_x_preferred":[
        "Kampung Kelaka"
    ],
    "name:und_x_variant":[
        "Kampong Kelaka"
    ],
    "wof:name":"Kampung Kelaka",
    "wof:placetype":"locality"
},
  "geometry": {"coordinates":[102.0309,2.8952],"type":"Point"}
}