{
  "type": "Feature",
  "properties": {
    "gn:country":"MY",
    "gn:fcode":"ADM3",
    "gn:pop":0,
    "iso:country":"MY",
    "name:msa_x_preferred":[
        "Sala Kechil"
    ],
    "qs:name":"Sala Kechil",
    "qs:photos_9r":0,
    "qs:photos_sr":0,
    "qs:pop_sr":"0",
    "wof:name":"Sala Kechil",
    "wof:placetype":"localadmin",
    "wof:population":0
},
  "geometry": {"coordinates":[100.37509,5.98255],"type":"Point"}
}