{
  "type": "Feature",
  "properties": {
    "gn:admin1_code":"16.0",
    "gn:asciiname":"Kampung Mangis Kotopoi",
    "gn:country_code":"MY",
    "gn:dem":58,
    "gn:feature_class":"P",
    "gn:feature_code":"PPL",
    "gn:name":"Kampung Mangis Kotopoi",
    "gn:population":0,
    "gn:timezone":"Asia/Kuching",
    "iso:country":"MY",
    "name:msa_x_preferred":[
        "Kampung Mangis Kotopoi"
    ],
    "wof:name":"Kampung Mangis Kotopoi",
    "wof:placetype":"locality"
},
  "geometry": {"coordinates":[117.17100000000001,6.3341],"type":"Point"}
}