{
  "type": "Feature",
  "properties": {
    "iso:country":"MY",
    "qs:name":"Pelubang",
    "qs:name_adm0":"Malaysia",
    "qs:name_adm1":"Kedah",
    "qs:photos":6,
    "qs:photos_1k":1,
    "qs:photos_9k":1,
    "qs:photos_9r":1,
    "qs:photos_all":6,
    "qs:photos_sr":1,
    "qs:placetype":"LocalAdmin",
    "qs:pop_sr":"0",
    "wof:name":"Pelubang",
    "wof:placetype":"localadmin"
},
  "geometry": {"coordinates":[100.437955,6.244998],"type":"Point"}
}