{
  "type": "Feature",
  "properties": {
    "gn:admin1_code":"6.0",
    "gn:asciiname":"Keratung Lapan",
    "gn:country_code":"MY",
    "gn:dem":53,
    "gn:feature_class":"P",
    "gn:feature_code":"PPL",
    "gn:name":"Keratung Lapan",
    "gn:population":0,
    "gn:timezone":"Asia/Kuala_Lumpur",
    "iso:country":"MY",
    "name:msa_x_preferred":[
        "Keratung Lapan"
    ],
    "wof:name":"Keratung Lapan",
    "wof:placetype":"locality"
},
  "geometry": {"coordinates":[102.9871,2.958],"type":"Point"}
}