{
  "type": "Feature",
  "properties": {
    "gn:admin1_code":"11.0",
    "gn:asciiname":"Nanga Tamin",
    "gn:cc2":"MY",
    "gn:country_code":"MY",
    "gn:dem":13,
    "gn:feature_class":"P",
    "gn:feature_code":"PPL",
    "gn:name":"Nanga Tamin",
    "gn:population":0,
    "gn:timezone":"Asia/Kuching",
    "iso:country":"MY",
    "name:und_x_variant":[
        "Tamin",
        "Nanga Tamin"
    ],
    "wof:name":"Nanga Tamin",
    "wof:placetype":"locality"
},
  "geometry": {"coordinates":[112.06667,2.51667],"type":"Point"}
}