{
  "type": "Feature",
  "properties": {
    "gn:admin1_code":"7.0",
    "gn:admin2_code":"1734400",
    "gn:asciiname":"Bukit Larut",
    "gn:country_code":"MY",
    "gn:dem":1032,
    "gn:feature_class":"P",
    "gn:feature_code":"PPLL",
    "gn:name":"Bukit Larut",
    "gn:population":0,
    "gn:timezone":"Asia/Kuala_Lumpur",
    "iso:country":"MY",
    "name:und_x_variant":[
        "Maxwell Hill"
    ],
    "wof:name":"Bukit Larut",
    "wof:placetype":"locality"
},
  "geometry": {"coordinates":[100.79264999999999,4.86247],"type":"Point"}
}