{
  "type": "Feature",
  "properties": {
    "gn:admin1_code":"1.0",
    "gn:asciiname":"Parit Sri Dayung Dua",
    "gn:country_code":"MY",
    "gn:dem":9,
    "gn:feature_class":"P",
    "gn:feature_code":"PPL",
    "gn:name":"Parit Sri Dayung Dua",
    "gn:population":0,
    "gn:timezone":"Asia/Kuala_Lumpur",
    "iso:country":"MY",
    "name:msa_x_preferred":[
        "Parit Sri Dayung Dua"
    ],
    "wof:name":"Parit Sri Dayung Dua",
    "wof:placetype":"locality"
},
  "geometry": {"coordinates":[102.9873,2.0386],"type":"Point"}
}