{
  "type": "Feature",
  "properties": {
    "gn:admin1_code":"4.0",
    "gn:asciiname":"Taman Maju",
    "gn:country_code":"MY",
    "gn:dem":39,
    "gn:feature_class":"P",
    "gn:feature_code":"PPL",
    "gn:name":"Taman Maju",
    "gn:population":0,
    "gn:timezone":"Asia/Kuala_Lumpur",
    "iso:country":"MY",
    "name:msa_x_preferred":[
        "Taman Maju"
    ],
    "wof:name":"Taman Maju",
    "wof:placetype":"locality"
},
  "geometry": {"coordinates":[102.41330000000001,2.2927],"type":"Point"}
}