{
  "type": "Feature",
  "properties": {
    "gn:admin1_code":"12",
    "gn:asciiname":"Kampung Sungai Michu",
    "gn:country_code":"MY",
    "gn:dem":88,
    "gn:feature_class":"P",
    "gn:feature_code":"PPL",
    "gn:name":"Kampung Sungai Michu",
    "gn:population":0,
    "gn:timezone":"Asia/Kuala_Lumpur",
    "iso:country":"MY",
    "name:msa_x_preferred":[
        "Kampung Sungai Michu"
    ],
    "name:und_x_variant":[
        "Kampong Sungai Michu"
    ],
    "wof:name":"Kampung Sungai Michu",
    "wof:placetype":"locality"
},
  "geometry": {"coordinates":[101.80540000000001,3.1144],"type":"Point"}
}