{
  "type": "Feature",
  "properties": {
    "gn:admin1_code":"13",
    "gn:asciiname":"Kampung Gajah Mati",
    "gn:country_code":"MY",
    "gn:dem":33,
    "gn:feature_class":"P",
    "gn:feature_code":"PPL",
    "gn:name":"Kampung Gajah Mati",
    "gn:population":0,
    "gn:timezone":"Asia/Kuala_Lumpur",
    "iso:country":"MY",
    "name:msa_x_preferred":[
        "Kampung Gajah Mati"
    ],
    "name:und_x_variant":[
        "Kampong Gaja Mati",
        "Kampong Gajah Mati"
    ],
    "wof:name":"Kampung Gajah Mati",
    "wof:placetype":"locality"
},
  "geometry": {"coordinates":[103.09059999999999,4.7421],"type":"Point"}
}