{
  "type": "Feature",
  "properties": {
    "gn:admin1_code":"6.0",
    "gn:asciiname":"Kampung Sri Melati",
    "gn:country_code":"MY",
    "gn:dem":11,
    "gn:feature_class":"P",
    "gn:feature_code":"PPL",
    "gn:name":"Kampung Sri Melati",
    "gn:population":0,
    "gn:timezone":"Asia/Kuala_Lumpur",
    "iso:country":"MY",
    "name:msa_x_preferred":[
        "Kampung Sri Melati"
    ],
    "wof:name":"Kampung Sri Melati",
    "wof:placetype":"locality"
},
  "geometry": {"coordinates":[103.2728,3.7011],"type":"Point"}
}