{
  "type": "Feature",
  "properties": {
    "gn:admin1_code":"16",
    "gn:asciiname":"Kampung Ranggum",
    "gn:country_code":"MY",
    "gn:dem":306,
    "gn:feature_class":"P",
    "gn:feature_code":"PPL",
    "gn:name":"Kampung Ranggum",
    "gn:population":0,
    "gn:timezone":"Asia/Kuching",
    "iso:country":"MY",
    "wof:name":"Kampung Ranggum",
    "wof:placetype":"locality"
},
  "geometry": {"coordinates":[116.76667,5.45],"type":"Point"}
}