{
  "type": "Feature",
  "properties": {
    "gn:admin1_code":"6.0",
    "gn:asciiname":"Tabung Haji",
    "gn:country_code":"MY",
    "gn:dem":37,
    "gn:feature_class":"P",
    "gn:feature_code":"PPL",
    "gn:name":"Tabung Haji",
    "gn:population":0,
    "gn:timezone":"Asia/Kuala_Lumpur",
    "iso:country":"MY",
    "name:ind_x_preferred":[
        "Tabung Haji"
    ],
    "name:msa_x_preferred":[
        "Tabung Haji"
    ],
    "wof:name":"Tabung Haji",
    "wof:placetype":"locality"
},
  "geometry": {"coordinates":[102.9284,2.9802],"type":"Point"}
}