{
  "type": "Feature",
  "properties": {
    "gn:admin1_code":"13",
    "gn:asciiname":"Kampung Lubuk Bayas",
    "gn:country_code":"MY",
    "gn:dem":41,
    "gn:feature_class":"P",
    "gn:feature_code":"PPL",
    "gn:name":"Kampung Lubuk Bayas",
    "gn:population":0,
    "gn:timezone":"Asia/Kuala_Lumpur",
    "iso:country":"MY",
    "name:und_x_variant":[
        "Kampong Lubok Bayas"
    ],
    "wof:name":"Kampung Lubuk Bayas",
    "wof:placetype":"locality"
},
  "geometry": {"coordinates":[103.22307000000001,4.58908],"type":"Point"}
}