{
  "type": "Feature",
  "properties": {
    "gn:admin1_code":"5.0",
    "gn:asciiname":"Kampung Mengkan",
    "gn:country_code":"MY",
    "gn:dem":137,
    "gn:feature_class":"P",
    "gn:feature_code":"PPL",
    "gn:name":"Kampung Mengkan",
    "gn:population":0,
    "gn:timezone":"Asia/Kuala_Lumpur",
    "iso:country":"MY",
    "name:msa_x_preferred":[
        "Kampung Mengkan"
    ],
    "wof:name":"Kampung Mengkan",
    "wof:placetype":"locality"
},
  "geometry": {"coordinates":[102.0633,2.9462],"type":"Point"}
}