{
  "type": "Feature",
  "properties": {
    "gn:admin1_code":"11",
    "gn:asciiname":"Nanga Setapang",
    "gn:cc2":"MY",
    "gn:country_code":"MY",
    "gn:dem":182,
    "gn:feature_class":"P",
    "gn:feature_code":"PPL",
    "gn:name":"Nanga Setapang",
    "gn:population":0,
    "gn:timezone":"Asia/Kuching",
    "iso:country":"MY",
    "name:und_x_variant":[
        "Nanga Stapang",
        "Nanga Setapang"
    ],
    "wof:name":"Nanga Setapang",
    "wof:placetype":"locality"
},
  "geometry": {"coordinates":[111.90000000000001,1.21667],"type":"Point"}
}