{
  "type": "Feature",
  "properties": {
    "iso:country":"MY",
    "name:und_x_variant":[
        "Bandaraya Georgetown"
    ],
    "qs:gn_adm0_cc":"MY",
    "qs:gn_local":1735106,
    "qs:local_max":5776,
    "qs:local_sum":22216,
    "qs:localhoods":25,
    "qs:name":"Bandaraya Georgetown",
    "qs:name_adm0":"Malaysia",
    "qs:name_adm1":"Pulau Pinang",
    "qs:name_adm2":"Timur Laut",
    "qs:name_lau":"George Town",
    "qs:name_local":"George Town",
    "qs:photo_max":1604,
    "qs:photo_sum":4682,
    "qs:placetype":"Suburb",
    "qs:quad_count":35,
    "qs:woe_adm0":23424901,
    "qs:woe_adm1":2346304,
    "qs:woe_adm2":56013581,
    "qs:woe_lau":56013803,
    "qs:woe_local":1141153,
    "qs:woe_ver":"7.10.0",
    "wof:lang":[
        "unk"
    ],
    "wof:name":"Bandaraya Georgetown",
    "wof:placetype":"neighbourhood"
},
  "geometry": {"coordinates":[100.331776,5.421824],"type":"Point"}
}