{
  "type": "Feature",
  "properties": {
    "gn:admin1_code":"9",
    "gn:asciiname":"Pajak Song",
    "gn:cc2":"MY",
    "gn:country_code":"MY",
    "gn:dem":7,
    "gn:feature_class":"P",
    "gn:feature_code":"PPL",
    "gn:name":"Pajak Song",
    "gn:population":0,
    "gn:timezone":"Asia/Kuala_Lumpur",
    "iso:country":"MY",
    "name:und_x_variant":[
        "Kampong Pajak Song",
        "Pajak Song"
    ],
    "wof:name":"Pajak Song",
    "wof:placetype":"locality"
},
  "geometry": {"coordinates":[100.43333,5.51667],"type":"Point"}
}