{
  "type": "Feature",
  "properties": {
    "gn:admin1_code":"11.0",
    "gn:asciiname":"Kampung Lubuk Nibung",
    "gn:cc2":"MY",
    "gn:country_code":"MY",
    "gn:dem":15,
    "gn:feature_class":"P",
    "gn:feature_code":"PPL",
    "gn:name":"Kampung Lubuk Nibung",
    "gn:population":0,
    "gn:timezone":"Asia/Kuching",
    "iso:country":"MY",
    "name:und_x_variant":[
        "Lubok Nibong",
        "Kampong Lubok Nibong",
        "Kampung Lubuk Nibung"
    ],
    "wof:name":"Kampung Lubuk Nibung",
    "wof:placetype":"locality"
},
  "geometry": {"coordinates":[114.31667,4.15],"type":"Point"}
}