{
  "type": "Feature",
  "properties": {
    "gn:admin1_code":"2",
    "gn:asciiname":"Kampung Sira",
    "gn:cc2":"MY",
    "gn:country_code":"MY",
    "gn:dem":44,
    "gn:feature_class":"P",
    "gn:feature_code":"PPL",
    "gn:name":"Kampung Sira",
    "gn:population":0,
    "gn:timezone":"Asia/Kuala_Lumpur",
    "iso:country":"MY",
    "name:msa_x_preferred":[
        "Kampung Sira"
    ],
    "name:und_x_variant":[
        "Kampong Sira"
    ],
    "wof:name":"Kampung Sira",
    "wof:placetype":"locality"
},
  "geometry": {"coordinates":[100.58838,5.38534],"type":"Point"}
}