{
  "type": "Feature",
  "properties": {
    "gn:admin1_code":"16",
    "gn:asciiname":"Kampung Mangin",
    "gn:country_code":"MY",
    "gn:dem":154,
    "gn:feature_class":"P",
    "gn:feature_code":"PPL",
    "gn:name":"Kampung Mangin",
    "gn:population":0,
    "gn:timezone":"Asia/Kuching",
    "iso:country":"MY",
    "name:msa_x_preferred":[
        "Kampung Mangin"
    ],
    "name:und_x_variant":[
        "Kampong Mangin"
    ],
    "wof:name":"Kampung Mangin",
    "wof:placetype":"locality"
},
  "geometry": {"coordinates":[116.6576,6.5594],"type":"Point"}
}