{
  "type": "Feature",
  "properties": {
    "gn:admin1_code":"16",
    "gn:asciiname":"Kampung Bungaliu",
    "gn:country_code":"MY",
    "gn:dem":25,
    "gn:feature_class":"P",
    "gn:feature_code":"PPL",
    "gn:name":"Kampung Bungaliu",
    "gn:population":0,
    "gn:timezone":"Asia/Kuching",
    "iso:country":"MY",
    "name:msa_x_preferred":[
        "Kampung Bungaliu"
    ],
    "name:und_x_variant":[
        "Kampong Bongaliu"
    ],
    "wof:name":"Kampung Bungaliu",
    "wof:placetype":"locality"
},
  "geometry": {"coordinates":[116.5364,6.4598],"type":"Point"}
}