{
  "type": "Feature",
  "properties": {
    "iso:country":"MY",
    "name:eng_x_preferred":[
        "Tampoi"
    ],
    "name:eng_x_variant":[
        "Pengkalan Rinting",
        "Tampoi Village"
    ],
    "name:msa_x_preferred":[
        "Tampoi"
    ],
    "qs:gn_adm0_cc":"MY",
    "qs:gn_local":1732752,
    "qs:local_max":681,
    "qs:local_sum":3607,
    "qs:localhoods":29,
    "qs:name":"Tampoi",
    "qs:name_adm0":"Malaysia",
    "qs:name_adm1":"Johor",
    "qs:name_adm2":"Johor Bahru",
    "qs:name_lau":"Pulai",
    "qs:name_local":"Johor Baharu",
    "qs:photo_max":10,
    "qs:photo_sum":16,
    "qs:placetype":"Suburb",
    "qs:quad_count":3,
    "qs:woe_adm0":23424901,
    "qs:woe_adm1":2346296,
    "qs:woe_adm2":56013565,
    "qs:woe_lau":56014111,
    "qs:woe_local":1154698,
    "qs:woe_ver":"7.10.0",
    "wd:wordcount":22,
    "wof:lang":[
        "eng"
    ],
    "wof:name":"Tampoi",
    "wof:placetype":"neighbourhood"
},
  "geometry": {"coordinates":[103.699265,1.480929],"type":"Point"}
}