{
  "type": "Feature",
  "properties": {
    "gn:admin1_code":"13.0",
    "gn:asciiname":"Kampung Tanah Lot",
    "gn:country_code":"MY",
    "gn:dem":8,
    "gn:feature_class":"P",
    "gn:feature_code":"PPL",
    "gn:name":"Kampung Tanah Lot",
    "gn:population":0,
    "gn:timezone":"Asia/Kuala_Lumpur",
    "iso:country":"MY",
    "name:msa_x_preferred":[
        "Kampung Tanah Lot"
    ],
    "wof:name":"Kampung Tanah Lot",
    "wof:placetype":"locality"
},
  "geometry": {"coordinates":[103.3026,5.0188],"type":"Point"}
}