{
  "type": "Feature",
  "properties": {
    "gn:gn_country":"MY",
    "gn:gn_fcode":"PPL",
    "gn:gn_pop":0,
    "iso:country":"MY",
    "name:dan_x_preferred":[
        "Senawang"
    ],
    "name:dut_x_preferred":[
        "Senawang"
    ],
    "name:eng_x_preferred":[
        "Senawang"
    ],
    "name:may_x_preferred":[
        "Senawang"
    ],
    "name:msa_x_preferred":[
        "Taman Senawang Indah"
    ],
    "name:unk_x_variant":[
        "Senawang"
    ],
    "qs_pg:aaroncc":"MY",
    "qs_pg:gn_country":"MY",
    "qs_pg:gn_fcode":"PPL",
    "qs_pg:gn_pop":0,
    "qs_pg:name":"Taman Mentakab Indah",
    "qs_pg:name_adm0":"Malaysia",
    "qs_pg:name_adm1":"Pahang",
    "qs_pg:photos_9r":0,
    "qs_pg:photos_sr":0,
    "qs_pg:pop_sr":0,
    "qs_pg:qs_pg_placetype":"locality",
    "qs_pg:qs_pg_placetype_gp":"Town",
    "qs_pg:woe_adm0":23424901,
    "woe:adm0_id":23424901,
    "woe:name_adm0":"Malaysia",
    "woe:name_adm1":"Pahang",
    "woe:placetype":"Town",
    "wof:name":"Taman Mentakab Indah",
    "wof:placetype":"locality"
},
  "geometry": {"coordinates":[101.989,2.691],"type":"Point"}
}