{
  "type": "Feature",
  "properties": {
    "iso:country":"MY",
    "qs:name":"Perupok",
    "qs:name_adm0":"Malaysia",
    "qs:name_adm1":"Kelantan",
    "qs:photos":4,
    "qs:photos_1k":1,
    "qs:photos_9k":1,
    "qs:photos_9r":3,
    "qs:photos_all":150,
    "qs:photos_sr":1,
    "qs:placetype":"LocalAdmin",
    "qs:pop_sr":"0",
    "wd:wordcount":15,
    "wof:name":"Perupok",
    "wof:placetype":"localadmin"
},
  "geometry": {"coordinates":[102.4010535,6.050259],"type":"Point"}
}