{
  "type": "Feature",
  "properties": {
    "gn:admin1_code":"4.0",
    "gn:asciiname":"Kampung Pulau Gedong",
    "gn:country_code":"MY",
    "gn:dem":3,
    "gn:feature_class":"P",
    "gn:feature_code":"PPL",
    "gn:name":"Kampung Pulau Gedong",
    "gn:population":0,
    "gn:timezone":"Asia/Kuala_Lumpur",
    "iso:country":"MY",
    "name:msa_x_preferred":[
        "Kampung Pulau Gedong"
    ],
    "wof:name":"Kampung Pulau Gedong",
    "wof:placetype":"locality"
},
  "geometry": {"coordinates":[102.2025,2.2289],"type":"Point"}
}