{
  "type": "Feature",
  "properties": {
    "gn:admin1_code":"6.0",
    "gn:asciiname":"Kampung Air Hitam Darat",
    "gn:country_code":"MY",
    "gn:dem":22,
    "gn:feature_class":"P",
    "gn:feature_code":"PPL",
    "gn:name":"Kampung Air Hitam Darat",
    "gn:population":0,
    "gn:timezone":"Asia/Kuala_Lumpur",
    "iso:country":"MY",
    "name:msa_x_preferred":[
        "Kampung Air Hitam Darat"
    ],
    "wof:name":"Kampung Air Hitam Darat",
    "wof:placetype":"locality"
},
  "geometry": {"coordinates":[103.0744,3.4229],"type":"Point"}
}