{
  "type": "Feature",
  "properties": {
    "gn:admin1_code":"6.0",
    "gn:asciiname":"Kampung Hulu Retang",
    "gn:country_code":"MY",
    "gn:dem":58,
    "gn:feature_class":"P",
    "gn:feature_code":"PPL",
    "gn:name":"Kampung Hulu Retang",
    "gn:population":0,
    "gn:timezone":"Asia/Kuala_Lumpur",
    "iso:country":"MY",
    "name:msa_x_preferred":[
        "Kampung Hulu Retang"
    ],
    "wof:name":"Kampung Hulu Retang",
    "wof:placetype":"locality"
},
  "geometry": {"coordinates":[102.35509999999999,4.0895],"type":"Point"}
}