{
  "type": "Feature",
  "properties": {
    "gn:admin1_code":"6",
    "gn:asciiname":"Kampung Hulu Tedung",
    "gn:country_code":"MY",
    "gn:dem":76,
    "gn:feature_class":"P",
    "gn:feature_code":"PPL",
    "gn:name":"Kampung Hulu Tedung",
    "gn:population":0,
    "gn:timezone":"Asia/Kuala_Lumpur",
    "iso:country":"MY",
    "name:und_x_variant":[
        "Kampong Ulu Tedong"
    ],
    "wof:name":"Kampung Hulu Tedung",
    "wof:placetype":"locality"
},
  "geometry": {"coordinates":[102.18115,3.53317],"type":"Point"}
}