{
  "type": "Feature",
  "properties": {
    "gn:admin1_code":"3.0",
    "gn:asciiname":"Pos Belatim",
    "gn:country_code":"MY",
    "gn:dem":483,
    "gn:feature_class":"P",
    "gn:feature_code":"PPL",
    "gn:name":"Pos Belatim",
    "gn:population":0,
    "gn:timezone":"Asia/Kuala_Lumpur",
    "iso:country":"MY",
    "name:msa_x_preferred":[
        "Pos Belatim"
    ],
    "wof:name":"Pos Belatim",
    "wof:placetype":"locality"
},
  "geometry": {"coordinates":[101.523,5.004],"type":"Point"}
}