{
  "type": "Feature",
  "properties": {
    "gn:admin1_code":"16.0",
    "gn:asciiname":"Kampung Nopotol",
    "gn:country_code":"MY",
    "gn:dem":322,
    "gn:feature_class":"P",
    "gn:feature_code":"PPL",
    "gn:name":"Kampung Nopotol",
    "gn:population":0,
    "gn:timezone":"Asia/Kuching",
    "iso:country":"MY",
    "name:msa_x_preferred":[
        "Kampung Nopotol"
    ],
    "wof:name":"Kampung Nopotol",
    "wof:placetype":"locality"
},
  "geometry": {"coordinates":[116.9967,6.4398],"type":"Point"}
}