{
  "type": "Feature",
  "properties": {
    "gn:admin1_code":"16.0",
    "gn:asciiname":"Kampung Kinanrap",
    "gn:country_code":"MY",
    "gn:dem":5,
    "gn:feature_class":"P",
    "gn:feature_code":"PPL",
    "gn:name":"Kampung Kinanrap",
    "gn:population":0,
    "gn:timezone":"Asia/Kuching",
    "iso:country":"MY",
    "name:msa_x_preferred":[
        "Kampung Kinanrap"
    ],
    "wof:name":"Kampung Kinanrap",
    "wof:placetype":"locality"
},
  "geometry": {"coordinates":[115.7989,5.4959],"type":"Point"}
}