{
  "type": "Feature",
  "properties": {
    "gn:admin1_code":"6",
    "gn:asciiname":"Kampung Harus Temelian",
    "gn:country_code":"MY",
    "gn:dem":58,
    "gn:feature_class":"P",
    "gn:feature_code":"PPL",
    "gn:name":"Kampung Harus Temelian",
    "gn:population":0,
    "gn:timezone":"Asia/Kuala_Lumpur",
    "iso:country":"MY",
    "name:und_x_variant":[
        "Kampong Tangong Harus Temelian",
        "Kampong Tanjong Harus",
        "Kampong Harus Temelian",
        "Kampung Harus Temelian"
    ],
    "wof:name":"Kampung Harus Temelian",
    "wof:placetype":"locality"
},
  "geometry": {"coordinates":[102.53386999999999,3.34198],"type":"Point"}
}