{
  "type": "Feature",
  "properties": {
    "iso:country":"MY",
    "qs:name":"Lundang",
    "qs:name_adm0":"Malaysia",
    "qs:name_adm1":"Kelantan",
    "qs:photos":20,
    "qs:photos_1k":4,
    "qs:photos_9k":1,
    "qs:photos_9r":2,
    "qs:photos_all":70,
    "qs:photos_sr":1,
    "qs:placetype":"LocalAdmin",
    "qs:pop_sr":"0",
    "wof:name":"Lundang",
    "wof:placetype":"localadmin"
},
  "geometry": {"coordinates":[102.274963,6.098649],"type":"Point"}
}