{
  "type": "Feature",
  "properties": {
    "gn:admin1_code":"9",
    "gn:asciiname":"Kampung Lahar Tembun",
    "gn:cc2":"MY",
    "gn:country_code":"MY",
    "gn:dem":7,
    "gn:feature_class":"P",
    "gn:feature_code":"PPL",
    "gn:name":"Kampung Lahar Tembun",
    "gn:population":0,
    "gn:timezone":"Asia/Kuala_Lumpur",
    "iso:country":"MY",
    "name:msa_x_preferred":[
        "Kampung Lahar Tembun"
    ],
    "name:und_x_variant":[
        "Kampong Lahar Tambun",
        "Kampong Lahar Tembun"
    ],
    "wof:name":"Kampung Lahar Tembun",
    "wof:placetype":"locality"
},
  "geometry": {"coordinates":[100.47750000000001,5.47469],"type":"Point"}
}