{
  "type": "Feature",
  "properties": {
    "gn:admin1_code":"11",
    "gn:asciiname":"Pang Batu",
    "gn:country_code":"MY",
    "gn:dem":20,
    "gn:feature_class":"P",
    "gn:feature_code":"PPL",
    "gn:name":"Pang Batu",
    "gn:population":0,
    "gn:timezone":"Asia/Kuching",
    "iso:country":"MY",
    "name:msa_x_preferred":[
        "Pang Batu"
    ],
    "name:und_x_variant":[
        "Pangkalan Batu"
    ],
    "wof:name":"Pang Batu",
    "wof:placetype":"locality"
},
  "geometry": {"coordinates":[115.4714,4.9587],"type":"Point"}
}