{
  "type": "Feature",
  "properties": {
    "gn:admin1_code":"5.0",
    "gn:asciiname":"Kampung Legong Jaya",
    "gn:country_code":"MY",
    "gn:dem":39,
    "gn:feature_class":"P",
    "gn:feature_code":"PPL",
    "gn:name":"Kampung Legong Jaya",
    "gn:population":0,
    "gn:timezone":"Asia/Kuala_Lumpur",
    "iso:country":"MY",
    "name:msa_x_preferred":[
        "Kampung Legong Jaya"
    ],
    "wof:name":"Kampung Legong Jaya",
    "wof:placetype":"locality"
},
  "geometry": {"coordinates":[102.1605,2.5008],"type":"Point"}
}