{
  "type": "Feature",
  "properties": {
    "gn:admin1_code":"11.0",
    "gn:asciiname":"Long Taan",
    "gn:country_code":"MY",
    "gn:dem":274,
    "gn:feature_class":"P",
    "gn:feature_code":"PPL",
    "gn:name":"Long Taan",
    "gn:population":0,
    "gn:timezone":"Asia/Kuching",
    "iso:country":"MY",
    "wof:name":"Long Taan",
    "wof:placetype":"locality"
},
  "geometry": {"coordinates":[114.95,2.98333],"type":"Point"}
}