{
  "type": "Feature",
  "properties": {
    "gn:admin1_code":"12.0",
    "gn:asciiname":"Kampung Sungai Buaya",
    "gn:country_code":"MY",
    "gn:dem":23,
    "gn:feature_class":"P",
    "gn:feature_code":"PPL",
    "gn:name":"Kampung Sungai Buaya",
    "gn:population":0,
    "gn:timezone":"Asia/Kuala_Lumpur",
    "iso:country":"MY",
    "name:msa_x_preferred":[
        "Kampung Sungai Buaya"
    ],
    "name:und_x_variant":[
        "Kampung Sungia Buaya"
    ],
    "wof:name":"Kampung Sungai Buaya",
    "wof:placetype":"locality"
},
  "geometry": {"coordinates":[101.52209999999999,3.393],"type":"Point"}
}