{
  "type": "Feature",
  "properties": {
    "gn:admin1_code":"3",
    "gn:asciiname":"Kampong Gual To' Eh Deng",
    "gn:country_code":"MY",
    "gn:dem":27,
    "gn:feature_class":"P",
    "gn:feature_code":"PPL",
    "gn:name":"Kampong Gual To\u2019 Eh Deng",
    "gn:population":0,
    "gn:timezone":"Asia/Kuala_Lumpur",
    "iso:country":"MY",
    "wof:name":"Kampong Gual To' Eh Deng",
    "wof:placetype":"locality"
},
  "geometry": {"coordinates":[102.08333,5.93333],"type":"Point"}
}