{
  "type": "Feature",
  "properties": {
    "gn:admin1_code":"16",
    "gn:asciiname":"Kampung Luba Selatan",
    "gn:country_code":"MY",
    "gn:dem":282,
    "gn:feature_class":"P",
    "gn:feature_code":"PPL",
    "gn:name":"Kampung Luba Selatan",
    "gn:population":0,
    "gn:timezone":"Asia/Kuching",
    "iso:country":"MY",
    "name:msa_x_preferred":[
        "Kampung Luba Selatan"
    ],
    "name:und_x_variant":[
        "Kampong Luba"
    ],
    "wof:name":"Kampung Luba Selatan",
    "wof:placetype":"locality"
},
  "geometry": {"coordinates":[116.5693,6.3466],"type":"Point"}
}