{
  "type": "Feature",
  "properties": {
    "gn:admin1_code":"13",
    "gn:asciiname":"Kampung Pacakan",
    "gn:cc2":"MY",
    "gn:country_code":"MY",
    "gn:dem":9,
    "gn:feature_class":"P",
    "gn:feature_code":"PPL",
    "gn:name":"Kampung Pacakan",
    "gn:population":0,
    "gn:timezone":"Asia/Kuala_Lumpur",
    "iso:country":"MY",
    "name:msa_x_preferred":[
        "Kampung Pacakan"
    ],
    "name:und_x_variant":[
        "Kampong Pachakan"
    ],
    "wof:name":"Kampung Pacakan",
    "wof:placetype":"locality"
},
  "geometry": {"coordinates":[102.53606000000001,5.84386],"type":"Point"}
}