{
  "type": "Feature",
  "properties": {
    "gn:admin1_code":"5",
    "gn:asciiname":"Kampung Tampin Kiri",
    "gn:country_code":"MY",
    "gn:dem":20,
    "gn:feature_class":"P",
    "gn:feature_code":"PPL",
    "gn:name":"Kampung Tampin Kiri",
    "gn:population":0,
    "gn:timezone":"Asia/Kuala_Lumpur",
    "iso:country":"MY",
    "name:msa_x_preferred":[
        "Kampung Tampin Kiri"
    ],
    "name:und_x_variant":[
        "Kampong Tampin Kiri"
    ],
    "wof:name":"Kampung Tampin Kiri",
    "wof:placetype":"locality"
},
  "geometry": {"coordinates":[102.0031,2.5082],"type":"Point"}
}