{
  "type": "Feature",
  "properties": {
    "gn:admin1_code":"13",
    "gn:asciiname":"Pengkalan Ubi Keling",
    "gn:country_code":"MY",
    "gn:dem":9,
    "gn:feature_class":"P",
    "gn:feature_code":"PPL",
    "gn:name":"Pengkalan Ubi Keling",
    "gn:population":0,
    "gn:timezone":"Asia/Kuala_Lumpur",
    "iso:country":"MY",
    "name:msa_x_preferred":[
        "Pengkalan Ubi Keling"
    ],
    "wof:name":"Pengkalan Ubi Keling",
    "wof:placetype":"locality"
},
  "geometry": {"coordinates":[102.55408,5.82179],"type":"Point"}
}