{
  "type": "Feature",
  "properties": {
    "gn:country":"MY",
    "gn:fcode":"PPL",
    "gn:pop":0,
    "iso:country":"MY",
    "qs:name":"Mandalom",
    "qs:name_adm0":"Malaysia",
    "qs:name_adm1":"Sabah",
    "qs:photos":120,
    "qs:photos_1k":24,
    "qs:photos_9k":1,
    "qs:photos_9r":3,
    "qs:photos_all":120,
    "qs:photos_sr":3,
    "qs:placetype":"Town",
    "qs:pop_sr":"0",
    "wof:name":"Mandalom",
    "wof:placetype":"locality",
    "wof:population":0
},
  "geometry": {"coordinates":[115.95,5.06667],"type":"Point"}
}