{
  "type": "Feature",
  "properties": {
    "gn:admin1_code":"6.0",
    "gn:asciiname":"Kampung Kekabu",
    "gn:country_code":"MY",
    "gn:dem":110,
    "gn:feature_class":"P",
    "gn:feature_code":"PPL",
    "gn:name":"Kampung Kekabu",
    "gn:population":0,
    "gn:timezone":"Asia/Kuala_Lumpur",
    "iso:country":"MY",
    "name:msa_x_preferred":[
        "Kampung Kekabu"
    ],
    "wof:name":"Kampung Kekabu",
    "wof:placetype":"locality"
},
  "geometry": {"coordinates":[101.8939,4.0153],"type":"Point"}
}