{
  "type": "Feature",
  "properties": {
    "gn:admin1_code":"5.0",
    "gn:asciiname":"Dusun Durian Grat",
    "gn:country_code":"MY",
    "gn:dem":57,
    "gn:feature_class":"P",
    "gn:feature_code":"PPL",
    "gn:name":"Dusun Durian Grat",
    "gn:population":0,
    "gn:timezone":"Asia/Kuala_Lumpur",
    "iso:country":"MY",
    "name:und_x_variant":[
        "Dusun Durian Gerat"
    ],
    "wof:name":"Dusun Durian Grat",
    "wof:placetype":"locality"
},
  "geometry": {"coordinates":[101.81296,2.67726],"type":"Point"}
}