{
  "type": "Feature",
  "properties": {
    "gn:admin1_code":"11",
    "gn:asciiname":"Rumah Dana",
    "gn:cc2":"MY",
    "gn:country_code":"MY",
    "gn:dem":8,
    "gn:feature_class":"P",
    "gn:feature_code":"PPL",
    "gn:name":"Rumah Dana",
    "gn:population":0,
    "gn:timezone":"Asia/Kuching",
    "iso:country":"MY",
    "name:und_x_variant":[
        "Rumah Dang",
        "Rumah Dana"
    ],
    "wof:name":"Rumah Dana",
    "wof:placetype":"locality"
},
  "geometry": {"coordinates":[111.45,2.08333],"type":"Point"}
}