{
  "type": "Feature",
  "properties": {
    "gn:admin1_code":"1",
    "gn:asciiname":"Kampung Telok Jeri",
    "gn:country_code":"MY",
    "gn:dem":8,
    "gn:feature_class":"P",
    "gn:feature_code":"PPL",
    "gn:name":"Kampung Telok Jeri",
    "gn:population":0,
    "gn:timezone":"Asia/Kuala_Lumpur",
    "iso:country":"MY",
    "name:msa_x_preferred":[
        "Kampung Telok Jeri"
    ],
    "name:und_x_variant":[
        "Kampong Telok Jeri"
    ],
    "wof:name":"Kampung Telok Jeri",
    "wof:placetype":"locality"
},
  "geometry": {"coordinates":[104.1018,1.9315],"type":"Point"}
}