{
  "type": "Feature",
  "properties": {
    "gn:admin1_code":"2",
    "gn:asciiname":"Kampung Kubang Sapi",
    "gn:cc2":"MY",
    "gn:country_code":"MY",
    "gn:dem":21,
    "gn:feature_class":"P",
    "gn:feature_code":"PPL",
    "gn:name":"Kampung Kubang Sapi",
    "gn:population":0,
    "gn:timezone":"Asia/Kuala_Lumpur",
    "iso:country":"MY",
    "name:msa_x_preferred":[
        "Kampung Kubang Sapi"
    ],
    "name:und_x_variant":[
        "Kampong Kubang Sapi"
    ],
    "wof:name":"Kampung Kubang Sapi",
    "wof:placetype":"locality"
},
  "geometry": {"coordinates":[100.55540000000001,5.56186],"type":"Point"}
}