{
  "type": "Feature",
  "properties": {
    "gn:admin1_code":"7.0",
    "gn:asciiname":"Ladang Ulu Bernam",
    "gn:country_code":"MY",
    "gn:dem":6,
    "gn:feature_class":"P",
    "gn:feature_code":"PPL",
    "gn:name":"Ladang Ulu Bernam",
    "gn:population":0,
    "gn:timezone":"Asia/Kuala_Lumpur",
    "iso:country":"MY",
    "name:msa_x_preferred":[
        "Ladang Ulu Bernam"
    ],
    "wof:name":"Ladang Ulu Bernam",
    "wof:placetype":"locality"
},
  "geometry": {"coordinates":[101.1461,3.7435],"type":"Point"}
}