{
  "type": "Feature",
  "properties": {
    "gn:admin1_code":"11",
    "gn:asciiname":"Kampong Siburuh",
    "gn:cc2":"MY",
    "gn:country_code":"MY",
    "gn:dem":32,
    "gn:feature_class":"P",
    "gn:feature_code":"PPL",
    "gn:name":"Kampong Siburuh",
    "gn:population":0,
    "gn:timezone":"Asia/Kuching",
    "iso:country":"MY",
    "name:und_x_variant":[
        "Sebuloh",
        "Kampong Siburuh"
    ],
    "wof:name":"Kampong Siburuh",
    "wof:placetype":"locality"
},
  "geometry": {"coordinates":[110.13333,1.45],"type":"Point"}
}