{
  "type": "Feature",
  "properties": {
    "gn:admin1_code":"13.0",
    "gn:asciiname":"Kampung Bukit Rambutan",
    "gn:country_code":"MY",
    "gn:dem":87,
    "gn:feature_class":"P",
    "gn:feature_code":"PPL",
    "gn:name":"Kampung Bukit Rambutan",
    "gn:population":0,
    "gn:timezone":"Asia/Kuala_Lumpur",
    "iso:country":"MY",
    "name:msa_x_preferred":[
        "Kampung Bukit Rambutan"
    ],
    "wof:name":"Kampung Bukit Rambutan",
    "wof:placetype":"locality"
},
  "geometry": {"coordinates":[103.3151,3.8999],"type":"Point"}
}