{
  "type": "Feature",
  "properties": {
    "gn:admin1_code":"4",
    "gn:asciiname":"Kampung Paya Rumput",
    "gn:country_code":"MY",
    "gn:dem":23,
    "gn:feature_class":"P",
    "gn:feature_code":"PPL",
    "gn:name":"Kampung Paya Rumput",
    "gn:population":0,
    "gn:timezone":"Asia/Kuala_Lumpur",
    "iso:country":"MY",
    "name:msa_x_preferred":[
        "Kampung Paya Rumput"
    ],
    "name:und_x_variant":[
        "Kampong Paya Rumput"
    ],
    "wof:name":"Kampung Paya Rumput",
    "wof:placetype":"locality"
},
  "geometry": {"coordinates":[102.09699999999999,2.3705],"type":"Point"}
}