{
  "type": "Feature",
  "properties": {
    "gn:admin1_code":"13",
    "gn:asciiname":"Kampung Sura Masjid",
    "gn:country_code":"MY",
    "gn:dem":11,
    "gn:feature_class":"P",
    "gn:feature_code":"PPL",
    "gn:name":"Kampung Sura Masjid",
    "gn:population":0,
    "gn:timezone":"Asia/Kuala_Lumpur",
    "iso:country":"MY",
    "name:msa_x_preferred":[
        "Kampung Sura Masjid"
    ],
    "name:und_x_variant":[
        "Kampong Sura Masjid"
    ],
    "wof:name":"Kampung Sura Masjid",
    "wof:placetype":"locality"
},
  "geometry": {"coordinates":[103.42619999999999,4.7376],"type":"Point"}
}