{
  "type": "Feature",
  "properties": {
    "gn:admin1_code":"16",
    "gn:asciiname":"Kampung Tigol",
    "gn:country_code":"MY",
    "gn:dem":331,
    "gn:feature_class":"P",
    "gn:feature_code":"PPL",
    "gn:name":"Kampung Tigol",
    "gn:population":0,
    "gn:timezone":"Asia/Kuching",
    "iso:country":"MY",
    "name:msa_x_preferred":[
        "Kampung Tigol"
    ],
    "name:und_x_variant":[
        "Kampong Tigol"
    ],
    "wof:name":"Kampung Tigol",
    "wof:placetype":"locality"
},
  "geometry": {"coordinates":[116.218,5.7877],"type":"Point"}
}