{
  "type": "Feature",
  "properties": {
    "iso:country":"MY",
    "qs:name":"Kedawang",
    "qs:name_adm0":"Malaysia",
    "qs:name_adm1":"Kedah",
    "qs:photos":6,
    "qs:photos_1k":1,
    "qs:photos_9k":14,
    "qs:photos_9r":11,
    "qs:photos_all":3081,
    "qs:photos_sr":1,
    "qs:placetype":"LocalAdmin",
    "qs:pop_sr":"0",
    "wof:name":"Kedawang",
    "wof:placetype":"localadmin"
},
  "geometry": {"coordinates":[99.729766,6.287421],"type":"Point"}
}