{
  "type": "Feature",
  "properties": {
    "gn:admin1_code":"4",
    "gn:asciiname":"Kampung Tanjung Dahan",
    "gn:country_code":"MY",
    "gn:dem":8,
    "gn:feature_class":"P",
    "gn:feature_code":"PPL",
    "gn:name":"Kampung Tanjung Dahan",
    "gn:population":0,
    "gn:timezone":"Asia/Kuala_Lumpur",
    "iso:country":"MY",
    "name:msa_x_preferred":[
        "Kampung Tanjung Dahan"
    ],
    "name:und_x_variant":[
        "Kampong Tanjong Dahan"
    ],
    "wof:name":"Kampung Tanjung Dahan",
    "wof:placetype":"locality"
},
  "geometry": {"coordinates":[101.9949,2.3724],"type":"Point"}
}