{
  "type": "Feature",
  "properties": {
    "gn:admin1_code":"2",
    "gn:asciiname":"Kampung Titi Panjang",
    "gn:country_code":"MY",
    "gn:dem":14,
    "gn:feature_class":"P",
    "gn:feature_code":"PPL",
    "gn:name":"Kampung Titi Panjang",
    "gn:population":0,
    "gn:timezone":"Asia/Kuala_Lumpur",
    "iso:country":"MY",
    "name:msa_x_preferred":[
        "Kampung Titi Panjang"
    ],
    "name:und_x_variant":[
        "Kampong Titi Panjang"
    ],
    "wof:name":"Kampung Titi Panjang",
    "wof:placetype":"locality"
},
  "geometry": {"coordinates":[100.42461,6.32642],"type":"Point"}
}