{
  "type": "Feature",
  "properties": {
    "gn:admin1_code":"12.0",
    "gn:asciiname":"Kampung Parit Enam",
    "gn:country_code":"MY",
    "gn:dem":4,
    "gn:feature_class":"P",
    "gn:feature_code":"PPL",
    "gn:name":"Kampung Parit Enam",
    "gn:population":0,
    "gn:timezone":"Asia/Kuala_Lumpur",
    "iso:country":"MY",
    "name:msa_x_preferred":[
        "Kampung Parit Enam"
    ],
    "wof:name":"Kampung Parit Enam",
    "wof:placetype":"locality"
},
  "geometry": {"coordinates":[101.01139999999999,3.7138],"type":"Point"}
}