{
  "type": "Feature",
  "properties": {
    "iso:country":"MY",
    "qs:name":"Sungai Baru Ilir",
    "qs:name_adm0":"Malaysia",
    "qs:name_adm1":"Melaka",
    "qs:photos":1,
    "qs:photos_1k":1,
    "qs:photos_9k":1,
    "qs:photos_9r":3,
    "qs:photos_all":95,
    "qs:photos_sr":1,
    "qs:placetype":"LocalAdmin",
    "qs:pop_sr":"0",
    "wd:wordcount":646,
    "wof:name":"Sungai Baru Ilir",
    "wof:placetype":"localadmin"
},
  "geometry": {"coordinates":[102.065612,2.3475],"type":"Point"}
}