{
  "type": "Feature",
  "properties": {
    "iso:country":"MY",
    "name:ceb_x_preferred":[
        "Bandar Baharu"
    ],
    "name:eng_x_preferred":[
        "Bandar Baharu"
    ],
    "name:fas_x_preferred":[
        "\u0628\u0646\u062f\u0631 \u0628\u0627\u0647\u0627\u0631\u0648"
    ],
    "name:ind_x_preferred":[
        "Bandar Baharu"
    ],
    "name:msa_x_preferred":[
        "Bandar Baharu"
    ],
    "name:nld_x_preferred":[
        "Bandar Baharu"
    ],
    "name:vie_x_preferred":[
        "Bandar Baharu"
    ],
    "name:zho_x_preferred":[
        "\u4e07\u62c9\u5cc7\u9c81"
    ],
    "qs:name":"Sungai Baru Ilir",
    "qs:name_adm0":"Malaysia",
    "qs:name_adm1":"Melaka",
    "qs:photos":1,
    "qs:photos_1k":1,
    "qs:photos_9k":1,
    "qs:photos_9r":3,
    "qs:photos_all":95,
    "qs:photos_sr":1,
    "qs:placetype":"LocalAdmin",
    "qs:pop_sr":"0",
    "wd:wordcount":646,
    "wof:name":"Sungai Baru Ilir",
    "wof:placetype":"localadmin"
},
  "geometry": {"coordinates":[102.065612,2.3475],"type":"Point"}
}