{
  "type": "Feature",
  "properties": {
    "gn:admin1_code":"11",
    "gn:asciiname":"Rumah Kimin",
    "gn:country_code":"MY",
    "gn:dem":19,
    "gn:feature_class":"P",
    "gn:feature_code":"PPL",
    "gn:name":"Rumah Kimin",
    "gn:population":0,
    "gn:timezone":"Asia/Kuching",
    "iso:country":"MY",
    "wof:name":"Rumah Kimin",
    "wof:placetype":"locality"
},
  "geometry": {"coordinates":[113.66667,3.75],"type":"Point"}
}