{
  "type": "Feature",
  "properties": {
    "gn:admin1_code":"3",
    "gn:asciiname":"Kampong Sungai Tasek",
    "gn:country_code":"MY",
    "gn:dem":13,
    "gn:feature_class":"P",
    "gn:feature_code":"PPL",
    "gn:name":"Kampong Sungai Tasek",
    "gn:population":0,
    "gn:timezone":"Asia/Kuala_Lumpur",
    "iso:country":"MY",
    "wof:name":"Kampong Sungai Tasek",
    "wof:placetype":"locality"
},
  "geometry": {"coordinates":[102.46666999999999,5.78333],"type":"Point"}
}