{
  "type": "Feature",
  "properties": {
    "gn:admin1_code":"1.0",
    "gn:asciiname":"Kampung Ulu Pelentong",
    "gn:country_code":"MY",
    "gn:dem":21,
    "gn:feature_class":"P",
    "gn:feature_code":"PPL",
    "gn:name":"Kampung Ulu Pelentong",
    "gn:population":0,
    "gn:timezone":"Asia/Kuala_Lumpur",
    "iso:country":"MY",
    "name:msa_x_preferred":[
        "Kampung Ulu Pelentong"
    ],
    "wof:name":"Kampung Ulu Pelentong",
    "wof:placetype":"locality"
},
  "geometry": {"coordinates":[103.84950000000001,1.5937],"type":"Point"}
}