{
  "type": "Feature",
  "properties": {
    "gn:admin1_code":"6",
    "gn:asciiname":"Kampung Kuala Liang",
    "gn:country_code":"MY",
    "gn:dem":127,
    "gn:feature_class":"P",
    "gn:feature_code":"PPL",
    "gn:name":"Kampung Kuala Liang",
    "gn:population":0,
    "gn:timezone":"Asia/Kuala_Lumpur",
    "iso:country":"MY",
    "name:und_x_variant":[
        "Kampong Kuala Liang"
    ],
    "wof:name":"Kampung Kuala Liang",
    "wof:placetype":"locality"
},
  "geometry": {"coordinates":[101.82353999999999,3.87554],"type":"Point"}
}