{
  "type": "Feature",
  "properties": {
    "gn:admin1_code":"6.0",
    "gn:asciiname":"Kampung Bukit Nikmat",
    "gn:country_code":"MY",
    "gn:dem":54,
    "gn:feature_class":"P",
    "gn:feature_code":"PPL",
    "gn:name":"Kampung Bukit Nikmat",
    "gn:population":0,
    "gn:timezone":"Asia/Kuala_Lumpur",
    "iso:country":"MY",
    "name:msa_x_preferred":[
        "Kampung Bukit Nikmat"
    ],
    "wof:name":"Kampung Bukit Nikmat",
    "wof:placetype":"locality"
},
  "geometry": {"coordinates":[102.4289,3.8311],"type":"Point"}
}