{
  "type": "Feature",
  "properties": {
    "gn:admin1_code":"1.0",
    "gn:asciiname":"Taman Jaya",
    "gn:country_code":"MY",
    "gn:dem":24,
    "gn:feature_class":"P",
    "gn:feature_code":"PPL",
    "gn:name":"Taman Jaya",
    "gn:population":0,
    "gn:timezone":"Asia/Kuala_Lumpur",
    "iso:country":"MY",
    "name:msa_x_preferred":[
        "Taman Jaya"
    ],
    "wof:name":"Taman Jaya",
    "wof:placetype":"locality"
},
  "geometry": {"coordinates":[103.07040000000001,2.0168],"type":"Point"}
}