{
  "type": "Feature",
  "properties": {
    "gn:admin1_code":"4.0",
    "gn:asciiname":"Taman Panglima Pak",
    "gn:country_code":"MY",
    "gn:dem":9,
    "gn:feature_class":"P",
    "gn:feature_code":"PPL",
    "gn:name":"Taman Panglima Pak",
    "gn:population":0,
    "gn:timezone":"Asia/Kuala_Lumpur",
    "iso:country":"MY",
    "name:msa_x_preferred":[
        "Taman Panglima Pak"
    ],
    "wof:name":"Taman Panglima Pak",
    "wof:placetype":"locality"
},
  "geometry": {"coordinates":[102.4053,2.1392],"type":"Point"}
}