{
  "type": "Feature",
  "properties": {
    "gn:admin1_code":"1.0",
    "gn:asciiname":"Kampung Parit Tunggol",
    "gn:country_code":"MY",
    "gn:dem":18,
    "gn:feature_class":"P",
    "gn:feature_code":"PPL",
    "gn:name":"Kampung Parit Tunggol",
    "gn:population":0,
    "gn:timezone":"Asia/Kuala_Lumpur",
    "iso:country":"MY",
    "name:msa_x_preferred":[
        "Kampung Parit Tunggol"
    ],
    "wof:name":"Kampung Parit Tunggol",
    "wof:placetype":"locality"
},
  "geometry": {"coordinates":[102.771,2.2596],"type":"Point"}
}