{
  "type": "Feature",
  "properties": {
    "gn:admin1_code":"7",
    "gn:asciiname":"Kampung Cangkat Kereta",
    "gn:country_code":"MY",
    "gn:dem":25,
    "gn:feature_class":"P",
    "gn:feature_code":"PPL",
    "gn:name":"Kampung Cangkat Kereta",
    "gn:population":0,
    "gn:timezone":"Asia/Kuala_Lumpur",
    "iso:country":"MY",
    "name:msa_x_preferred":[
        "Kampung Cangkat Kereta"
    ],
    "name:und_x_variant":[
        "Kampong Changkat Kereta"
    ],
    "wof:name":"Kampung Cangkat Kereta",
    "wof:placetype":"locality"
},
  "geometry": {"coordinates":[101.2248,3.7861],"type":"Point"}
}