{
  "type": "Feature",
  "properties": {
    "gn:admin1_code":"16",
    "gn:asciiname":"Kampung Taguli",
    "gn:country_code":"MY",
    "gn:dem":8,
    "gn:feature_class":"P",
    "gn:feature_code":"PPL",
    "gn:name":"Kampung Taguli",
    "gn:population":0,
    "gn:timezone":"Asia/Kuching",
    "iso:country":"MY",
    "name:msa_x_preferred":[
        "Kampung Taguli"
    ],
    "name:und_x_variant":[
        "Kampong Taguli"
    ],
    "wof:name":"Kampung Taguli",
    "wof:placetype":"locality"
},
  "geometry": {"coordinates":[116.0508,5.901],"type":"Point"}
}