{
  "type": "Feature",
  "properties": {
    "gn:admin1_code":"5",
    "gn:asciiname":"Kampung Jumbang",
    "gn:country_code":"MY",
    "gn:dem":131,
    "gn:feature_class":"P",
    "gn:feature_code":"PPL",
    "gn:name":"Kampung Jumbang",
    "gn:population":0,
    "gn:timezone":"Asia/Kuala_Lumpur",
    "iso:country":"MY",
    "name:msa_x_preferred":[
        "Kampung Jumbang"
    ],
    "name:und_x_variant":[
        "Kampong Jumbang"
    ],
    "wof:name":"Kampung Jumbang",
    "wof:placetype":"locality"
},
  "geometry": {"coordinates":[102.1408,2.6629],"type":"Point"}
}