{
  "type": "Feature",
  "properties": {
    "gn:admin1_code":"1",
    "gn:asciiname":"Kampung Permatang Panjang",
    "gn:country_code":"MY",
    "gn:dem":43,
    "gn:feature_class":"P",
    "gn:feature_code":"PPL",
    "gn:name":"Kampung Permatang Panjang",
    "gn:population":0,
    "gn:timezone":"Asia/Kuala_Lumpur",
    "iso:country":"MY",
    "name:msa_x_preferred":[
        "Kampung Permatang Panjang"
    ],
    "name:und_x_variant":[
        "Kampong Permatang Panjang"
    ],
    "wof:name":"Kampung Permatang Panjang",
    "wof:placetype":"locality"
},
  "geometry": {"coordinates":[102.6758,2.4349],"type":"Point"}
}