{
  "type": "Feature",
  "properties": {
    "gn:admin1_code":"16",
    "gn:asciiname":"Kampung Sen Bantaian",
    "gn:country_code":"MY",
    "gn:dem":-9999,
    "gn:feature_class":"P",
    "gn:feature_code":"PPL",
    "gn:name":"Kampung Sen Bantaian",
    "gn:population":0,
    "gn:timezone":"Asia/Kuching",
    "iso:country":"MY",
    "wof:name":"Kampung Sen Bantaian",
    "wof:placetype":"locality"
},
  "geometry": {"coordinates":[118.58879,4.42408],"type":"Point"}
}