{
  "type": "Feature",
  "properties": {
    "gn:admin1_code":"6",
    "gn:asciiname":"Kampung Bukit Sambau",
    "gn:country_code":"MY",
    "gn:dem":107,
    "gn:feature_class":"P",
    "gn:feature_code":"PPL",
    "gn:name":"Kampung Bukit Sambau",
    "gn:population":0,
    "gn:timezone":"Asia/Kuala_Lumpur",
    "iso:country":"MY",
    "name:msa_x_preferred":[
        "Kampung Bukit Sambau"
    ],
    "name:und_x_variant":[
        "Kampong Bukit Sambau"
    ],
    "wof:name":"Kampung Bukit Sambau",
    "wof:placetype":"locality"
},
  "geometry": {"coordinates":[101.8871,3.975],"type":"Point"}
}