{
  "type": "Feature",
  "properties": {
    "gn:admin1_code":"3",
    "gn:asciiname":"Kampung Padang Nyior",
    "gn:country_code":"MY",
    "gn:dem":16,
    "gn:feature_class":"P",
    "gn:feature_code":"PPL",
    "gn:name":"Kampung Padang Nyior",
    "gn:population":0,
    "gn:timezone":"Asia/Kuala_Lumpur",
    "iso:country":"MY",
    "name:msa_x_preferred":[
        "Kampung Padang Nyior"
    ],
    "name:und_x_variant":[
        "Kampong Padang Nyior"
    ],
    "wof:name":"Kampung Padang Nyior",
    "wof:placetype":"locality"
},
  "geometry": {"coordinates":[101.96720000000001,5.989],"type":"Point"}
}