{
  "type": "Feature",
  "properties": {
    "gn:admin1_code":"16.0",
    "gn:asciiname":"Kampung Bukah",
    "gn:country_code":"MY",
    "gn:dem":22,
    "gn:feature_class":"P",
    "gn:feature_code":"PPL",
    "gn:name":"Kampung Bukah",
    "gn:population":0,
    "gn:timezone":"Asia/Kuching",
    "iso:country":"MY",
    "name:msa_x_preferred":[
        "Kampung Bukah"
    ],
    "wof:name":"Kampung Bukah",
    "wof:placetype":"locality"
},
  "geometry": {"coordinates":[116.78789999999999,6.6852],"type":"Point"}
}