{
  "type": "Feature",
  "properties": {
    "gn:admin1_code":"16.0",
    "gn:asciiname":"Kampung Balapat",
    "gn:country_code":"MY",
    "gn:dem":33,
    "gn:feature_class":"P",
    "gn:feature_code":"PPL",
    "gn:name":"Kampung Balapat",
    "gn:population":0,
    "gn:timezone":"Asia/Kuching",
    "iso:country":"MY",
    "name:msa_x_preferred":[
        "Kampung Balapat"
    ],
    "wof:name":"Kampung Balapat",
    "wof:placetype":"locality"
},
  "geometry": {"coordinates":[116.7196,6.8076],"type":"Point"}
}