{
  "type": "Feature",
  "properties": {
    "gn:admin1_code":"7",
    "gn:asciiname":"Kampung Sungai Sitiawan",
    "gn:country_code":"MY",
    "gn:dem":4,
    "gn:feature_class":"P",
    "gn:feature_code":"PPL",
    "gn:name":"Kampung Sungai Sitiawan",
    "gn:population":0,
    "gn:timezone":"Asia/Kuala_Lumpur",
    "iso:country":"MY",
    "name:msa_x_preferred":[
        "Kampung Sungai Sitiawan"
    ],
    "name:und_x_variant":[
        "Kampong Sungai Sitiawan"
    ],
    "wof:name":"Kampung Sungai Sitiawan",
    "wof:placetype":"locality"
},
  "geometry": {"coordinates":[100.68170000000001,4.2535],"type":"Point"}
}