{
  "type": "Feature",
  "properties": {
    "gn:admin1_code":"6.0",
    "gn:asciiname":"Kampong Kepong",
    "gn:country_code":"MY",
    "gn:dem":26,
    "gn:feature_class":"P",
    "gn:feature_code":"PPL",
    "gn:name":"Kampong Kepong",
    "gn:population":0,
    "gn:timezone":"Asia/Kuala_Lumpur",
    "iso:country":"MY",
    "name:msa_x_preferred":[
        "Kampong Kepong"
    ],
    "wof:name":"Kampong Kepong",
    "wof:placetype":"locality"
},
  "geometry": {"coordinates":[103.4532,2.74088],"type":"Point"}
}