{
  "type": "Feature",
  "properties": {
    "gn:admin1_code":"2.0",
    "gn:asciiname":"Kampung Gajah Mati",
    "gn:cc2":"MY",
    "gn:country_code":"MY",
    "gn:dem":65,
    "gn:feature_class":"P",
    "gn:feature_code":"PPL",
    "gn:name":"Kampung Gajah Mati",
    "gn:population":0,
    "gn:timezone":"Asia/Kuala_Lumpur",
    "iso:country":"MY",
    "name:msa_x_preferred":[
        "Kampung Gajah Mati"
    ],
    "wof:name":"Kampung Gajah Mati",
    "wof:placetype":"locality"
},
  "geometry": {"coordinates":[100.71169999999999,6.00319],"type":"Point"}
}