{
  "type": "Feature",
  "properties": {
    "gn:admin1_code":"16.0",
    "gn:asciiname":"Kampung Sinisian",
    "gn:country_code":"MY",
    "gn:dem":1320,
    "gn:feature_class":"P",
    "gn:feature_code":"PPL",
    "gn:name":"Kampung Sinisian",
    "gn:population":0,
    "gn:timezone":"Asia/Kuching",
    "iso:country":"MY",
    "name:msa_x_preferred":[
        "Kampung Sinisian"
    ],
    "name:und_x_variant":[
        "Kampong Sinisian",
        "Sinisian"
    ],
    "wof:name":"Kampung Sinisian",
    "wof:placetype":"locality"
},
  "geometry": {"coordinates":[116.35809999999999,5.8523],"type":"Point"}
}