{
  "type": "Feature",
  "properties": {
    "gn:admin1_code":"1.0",
    "gn:asciiname":"Kampung Labong",
    "gn:country_code":"MY",
    "gn:dem":10,
    "gn:feature_class":"P",
    "gn:feature_code":"PPL",
    "gn:name":"Kampung Labong",
    "gn:population":0,
    "gn:timezone":"Asia/Kuala_Lumpur",
    "iso:country":"MY",
    "name:msa_x_preferred":[
        "Kampung Labong"
    ],
    "name:und_x_variant":[
        "Kampung Labung"
    ],
    "wof:name":"Kampung Labong",
    "wof:placetype":"locality"
},
  "geometry": {"coordinates":[103.62997,2.58913],"type":"Point"}
}