{
  "type": "Feature",
  "properties": {
    "gn:admin1_code":"1.0",
    "gn:asciiname":"Kampung Sungai Sembilang",
    "gn:country_code":"MY",
    "gn:dem":28,
    "gn:feature_class":"P",
    "gn:feature_code":"PPL",
    "gn:name":"Kampung Sungai Sembilang",
    "gn:population":0,
    "gn:timezone":"Asia/Kuala_Lumpur",
    "iso:country":"MY",
    "name:msa_x_preferred":[
        "Kampung Sungai Sembilang"
    ],
    "wof:name":"Kampung Sungai Sembilang",
    "wof:placetype":"locality"
},
  "geometry": {"coordinates":[103.98569999999999,1.6445],"type":"Point"}
}