{
  "type": "Feature",
  "properties": {
    "gn:admin1_code":"11.0",
    "gn:asciiname":"Kampung Panglima Seman Lama",
    "gn:country_code":"MY",
    "gn:dem":6,
    "gn:feature_class":"P",
    "gn:feature_code":"PPL",
    "gn:name":"Kampung Panglima Seman Lama",
    "gn:population":0,
    "gn:timezone":"Asia/Kuching",
    "iso:country":"MY",
    "wof:name":"Kampung Panglima Seman Lama",
    "wof:placetype":"locality"
},
  "geometry": {"coordinates":[110.35944000000001,1.56056],"type":"Point"}
}