{
  "type": "Feature",
  "properties": {
    "gn:admin1_code":"6.0",
    "gn:asciiname":"Kampung Janda Baik",
    "gn:country_code":"MY",
    "gn:dem":435,
    "gn:feature_class":"P",
    "gn:feature_code":"PPL",
    "gn:name":"Kampung Janda Baik",
    "gn:population":0,
    "gn:timezone":"Asia/Kuala_Lumpur",
    "iso:country":"MY",
    "wof:name":"Kampung Janda Baik",
    "wof:placetype":"locality"
},
  "geometry": {"coordinates":[101.86667,3.31667],"type":"Point"}
}