{
  "type": "Feature",
  "properties": {
    "gn:admin1_code":"15",
    "gn:asciiname":"Kampung Belukut",
    "gn:cc2":"MY",
    "gn:country_code":"MY",
    "gn:dem":48,
    "gn:feature_class":"P",
    "gn:feature_code":"PPL",
    "gn:name":"Kampung Belukut",
    "gn:population":0,
    "gn:timezone":"Asia/Kuching",
    "iso:country":"MY",
    "name:und_x_variant":[
        "Kampong Belukut",
        "Belukut",
        "Kampung Belukut"
    ],
    "wof:name":"Kampung Belukut",
    "wof:placetype":"locality"
},
  "geometry": {"coordinates":[115.18333,5.28333],"type":"Point"}
}