{
  "type": "Feature",
  "properties": {
    "gn:admin1_code":"1.0",
    "gn:asciiname":"Kebun Baharu",
    "gn:country_code":"MY",
    "gn:dem":48,
    "gn:feature_class":"P",
    "gn:feature_code":"PPL",
    "gn:name":"Kebun Baharu",
    "gn:population":0,
    "gn:timezone":"Asia/Kuala_Lumpur",
    "iso:country":"MY",
    "name:msa_x_preferred":[
        "Kebun Baharu"
    ],
    "wof:name":"Kebun Baharu",
    "wof:placetype":"locality"
},
  "geometry": {"coordinates":[102.684,2.393],"type":"Point"}
}