{
  "type": "Feature",
  "properties": {
    "gn:admin1_code":"11",
    "gn:asciiname":"Kampung Penambai",
    "gn:country_code":"MY",
    "gn:dem":1,
    "gn:feature_class":"P",
    "gn:feature_code":"PPL",
    "gn:name":"Kampung Penambai",
    "gn:population":0,
    "gn:timezone":"Asia/Kuching",
    "iso:country":"MY",
    "name:und_x_variant":[
        "Kampong Penambai"
    ],
    "wof:name":"Kampung Penambai",
    "wof:placetype":"locality"
},
  "geometry": {"coordinates":[110.38951000000002,1.65964],"type":"Point"}
}