{
  "type": "Feature",
  "properties": {
    "gn:admin1_code":"6.0",
    "gn:asciiname":"Kampung Belimbing",
    "gn:country_code":"MY",
    "gn:dem":48,
    "gn:feature_class":"P",
    "gn:feature_code":"PPL",
    "gn:name":"Kampung Belimbing",
    "gn:population":0,
    "gn:timezone":"Asia/Kuala_Lumpur",
    "iso:country":"MY",
    "name:msa_x_preferred":[
        "Kampung Belimbing"
    ],
    "wof:name":"Kampung Belimbing",
    "wof:placetype":"locality"
},
  "geometry": {"coordinates":[102.5561,3.4976],"type":"Point"}
}