{
  "type": "Feature",
  "properties": {
    "gn:admin1_code":"7",
    "gn:asciiname":"Kampung Pasir Garam",
    "gn:country_code":"MY",
    "gn:dem":19,
    "gn:feature_class":"P",
    "gn:feature_code":"PPL",
    "gn:name":"Kampung Pasir Garam",
    "gn:population":0,
    "gn:timezone":"Asia/Kuala_Lumpur",
    "iso:country":"MY",
    "name:msa_x_preferred":[
        "Kampung Pasir Garam"
    ],
    "name:und_x_variant":[
        "Kampong Pasir Garam"
    ],
    "wof:name":"Kampung Pasir Garam",
    "wof:placetype":"locality"
},
  "geometry": {"coordinates":[100.8994,4.2303],"type":"Point"}
}