{
  "type": "Feature",
  "properties": {
    "gn:admin1_code":"5",
    "gn:asciiname":"Kampung Kota Lama",
    "gn:country_code":"MY",
    "gn:dem":40,
    "gn:feature_class":"P",
    "gn:feature_code":"PPL",
    "gn:name":"Kampung Kota Lama",
    "gn:population":0,
    "gn:timezone":"Asia/Kuala_Lumpur",
    "iso:country":"MY",
    "name:msa_x_preferred":[
        "Kampung Kota Lama"
    ],
    "name:und_x_variant":[
        "Kampong Kota Lama"
    ],
    "wof:name":"Kampung Kota Lama",
    "wof:placetype":"locality"
},
  "geometry": {"coordinates":[102.1664,2.5181],"type":"Point"}
}