{
  "type": "Feature",
  "properties": {
    "gn:admin1_code":"15.0",
    "gn:asciiname":"Maligan",
    "gn:country_code":"MY",
    "gn:dem":605,
    "gn:feature_class":"P",
    "gn:feature_code":"PPL",
    "gn:name":"Maligan",
    "gn:population":0,
    "gn:timezone":"Asia/Kuching",
    "iso:country":"MY",
    "name:msa_x_preferred":[
        "Maligan"
    ],
    "name:und_x_variant":[
        "Meligan"
    ],
    "wof:name":"Maligan",
    "wof:placetype":"locality"
},
  "geometry": {"coordinates":[115.70247999999999,4.67522],"type":"Point"}
}