{
  "type": "Feature",
  "properties": {
    "gn:admin1_code":"16.0",
    "gn:asciiname":"Kampong Pengkalan Peturu",
    "gn:country_code":"MY",
    "gn:dem":9,
    "gn:feature_class":"P",
    "gn:feature_code":"PPL",
    "gn:name":"Kampong Pengkalan Peturu",
    "gn:population":0,
    "gn:timezone":"Asia/Kuching",
    "iso:country":"MY",
    "name:msa_x_preferred":[
        "Kampong Pengkalan Peturu"
    ],
    "wof:name":"Kampong Pengkalan Peturu",
    "wof:placetype":"locality"
},
  "geometry": {"coordinates":[116.3302,6.3378],"type":"Point"}
}