{
  "type": "Feature",
  "properties": {
    "gn:admin1_code":"5",
    "gn:asciiname":"Kampung Pauh",
    "gn:country_code":"MY",
    "gn:dem":66,
    "gn:feature_class":"P",
    "gn:feature_code":"PPL",
    "gn:name":"Kampung Pauh",
    "gn:population":0,
    "gn:timezone":"Asia/Kuala_Lumpur",
    "iso:country":"MY",
    "name:msa_x_preferred":[
        "Kampung Pauh"
    ],
    "name:und_x_variant":[
        "Kampong Pauh"
    ],
    "wof:name":"Kampung Pauh",
    "wof:placetype":"locality"
},
  "geometry": {"coordinates":[102.2398,2.5009],"type":"Point"}
}