{
  "type": "Feature",
  "properties": {
    "gn:admin1_code":"4",
    "gn:asciiname":"Solok Ulu Seroja",
    "gn:country_code":"MY",
    "gn:dem":17,
    "gn:feature_class":"P",
    "gn:feature_code":"PPL",
    "gn:name":"Solok Ulu Seroja",
    "gn:population":0,
    "gn:timezone":"Asia/Kuala_Lumpur",
    "iso:country":"MY",
    "name:msa_x_preferred":[
        "Solok Ulu Seroja"
    ],
    "name:und_x_variant":[
        "Kampong Ulu Seraja",
        "Solok Ulu Seraja"
    ],
    "wof:name":"Solok Ulu Seroja",
    "wof:placetype":"locality"
},
  "geometry": {"coordinates":[102.2696,2.3474],"type":"Point"}
}