{
  "type": "Feature",
  "properties": {
    "iso:country":"MY",
    "qs:name":"Losong",
    "qs:name_adm0":"Malaysia",
    "qs:name_adm1":"Terengganu",
    "qs:photos":2,
    "qs:photos_1k":1,
    "qs:photos_9k":1,
    "qs:photos_9r":1,
    "qs:photos_all":22,
    "qs:photos_sr":1,
    "qs:placetype":"LocalAdmin",
    "qs:pop_sr":"0",
    "wof:name":"Losong",
    "wof:placetype":"localadmin"
},
  "geometry": {"coordinates":[103.1156915,5.321415],"type":"Point"}
}