{
  "type": "Feature",
  "properties": {
    "iso:country":"MY",
    "name:und_x_variant":[
        "Taman Bukit Mentok"
    ],
    "qs:gn_adm0_cc":"MY",
    "qs:gn_local":1732945,
    "qs:gn_nam_loc":"cukai",
    "qs:gn_namadm1":"13",
    "qs:local_max":81,
    "qs:local_sum":87,
    "qs:localhoods":2,
    "qs:name":"Taman Bukit Mentok",
    "qs:name_adm0":"Malaysia",
    "qs:name_adm1":"Terengganu",
    "qs:name_adm2":"Kemaman",
    "qs:name_lau":"Cukai",
    "qs:name_local":"Cukai",
    "qs:photo_max":23,
    "qs:photo_sum":81,
    "qs:placetype":"Suburb",
    "qs:quad_count":11,
    "qs:woe_adm0":23424901,
    "qs:woe_adm1":2346307,
    "qs:woe_adm2":56013617,
    "qs:woe_lau":56013754,
    "qs:woe_local":1141037,
    "qs:woe_ver":"7.10.0",
    "wof:lang":[
        "unk"
    ],
    "wof:name":"Taman Bukit Mentok",
    "wof:placetype":"neighbourhood"
},
  "geometry": {"coordinates":[103.422208,4.228436],"type":"Point"}
}