{
  "type": "Feature",
  "properties": {
    "gn:admin1_code":"11.0",
    "gn:asciiname":"Kampung Medong",
    "gn:cc2":"MY",
    "gn:country_code":"MY",
    "gn:dem":19,
    "gn:feature_class":"P",
    "gn:feature_code":"PPL",
    "gn:name":"Kampung Medong",
    "gn:population":0,
    "gn:timezone":"Asia/Kuching",
    "iso:country":"MY",
    "name:und_x_variant":[
        "Medong",
        "Kampung Medong"
    ],
    "wof:name":"Kampung Medong",
    "wof:placetype":"locality"
},
  "geometry": {"coordinates":[111.93333,2.66667],"type":"Point"}
}