{
  "type": "Feature",
  "properties": {
    "gn:admin1_code":"7.0",
    "gn:asciiname":"Taman Sri Emas",
    "gn:country_code":"MY",
    "gn:dem":3,
    "gn:feature_class":"P",
    "gn:feature_code":"PPL",
    "gn:name":"Taman Sri Emas",
    "gn:population":0,
    "gn:timezone":"Asia/Kuala_Lumpur",
    "iso:country":"MY",
    "name:msa_x_preferred":[
        "Taman Sri Emas"
    ],
    "wof:name":"Taman Sri Emas",
    "wof:placetype":"locality"
},
  "geometry": {"coordinates":[101.0072,3.9986],"type":"Point"}
}