{
  "type": "Feature",
  "properties": {
    "gn:admin1_code":"16.0",
    "gn:asciiname":"Kampung Karagasan",
    "gn:country_code":"MY",
    "gn:dem":75,
    "gn:feature_class":"P",
    "gn:feature_code":"PPL",
    "gn:name":"Kampung Karagasan",
    "gn:population":0,
    "gn:timezone":"Asia/Kuching",
    "iso:country":"MY",
    "name:msa_x_preferred":[
        "Kampung Karagasan"
    ],
    "wof:name":"Kampung Karagasan",
    "wof:placetype":"locality"
},
  "geometry": {"coordinates":[117.00879999999999,6.111],"type":"Point"}
}