{
  "type": "Feature",
  "properties": {
    "gn:admin1_code":"7",
    "gn:asciiname":"Kampung Kepala Bendang",
    "gn:country_code":"MY",
    "gn:dem":52,
    "gn:feature_class":"P",
    "gn:feature_code":"PPL",
    "gn:name":"Kampung Kepala Bendang",
    "gn:population":0,
    "gn:timezone":"Asia/Kuala_Lumpur",
    "iso:country":"MY",
    "name:msa_x_preferred":[
        "Kampung Kepala Bendang"
    ],
    "name:und_x_variant":[
        "Kampong Kapala Bendang"
    ],
    "wof:name":"Kampung Kepala Bendang",
    "wof:placetype":"locality"
},
  "geometry": {"coordinates":[100.973,4.7779],"type":"Point"}
}