{
  "type": "Feature",
  "properties": {
    "gn:admin1_code":"3",
    "gn:asciiname":"Kampong Tok Mat",
    "gn:country_code":"MY",
    "gn:dem":15,
    "gn:feature_class":"P",
    "gn:feature_code":"PPL",
    "gn:name":"Kampong Tok Mat",
    "gn:population":0,
    "gn:timezone":"Asia/Kuala_Lumpur",
    "iso:country":"MY",
    "wof:name":"Kampong Tok Mat",
    "wof:placetype":"locality"
},
  "geometry": {"coordinates":[102.26667,5.96667],"type":"Point"}
}