{
  "type": "Feature",
  "properties": {
    "gn:admin1_code":"1.0",
    "gn:asciiname":"Kampung Seelong",
    "gn:country_code":"MY",
    "gn:dem":48,
    "gn:feature_class":"P",
    "gn:feature_code":"PPL",
    "gn:name":"Kampung Seelong",
    "gn:population":0,
    "gn:timezone":"Asia/Kuala_Lumpur",
    "iso:country":"MY",
    "name:msa_x_preferred":[
        "Kampung Seelong"
    ],
    "name:msa_x_variant":[
        "Seelong"
    ],
    "name:und_x_variant":[
        "Selong Village",
        "Kampong Selong",
        "Seelong",
        "Selong",
        "Kampung Seelung"
    ],
    "wof:name":"Kampung Seelong",
    "wof:placetype":"locality"
},
  "geometry": {"coordinates":[103.6957,1.63],"type":"Point"}
}