{
  "type": "Feature",
  "properties": {
    "gn:admin1_code":"7",
    "gn:asciiname":"Kampong Ulu Beruas",
    "gn:cc2":"MY",
    "gn:country_code":"MY",
    "gn:dem":77,
    "gn:feature_class":"P",
    "gn:feature_code":"PPL",
    "gn:name":"Kampong Ulu Beruas",
    "gn:population":0,
    "gn:timezone":"Asia/Kuala_Lumpur",
    "iso:country":"MY",
    "name:und_x_variant":[
        "Kampong Ulu Bruas",
        "Kampong Ulu Beruas"
    ],
    "wof:name":"Kampong Ulu Beruas",
    "wof:placetype":"locality"
},
  "geometry": {"coordinates":[100.75,4.51667],"type":"Point"}
}