{
  "type": "Feature",
  "properties": {
    "gn:admin1_code":"1",
    "gn:asciiname":"Kampung Tanjung Kupang",
    "gn:country_code":"MY",
    "gn:dem":11,
    "gn:feature_class":"P",
    "gn:feature_code":"PPL",
    "gn:name":"Kampung Tanjung Kupang",
    "gn:population":0,
    "gn:timezone":"Asia/Kuala_Lumpur",
    "iso:country":"MY",
    "name:msa_x_preferred":[
        "Kampung Tanjung Kupang"
    ],
    "name:und_x_variant":[
        "Kampong Tanjong Kupang"
    ],
    "wof:name":"Kampung Tanjung Kupang",
    "wof:placetype":"locality"
},
  "geometry": {"coordinates":[103.6003,1.3521],"type":"Point"}
}