{
  "type": "Feature",
  "properties": {
    "gn:admin1_code":"16.0",
    "gn:asciiname":"Kampong Tambisan",
    "gn:country_code":"MY",
    "gn:dem":9,
    "gn:feature_class":"P",
    "gn:feature_code":"PPL",
    "gn:name":"Kampong Tambisan",
    "gn:population":0,
    "gn:timezone":"Asia/Kuching",
    "iso:country":"MY",
    "name:und_x_variant":[
        "Tambisan",
        "Kampong Tambisan"
    ],
    "wof:name":"Kampong Tambisan",
    "wof:placetype":"locality"
},
  "geometry": {"coordinates":[119.14496,5.45231],"type":"Point"}
}