{
  "type": "Feature",
  "properties": {
    "gn:admin1_code":"12.0",
    "gn:asciiname":"Bagan Sungai Pulai",
    "gn:country_code":"MY",
    "gn:dem":4,
    "gn:feature_class":"P",
    "gn:feature_code":"PPL",
    "gn:name":"Bagan Sungai Pulai",
    "gn:population":0,
    "gn:timezone":"Asia/Kuala_Lumpur",
    "iso:country":"MY",
    "name:msa_x_preferred":[
        "Bagan Sungai Pulai"
    ],
    "wof:name":"Bagan Sungai Pulai",
    "wof:placetype":"locality"
},
  "geometry": {"coordinates":[100.9194,3.7252],"type":"Point"}
}