{
  "type": "Feature",
  "properties": {
    "gn:admin1_code":"3",
    "gn:asciiname":"Kampung Gual Petai Beruk",
    "gn:country_code":"MY",
    "gn:dem":23,
    "gn:feature_class":"P",
    "gn:feature_code":"PPL",
    "gn:name":"Kampung Gual Petai Beruk",
    "gn:population":0,
    "gn:timezone":"Asia/Kuala_Lumpur",
    "iso:country":"MY",
    "name:msa_x_preferred":[
        "Kampung Gual Petai Beruk"
    ],
    "name:und_x_variant":[
        "Kampong Gual Petai Betuk",
        "Kampong Gual Petai Berok"
    ],
    "wof:name":"Kampung Gual Petai Beruk",
    "wof:placetype":"locality"
},
  "geometry": {"coordinates":[102.00360000000001,5.9783],"type":"Point"}
}