{
  "type": "Feature",
  "properties": {
    "gn:admin1_code":"9.0",
    "gn:asciiname":"Kampung Dato Keramat",
    "gn:country_code":"MY",
    "gn:dem":4,
    "gn:feature_class":"P",
    "gn:feature_code":"PPL",
    "gn:name":"Kampung Dato Keramat",
    "gn:population":0,
    "gn:timezone":"Asia/Kuala_Lumpur",
    "iso:country":"MY",
    "name:msa_x_preferred":[
        "Kampung Dato Keramat"
    ],
    "wof:name":"Kampung Dato Keramat",
    "wof:placetype":"locality"
},
  "geometry": {"coordinates":[100.477,5.15347],"type":"Point"}
}