{
  "type": "Feature",
  "properties": {
    "gn:admin1_code":"5.0",
    "gn:asciiname":"Kemajuan Tanah Lui Barat",
    "gn:country_code":"MY",
    "gn:dem":84,
    "gn:feature_class":"P",
    "gn:feature_code":"PPL",
    "gn:name":"Kemajuan Tanah Lui Barat",
    "gn:population":0,
    "gn:timezone":"Asia/Kuala_Lumpur",
    "iso:country":"MY",
    "name:msa_x_preferred":[
        "Kemajuan Tanah Lui Barat"
    ],
    "wof:name":"Kemajuan Tanah Lui Barat",
    "wof:placetype":"locality"
},
  "geometry": {"coordinates":[102.38039999999999,2.955],"type":"Point"}
}