{
  "type": "Feature",
  "properties": {
    "gn:admin1_code":"1.0",
    "gn:asciiname":"Kampung Perpat Punggor",
    "gn:country_code":"MY",
    "gn:dem":11,
    "gn:feature_class":"P",
    "gn:feature_code":"PPL",
    "gn:name":"Kampung Perpat Punggor",
    "gn:population":0,
    "gn:timezone":"Asia/Kuala_Lumpur",
    "iso:country":"MY",
    "name:msa_x_preferred":[
        "Kampung Perpat Punggor"
    ],
    "wof:name":"Kampung Perpat Punggor",
    "wof:placetype":"locality"
},
  "geometry": {"coordinates":[103.5056,1.2895],"type":"Point"}
}