{
  "type": "Feature",
  "properties": {
    "gn:admin1_code":"6.0",
    "gn:asciiname":"Kampung Darat Sekolah",
    "gn:country_code":"MY",
    "gn:dem":18,
    "gn:feature_class":"P",
    "gn:feature_code":"PPL",
    "gn:name":"Kampung Darat Sekolah",
    "gn:population":0,
    "gn:timezone":"Asia/Kuala_Lumpur",
    "iso:country":"MY",
    "name:msa_x_preferred":[
        "Kampung Darat Sekolah"
    ],
    "wof:name":"Kampung Darat Sekolah",
    "wof:placetype":"locality"
},
  "geometry": {"coordinates":[103.36369999999999,3.8564],"type":"Point"}
}