{
  "type": "Feature",
  "properties": {
    "gn:admin1_code":"12.0",
    "gn:asciiname":"Kampung Seri Geriang",
    "gn:country_code":"MY",
    "gn:dem":51,
    "gn:feature_class":"P",
    "gn:feature_code":"PPL",
    "gn:name":"Kampung Seri Geriang",
    "gn:population":0,
    "gn:timezone":"Asia/Kuala_Lumpur",
    "iso:country":"MY",
    "name:msa_x_preferred":[
        "Kampung Seri Geriang"
    ],
    "wof:name":"Kampung Seri Geriang",
    "wof:placetype":"locality"
},
  "geometry": {"coordinates":[101.5202,3.6687],"type":"Point"}
}