{
  "type": "Feature",
  "properties": {
    "gn:admin1_code":"1",
    "gn:asciiname":"Kampung Ayer Puteh",
    "gn:country_code":"MY",
    "gn:dem":27,
    "gn:feature_class":"P",
    "gn:feature_code":"PPL",
    "gn:name":"Kampung Ayer Puteh",
    "gn:population":0,
    "gn:timezone":"Asia/Kuala_Lumpur",
    "iso:country":"MY",
    "name:msa_x_preferred":[
        "Kampung Ayer Puteh"
    ],
    "name:und_x_variant":[
        "Kampong Ayer Puteh"
    ],
    "wof:name":"Kampung Ayer Puteh",
    "wof:placetype":"locality"
},
  "geometry": {"coordinates":[103.9512,1.6338],"type":"Point"}
}