{
  "type": "Feature",
  "properties": {
    "gn:admin1_code":"1.0",
    "gn:asciiname":"Kemajuan Tanah Bukit Kepung Paya Kepar dan Kampung Tui",
    "gn:country_code":"MY",
    "gn:dem":18,
    "gn:feature_class":"P",
    "gn:feature_code":"PPL",
    "gn:name":"Kemajuan Tanah Bukit Kepung Paya Kepar dan Kampung Tui",
    "gn:population":0,
    "gn:timezone":"Asia/Kuala_Lumpur",
    "iso:country":"MY",
    "name:msa_x_preferred":[
        "Kemajuan Tanah Bukit Kepung Paya Kepar dan Kampung Tui"
    ],
    "wof:name":"Kemajuan Tanah Bukit Kepung Paya Kepar dan Kampung Tui",
    "wof:placetype":"locality"
},
  "geometry": {"coordinates":[102.917,2.38],"type":"Point"}
}