{
  "type": "Feature",
  "properties": {
    "gn:admin1_code":"0.0",
    "gn:asciiname":"Sungai Limau Dalam",
    "gn:country_code":"MY",
    "gn:dem":6,
    "gn:feature_class":"P",
    "gn:feature_code":"PPL",
    "gn:name":"Sungai Limau Dalam",
    "gn:population":0,
    "gn:timezone":"Asia/Kuala_Lumpur",
    "iso:country":"MY",
    "name:epo_x_preferred":[
        "Sungai Limau"
    ],
    "name:msa_x_preferred":[
        "Sungai Limau"
    ],
    "name:und_x_variant":[
        "Sungai Limau Dalam"
    ],
    "wof:name":"Sungai Limau Dalam",
    "wof:placetype":"locality"
},
  "geometry": {"coordinates":[100.37692,5.9007],"type":"Point"}
}