{
  "type": "Feature",
  "properties": {
    "gn:admin1_code":"13",
    "gn:asciiname":"Kampung Padang Tepas",
    "gn:country_code":"MY",
    "gn:dem":52,
    "gn:feature_class":"P",
    "gn:feature_code":"PPL",
    "gn:name":"Kampung Padang Tepas",
    "gn:population":0,
    "gn:timezone":"Asia/Kuala_Lumpur",
    "iso:country":"MY",
    "name:msa_x_preferred":[
        "Kampung Padang Tepas"
    ],
    "name:und_x_variant":[
        "Kampong Padang Tepas"
    ],
    "wof:name":"Kampung Padang Tepas",
    "wof:placetype":"locality"
},
  "geometry": {"coordinates":[102.9693,4.5624],"type":"Point"}
}