{
  "type": "Feature",
  "properties": {
    "gn:admin1_code":"6",
    "gn:asciiname":"Kampung Kumit",
    "gn:country_code":"MY",
    "gn:dem":113,
    "gn:feature_class":"P",
    "gn:feature_code":"PPL",
    "gn:name":"Kampung Kumit",
    "gn:population":0,
    "gn:timezone":"Asia/Kuala_Lumpur",
    "iso:country":"MY",
    "name:msa_x_preferred":[
        "Kampung Kumit"
    ],
    "name:und_x_variant":[
        "Kampong Kumit"
    ],
    "wof:name":"Kampung Kumit",
    "wof:placetype":"locality"
},
  "geometry": {"coordinates":[102.5757,4.51],"type":"Point"}
}