{
  "type": "Feature",
  "properties": {
    "gn:admin1_code":"16",
    "gn:asciiname":"Lingawan",
    "gn:country_code":"MY",
    "gn:dem":139,
    "gn:feature_class":"P",
    "gn:feature_code":"PPL",
    "gn:name":"Lingawan",
    "gn:population":0,
    "gn:timezone":"Asia/Kuching",
    "iso:country":"MY",
    "wof:name":"Lingawan",
    "wof:placetype":"locality"
},
  "geometry": {"coordinates":[116.86667,5.05],"type":"Point"}
}