{
  "type": "Feature",
  "properties": {
    "gn:admin1_code":"7",
    "gn:asciiname":"Kampung Telok Jual",
    "gn:country_code":"MY",
    "gn:dem":8,
    "gn:feature_class":"P",
    "gn:feature_code":"PPL",
    "gn:name":"Kampung Telok Jual",
    "gn:population":0,
    "gn:timezone":"Asia/Kuala_Lumpur",
    "iso:country":"MY",
    "name:und_x_variant":[
        "Kampong Telok Jual"
    ],
    "wof:name":"Kampung Telok Jual",
    "wof:placetype":"locality"
},
  "geometry": {"coordinates":[100.93163,4.09548],"type":"Point"}
}