{
  "type": "Feature",
  "properties": {
    "gn:admin1_code":"2.0",
    "gn:asciiname":"Kampung Rigen",
    "gn:cc2":"MY",
    "gn:country_code":"MY",
    "gn:dem":19,
    "gn:feature_class":"P",
    "gn:feature_code":"PPL",
    "gn:name":"Kampung Rigen",
    "gn:population":0,
    "gn:timezone":"Asia/Kuala_Lumpur",
    "iso:country":"MY",
    "name:msa_x_preferred":[
        "Kampung Rigen"
    ],
    "wof:name":"Kampung Rigen",
    "wof:placetype":"locality"
},
  "geometry": {"coordinates":[100.52215,5.87496],"type":"Point"}
}