{
  "type": "Feature",
  "properties": {
    "gn:admin1_code":"16",
    "gn:asciiname":"Tantagas",
    "gn:country_code":"MY",
    "gn:dem":23,
    "gn:feature_class":"P",
    "gn:feature_code":"PPL",
    "gn:name":"Tantagas",
    "gn:population":0,
    "gn:timezone":"Asia/Kuching",
    "iso:country":"MY",
    "wof:name":"Tantagas",
    "wof:placetype":"locality"
},
  "geometry": {"coordinates":[117.25,7.31667],"type":"Point"}
}