{
  "type": "Feature",
  "properties": {
    "gn:country":"MY",
    "gn:fcode":"PPL",
    "gn:pop":0,
    "iso:country":"MY",
    "name:msa_x_preferred":[
        "Manir"
    ],
    "qs:name":"Manir",
    "qs:name_adm0":"Malaysia",
    "qs:name_adm1":"Terengganu",
    "qs:photos":44,
    "qs:photos_1k":9,
    "qs:photos_9k":1,
    "qs:photos_9r":2,
    "qs:photos_all":44,
    "qs:photos_sr":2,
    "qs:placetype":"Town",
    "qs:pop_sr":"0",
    "wof:name":"Manir",
    "wof:placetype":"locality",
    "wof:population":0
},
  "geometry": {"coordinates":[103.08369999999999,5.3073],"type":"Point"}
}