{
  "type": "Feature",
  "properties": {
    "gn:admin1_code":"16.0",
    "gn:asciiname":"Kampung Bambangan",
    "gn:country_code":"MY",
    "gn:dem":19,
    "gn:feature_class":"P",
    "gn:feature_code":"PPL",
    "gn:name":"Kampung Bambangan",
    "gn:population":0,
    "gn:timezone":"Asia/Kuching",
    "iso:country":"MY",
    "name:msa_x_preferred":[
        "Kampung Bambangan"
    ],
    "wof:name":"Kampung Bambangan",
    "wof:placetype":"locality"
},
  "geometry": {"coordinates":[116.77979999999999,6.8668],"type":"Point"}
}