{
  "type": "Feature",
  "properties": {
    "gn:admin1_code":"6",
    "gn:asciiname":"Kampung Ludung",
    "gn:country_code":"MY",
    "gn:dem":48,
    "gn:feature_class":"P",
    "gn:feature_code":"PPL",
    "gn:name":"Kampung Ludung",
    "gn:population":0,
    "gn:timezone":"Asia/Kuala_Lumpur",
    "iso:country":"MY",
    "name:und_x_variant":[
        "Kampong Lodong"
    ],
    "wof:name":"Kampung Ludung",
    "wof:placetype":"locality"
},
  "geometry": {"coordinates":[102.79300000000001,3.52005],"type":"Point"}
}