{
  "type": "Feature",
  "properties": {
    "gn:admin1_code":"3.0",
    "gn:asciiname":"Kampung Che Da'ah",
    "gn:country_code":"MY",
    "gn:dem":16,
    "gn:feature_class":"P",
    "gn:feature_code":"PPL",
    "gn:name":"Kampung Che Da\u2019ah",
    "gn:population":0,
    "gn:timezone":"Asia/Kuala_Lumpur",
    "iso:country":"MY",
    "name:msa_x_preferred":[
        "Kampung Che Da\u2019ah"
    ],
    "wof:name":"Kampung Che Da'ah",
    "wof:placetype":"locality"
},
  "geometry": {"coordinates":[102.01090000000001,6.0415],"type":"Point"}
}