{
  "type": "Feature",
  "properties": {
    "gn:admin1_code":"16.0",
    "gn:asciiname":"Kampung Kimihang",
    "gn:country_code":"MY",
    "gn:dem":69,
    "gn:feature_class":"P",
    "gn:feature_code":"PPL",
    "gn:name":"Kampung Kimihang",
    "gn:population":0,
    "gn:timezone":"Asia/Kuching",
    "iso:country":"MY",
    "name:msa_x_preferred":[
        "Kampung Kimihang"
    ],
    "wof:name":"Kampung Kimihang",
    "wof:placetype":"locality"
},
  "geometry": {"coordinates":[116.7261,6.95494],"type":"Point"}
}