{
  "type": "Feature",
  "properties": {
    "gn:admin1_code":"13",
    "gn:asciiname":"Kampung Pasir Gajah",
    "gn:country_code":"MY",
    "gn:dem":12,
    "gn:feature_class":"P",
    "gn:feature_code":"PPL",
    "gn:name":"Kampung Pasir Gajah",
    "gn:population":0,
    "gn:timezone":"Asia/Kuala_Lumpur",
    "iso:country":"MY",
    "name:msa_x_preferred":[
        "Kampung Pasir Gajah"
    ],
    "name:und_x_variant":[
        "Kampong Pasir Gagah"
    ],
    "wof:name":"Kampung Pasir Gajah",
    "wof:placetype":"locality"
},
  "geometry": {"coordinates":[103.2829,4.2441],"type":"Point"}
}