{
  "type": "Feature",
  "properties": {
    "gn:admin1_code":"5",
    "gn:asciiname":"Kampung Sompo",
    "gn:country_code":"MY",
    "gn:dem":75,
    "gn:feature_class":"P",
    "gn:feature_code":"PPL",
    "gn:name":"Kampung Sompo",
    "gn:population":0,
    "gn:timezone":"Asia/Kuala_Lumpur",
    "iso:country":"MY",
    "name:msa_x_preferred":[
        "Kampung Sompo"
    ],
    "name:und_x_variant":[
        "Kampong Sompo"
    ],
    "wof:name":"Kampung Sompo",
    "wof:placetype":"locality"
},
  "geometry": {"coordinates":[101.9469,2.85],"type":"Point"}
}