{
  "type": "Feature",
  "properties": {
    "gn:admin1_code":"4",
    "gn:asciiname":"Kampung Sempang",
    "gn:country_code":"MY",
    "gn:dem":34,
    "gn:feature_class":"P",
    "gn:feature_code":"PPL",
    "gn:name":"Kampung Sempang",
    "gn:population":0,
    "gn:timezone":"Asia/Kuala_Lumpur",
    "iso:country":"MY",
    "name:msa_x_preferred":[
        "Kampung Sempang"
    ],
    "name:und_x_variant":[
        "Kampong Sempang Bekoh"
    ],
    "wof:name":"Kampung Sempang",
    "wof:placetype":"locality"
},
  "geometry": {"coordinates":[102.5095,2.3601],"type":"Point"}
}