{
  "type": "Feature",
  "properties": {
    "gn:admin1_code":"12",
    "gn:asciiname":"Kampung Sungai Rinching",
    "gn:country_code":"MY",
    "gn:dem":46,
    "gn:feature_class":"P",
    "gn:feature_code":"PPL",
    "gn:name":"Kampung Sungai Rinching",
    "gn:population":0,
    "gn:timezone":"Asia/Kuala_Lumpur",
    "iso:country":"MY",
    "name:msa_x_preferred":[
        "Kampung Sungai Rinching"
    ],
    "name:und_x_variant":[
        "Kampong Sungai Rinching"
    ],
    "wof:name":"Kampung Sungai Rinching",
    "wof:placetype":"locality"
},
  "geometry": {"coordinates":[101.8509,2.9167],"type":"Point"}
}