{
  "type": "Feature",
  "properties": {
    "gn:admin1_code":"1",
    "gn:asciiname":"Kampung Belokok",
    "gn:country_code":"MY",
    "gn:dem":12,
    "gn:feature_class":"P",
    "gn:feature_code":"PPL",
    "gn:name":"Kampung Belokok",
    "gn:population":0,
    "gn:timezone":"Asia/Kuala_Lumpur",
    "iso:country":"MY",
    "name:msa_x_preferred":[
        "Kampung Belokok"
    ],
    "name:und_x_variant":[
        "Kampong Belokok"
    ],
    "wof:name":"Kampung Belokok",
    "wof:placetype":"locality"
},
  "geometry": {"coordinates":[103.4686,1.4309],"type":"Point"}
}