{
  "type": "Feature",
  "properties": {
    "gn:admin1_code":"13",
    "gn:asciiname":"Kampung Teluk Masjid",
    "gn:country_code":"MY",
    "gn:dem":21,
    "gn:feature_class":"P",
    "gn:feature_code":"PPL",
    "gn:name":"Kampung Teluk Masjid",
    "gn:population":0,
    "gn:timezone":"Asia/Kuala_Lumpur",
    "iso:country":"MY",
    "name:msa_x_preferred":[
        "Kampung Teluk Masjid"
    ],
    "name:und_x_variant":[
        "Kampong Telok Masjid"
    ],
    "wof:name":"Kampung Teluk Masjid",
    "wof:placetype":"locality"
},
  "geometry": {"coordinates":[102.9992,5.0741],"type":"Point"}
}