{
  "type": "Feature",
  "properties": {
    "gn:admin1_code":"13.0",
    "gn:asciiname":"Kemajuan Tanah Bukit Seri Cadur",
    "gn:country_code":"MY",
    "gn:dem":21,
    "gn:feature_class":"P",
    "gn:feature_code":"PPL",
    "gn:name":"Kemajuan Tanah Bukit Seri Cadur",
    "gn:population":0,
    "gn:timezone":"Asia/Kuala_Lumpur",
    "iso:country":"MY",
    "name:msa_x_preferred":[
        "Kemajuan Tanah Bukit Seri Cadur"
    ],
    "wof:name":"Kemajuan Tanah Bukit Seri Cadur",
    "wof:placetype":"locality"
},
  "geometry": {"coordinates":[103.1733,5.0502],"type":"Point"}
}