{
  "type": "Feature",
  "properties": {
    "gn:admin1_code":"16.0",
    "gn:asciiname":"Kampung Gapu",
    "gn:country_code":"MY",
    "gn:dem":14,
    "gn:feature_class":"P",
    "gn:feature_code":"PPL",
    "gn:name":"Kampung Gapu",
    "gn:population":0,
    "gn:timezone":"Asia/Kuching",
    "iso:country":"MY",
    "name:msa_x_preferred":[
        "Kampung Gapu"
    ],
    "wof:name":"Kampung Gapu",
    "wof:placetype":"locality"
},
  "geometry": {"coordinates":[115.81359999999999,5.4793],"type":"Point"}
}