{
  "type": "Feature",
  "properties": {
    "gn:admin1_code":"1.0",
    "gn:asciiname":"Taman Seri Kulai",
    "gn:country_code":"MY",
    "gn:dem":39,
    "gn:feature_class":"P",
    "gn:feature_code":"PPL",
    "gn:name":"Taman Seri Kulai",
    "gn:population":0,
    "gn:timezone":"Asia/Kuala_Lumpur",
    "iso:country":"MY",
    "name:msa_x_preferred":[
        "Taman Seri Kulai"
    ],
    "wof:name":"Taman Seri Kulai",
    "wof:placetype":"locality"
},
  "geometry": {"coordinates":[103.59,1.6654],"type":"Point"}
}