{
  "type": "Feature",
  "properties": {
    "gn:admin1_code":"2",
    "gn:asciiname":"Kampung Sungai Tembak",
    "gn:cc2":"MY",
    "gn:country_code":"MY",
    "gn:dem":52,
    "gn:feature_class":"P",
    "gn:feature_code":"PPL",
    "gn:name":"Kampung Sungai Tembak",
    "gn:population":0,
    "gn:timezone":"Asia/Kuala_Lumpur",
    "iso:country":"MY",
    "name:msa_x_preferred":[
        "Kampung Sungai Tembak"
    ],
    "name:und_x_variant":[
        "Kampong Tambak"
    ],
    "wof:name":"Kampung Sungai Tembak",
    "wof:placetype":"locality"
},
  "geometry": {"coordinates":[100.76467,5.71281],"type":"Point"}
}