{
  "type": "Feature",
  "properties": {
    "gn:admin1_code":"12.0",
    "gn:asciiname":"Taman Nirwana Indah",
    "gn:country_code":"MY",
    "gn:dem":6,
    "gn:feature_class":"P",
    "gn:feature_code":"PPL",
    "gn:name":"Taman Nirwana Indah",
    "gn:population":0,
    "gn:timezone":"Asia/Kuala_Lumpur",
    "iso:country":"MY",
    "name:msa_x_preferred":[
        "Taman Nirwana Indah"
    ],
    "wof:name":"Taman Nirwana Indah",
    "wof:placetype":"locality"
},
  "geometry": {"coordinates":[100.9894,3.6675],"type":"Point"}
}