{
  "type": "Feature",
  "properties": {
    "gn:admin1_code":"5",
    "gn:asciiname":"Kampung Kepis",
    "gn:country_code":"MY",
    "gn:dem":106,
    "gn:feature_class":"P",
    "gn:feature_code":"PPL",
    "gn:name":"Kampung Kepis",
    "gn:population":0,
    "gn:timezone":"Asia/Kuala_Lumpur",
    "iso:country":"MY",
    "name:msa_x_preferred":[
        "Kampung Kepis"
    ],
    "name:und_x_variant":[
        "Kampong Kepis"
    ],
    "wof:name":"Kampung Kepis",
    "wof:placetype":"locality"
},
  "geometry": {"coordinates":[102.325,2.6997],"type":"Point"}
}