{
  "type": "Feature",
  "properties": {
    "gn:admin1_code":"6.0",
    "gn:asciiname":"Kampung Teh",
    "gn:country_code":"MY",
    "gn:dem":69,
    "gn:feature_class":"P",
    "gn:feature_code":"PPL",
    "gn:name":"Kampung Teh",
    "gn:population":0,
    "gn:timezone":"Asia/Kuala_Lumpur",
    "iso:country":"MY",
    "name:msa_x_preferred":[
        "Kampung Teh"
    ],
    "wof:name":"Kampung Teh",
    "wof:placetype":"locality"
},
  "geometry": {"coordinates":[102.34699999999999,3.9607],"type":"Point"}
}