{
  "type": "Feature",
  "properties": {
    "gn:admin1_code":"6",
    "gn:asciiname":"Kampung Cangkung",
    "gn:country_code":"MY",
    "gn:dem":68,
    "gn:feature_class":"P",
    "gn:feature_code":"PPL",
    "gn:name":"Kampung Cangkung",
    "gn:population":0,
    "gn:timezone":"Asia/Kuala_Lumpur",
    "iso:country":"MY",
    "name:msa_x_preferred":[
        "Kampung Cangkung"
    ],
    "name:und_x_variant":[
        "Kampong Changkong"
    ],
    "wof:name":"Kampung Cangkung",
    "wof:placetype":"locality"
},
  "geometry": {"coordinates":[102.2229,4.1344],"type":"Point"}
}