{
  "type": "Feature",
  "properties": {
    "gn:admin1_code":"3",
    "gn:asciiname":"Kampong Telekong Baharu",
    "gn:cc2":"MY",
    "gn:country_code":"MY",
    "gn:dem":50,
    "gn:feature_class":"P",
    "gn:feature_code":"PPL",
    "gn:name":"Kampong Telekong Baharu",
    "gn:population":0,
    "gn:timezone":"Asia/Kuala_Lumpur",
    "iso:country":"MY",
    "name:und_x_variant":[
        "Kampong Telekong",
        "Kampong Telkong Bharu",
        "Kampong Telekong Baharu"
    ],
    "wof:name":"Kampong Telekong Baharu",
    "wof:placetype":"locality"
},
  "geometry": {"coordinates":[102.21666999999999,5.65],"type":"Point"}
}