{
  "type": "Feature",
  "properties": {
    "gn:admin1_code":"1",
    "gn:asciiname":"Kampung Sialang Relau",
    "gn:country_code":"MY",
    "gn:dem":38,
    "gn:feature_class":"P",
    "gn:feature_code":"PPL",
    "gn:name":"Kampung Sialang Relau",
    "gn:population":0,
    "gn:timezone":"Asia/Kuala_Lumpur",
    "iso:country":"MY",
    "name:msa_x_preferred":[
        "Kampung Sialang Relau"
    ],
    "name:und_x_variant":[
        "Kampong Sialang Relau"
    ],
    "wof:name":"Kampung Sialang Relau",
    "wof:placetype":"locality"
},
  "geometry": {"coordinates":[102.541,2.3857],"type":"Point"}
}