{
  "type": "Feature",
  "properties": {
    "gn:admin1_code":"16",
    "gn:asciiname":"Kampung Minatakon",
    "gn:country_code":"MY",
    "gn:dem":444,
    "gn:feature_class":"P",
    "gn:feature_code":"PPL",
    "gn:name":"Kampung Minatakon",
    "gn:population":0,
    "gn:timezone":"Asia/Kuching",
    "iso:country":"MY",
    "name:msa_x_preferred":[
        "Kampung Minatakon"
    ],
    "name:und_x_variant":[
        "Kampong Minatakon"
    ],
    "wof:name":"Kampung Minatakon",
    "wof:placetype":"locality"
},
  "geometry": {"coordinates":[116.5938,6.5452],"type":"Point"}
}