{
  "type": "Feature",
  "properties": {
    "gn:admin1_code":"13.0",
    "gn:asciiname":"Kampung Gong Pauh",
    "gn:country_code":"MY",
    "gn:dem":9,
    "gn:feature_class":"P",
    "gn:feature_code":"PPL",
    "gn:name":"Kampung Gong Pauh",
    "gn:population":0,
    "gn:timezone":"Asia/Kuala_Lumpur",
    "iso:country":"MY",
    "name:msa_x_preferred":[
        "Kampung Gong Pauh"
    ],
    "wof:name":"Kampung Gong Pauh",
    "wof:placetype":"locality"
},
  "geometry": {"coordinates":[103.1157,5.2872],"type":"Point"}
}