{
  "type": "Feature",
  "properties": {
    "gn:admin1_code":"11.0",
    "gn:asciiname":"Pa Umor",
    "gn:country_code":"MY",
    "gn:dem":1076,
    "gn:feature_class":"P",
    "gn:feature_code":"PPL",
    "gn:name":"Pa Umor",
    "gn:population":0,
    "gn:timezone":"Asia/Kuching",
    "iso:country":"MY",
    "wof:name":"Pa Umor",
    "wof:placetype":"locality"
},
  "geometry": {"coordinates":[115.51667,3.73333],"type":"Point"}
}