{
  "type": "Feature",
  "properties": {
    "gn:admin1_code":"9",
    "gn:asciiname":"Kampung Sungai Buluh",
    "gn:cc2":"MY",
    "gn:country_code":"MY",
    "gn:dem":157,
    "gn:feature_class":"P",
    "gn:feature_code":"PPL",
    "gn:name":"Kampung Sungai Buluh",
    "gn:population":0,
    "gn:timezone":"Asia/Kuala_Lumpur",
    "iso:country":"MY",
    "name:msa_x_preferred":[
        "Kampung Sungai Buluh"
    ],
    "name:und_x_variant":[
        "Kampong Sungai Buloh"
    ],
    "wof:name":"Kampung Sungai Buluh",
    "wof:placetype":"locality"
},
  "geometry": {"coordinates":[100.51654000000001,5.2552],"type":"Point"}
}