{
  "type": "Feature",
  "properties": {
    "gn:admin1_code":"9",
    "gn:asciiname":"Permatang Tengah",
    "gn:cc2":"MY",
    "gn:country_code":"MY",
    "gn:dem":8,
    "gn:feature_class":"P",
    "gn:feature_code":"PPL",
    "gn:name":"Permatang Tengah",
    "gn:population":0,
    "gn:timezone":"Asia/Kuala_Lumpur",
    "iso:country":"MY",
    "name:msa_x_preferred":[
        "Permatang Tengah"
    ],
    "name:und_x_variant":[
        "Permatang Tenah"
    ],
    "wof:name":"Permatang Tengah",
    "wof:placetype":"locality"
},
  "geometry": {"coordinates":[100.38822,5.4495],"type":"Point"}
}