{
  "type": "Feature",
  "properties": {
    "gn:admin1_code":"7",
    "gn:asciiname":"Kampung Tanjung Bayan",
    "gn:country_code":"MY",
    "gn:dem":8,
    "gn:feature_class":"P",
    "gn:feature_code":"PPL",
    "gn:name":"Kampung Tanjung Bayan",
    "gn:population":0,
    "gn:timezone":"Asia/Kuala_Lumpur",
    "iso:country":"MY",
    "name:msa_x_preferred":[
        "Kampung Tanjung Bayan"
    ],
    "name:und_x_variant":[
        "Kampong Tanjong Bayan"
    ],
    "wof:name":"Kampung Tanjung Bayan",
    "wof:placetype":"locality"
},
  "geometry": {"coordinates":[100.9084,3.8788],"type":"Point"}
}