{
  "type": "Feature",
  "properties": {
    "gn:admin1_code":"1.0",
    "gn:asciiname":"Desa Bukit Kelompok",
    "gn:country_code":"MY",
    "gn:dem":28,
    "gn:feature_class":"P",
    "gn:feature_code":"PPL",
    "gn:name":"Desa Bukit Kelompok",
    "gn:population":0,
    "gn:timezone":"Asia/Kuala_Lumpur",
    "iso:country":"MY",
    "name:msa_x_preferred":[
        "Desa Bukit Kelompok"
    ],
    "wof:name":"Desa Bukit Kelompok",
    "wof:placetype":"locality"
},
  "geometry": {"coordinates":[103.9983,1.9924],"type":"Point"}
}